Workbook

Sheet 封面
B2: 伯克希尔账本
B4: 2021—2025 年 + 2026 年上半年 · 按年报分部口径重述
B5: Buffett 交班之后，一家公司的钱从哪里来、放在哪里、又去了哪里
B9: 这本账包含什么
B11: 01 分部利润 | D11: 保险承保、保险投资收益、BNSF、BHE、制造/服务/零售、其他；2021—2025 与 2026H1，含同比与占比。
B13: 02 保险与资产 | D13: 保险浮存金、现金与短期国债、股票投资组合、归母权益、A 等价股数、每股账面价值、回购。
B15: 03 股票组合 | D15: 按年报披露的三个行业类别拆分；2025 年末核心持仓与五大持仓集中度。
B17: 04 变化 | D17: 一页仪表盘：同比、占比与四张图。
B19: 05 情景 | D19: 可修改假设与 2026 全年机械情景；改一个假设，相关结果自动更新。
B21: 06 历史决策 | D21: 小游戏使用的 10 个历史决策及其关键数字，与网页口径一致。
B23: 07 来源与口径 | D23: 每个数字的来源编号、SEC 补充链接、定义、重述与局限。
B25: 颜色约定
C26: 披露输入值 | D26: 来自年报、季报、业绩公告或股东信的原始数字，未做加工。
C28: 公式计算 | D28: 同比、占比、合计、每股账面价值、比率等，均由单元格公式联动。
C30: 可修改假设 | D30: 「变化」表中的年化系数、下半年回购/浮存金/每股账面价值假设；改一个，相关估算自动更新。
B34: 口径一句话
B35: 分部利润为「归属于伯克希尔股东的税后利润」，取自各年年报 MD&A 的 Results of Operations 表；不含投资损益与 OTTI。2021—2022 采用 2023 年 10-K 追溯重述数；2023 年起 Pilot 并入「制造、服务与零售」。2026H1 取自 2026 年二季度业绩公告（8-K Exhibit 99.1）。
B40: 免责声明：本文件是研究与展示用的历史财务分析，不构成投资建议，不提供买入、卖出、持有或目标价，也不评价股价。所有假设均以「假设」标注，与披露事实分开。数据截至 2026 年 6 月 30 日；网页与文档中的数字与本工作簿一致。
B45: 编制日期：2026 年 10 月 22 日 | 单位：百万美元（另注者除外）

Sheet 分部利润
A1: 01 分部利润：钱从哪里来
A2: 税后、归属于伯克希尔股东；单位：百万美元。2021—2022 为 2023 年 10-K 追溯重述数；2023 年起 Pilot 并入「制造、服务与零售」。
A4: 项目 | B4: 2021 | C4: 2022 | D4: 2023 | E4: 2024 | F4: 2025 | G4: 2025H1 | H4: 2026H1 | I4: 2021-25 复合增速 | J4: 2025 同比 | K4: 2026H1 同比 | L4: 出处（按年份/表）
B5: S5 | C5: S5 | D5: S1 | E5: S1 | F5: S1 | G5: S3 | H5: S3
A6: 保险承保 | B6: 870 | C6: -30 | D6: 5428 | E6: 9020 | F6: 7258 | G6: 3328 | H6: 3448 | I6: =IFERROR((F6/B6)^(1/4)-1,"") | J6: =IFERROR(F6/E6-1,"") | K6: =IFERROR(H6/G6-1,"") | L6: S5 p.K-34（2021-2022，经 ASU 2018-12 追溯重述）；S1 p.K-34（2023-2025）；S3（2026H1）
A7: 保险投资收益 | B7: 4807 | C7: 6484 | D7: 9567 | E7: 13670 | F7: 12513 | G7: 6260 | H7: 5738 | I7: =IFERROR((F7/B7)^(1/4)-1,"") | J7: =IFERROR(F7/E7-1,"") | K7: =IFERROR(H7/G7-1,"") | L7: S5 p.K-34（2021-2022）；S1 p.K-34（2023-2025）；S3（2026H1）
A8: 铁路（BNSF） | B8: 5990 | C8: 5946 | D8: 5087 | E8: 5031 | F8: 5476 | G8: 2680 | H8: 2935 | I8: =IFERROR((F8/B8)^(1/4)-1,"") | J8: =IFERROR(F8/E8-1,"") | K8: =IFERROR(H8/G8-1,"") | L8: S5 p.K-34（2021-2022）；S1 p.K-34（2023-2025）；S3（2026H1）
A9: 能源（BHE） | B9: 3572 | C9: 3904 | D9: 2331 | E9: 3730 | F9: 3979 | G9: 1799 | H9: 2005 | I9: =IFERROR((F9/B9)^(1/4)-1,"") | J9: =IFERROR(F9/E9-1,"") | K9: =IFERROR(H9/G9-1,"") | L9: S5 p.K-34（2021-2022）；S1 p.K-34（2023-2025）；S3（2026H1）
A10: 制造、服务与零售 | B10: 11120 | C10: 12512 | D10: 13362 | E10: 13072 | F10: 13647 | G10: 6661 | H10: 7669 | I10: =IFERROR((F10/B10)^(1/4)-1,"") | J10: =IFERROR(F10/E10-1,"") | K10: =IFERROR(H10/G10-1,"") | L10: S5 p.K-34（2021-2022）；S1 p.K-34（2023-2025）；S3（2026H1）。2023 年起含 Pilot。
A11: 其他 | B11: 1238 | C11: 2037 | D11: 1575 | E11: 2914 | F11: 1613 | G11: 73 | H11: 2534 | I11: =IFERROR((F11/B11)^(1/4)-1,"") | J11: =IFERROR(F11/E11-1,"") | K11: =IFERROR(H11/G11-1,"") | L11: S5 p.K-34（2021-2022：非控股业务+其他）；S1 p.K-34（2023-2025）；S3（2026H1）
A12: 营运利润合计 | B12: =SUM(B6:B11) | C12: =SUM(C6:C11) | D12: =SUM(D6:D11) | E12: =SUM(E6:E11) | F12: =SUM(F6:F11) | G12: =SUM(G6:G11) | H12: =SUM(H6:H11) | I12: =IFERROR((F12/B12)^(1/4)-1,"") | J12: =IFERROR(F12/E12-1,"") | K12: =IFERROR(H12/G12-1,"") | L12: 计算：6-11 行之和
A13: 投资损益 | B13: 62340 | C13: -53612 | D13: 58873 | E13: 41558 | F13: 30737 | G13: -68 | H13: 11444 | L13: S5 p.K-34（2021-2022）；S1 p.K-34（2023-2025）；S3（2026H1）
A14: 非暂时性减值（OTTI） | B14: 0 | C14: 0 | D14: 0 | E14: 0 | F14: -8255 | G14: -3760 | H14: 0 | L14: S1 p.K-34（2025 年 Kraft Heinz 3.76B + Occidental 4.50B）；2021-2024 无此项
A15: 归母净利润 | B15: 89937 | C15: -22759 | D15: 96223 | E15: 88995 | F15: 66968 | G15: 16973 | H15: 35773 | L15: S5 p.K-34（2021-2022）；S1 p.K-34（2023-2025）；S3（2026H1）
A16: 勾稽差异（合计+投资损益+OTTI-净利润） | B16: =B12+B13+B14-B15 | C16: =C12+C13+C14-C15 | D16: =D12+D13+D14-D15 | E16: =E12+E13+E14-E15 | F16: =F12+F13+F14-F15 | G16: =G12+G13+G14-G15 | H16: =H12+H13+H14-H15 | L16: 计算：应为 0
A18: 读法：2021—2025 年营运利润从 276 亿美元增至 445 亿美元，四年复合增速 12.7%；2025 年同比下降 6.2%，2026H1 同比回升 17.0%。保险承保的占比从 2021 年的 3.2% 升至 2025 年的 16.3%，又在 2026H1 回落至 14.2%；制造、服务与零售始终是最大单一板块。
A19: 2021—2022 的「其他」= 2023 年 10-K 表中的「非控股业务」+「其他」；2023 年起「制造、服务与零售」含 Pilot（2023 年仅含 2—12 月，1 月按权益法计入其他）。2022 年保险承保为 -0.30 亿美元；2021 年基数较低，70% 的 2021-25 复合增速不宜外推。
A21: 占营运利润比重（公式）
A22: 项目 | B22: 2021 | C22: 2022 | D22: 2023 | E22: 2024 | F22: 2025 | G22: 2025H1 | H22: 2026H1
A23: 保险承保 | B23: =IFERROR(B6/B$12,"") | C23: =IFERROR(C6/C$12,"") | D23: =IFERROR(D6/D$12,"") | E23: =IFERROR(E6/E$12,"") | F23: =IFERROR(F6/F$12,"") | G23: =IFERROR(G6/G$12,"") | H23: =IFERROR(H6/H$12,"") | L23: 计算：各分部 ÷ 营运利润合计
A24: 保险投资收益 | B24: =IFERROR(B7/B$12,"") | C24: =IFERROR(C7/C$12,"") | D24: =IFERROR(D7/D$12,"") | E24: =IFERROR(E7/E$12,"") | F24: =IFERROR(F7/F$12,"") | G24: =IFERROR(G7/G$12,"") | H24: =IFERROR(H7/H$12,"")
A25: 铁路（BNSF） | B25: =IFERROR(B8/B$12,"") | C25: =IFERROR(C8/C$12,"") | D25: =IFERROR(D8/D$12,"") | E25: =IFERROR(E8/E$12,"") | F25: =IFERROR(F8/F$12,"") | G25: =IFERROR(G8/G$12,"") | H25: =IFERROR(H8/H$12,"")
A26: 能源（BHE） | B26: =IFERROR(B9/B$12,"") | C26: =IFERROR(C9/C$12,"") | D26: =IFERROR(D9/D$12,"") | E26: =IFERROR(E9/E$12,"") | F26: =IFERROR(F9/F$12,"") | G26: =IFERROR(G9/G$12,"") | H26: =IFERROR(H9/H$12,"")
A27: 制造、服务与零售 | B27: =IFERROR(B10/B$12,"") | C27: =IFERROR(C10/C$12,"") | D27: =IFERROR(D10/D$12,"") | E27: =IFERROR(E10/E$12,"") | F27: =IFERROR(F10/F$12,"") | G27: =IFERROR(G10/G$12,"") | H27: =IFERROR(H10/H$12,"")
A28: 其他 | B28: =IFERROR(B11/B$12,"") | C28: =IFERROR(C11/C$12,"") | D28: =IFERROR(D11/D$12,"") | E28: =IFERROR(E11/E$12,"") | F28: =IFERROR(F11/F$12,"") | G28: =IFERROR(G11/G$12,"") | H28: =IFERROR(H11/H$12,"")
A29: 合计 | B29: =SUM(B23:B28) | C29: =SUM(C23:C28) | D29: =SUM(D23:D28) | E29: =SUM(E23:E28) | F29: =SUM(F23:F28) | G29: =SUM(G23:G28) | H29: =SUM(H23:H28)
A31: 补充：保险承保税前利润，按集团（百万美元）
A32: 集团 | B32: 2021 | C32: 2022 | D32: 2023 | E32: 2024 | F32: 2025 | G32: 2025H1 | H32: 2026H1
A33: GEICO | B33: 1259 | C33: -1880 | D33: 3635 | E33: 7813 | F33: 6824 | G33: 3994 | H33: 2410 | L33: S5 p.K-35（2021-2022）；S1 p.K-35（2023-2025）；S3（2026H1）
A34: BH Primary | B34: 607 | C34: 393 | D34: 1374 | E34: 855 | F34: 785 | G34: -81 | H34: 749
A35: BHRG | B35: -930 | C35: 1389 | D35: 1904 | E35: 2737 | F35: 1851 | G35: 343 | H35: 1286
A36: 合计 | B36: =SUM(B33:B35) | C36: =SUM(C33:C35) | D36: =SUM(D33:D35) | E36: =SUM(E33:E35) | F36: =SUM(F33:F35) | G36: =SUM(G33:G35) | H36: =SUM(H33:H35)
A38: 2025 年承保利润下降，主要因为 GEICO 费用率上升、BH Primary 与 BHRG 的赔付与既往年度准备金变动；2026H1 GEICO 承保利润下降，但 BH Primary 与 BHRG 回升。

Sheet 保险与资产
A1: 02 保险与资产：钱放在哪里
A2: 单位：百万美元（股数除外）。现金与短期国债为「保险及其他」板块口径；合并口径另加 BNSF/BHE 的现金。
A4: 项目 | B4: 2021 | C4: 2022 | D4: 2023 | E4: 2024 | F4: 2025 | G4: 2026H1 | H4: 2025 同比 | I4: 2026H1 较2025末 | J4: 出处
B5: S6 | C5: S5 | D5: S4 | E5: S1 | F5: S1 | G5: S2
A6: 保险浮存金 | B6: 147000 | C6: 164000 | D6: 169000 | E6: 171000 | F6: 176400 | G6: 177500 | H6: =IFERROR(F6/E6-1,"") | I6: =IFERROR(G6/F6-1,"") | J6: S6/S5/S1 MD&A 浮存金；S3
A7: 现金及现金等价物（保险及其他） | B7: 85319 | C7: 32260 | D7: 34268 | E7: 44333 | F7: 47719 | G7: 35096 | H7: =IFERROR(F7/E7-1,"") | I7: =IFERROR(G7/F7-1,"") | J7: S6/S5/S4/S1/S2 合并资产负债表
A8: 短期国债（保险及其他） | B8: 58535 | C8: 92774 | D8: 129619 | E8: 286472 | F8: 321434 | G8: 324905 | H8: =IFERROR(F8/E8-1,"") | I8: =IFERROR(G8/F8-1,"") | J8: 同上
A9: 现金 + 短期国债（保险及其他） | B9: =B7+B8 | C9: =C7+C8 | D9: =D7+D8 | E9: =E7+E8 | F9: =F7+F8 | G9: =G7+G8 | H9: =IFERROR(F9/E9-1,"") | I9: =IFERROR(G9/F9-1,"") | J9: 计算
A10: BNSF / BHE 现金 | B10: 2865 | C10: 3551 | D10: 3754 | E10: 3396 | F10: 4158 | G10: 5513 | H10: =IFERROR(F10/E10-1,"") | I10: =IFERROR(G10/F10-1,"") | J10: S6/S5/S4/S1/S2 合并资产负债表
A11: 现金 + 短期国债（合并） | B11: =B9+B10 | C11: =C9+C10 | D11: =D9+D10 | E11: =E9+E10 | F11: =F9+F10 | G11: =G9+G10 | H11: =IFERROR(F11/E11-1,"") | I11: =IFERROR(G11/F11-1,"") | J11: 计算
A12: 股票投资组合（公允价值） | B12: 350719 | C12: 308793 | D12: 353842 | E12: 271588 | F12: 297778 | G12: 323779 | H12: =IFERROR(F12/E12-1,"") | I12: =IFERROR(G12/F12-1,"") | J12: S6/S5/S4/S1/S2 Note 4
A13: 归母股东权益 | B13: 506199 | C13: 473424 | D13: 561273 | E13: 649368 | F13: 717419 | G13: 747910 | H13: =IFERROR(F13/E13-1,"") | I13: =IFERROR(G13/F13-1,"") | J13: S6/S5/S4/S1/S2 合并资产负债表
A14: A 等价股数（股） | B14: 1477429 | C14: 1459733 | D14: 1441483 | E14: 1438223 | F14: 1438223 | G14: 1431693 | H14: =IFERROR(F14/E14-1,"") | I14: =IFERROR(G14/F14-1,"") | J14: S6/S5/S4/S1 Note 22；S3
A15: 每股账面价值（Class A 等价，美元） | B15: =IFERROR(B13*1000000/B14,"") | C15: =IFERROR(C13*1000000/C14,"") | D15: =IFERROR(D13*1000000/D14,"") | E15: =IFERROR(E13*1000000/E14,"") | F15: =IFERROR(F13*1000000/F14,"") | G15: =IFERROR(G13*1000000/G14,"") | H15: =IFERROR(F15/E15-1,"") | I15: =IFERROR(G15/F15-1,"") | J15: 计算
A16: 回购金额（现金流量表：购买库存股） | B16: 27061 | C16: 7854 | D16: 9171 | E16: 2918 | F16: 0 | G16: 4444 | H16: =IFERROR(F16/E16-1,"") | I16: =IFERROR(G16/F16-1,"") | J16: S6/S5/S4/S1 现金流量表；S2 4,444；S3 约4,800
A17: 回购 / 归母净利润 | B17: =IFERROR(B16/'分部利润'!B15,"") | C17: =IFERROR(C16/'分部利润'!C15,"") | D17: =IFERROR(D16/'分部利润'!D15,"") | E17: =IFERROR(E16/'分部利润'!E15,"") | F17: =IFERROR(F16/'分部利润'!F15,"") | G17: =IFERROR(G16/'分部利润'!H15,"") | H17: =IFERROR(F17/E17-1,"") | I17: =IFERROR(G17/F17-1,"") | J17: 计算
A18: 保险浮存金 / 归母股东权益 | B18: =IFERROR(B6/B13,"") | C18: =IFERROR(C6/C13,"") | D18: =IFERROR(D6/D13,"") | E18: =IFERROR(E6/E13,"") | F18: =IFERROR(F6/F13,"") | G18: =IFERROR(G6/G13,"") | H18: =IFERROR(F18/E18-1,"") | I18: =IFERROR(G18/F18-1,"") | J18: 计算
A19: 股票投资组合 / 归母股东权益 | B19: =IFERROR(B12/B13,"") | C19: =IFERROR(C12/C13,"") | D19: =IFERROR(D12/D13,"") | E19: =IFERROR(E12/E13,"") | F19: =IFERROR(F12/F13,"") | G19: =IFERROR(G12/G13,"") | H19: =IFERROR(F19/E19-1,"") | I19: =IFERROR(G19/F19-1,"") | J19: 计算
A20: 现金 + 短期国债 / 股票投资组合 | B20: =IFERROR(B9/B12,"") | C20: =IFERROR(C9/C12,"") | D20: =IFERROR(D9/D12,"") | E20: =IFERROR(E9/E12,"") | F20: =IFERROR(F9/F12,"") | G20: =IFERROR(G9/G12,"") | H20: =IFERROR(F20/E20-1,"") | I20: =IFERROR(G20/F20-1,"") | J20: 计算：保险及其他口径
A22: 每股账面价值：归母权益（百万美元）×1,000,000 ÷ A 等价股数；Class B 为 Class A 的 1/1,500。2022 年归母权益采用 2023 年 10-K 的追溯重述数 473,424（较 2022 年 10-K 的 472,360 高 1,064）；2021 年仍为 2022 年 10-K 原披露数 506,199。
A23: 2026H1 回购：10-Q 现金流量表列示「购买库存股」4,444；业绩公告称二季度约 45 亿、上半年约 48 亿（含期末未结算）。本表统一采用现金流量表口径，另在「来源」与 README 注明差异。
A24: 2025 年回购为 0：2025 年 10-K 明确「There were no share repurchases in 2025」。这是 2021 年 271 亿美元回购之后的急刹车，也是 2026 年重启回购（上半年约 48 亿美元）的起点。
A25: 浮存金：10-K 仅以十亿美元整数披露（2025 年末约 1,760 亿）；2026 年业绩公告称 2026H1 为 1,775 亿、较 2025 年末增加约 11 亿，故 2025 年末按 1,764 亿列示，以保持前后可比。

Sheet 股票组合
A1: 03 股票组合：按披露的行业与核心持仓
A2: 单位：百万美元。行业分类按年报 Note 4「primary industry of the investee」；不含 Kraft Heinz、Occidental 等权益法投资。
A4: 行业类别 | B4: 2021 | C4: 2022 | D4: 2023 | E4: 2024 | F4: 2025 | G4: 2026H1 | H4: 出处
B5: S6 | C5: S5 | D5: S4 | E5: S1 | F5: S1 | G5: S2
A6: 银行、保险与金融 | B6: 89058 | C6: 69556 | D6: 78312 | E6: 91643 | F6: 104129 | G6: 94477 | H6: S6/S5/S4/S1/S2 Note 4
A7: 消费品 | B7: 191021 | C7: 152892 | D7: 201143 | E7: 104749 | F7: 94954 | G7: 100486 | H7: S6/S5/S4/S1/S2 Note 4
A8: 商业、工业及其他 | B8: 70640 | C8: 86345 | D8: 74387 | E8: 75196 | F8: 98695 | G8: 128816 | H8: S6/S5/S4/S1/S2 Note 4
A9: 合计 | B9: =SUM(B6:B8) | C9: =SUM(C6:C8) | D9: =SUM(D6:D8) | E9: =SUM(E6:E8) | F9: =SUM(F6:F8) | G9: =SUM(G6:G8) | H9: 计算
A11: 行业占比（公式）
A12: 行业类别 | B12: 2021 | C12: 2022 | D12: 2023 | E12: 2024 | F12: 2025 | G12: 2026H1
A13: 银行、保险与金融 | B13: =IFERROR(B6/B$9,"") | C13: =IFERROR(C6/C$9,"") | D13: =IFERROR(D6/D$9,"") | E13: =IFERROR(E6/E$9,"") | F13: =IFERROR(F6/F$9,"") | G13: =IFERROR(G6/G$9,"") | H13: 计算
A14: 消费品 | B14: =IFERROR(B7/B$9,"") | C14: =IFERROR(C7/C$9,"") | D14: =IFERROR(D7/D$9,"") | E14: =IFERROR(E7/E$9,"") | F14: =IFERROR(F7/F$9,"") | G14: =IFERROR(G7/G$9,"")
A15: 商业、工业及其他 | B15: =IFERROR(B8/B$9,"") | C15: =IFERROR(C8/C$9,"") | D15: =IFERROR(D8/D$9,"") | E15: =IFERROR(E8/E$9,"") | F15: =IFERROR(F8/F$9,"") | G15: =IFERROR(G8/G$9,"")
A16: 合计 | B16: =SUM(B13:B15) | C16: =SUM(C13:C15) | D16: =SUM(D13:D15) | E16: =SUM(E13:E15) | F16: =SUM(F13:F15) | G16: =SUM(G13:G15)
A18: 五大持仓占股票组合比重 | B18: 0.73 | C18: 0.75 | D18: 0.79 | E18: 0.71 | F18: 0.65 | G18: 0.66 | H18: S6/S5/S4/S1/S2 Note 4；2021 为 4 家
A19: 集中度在 2023 年见顶（79%），随后因 Apple 持仓下降、其他持仓上升而回落至 65%—66%。2026H1 前五大为 Alphabet、American Express、Apple、Bank of America、Coca-Cola（S2 Note 4）。
A21: 2025 年末核心持仓（股东信披露；出处 L2025 p.15）
A22: 公司 | B22: 伯克希尔持股比例 | C22: 成本 | D22: 2025年末市值 | E22: 2025年分红 | F22: 备注
A23: Apple Inc. | B23: 0.016 | C23: 6255 | D23: 61962 | E23: 280 | F23: 最大单一持仓；2025 年末市值 619.6 亿美元
A24: American Express Company | B24: 0.221 | C24: 1287 | D24: 56088 | E24: 479 | F24: 持股比例 22.1%
A25: The Coca-Cola Company | B25: 0.093 | C25: 1299 | D25: 27964 | E25: 816 | F25: 分红最高
A26: Moody's Corporation | B26: 0.139 | C26: 248 | D26: 12603 | E26: 93 | F26: 持股比例 13.9%
A27: 日本五家商社合计 | C27: 15382 | D27: 35368 | E27: 862 | F27: Mitsubishi 9,207；ITOCHU 8,886；Mitsui 8,785；Marubeni 4,468；Sumitomo 4,022
A28: 核心持仓合计 | C28: =SUM(C23:C27) | D28: =SUM(D23:D27) | E28: =SUM(E23:E27) | F28: 成本/市值/分红为五项合计
A29: 占 2025 年末股票组合 | B29: =IFERROR(D28/'股票组合'!F9,"")
A30: 核心持仓合计 1,940 亿美元，约占 2025 年末 2,977.8 亿美元股票组合的 65.1%。该表只列股东信点名的核心持仓，不等于全部持仓；五大持仓的完整名单以 10-K Note 4 为准。
A31: 2025 年末五大持仓（10-K）：American Express、Apple、Bank of America、Coca-Cola、Chevron，合计占 65%。2026H1 五大持仓变为 Alphabet、American Express、Apple、Bank of America、Coca-Cola，合计 66%。

Sheet 图表数据
A1: 图表数据（全部为公式，供「变化」页图表引用）
A2: 单位：十亿美元（除注明外）。请勿手填。
A3: 年份 | B3: 保险承保 | C3: 保险投资收益 | D3: 铁路（BNSF） | E3: 能源（BHE） | F3: 制造、服务与零售 | G3: 其他
A4: 2021 | B4: ='分部利润'!B6/1000 | C4: ='分部利润'!B7/1000 | D4: ='分部利润'!B8/1000 | E4: ='分部利润'!B9/1000 | F4: ='分部利润'!B10/1000 | G4: ='分部利润'!B11/1000
A5: 2022 | B5: ='分部利润'!C6/1000 | C5: ='分部利润'!C7/1000 | D5: ='分部利润'!C8/1000 | E5: ='分部利润'!C9/1000 | F5: ='分部利润'!C10/1000 | G5: ='分部利润'!C11/1000
A6: 2023 | B6: ='分部利润'!D6/1000 | C6: ='分部利润'!D7/1000 | D6: ='分部利润'!D8/1000 | E6: ='分部利润'!D9/1000 | F6: ='分部利润'!D10/1000 | G6: ='分部利润'!D11/1000
A7: 2024 | B7: ='分部利润'!E6/1000 | C7: ='分部利润'!E7/1000 | D7: ='分部利润'!E8/1000 | E7: ='分部利润'!E9/1000 | F7: ='分部利润'!E10/1000 | G7: ='分部利润'!E11/1000
A8: 2025 | B8: ='分部利润'!F6/1000 | C8: ='分部利润'!F7/1000 | D8: ='分部利润'!F8/1000 | E8: ='分部利润'!F9/1000 | F8: ='分部利润'!F10/1000 | G8: ='分部利润'!F11/1000
A9: 2026H1 | B9: ='分部利润'!H6/1000 | C9: ='分部利润'!H7/1000 | D9: ='分部利润'!H8/1000 | E9: ='分部利润'!H9/1000 | F9: ='分部利润'!H10/1000 | G9: ='分部利润'!H11/1000
A13: 年份 | B13: 保险浮存金 | C13: 现金+短债（合并） | D13: 股票投资组合
A14: 2021 | B14: ='保险与资产'!B6/1000 | C14: ='保险与资产'!B11/1000 | D14: ='保险与资产'!B12/1000
A15: 2022 | B15: ='保险与资产'!C6/1000 | C15: ='保险与资产'!C11/1000 | D15: ='保险与资产'!C12/1000
A16: 2023 | B16: ='保险与资产'!D6/1000 | C16: ='保险与资产'!D11/1000 | D16: ='保险与资产'!D12/1000
A17: 2024 | B17: ='保险与资产'!E6/1000 | C17: ='保险与资产'!E11/1000 | D17: ='保险与资产'!E12/1000
A18: 2025 | B18: ='保险与资产'!F6/1000 | C18: ='保险与资产'!F11/1000 | D18: ='保险与资产'!F12/1000
A19: 2026H1 | B19: ='保险与资产'!G6/1000 | C19: ='保险与资产'!G11/1000 | D19: ='保险与资产'!G12/1000
A22: 板块 | B22: 2025年同比
A23: 承保 | B23: ='变化'!E22
A24: 投资收益 | B24: ='变化'!E23
A25: BNSF | B25: ='变化'!E24
A26: BHE | B26: ='变化'!E25
A27: 制造/零售 | B27: ='变化'!E26
A28: 其他 | B28: ='变化'!E27

Sheet 变化
A1: 04 变化：一页看懂五年半
A2: 左表为公式联动；右侧四图。原始出处见各数据页行末与「来源」页；2026 年情景与可修改假设见「情景」页。单位：百万美元（图：十亿美元）。
A4: A. 关键指标（公式）
A5: 指标 | B5: 2024 | C5: 2025 | D5: 2025同比 | E5: 2026H1 | F5: 2025H1 / 2025末 | G5: 2026H1 变化
A6: 营运利润 | B6: ='分部利润'!E12 | C6: ='分部利润'!F12 | D6: ='分部利润'!J12 | E6: ='分部利润'!H12 | F6: ='分部利润'!G12 | G6: ='分部利润'!K12
A7: 保险承保 | B7: ='分部利润'!E6 | C7: ='分部利润'!F6 | D7: ='分部利润'!J6 | E7: ='分部利润'!H6 | F7: ='分部利润'!G6 | G7: ='分部利润'!K6
A8: 保险投资收益 | B8: ='分部利润'!E7 | C8: ='分部利润'!F7 | D8: ='分部利润'!J7 | E8: ='分部利润'!H7 | F8: ='分部利润'!G7 | G8: ='分部利润'!K7
A9: 铁路（BNSF） | B9: ='分部利润'!E8 | C9: ='分部利润'!F8 | D9: ='分部利润'!J8 | E9: ='分部利润'!H8 | F9: ='分部利润'!G8 | G9: ='分部利润'!K8
A10: 能源（BHE） | B10: ='分部利润'!E9 | C10: ='分部利润'!F9 | D10: ='分部利润'!J9 | E10: ='分部利润'!H9 | F10: ='分部利润'!G9 | G10: ='分部利润'!K9
A11: 制造、服务与零售 | B11: ='分部利润'!E10 | C11: ='分部利润'!F10 | D11: ='分部利润'!J10 | E11: ='分部利润'!H10 | F11: ='分部利润'!G10 | G11: ='分部利润'!K10
A13: 保险浮存金 | B13: ='保险与资产'!E6 | C13: ='保险与资产'!F6 | D13: ='保险与资产'!H6 | E13: ='保险与资产'!G6 | F13: — | G13: ='保险与资产'!I6
A14: 现金+短债（合并） | B14: ='保险与资产'!E11 | C14: ='保险与资产'!F11 | D14: ='保险与资产'!H11 | E14: ='保险与资产'!G11 | F14: — | G14: ='保险与资产'!I11
A15: 股票投资组合 | B15: ='保险与资产'!E12 | C15: ='保险与资产'!F12 | D15: ='保险与资产'!H12 | E15: ='保险与资产'!G12 | F15: — | G15: ='保险与资产'!I12
A16: 归母股东权益 | B16: ='保险与资产'!E13 | C16: ='保险与资产'!F13 | D16: ='保险与资产'!H13 | E16: ='保险与资产'!G13 | F16: — | G16: ='保险与资产'!I13
A17: 每股账面价值（美元） | B17: ='保险与资产'!E15 | C17: ='保险与资产'!F15 | D17: ='保险与资产'!H15 | E17: ='保险与资产'!G15 | F17: — | G17: ='保险与资产'!I15
A18: 回购金额 | B18: ='保险与资产'!E16 | C18: ='保险与资产'!F16 | D18: ='保险与资产'!H16 | E18: ='保险与资产'!G16 | F18: — | G18: n.m.
A20: B. 各板块营运利润同比（公式）
A21: 板块 | B21: 2022 vs 2021 | C21: 2023 vs 2022 | D21: 2024 vs 2023 | E21: 2025 vs 2024 | F21: 2026H1 vs 2025H1
A22: 保险承保 | B22: =IF(OR('分部利润'!B6<=0,'分部利润'!C6<=0),"n.m.",'分部利润'!C6/'分部利润'!B6-1) | C22: =IF(OR('分部利润'!C6<=0,'分部利润'!D6<=0),"n.m.",'分部利润'!D6/'分部利润'!C6-1) | D22: =IF(OR('分部利润'!D6<=0,'分部利润'!E6<=0),"n.m.",'分部利润'!E6/'分部利润'!D6-1) | E22: =IF(OR('分部利润'!E6<=0,'分部利润'!F6<=0),"n.m.",'分部利润'!F6/'分部利润'!E6-1) | F22: =IF(OR('分部利润'!G6<=0,'分部利润'!H6<=0),"n.m.",'分部利润'!H6/'分部利润'!G6-1)
A23: 保险投资收益 | B23: =IF(OR('分部利润'!B7<=0,'分部利润'!C7<=0),"n.m.",'分部利润'!C7/'分部利润'!B7-1) | C23: =IF(OR('分部利润'!C7<=0,'分部利润'!D7<=0),"n.m.",'分部利润'!D7/'分部利润'!C7-1) | D23: =IF(OR('分部利润'!D7<=0,'分部利润'!E7<=0),"n.m.",'分部利润'!E7/'分部利润'!D7-1) | E23: =IF(OR('分部利润'!E7<=0,'分部利润'!F7<=0),"n.m.",'分部利润'!F7/'分部利润'!E7-1) | F23: =IF(OR('分部利润'!G7<=0,'分部利润'!H7<=0),"n.m.",'分部利润'!H7/'分部利润'!G7-1)
A24: 铁路（BNSF） | B24: =IF(OR('分部利润'!B8<=0,'分部利润'!C8<=0),"n.m.",'分部利润'!C8/'分部利润'!B8-1) | C24: =IF(OR('分部利润'!C8<=0,'分部利润'!D8<=0),"n.m.",'分部利润'!D8/'分部利润'!C8-1) | D24: =IF(OR('分部利润'!D8<=0,'分部利润'!E8<=0),"n.m.",'分部利润'!E8/'分部利润'!D8-1) | E24: =IF(OR('分部利润'!E8<=0,'分部利润'!F8<=0),"n.m.",'分部利润'!F8/'分部利润'!E8-1) | F24: =IF(OR('分部利润'!G8<=0,'分部利润'!H8<=0),"n.m.",'分部利润'!H8/'分部利润'!G8-1)
A25: 能源（BHE） | B25: =IF(OR('分部利润'!B9<=0,'分部利润'!C9<=0),"n.m.",'分部利润'!C9/'分部利润'!B9-1) | C25: =IF(OR('分部利润'!C9<=0,'分部利润'!D9<=0),"n.m.",'分部利润'!D9/'分部利润'!C9-1) | D25: =IF(OR('分部利润'!D9<=0,'分部利润'!E9<=0),"n.m.",'分部利润'!E9/'分部利润'!D9-1) | E25: =IF(OR('分部利润'!E9<=0,'分部利润'!F9<=0),"n.m.",'分部利润'!F9/'分部利润'!E9-1) | F25: =IF(OR('分部利润'!G9<=0,'分部利润'!H9<=0),"n.m.",'分部利润'!H9/'分部利润'!G9-1)
A26: 制造、服务与零售 | B26: =IF(OR('分部利润'!B10<=0,'分部利润'!C10<=0),"n.m.",'分部利润'!C10/'分部利润'!B10-1) | C26: =IF(OR('分部利润'!C10<=0,'分部利润'!D10<=0),"n.m.",'分部利润'!D10/'分部利润'!C10-1) | D26: =IF(OR('分部利润'!D10<=0,'分部利润'!E10<=0),"n.m.",'分部利润'!E10/'分部利润'!D10-1) | E26: =IF(OR('分部利润'!E10<=0,'分部利润'!F10<=0),"n.m.",'分部利润'!F10/'分部利润'!E10-1) | F26: =IF(OR('分部利润'!G10<=0,'分部利润'!H10<=0),"n.m.",'分部利润'!H10/'分部利润'!G10-1)
A27: 其他 | B27: =IF(OR('分部利润'!B11<=0,'分部利润'!C11<=0),"n.m.",'分部利润'!C11/'分部利润'!B11-1) | C27: =IF(OR('分部利润'!C11<=0,'分部利润'!D11<=0),"n.m.",'分部利润'!D11/'分部利润'!C11-1) | D27: =IF(OR('分部利润'!D11<=0,'分部利润'!E11<=0),"n.m.",'分部利润'!E11/'分部利润'!D11-1) | E27: =IF(OR('分部利润'!E11<=0,'分部利润'!F11<=0),"n.m.",'分部利润'!F11/'分部利润'!E11-1) | F27: =IF(OR('分部利润'!G11<=0,'分部利润'!H11<=0),"n.m.",'分部利润'!H11/'分部利润'!G11-1)
A28: 营运利润合计 | B28: =IFERROR('分部利润'!C12/'分部利润'!B12-1,"") | C28: =IFERROR('分部利润'!D12/'分部利润'!C12-1,"") | D28: =IFERROR('分部利润'!E12/'分部利润'!D12-1,"") | E28: =IFERROR('分部利润'!F12/'分部利润'!E12-1,"") | F28: =IFERROR('分部利润'!H12/'分部利润'!G12-1,"")
A30: C. 各板块占营运利润比重（公式）
A31: 板块 | B31: 2021 | C31: 2022 | D31: 2023 | E31: 2024 | F31: 2025 | G31: 2026H1
A32: 保险承保 | B32: =IFERROR('分部利润'!B6/'分部利润'!B12,"") | C32: =IFERROR('分部利润'!C6/'分部利润'!C12,"") | D32: =IFERROR('分部利润'!D6/'分部利润'!D12,"") | E32: =IFERROR('分部利润'!E6/'分部利润'!E12,"") | F32: =IFERROR('分部利润'!F6/'分部利润'!F12,"") | G32: =IFERROR('分部利润'!H6/'分部利润'!H12,"")
A33: 保险投资收益 | B33: =IFERROR('分部利润'!B7/'分部利润'!B12,"") | C33: =IFERROR('分部利润'!C7/'分部利润'!C12,"") | D33: =IFERROR('分部利润'!D7/'分部利润'!D12,"") | E33: =IFERROR('分部利润'!E7/'分部利润'!E12,"") | F33: =IFERROR('分部利润'!F7/'分部利润'!F12,"") | G33: =IFERROR('分部利润'!H7/'分部利润'!H12,"")
A34: 铁路（BNSF） | B34: =IFERROR('分部利润'!B8/'分部利润'!B12,"") | C34: =IFERROR('分部利润'!C8/'分部利润'!C12,"") | D34: =IFERROR('分部利润'!D8/'分部利润'!D12,"") | E34: =IFERROR('分部利润'!E8/'分部利润'!E12,"") | F34: =IFERROR('分部利润'!F8/'分部利润'!F12,"") | G34: =IFERROR('分部利润'!H8/'分部利润'!H12,"")
A35: 能源（BHE） | B35: =IFERROR('分部利润'!B9/'分部利润'!B12,"") | C35: =IFERROR('分部利润'!C9/'分部利润'!C12,"") | D35: =IFERROR('分部利润'!D9/'分部利润'!D12,"") | E35: =IFERROR('分部利润'!E9/'分部利润'!E12,"") | F35: =IFERROR('分部利润'!F9/'分部利润'!F12,"") | G35: =IFERROR('分部利润'!H9/'分部利润'!H12,"")
A36: 制造、服务与零售 | B36: =IFERROR('分部利润'!B10/'分部利润'!B12,"") | C36: =IFERROR('分部利润'!C10/'分部利润'!C12,"") | D36: =IFERROR('分部利润'!D10/'分部利润'!D12,"") | E36: =IFERROR('分部利润'!E10/'分部利润'!E12,"") | F36: =IFERROR('分部利润'!F10/'分部利润'!F12,"") | G36: =IFERROR('分部利润'!H10/'分部利润'!H12,"")
A37: 其他 | B37: =IFERROR('分部利润'!B11/'分部利润'!B12,"") | C37: =IFERROR('分部利润'!C11/'分部利润'!C12,"") | D37: =IFERROR('分部利润'!D11/'分部利润'!D12,"") | E37: =IFERROR('分部利润'!E11/'分部利润'!E12,"") | F37: =IFERROR('分部利润'!F11/'分部利润'!F12,"") | G37: =IFERROR('分部利润'!H11/'分部利润'!H12,"")
A38: 合计 | B38: =SUM(B32:B37) | C38: =SUM(C32:C37) | D38: =SUM(D32:D37) | E38: =SUM(E32:E37) | F38: =SUM(F32:F37) | G38: =SUM(G32:G37)
A40: 读法：2025 年营运利润同比下降 6.2%，但 2026H1 同比回升 17.0%；结构上，保险承保与投资收益的合计占比从 2021 年的 20.6% 升至 2025 年的 44.4%，2026H1 为 37.8%。「n.m.」表示基期或当期 ≤0，同比不具经济意义。2026 年情景与可修改假设见「情景」页。

Sheet 情景
A1: 05 2026 年情景：改一个假设，结果自动变
A2: 橙色格可修改；蓝色格为公式。2026H1 实际与 2025 基数来自「分部利润」「保险与资产」页，出处见「来源」页。所有结果都是机械情景，不是预测，也不是公司指引。单位：百万美元（另注者除外）。
A4: 可修改假设
A5: 假设 | B5: 值 | C5: 说明
A6: 2026H1 年化系数 | B6: 2 | C6: 把 2026H1 营运利润简单年化；2.0 = 上下半年等量。
A7: 2026H2 回购金额 | B7: 5000 | C7: 在 H1 现金支付 4,444 基础上，假设下半年再回购 50 亿美元。
A8: 2026H2 浮存金环比增速 | B8: 0.01 | C8: 假设下半年浮存金增长 1.0%。
A9: 2026H2 每股账面价值增速 | B9: 0.025 | C9: 假设下半年 BVPS 增长 2.5%（含留存收益与投资市值变动）。
A11: 2026 全年估算（公式）
A12: 项目 | B12: 2026H1 实际 | C12: 2026 全年估算 | D12: 说明
A14: 营运利润 | B14: ='分部利润'!H12 | C14: =B14*$B$6 | D14: H1 × 年化系数
A15: 回购金额 | B15: ='保险与资产'!G16 | C15: =B15+$B$7 | D15: H1 + 假设 H2
A16: 保险浮存金 | B16: ='保险与资产'!G6 | C16: =B16*(1+$B$8) | D16: H1 × (1 + H2 增速)
A17: 每股账面价值（美元） | B17: ='保险与资产'!G15 | C17: =B17*(1+$B$9) | D17: H1 × (1 + H2 增速)
A19: 敏感性：年化系数对 2026E 营运利润的影响（公式）
A20: 年化系数 | B20: 2026E 营运利润 | C20: 相对 2025 全年 | D20: 相对 2026H1
A21: 1.6 | B21: =$B$14*A21 | C21: =IFERROR(B21/'分部利润'!F12-1,"") | D21: =IFERROR(B21/$B$14-1,"")
A22: 1.8 | B22: =$B$14*A22 | C22: =IFERROR(B22/'分部利润'!F12-1,"") | D22: =IFERROR(B22/$B$14-1,"")
A23: 2 | B23: =$B$14*A23 | C23: =IFERROR(B23/'分部利润'!F12-1,"") | D23: =IFERROR(B23/$B$14-1,"")
A24: 2.2 | B24: =$B$14*A24 | C24: =IFERROR(B24/'分部利润'!F12-1,"") | D24: =IFERROR(B24/$B$14-1,"")
A25: 2.4 | B25: =$B$14*A25 | C25: =IFERROR(B25/'分部利润'!F12-1,"") | D25: =IFERROR(B25/$B$14-1,"")
A26: 怎么用：把 B6 从 2.00 改成 1.80，C14 会立即变化；B21:B25 是并列列出的五个情景，用于对比。把 B7 改成 0，全年回购变为 4,444；把 B8/B9 改成 0，浮存金/BVPS 保持 H1 水平。这些只是把「如果下半年与上半年相同/不同」翻译成数字，不能当作对 2026 年真实结果的预测。

Sheet 历史决策
A1: 06 历史决策：网页小游戏的 10 个关卡数据
A2: 这些数字同时用于「和巴菲特一起做决定」网页，保证网页与本工作簿一致。所有引用均来自致股东信；不涉及当下买卖任何股票。
A4: 年份 | B4: 决策 | C4: 关键数字 | D4: 巴菲特实际选择 | E4: 后见/结果 | F4: 出处
A5: 1967 | B5: 从纺织转向保险：收购 National Indemnity | C5: $8.6M 收购价 | D5: 买下这家奥马哈保险公司，把纺织产生的现金转向保险浮存金 | E5: 浮存金从 1967 年的起点增长到 2025 年的约 1,760 亿美元；保险成为伯克希尔的资本引擎 | F5: L2021 p.5；L2022「58 Years」
A6: 1972 | B6: 收购喜诗糖果（See's Candies） | C6: $25M 收购价；有形资本 $8M；税前利润 <$5M | D6: 在卖家要价 $30M 时坚持不超过 $25M，最终以 $25M 买下 | E6: 2007 年销售额 $383M、税前利润 $82M；1972 年以来累计税前利润约 $13.5 亿，只需再投入 $32M | F6: L2007「See's Candy」
A7: 1976 | B7: 逆势买入 GEICO | C7: 约 1/3 股权，总成本 $47M，其中约一半投于 1976 年 | D7: 在 GEICO 濒临破产、市场恐慌时买入，支持 Jack Byrne 的重整，但不干预经营 | E7: 1996 年以 $23 亿买下剩余 49%；GEICO 成为伯克希尔核心保险资产 | F7: L1980 p.14；L2004「GEICO」；L1996
A8: 1985 | B8: 关闭纺织业务 | C8: 纺织资产账面价值 $22M；前九年销售额 $530M、累计亏损 $10M | D8: 1985 年 7 月决定关闭纺织厂，把资本转向保险与其他业务 | E8: 巴菲特后来承认应更早退出；这次退出释放了后来收购所需的资本 | F8: L1985「Shutdown of Textile Business」
A9: 1988 | B9: 重仓可口可乐 | C9: 1988 年末 1,417 万股；1989 年末 2,335 万股，成本 10.24 亿美元（$1.024B），市值 18.04 亿美元（$1.804B） | D9: 在 1987 年股灾后大举买入，并长期持有 | E9: 成为伯克希尔「四大巨头」之一；2025 年末 4 亿股，成本 $12.99 亿，市值 $279.64 亿，年分红 $8.16 亿 | F9: L1989 p.14；L2025 p.15
A10: 1998 | B10: 换股并购 General Re | C10: $220 亿，全部以伯克希尔股票支付 | D10: 完成对 General Re 的收购，把伯克希尔的资本实力与全球再保险网络结合 | E10: 整合初期承保与准备金问题频出，巴菲特一度自认「巨大错误」；2014 年称其已「成为宝石」 | F10: L1998「General Re」；L2014
A11: 2008 | B11: 金融危机中的固定收益投资 | C11: $145 亿，投向 Wrigley、Goldman Sachs、General Electric 的固定收益证券，并附带股权参与 | D11: 在市场冻结时提供资本，换取高 current yield + 股权上行 | E11: 三家后来均以溢价赎回；2011 年合计赎回 $128 亿，此前每年贡献约 $12 亿税前收益 | F11: L2008 p.13；L2010 p.17；L2011 p.4
A12: 2009 | B12: 收购 BNSF 铁路 | C12: $100/股；总对价中 40% 为伯克希尔股票；整体成本约 30% 用股票支付；部署 $220 亿现金 | D12: 买下尚未持有的 77.5%，把 BNSF 变成全资子公司 | E12: BNSF 成为伯克希尔最大非保险业务之一；2025 年税后利润 $54.76 亿、营收 $233.50 亿 | F12: L2009「BNSF」；S1 p.K-42
A13: 2011 | B13: 买入 IBM | C13: 6,390 万股，成本 $109 亿，约 5.5% 股权 | D13: 在 IBM 回购与 enterprise 客户黏性上押注，公开表示「希望股价低迷五年」 | E13: IBM 后来在云计算转型中增长乏力，这笔投资未达到信中设想；成为巴菲特少见的科技股失误 | F13: L2011「IBM」
A14: 2019–2020 | B14: 买入日本五大商社 | C14: 2019 年 7 月 4 日开始买入；2023 年持股约 9%；成本 ¥1.6 万亿，2023 年末市值 ¥2.9 万亿 | D14: 用日元债融资，买入伊藤忠、丸红、三菱、三井、住友，并承诺不超过 9.9% | E14: 2023 年末美元口径未实现收益约 61%（$80 亿）；2025 年末五家市值 $353.68 亿、年分红 $8.62 亿 | F14: L2023「日本商社」；L2025 p.15
A16: 说明：本表只用于历史回顾与游戏计分，不构成对任何公司或证券的当前评价。2011 年 IBM 一栏的「后见」为公开史实概述；网页只要求引用股东信原文，不引用当前股价。

Sheet 来源
A1: 07 来源登记表
A2: 本地文件均在「材料/」；SEC 补充文件为 2021—2023 年比较数据所必需，访问日期 2026-10-22。
A4: 编号 | B4: 类型 | C4: 文件 / 网页 | D4: 章节 / 表 | E4: 用途 | F4: URL | G4: 访问日期 | H4: 备注
A5: S1 | B5: 本地 10-K | C5: 材料/Berkshire_2025年报__brka-20251231.htm | D5: MD&A Results of Operations p.K-34；合并资产负债表；Note 4 p.K-79；Note 22 p.K-102；MD&A 浮存金；MD&A 流动性；现金流量表 | E5: 2023—2025 分部利润、2024—2025 资产负债与股票组合、股数、回购、浮存金 | F5: —（任务提供） | G5: 2026-10-22 | H5: 主口径；2025 年回购为 0
A6: S2 | B6: 本地 10-Q | C6: 材料/Berkshire_2026Q2季报__brka-20260630.htm | D6: 合并资产负债表 p.2；Note 4 p.9；现金流量表 p.7；MD&A p.33—41 | E6: 2026H1 现金、股票组合、权益、回购现金支付、股数 | F6: —（任务提供） | G6: 2026-10-22 | H6: 未经审计
A7: S3 | B7: 本地 8-K 附件 | C7: 材料/Berkshire_2026Q2业绩公告__d159922dex991.htm | D7: Operating earnings 表；float/buyback 段落 | E7: 2026H1 与 2025H1 分部利润、浮存金 1,775 亿、回购约 48 亿、A 等价股数 1,431,693 | F7: —（任务提供） | G7: 2026-10-22 | H7: 公司公告口径
A8: S4 | B8: SEC 10-K | C8: Berkshire Hathaway Inc. Form 10-K for FY2024 | D8: MD&A p.K-33；合并资产负债表；Note 4 p.K-81；Note 22；现金流量表 | E8: 2023 年资产负债与股票组合（经 Pilot 重分类）；2024 年回购 2,918；2023 年回购 9,171 | F8: https://www.sec.gov/Archives/edgar/data/1067983/000095017025025210/brka-20241231.htm | G8: 2026-10-22 | H8: 用于 2023 年可比口径
A9: S5 | B9: SEC 10-K | C9: Berkshire Hathaway Inc. Form 10-K for FY2023 | D9: MD&A p.K-34；合并资产负债表；Note 4；Note 22；现金流量表 | E9: 2021—2022 分部利润（追溯重述）；2022 年资产负债与股票组合；2022 年回购 7,854 | F9: https://www.sec.gov/Archives/edgar/data/1067983/000095017024019719/brka-20231231.htm | G9: 2026-10-22 | H9: ASU 2018-12 追溯重述
A10: S6 | B10: SEC 10-K | C10: Berkshire Hathaway Inc. Form 10-K for FY2022 | D10: 合并资产负债表；Note 4；Note 22；现金流量表；MD&A 浮存金 | E10: 2021 年现金、股票组合、权益、股数、回购 27,061、浮存金 1,470 亿 | F10: https://www.sec.gov/Archives/edgar/data/1067983/000095017023004451/brka-20221231.htm | G10: 2026-10-22 | H10: 2021 年为主
A11: L1980 | B11: 股东信 | C11: 材料/股东信/1980ltr.html | D11: GEICO 部分 | E11: 1976 年 GEICO 投资成本与理由 | F11: — | G11: 2026-10-22
A12: L1985 | B12: 股东信 | C12: 材料/股东信/1985ltr.html | D12: Shutdown of Textile Business | E12: 1985 年关闭纺织业务 | F12: — | G12: 2026-10-22
A13: L1989 | B13: 股东信 | C13: 材料/股东信/1989ltr.html | D13: Coca-Cola 部分 | E13: 1988—1989 年可口可乐持仓与成本 | F13: — | G13: 2026-10-22
A14: L1996 | B14: 股东信 | C14: 材料/股东信/1996ltr.pdf | D14: Insurance—GEICO | E14: 1996 年买下 GEICO 剩余 49% | F14: — | G14: 2026-10-22
A15: L1998 | B15: 股东信 | C15: 材料/股东信/1998ltr.pdf | D15: General Re | E15: 1998 年 General Re 并购 | F15: — | G15: 2026-10-22
A16: L2007 | B16: 股东信 | C16: 材料/股东信/2007ltr.pdf | D16: See's Candy | E16: 1972 年喜诗糖果收购与后续 | F16: — | G16: 2026-10-22
A17: L2008 | B17: 股东信 | C17: 材料/股东信/2008ltr.pdf | D17: Fixed-income investments | E17: 2008 年 $145 亿固定收益投资 | F17: — | G17: 2026-10-22
A18: L2009 | B18: 股东信 | C18: 材料/股东信/2009ltr.pdf | D18: BNSF | E18: 2009 年 BNSF 收购 | F18: — | G18: 2026-10-22
A19: L2011 | B19: 股东信 | C19: 材料/股东信/2011ltr.pdf | D19: IBM | E19: 2011 年 IBM 投资 | F19: — | G19: 2026-10-22
A20: L2014 | B20: 股东信 | C20: 材料/股东信/2014ltr.pdf | D20: General Re | E20: General Re 后续反思 | F20: — | G20: 2026-10-22
A21: L2021 | B21: 股东信 | C21: 材料/股东信/2021ltr.pdf | D21: Insurance / Share Repurchases | E21: 1967 年 National Indemnity 与 2021 年回购 | F21: — | G21: 2026-10-22
A22: L2022 | B22: 股东信 | C22: 材料/股东信/2022ltr.pdf | D22: 58 Years | E22: 1967 年转向保险的回顾 | F22: — | G22: 2026-10-22
A23: L2023 | B23: 股东信 | C23: 材料/股东信/2023ltr.pdf | D23: 日本商社 / 营运利润表 | E23: 日本五家商社；2021—2023 营运利润 | F23: — | G23: 2026-10-22
A24: L2025 | B24: 股东信 | C24: 材料/股东信/2025ltr.pdf | D24: p.8, p.15 | E24: 2025 年经营回顾；核心持仓表；现金与国债 | F24: — | G24: 2026-10-22 | H24: Abel 首封年度信
A26: 本地材料为任务提供，未做修改。SEC 文件仅用于补齐任务材料未覆盖的 2021—2022 年（及 2023 年重分类）比较数据；所有 SEC 数字均可在上述 URL 的对应表中复核。

Sheet 口径
A1: 08 口径、假设与限制
A2: 读数字之前先读这一页。
B4: 单位 | C4: 除特别注明外，所有金额为百万美元；股数为股；每股账面价值为美元。
B5: 分部利润 | C5: 归属于伯克希尔股东的税后利润，取自各年年报 MD&A「Results of Operations」分部表；不含投资损益、OTTI、商誉减值等。
B6: 2021—2022 重述 | C6: 采用 2023 年 10-K 追溯重述数（ASU 2018-12）。2021 年保险承保为 8.70 亿（2022 年 10-K 原披露 7.28 亿）；2022 年保险承保为 -0.30 亿（原披露 -0.90 亿）。
B7: Pilot 口径 | C7: 2023 年 1 月 31 日取得控制并自 2 月 1 日合并。2021—2022 年 Pilot 按权益法计入「其他」；2023 年起并入「制造、服务与零售」（2023 年仅含 2—12 月）。2023 年该板块 133.62 亿 = 2023 年 10-K 的 127.59 亿 + Pilot 6.03 亿。
B8: 其他 | C8: 2021—2022 年「其他」= 2023 年 10-K 表中的「非控股业务」+「其他」；2023 年起 2025 年 10-K 将两者合并列示。
B9: 保险浮存金 | C9: 公司口径的近似净保单持有人资金；10-K 以十亿美元整数披露，2026H1 为 1,775 亿（业绩公告）。
B10: 现金与短期国债 | C10: 「保险及其他」板块的 Cash and cash equivalents + Short-term investments in U.S. Treasury Bills；合并口径另加 BNSF/BHE 的现金（两者无短期国债）。2026H1 公司另称净额 3,592 亿（扣除未结算购买）。
B11: 股票投资组合 | C11: 合并资产负债表「Investments in equity securities」公允价值，不含 Kraft Heinz、Occidental 等权益法投资；行业分类按 Note 4 的 primary industry。
B12: 每股账面价值 | C12: 计算值 = 归母股东权益 × 1,000,000 ÷ A 等价股数；A 等价股数 = Class A + Class B/1,500。不是公司披露指标，和股价无关。
B13: 回购金额 | C13: 现金流量表「Acquisitions of treasury stock」的现金支付额；2026H1 为 4,444，业绩公告称约 4,800（含期末未结算）。2025 年为 0。
B14: 核心持仓 | C14: 2025 年股东信 p.15 点名披露的 Apple、Amex、Coca-Cola、Moody's 与日本五家；不是全部持仓，也不是投资建议。
B15: 2026 全年估算 | C15: 「变化」页 D/E 两块的年化系数、H2 回购、浮存金增速、BVPS 增速均为假设，仅用于展示敏感性；不是公司指引或预测。
... B17: 免责声明 | C17: 本工作簿为研究与展示用的历史财务分析，不构成投资建议；不提供买入、卖出、持有或目标价，不评价股价。
