Workbook

Sheet 说明
B2: AI 的电从哪来 · 数据表
B3: 编制日期：2026-10-22；网页来源访问日期：2026-10-22。研究与展示用途，不构成投资建议。
B5: 用途 | C5: 汇集研究报告与 3D 网页用到的全部数据：每行注明来源名称、发布日期、口径说明与出处定位；汇总与图表全部用公式从明细计算。
B6: 颜色约定
C7: 蓝底：输入——披露数据（原始材料或网页来源），可追溯到“来源清单”。
C8: 橙底：输入——假设（见“假设”页），修改后汇总、图表、网页数据自动重算。
C9: 绿底：公式——本表计算，请勿手工覆盖。
B10: 工作表
C11: 汇总：七个部分的关键结论数字 + 7 张图表（图表数据块也是公式）。
C12: 网页数据：网页第一、二部分出现的所有数字（键值对，公式），据此导出 web/data/web-data.json。
C13: 假设：2030 年情景、2030 年“其他”电源占比、美国 2024 年天然气占比、指引取值位置、每 GW 投资、负荷率、核电容量系数。
C14: D1 数据中心用电｜D2 电源结构（含美国电网）｜D3 科技公司资本开支与电力｜D4 Meta 三季报（原始材料）｜D5 Constellation（原始材料）
C15: D6 购电协议（逐笔）｜D7 聚变｜D8 成本与瓶颈｜D9 托卡马克部件参数与网页卡片文字｜来源清单
B16: 性质分类 | C16: 披露事实 / 官方估计（如 IEA 模型估计的历史数）/ 官方预测 / 公司指引 / 公司目标 / 第三方估计 / 本表计算 / 假设。
B17: 口径提醒 | C17: ① IEA 数据中心“用电量”为设施总用电；“为数据中心供电的发电量”为发电侧口径（含输配损耗），两者不同。
C18: ② 各公司资本开支口径不同：微软含融资租赁（电话会口径），Meta 含融资租赁本金，Alphabet 与亚马逊为购置物业与设备（亚马逊为总额）。
C19: ③ 购电协议容量为合同/公告容量，不等于实际发电量；均未披露电价。先进堆合同多为意向或选择权。
C20: ④ 2030 年电源结构中，可再生、气、核为 IEA 给出的数值，煤电与“其他”依赖“其他占比”假设推算。
B21: 财务数字 | C21: Meta 与 Constellation 的财务数字以 材料/ 目录中的原始 10-Q、10-K 为准（D4、D5）；其他公司来自其官方披露。

Sheet 汇总
A1: 汇总：关键结论数字（全部为公式，从明细页与假设页计算）
A2: 绿底单元格均为公式；修改“假设”页橙色单元格（如 2030 年情景、指引取值位置、每 GW 投资）后自动重算。右侧为图表及其数据块（同样为公式）。
A4: 编号 | B4: 指标 | C4: 数值 | D4: 单位 | E4: 说明 | Q4: 图表数据 1：全球数据中心用电（TWh）
A5: 一、全球数据中心用电（IEA） | Q5: 类别 | R5: 美国 | S5: 中国 | T5: 欧洲 | U5: 其他地区
A6: S-A01 | B6: 2024 年全球数据中心用电量 | C6: ='D1_数据中心用电'!$E$5 -> 415 | D6: TWh | E6: IEA 2025 年版 | Q6: 2024 | R6: ='D1_数据中心用电'!$E$27 -> 183 | S6: ='D1_数据中心用电'!$E$30 -> 102 | T6: ='D1_数据中心用电'!$E$33 -> 68 | U6: ='D1_数据中心用电'!$E$5-'D1_数据中心用电'!$E$27-'D1_数据中心用电'!$E$30-'D1_数据中心用电'!$E$33 -> 62
A7: S-A02 | B7: 2025 年全球数据中心用电量 | C7: ='D1_数据中心用电'!$E$6 -> 485 | D7: TWh | E7: IEA 2026 年更新版 | Q7: 2025 | R7: ='D1_数据中心用电'!$E$28 -> 224 | S7: ='D1_数据中心用电'!$E$31 -> 117 | T7: ='D1_数据中心用电'!$E$34 -> 72 | U7: ='D1_数据中心用电'!$E$6-'D1_数据中心用电'!$E$28-'D1_数据中心用电'!$E$31-'D1_数据中心用电'!$E$34 -> 72
A8: S-A03 | B8: 2030 年全球数据中心用电量（所选情景） | C8: =IF('假设'!$C$5="起飞",'D1_数据中心用电'!$E$9,IF('假设'!$C$5="高效",'D1_数据中心用电'!$E$10,IF('假设'!$C$5="逆风",'D1_数据中心用电'!$E$11,'D1_数据中心用电'!$E$7))) -> 945 | D8: TWh | E8: 情景在“假设”页选择 | Q8: 2030（所选情景） | R8: ='D1_数据中心用电'!$E$29 -> 426 | S8: ='D1_数据中心用电'!$E$32 -> 277 | T8: ='D1_数据中心用电'!$E$35 -> 114 | U8: =$C$8-'D1_数据中心用电'!$E$29-'D1_数据中心用电'!$E$32-'D1_数据中心用电'!$E$35 -> 128
A9: S-A04 | B9: 2030 年全球数据中心用电量（基准情景） | C9: ='D1_数据中心用电'!$E$7 -> 945 | D9: TWh | Q9: 注：2030 年美、中、欧取基准情景，“其他地区”= 所选情景总量 − 三者。
A10: S-A05 | B10: 2035 年全球数据中心用电量（基准情景） | C10: ='D1_数据中心用电'!$E$8 -> 1193 | D10: TWh | E10: 探索性情景
A11: S-A06 | B11: 2025→2030 年均增速（所选情景） | C11: =($C$8/$C$7)^(1/5)-1 -> 0.14271523 | D11: % | E11: 复合年增长率
A12: S-A07 | B12: 2030 年用电量相当于 2024 年的倍数（所选情景） | C12: =$C$8/$C$6 -> 2.2771084 | D12: 倍
A13: S-A08 | B13: 2024 年数据中心占全球电力需求比例 | C13: ='D1_数据中心用电'!$E$5/'D1_数据中心用电'!$E$40 -> 0.015150962 | D13: % | E13: IEA 正文“约 1.5%”
A14: S-A09 | B14: 2025 年数据中心占全球电力需求比例 | C14: ='D1_数据中心用电'!$E$6/'D1_数据中心用电'!$E$41 -> 0.017199191 | D14: % | E14: IEA 正文“略高于 1.5%”（分母口径可能不同）
A15: S-A10 | B15: 2030 年数据中心占全球电力需求比例（所选情景） | C15: =$C$8/'D1_数据中心用电'!$E$42 -> 0.028130023 | D15: % | E15: IEA 正文“约 3%”
A16: S-A11 | B16: 2025–2030 年数据中心占全球新增电力需求比例（所选情景） | C16: =($C$8-'D1_数据中心用电'!$E$6)/('D1_数据中心用电'!$E$42-'D1_数据中心用电'!$E$41) -> 0.085264133 | D16: % | E16: IEA 正文“略低于 10%”
A17: S-A12 | B17: 美国数据中心用电量 2025 | C17: ='D1_数据中心用电'!$E$28 -> 224 | D17: TWh
A18: S-A13 | B18: 美国数据中心用电量 2030（基准） | C18: ='D1_数据中心用电'!$E$29 -> 426 | D18: TWh
A19: S-A14 | B19: 中国数据中心用电量 2025 | C19: ='D1_数据中心用电'!$E$31 -> 117 | D19: TWh
A20: S-A15 | B20: 中国数据中心用电量 2030（基准） | C20: ='D1_数据中心用电'!$E$32 -> 277 | D20: TWh
A21: S-A16 | B21: 欧洲数据中心用电量 2025 | C21: ='D1_数据中心用电'!$E$34 -> 72 | D21: TWh
A22: S-A17 | B22: 欧洲数据中心用电量 2030（基准） | C22: ='D1_数据中心用电'!$E$35 -> 114 | D22: TWh | Q22: 图表数据 2：为数据中心供电的发电量（TWh）
A23: S-A18 | B23: 美国占全球数据中心用电比例 2025 | C23: ='D1_数据中心用电'!$E$28/'D1_数据中心用电'!$E$6 -> 0.46185567 | D23: % | Q23: 类别 | R23: 煤电 | S23: 天然气 | T23: 可再生能源 | U23: 核电 | V23: 其他
A24: S-A19 | B24: 美中两国占 2025–2030 全球增量比例（基准） | C24: =(('D1_数据中心用电'!$E$29-'D1_数据中心用电'!$E$28)+('D1_数据中心用电'!$E$32-'D1_数据中心用电'!$E$31))/('D1_数据中心用电'!$E$7-'D1_数据中心用电'!$E$6) -> 0.78695652 | D24: % | E24: IEA 称“接近 80%” | Q24: 2024 | R24: ='D2_电源结构'!$E$11 -> 138 | S24: ='D2_电源结构'!$E$13 -> 119.6 | T24: ='D2_电源结构'!$E$12 -> 124.2 | U24: ='D2_电源结构'!$E$14 -> 69 | V24: ='D2_电源结构'!$E$15 -> 9.2
A25: S-A20 | B25: 美国数据中心占美国电力需求比例 2025 | C25: ='D1_数据中心用电'!$E$28/'D1_数据中心用电'!$E$44 -> 0.052942567 | D25: % | Q25: 2030（基准，推算） | R25: ='D2_电源结构'!$E$22 -> 210.25641 | S25: ='D2_电源结构'!$E$18 -> 340 | T25: ='D2_电源结构'!$E$17 -> 360 | U25: ='D2_电源结构'!$E$19 -> 120 | V25: ='D2_电源结构'!$E$23 -> 21.025641
A26: S-A21 | B26: 美国数据中心占美国电力需求比例 2030（基准） | C26: ='D1_数据中心用电'!$E$29/'D1_数据中心用电'!$E$45 -> 0.091475199 | D26: %
A27: S-A22 | B27: AI 专用数据中心用电 2025 | C27: ='D1_数据中心用电'!$E$20 -> 155 | D27: TWh | E27: 第三方读取 IEA 数据
A28: S-A23 | B28: AI 专用数据中心用电 2030（基准） | C28: ='D1_数据中心用电'!$E$21 -> 465 | D28: TWh
A29: S-A24 | B29: AI 专用占数据中心用电比例 2030（基准） | C29: ='D1_数据中心用电'!$E$21/'D1_数据中心用电'!$E$7 -> 0.49206349 | D29: %
A30: S-A25 | B30: 2030 年用电量隐含的设施装机（所选情景，按 IEA 2025 年利用率） | C30: =$C$8*1000/('假设'!$C$12*'D1_数据中心用电'!$E$24) -> 224.74315 | D30: GW | E30: IEA 基准情景装机为 226 GW，可对照
A31: S-A26 | B31: AI 专用数据中心用电 2025→2030 增量（基准） | C31: ='D1_数据中心用电'!$E$21-'D1_数据中心用电'!$E$20 -> 310 | D31: TWh
A32: 二、数据中心电源结构（桑基图数据，发电侧口径）
A33: S-B01 | B33: 2024 煤电 | C33: ='D2_电源结构'!$E$11 -> 138 | D33: TWh | E33: 占比 30%
A34: S-B02 | B34: 2024 天然气 | C34: ='D2_电源结构'!$E$13 -> 119.6 | D34: TWh | E34: 占比 26%
A35: S-B03 | B35: 2024 可再生能源 | C35: ='D2_电源结构'!$E$12 -> 124.2 | D35: TWh | E35: 占比 27%
A36: S-B04 | B36: 2024 核电 | C36: ='D2_电源结构'!$E$14 -> 69 | D36: TWh | E36: 占比 15%
A37: S-B05 | B37: 2024 其他 | C37: ='D2_电源结构'!$E$15 -> 9.2 | D37: TWh | E37: 残差
A38: S-B06 | B38: 2024 为数据中心供电的总发电量 | C38: ='D2_电源结构'!$E$5 -> 460 | D38: TWh
A39: S-B07 | B39: 2024 输配损耗等（发电量 − 用电量） | C39: ='D2_电源结构'!$E$16 -> 45 | D39: TWh
A40: S-B11 | B40: 2030 煤电（推算） | C40: ='D2_电源结构'!$E$22 -> 210.25641 | D40: TWh | E40: IEA：约 20% | Q40: 图表数据 3：四大科技公司资本开支（十亿美元）
A41: S-B12 | B41: 2030 天然气 | C41: ='D2_电源结构'!$E$18 -> 340 | D41: TWh | E41: IEA：约 340 | Q41: 类别 | R41: 微软 | S41: Alphabet | T41: 亚马逊 | U41: Meta
A42: S-B13 | B42: 2030 可再生能源 | C42: ='D2_电源结构'!$E$17 -> 360 | D42: TWh | E42: IEA：360 | Q42: 2024 | R42: =$C$64 -> 75.6 | S42: =$C$65 -> 52.535 | T42: =$C$66 -> 82.999 | U42: =$C$67 -> 39.225
A43: S-B14 | B43: 2030 核电 | C43: ='D2_电源结构'!$E$19 -> 120 | D43: TWh | E43: IEA：接近 120 | Q43: 2025 | R43: =$C$69 -> 118 | S43: =$C$70 -> 91.447 | T43: =$C$71 -> 131.819 | U43: =$C$72 -> 72.215
A44: S-B15 | B44: 2030 其他（推算） | C44: ='D2_电源结构'!$E$23 -> 21.025641 | D44: TWh | E44: 依赖假设 | Q44: 2026E | R44: =$C$75 -> 175 | S44: =$C$76 -> 200 | T44: =$C$77 -> 220 | U44: =$C$78 -> 140
A45: S-B16 | B45: 2030 为数据中心供电的总发电量（推算） | C45: ='D2_电源结构'!$E$21 -> 1051.2821 | D45: TWh | E45: IEA：超过 1000
A46: S-B17 | B46: 2030 输配损耗等（推算） | C46: ='D2_电源结构'!$E$24 -> 106.28205 | D46: TWh
A47: S-B18 | B47: 2030 化石能源（煤 + 气）占比（推算） | C47: =('D2_电源结构'!$E$22+'D2_电源结构'!$E$18)/'D2_电源结构'!$E$21 -> 0.52341463 | D47: % | E47: IEA：化石能源仍约占一半
A48: S-B19 | B48: 2030 低排放（可再生 + 核）占比（推算） | C48: =('D2_电源结构'!$E$17+'D2_电源结构'!$E$19)/'D2_电源结构'!$E$21 -> 0.45658537 | D48: %
A49: S-B20 | B49: 2024→2030 新增发电中可再生能源贡献比例 | C49: =('D2_电源结构'!$E$17-'D2_电源结构'!$E$12)/('D2_电源结构'!$E$21-'D2_电源结构'!$E$5) -> 0.39879445 | D49: % | E49: 2025 年版称“接近一半”，按 2026 年版数字约四成
A50: S-B21 | B50: 2024→2030 新增发电中天然气贡献比例 | C50: =('D2_电源结构'!$E$18-'D2_电源结构'!$E$13)/('D2_电源结构'!$E$21-'D2_电源结构'!$E$5) -> 0.37274935 | D50: %
A51: S-B22 | B51: 2024→2030 新增发电中核电贡献比例 | C51: =('D2_电源结构'!$E$19-'D2_电源结构'!$E$14)/('D2_电源结构'!$E$21-'D2_电源结构'!$E$5) -> 0.086253252 | D51: %
A52: S-B23 | B52: 2024→2030 新增发电中煤电贡献比例 | C52: =('D2_电源结构'!$E$22-'D2_电源结构'!$E$11)/('D2_电源结构'!$E$21-'D2_电源结构'!$E$5) -> 0.12220295 | D52: %
A53: S-B30 | B53: 美国 2024 为数据中心供电的发电量（推算） | C53: ='D2_电源结构'!$E$31 -> 202.84337 | D53: TWh
A54: S-B31 | B54: 美国 2024 天然气 | C54: ='D2_电源结构'!$E$26*'D2_电源结构'!$E$31 -> 83.165783 | D54: TWh | E54: 占比依赖假设
A55: S-B32 | B55: 美国 2024 可再生能源 | C55: ='D2_电源结构'!$E$27*'D2_电源结构'!$E$31 -> 48.68241 | D55: TWh
A56: S-B33 | B56: 美国 2024 煤电 | C56: ='D2_电源结构'!$E$28*'D2_电源结构'!$E$31 -> 40.568675 | D56: TWh
A57: S-B34 | B57: 美国 2024 核电 | C57: ='D2_电源结构'!$E$29*'D2_电源结构'!$E$31 -> 30.426506 | D57: TWh
A58: S-B35 | B58: 美国 2024 其他（残差） | C58: ='D2_电源结构'!$E$31-$C$54-$C$55-$C$56-$C$57 -> 0 | D58: TWh | Q58: 图表数据 4：季度资本开支（十亿美元）
A59: S-B36 | B59: 美国电网 2025 天然气占比 | C59: ='D2_电源结构'!$E$40/'D2_电源结构'!$E$39 -> 0.40801445 | D59: % | E59: EIA | Q59: 类别 | R59: 微软 | S59: Alphabet | T59: 亚马逊 | U59: Meta
A60: S-B37 | B60: 美国电网 2025 核电占比 | C60: ='D2_电源结构'!$E$41/'D2_电源结构'!$E$39 -> 0.17717575 | D60: % | E60: EIA | Q60: 2025Q1 | R60: ='D3_科技公司资本开支'!$E$9 -> 21.4 | S60: ='D3_科技公司资本开支'!$E$17 -> 17.197 | T60: ='D3_科技公司资本开支'!$E$25 -> 25.019 | U60: ='D3_科技公司资本开支'!$E$33 -> 13.692
A61: S-B38 | B61: 美国电网 2025 煤电占比 | C61: ='D2_电源结构'!$E$42/'D2_电源结构'!$E$39 -> 0.16642962 | D61: % | E61: EIA | Q61: 2025Q2 | R61: ='D3_科技公司资本开支'!$E$10 -> 24.2 | S61: ='D3_科技公司资本开支'!$E$18 -> 22.446 | T61: ='D3_科技公司资本开支'!$E$26 -> 32.183 | U61: ='D3_科技公司资本开支'!$E$34 -> 17.012
A62: S-B39 | B62: 美国电网 2025 风光水占比 | C62: =('D2_电源结构'!$E$43+'D2_电源结构'!$E$44+'D2_电源结构'!$E$45)/'D2_电源结构'!$E$39 -> 0.227362 | D62: % | E62: EIA | Q62: 2025Q3 | R62: ='D3_科技公司资本开支'!$E$11 -> 34.9 | S62: ='D3_科技公司资本开支'!$E$20 -> 23.953 | T62: ='D3_科技公司资本开支'!$E$28 -> 35.095 | U62: ='D3_科技公司资本开支'!$E$35 -> 19.374
A63: 三、美国科技巨头资本开支（十亿美元） | Q63: 2025Q4 | R63: ='D3_科技公司资本开支'!$E$12 -> 37.5 | S63: ='D3_科技公司资本开支'!$E$19 -> 27.851 | T63: ='D3_科技公司资本开支'!$E$27 -> 39.522 | U63: ='D3_科技公司资本开支'!$E$36 -> 22.137
A64: S-C01 | B64: 微软 2024 自然年（季度相加） | C64: ='D3_科技公司资本开支'!$E$5+'D3_科技公司资本开支'!$E$6+'D3_科技公司资本开支'!$E$7+'D3_科技公司资本开支'!$E$8 -> 75.6 | D64: 十亿美元 | E64: 含融资租赁 | Q64: 2026Q1 | R64: ='D3_科技公司资本开支'!$E$13 -> 31.9 | S64: ='D3_科技公司资本开支'!$E$21 -> 35.674 | T64: ='D3_科技公司资本开支'!$E$29 -> 44.203 | U64: ='D3_科技公司资本开支'!$E$37 -> 19.84
A65: S-C02 | B65: Alphabet 2024 | C65: ='D3_科技公司资本开支'!$E$15 -> 52.535 | D65: 十亿美元 | Q65: 2026Q2 | R65: ='D3_科技公司资本开支'!$E$14 -> 41 | S65: ='D3_科技公司资本开支'!$E$22 -> 44.924 | T65: ='D3_科技公司资本开支'!$E$30 -> 54.208 | U65: ='D3_科技公司资本开支'!$E$38 -> 31.08
A66: S-C03 | B66: 亚马逊 2024 | C66: ='D3_科技公司资本开支'!$E$23 -> 82.999 | D66: 十亿美元
A67: S-C04 | B67: Meta 2024 | C67: ='D3_科技公司资本开支'!$E$31 -> 39.225 | D67: 十亿美元
A68: S-C05 | B68: 四家合计 2024 | C68: =$C$64+$C$65+$C$66+$C$67 -> 250.359 | D68: 十亿美元 | E68: 各公司口径不完全一致
A69: S-C11 | B69: 微软 2025 自然年（季度相加） | C69: ='D3_科技公司资本开支'!$E$9+'D3_科技公司资本开支'!$E$10+'D3_科技公司资本开支'!$E$11+'D3_科技公司资本开支'!$E$12 -> 118 | D69: 十亿美元
A70: S-C12 | B70: Alphabet 2025 | C70: ='D3_科技公司资本开支'!$E$16 -> 91.447 | D70: 十亿美元
A71: S-C13 | B71: 亚马逊 2025 | C71: ='D3_科技公司资本开支'!$E$24 -> 131.819 | D71: 十亿美元
A72: S-C14 | B72: Meta 2025 | C72: ='D3_科技公司资本开支'!$E$32 -> 72.215 | D72: 十亿美元
A73: S-C15 | B73: 四家合计 2025 | C73: =$C$69+$C$70+$C$71+$C$72 -> 413.481 | D73: 十亿美元
A74: S-C16 | B74: 2025 年同比增速 | C74: =$C$73/$C$68-1 -> 0.65155237 | D74: %
A75: S-C21 | B75: 微软 2026E（公司指引） | C75: ='D3_科技公司资本开支'!$E$41 -> 175 | D75: 十亿美元 | E75: 租赁重分类后口径
A76: S-C22 | B76: Alphabet 2026E（指引区间取值） | C76: ='D3_科技公司资本开支'!$E$43+('D3_科技公司资本开支'!$E$44-'D3_科技公司资本开支'!$E$43)*'假设'!$C$8 -> 200 | D76: 十亿美元 | E76: 取值位置见假设页 | Q76: 图表数据 5：核电确定购电协议（MW）
A77: S-C23 | B77: 亚马逊 2026E（公司预期） | C77: ='D3_科技公司资本开支'!$E$45 -> 220 | D77: 十亿美元 | Q77: 类别 | R77: 确定购电协议（MW）
A78: S-C24 | B78: Meta 2026E（指引区间取值） | C78: ='D3_科技公司资本开支'!$E$46+('D3_科技公司资本开支'!$E$47-'D3_科技公司资本开支'!$E$46)*'假设'!$C$8 -> 140 | D78: 十亿美元 | Q78: 微软 | R78: =$C$120 -> 835
A79: S-C25 | B79: 四家合计 2026E | C79: =$C$75+$C$76+$C$77+$C$78 -> 735 | D79: 十亿美元 | E79: 指引口径 | Q79: Meta | R79: =$C$121 -> 3730
A80: S-C26 | B80: 2026E 同比增速 | C80: =$C$79/$C$73-1 -> 0.77759075 | D80: % | Q80: 亚马逊 | R80: =$C$122 -> 3810
A81: S-C27 | B81: 2026E 相当于 2024 年的倍数 | C81: =$C$79/$C$68 -> 2.9357842 | D81: 倍 | Q81: Google | R81: =$C$123 -> 1601
A82: S-C31 | B82: 四家合计 2025Q1 | C82: ='D3_科技公司资本开支'!$E$9+'D3_科技公司资本开支'!$E$17+'D3_科技公司资本开支'!$E$25+'D3_科技公司资本开支'!$E$33 -> 77.308 | D82: 十亿美元
A83: S-C32 | B83: 四家合计 2025Q2 | C83: ='D3_科技公司资本开支'!$E$10+'D3_科技公司资本开支'!$E$18+'D3_科技公司资本开支'!$E$26+'D3_科技公司资本开支'!$E$34 -> 95.841 | D83: 十亿美元
A84: S-C33 | B84: 四家合计 2025Q3 | C84: ='D3_科技公司资本开支'!$E$11+'D3_科技公司资本开支'!$E$20+'D3_科技公司资本开支'!$E$28+'D3_科技公司资本开支'!$E$35 -> 113.322 | D84: 十亿美元
A85: S-C34 | B85: 四家合计 2025Q4 | C85: ='D3_科技公司资本开支'!$E$12+'D3_科技公司资本开支'!$E$19+'D3_科技公司资本开支'!$E$27+'D3_科技公司资本开支'!$E$36 -> 127.01 | D85: 十亿美元
A86: S-C35 | B86: 四家合计 2026Q1 | C86: ='D3_科技公司资本开支'!$E$13+'D3_科技公司资本开支'!$E$21+'D3_科技公司资本开支'!$E$29+'D3_科技公司资本开支'!$E$37 -> 131.617 | D86: 十亿美元
A87: S-C36 | B87: 四家合计 2026Q2 | C87: ='D3_科技公司资本开支'!$E$14+'D3_科技公司资本开支'!$E$22+'D3_科技公司资本开支'!$E$30+'D3_科技公司资本开支'!$E$38 -> 171.212 | D87: 十亿美元
A88: S-C37 | B88: 2026Q2 同比增速 | C88: =$C$87/$C$83-1 -> 0.78641709 | D88: %
A89: S-C38 | B89: 2026 下半年隐含资本开支（四家） | C89: =$C$79-$C$86-$C$87 -> 432.171 | D89: 十亿美元 | E89: 全年指引 − 上半年实际
A90: S-C40 | B90: 甲骨文 FY2026（2025-06 至 2026-05） | C90: ='D3_科技公司资本开支'!$E$50 -> 55.663 | D90: 十亿美元 | E90: 财年口径，未计入四家合计
A91: S-C41 | B91: 甲骨文 FY2027E（上限） | C91: ='D3_科技公司资本开支'!$E$52 -> 95 | D91: 十亿美元 | E91: 媒体报道
A92: S-C50 | B92: 【假设推算】2026E 四家资本开支可支撑的 AI 数据中心容量（上限示意） | C92: =$C$79/'假设'!$C$9 -> 16.333333 | D92: GW | E92: 假设全部投向 AI 数据中心；实际包含非 AI 资产
A93: S-C51 | B93: 【假设推算】上述容量满负荷运转后的年用电量 | C93: =$C$92*'假设'!$C$12*'假设'!$C$10/1000 -> 100.156 | D93: TWh | E93: 负荷率见假设页
A94: S-C52 | B94: 【假设推算】相当于 2025 年全球数据中心用电的比例 | C94: =$C$93/'D1_数据中心用电'!$E$6 -> 0.20650722 | D94: % | Q94: 图表数据 6：PJM 容量拍卖全网出清价
A95: S-C53 | B95: 【敏感性】按 Epoch AI 每 GW 成本估计可支撑的容量 | C95: =$C$79/'D3_科技公司资本开支'!$E$65 -> 19.342105 | D95: GW | E95: 每 GW IT 功率约 380 亿美元 | Q95: 类别 | R95: 全网出清价（美元/MW·天）
A96: S-C54 | B96: 【敏感性】按星际之门隐含每 GW 投资可支撑的容量 | C96: =$C$79/'D3_科技公司资本开支'!$E$66 -> 12.8625 | D96: GW | E96: 约 571 亿美元/GW | Q96: 2024/25 | R96: ='D8_成本与瓶颈'!$E$34 -> 28.92
A97: 四、Meta：以最新季报为例（原始材料 10-Q） | Q97: 2025/26 | R97: ='D8_成本与瓶颈'!$E$35 -> 269.92
A98: S-D01 | B98: 2026 年三季度资本开支（含融资租赁本金） | C98: ='D4_Meta三季报'!$E$5 -> 34.91 | D98: 十亿美元 | Q98: 2026/27 | R98: ='D8_成本与瓶颈'!$E$36 -> 329.17
A99: S-D02 | B99: 2026 年三季度资本开支同比增速 | C99: ='D4_Meta三季报'!$E$5/'D3_科技公司资本开支'!$E$35-1 -> 0.80189945 | D99: % | E99: 上年同期取自季度新闻稿 | Q99: 2027/28 | R99: ='D8_成本与瓶颈'!$E$37 -> 333.44
A100: S-D03 | B100: 2026 年前三季度资本开支 | C100: ='D4_Meta三季报'!$E$6 -> 85.82 | D100: 十亿美元 | Q100: 2028/29 | R100: ='D8_成本与瓶颈'!$E$38 -> 325
A101: S-D04 | B101: 前三季度同比增速 | C101: ='D4_Meta三季报'!$E$12 -> 0.71372659 | D101: %
...

Sheet 网页数据
A1: 网页数据（网页 3D 场景使用的全部数字，均为公式，引用汇总与明细）
A2: 交付/web/data/web-data.json 由本页导出（脚本读取重算后的数值）；网页上出现的数字都能在这里按“键”找到。
A4: 键 | B4: 数值 | C4: 单位 | D4: 说明
A5: hero.dc2025 | B5: ='D1_数据中心用电'!$E$6 -> 485 | C5: TWh | D5: 2025 年全球数据中心用电
A6: hero.dc2030 | B6: ='D1_数据中心用电'!$E$7 -> 945 | C6: TWh | D6: 2030 年全球数据中心用电（基准情景）
A7: hero.capex2026 | B7: ='汇总'!$C$79 -> 735 | C7: 十亿美元 | D7: 四大科技公司 2026E 资本开支
A8: hero.nucfirm | B8: ='汇总'!$C$117 -> 9976 | C8: MW | D8: 科技公司核电确定购电协议
A9: flow.y2024.src.coal | B9: ='D2_电源结构'!$E$11 -> 138 | C9: TWh
A10: flow.y2024.src.gas | B10: ='D2_电源结构'!$E$13 -> 119.6 | C10: TWh
A11: flow.y2024.src.renew | B11: ='D2_电源结构'!$E$12 -> 124.2 | C11: TWh
A12: flow.y2024.src.nuclear | B12: ='D2_电源结构'!$E$14 -> 69 | C12: TWh
A13: flow.y2024.src.other | B13: ='D2_电源结构'!$E$15 -> 9.2 | C13: TWh
A14: flow.y2024.sink.us | B14: ='D1_数据中心用电'!$E$27 -> 183 | C14: TWh
A15: flow.y2024.sink.cn | B15: ='D1_数据中心用电'!$E$30 -> 102 | C15: TWh
A16: flow.y2024.sink.eu | B16: ='D1_数据中心用电'!$E$33 -> 68 | C16: TWh
A17: flow.y2024.sink.row | B17: ='D1_数据中心用电'!$E$5-'D1_数据中心用电'!$E$27-'D1_数据中心用电'!$E$30-'D1_数据中心用电'!$E$33 -> 62 | C17: TWh
A18: flow.y2024.sink.loss | B18: ='D2_电源结构'!$E$16 -> 45 | C18: TWh
A19: flow.y2024.gen | B19: ='D2_电源结构'!$E$5 -> 460 | C19: TWh
A20: flow.y2024.use | B20: ='D1_数据中心用电'!$E$5 -> 415 | C20: TWh
A21: flow.y2024.share | B21: ='汇总'!$C$13 -> 0.015150962 | C21: %
A22: flow.y2030.src.coal | B22: ='D2_电源结构'!$E$22 -> 210.25641 | C22: TWh
A23: flow.y2030.src.gas | B23: ='D2_电源结构'!$E$18 -> 340 | C23: TWh
A24: flow.y2030.src.renew | B24: ='D2_电源结构'!$E$17 -> 360 | C24: TWh
A25: flow.y2030.src.nuclear | B25: ='D2_电源结构'!$E$19 -> 120 | C25: TWh
A26: flow.y2030.src.other | B26: ='D2_电源结构'!$E$23 -> 21.025641 | C26: TWh
A27: flow.y2030.sink.us | B27: ='D1_数据中心用电'!$E$29 -> 426 | C27: TWh
A28: flow.y2030.sink.cn | B28: ='D1_数据中心用电'!$E$32 -> 277 | C28: TWh
A29: flow.y2030.sink.eu | B29: ='D1_数据中心用电'!$E$35 -> 114 | C29: TWh
A30: flow.y2030.sink.row | B30: ='D1_数据中心用电'!$E$7-'D1_数据中心用电'!$E$29-'D1_数据中心用电'!$E$32-'D1_数据中心用电'!$E$35 -> 128 | C30: TWh
A31: flow.y2030.sink.loss | B31: ='D2_电源结构'!$E$24 -> 106.28205 | C31: TWh
A32: flow.y2030.gen | B32: ='D2_电源结构'!$E$21 -> 1051.2821 | C32: TWh
A33: flow.y2030.use | B33: ='D1_数据中心用电'!$E$7 -> 945 | C33: TWh
A34: flow.y2030.share | B34: ='D1_数据中心用电'!$E$7/'D1_数据中心用电'!$E$42 -> 0.028130023 | C34: %
A35: flow.y2030.renewIncShare | B35: ='汇总'!$C$49 -> 0.39879445 | C35: %
A36: flow.y2030.gasIncShare | B36: ='汇总'!$C$50 -> 0.37274935 | C36: %
A37: flow.y2030.fossilShare | B37: ='汇总'!$C$47 -> 0.52341463 | C37: %
A38: flow.us2024.src.gas | B38: ='汇总'!$C$54 -> 83.165783 | C38: TWh
A39: flow.us2024.src.renew | B39: ='汇总'!$C$55 -> 48.68241 | C39: TWh
A40: flow.us2024.src.coal | B40: ='汇总'!$C$56 -> 40.568675 | C40: TWh
A41: flow.us2024.src.nuclear | B41: ='汇总'!$C$57 -> 30.426506 | C41: TWh
A42: flow.us2024.src.other | B42: ='汇总'!$C$58 -> 0 | C42: TWh
A43: flow.us2024.sink.us | B43: ='D1_数据中心用电'!$E$27 -> 183 | C43: TWh
A44: flow.us2024.sink.loss | B44: ='汇总'!$C$53-'D1_数据中心用电'!$E$27 -> 19.843373 | C44: TWh
A45: flow.us2024.gen | B45: ='汇总'!$C$53 -> 202.84337 | C45: TWh
A46: flow.us2024.use | B46: ='D1_数据中心用电'!$E$27 -> 183 | C46: TWh
A47: flow.us2024.shareUS | B47: ='D1_数据中心用电'!$E$27/'D1_数据中心用电'!$E$43 -> 0.044181555 | C47: % | D47: 占美国电力需求
A48: flow.us2024.dc2030 | B48: ='D1_数据中心用电'!$E$29 -> 426 | C48: TWh
A49: ppa.total | B49: ='汇总'!$C$117 -> 9976 | C49: MW
A50: ppa.new | B50: ='汇总'!$C$118 -> 3089 | C50: MW
A51: ppa.twh | B51: ='汇总'!$C$124 -> 79.524682 | C51: TWh
A52: ppa.share_us | B52: ='汇总'!$C$125 -> 0.3550209 | C52: %
A53: ppa.adv | B53: ='汇总'!$C$126 -> 7840 | C53: MW
A54: ppa.fusion | B54: ='汇总'!$C$142 -> 250 | C54: MW
A55: ppa.deal.PPA-01.mw | B55: ='D6_购电协议'!$I$5 -> 835 | C55: MW | D55: 重启
A56: ppa.deal.PPA-02.mw | B56: ='D6_购电协议'!$I$6 -> 1121 | C56: MW | D56: 现役 + 增容
A57: ppa.deal.PPA-03.mw | B57: ='D6_购电协议'!$I$7 -> 1920 | C57: MW | D57: 现役
A58: ppa.deal.PPA-04.mw | B58: ='D6_购电协议'!$I$8 -> 1200 | C58: MW | D58: 现役
A59: ppa.deal.PPA-05.mw | B59: ='D6_购电协议'!$I$9 -> 2609 | C59: MW | D59: 现役 + 增容
A60: ppa.deal.PPA-06.mw | B60: ='D6_购电协议'!$I$10 -> 615 | C60: MW | D60: 重启
A61: ppa.deal.PPA-07.mw | B61: ='D6_购电协议'!$I$11 -> 690 | C61: MW | D61: 现役 + 增容
A62: ppa.deal.PPA-08.mw | B62: ='D6_购电协议'!$I$12 -> 890 | C62: MW | D62: 增容
A63: ppa.deal.PPA-09.mw | B63: ='D6_购电协议'!$I$13 -> 96 | C63: MW | D63: 增容
A64: ppa.deal.PPA-01.new | B64: ='D6_购电协议'!$J$5 -> 835 | C64: MW
A65: ppa.deal.PPA-02.new | B65: ='D6_购电协议'!$J$6 -> 30 | C65: MW
A66: ppa.deal.PPA-03.new | B66: ='D6_购电协议'!$J$7 -> 0 | C66: MW
A67: ppa.deal.PPA-04.new | B67: ='D6_购电协议'!$J$8 -> 0 | C67: MW
A68: ppa.deal.PPA-05.new | B68: ='D6_购电协议'!$J$9 -> 433 | C68: MW
A69: ppa.deal.PPA-06.new | B69: ='D6_购电协议'!$J$10 -> 615 | C69: MW
A70: ppa.deal.PPA-07.new | B70: ='D6_购电协议'!$J$11 -> 190 | C70: MW
A71: ppa.deal.PPA-08.new | B71: ='D6_购电协议'!$J$12 -> 890 | C71: MW
A72: ppa.deal.PPA-09.new | B72: ='D6_购电协议'!$J$13 -> 96 | C72: MW
A73: ppa.fus.FU-P01 | B73: ='D7_聚变'!$E$23 -> 50 | C73: MW | D73: 微软—Helion
A74: ppa.fus.FU-P02 | B74: ='D7_聚变'!$E$24 -> 200 | C74: MW | D74: Google—CFS
A75: ppa.fus.year.helion | B75: ='D7_聚变'!$E$28 -> 2028 | C75: 年
A76: ppa.buyer.ms | B76: ='汇总'!$C$120 -> 835 | C76: MW
A77: ppa.buyer.me | B77: ='汇总'!$C$121 -> 3730 | C77: MW
A78: ppa.buyer.am | B78: ='汇总'!$C$122 -> 3810 | C78: MW
A79: ppa.buyer.go | B79: ='汇总'!$C$123 -> 1601 | C79: MW
A80: bridge.fusionFirstYear | B80: ='D7_聚变'!$E$28 -> 2028 | C80: 年
A81: bridge.arcMW | B81: ='D9_托卡马克部件'!$E$33 -> 400 | C81: MW
A82: bridge.fiaTotal | B82: ='D7_聚变'!$E$6 -> 14.24 | C82: 十亿美元
A83: tok.TK-01 | B83: ='D9_托卡马克部件'!$E$5 -> 150 | C83: 百万摄氏度 | D83: 等离子体温度
A84: tok.TK-02 | B84: ='D9_托卡马克部件'!$E$6 -> 500 | C84: MW | D84: 聚变功率（Q≥10 目标）
A85: tok.TK-03 | B85: ='D9_托卡马克部件'!$E$7 -> 50 | C85: MW | D85: 加热功率
A86: tok.TK-04 | B86: ='D9_托卡马克部件'!$E$8 -> 23000 | C86: 吨 | D86: 整机重量
A87: tok.TK-10 | B87: ='D9_托卡马克部件'!$E$9 -> 30 | C87: 米（约） | D87: 宽度与高度
A88: tok.TK-11 | B88: ='D9_托卡马克部件'!$E$10 -> 3850 | C88: 吨 | D88: 重量
A89: tok.TK-12 | B89: ='D9_托卡马克部件'!$E$11 -> 16000 | C89: 立方米 | D89: 容积
A90: tok.TK-20 | B90: ='D9_托卡马克部件'!$E$12 -> 18 | C90: 个 | D90: 线圈数量
A91: tok.TK-21 | B91: ='D9_托卡马克部件'!$E$13 -> 11.8 | C91: 特斯拉 | D91: 最大磁场
A92: tok.TK-22 | B92: ='D9_托卡马克部件'!$E$14 -> 330 | C92: 吨 | D92: 单个重量
A93: tok.TK-30 | B93: ='D9_托卡马克部件'!$E$15 -> 6 | C93: 个 | D93: 线圈数量
A94: tok.TK-31 | B94: ='D9_托卡马克部件'!$E$16 -> 24 | C94: 米 | D94: 最大直径
A95: tok.TK-32 | B95: ='D9_托卡马克部件'!$E$17 -> 6 | C95: 特斯拉 | D95: 最大磁场
A96: tok.TK-40 | B96: ='D9_托卡马克部件'!$E$18 -> 6 | C96: 个 | D96: 模块数量
A97: tok.TK-41 | B97: ='D9_托卡马克部件'!$E$19 -> 13 | C97: 特斯拉 | D97: 最大磁场
A98: tok.TK-42 | B98: ='D9_托卡马克部件'!$E$20 -> 15 | C98: 兆安 | D98: 驱动的等离子体电流
A99: tok.TK-50 | B99: ='D9_托卡马克部件'!$E$21 -> 19.4 | C99: 米 | D99: 外径
A100: tok.TK-51 | B100: ='D9_托卡马克部件'!$E$22 -> 11.4 | C100: 米 | D100: 高度
A101: tok.TK-52 | B101: ='D9_托卡马克部件'!$E$23 -> 5200 | C101: 吨 | D101: 重量（空载）
...

Sheet 假设
A1: 假设（橙色单元格可修改，相关结果自动联动）
A2: 这里的数值不是披露事实，而是本研究为计算设定的假设或常数；修改后，汇总、图表与“网页数据”页会自动重算。网页使用的 JSON 由“网页数据”页导出，改动后需重新导出网页数据才会同步到网页。
A4: 键 | B4: 假设项 | C4: 取值 | D4: 单位 | E4: 依据 | F4: 影响的结果
A5: scenario_2030 | B5: 2030 年全球数据中心用电情景（下拉选择） | C5: 基准 | D5: 情景 | E5: IEA 2026 年更新版四种情景：基准 945、起飞 1008、高效 868、逆风 833 TWh（D1 表 DC-03、DC-05～DC-07） | F5: 汇总 A 节 2030 年用电、增速、占比；图表 1
A6: other_share_2030 | B6: 2030 年数据中心供电中“其他”来源占比 | C6: 0.02 | D6: % | E6: IEA 未给出 2030 年“其他”占比；取 2024 年残差约 2%（D2 表 MIX-06） | F6: D2 表 2030 年总发电量、煤电与其他发电量；网页桑基图 2030 年
A7: us_gas_share_2024 | B7: 2024 年美国数据中心供电中天然气占比 | C7: 0.41 | D7: % | E7: IEA 原文“超过 40%”；取 41% 使四类合计约 100% | F7: 美国 2024 年电源结构（网页“美国 2024”视图）
A8: guidance_pos | B8: 资本开支指引在区间内的取值位置（0=下限，0.5=中值，1=上限） | C8: 0.5 | D8: 比例 | E8: 公司只给区间；默认取中值 | F8: Alphabet、Meta 2026 年资本开支；Meta 四季度隐含值
A9: capex_per_gw | B9: 每 GW AI 数据中心的全口径投资（含芯片与设施） | C9: 45 | D9: 十亿美元/GW | E9: 介于 Epoch AI 估计（约 300–380 亿美元/GW，D3 表 PW-13）与星际之门隐含值（约 570 亿美元/GW，PW-14）之间 | F9: 资本开支可支撑的 GW 推算（示意上限）
A10: ai_load_factor | B10: AI 数据中心年平均负荷率 | C10: 0.7 | D10: % | E10: Epoch AI：平均功率通常为装机的 60–80%（第三方估计） | F10: GW → 年用电量 TWh 的换算
A11: nuclear_cf | B11: 核电购电协议的年容量系数 | C11: 0.91 | D11: % | E11: 取 EIA 2025 年美国核电平均容量系数 91%（D2 表 GRID-11） | F11: 购电协议 MW → 年发电量 TWh
A12: hours | B12: 一年小时数 | C12: 8760 | D12: 小时 | E12: 常数 | F12: 所有 MW/GW 与 TWh 的换算

Sheet D1_数据中心用电
A1: D1 数据中心用电：全球、地区、情景与分母（IEA、LBNL、EIA）
A2: 蓝底=输入（披露数据）；橙底=输入（假设）；绿底=公式（本表计算）。“出处定位”给出原始材料的文件与章节，或网页链接；“访问日期”为网页查阅日期。
A4: 编号 | B4: 类别 | C4: 指标 | D4: 主体/地区 | E4: 数值 | F4: 单位 | G4: 期间 | H4: 性质 | I4: 口径说明 | J4: 来源名称 | K4: 发布日期 | L4: 出处定位（文件章节/表名或网页链接） | M4: 访问日期 | N4: 来源编号
A5: DC-01 | B5: 全球用电 | C5: 全球数据中心用电量 | D5: 全球 | E5: 415 | F5: TWh | G5: 2024 | H5: 官方估计 | I5: 含超大规模、托管、企业数据中心；设施总用电（IT×PUE）。IEA 附表 A.1 为 416 | J5: IEA《能源与人工智能》Energy and AI（世界能源展望特别报告） | K5: 2025-04（PDF 元数据 2025-04-11） | L5: https://iea.blob.core.windows.net/assets/b3a8b37f-32d1-4873-9eca-31cec5895264/EnergyandAI.pdf｜PDF 第 14 页执行摘要；附表 A.1 | M5: 2026-10-22 | N5: IEA25
A6: DC-02 | B6: 全球用电 | C6: 全球数据中心用电量 | D6: 全球 | E6: 485 | F6: TWh | G6: 2025 | H6: 官方估计 | I6: 同上口径；2026 年更新版首次给出 2025 年数 | J6: IEA《能源与人工智能关键问题》Key Questions on Energy and AI（2026 年更新版） | K6: 2026-04-16 | L6: https://iea.blob.core.windows.net/assets/3179f7f8-01f6-4dd6-bffa-c9f7b73f1dc9/KeyQuestionsonEnergyandAI.pdf｜PDF 第 10 页执行摘要；PDF 第 108 页表 A.1 | M6: 2026-10-22 | N6: IEA26
A7: DC-03 | B7: 全球用电 | C7: 全球数据中心用电量（基准情景） | D7: 全球 | E7: 945 | F7: TWh | G7: 2030 | H7: 官方预测 | I7: 基准情景；正文写“约 950 TWh”，附表 A.1 为 945 | J7: IEA《能源与人工智能关键问题》Key Questions on Energy and AI（2026 年更新版） | K7: 2026-04-16 | L7: https://iea.blob.core.windows.net/assets/3179f7f8-01f6-4dd6-bffa-c9f7b73f1dc9/KeyQuestionsonEnergyandAI.pdf｜PDF 第 108 页表 A.1（2025 年版附表为 946） | M7: 2026-10-22 | N7: IEA26
A8: DC-04 | B8: 全球用电 | C8: 全球数据中心用电量（基准情景） | D8: 全球 | E8: 1193 | F8: TWh | G8: 2035 | H8: 官方预测 | I8: 2035 年为探索性情景 | J8: IEA《能源与人工智能关键问题》Key Questions on Energy and AI（2026 年更新版） | K8: 2026-04-16 | L8: https://iea.blob.core.windows.net/assets/3179f7f8-01f6-4dd6-bffa-c9f7b73f1dc9/KeyQuestionsonEnergyandAI.pdf｜PDF 第 108 页表 A.1 | M8: 2026-10-22 | N8: IEA26
A9: DC-05 | B9: 全球用电 | C9: 全球数据中心用电量（起飞情景 Lift-Off） | D9: 全球 | E9: 1008 | F9: TWh | G9: 2030 | H9: 官方预测 | I9: AI 需求更快、供应链与电网瓶颈缓解 | J9: IEA《能源与人工智能关键问题》Key Questions on Energy and AI（2026 年更新版） | K9: 2026-04-16 | L9: https://iea.blob.core.windows.net/assets/3179f7f8-01f6-4dd6-bffa-c9f7b73f1dc9/KeyQuestionsonEnergyandAI.pdf｜PDF 第 108 页表 A.1 | M9: 2026-10-22 | N9: IEA26
A10: DC-06 | B10: 全球用电 | C10: 全球数据中心用电量（高效情景 High Efficiency） | D10: 全球 | E10: 868 | F10: TWh | G10: 2030 | H10: 官方预测 | I10: 能效提升更快 | J10: IEA《能源与人工智能关键问题》Key Questions on Energy and AI（2026 年更新版） | K10: 2026-04-16 | L10: https://iea.blob.core.windows.net/assets/3179f7f8-01f6-4dd6-bffa-c9f7b73f1dc9/KeyQuestionsonEnergyandAI.pdf｜PDF 第 108 页表 A.1 | M10: 2026-10-22 | N10: IEA26
A11: DC-07 | B11: 全球用电 | C11: 全球数据中心用电量（逆风情景 Headwinds） | D11: 全球 | E11: 833 | F11: TWh | G11: 2030 | H11: 官方预测 | I11: AI 应用放缓、瓶颈更严重 | J11: IEA《能源与人工智能关键问题》Key Questions on Energy and AI（2026 年更新版） | K11: 2026-04-16 | L11: https://iea.blob.core.windows.net/assets/3179f7f8-01f6-4dd6-bffa-c9f7b73f1dc9/KeyQuestionsonEnergyandAI.pdf｜PDF 第 108 页表 A.1 | M11: 2026-10-22 | N11: IEA26
A12: DC-08 | B12: 全球用电 | C12: 全球数据中心用电量（起飞情景） | D12: 全球 | E12: 1637 | F12: TWh | G12: 2035 | H12: 官方预测 | I12: 探索性情景 | J12: IEA《能源与人工智能关键问题》Key Questions on Energy and AI（2026 年更新版） | K12: 2026-04-16 | L12: https://iea.blob.core.windows.net/assets/3179f7f8-01f6-4dd6-bffa-c9f7b73f1dc9/KeyQuestionsonEnergyandAI.pdf｜PDF 第 108 页表 A.1 | M12: 2026-10-22 | N12: IEA26
A13: DC-09 | B13: 全球用电 | C13: 全球数据中心用电量（高效情景） | D13: 全球 | E13: 1013 | F13: TWh | G13: 2035 | H13: 官方预测 | I13: 探索性情景 | J13: IEA《能源与人工智能关键问题》Key Questions on Energy and AI（2026 年更新版） | K13: 2026-04-16 | L13: https://iea.blob.core.windows.net/assets/3179f7f8-01f6-4dd6-bffa-c9f7b73f1dc9/KeyQuestionsonEnergyandAI.pdf｜PDF 第 108 页表 A.1 | M13: 2026-10-22 | N13: IEA26
A14: DC-10 | B14: 全球用电 | C14: 全球数据中心用电量（逆风情景） | D14: 全球 | E14: 942 | F14: TWh | G14: 2035 | H14: 官方预测 | I14: 探索性情景 | J14: IEA《能源与人工智能关键问题》Key Questions on Energy and AI（2026 年更新版） | K14: 2026-04-16 | L14: https://iea.blob.core.windows.net/assets/3179f7f8-01f6-4dd6-bffa-c9f7b73f1dc9/KeyQuestionsonEnergyandAI.pdf｜PDF 第 108 页表 A.1 | M14: 2026-10-22 | N14: IEA26
A15: DC-11 | B15: 全球用电 | C15: 2025 年版报告给出的 2030 年区间下限（逆风） | D15: 全球 | E15: 669 | F15: TWh | G15: 2030 | H15: 官方预测 | I15: 2025 年版四情景区间 669–1264；2026 年版收窄为 833–1008 | J15: IEA《能源与人工智能》Energy and AI（世界能源展望特别报告） | K15: 2025-04（PDF 元数据 2025-04-11） | L15: https://iea.blob.core.windows.net/assets/b3a8b37f-32d1-4873-9eca-31cec5895264/EnergyandAI.pdf｜附件 A 表 A.1 | M15: 2026-10-22 | N15: IEA25
A16: DC-12 | B16: 全球用电 | C16: 2025 年版报告给出的 2030 年区间上限（起飞） | D16: 全球 | E16: 1264 | F16: TWh | G16: 2030 | H16: 官方预测 | I16: 同上 | J16: IEA《能源与人工智能》Energy and AI（世界能源展望特别报告） | K16: 2025-04（PDF 元数据 2025-04-11） | L16: https://iea.blob.core.windows.net/assets/b3a8b37f-32d1-4873-9eca-31cec5895264/EnergyandAI.pdf｜附件 A 表 A.1 | M16: 2026-10-22 | N16: IEA25
A17: DC-13 | B17: 全球用电 | C17: 全球数据中心用电量 | D17: 全球 | E17: 360 | F17: TWh | G17: 2023 | H17: 官方估计 | I17: 2026 年版附表（2025 年版为 361） | J17: IEA《能源与人工智能关键问题》Key Questions on Energy and AI（2026 年更新版） | K17: 2026-04-16 | L17: https://iea.blob.core.windows.net/assets/3179f7f8-01f6-4dd6-bffa-c9f7b73f1dc9/KeyQuestionsonEnergyandAI.pdf｜PDF 第 108 页表 A.1 | M17: 2026-10-22 | N17: IEA26
A18: DC-14 | B18: 全球用电 | C18: 数据中心用电同比增速 | D18: 全球 | E18: 0.17 | F18: % | G18: 2025 | H18: 官方估计 | J18: IEA《能源与人工智能关键问题》Key Questions on Energy and AI（2026 年更新版） | K18: 2026-04-16 | L18: https://iea.blob.core.windows.net/assets/3179f7f8-01f6-4dd6-bffa-c9f7b73f1dc9/KeyQuestionsonEnergyandAI.pdf｜PDF 第 9 页执行摘要 | M18: 2026-10-22 | N18: IEA26
A19: DC-15 | B19: 全球用电 | C19: AI 专用数据中心用电同比增速 | D19: 全球 | E19: 0.5 | F19: % | G19: 2025 | H19: 官方估计 | I19: AI 专用 = 大量配备专用加速器服务器的数据中心 | J19: IEA《能源与人工智能关键问题》Key Questions on Energy and AI（2026 年更新版） | K19: 2026-04-16 | L19: https://iea.blob.core.windows.net/assets/3179f7f8-01f6-4dd6-bffa-c9f7b73f1dc9/KeyQuestionsonEnergyandAI.pdf｜PDF 第 9–10 页执行摘要 | M19: 2026-10-22 | N19: IEA26
A20: DC-16 | B20: 全球用电 | C20: AI 专用数据中心用电量 | D20: 全球 | E20: 155 | F20: TWh | G20: 2025 | H20: 第三方估计 | I20: OWID 读取 IEA 2026 图表数据所得；约占当年总量三分之一 | J20: Our World in Data：数据中心和人工智能用多少电（图表数据来源 IEA 2026） | K20: 2026-07-20 | L20: https://ourworldindata.org/how-much-energy-do-data-centers-and-artificial-intelligence-use｜图表“数据中心用电：AI 专用 vs 其他” | M20: 2026-10-22 | N20: OWID26
A21: DC-17 | B21: 全球用电 | C21: AI 专用数据中心用电量（基准情景） | D21: 全球 | E21: 465 | F21: TWh | G21: 2030 | H21: 官方预测 | I21: 约为 2030 年数据中心总用电的一半 | J21: IEA《能源与人工智能关键问题》Key Questions on Energy and AI（2026 年更新版） | K21: 2026-04-16 | L21: https://iea.blob.core.windows.net/assets/3179f7f8-01f6-4dd6-bffa-c9f7b73f1dc9/KeyQuestionsonEnergyandAI.pdf｜PDF 第 26 页 | M21: 2026-10-22 | N21: IEA26
A22: DC-18 | B22: 全球用电 | C22: 数据中心装机容量（设施） | D22: 全球 | E22: 114 | F22: GW | G22: 2025 | H22: 官方估计 | I22: 设施总容量 | J22: IEA《能源与人工智能关键问题》Key Questions on Energy and AI（2026 年更新版） | K22: 2026-04-16 | L22: https://iea.blob.core.windows.net/assets/3179f7f8-01f6-4dd6-bffa-c9f7b73f1dc9/KeyQuestionsonEnergyandAI.pdf｜PDF 第 108 页表 A.1 | M22: 2026-10-22 | N22: IEA26
A23: DC-19 | B23: 全球用电 | C23: 数据中心装机容量（设施，基准情景） | D23: 全球 | E23: 226 | F23: GW | G23: 2030 | H23: 官方预测 | J23: IEA《能源与人工智能关键问题》Key Questions on Energy and AI（2026 年更新版） | K23: 2026-04-16 | L23: https://iea.blob.core.windows.net/assets/3179f7f8-01f6-4dd6-bffa-c9f7b73f1dc9/KeyQuestionsonEnergyandAI.pdf｜PDF 第 108 页表 A.1 | M23: 2026-10-22 | N23: IEA26
A24: DC-20 | B24: 全球用电 | C24: 数据中心平均利用率（容量系数） | D24: 全球 | E24: 0.48 | F24: % | G24: 2025 | H24: 官方估计 | I24: 用电量 ÷（装机 × 8760 小时） | J24: IEA《能源与人工智能关键问题》Key Questions on Energy and AI（2026 年更新版） | K24: 2026-04-16 | L24: https://iea.blob.core.windows.net/assets/3179f7f8-01f6-4dd6-bffa-c9f7b73f1dc9/KeyQuestionsonEnergyandAI.pdf｜PDF 第 108 页表 A.1 | M24: 2026-10-22 | N24: IEA26
A25: DC-21 | B25: 全球用电 | C25: 数据中心平均 PUE | D25: 全球 | E25: 1.38 | F25: 倍 | G25: 2025 | H25: 官方估计 | I25: 设施总用电 ÷ IT 用电；2024 年 1.41 | J25: IEA《能源与人工智能关键问题》Key Questions on Energy and AI（2026 年更新版） | K25: 2026-04-16 | L25: https://iea.blob.core.windows.net/assets/3179f7f8-01f6-4dd6-bffa-c9f7b73f1dc9/KeyQuestionsonEnergyandAI.pdf｜PDF 第 108 页表 A.1 | M25: 2026-10-22 | N25: IEA26
A26: DC-22 | B26: 全球用电 | C26: 数据中心平均 PUE（基准情景） | D26: 全球 | E26: 1.29 | F26: 倍 | G26: 2030 | H26: 官方预测 | J26: IEA《能源与人工智能关键问题》Key Questions on Energy and AI（2026 年更新版） | K26: 2026-04-16 | L26: https://iea.blob.core.windows.net/assets/3179f7f8-01f6-4dd6-bffa-c9f7b73f1dc9/KeyQuestionsonEnergyandAI.pdf｜PDF 第 108 页表 A.1 | M26: 2026-10-22 | N26: IEA26
A27: DC-30 | B27: 地区 | C27: 美国数据中心用电量 | D27: 美国 | E27: 183 | F27: TWh | G27: 2024 | H27: 官方估计 | I27: IEA 模型口径（与 LBNL 口径不同） | J27: IEA《能源与人工智能关键问题》Key Questions on Energy and AI（2026 年更新版） | K27: 2026-04-16 | L27: https://iea.blob.core.windows.net/assets/3179f7f8-01f6-4dd6-bffa-c9f7b73f1dc9/KeyQuestionsonEnergyandAI.pdf｜PDF 第 110 页表 A.4 | M27: 2026-10-22 | N27: IEA26
A28: DC-31 | B28: 地区 | C28: 美国数据中心用电量 | D28: 美国 | E28: 224 | F28: TWh | G28: 2025 | H28: 官方估计 | I28: 同上 | J28: IEA《能源与人工智能关键问题》Key Questions on Energy and AI（2026 年更新版） | K28: 2026-04-16 | L28: https://iea.blob.core.windows.net/assets/3179f7f8-01f6-4dd6-bffa-c9f7b73f1dc9/KeyQuestionsonEnergyandAI.pdf｜PDF 第 110 页表 A.4 | M28: 2026-10-22 | N28: IEA26
A29: DC-32 | B29: 地区 | C29: 美国数据中心用电量（基准情景） | D29: 美国 | E29: 426 | F29: TWh | G29: 2030 | H29: 官方预测 | I29: 同上 | J29: IEA《能源与人工智能关键问题》Key Questions on Energy and AI（2026 年更新版） | K29: 2026-04-16 | L29: https://iea.blob.core.windows.net/assets/3179f7f8-01f6-4dd6-bffa-c9f7b73f1dc9/KeyQuestionsonEnergyandAI.pdf｜PDF 第 110 页表 A.4 | M29: 2026-10-22 | N29: IEA26
A30: DC-33 | B30: 地区 | C30: 中国数据中心用电量 | D30: 中国 | E30: 102 | F30: TWh | G30: 2024 | H30: 官方估计 | I30: IEA 模型口径 | J30: IEA《能源与人工智能关键问题》Key Questions on Energy and AI（2026 年更新版） | K30: 2026-04-16 | L30: https://iea.blob.core.windows.net/assets/3179f7f8-01f6-4dd6-bffa-c9f7b73f1dc9/KeyQuestionsonEnergyandAI.pdf｜PDF 第 110 页表 A.4 | M30: 2026-10-22 | N30: IEA26
A31: DC-34 | B31: 地区 | C31: 中国数据中心用电量 | D31: 中国 | E31: 117 | F31: TWh | G31: 2025 | H31: 官方估计 | I31: 同上 | J31: IEA《能源与人工智能关键问题》Key Questions on Energy and AI（2026 年更新版） | K31: 2026-04-16 | L31: https://iea.blob.core.windows.net/assets/3179f7f8-01f6-4dd6-bffa-c9f7b73f1dc9/KeyQuestionsonEnergyandAI.pdf｜PDF 第 110 页表 A.4 | M31: 2026-10-22 | N31: IEA26
A32: DC-35 | B32: 地区 | C32: 中国数据中心用电量（基准情景） | D32: 中国 | E32: 277 | F32: TWh | G32: 2030 | H32: 官方预测 | I32: 同上 | J32: IEA《能源与人工智能关键问题》Key Questions on Energy and AI（2026 年更新版） | K32: 2026-04-16 | L32: https://iea.blob.core.windows.net/assets/3179f7f8-01f6-4dd6-bffa-c9f7b73f1dc9/KeyQuestionsonEnergyandAI.pdf｜PDF 第 110 页表 A.4 | M32: 2026-10-22 | N32: IEA26
A33: DC-36 | B33: 地区 | C33: 欧洲数据中心用电量 | D33: 欧洲 | E33: 68 | F33: TWh | G33: 2024 | H33: 官方估计 | I33: IEA 模型口径 | J33: IEA《能源与人工智能关键问题》Key Questions on Energy and AI（2026 年更新版） | K33: 2026-04-16 | L33: https://iea.blob.core.windows.net/assets/3179f7f8-01f6-4dd6-bffa-c9f7b73f1dc9/KeyQuestionsonEnergyandAI.pdf｜PDF 第 110 页表 A.4 | M33: 2026-10-22 | N33: IEA26
A34: DC-37 | B34: 地区 | C34: 欧洲数据中心用电量 | D34: 欧洲 | E34: 72 | F34: TWh | G34: 2025 | H34: 官方估计 | I34: 同上 | J34: IEA《能源与人工智能关键问题》Key Questions on Energy and AI（2026 年更新版） | K34: 2026-04-16 | L34: https://iea.blob.core.windows.net/assets/3179f7f8-01f6-4dd6-bffa-c9f7b73f1dc9/KeyQuestionsonEnergyandAI.pdf｜PDF 第 110 页表 A.4 | M34: 2026-10-22 | N34: IEA26
A35: DC-38 | B35: 地区 | C35: 欧洲数据中心用电量（基准情景） | D35: 欧洲 | E35: 114 | F35: TWh | G35: 2030 | H35: 官方预测 | I35: 同上（2025 年版为 113） | J35: IEA《能源与人工智能关键问题》Key Questions on Energy and AI（2026 年更新版） | K35: 2026-04-16 | L35: https://iea.blob.core.windows.net/assets/3179f7f8-01f6-4dd6-bffa-c9f7b73f1dc9/KeyQuestionsonEnergyandAI.pdf｜PDF 第 110 页表 A.4 | M35: 2026-10-22 | N35: IEA26
A36: DC-46 | B36: 地区 | C36: 美国数据中心用电量 | D36: 美国 | E36: 154 | F36: TWh | G36: 2023 | H36: 官方估计 | I36: IEA 模型口径（LBNL 同年估计为 176） | J36: IEA《能源与人工智能关键问题》Key Questions on Energy and AI（2026 年更新版） | K36: 2026-04-16 | L36: https://iea.blob.core.windows.net/assets/3179f7f8-01f6-4dd6-bffa-c9f7b73f1dc9/KeyQuestionsonEnergyandAI.pdf｜PDF 第 110 页表 A.4 | M36: 2026-10-22 | N36: IEA26
A37: DC-47 | B37: 地区 | C37: 中国数据中心用电量 | D37: 中国 | E37: 84 | F37: TWh | G37: 2023 | H37: 官方估计 | I37: IEA 模型口径 | J37: IEA《能源与人工智能关键问题》Key Questions on Energy and AI（2026 年更新版） | K37: 2026-04-16 | L37: https://iea.blob.core.windows.net/assets/3179f7f8-01f6-4dd6-bffa-c9f7b73f1dc9/KeyQuestionsonEnergyandAI.pdf｜PDF 第 110 页表 A.4 | M37: 2026-10-22 | N37: IEA26
A38: DC-48 | B38: 地区 | C38: 欧洲数据中心用电量 | D38: 欧洲 | E38: 66 | F38: TWh | G38: 2023 | H38: 官方估计 | I38: IEA 模型口径 | J38: IEA《能源与人工智能关键问题》Key Questions on Energy and AI（2026 年更新版） | K38: 2026-04-16 | L38: https://iea.blob.core.windows.net/assets/3179f7f8-01f6-4dd6-bffa-c9f7b73f1dc9/KeyQuestionsonEnergyandAI.pdf｜PDF 第 110 页表 A.4 | M38: 2026-10-22 | N38: IEA26
... A52: DC-61 | B52: 科技公司 | C52: 大型科技公司资本开支 | D52: 五家公司 | E52: 400 | F52: 十亿美元 | G52: 2025 | H52: 官方估计 | I52: IEA 原文“超过 4000 亿美元” | J52: IEA《能源与人工智能关键问题》Key Questions on Energy and AI（2026 年更新版） | K52: 2026-04-16 | L52: https://iea.blob.core.windows.net/assets/3179f7f8-01f6-4dd6-bffa-c9f7b73f1dc9/KeyQuestionsonEnergyandAI.pdf｜PDF 第 9 页执行摘要 | M52: 2026-10-22 | N52: IEA26
A53: DC-62 | B53: 科技公司 | C53: 大型科技公司资本开支 2026 年预期增幅 | D53: 五家公司 | E53: 0.75 | F53: % | G53: 2026 | H53: 官方预测 | J53: IEA《能源与人工智能关键问题》Key Questions on Energy and AI（2026 年更新版） | K53: 2026-04-16 | L53: https://iea.blob.core.windows.net/assets/3179f7f8-01f6-4dd6-bffa-c9f7b73f1dc9/KeyQuestionsonEnergyandAI.pdf｜PDF 第 9 页执行摘要 | M53: 2026-10-22 | N53: IEA26
A54: DC-63 | B54: 供给 | C54: 计划作为数据中心专用电源的新增燃气装机 | D54: 全球（主要在美国） | E54: 100 | F54: GW | G54: 2026 | H54: 官方估计 | I54: 原文“超过 100 GW”，以现场发电为主 | J54: IEA《能源与人工智能关键问题》Key Questions on Energy and AI（2026 年更新版） | K54: 2026-04-16 | L54: https://iea.blob.core.windows.net/assets/3179f7f8-01f6-4dd6-bffa-c9f7b73f1dc9/KeyQuestionsonEnergyandAI.pdf｜PDF 第 49 页 §5.2 | M54: 2026-10-22 | N54: IEA26
A55: DC-64 | B55: 供给 | C55: 2030 年可能为数据中心供电的现场燃气装机（下限） | D55: 全球 | E55: 15 | F55: GW | G55: 2030 | H55: 官方预测 | I55: 区间 15–27 GW | J55: IEA《能源与人工智能关键问题》Key Questions on Energy and AI（2026 年更新版） | K55: 2026-04-16 | L55: https://iea.blob.core.windows.net/assets/3179f7f8-01f6-4dd6-bffa-c9f7b73f1dc9/KeyQuestionsonEnergyandAI.pdf｜PDF 第 11 页执行摘要 | M55: 2026-10-22 | N55: IEA26
A56: DC-65 | B56: 供给 | C56: 2030 年可能为数据中心供电的现场燃气装机（上限） | D56: 全球 | E56: 27 | F56: GW | G56: 2030 | H56: 官方预测 | I56: 区间 15–27 GW | J56: IEA《能源与人工智能关键问题》Key Questions on Energy and AI（2026 年更新版） | K56: 2026-04-16 | L56: https://iea.blob.core.windows.net/assets/3179f7f8-01f6-4dd6-bffa-c9f7b73f1dc9/KeyQuestionsonEnergyandAI.pdf｜PDF 第 11 页执行摘要 | M56: 2026-10-22 | N56: IEA26
A57: DC-66 | B57: 供给 | C57: 数据中心与小型模块堆（SMR）签署的承购协议规模 | D57: 全球 | E57: 45 | F57: GW | G57: 2025 年底 | H57: 官方估计 | I57: 2024 年底约 25 GW；首批项目约 2030 年投运 | J57: IEA《能源与人工智能关键问题》Key Questions on Energy and AI（2026 年更新版） | K57: 2026-04-16 | L57: https://iea.blob.core.windows.net/assets/3179f7f8-01f6-4dd6-bffa-c9f7b73f1dc9/KeyQuestionsonEnergyandAI.pdf｜PDF 第 11 页执行摘要 | M57: 2026-10-22 | N57: IEA26
A58: DC-67 | B58: 供给 | C58: 科技行业占全球企业可再生能源购电协议比例 | D58: 全球 | E58: 0.4 | F58: % | G58: 2025 | H58: 官方估计 | I58: 数据中心企业签署超过 40 TWh | J58: IEA《能源与人工智能关键问题》Key Questions on Energy and AI（2026 年更新版） | K58: 2026-04-16 | L58: https://iea.blob.core.windows.net/assets/3179f7f8-01f6-4dd6-bffa-c9f7b73f1dc9/KeyQuestionsonEnergyandAI.pdf｜执行摘要；p.47 | M58: 2026-10-22 | N58: IEA26
A59: DC-68 | B59: 供给 | C59: 燃气轮机订单同比增幅 | D59: 全球 | E59: 0.7 | F59: % | G59: 2025 | H59: 官方估计 | J59: IEA《能源与人工智能关键问题》Key Questions on Energy and AI（2026 年更新版） | K59: 2026-04-16 | L59: https://iea.blob.core.windows.net/assets/3179f7f8-01f6-4dd6-bffa-c9f7b73f1dc9/KeyQuestionsonEnergyandAI.pdf｜PDF 第 11 页执行摘要 | M59: 2026-10-22 | N59: IEA26
A60: DC-69 | B60: 瓶颈 | C60: 因电网拥堵而面临延期风险的全球数据中心建设比例 | D60: 全球 | E60: 0.2 | F60: % | G60: 2026 | H60: 官方估计 | I60: 原文“五分之一” | J60: IEA《电力 2026》Electricity 2026 – Analysis and forecast to 2030 | K60: 2026-02 | L60: https://iea.blob.core.windows.net/assets/b73798cb-e452-42b9-9d8a-07542de7a041/Electricity_2026.pdf｜p.49 | M60: 2026-10-22 | N60: IEAE26

Sheet D2_电源结构
A1: D2 数据中心电源结构与美国电网结构（IEA、EIA；含本表计算的桑基图数值）
A2: 蓝底=输入（披露数据）；橙底=输入（假设）；绿底=公式（本表计算）。“出处定位”给出原始材料的文件与章节，或网页链接；“访问日期”为网页查阅日期。
A4: 编号 | B4: 类别 | C4: 指标 | D4: 主体/地区 | E4: 数值 | F4: 单位 | G4: 期间 | H4: 性质 | I4: 口径说明 | J4: 来源名称 | K4: 发布日期 | L4: 出处定位（文件章节/表名或网页链接） | M4: 访问日期 | N4: 来源编号
A5: MIX-01 | B5: 全球 2024 | C5: 为数据中心供电的发电量 | D5: 全球 | E5: 460 | F5: TWh | G5: 2024 | H5: 官方估计 | I5: 发电侧口径，含输配损耗，大于用电量 415 | J5: IEA《能源与人工智能》Energy and AI（世界能源展望特别报告） | K5: 2025-04（PDF 元数据 2025-04-11） | L5: https://iea.blob.core.windows.net/assets/b3a8b37f-32d1-4873-9eca-31cec5895264/EnergyandAI.pdf｜PDF 第 86 页 §2.5.3 | M5: 2026-10-22 | N5: IEA25
A6: MIX-02 | B6: 全球 2024 | C6: 煤电占比 | D6: 全球 | E6: 0.3 | F6: % | G6: 2024 | H6: 官方估计 | I6: 原文“约 30%”，中国占比最高 | J6: IEA《能源与人工智能》Energy and AI（世界能源展望特别报告） | K6: 2025-04（PDF 元数据 2025-04-11） | L6: https://iea.blob.core.windows.net/assets/b3a8b37f-32d1-4873-9eca-31cec5895264/EnergyandAI.pdf｜PDF 第 86 页 | M6: 2026-10-22 | N6: IEA25
A7: MIX-03 | B7: 全球 2024 | C7: 可再生能源占比 | D7: 全球 | E7: 0.27 | F7: % | G7: 2024 | H7: 官方估计 | I7: 风电、光伏、水电为主 | J7: IEA《能源与人工智能》Energy and AI（世界能源展望特别报告） | K7: 2025-04（PDF 元数据 2025-04-11） | L7: https://iea.blob.core.windows.net/assets/b3a8b37f-32d1-4873-9eca-31cec5895264/EnergyandAI.pdf｜PDF 第 86 页 | M7: 2026-10-22 | N7: IEA25
A8: MIX-04 | B8: 全球 2024 | C8: 天然气发电占比 | D8: 全球 | E8: 0.26 | F8: % | G8: 2024 | H8: 官方估计 | J8: IEA《能源与人工智能》Energy and AI（世界能源展望特别报告） | K8: 2025-04（PDF 元数据 2025-04-11） | L8: https://iea.blob.core.windows.net/assets/b3a8b37f-32d1-4873-9eca-31cec5895264/EnergyandAI.pdf｜PDF 第 86 页 | M8: 2026-10-22 | N8: IEA25
A9: MIX-05 | B9: 全球 2024 | C9: 核电占比 | D9: 全球 | E9: 0.15 | F9: % | G9: 2024 | H9: 官方估计 | J9: IEA《能源与人工智能》Energy and AI（世界能源展望特别报告） | K9: 2025-04（PDF 元数据 2025-04-11） | L9: https://iea.blob.core.windows.net/assets/b3a8b37f-32d1-4873-9eca-31cec5895264/EnergyandAI.pdf｜PDF 第 86 页 | M9: 2026-10-22 | N9: IEA25
A10: MIX-06 | B10: 全球 2024 | C10: 其他（残差）占比 | D10: 全球 | E10: =1-$E$6-$E$7-$E$8-$E$9 -> 0.02 | F10: % | G10: 2024 | H10: 本表计算 | I10: 100% 减去上述四项 | J10: 本表计算（公式见单元格） | K10: 2026-10-22 | M10: — | N10: CALC
A11: MIX-07 | B11: 全球 2024 | C11: 煤电供数据中心发电量 | D11: 全球 | E11: =$E$5*$E$6 -> 138 | F11: TWh | G11: 2024 | H11: 本表计算 | I11: 占比 × 460 | J11: 本表计算（公式见单元格） | K11: 2026-10-22 | M11: — | N11: CALC
A12: MIX-08 | B12: 全球 2024 | C12: 可再生能源供数据中心发电量 | D12: 全球 | E12: =$E$5*$E$7 -> 124.2 | F12: TWh | G12: 2024 | H12: 本表计算 | I12: 占比 × 460 | J12: 本表计算（公式见单元格） | K12: 2026-10-22 | M12: — | N12: CALC
A13: MIX-09 | B13: 全球 2024 | C13: 天然气供数据中心发电量 | D13: 全球 | E13: =$E$5*$E$8 -> 119.6 | F13: TWh | G13: 2024 | H13: 本表计算 | I13: 占比 × 460 | J13: 本表计算（公式见单元格） | K13: 2026-10-22 | M13: — | N13: CALC
A14: MIX-10 | B14: 全球 2024 | C14: 核电供数据中心发电量 | D14: 全球 | E14: =$E$5*$E$9 -> 69 | F14: TWh | G14: 2024 | H14: 本表计算 | I14: 占比 × 460 | J14: 本表计算（公式见单元格） | K14: 2026-10-22 | M14: — | N14: CALC
A15: MIX-11 | B15: 全球 2024 | C15: 其他供数据中心发电量 | D15: 全球 | E15: =$E$5*$E$10 -> 9.2 | F15: TWh | G15: 2024 | H15: 本表计算 | I15: 占比 × 460 | J15: 本表计算（公式见单元格） | K15: 2026-10-22 | M15: — | N15: CALC
A16: MIX-12 | B16: 全球 2024 | C16: 输配损耗等（发电量 − 用电量） | D16: 全球 | E16: =$E$5-'D1_数据中心用电'!$E$5 -> 45 | F16: TWh | G16: 2024 | H16: 本表计算 | I16: 460 − 415 | J16: 本表计算（公式见单元格） | K16: 2026-10-22 | M16: — | N16: CALC
A17: MIX-20 | B17: 全球 2030 | C17: 可再生能源供数据中心发电量（基准情景） | D17: 全球 | E17: 360 | F17: TWh | G17: 2030 | H17: 官方预测 | I17: 原文：较当前增加 200 TWh 以上，2030 年达 360 TWh，超过总发电量三分之一 | J17: IEA《能源与人工智能关键问题》Key Questions on Energy and AI（2026 年更新版） | K17: 2026-04-16 | L17: https://iea.blob.core.windows.net/assets/3179f7f8-01f6-4dd6-bffa-c9f7b73f1dc9/KeyQuestionsonEnergyandAI.pdf｜PDF 第 49 页 §5.3 | M17: 2026-10-22 | N17: IEA26
A18: MIX-21 | B18: 全球 2030 | C18: 天然气供数据中心发电量（基准情景） | D18: 全球 | E18: 340 | F18: TWh | G18: 2030 | H18: 官方预测 | I18: 原文“约 340 TWh”，占比约 30% | J18: IEA《能源与人工智能关键问题》Key Questions on Energy and AI（2026 年更新版） | K18: 2026-04-16 | L18: https://iea.blob.core.windows.net/assets/3179f7f8-01f6-4dd6-bffa-c9f7b73f1dc9/KeyQuestionsonEnergyandAI.pdf｜PDF 第 50 页 §5.3 | M18: 2026-10-22 | N18: IEA26
A19: MIX-22 | B19: 全球 2030 | C19: 核电供数据中心发电量（基准情景） | D19: 全球 | E19: 120 | F19: TWh | G19: 2030 | H19: 官方预测 | I19: 原文“接近 120 TWh”，2025 年约 75 TWh | J19: IEA《能源与人工智能关键问题》Key Questions on Energy and AI（2026 年更新版） | K19: 2026-04-16 | L19: https://iea.blob.core.windows.net/assets/3179f7f8-01f6-4dd6-bffa-c9f7b73f1dc9/KeyQuestionsonEnergyandAI.pdf｜PDF 第 50 页 §5.3 | M19: 2026-10-22 | N19: IEA26
A20: MIX-23 | B20: 全球 2030 | C20: 煤电占数据中心供电比例（基准情景） | D20: 全球 | E20: 0.2 | F20: % | G20: 2030 | H20: 官方预测 | I20: 原文“约 20%”，主要在中国 | J20: IEA《能源与人工智能关键问题》Key Questions on Energy and AI（2026 年更新版） | K20: 2026-04-16 | L20: https://iea.blob.core.windows.net/assets/3179f7f8-01f6-4dd6-bffa-c9f7b73f1dc9/KeyQuestionsonEnergyandAI.pdf｜PDF 第 50 页 §5.3 | M20: 2026-10-22 | N20: IEA26
A21: MIX-24 | B21: 全球 2030 | C21: 为数据中心供电的总发电量（推算） | D21: 全球 | E21: =($E$17+$E$18+$E$19)/(1-$E$20-'假设'!$C$6) -> 1051.2821 | F21: TWh | G21: 2030 | H21: 本表计算 | I21: IEA 只说“超过 1000 TWh”；用 (可再生+气+核)÷(1−煤占比−其他占比) 推算，其他占比为假设 | J21: 本表计算（公式见单元格） | K21: 2026-10-22 | M21: — | N21: CALC
A22: MIX-25 | B22: 全球 2030 | C22: 煤电供数据中心发电量（推算） | D22: 全球 | E22: =$E$21*$E$20 -> 210.25641 | F22: TWh | G22: 2030 | H22: 本表计算 | I22: 总发电量 × 20% | J22: 本表计算（公式见单元格） | K22: 2026-10-22 | M22: — | N22: CALC
A23: MIX-26 | B23: 全球 2030 | C23: 其他供数据中心发电量（推算） | D23: 全球 | E23: =$E$21*'假设'!$C$6 -> 21.025641 | F23: TWh | G23: 2030 | H23: 本表计算 | I23: 总发电量 × 假设占比 | J23: 本表计算（公式见单元格） | K23: 2026-10-22 | M23: — | N23: CALC
A24: MIX-27 | B24: 全球 2030 | C24: 输配损耗等（发电量 − 用电量） | D24: 全球 | E24: =$E$21-'D1_数据中心用电'!$E$7 -> 106.28205 | F24: TWh | G24: 2030 | H24: 本表计算 | I24: 推算发电量 − 945 | J24: 本表计算（公式见单元格） | K24: 2026-10-22 | M24: — | N24: CALC
A25: MIX-28 | B25: 全球 2025 | C25: 核电供数据中心发电量 | D25: 全球 | E25: 75 | F25: TWh | G25: 2025 | H25: 官方估计 | I25: 原文“约 75 TWh” | J25: IEA《能源与人工智能关键问题》Key Questions on Energy and AI（2026 年更新版） | K25: 2026-04-16 | L25: https://iea.blob.core.windows.net/assets/3179f7f8-01f6-4dd6-bffa-c9f7b73f1dc9/KeyQuestionsonEnergyandAI.pdf｜PDF 第 50 页 §5.3 | M25: 2026-10-22 | N25: IEA26
A26: MIX-30 | B26: 美国 2024 | C26: 天然气占美国数据中心供电比例 | D26: 美国 | E26: ='假设'!$C$7 -> 0.41 | F26: % | G26: 2024 | H26: 假设 | I26: IEA 原文“超过 40%”，取假设值使四项合计约 100% | J26: 本研究假设（见“假设”工作表） | K26: 2026-10-22 | L26: “假设”页 | M26: — | N26: ASSUME
A27: MIX-31 | B27: 美国 2024 | C27: 可再生能源占比 | D27: 美国 | E27: 0.24 | F27: % | G27: 2024 | H27: 官方估计 | I27: 主要为光伏和风电 | J27: IEA《能源与人工智能》Energy and AI（世界能源展望特别报告） | K27: 2025-04（PDF 元数据 2025-04-11） | L27: https://iea.blob.core.windows.net/assets/b3a8b37f-32d1-4873-9eca-31cec5895264/EnergyandAI.pdf｜PDF 第 87 页 | M27: 2026-10-22 | N27: IEA25
A28: MIX-32 | B28: 美国 2024 | C28: 煤电占比 | D28: 美国 | E28: 0.2 | F28: % | G28: 2024 | H28: 官方估计 | I28: 原文“约 20%” | J28: IEA《能源与人工智能》Energy and AI（世界能源展望特别报告） | K28: 2025-04（PDF 元数据 2025-04-11） | L28: https://iea.blob.core.windows.net/assets/b3a8b37f-32d1-4873-9eca-31cec5895264/EnergyandAI.pdf｜PDF 第 87 页 | M28: 2026-10-22 | N28: IEA25
A29: MIX-33 | B29: 美国 2024 | C29: 核电占比 | D29: 美国 | E29: 0.15 | F29: % | G29: 2024 | H29: 官方估计 | I29: 原文“接近 15%” | J29: IEA《能源与人工智能》Energy and AI（世界能源展望特别报告） | K29: 2025-04（PDF 元数据 2025-04-11） | L29: https://iea.blob.core.windows.net/assets/b3a8b37f-32d1-4873-9eca-31cec5895264/EnergyandAI.pdf｜PDF 第 87 页 | M29: 2026-10-22 | N29: IEA25
A30: MIX-34 | B30: 美国 2024 | C30: 发电量/用电量系数（借用全球 2024） | D30: 美国 | E30: =$E$5/'D1_数据中心用电'!$E$5 -> 1.1084337 | F30: 倍 | G30: 2024 | H30: 本表计算 | I30: 美国未单独披露，借用全球 460÷415 | J30: 本表计算（公式见单元格） | K30: 2026-10-22 | M30: — | N30: CALC
A31: MIX-35 | B31: 美国 2024 | C31: 为美国数据中心供电的发电量（推算） | D31: 美国 | E31: ='D1_数据中心用电'!$E$27*$E$30 -> 202.84337 | F31: TWh | G31: 2024 | H31: 本表计算 | I31: 183 × 系数 | J31: 本表计算（公式见单元格） | K31: 2026-10-22 | M31: — | N31: CALC
A32: MIX-40 | B32: 中国 2024 | C32: 煤电占中国数据中心供电比例 | D32: 中国 | E32: 0.7 | F32: % | G32: 2024 | H32: 官方估计 | I32: 原文“约 70%”，数据中心多在东部 | J32: IEA《能源与人工智能》Energy and AI（世界能源展望特别报告） | K32: 2025-04（PDF 元数据 2025-04-11） | L32: https://iea.blob.core.windows.net/assets/b3a8b37f-32d1-4873-9eca-31cec5895264/EnergyandAI.pdf｜PDF 第 88 页 | M32: 2026-10-22 | N32: IEA25
A33: MIX-41 | B33: 中国 2024 | C33: 可再生能源占比 | D33: 中国 | E33: 0.2 | F33: % | G33: 2024 | H33: 官方估计 | I33: 原文“接近 20%” | J33: IEA《能源与人工智能》Energy and AI（世界能源展望特别报告） | K33: 2025-04（PDF 元数据 2025-04-11） | L33: https://iea.blob.core.windows.net/assets/b3a8b37f-32d1-4873-9eca-31cec5895264/EnergyandAI.pdf｜PDF 第 88 页 | M33: 2026-10-22 | N33: IEA25
A34: MIX-42 | B34: 中国 2024 | C34: 核电占比 | D34: 中国 | E34: 0.1 | F34: % | G34: 2024 | H34: 官方估计 | I34: 原文“接近 10%”，其余为天然气 | J34: IEA《能源与人工智能》Energy and AI（世界能源展望特别报告） | K34: 2025-04（PDF 元数据 2025-04-11） | L34: https://iea.blob.core.windows.net/assets/b3a8b37f-32d1-4873-9eca-31cec5895264/EnergyandAI.pdf｜PDF 第 88 页 | M34: 2026-10-22 | N34: IEA25
A35: MIX-50 | B35: 结论 | C35: 2024–2030 年可再生能源满足的数据中心新增需求比例 | D35: 全球 | E35: 0.5 | F35: % | G35: 2024–2030 | H35: 官方预测 | I35: 原文“接近一半” | J35: IEA《能源与人工智能》Energy and AI（世界能源展望特别报告） | K35: 2025-04（PDF 元数据 2025-04-11） | L35: https://iea.blob.core.windows.net/assets/b3a8b37f-32d1-4873-9eca-31cec5895264/EnergyandAI.pdf｜PDF 第 86 页图 2.20 说明 | M35: 2026-10-22 | N35: IEA25
A36: MIX-51 | B36: 结论 | C36: 2024–2030 年天然气与煤电合计满足的新增需求比例 | D36: 全球 | E36: 0.4 | F36: % | G36: 2024–2030 | H36: 官方预测 | I36: 原文“超过 40%” | J36: IEA《能源与人工智能》Energy and AI（世界能源展望特别报告） | K36: 2025-04（PDF 元数据 2025-04-11） | L36: https://iea.blob.core.windows.net/assets/b3a8b37f-32d1-4873-9eca-31cec5895264/EnergyandAI.pdf｜PDF 第 86 页 | M36: 2026-10-22 | N36: IEA25
A37: MIX-52 | B37: 结论 | C37: 2024–2035 年为数据中心新增的天然气发电量 | D37: 全球（主要在美国） | E37: 175 | F37: TWh | G37: 2024–2035 | H37: 官方预测 | I37: 起飞情景 +290 TWh | J37: IEA《能源与人工智能》Energy and AI（世界能源展望特别报告） | K37: 2025-04（PDF 元数据 2025-04-11） | L37: https://iea.blob.core.windows.net/assets/b3a8b37f-32d1-4873-9eca-31cec5895264/EnergyandAI.pdf｜PDF 第 49 页（执行摘要） | M37: 2026-10-22 | N37: IEA25
A38: MIX-53 | B38: 结论 | C38: 2024–2030 年美国为数据中心新增的天然气发电量 | D38: 美国 | E38: 130 | F38: TWh | G38: 2024–2030 | H38: 官方预测 | I38: 原文“超过 130 TWh”；可再生能源 +110 TWh | J38: IEA《能源与人工智能》Energy and AI（世界能源展望特别报告） | K38: 2025-04（PDF 元数据 2025-04-11） | L38: https://iea.blob.core.windows.net/assets/b3a8b37f-32d1-4873-9eca-31cec5895264/EnergyandAI.pdf｜PDF 第 87 页 | M38: 2026-10-22 | N38: IEA25
A39: GRID-01 | B39: 美国电网 2025 | C39: 美国公用事业级总发电量 | D39: 美国 | E39: 4429.5 | F39: TWh | G39: 2025 | H39: 披露事实 | I39: 公用事业级，不含小型分布式光伏 | J39: EIA《电力月报》表 1.1 分能源净发电量 | K39: 2026-09-24 | L39: https://www.eia.gov/electricity/monthly/epm_table_grapher.php?t=epmt_1_01｜表 1.1 | M39: 2026-10-22 | N39: EIA_EPM11
A40: GRID-02 | B40: 美国电网 2025 | C40: 天然气发电量 | D40: 美国 | E40: 1807.3 | F40: TWh | G40: 2025 | H40: 披露事实 | J40: EIA《电力月报》表 1.1 分能源净发电量 | K40: 2026-09-24 | L40: https://www.eia.gov/electricity/monthly/epm_table_grapher.php?t=epmt_1_01｜表 1.1 | M40: 2026-10-22 | N40: EIA_EPM11
A41: GRID-03 | B41: 美国电网 2025 | C41: 核电发电量 | D41: 美国 | E41: 784.8 | F41: TWh | G41: 2025 | H41: 披露事实 | J41: EIA《电力月报》表 1.1 分能源净发电量 | K41: 2026-09-24 | L41: https://www.eia.gov/electricity/monthly/epm_table_grapher.php?t=epmt_1_01｜表 1.1 | M41: 2026-10-22 | N41: EIA_EPM11
A42: GRID-04 | B42: 美国电网 2025 | C42: 煤电发电量 | D42: 美国 | E42: 737.2 | F42: TWh | G42: 2025 | H42: 披露事实 | I42: 较 2024 年 +13% | J42: EIA《电力月报》表 1.1 分能源净发电量 | K42: 2026-09-24 | L42: https://www.eia.gov/electricity/monthly/epm_table_grapher.php?t=epmt_1_01｜表 1.1 | M42: 2026-10-22 | N42: EIA_EPM11
A43: GRID-05 | B43: 美国电网 2025 | C43: 风电发电量 | D43: 美国 | E43: 464.4 | F43: TWh | G43: 2025 | H43: 披露事实 | J43: EIA《电力月报》表 1.1 分能源净发电量 | K43: 2026-09-24 | L43: https://www.eia.gov/electricity/monthly/epm_table_grapher.php?t=epmt_1_01｜表 1.1.A | M43: 2026-10-22 | N43: EIA_EPM11
A44: GRID-06 | B44: 美国电网 2025 | C44: 公用事业级光伏发电量 | D44: 美国 | E44: 295.7 | F44: TWh | G44: 2025 | H44: 披露事实 | I44: 含光热 | J44: EIA《电力月报》表 1.1 分能源净发电量 | K44: 2026-09-24 | L44: https://www.eia.gov/electricity/monthly/epm_table_grapher.php?t=epmt_1_01｜表 1.1 | M44: 2026-10-22 | N44: EIA_EPM11
A45: GRID-07 | B45: 美国电网 2025 | C45: 常规水电发电量 | D45: 美国 | E45: 247 | F45: TWh | G45: 2025 | H45: 披露事实 | J45: EIA《电力月报》表 1.1 分能源净发电量 | K45: 2026-09-24 | L45: https://www.eia.gov/electricity/monthly/epm_table_grapher.php?t=epmt_1_01｜表 1.1 | M45: 2026-10-22 | N45: EIA_EPM11
A46: GRID-08 | B46: 美国电网 2025 | C46: 其他（生物质、地热、燃油等） | D46: 美国 | E46: =$E$39-$E$40-$E$41-$E$42-$E$43-$E$44-$E$45 -> 93.1 | F46: TWh | G46: 2025 | H46: 本表计算 | I46: 总量减去上述各项 | J46: 本表计算（公式见单元格） | K46: 2026-10-22 | M46: — | N46: CALC
A47: GRID-10 | B47: 美国电网 2025 | C47: 美国在运核电装机（净夏季） | D47: 美国 | E47: 98441 | F47: MW | G47: 2026-03 | H47: 披露事实 | I47: 94 台机组；含报告为“运行但停机”的 Palisades 与 Crane | J47: EIA《核能释义：美国核电产业》 | K47: 2026（页面未标更新日） | L47: https://www.eia.gov/energyexplained/nuclear/us-nuclear-industry.php｜页面正文 | M47: 2026-10-22 | N47: EIA_NUC
A48: GRID-11 | B48: 美国电网 2025 | C48: 美国核电平均容量系数 | D48: 美国 | E48: 0.91 | F48: % | G48: 2025 | H48: 披露事实 | I48: 2024 年 90.8% | J48: EIA《核能释义：美国核电产业》 | K48: 2026（页面未标更新日） | L48: https://www.eia.gov/energyexplained/nuclear/us-nuclear-industry.php｜页面正文 | M48: 2026-10-22 | N48: EIA_NUC
A49: GRID-12 | B49: 美国电网 2026 | C49: 2026 年计划新增装机 | D49: 美国 | E49: 86 | F49: GW | G49: 2026E | H49: 官方预测 | I49: 光伏 43.4、电池 24、风电 11.8、燃气 6.3 GW（开发商计划） | J49: EIA《今日能源》：2026 年美国新增发电装机预计创纪录 | K49: 2026-02-20 | L49: https://www.eia.gov/todayinenergy/detail.php?id=67205｜正文 | M49: 2026-10-22 | N49: EIA_TIE
A50: GRID-13 | B50: 美国电网 2026 | C50: 其中燃气 | D50: 美国 | E50: 6.3 | F50: GW | G50: 2026E | H50: 官方预测 | J50: EIA《今日能源》：2026 年美国新增发电装机预计创纪录 | K50: 2026-02-20 | L50: https://www.eia.gov/todayinenergy/detail.php?id=67205｜正文 | M50: 2026-10-22 | N50: EIA_TIE
A51: GRID-14 | B51: 美国电网 2026 | C51: 其中光伏 | D51: 美国 | E51: 43.4 | F51: GW | G51: 2026E | H51: 官方预测 | J51: EIA《今日能源》：2026 年美国新增发电装机预计创纪录 | K51: 2026-02-20 | L51: https://www.eia.gov/todayinenergy/detail.php?id=67205｜正文 | M51: 2026-10-22 | N51: EIA_TIE

Sheet D3_科技公司资本开支
A1: D3 美国科技巨头资本开支、指引与电力相关披露（各公司财报、电话会及官网）
A2: 蓝底=输入（披露数据）；橙底=输入（假设）；绿底=公式（本表计算）。“出处定位”给出原始材料的文件与章节，或网页链接；“访问日期”为网页查阅日期。
A4: 编号 | B4: 类别 | C4: 指标 | D4: 主体/地区 | E4: 数值 | F4: 单位 | G4: 期间 | H4: 性质 | I4: 口径说明 | J4: 来源名称 | K4: 发布日期 | L4: 出处定位（文件章节/表名或网页链接） | M4: 访问日期 | N4: 来源编号
A5: CQ-MS-24Q1 | B5: 季度资本开支 | C5: 微软资本开支 | D5: 微软 | E5: 14 | F5: 十亿美元 | G5: 2024Q1（FY24 Q3） | H5: 披露事实 | I5: 微软口径：含融资租赁的资本开支（电话会口径） | J5: 微软 FY24 Q3 业绩电话会（投资者关系页） | K5: 2024-04-25 | L5: https://www.microsoft.com/en-us/investor/events/fy-2024/earnings-fy-2024-q3｜CFO 发言 | M5: 2026-10-22 | N5: MSFT24Q3
A6: CQ-MS-24Q2 | B6: 季度资本开支 | C6: 微软资本开支 | D6: 微软 | E6: 19 | F6: 十亿美元 | G6: 2024Q2（FY24 Q4） | H6: 披露事实 | I6: 微软口径：含融资租赁的资本开支（电话会口径） | J6: 微软 FY24 Q4 业绩电话会 | K6: 2024-07-30 | L6: https://www.microsoft.com/en-us/investor/events/fy-2024/earnings-fy-2024-q4｜CFO 发言 | M6: 2026-10-22 | N6: MSFT24Q4
A7: CQ-MS-24Q3 | B7: 季度资本开支 | C7: 微软资本开支 | D7: 微软 | E7: 20 | F7: 十亿美元 | G7: 2024Q3（FY25 Q1） | H7: 披露事实 | I7: 微软口径：含融资租赁的资本开支（电话会口径） | J7: 微软 FY25 Q1 业绩电话会 | K7: 2024-10-30 | L7: https://www.microsoft.com/en-us/investor/events/fy-2025/earnings-fy-2025-q1｜CFO 发言 | M7: 2026-10-22 | N7: MSFT25Q1
A8: CQ-MS-24Q4 | B8: 季度资本开支 | C8: 微软资本开支 | D8: 微软 | E8: 22.6 | F8: 十亿美元 | G8: 2024Q4（FY25 Q2） | H8: 披露事实 | I8: 微软口径：含融资租赁的资本开支（电话会口径） | J8: 微软 FY25 Q2 业绩电话会 | K8: 2025-01-29 | L8: https://www.microsoft.com/en-us/investor/events/fy-2025/earnings-fy-2025-q2｜CFO 发言 | M8: 2026-10-22 | N8: MSFT25Q2
A9: CQ-MS-25Q1 | B9: 季度资本开支 | C9: 微软资本开支 | D9: 微软 | E9: 21.4 | F9: 十亿美元 | G9: 2025Q1（FY25 Q3） | H9: 披露事实 | I9: 微软口径：含融资租赁的资本开支（电话会口径） | J9: 微软 FY25 Q3 业绩电话会 | K9: 2025-04-30 | L9: https://www.microsoft.com/en-us/investor/events/fy-2025/earnings-fy-2025-q3｜CFO 发言 | M9: 2026-10-22 | N9: MSFT25Q3
A10: CQ-MS-25Q2 | B10: 季度资本开支 | C10: 微软资本开支 | D10: 微软 | E10: 24.2 | F10: 十亿美元 | G10: 2025Q2（FY25 Q4） | H10: 披露事实 | I10: 微软口径：含融资租赁的资本开支（电话会口径）；含融资租赁 65 亿 | J10: 微软 FY25 Q4 业绩电话会 | K10: 2025-07-30 | L10: https://www.microsoft.com/en-us/investor/events/fy-2025/earnings-fy-2025-q4｜CFO 发言 | M10: 2026-10-22 | N10: MSFT25Q4
A11: CQ-MS-25Q3 | B11: 季度资本开支 | C11: 微软资本开支 | D11: 微软 | E11: 34.9 | F11: 十亿美元 | G11: 2025Q3（FY26 Q1） | H11: 披露事实 | I11: 微软口径：含融资租赁的资本开支（电话会口径）；含融资租赁 111 亿 | J11: 微软 FY26 Q1 业绩电话会 | K11: 2025-10-29 | L11: https://www.microsoft.com/en-us/investor/events/fy-2026/earnings-fy-2026-q1｜CFO 发言 | M11: 2026-10-22 | N11: MSFT26Q1
A12: CQ-MS-25Q4 | B12: 季度资本开支 | C12: 微软资本开支 | D12: 微软 | E12: 37.5 | F12: 十亿美元 | G12: 2025Q4（FY26 Q2） | H12: 披露事实 | I12: 微软口径：含融资租赁的资本开支（电话会口径）；含融资租赁 67 亿 | J12: 微软 FY26 Q2 业绩电话会 | K12: 2026-01-28 | L12: https://www.microsoft.com/en-us/investor/events/fy-2026/earnings-fy-2026-q2｜CFO 发言 | M12: 2026-10-22 | N12: MSFT26Q2
A13: CQ-MS-26Q1 | B13: 季度资本开支 | C13: 微软资本开支 | D13: 微软 | E13: 31.9 | F13: 十亿美元 | G13: 2026Q1（FY26 Q3） | H13: 披露事实 | I13: 微软口径：含融资租赁的资本开支（电话会口径）；含融资租赁 47 亿 | J13: 微软 FY26 Q3 业绩电话会 | K13: 2026-04-29 | L13: https://www.microsoft.com/en-us/investor/events/fy-2026/earnings-fy-2026-q3｜CFO 发言 | M13: 2026-10-22 | N13: MSFT26Q3
A14: CQ-MS-26Q2 | B14: 季度资本开支 | C14: 微软资本开支 | D14: 微软 | E14: 41 | F14: 十亿美元 | G14: 2026Q2（FY26 Q4） | H14: 披露事实 | I14: 微软口径：含融资租赁的资本开支（电话会口径）；含融资租赁 56 亿；含元器件涨价影响 | J14: 微软 FY26 Q4 业绩电话会 | K14: 2026-07-29 | L14: https://www.microsoft.com/en-us/investor/events/fy-2026/earnings-fy-2026-q4｜CFO 发言 | M14: 2026-10-22 | N14: MSFT26Q4
A15: CY-GO-2024 | B15: 年度资本开支 | C15: Alphabet 资本开支 | D15: Alphabet | E15: 52.535 | F15: 十亿美元 | G15: 2024 | H15: 披露事实 | I15: Alphabet 口径：购置物业与设备（现金流量表） | J15: Alphabet 2025 年四季度及全年业绩（8-K 附件 99.1） | K15: 2026-02-04 | L15: https://www.sec.gov/Archives/edgar/data/1652044/000165204426000012/googexhibit991q42025.htm｜现金流量表 2024 列 | M15: 2026-10-22 | N15: GOOG25Q4
A16: CY-GO-2025 | B16: 年度资本开支 | C16: Alphabet 资本开支 | D16: Alphabet | E16: 91.447 | F16: 十亿美元 | G16: 2025 | H16: 披露事实 | I16: Alphabet 口径：购置物业与设备（现金流量表） | J16: Alphabet 2025 年四季度及全年业绩（8-K 附件 99.1） | K16: 2026-02-04 | L16: https://www.sec.gov/Archives/edgar/data/1652044/000165204426000012/googexhibit991q42025.htm｜现金流量表 2025 列 | M16: 2026-10-22 | N16: GOOG25Q4
... A19: CQ-GO-25Q4 | B19: 季度资本开支 | C19: Alphabet 资本开支 | D19: Alphabet | E19: 27.851 | F19: 十亿美元 | G19: 2025Q4 | H19: 披露事实 | I19: Alphabet 口径：购置物业与设备（现金流量表） | J19: Alphabet 2025 年四季度及全年业绩（8-K 附件 99.1） | K19: 2026-02-04 | L19: https://www.sec.gov/Archives/edgar/data/1652044/000165204426000012/googexhibit991q42025.htm｜现金流量表 | M19: 2026-10-22 | N19: GOOG25Q4
A20: CQ-GO-25Q3 | B20: 季度资本开支 | C20: Alphabet 资本开支（推算） | D20: Alphabet | E20: =$E$16-$E$17-$E$18-$E$19 -> 23.953 | F20: 十亿美元 | G20: 2025Q3 | H20: 本表计算 | I20: 全年 − 其余三个季度 | J20: 本表计算（公式见单元格） | K20: 2026-10-22 | M20: — | N20: CALC
A21: CQ-GO-26Q1 | B21: 季度资本开支 | C21: Alphabet 资本开支 | D21: Alphabet | E21: 35.674 | F21: 十亿美元 | G21: 2026Q1 | H21: 披露事实 | I21: Alphabet 口径：购置物业与设备（现金流量表） | J21: Alphabet 2026 年一季度业绩（8-K 附件 99.1） | K21: 2026-04-29 | L21: https://www.sec.gov/Archives/edgar/data/0001652044/000165204426000043/googexhibit991q12026.htm｜现金流量表 | M21: 2026-10-22 | N21: GOOG26Q1
A22: CQ-GO-26Q2 | B22: 季度资本开支 | C22: Alphabet 资本开支 | D22: Alphabet | E22: 44.924 | F22: 十亿美元 | G22: 2026Q2 | H22: 披露事实 | I22: Alphabet 口径：购置物业与设备（现金流量表） | J22: Alphabet 2026 年二季度业绩（8-K 附件 99.1）及业绩电话会 | K22: 2026-07-22 | L22: https://www.sec.gov/Archives/edgar/data/0001652044/000165204426000066/googexhibit991q22026.htm｜现金流量表 | M22: 2026-10-22 | N22: GOOG26Q2
A23: CY-AM-2024 | B23: 年度资本开支 | C23: 亚马逊资本开支 | D23: 亚马逊 | E23: 82.999 | F23: 十亿美元 | G23: 2024 | H23: 披露事实 | I23: 亚马逊口径：购置物业与设备总额（未扣除处置收入与激励） | J23: 亚马逊 2025 年四季度业绩（8-K 附件 99.1） | K23: 2026-02-05 | L23: https://www.sec.gov/Archives/edgar/data/1018724/000101872426000002/amzn-20251231xex991.htm｜十二个月现金流 2024 列 | M23: 2026-10-22 | N23: AMZN25Q4
A24: CY-AM-2025 | B24: 年度资本开支 | C24: 亚马逊资本开支 | D24: 亚马逊 | E24: 131.819 | F24: 十亿美元 | G24: 2025 | H24: 披露事实 | I24: 亚马逊口径：购置物业与设备总额（未扣除处置收入与激励） | J24: 亚马逊 2025 年四季度业绩（8-K 附件 99.1） | K24: 2026-02-05 | L24: https://www.sec.gov/Archives/edgar/data/1018724/000101872426000002/amzn-20251231xex991.htm｜十二个月现金流 2025 列 | M24: 2026-10-22 | N24: AMZN25Q4
A25: CQ-AM-25Q1 | B25: 季度资本开支 | C25: 亚马逊资本开支 | D25: 亚马逊 | E25: 25.019 | F25: 十亿美元 | G25: 2025Q1 | H25: 披露事实 | I25: 亚马逊口径：购置物业与设备总额（未扣除处置收入与激励） | J25: 亚马逊 2026 年一季度业绩（8-K 附件 99.1） | K25: 2026-04-29 | L25: https://www.sec.gov/Archives/edgar/data/0001018724/000101872426000012/amzn-20260331xex991.htm｜上年同期列 | M25: 2026-10-22 | N25: AMZN26Q1
A26: CQ-AM-25Q2 | B26: 季度资本开支 | C26: 亚马逊资本开支 | D26: 亚马逊 | E26: 32.183 | F26: 十亿美元 | G26: 2025Q2 | H26: 披露事实 | I26: 亚马逊口径：购置物业与设备总额（未扣除处置收入与激励） | J26: 亚马逊 2026 年二季度业绩（8-K 附件 99.1） | K26: 2026-07-30 | L26: https://www.sec.gov/Archives/edgar/data/0001018724/000101872426000024/amzn-20260630xex991.htm｜上年同期列 | M26: 2026-10-22 | N26: AMZN26Q2
A27: CQ-AM-25Q4 | B27: 季度资本开支 | C27: 亚马逊资本开支 | D27: 亚马逊 | E27: 39.522 | F27: 十亿美元 | G27: 2025Q4 | H27: 披露事实 | I27: 亚马逊口径：购置物业与设备总额（未扣除处置收入与激励） | J27: 亚马逊 2025 年四季度业绩（8-K 附件 99.1） | K27: 2026-02-05 | L27: https://www.sec.gov/Archives/edgar/data/1018724/000101872426000002/amzn-20251231xex991.htm｜现金流量表 | M27: 2026-10-22 | N27: AMZN25Q4
A28: CQ-AM-25Q3 | B28: 季度资本开支 | C28: 亚马逊资本开支（推算） | D28: 亚马逊 | E28: =$E$24-$E$25-$E$26-$E$27 -> 35.095 | F28: 十亿美元 | G28: 2025Q3 | H28: 本表计算 | I28: 全年 − 其余三个季度 | J28: 本表计算（公式见单元格） | K28: 2026-10-22 | M28: — | N28: CALC
A29: CQ-AM-26Q1 | B29: 季度资本开支 | C29: 亚马逊资本开支 | D29: 亚马逊 | E29: 44.203 | F29: 十亿美元 | G29: 2026Q1 | H29: 披露事实 | I29: 亚马逊口径：购置物业与设备总额（未扣除处置收入与激励） | J29: 亚马逊 2026 年一季度业绩（8-K 附件 99.1） | K29: 2026-04-29 | L29: https://www.sec.gov/Archives/edgar/data/0001018724/000101872426000012/amzn-20260331xex991.htm｜现金流量表 | M29: 2026-10-22 | N29: AMZN26Q1
A30: CQ-AM-26Q2 | B30: 季度资本开支 | C30: 亚马逊资本开支 | D30: 亚马逊 | E30: 54.208 | F30: 十亿美元 | G30: 2026Q2 | H30: 披露事实 | I30: 亚马逊口径：购置物业与设备总额（未扣除处置收入与激励） | J30: 亚马逊 2026 年二季度业绩（8-K 附件 99.1） | K30: 2026-07-30 | L30: https://www.sec.gov/Archives/edgar/data/0001018724/000101872426000024/amzn-20260630xex991.htm｜现金流量表 | M30: 2026-10-22 | N30: AMZN26Q2
A31: CY-ME-2024 | B31: 年度资本开支 | C31: Meta 资本开支 | D31: Meta | E31: 39.225 | F31: 十亿美元 | G31: 2024 | H31: 披露事实 | I31: Meta 口径：购置物业与设备 + 融资租赁本金（372.56 + 19.69） | J31: Meta 2025 年四季度及全年业绩新闻稿 | K31: 2026-01-28 | L31: https://investor.atmeta.com/investor-news/press-release-details/2026/Meta-Reports-Fourth-Quarter-and-Full-Year-2025-Results/default.aspx｜现金流量表 | M31: 2026-10-22 | N31: META25Q4
A32: CY-ME-2025 | B32: 年度资本开支 | C32: Meta 资本开支 | D32: Meta | E32: 72.215 | F32: 十亿美元 | G32: 2025 | H32: 披露事实 | I32: Meta 口径：购置物业与设备 + 融资租赁本金（696.91 + 25.24） | J32: Meta 2025 年四季度及全年业绩新闻稿 | K32: 2026-01-28 | L32: https://investor.atmeta.com/investor-news/press-release-details/2026/Meta-Reports-Fourth-Quarter-and-Full-Year-2025-Results/default.aspx｜新闻稿“722.2 亿美元” | M32: 2026-10-22 | N32: META25Q4
A33: CQ-ME-25Q1 | B33: 季度资本开支 | C33: Meta 资本开支 | D33: Meta | E33: 13.692 | F33: 十亿美元 | G33: 2025Q1 | H33: 披露事实 | I33: Meta 口径：购置物业与设备 + 融资租赁本金；两项取自季度报表同期列后相加 | J33: Meta 2026 年一季度业绩新闻稿 | K33: 2026-04-29 | L33: https://investor.atmeta.com/investor-news/press-release-details/2026/Meta-Reports-First-Quarter-2026-Results/default.aspx｜上年同期列 | M33: 2026-10-22 | N33: META26Q1
A34: CQ-ME-25Q2 | B34: 季度资本开支 | C34: Meta 资本开支 | D34: Meta | E34: 17.012 | F34: 十亿美元 | G34: 2025Q2 | H34: 披露事实 | I34: Meta 口径：购置物业与设备 + 融资租赁本金；同上 | J34: Meta 2026 年二季度业绩新闻稿 | K34: 2026-07-29 | L34: https://investor.atmeta.com/investor-news/press-release-details/2026/Meta-Reports-Second-Quarter-2026-Results/default.aspx｜上年同期列 | M34: 2026-10-22 | N34: META26Q2
A35: CQ-ME-25Q3 | B35: 季度资本开支 | C35: Meta 资本开支 | D35: Meta | E35: 19.374 | F35: 十亿美元 | G35: 2025Q3 | H35: 披露事实 | I35: Meta 口径：购置物业与设备 + 融资租赁本金；同上 | J35: Meta 2026 年三季度业绩新闻稿 | K35: 2026-10-21 | L35: https://investor.atmeta.com/investor-news/press-release-details/2026/Meta-Reports-Third-Quarter-2026-Results/default.aspx｜上年同期列 | M35: 2026-10-22 | N35: META26Q3
A36: CQ-ME-25Q4 | B36: 季度资本开支 | C36: Meta 资本开支 | D36: Meta | E36: 22.137 | F36: 十亿美元 | G36: 2025Q4 | H36: 披露事实 | I36: Meta 口径：购置物业与设备 + 融资租赁本金 | J36: Meta 2025 年四季度及全年业绩新闻稿 | K36: 2026-01-28 | L36: https://investor.atmeta.com/investor-news/press-release-details/2026/Meta-Reports-Fourth-Quarter-and-Full-Year-2025-Results/default.aspx｜新闻稿“221.4 亿美元” | M36: 2026-10-22 | N36: META25Q4
A37: CQ-ME-26Q1 | B37: 季度资本开支 | C37: Meta 资本开支 | D37: Meta | E37: 19.84 | F37: 十亿美元 | G37: 2026Q1 | H37: 披露事实 | I37: Meta 口径：购置物业与设备 + 融资租赁本金 | J37: Meta 2026 年一季度业绩新闻稿 | K37: 2026-04-29 | L37: https://investor.atmeta.com/investor-news/press-release-details/2026/Meta-Reports-First-Quarter-2026-Results/default.aspx｜新闻稿“198.4 亿美元” | M37: 2026-10-22 | N37: META26Q1
A38: CQ-ME-26Q2 | B38: 季度资本开支 | C38: Meta 资本开支 | D38: Meta | E38: 31.08 | F38: 十亿美元 | G38: 2026Q2 | H38: 披露事实 | I38: Meta 口径：购置物业与设备 + 融资租赁本金 | J38: Meta 2026 年二季度业绩新闻稿 | K38: 2026-07-29 | L38: https://investor.atmeta.com/investor-news/press-release-details/2026/Meta-Reports-Second-Quarter-2026-Results/default.aspx｜新闻稿“310.8 亿美元” | M38: 2026-10-22 | N38: META26Q2
A39: CQ-ME-26Q3 | B39: 季度资本开支 | C39: Meta 资本开支 | D39: Meta | E39: ='D4_Meta三季报'!$E$5 -> 34.91 | F39: 十亿美元 | G39: 2026Q3 | H39: 披露事实 | I39: Meta 口径：购置物业与设备 + 融资租赁本金；引用 D4 原始材料 10-Q | J39: Meta Platforms, Inc. 10-Q 季报（截至 2026-09-30 的季度） | K39: 2026-10-21（签署日） | L39: 材料/Meta_2026Q3季报__meta-20260930.htm｜见 D4 META-01 | M39: 原始材料 | N39: M1
A40: CQ-ME-CHK | B40: 季度资本开支 | C40: 核对：Meta 2026 年前三季度（季度相加 − 10-Q 累计） | D40: Meta | E40: =$E$37+$E$38+$E$39-'D4_Meta三季报'!$E$6 -> 0.01 | F40: 十亿美元 | G40: 2026 年前三季度 | H40: 本表计算 | I40: 差值应接近 0（四舍五入误差） | J40: 本表计算（公式见单元格） | K40: 2026-10-22 | M40: — | N40: CALC
A41: G-MS-2026 | B41: 指引 | C41: 微软 2026 自然年资本开支预期（租赁重分类后） | D41: 微软 | E41: 175 | F41: 十亿美元 | G41: 2026E | H41: 公司指引 | I41: 2026-07-29 称“约 1750 亿美元”；4 月给出的约 1900 亿口径因部分融资租赁改为经营租赁而下调，公司称投资计划未变 | J41: 微软 FY26 Q4 业绩电话会 | K41: 2026-07-29 | L41: https://www.microsoft.com/en-us/investor/events/fy-2026/earnings-fy-2026-q4｜CFO 发言 | M41: 2026-10-22 | N41: MSFT26Q4
A42: G-MS-2026B | B42: 指引 | C42: 微软 2026 自然年资本开支预期（重分类前口径） | D42: 微软 | E42: 190 | F42: 十亿美元 | G42: 2026E | H42: 公司指引 | I42: 含约 250 亿美元元器件涨价影响 | J42: 微软 FY26 Q3 业绩电话会 | K42: 2026-04-29 | L42: https://www.microsoft.com/en-us/investor/events/fy-2026/earnings-fy-2026-q3｜CFO 发言 | M42: 2026-10-22 | N42: MSFT26Q3
A43: G-GO-2026L | B43: 指引 | C43: Alphabet 2026 年资本开支指引下限 | D43: Alphabet | E43: 195 | F43: 十亿美元 | G43: 2026E | H43: 公司指引 | I43: 2 月 175–185 → 4 月 180–190 → 7 月 195–205 | J43: Alphabet 2026 年二季度业绩（8-K 附件 99.1）及业绩电话会 | K43: 2026-07-22 | L43: https://www.sec.gov/Archives/edgar/data/0001652044/000165204426000066/googexhibit991q22026.htm｜业绩电话会 | M43: 2026-10-22 | N43: GOOG26Q2
A44: G-GO-2026H | B44: 指引 | C44: Alphabet 2026 年资本开支指引上限 | D44: Alphabet | E44: 205 | F44: 十亿美元 | G44: 2026E | H44: 公司指引 | I44: 同上 | J44: Alphabet 2026 年二季度业绩（8-K 附件 99.1）及业绩电话会 | K44: 2026-07-22 | L44: https://www.sec.gov/Archives/edgar/data/0001652044/000165204426000066/googexhibit991q22026.htm｜业绩电话会 | M44: 2026-10-22 | N44: GOOG26Q2
A45: G-AM-2026 | B45: 指引 | C45: 亚马逊 2026 年资本开支预期 | D45: 亚马逊 | E45: 220 | F45: 十亿美元 | G45: 2026E | H45: 公司指引 | I45: 2 月新闻稿“约 2000 亿美元”；7 月电话会上调至约 2200 亿（内存涨价），来自电话会文字记录（二手） | J45: 亚马逊 2026 年二季度业绩电话会文字记录（Motley Fool，经 Webull 转载） | K45: 2026-07-30 | L45: https://www.webull.com/news/15364638750483456｜电话会文字记录 | M45: 2026-10-22 | N45: AMZN26Q2C
A46: G-ME-2026L | B46: 指引 | C46: Meta 2026 年资本开支指引下限 | D46: Meta | E46: ='D4_Meta三季报'!$E$13 -> 135 | F46: 十亿美元 | G46: 2026E | H46: 公司指引 | I46: 引用原始材料 10-Q | J46: Meta Platforms, Inc. 10-Q 季报（截至 2026-09-30 的季度） | K46: 2026-10-21（签署日） | L46: 材料/Meta_2026Q3季报__meta-20260930.htm｜见 D4 META-09 | M46: 原始材料 | N46: M1
A47: G-ME-2026H | B47: 指引 | C47: Meta 2026 年资本开支指引上限 | D47: Meta | E47: ='D4_Meta三季报'!$E$14 -> 145 | F47: 十亿美元 | G47: 2026E | H47: 公司指引 | I47: 引用原始材料 10-Q | J47: Meta Platforms, Inc. 10-Q 季报（截至 2026-09-30 的季度） | K47: 2026-10-21（签署日） | L47: 材料/Meta_2026Q3季报__meta-20260930.htm｜见 D4 META-10 | M47: 原始材料 | N47: M1
A48: G-ME-2026J | B48: 指引 | C48: Meta 2026 年 1 月给出的初始指引中值 | D48: Meta | E48: 125 | F48: 十亿美元 | G48: 2026E | H48: 公司指引 | I48: 初始区间 1150–1350 亿美元 | J48: Meta 2025 年四季度及全年业绩新闻稿 | K48: 2026-01-28 | L48: https://investor.atmeta.com/investor-news/press-release-details/2026/Meta-Reports-Fourth-Quarter-and-Full-Year-2025-Results/default.aspx｜新闻稿 | M48: 2026-10-22 | N48: META25Q4
A49: FY-OR-2025 | B49: 年度资本开支 | C49: 甲骨文资本开支 | D49: 甲骨文 | E49: 21.215 | F49: 十亿美元 | G49: FY2025（2024-06 至 2025-05） | H49: 披露事实 | I49: 现金流量表资本开支 | J49: 甲骨文 FY2026 年报 10-K（现金流量表） | K49: 2026-06-22 | L49: https://www.sec.gov/Archives/edgar/data/1341439/000119312526277521/R8.htm｜现金流量表 | M49: 2026-10-22 | N49: ORCL10K26
A50: FY-OR-2026 | B50: 年度资本开支 | C50: 甲骨文资本开支 | D50: 甲骨文 | E50: 55.663 | F50: 十亿美元 | G50: FY2026（2025-06 至 2026-05） | H50: 披露事实 | I50: 同上 | J50: 甲骨文 FY2026 年报 10-K（现金流量表） | K50: 2026-06-22 | L50: https://www.sec.gov/Archives/edgar/data/1341439/000119312526277521/R8.htm｜现金流量表 | M50: 2026-10-22 | N50: ORCL10K26
A51: FQ-OR-27Q1 | B51: 季度资本开支 | C51: 甲骨文资本开支 | D51: 甲骨文 | E51: 28.499 | F51: 十亿美元 | G51: FY27 Q1（2026-06 至 08） | H51: 披露事实 | I51: 同上；同期交付约 850 MW 数据中心容量 | J51: 甲骨文 FY27 一季度业绩（8-K 附件 99.1） | K51: 2026-09-10 | L51: https://www.sec.gov/Archives/edgar/data/0001341439/000119312526387905/orcl-ex99_1.htm｜新闻稿现金流 | M51: 2026-10-22 | N51: ORCL27Q1
A52: G-OR-2027 | B52: 指引 | C52: 甲骨文 FY2027 资本开支预期（上限） | D52: 甲骨文 | E52: 95 | F52: 十亿美元 | G52: FY2027E | H52: 公司指引 | I52: 其中最多约 250 亿美元预计由客户偿付（媒体报道） | J52: The Standard（香港）：甲骨文 AI 支出超预期（FY27 资本开支指引报道） | K52: 2026-06-11 | L52: https://www.thestandard.com.hk/finance/article/334347/Oracles-AI-spending-blows-past-estimates-raising-worries-over-growing-debt｜报道正文 | M52: 2026-10-22 | N52: ORCL_G
A53: PW-01 | B53: 电力 | C53: 微软单季新增数据中心容量 | D53: 微软 | E53: 1 | F53: GW/季度 | G53: FY26 Q3–Q4 | H53: 披露事实 | I53: 电话会：本季度再增加约 1 GW | J53: 微软 FY26 Q4 业绩电话会 | K53: 2026-07-29 | L53: https://www.microsoft.com/en-us/investor/events/fy-2026/earnings-fy-2026-q4｜CEO/CFO 发言 | M53: 2026-10-22 | N53: MSFT26Q4
A54: PW-02 | B54: 电力 | C54: 微软 Fairwater（威斯康星）园区规划规模 | D54: 微软 | E54: 2 | F54: GW | G54: 规划 | H54: 公司指引 | I54: CEO 称“单此一处将扩展到 2 GW” | J54: 微软 FY26 Q1 业绩电话会 | K54: 2025-10-29 | L54: https://www.microsoft.com/en-us/investor/events/fy-2026/earnings-fy-2026-q1｜CEO 发言 | M54: 2026-10-22 | N54: MSFT26Q1
A55: PW-03 | B55: 电力 | C55: Meta Hyperion（路易斯安那）园区算力容量 | D55: Meta | E55: 5 | F55: GW | G55: 规划 | H55: 公司指引 | I55: 在路易斯安那投资 500 亿美元以上 | J55: Meta 数据中心：Richland Parish（Hyperion） | K55: 页面未标日期 | L55: https://datacenters.atmeta.com/richland-parish-data-center/｜园区页面 | M55: 2026-10-22 | N55: META_RP
A56: PW-04 | B56: 电力 | C56: 为 Hyperion 获批新建的燃气联合循环机组 | D56: Entergy → Meta | E56: 2262 | F56: MW | G56: 2025-08-20 获批 | H56: 披露事实 | I56: 3 台机组（MW 数据据 Entergy 申请文件，经 POWER 报道）；2028–2029 年投运 | J56: Entergy 新闻稿：路易斯安那监管委员会批准为 Meta 数据中心建设的基础设施 | K56: 2025-08-20 | L56: https://www.entergy.com/news/entergy-louisiana-receives-lpsc-approval-for-major-infrastructure-investments-to-support-metas-data-center-and-improve-reliability｜新闻稿；MW 见 POWER 2024-11-19 | M56: 2026-10-22 | N56: ENTG25
A57: PW-05 | B57: 电力 | C57: Hyperion 扩建拟新增燃气联合循环机组 | D57: Entergy → Meta | E57: 5200 | F57: MW | G57: 2026-03-27 申报 | H57: 公司指引 | I57: 7 台机组，原文“超过 5200 MW”，2030–2031 年；截至调研日未见监管批准 | J57: Entergy 新闻稿：与 Meta 签署新协议（Evest 扩建） | K57: 2026-03-27 | L57: https://www.entergy.com/news/entergy-louisiana-announces-a-new-agreement-with-meta-that-will-deliver-an-additional-2b-in-customer-savings｜新闻稿 | M57: 2026-10-22 | N57: ENTG26
A58: PW-06 | B58: 电力 | C58: 甲骨文单季交付数据中心容量 | D58: 甲骨文 | E58: 850 | F58: MW | G58: FY27 Q1 | H58: 披露事实 | I58: 约为上一季度的三倍 | J58: 甲骨文 FY27 一季度业绩（8-K 附件 99.1） | K58: 2026-09-10 | L58: https://www.sec.gov/Archives/edgar/data/0001341439/000119312526387905/orcl-ex99_1.htm｜新闻稿 | M58: 2026-10-22 | N58: ORCL27Q1
A59: PW-07 | B59: 电力 | C59: OpenAI 与 NVIDIA 合作部署的系统规模 | D59: OpenAI / NVIDIA | E59: 10 | F59: GW | G59: 2026 下半年起 | H59: 公司指引 | I59: 原文“至少 10 GW” | J59: NVIDIA 新闻稿：OpenAI 与 NVIDIA 宣布部署 10 GW NVIDIA 系统 | K59: 2025-09-22 | L59: https://nvidianews.nvidia.com/news/openai-and-nvidia-announce-strategic-partnership-to-deploy-10gw-of-nvidia-systems｜新闻稿 | M59: 2026-10-22 | N59: NV_OAI
... A65: PW-13 | B65: 成本 | C65: 每 GW IT 功率的 AI 数据中心总成本 | D65: Epoch AI | E65: 38 | F65: 十亿美元/GW | G65: 2026 | H65: 第三方估计 | I65: 其中算力设备约 260 亿、建设约 120 亿；按设施总功率约 300 亿/GW | J65: Epoch AI：前沿数据中心数据库与成本方法 | K65: 2026-10-20（数据库更新） | L65: https://epoch.ai/data/data-centers｜成本方法说明 | M65: 2026-10-22 | N65: EPOCH
A66: PW-14 | B66: 成本 | C66: 星际之门隐含每 GW 投资 | D66: OpenAI 等 | E66: =$E$67/$E$60 -> 57.142857 | F66: 十亿美元/GW | G66: 2025-09 | H66: 本表计算 | I66: 4000 亿美元 ÷ 约 7 GW（二手公告数字） | J66: 本表计算（公式见单元格） | K66: 2026-10-22 | M66: — | N66: CALC
A67: PW-16 | B67: 成本 | C67: 星际之门三年规划投资 | D67: OpenAI / 甲骨文 / 软银 | E67: 400 | F67: 十亿美元 | G67: 2025-09 | H67: 公司指引 | I67: 原文“未来三年投资超过 4000 亿美元”（二手） | J67: 维基百科：Stargate LLC（引用 OpenAI 2025-09-23 公告） | K67: 2025-09-23（被引公告） | L67: https://en.wikipedia.org/wiki/Stargate_LLC｜词条引用 OpenAI 公告 | M67: 2026-10-22 | N67: WIKI_SG
A68: PW-15 | B68: 电力 | C68: 规划中的数据中心自建电源（表后） | D68: 美国 | E68: 90 | F68: GW | G68: 截至 2026-05 | H68: 第三方估计 | I68: 59 个项目，多为燃气；仅约 2 GW（2.2%）已运行 | J68: Cleanview：绕开电网——数据中心开发商自建电厂报告 | K68: 2026 年中（数据截至 2026-05） | L68: https://cleanview.co/reports/behind-the-meter-data-centers｜报告正文 | M68: 2026-10-22 | N68: CLEANVIEW

Sheet D4_Meta三季报
A1: D4 Meta 2026 年三季报（10-Q）关键数据——原始材料，财务数字以此为准
A2: 蓝底=输入（披露数据）；橙底=输入（假设）；绿底=公式（本表计算）。“出处定位”给出原始材料的文件与章节，或网页链接；“访问日期”为网页查阅日期。
A4: 编号 | B4: 类别 | C4: 指标 | D4: 主体/地区 | E4: 数值 | F4: 单位 | G4: 期间 | H4: 性质 | I4: 口径说明 | J4: 来源名称 | K4: 发布日期 | L4: 出处定位（文件章节/表名或网页链接） | M4: 访问日期 | N4: 来源编号
A5: META-01 | B5: 资本开支 | C5: 资本开支（含融资租赁本金支付） | D5: Meta | E5: 34.91 | F5: 十亿美元 | G5: 2026Q3 | H5: 披露事实 | I5: 购置物业与设备 + 融资租赁本金支付 | J5: Meta Platforms, Inc. 10-Q 季报（截至 2026-09-30 的季度） | K5: 2026-10-21（签署日） | L5: 材料/Meta_2026Q3季报__meta-20260930.htm｜第 2 项 MD&A“第三季度业绩概览” | M5: 原始材料 | N5: M1
A6: META-02 | B6: 资本开支 | C6: 资本开支（含融资租赁本金支付） | D6: Meta | E6: 85.82 | F6: 十亿美元 | G6: 2026 年前三季度 | H6: 披露事实 | I6: 同上 | J6: Meta Platforms, Inc. 10-Q 季报（截至 2026-09-30 的季度） | K6: 2026-10-21（签署日） | L6: 材料/Meta_2026Q3季报__meta-20260930.htm｜MD&A“流动性与资本资源” | M6: 原始材料 | N6: M1
A7: META-03 | B7: 资本开支 | C7: 购置物业与设备 | D7: Meta | E7: 83.055 | F7: 十亿美元 | G7: 2026 年前三季度 | H7: 披露事实 | I7: 现金流量表 | J7: Meta Platforms, Inc. 10-Q 季报（截至 2026-09-30 的季度） | K7: 2026-10-21（签署日） | L7: 材料/Meta_2026Q3季报__meta-20260930.htm｜简明合并现金流量表 | M7: 原始材料 | N7: M1
A8: META-04 | B8: 资本开支 | C8: 融资租赁本金支付 | D8: Meta | E8: 2.769 | F8: 十亿美元 | G8: 2026 年前三季度 | H8: 披露事实 | I8: 现金流量表 | J8: Meta Platforms, Inc. 10-Q 季报（截至 2026-09-30 的季度） | K8: 2026-10-21（签署日） | L8: 材料/Meta_2026Q3季报__meta-20260930.htm｜简明合并现金流量表 | M8: 原始材料 | N8: M1
A9: META-05 | B9: 资本开支 | C9: 购置物业与设备 | D9: Meta | E9: 48.308 | F9: 十亿美元 | G9: 2025 年前三季度 | H9: 披露事实 | I9: 现金流量表（上年同期） | J9: Meta Platforms, Inc. 10-Q 季报（截至 2026-09-30 的季度） | K9: 2026-10-21（签署日） | L9: 材料/Meta_2026Q3季报__meta-20260930.htm｜简明合并现金流量表 | M9: 原始材料 | N9: M1
A10: META-06 | B10: 资本开支 | C10: 融资租赁本金支付 | D10: Meta | E10: 1.77 | F10: 十亿美元 | G10: 2025 年前三季度 | H10: 披露事实 | I10: 现金流量表（上年同期） | J10: Meta Platforms, Inc. 10-Q 季报（截至 2026-09-30 的季度） | K10: 2026-10-21（签署日） | L10: 材料/Meta_2026Q3季报__meta-20260930.htm｜简明合并现金流量表 | M10: 原始材料 | N10: M1
A11: META-07 | B11: 资本开支 | C11: 2025 年前三季度资本开支（含融资租赁本金） | D11: Meta | E11: =$E$9+$E$10 -> 50.078 | F11: 十亿美元 | G11: 2025 年前三季度 | H11: 本表计算 | I11: 与 2026 年同口径 | J11: 本表计算（公式见单元格） | K11: 2026-10-22 | M11: — | N11: CALC
A12: META-08 | B12: 资本开支 | C12: 2026 年前三季度资本开支同比增速 | D12: Meta | E12: =$E$6/$E$11-1 -> 0.71372659 | F12: % | G12: 2026 年前三季度 | H12: 本表计算 | J12: 本表计算（公式见单元格） | K12: 2026-10-22 | M12: — | N12: CALC
A13: META-09 | B13: 资本开支 | C13: 2026 年资本开支指引下限 | D13: Meta | E13: 135 | F13: 十亿美元 | G13: 2026 | H13: 公司指引 | I13: “约 1350 亿至 1450 亿美元”，用于 AI 与核心业务 | J13: Meta Platforms, Inc. 10-Q 季报（截至 2026-09-30 的季度） | K13: 2026-10-21（签署日） | L13: 材料/Meta_2026Q3季报__meta-20260930.htm｜MD&A“投资活动现金流” | M13: 原始材料 | N13: M1
A14: META-10 | B14: 资本开支 | C14: 2026 年资本开支指引上限 | D14: Meta | E14: 145 | F14: 十亿美元 | G14: 2026 | H14: 公司指引 | I14: 同上 | J14: Meta Platforms, Inc. 10-Q 季报（截至 2026-09-30 的季度） | K14: 2026-10-21（签署日） | L14: 材料/Meta_2026Q3季报__meta-20260930.htm｜MD&A“投资活动现金流” | M14: 原始材料 | N14: M1
A15: META-11 | B15: 资本开支 | C15: 2026 年四季度隐含资本开支（按指引中值） | D15: Meta | E15: =($E$13+$E$14)/2-$E$6 -> 54.18 | F15: 十亿美元 | G15: 2026Q4E | H15: 本表计算 | I15: 指引中值 − 前三季度实际；取中值为假设 | J15: 本表计算（公式见单元格） | K15: 2026-10-22 | M15: — | N15: CALC
A16: META-38 | B16: 经营 | C16: 营业收入 | D16: Meta | E16: 181.712 | F16: 十亿美元 | G16: 2026 年前三季度 | H16: 披露事实 | J16: Meta Platforms, Inc. 10-Q 季报（截至 2026-09-30 的季度） | K16: 2026-10-21（签署日） | L16: 材料/Meta_2026Q3季报__meta-20260930.htm｜简明合并利润表 | M16: 原始材料 | N16: M1
A17: META-39 | B17: 经营 | C17: 物业与设备折旧 | D17: Meta | E17: 6.81 | F17: 十亿美元 | G17: 2026Q3 | H17: 披露事实 | I17: 其中服务器与网络资产折旧 53.4 亿 | J17: Meta Platforms, Inc. 10-Q 季报（截至 2026-09-30 的季度） | K17: 2026-10-21（签署日） | L17: 材料/Meta_2026Q3季报__meta-20260930.htm｜附注 6 | M17: 原始材料 | N17: M1
A18: META-40 | B18: 经营 | C18: 物业与设备折旧 | D18: Meta | E18: 4.76 | F18: 十亿美元 | G18: 2025Q3 | H18: 披露事实 | J18: Meta Platforms, Inc. 10-Q 季报（截至 2026-09-30 的季度） | K18: 2026-10-21（签署日） | L18: 材料/Meta_2026Q3季报__meta-20260930.htm｜附注 6 | M18: 原始材料 | N18: M1
A19: META-12 | B19: 经营 | C19: 营业收入 | D19: Meta | E19: 64.601 | F19: 十亿美元 | G19: 2026Q3 | H19: 披露事实 | J19: Meta Platforms, Inc. 10-Q 季报（截至 2026-09-30 的季度） | K19: 2026-10-21（签署日） | L19: 材料/Meta_2026Q3季报__meta-20260930.htm｜简明合并利润表 | M19: 原始材料 | N19: M1
A20: META-13 | B20: 经营 | C20: 营业收入 | D20: Meta | E20: 51.242 | F20: 十亿美元 | G20: 2025Q3 | H20: 披露事实 | J20: Meta Platforms, Inc. 10-Q 季报（截至 2026-09-30 的季度） | K20: 2026-10-21（签署日） | L20: 材料/Meta_2026Q3季报__meta-20260930.htm｜简明合并利润表 | M20: 原始材料 | N20: M1
A21: META-14 | B21: 经营 | C21: 营业利润 | D21: Meta | E21: 12.988 | F21: 十亿美元 | G21: 2026Q3 | H21: 披露事实 | I21: 含 98.9 亿美元多州总检察长和解费用 | J21: Meta Platforms, Inc. 10-Q 季报（截至 2026-09-30 的季度） | K21: 2026-10-21（签署日） | L21: 材料/Meta_2026Q3季报__meta-20260930.htm｜简明合并利润表 | M21: 原始材料 | N21: M1
A22: META-15 | B22: 经营 | C22: 营业利润 | D22: Meta | E22: 20.535 | F22: 十亿美元 | G22: 2025Q3 | H22: 披露事实 | J22: Meta Platforms, Inc. 10-Q 季报（截至 2026-09-30 的季度） | K22: 2026-10-21（签署日） | L22: 材料/Meta_2026Q3季报__meta-20260930.htm｜简明合并利润表 | M22: 原始材料 | N22: M1
A23: META-16 | B23: 经营 | C23: 经营活动现金流 | D23: Meta | E23: 96.873 | F23: 十亿美元 | G23: 2026 年前三季度 | H23: 披露事实 | J23: Meta Platforms, Inc. 10-Q 季报（截至 2026-09-30 的季度） | K23: 2026-10-21（签署日） | L23: 材料/Meta_2026Q3季报__meta-20260930.htm｜简明合并现金流量表 | M23: 原始材料 | N23: M1
A24: META-17 | B24: 经营 | C24: 折旧与摊销 | D24: Meta | E24: 19.509 | F24: 十亿美元 | G24: 2026 年前三季度 | H24: 披露事实 | I24: 上年同期 13.205 | J24: Meta Platforms, Inc. 10-Q 季报（截至 2026-09-30 的季度） | K24: 2026-10-21（签署日） | L24: 材料/Meta_2026Q3季报__meta-20260930.htm｜简明合并现金流量表 | M24: 原始材料 | N24: M1
A25: META-18 | B25: 经营 | C25: 折旧与摊销 | D25: Meta | E25: 13.205 | F25: 十亿美元 | G25: 2025 年前三季度 | H25: 披露事实 | J25: Meta Platforms, Inc. 10-Q 季报（截至 2026-09-30 的季度） | K25: 2026-10-21（签署日） | L25: 材料/Meta_2026Q3季报__meta-20260930.htm｜简明合并现金流量表 | M25: 原始材料 | N25: M1
A26: META-19 | B26: 资产 | C26: 服务器与网络资产（原值） | D26: Meta | E26: 133.626 | F26: 十亿美元 | G26: 2026-09-30 | H26: 披露事实 | I26: 2025 年末 98.040 | J26: Meta Platforms, Inc. 10-Q 季报（截至 2026-09-30 的季度） | K26: 2026-10-21（签署日） | L26: 材料/Meta_2026Q3季报__meta-20260930.htm｜附注 6 物业与设备 | M26: 原始材料 | N26: M1
A27: META-20 | B27: 资产 | C27: 服务器与网络资产（原值） | D27: Meta | E27: 98.04 | F27: 十亿美元 | G27: 2025-12-31 | H27: 披露事实 | J27: Meta Platforms, Inc. 10-Q 季报（截至 2026-09-30 的季度） | K27: 2026-10-21（签署日） | L27: 材料/Meta_2026Q3季报__meta-20260930.htm｜附注 6 | M27: 原始材料 | N27: M1
A28: META-21 | B28: 资产 | C28: 在建工程（主要为数据中心、服务器与网络） | D28: Meta | E28: 89.499 | F28: 十亿美元 | G28: 2026-09-30 | H28: 披露事实 | I28: 2025 年末 50.521 | J28: Meta Platforms, Inc. 10-Q 季报（截至 2026-09-30 的季度） | K28: 2026-10-21（签署日） | L28: 材料/Meta_2026Q3季报__meta-20260930.htm｜附注 6 | M28: 原始材料 | N28: M1
A29: META-22 | B29: 资产 | C29: 在建工程 | D29: Meta | E29: 50.521 | F29: 十亿美元 | G29: 2025-12-31 | H29: 披露事实 | J29: Meta Platforms, Inc. 10-Q 季报（截至 2026-09-30 的季度） | K29: 2026-10-21（签署日） | L29: 材料/Meta_2026Q3季报__meta-20260930.htm｜附注 6 | M29: 原始材料 | N29: M1
A30: META-23 | B30: 资产 | C30: 物业与设备净值 | D30: Meta | E30: 253.222 | F30: 十亿美元 | G30: 2026-09-30 | H30: 披露事实 | I30: 2025 年末 176.400 | J30: Meta Platforms, Inc. 10-Q 季报（截至 2026-09-30 的季度） | K30: 2026-10-21（签署日） | L30: 材料/Meta_2026Q3季报__meta-20260930.htm｜附注 6 | M30: 原始材料 | N30: M1
A31: META-24 | B31: 资产 | C31: 物业与设备净值 | D31: Meta | E31: 176.4 | F31: 十亿美元 | G31: 2025-12-31 | H31: 披露事实 | J31: Meta Platforms, Inc. 10-Q 季报（截至 2026-09-30 的季度） | K31: 2026-10-21（签署日） | L31: 材料/Meta_2026Q3季报__meta-20260930.htm｜附注 6 | M31: 原始材料 | N31: M1
A32: META-25 | B32: 承诺 | C32: 尚未起租的经营与融资租赁 | D32: Meta | E32: 355.73 | F32: 十亿美元 | G32: 2026-09-30 | H32: 披露事实 | I32: 数据中心、能源相关基础设施、托管与网络；2026–2036 年起租，租期 1–30 年 | J32: Meta Platforms, Inc. 10-Q 季报（截至 2026-09-30 的季度） | K32: 2026-10-21（签署日） | L32: 材料/Meta_2026Q3季报__meta-20260930.htm｜附注 10 承诺与或有事项 | M32: 原始材料 | N32: M1
A33: META-26 | B33: 承诺 | C33: 不可撤销合同承诺 | D33: Meta | E33: 454.52 | F33: 十亿美元 | G33: 2026-09-30 | H33: 披露事实 | I33: 主要为第三方云容量、服务器与网络投资、数据中心能源服务协议、Reality Labs 硬件 | J33: Meta Platforms, Inc. 10-Q 季报（截至 2026-09-30 的季度） | K33: 2026-10-21（签署日） | L33: 材料/Meta_2026Q3季报__meta-20260930.htm｜附注 10 | M33: 原始材料 | N33: M1
A34: META-27 | B34: 承诺 | C34: 其中 2026 年剩余期间到期 | D34: Meta | E34: 45.85 | F34: 十亿美元 | G34: 2026Q4 | H34: 披露事实 | J34: Meta Platforms, Inc. 10-Q 季报（截至 2026-09-30 的季度） | K34: 2026-10-21（签署日） | L34: 材料/Meta_2026Q3季报__meta-20260930.htm｜附注 10 | M34: 原始材料 | N34: M1
A35: META-28 | B35: 承诺 | C35: 其中 2027 年到期 | D35: Meta | E35: 121.41 | F35: 十亿美元 | G35: 2027 | H35: 披露事实 | J35: Meta Platforms, Inc. 10-Q 季报（截至 2026-09-30 的季度） | K35: 2026-10-21（签署日） | L35: 材料/Meta_2026Q3季报__meta-20260930.htm｜附注 10 | M35: 原始材料 | N35: M1
A36: META-29 | B36: 承诺 | C36: 或有云容量采购义务（五年内，上限） | D36: Meta | E36: 14.72 | F36: 十亿美元 | G36: 2026-09-30 | H36: 披露事实 | I36: 若云服务商转售可减少 | J36: Meta Platforms, Inc. 10-Q 季报（截至 2026-09-30 的季度） | K36: 2026-10-21（签署日） | L36: 材料/Meta_2026Q3季报__meta-20260930.htm｜附注 10 | M36: 原始材料 | N36: M1
A37: META-30 | B37: 承诺 | C37: 为多年期基础设施采购协议托管的受限现金 | D37: Meta | E37: 10.8 | F37: 十亿美元 | G37: 2026-09-30 | H37: 披露事实 | I37: 预计 2028–2030 年释放 | J37: Meta Platforms, Inc. 10-Q 季报（截至 2026-09-30 的季度） | K37: 2026-10-21（签署日） | L37: 材料/Meta_2026Q3季报__meta-20260930.htm｜附注 4 金融工具 | M37: 原始材料 | N37: M1
A38: META-31 | B38: 数据中心合资 | C38: 路易斯安那数据中心合资项目总开发成本（估） | D38: Meta 与合作方 | E38: 27 | F38: 十亿美元 | G38: 2025-10 签署 | H38: 披露事实 | I38: Meta 持股 20%；租约 2029 年起租，初始 4 年、最长 20 年；提供残值担保 | J38: Meta Platforms, Inc. 10-Q 季报（截至 2026-09-30 的季度） | K38: 2026-10-21（签署日） | L38: 材料/Meta_2026Q3季报__meta-20260930.htm｜附注 5 非上市权益投资“数据中心合资” | M38: 原始材料 | N38: M1
A39: META-32 | B39: 数据中心合资 | C39: 得克萨斯数据中心合资项目总开发成本（估） | D39: Meta 与合作方 | E39: 14 | F39: 十亿美元 | G39: 2026-07 签署 | H39: 披露事实 | I39: Meta 持股 20%；租约 2028 年起租 | J39: Meta Platforms, Inc. 10-Q 季报（截至 2026-09-30 的季度） | K39: 2026-10-21（签署日） | L39: 材料/Meta_2026Q3季报__meta-20260930.htm｜附注 5 | M39: 原始材料 | N39: M1
A40: META-33 | B40: 数据中心合资 | C40: 对两家数据中心合资企业的最大损失敞口 | D40: Meta | E40: 68.404 | F40: 十亿美元 | G40: 2026-09-30 | H40: 披露事实 | I40: 含最大残值担保 41.493、租赁承诺 18.476 | J40: Meta Platforms, Inc. 10-Q 季报（截至 2026-09-30 的季度） | K40: 2026-10-21（签署日） | L40: 材料/Meta_2026Q3季报__meta-20260930.htm｜附注 5 | M40: 原始材料 | N40: M1
A41: META-34 | B41: 融资 | C41: 长期债券本金余额 | D41: Meta | E41: 84 | F41: 十亿美元 | G41: 2026-09-30 | H41: 披露事实 | I41: 2026 年 5 月新发 250 亿美元 | J41: Meta Platforms, Inc. 10-Q 季报（截至 2026-09-30 的季度） | K41: 2026-10-21（签署日） | L41: 材料/Meta_2026Q3季报__meta-20260930.htm｜附注 9 长期债务 | M41: 原始材料 | N41: M1
A42: META-35 | B42: 融资 | C42: 现金、现金等价物及有价证券 | D42: Meta | E42: 82.45 | F42: 十亿美元 | G42: 2026-09-30 | H42: 披露事实 | J42: Meta Platforms, Inc. 10-Q 季报（截至 2026-09-30 的季度） | K42: 2026-10-21（签署日） | L42: 材料/Meta_2026Q3季报__meta-20260930.htm｜MD&A | M42: 原始材料 | N42: M1
A43: META-36 | B43: 能源 | C43: 清洁与可再生能源采购协议期限（下限） | D43: Meta | E43: 9 | F43: 年 | G43: 2026-09-30 | H43: 披露事实 | I43: 期限 9–25 年，未约定固定或最低采购量 | J43: Meta Platforms, Inc. 10-Q 季报（截至 2026-09-30 的季度） | K43: 2026-10-21（签署日） | L43: 材料/Meta_2026Q3季报__meta-20260930.htm｜附注 10 | M43: 原始材料 | N43: M1
A44: META-37 | B44: 能源 | C44: 清洁与可再生能源采购协议期限（上限） | D44: Meta | E44: 25 | F44: 年 | G44: 2026-09-30 | H44: 披露事实 | I44: 同上 | J44: Meta Platforms, Inc. 10-Q 季报（截至 2026-09-30 的季度） | K44: 2026-10-21（签署日） | L44: 材料/Meta_2026Q3季报__meta-20260930.htm｜附注 10 | M44: 原始材料 | N44: M1

Sheet D5_Constellation
A1: D5 Constellation 2025 年报（10-K）与 2026 年二季报（10-Q）关键数据——原始材料
A2: 蓝底=输入（披露数据）；橙底=输入（假设）；绿底=公式（本表计算）。“出处定位”给出原始材料的文件与章节，或网页链接；“访问日期”为网页查阅日期。
A4: 编号 | B4: 类别 | C4: 指标 | D4: 主体/地区 | E4: 数值 | F4: 单位 | G4: 期间 | H4: 性质 | I4: 口径说明 | J4: 来源名称 | K4: 发布日期 | L4: 出处定位（文件章节/表名或网页链接） | M4: 访问日期 | N4: 来源编号
A5: CEG-01 | B5: 规模 | C5: 收购 Calpine 后总装机 | D5: Constellation | E5: 55 | F5: GW | G5: 2026-01 | H5: 披露事实 | I5: 核电、燃气、地热、水电、风电、光伏 | J5: Constellation Energy Corp. 10-K 年报（2025 财年） | K5: 2026-02-24（签署日） | L5: 材料/Constellation_2025年报__ceg-20251231.htm｜第 1 项“业务” | M5: 原始材料 | N5: M2
A6: CEG-02 | B6: 规模 | C6: 自有发电装机（未含 Calpine） | D6: Constellation | E6: 31676 | F6: MW | G6: 2025-12-31 | H6: 披露事实 | I6: 按权益比例；另有合同电源 4798 MW | J6: Constellation Energy Corp. 10-K 年报（2025 财年） | K6: 2026-02-24（签署日） | L6: 材料/Constellation_2025年报__ceg-20251231.htm｜“我们的运营” | M6: 原始材料 | N6: M2
A7: CEG-03 | B7: 规模 | C7: 核电装机 | D7: Constellation | E7: 22 | F7: GW | G7: 2025 | H7: 披露事实 | I7: 14 座电站、25 台机组 | J7: Constellation Energy Corp. 10-K 年报（2025 财年） | K7: 2026-02-24（签署日） | L7: 材料/Constellation_2025年报__ceg-20251231.htm｜“核电设施” | M7: 原始材料 | N7: M2
A8: CEG-04 | B8: 规模 | C8: 核电发电量 | D8: Constellation | E8: 182690 | F8: GWh | G8: 2025 | H8: 披露事实 | I8: 按权益比例；2024 年 181711 | J8: Constellation Energy Corp. 10-K 年报（2025 财年） | K8: 2026-02-24（签署日） | L8: 材料/Constellation_2025年报__ceg-20251231.htm｜MD&A 售电与供电量表 | M8: 原始材料 | N8: M2
A9: CEG-05 | B9: 规模 | C9: 核电机组容量系数 | D9: Constellation | E9: 0.947 | F9: % | G9: 2025 | H9: 披露事实 | I9: 不含 Salem、STP；2024 年 94.6% | J9: Constellation Energy Corp. 10-K 年报（2025 财年） | K9: 2026-02-24（签署日） | L9: 材料/Constellation_2025年报__ceg-20251231.htm｜MD&A“核电机组容量系数” | M9: 原始材料 | N9: M2
A10: CEG-06 | B10: 规模 | C10: 电力供应总量（自发 + 外购） | D10: Constellation | E10: 268943 | F10: GWh | G10: 2025 | H10: 披露事实 | I10: 其中外购 63999 | J10: Constellation Energy Corp. 10-K 年报（2025 财年） | K10: 2026-02-24（签署日） | L10: 材料/Constellation_2025年报__ceg-20251231.htm｜MD&A 售电与供电量表 | M10: 原始材料 | N10: M2
A11: CEG-07 | B11: 规模 | C11: Calpine 新增装机 | D11: Constellation | E11: 23 | F11: GW | G11: 2026-01-07 | H11: 披露事实 | I11: 72 个发电与储能资产（扣除监管要求剥离后）；零售负荷约 62 TWh | J11: Constellation Energy Corp. 10-K 年报（2025 财年） | K11: 2026-02-24（签署日） | L11: 材料/Constellation_2025年报__ceg-20251231.htm｜附注 2；第 1 项 | M11: 原始材料 | N11: M2
A12: CEG-08 | B12: 规模 | C12: Calpine 燃气装机 | D12: Calpine | E12: 21 | F12: GW | G12: 2026-01 | H12: 披露事实 | I12: 以联合循环为主，分布于得州、加州、东北部 | J12: Constellation Energy Corp. 10-K 年报（2025 财年） | K12: 2026-02-24（签署日） | L12: 材料/Constellation_2025年报__ceg-20251231.htm｜“燃气与燃油设施” | M12: 原始材料 | N12: M2
A13: CEG-09 | B13: 交易 | C13: Calpine 收购对价 | D13: Constellation | E13: 21.8 | F13: 十亿美元 | G13: 2026-01-07 | H13: 披露事实 | I13: 5000 万股新股 + 约 45 亿美元现金；10-K 写约 220 亿美元，10-Q 写约 218 亿美元 | J13: Constellation Energy Corp. 10-Q 季报（截至 2026-06-30 的季度） | K13: 2026-08-06（签署日） | L13: 材料/Constellation_2026Q2季报__ceg-20260630.htm｜“重大交易与进展” | M13: 原始材料 | N13: M3
A14: CEG-10 | B14: 交易 | C14: 为满足监管承诺出售 5 座燃气电站（PJM） | D14: Constellation | E14: 4.4 | F14: GW | G14: 2026-03 | H14: 披露事实 | I14: 作价 50 亿美元，买方 LS Power | J14: Constellation Energy Corp. 10-Q 季报（截至 2026-06-30 的季度） | K14: 2026-08-06（签署日） | L14: 材料/Constellation_2026Q2季报__ceg-20260630.htm｜“重大交易与进展” | M14: 原始材料 | N14: M3
A15: CEG-11 | B15: 财务 | C15: 营业收入 | D15: Constellation | E15: 25533 | F15: 百万美元 | G15: 2025 | H15: 披露事实 | I15: 2024 年 23568 | J15: Constellation Energy Corp. 10-K 年报（2025 财年） | K15: 2026-02-24（签署日） | L15: 材料/Constellation_2025年报__ceg-20251231.htm｜MD&A 经营业绩 | M15: 原始材料 | N15: M2
A16: CEG-12 | B16: 财务 | C16: 营业收入 | D16: Constellation | E16: 23568 | F16: 百万美元 | G16: 2024 | H16: 披露事实 | J16: Constellation Energy Corp. 10-K 年报（2025 财年） | K16: 2026-02-24（签署日） | L16: 材料/Constellation_2025年报__ceg-20251231.htm｜MD&A 经营业绩 | M16: 原始材料 | N16: M2
A17: CEG-13 | B17: 财务 | C17: 归母净利润 | D17: Constellation | E17: 2319 | F17: 百万美元 | G17: 2025 | H17: 披露事实 | I17: 2024 年 3749（核电 PTC 收入下降等） | J17: Constellation Energy Corp. 10-K 年报（2025 财年） | K17: 2026-02-24（签署日） | L17: 材料/Constellation_2025年报__ceg-20251231.htm｜MD&A 经营业绩 | M17: 原始材料 | N17: M2
A18: CEG-14 | B18: 财务 | C18: 营业收入 | D18: Constellation | E18: 18626 | F18: 百万美元 | G18: 2026H1 | H18: 披露事实 | I18: 含 Calpine；2025H1 为 12889 | J18: Constellation Energy Corp. 10-Q 季报（截至 2026-06-30 的季度） | K18: 2026-08-06（签署日） | L18: 材料/Constellation_2026Q2季报__ceg-20260630.htm｜合并利润表 | M18: 原始材料 | N18: M3
A19: CEG-15 | B19: 财务 | C19: 营业收入 | D19: Constellation | E19: 12889 | F19: 百万美元 | G19: 2025H1 | H19: 披露事实 | J19: Constellation Energy Corp. 10-Q 季报（截至 2026-06-30 的季度） | K19: 2026-08-06（签署日） | L19: 材料/Constellation_2026Q2季报__ceg-20260630.htm｜合并利润表 | M19: 原始材料 | N19: M3
A20: CEG-16 | B20: 财务 | C20: 资本开支 | D20: Constellation | E20: 2949 | F20: 百万美元 | G20: 2025 | H20: 披露事实 | I20: 2024 年 2565 | J20: Constellation Energy Corp. 10-K 年报（2025 财年） | K20: 2026-02-24（签署日） | L20: 材料/Constellation_2025年报__ceg-20251231.htm｜合并现金流量表 | M20: 原始材料 | N20: M2
A21: CEG-17 | B21: 财务 | C21: 资本开支预估（含 Calpine） | D21: Constellation | E21: 5.7 | F21: 十亿美元 | G21: 2026E | H21: 公司指引 | I21: 其中增长性资本开支 39 亿美元（Crane 重启、核电增容、共址基础设施、延寿）；约 29% 为核燃料 | J21: Constellation Energy Corp. 10-K 年报（2025 财年） | K21: 2026-02-24（签署日） | L21: 材料/Constellation_2025年报__ceg-20251231.htm｜“流动性与资本资源” | M21: 原始材料 | N21: M2
A22: CEG-18 | B22: 财务 | C22: 资本开支预估（含 Calpine） | D22: Constellation | E22: 4.7 | F22: 十亿美元 | G22: 2027E | H22: 公司指引 | J22: Constellation Energy Corp. 10-K 年报（2025 财年） | K22: 2026-02-24（签署日） | L22: 材料/Constellation_2025年报__ceg-20251231.htm｜“流动性与资本资源” | M22: 原始材料 | N22: M2
A23: CEG-19 | B23: 财务 | C23: 资本开支 | D23: Constellation | E23: 2521 | F23: 百万美元 | G23: 2026H1 | H23: 披露事实 | I23: 2025H1 为 1573 | J23: Constellation Energy Corp. 10-Q 季报（截至 2026-06-30 的季度） | K23: 2026-08-06（签署日） | L23: 材料/Constellation_2026Q2季报__ceg-20260630.htm｜合并现金流量表 | M23: 原始材料 | N23: M3
A24: CEG-20 | B24: 协议 | C24: Crane（原三哩岛 1 号机组）重启后装机 | D24: Constellation → 微软 | E24: 835 | F24: MW | G24: 2024-09 签约 | H24: 披露事实 | I24: 20 年购电协议，微软购买电量、容量与零排放属性，用于其 PJM 区域数据中心 | J24: Constellation Energy Corp. 10-K 年报（2025 财年） | K24: 2026-02-24（签署日） | L24: 材料/Constellation_2025年报__ceg-20251231.htm｜“核电设施” | M24: 原始材料 | N24: M2
A25: CEG-21 | B25: 协议 | C25: Crane 重启贷款担保（美国能源部） | D25: Constellation | E25: 1 | F25: 十亿美元 | G25: 2025-11 | H25: 披露事实 | I25: 联邦融资银行贷款，美国国债利率 + 0.375%；到期日 10-K 两处分别写 2055 年 10 月和 11 月 | J25: Constellation Energy Corp. 10-K 年报（2025 财年） | K25: 2026-02-24（签署日） | L25: 材料/Constellation_2025年报__ceg-20251231.htm｜附注 16；MD&A | M25: 原始材料 | N25: M2
A26: CEG-22 | B26: 协议 | C26: Crane 并网：PJM 研究显示部分输电升级最晚至 | D26: Constellation | E26: 2030 | F26: 年 | G26: 2026-06 | H26: 披露事实 | I26: 2026 年 3 月申请将 Eddystone 容量并网权转给 Crane，FERC 于 2026 年 6 月批准 | J26: Constellation Energy Corp. 10-Q 季报（截至 2026-06-30 的季度） | K26: 2026-08-06（签署日） | L26: 材料/Constellation_2026Q2季报__ceg-20260630.htm｜附注 3 监管事项 | M26: 原始材料 | N26: M3
A27: CEG-23 | B27: 协议 | C27: Clinton 核电站净装机 | D27: Constellation → Meta | E27: 1092 | F27: MW | G27: 2025-12-31 | H27: 披露事实 | I27: 20 年购电协议，2027 年 6 月起；另增容 30 MW（2029 年完成） | J27: Constellation Energy Corp. 10-K 年报（2025 财年） | K27: 2026-02-24（签署日） | L27: 材料/Constellation_2025年报__ceg-20251231.htm｜第 2 项“物业”；MD&A | M27: 原始材料 | N27: M2
A28: CEG-24 | B28: 协议 | C28: Clinton 增容 | D28: Constellation → Meta | E28: 30 | F28: MW | G28: 2029 | H28: 公司指引 | J28: Constellation Energy Corp. 10-K 年报（2025 财年） | K28: 2026-02-24（签署日） | L28: 材料/Constellation_2025年报__ceg-20251231.htm｜MD&A“Clinton 清洁能源中心” | M28: 原始材料 | N28: M2
A29: CEG-25 | B29: 协议 | C29: CyrusOne 数据中心接入（Freestone 一期） | D29: Constellation → CyrusOne | E29: 380 | F29: MW | G29: 2026Q1 | H29: 披露事实 | I29: 紧邻得州 Freestone 能源中心；二期再 380 MW 为独家协议 | J29: Constellation Energy Corp. 10-Q 季报（截至 2026-06-30 的季度） | K29: 2026-08-06（签署日） | L29: 材料/Constellation_2026Q2季报__ceg-20260630.htm｜“Freestone 新数据中心设施” | M29: 原始材料 | N29: M3
A30: CEG-26 | B30: 协议 | C30: CyrusOne 数据中心接入（Freestone 二期，独家） | D30: Constellation → CyrusOne | E30: 380 | F30: MW | G30: 2026Q1 | H30: 披露事实 | I30: 独家协议 | J30: Constellation Energy Corp. 10-Q 季报（截至 2026-06-30 的季度） | K30: 2026-08-06（签署日） | L30: 材料/Constellation_2026Q2季报__ceg-20260630.htm｜同上 | M30: 原始材料 | N30: M3
A31: CEG-27 | B31: 协议 | C31: Calpine 与 CyrusOne（Thad Hill 能源中心） | D31: Calpine → CyrusOne | E31: 400 | F31: MW | G31: 2025 下半年 | H31: 披露事实 | I31: 得州 Bosque 县 | J31: Constellation Energy Corp. 10-Q 季报（截至 2026-06-30 的季度） | K31: 2026-08-06（签署日） | L31: 材料/Constellation_2026Q2季报__ceg-20260630.htm｜同上 | M31: 原始材料 | N31: M3
A32: CEG-28 | B32: 协议 | C32: 新签长期核电购电协议 | D32: Constellation → 多家投资级客户 | E32: 920 | F32: MW | G32: 2026 | H32: 披露事实 | I32: 期限 15–20 年，2029–2032 年起；含沃尔玛 176 MW（支持 Dresden 增容 30 MW） | J32: Constellation Energy Corp. 10-Q 季报（截至 2026-06-30 的季度） | K32: 2026-08-06（签署日） | L32: 材料/Constellation_2026Q2季报__ceg-20260630.htm｜“长期核电购电协议” | M32: 原始材料 | N32: M3
A33: CEG-29 | B33: 电价 | C33: PJM West 平均电价 | D33: PJM | E33: 50.19 | F33: 美元/MWh | G33: 2025 | H33: 披露事实 | I33: 2024 年 33.74，+48.8% | J33: Constellation Energy Corp. 10-K 年报（2025 财年） | K33: 2026-02-24（签署日） | L33: 材料/Constellation_2025年报__ceg-20251231.htm｜MD&A“电价” | M33: 原始材料 | N33: M2
A34: CEG-30 | B34: 电价 | C34: PJM West 平均电价 | D34: PJM | E34: 33.74 | F34: 美元/MWh | G34: 2024 | H34: 披露事实 | J34: Constellation Energy Corp. 10-K 年报（2025 财年） | K34: 2026-02-24（签署日） | L34: 材料/Constellation_2025年报__ceg-20251231.htm｜MD&A“电价” | M34: 原始材料 | N34: M2
A35: CEG-31 | B35: 电价 | C35: PJM West 平均电价 | D35: PJM | E35: 74.28 | F35: 美元/MWh | G35: 2026H1 | H35: 披露事实 | I35: 2025H1 为 48.06，+54.6% | J35: Constellation Energy Corp. 10-Q 季报（截至 2026-06-30 的季度） | K35: 2026-08-06（签署日） | L35: 材料/Constellation_2026Q2季报__ceg-20260630.htm｜MD&A“电价” | M35: 原始材料 | N35: M3
A36: CEG-32 | B36: 电价 | C36: PJM West 平均电价 | D36: PJM | E36: 48.06 | F36: 美元/MWh | G36: 2025H1 | H36: 披露事实 | J36: Constellation Energy Corp. 10-Q 季报（截至 2026-06-30 的季度） | K36: 2026-08-06（签署日） | L36: 材料/Constellation_2026Q2季报__ceg-20260630.htm｜MD&A“电价” | M36: 原始材料 | N36: M3
A37: CEG-33 | B37: 容量价格 | C37: PJM 东部（EMAAC）平均容量价格 | D37: PJM | E37: 179.79 | F37: 美元/MW·天 | G37: 2025 | H37: 披露事实 | I37: 2024 年 51.89 | J37: Constellation Energy Corp. 10-K 年报（2025 财年） | K37: 2026-02-24（签署日） | L37: 材料/Constellation_2025年报__ceg-20251231.htm｜MD&A“容量价格” | M37: 原始材料 | N37: M2
A38: CEG-34 | B38: 容量价格 | C38: PJM 东部（EMAAC）平均容量价格 | D38: PJM | E38: 51.89 | F38: 美元/MW·天 | G38: 2024 | H38: 披露事实 | J38: Constellation Energy Corp. 10-K 年报（2025 财年） | K38: 2026-02-24（签署日） | L38: 材料/Constellation_2025年报__ceg-20251231.htm｜MD&A“容量价格” | M38: 原始材料 | N38: M2
A39: CEG-35 | B39: 容量价格 | C39: PJM 东部（EMAAC）平均容量价格 | D39: PJM | E39: 279.8 | F39: 美元/MW·天 | G39: 2026H1 | H39: 披露事实 | I39: 2025H1 为 89.65 | J39: Constellation Energy Corp. 10-Q 季报（截至 2026-06-30 的季度） | K39: 2026-08-06（签署日） | L39: 材料/Constellation_2026Q2季报__ceg-20260630.htm｜MD&A“容量价格” | M39: 原始材料 | N39: M3
A40: CEG-36 | B40: 容量价格 | C40: PJM 2028/29 容量拍卖全网出清价（触及上限） | D40: PJM | E40: 325 | F40: 美元/MW·天 | G40: 2026-07 | H40: 披露事实 | I40: FERC 2026 年 4 月批准把约 175–325 美元的价格区间延用到 2028/29、2029/30 两期 | J40: Constellation Energy Corp. 10-Q 季报（截至 2026-06-30 的季度） | K40: 2026-08-06（签署日） | L40: 材料/Constellation_2026Q2季报__ceg-20260630.htm｜“其他关键业务驱动因素—PJM 市场改革” | M40: 原始材料 | N40: M3
A41: CEG-37 | B41: 政策 | C41: 核电生产税收抵免（PTC）上限 | D41: 美国 | E41: 15 | F41: 美元/MWh | G41: 2024–2032 | H41: 披露事实 | I41: 随收入阈值递减，按通胀调整 | J41: Constellation Energy Corp. 10-K 年报（2025 财年） | K41: 2026-02-24（签署日） | L41: 材料/Constellation_2025年报__ceg-20251231.htm｜MD&A“核电 PTC” | M41: 原始材料 | N41: M2

Sheet D6_购电协议
A1: D6 核电（及其他）与科技公司的长期购电协议：逐笔明细
A2: “容量”为合同或公告中的装机/合同容量；“计入确定合同”= 现役、重启、增容机组的确定购电协议（不含先进堆意向、供电合同、燃气共址与非科技公司）。年发电量当量 = 容量 × 核电容量系数（假设页）× 8760 ÷ 10^6。均未披露电价。
A4: 编号 | B4: 买方 | C4: 买方归类 | D4: 卖方/开发商 | E4: 电厂/项目 | F4: 技术类型 | G4: 归类 | H4: 合同性质 | I4: 容量（MW） | J4: 其中新增上网容量（MW） | K4: 期限（年） | L4: 起始/目标 | M4: 公告日期 | N4: 计入“确定合同”合计 | O4: 年发电量当量（TWh，公式） | P4: 结构说明 | Q4: 来源名称 | R4: 发布日期 | S4: 出处定位（文件章节或网页链接） | T4: 访问日期 | U4: 性质 | V4: 备注 | W4: 来源编号
A5: PPA-01 | B5: 微软 | C5: 微软 | D5: Constellation | E5: Crane（原三哩岛 1 号，宾州，PJM） | F5: 重启 | G5: 重启 | H5: 确定 | I5: 835 | J5: 835 | K5: 20 | L5: 2027 年（原定 2028） | M5: 2024-09-20 | N5: 是 | O5: =IF(N5="是",I5*'假设'!$C$11*'假设'!$C$12/1000000,0) -> 6.656286 | P5: 购电协议，电厂接入 PJM 电网 | Q5: Constellation 新闻稿：启动 Crane 清洁能源中心（与微软签署 20 年协议） | R5: 2024-09-20 | S5: https://www.constellationenergy.com/news/2024/Constellation-to-Launch-Crane-Clean-Energy-Center-Restoring-Jobs-and-Carbon-Free-Power-to-The-Grid.html｜新闻稿；重启提前至 2027 见 2025-09-23 新闻稿；原始材料 10-K“核电设施” | T5: 2026-10-22 | U5: 披露事实 | V5: 美国能源部 10 亿美元贷款（2025-11） | W5: CEG_CRANE24
A6: PPA-02 | B6: Meta | C6: Meta | D6: Constellation | E6: Clinton（伊利诺伊，MISO） | F6: 现役 + 增容 | G6: 现役/增容 | H6: 确定 | I6: 1121 | J6: 30 | K6: 20 | L6: 2027-06 | M6: 2025-06-03 | N6: 是 | O6: =IF(N6="是",I6*'假设'!$C$11*'假设'!$C$12/1000000,0) -> 8.9361636 | P6: 购电协议；接替伊州零排放补贴，支持延寿 | Q6: Constellation 新闻稿：与 Meta 签署 20 年伊利诺伊核电协议 | R6: 2025-06-03 | S6: https://www.constellationenergy.com/news/2025/constellation-meta-sign-20-year-deal-for-clean-reliable-nuclear-energy-in-illinois.html｜新闻稿；原始材料 10-K MD&A“Clinton 清洁能源中心” | T6: 2026-10-22 | U6: 披露事实 | V6: 10-K 物业表中 Clinton 净装机 1092 MW | W6: CEG_META
A7: PPA-03 | B7: 亚马逊（AWS） | C7: 亚马逊 | D7: Talen Energy | E7: Susquehanna（宾州，PJM） | F7: 现役 | G7: 现役/增容 | H7: 确定 | I7: 1920 | J7: 0 | K7: 17 | L7: 逐步爬坡，最迟 2032 年满量 | M7: 2025-06-11 | N7: 是 | O7: =IF(N7="是",I7*'假设'!$C$11*'假设'!$C$12/1000000,0) -> 15.305472 | P7: 电网侧零售供电；过渡期 300 MW 表后 | Q7: Talen Energy 8-K：扩大与亚马逊的核电合作 | R7: 2025-06-11 | S7: https://www.sec.gov/Archives/edgar/data/1622536/000162828025030559/a20250611pressreleasebusin.htm｜8-K 新闻稿与投资者演示 | T7: 2026-10-22 | U7: 披露事实 | V7: 17 年名义收入约 180 亿美元（非价格） | W7: TALEN25
A8: PPA-04 | B8: 亚马逊（AWS） | C8: 亚马逊 | D8: Vistra | E8: Comanche Peak（得州，ERCOT） | F8: 现役 | G8: 现役/增容 | H8: 确定 | I8: 1200 | J8: 0 | K8: 20 | L8: 2027Q4 起，2032 年满量 | M8: 2026-02-26（披露买方） | N8: 是 | O8: =IF(N8="是",I8*'假设'!$C$11*'假设'!$C$12/1000000,0) -> 9.56592 | P8: 购电协议；物理结构未披露 | Q8: Vistra 2025 年四季度及全年业绩新闻稿（Comanche Peak 与 AWS 协议） | R8: 2026-02-26 | S8: https://investor.vistracorp.com/2026-02-26-Vistra-Reports-Fourth-Quarter-and-Full-Year-2025-Results｜业绩新闻稿 | T8: 2026-10-22 | U8: 披露事实 | V8: 2025-09-29 8-K 首次披露时未点名买方 | W8: VST_4Q25
A9: PPA-05 | B9: Meta | C9: Meta | D9: Vistra | E9: Perry、Davis-Besse（俄亥俄）及 Beaver Valley 增容（宾州），PJM | F9: 现役 + 增容 | G9: 现役/增容 | H9: 确定 | I9: 2609 | J9: 433 | K9: 20 | L9: 2026 年底起；增容 2031–2034 | M9: 2026-01-09 | N9: 是 | O9: =IF(N9="是",I9*'假设'!$C$11*'假设'!$C$12/1000000,0) -> 20.797904 | P9: 电量 + 容量购电协议，电力继续进入电网 | Q9: Vistra 8-K：与 Meta 签署核电购电协议 | R9: 2026-01-09 | S9: https://www.sec.gov/Archives/edgar/data/1692819/000119312526008508/d20785d8k.htm｜8-K | T9: 2026-10-22 | U9: 披露事实 | V9: 能源部 42 亿美元有条件承诺支持 433 MW 增容（2026-10-05） | W9: VST_META
A10: PPA-06 | B10: Google | C10: Google | D10: NextEra | E10: Duane Arnold（艾奥瓦，MISO） | F10: 重启 | G10: 重启 | H10: 确定 | I10: 615 | J10: 615 | K10: 25 | L10: 2029Q1 前 | M10: 2025-10-27 | N10: 是 | O10: =IF(N10="是",I10*'假设'!$C$11*'假设'!$C$12/1000000,0) -> 4.902534 | P10: 购电协议（其余电量由 CIPCO 按相同条款购买） | Q10: NextEra 新闻稿：与 Google 合作重启 Duane Arnold | R10: 2025-10-27 | S10: https://investor.nexteraenergy.com/news-and-events/news-releases/2025/10-27-2025-203948689｜新闻稿 | T10: 2026-10-22 | U10: 披露事实 | V10: 能源部 19 亿美元贷款于 2026-09-08 完成 | W10: NEE_GOOG
A11: PPA-07 | B11: 亚马逊（AWS） | C11: 亚马逊 | D11: Constellation | E11: Calvert Cliffs（马里兰，PJM） | F11: 现役 + 增容 | G11: 现役/增容 | H11: 确定 | I11: 690 | J11: 190 | K11: 20 | L11: 增容 2030–2032 | M11: 2026-09-30 | N11: 是 | O11: =IF(N11="是",I11*'假设'!$C$11*'假设'!$C$12/1000000,0) -> 5.500404 | P11: 购电协议 + PJM 零售供电；电力继续进入电网 | Q11: Constellation 新闻稿：与亚马逊签署 Calvert Cliffs 20 年购电协议 | R11: 2026-09-30 | S11: https://www.constellationenergy.com/news/2026/09/constellation-and-amazon-announce-20-year-power-purchase-agreement-at-calvert-cliffs.html｜新闻稿 | T11: 2026-10-22 | U11: 披露事实 | V11: Constellation 投资超 30 亿美元并延寿 20 年 | W11: CEG_AMZN
A12: PPA-08 | B12: Google | C12: Google | D12: Constellation | E12: 伊利诺伊、宾州、新泽西 11 台机组增容（PJM） | F12: 增容 | G12: 现役/增容 | H12: 确定 | I12: 890 | J12: 890 | K12: 20 | L12: 首批 2028 年 | M12: 2026-10-06 | N12: 是 | O12: =IF(N12="是",I12*'假设'!$C$11*'假设'!$C$12/1000000,0) -> 7.094724 | P12: 新增容量购电协议 | Q12: Constellation 新闻稿：Google 与 Constellation 宣布为 PJM 带来 890 MW 新增核电容量 | R12: 2026-10-06 | S12: https://www.constellationenergy.com/news/2026/10/google-and-constellation-announce-landmark-agreement-to-bring-890-mw-of-new-nuclear-capacity-to-pjm-grid.html｜新闻稿 | T12: 2026-10-22 | U12: 披露事实 | V12: Constellation 新增投资超 43 亿美元 | W12: CEG_GOOG
A13: PPA-09 | B13: Google | C13: Google | D13: 佐治亚电力 | E13: Vogtle 1–2、Hatch 1–2 增容（佐治亚） | F13: 增容 | G13: 现役/增容 | H13: 确定（待州监管批准） | I13: 96 | J13: 96 | L13: 未披露 | M13: 2026-09-21 | N13: 是 | O13: =IF(N13="是",I13*'假设'!$C$11*'假设'!$C$12/1000000,0) -> 0.7652736 | P13: 新设 NU-1 认购电价，Google 获得零排放证书 | Q13: 佐治亚电力新闻稿：与 Google 签署核电增容协议 | R13: 2026-09-21 | S13: https://www.georgiapower.com/news-hub/press-releases/agreement-with-google-provides-$900-million-customer-benefits-advances-nuclear-energy.html｜新闻稿 | T13: 2026-10-22 | U13: 披露事实 | V13: 约 96 MW 为佐治亚电力份额 | W13: GPC_GOOG
A14: PPA-10 | B14: Google | C14: Google | D14: Constellation | E14: PJM 现役机组（能源供应合同） | F14: 现役（供电合同） | G14: 供电合同 | H14: 确定 | I14: 2700 | J14: 0 | K14: 15 | L14: 未披露 | M14: 2026-10-06 | N14: 否 | O14: =IF(N14="是",I14*'假设'!$C$11*'假设'!$C$12/1000000,0) -> 0 | P14: 15 年能源供应协议，不是新增容量 | Q14: Constellation 新闻稿：Google 与 Constellation 宣布为 PJM 带来 890 MW 新增核电容量 | R14: 2026-10-06 | S14: https://www.constellationenergy.com/news/2026/10/google-and-constellation-announce-landmark-agreement-to-bring-890-mw-of-new-nuclear-capacity-to-pjm-grid.html｜新闻稿 | T14: 2026-10-22 | U14: 披露事实 | V14: 与 PPA-08 同日签署；单独统计，不计入购电协议合计 | W14: CEG_GOOG
A15: PPA-11 | B15: Meta | C15: Meta | D15: TerraPower | E15: Natrium 先进堆（最多 8 台，场址待定） | F15: 先进堆 | G15: 先进堆/小堆 | H15: 开发资金 + 电量权利 | I15: 2760 | L15: 最早 2032 年，其余至 2035 年 | M15: 2026-01-09 | N15: 否 | O15: =IF(N15="是",I15*'假设'!$C$11*'假设'!$C$12/1000000,0) -> 0 | P15: 2 台确定（690 MW）+ 6 台选择权 | Q15: TerraPower 新闻稿：与 Meta 签署 8 座 Natrium 先进核电站协议 | R15: 2026-01-09 | S15: https://www.terrapower.com/terrapower-announces-deal-with-meta｜新闻稿 | T15: 2026-10-22 | U15: 公司目标 | V15: 首座 Natrium（Kemmerer 1 号）2026 年 4 月开工，目标 2030 年 | W15: TP_META
A16: PPA-12 | B16: Meta | C16: Meta | D16: Oklo | E16: Pike 县园区（俄亥俄） | F16: 先进堆 | G16: 先进堆/小堆 | H16: 预付电费 + 项目资金 | I16: 1200 | L16: 最早 2030 年，2034 年满量 | M16: 2026-01-09 | N16: 否 | O16: =IF(N16="是",I16*'假设'!$C$11*'假设'!$C$12/1000000,0) -> 0 | P16: “最多 1.2 GW” | Q16: Oklo 与 Meta 宣布支持俄亥俄 1.2 GW 核能开发（Business Wire；页面拒绝访问，据检索摘录与世界核新闻） | R16: 2026-01-09 | S16: https://wnn.world-nuclear.org/articles/meta-announces-landmark-agreements-for-new-nuclear｜世界核新闻转述；Business Wire 原稿拒绝访问 | T16: 2026-10-22 | U16: 公司目标 | W16: OKLO_META
A17: PPA-13 | B17: Google | C17: Google | D17: Kairos Power | E17: KP-FHR 熔盐堆（含经 TVA 的 Hermes 2，50 MW） | F17: 先进堆 | G17: 先进堆/小堆 | H17: 框架协议 | I17: 500 | L17: 首台 2030 年，2035 年前 | M17: 2024-10-14 | N17: 否 | O17: =IF(N17="是",I17*'假设'!$C$11*'假设'!$C$12/1000000,0) -> 0 | P17: 主开发协议 + 购电协议 | Q17: Kairos Power 新闻：与 Google 合作部署 500 MW | R17: 2024-10-14 | S17: https://kairospower.com/updates/google-and-kairos-power-partner-to-deploy-500-mw-of-clean-electricity-generation｜新闻稿 | T17: 2026-10-22 | U17: 公司目标 | W17: KAIROS24
A18: PPA-14 | B18: Google | C18: Google | D18: Elementl Power | E18: 三处先进核电场址（每处 ≥600 MW） | F18: 先进堆 | G18: 先进堆/小堆 | H18: 早期开发资金 + 购电选择权 | I18: 1800 | L18: 约 2035 年 | M18: 2025-05-07 | N18: 否 | O18: =IF(N18="是",I18*'假设'!$C$11*'假设'!$C$12/1000000,0) -> 0 | P18: 技术路线未定 | Q18: Google 官方博客：与 Elementl 合作开发三处先进核电场址 | R18: 2025-05-07 | S18: https://blog.google/feed/google-and-elementl-nuclear-energy-site-development/｜官方博客 | T18: 2026-10-22 | U18: 公司目标 | W18: ELEMENTL
A19: PPA-15 | B19: 亚马逊 | C19: 亚马逊 | D19: Energy Northwest / X-energy | E19: Cascade（华盛顿州） | F19: 小型模块堆 | G19: 先进堆/小堆 | H19: 开发资金 | I19: 320 | L19: 2030 年代初 | M19: 2024-10-16 | N19: 否 | O19: =IF(N19="是",I19*'假设'!$C$11*'假设'!$C$12/1000000,0) -> 0 | P19: 一期约 320 MW，可扩至 960 MW | Q19: 亚马逊新闻：签署先进核能项目协议（Energy Northwest、Dominion） | R19: 2024-10-16 | S19: https://www.aboutamazon.com/news/sustainability/amazon-nuclear-small-modular-reactor-net-carbon-zero｜新闻 | T19: 2026-10-22 | U19: 公司目标 | V19: 属亚马逊–X-energy“2039 年前超过 5 GW”目标 | W19: AMZN_NUC
A20: PPA-16 | B20: 亚马逊 | C20: 亚马逊 | D20: Dominion Energy | E20: North Anna 附近小堆（弗吉尼亚，PJM） | F20: 小型模块堆 | G20: 先进堆/小堆 | H20: 探索协议 | I20: 300 | L20: 未披露 | M20: 2024-10-16 | N20: 否 | O20: =IF(N20="是",I20*'假设'!$C$11*'假设'!$C$12/1000000,0) -> 0 | P20: “至少 300 MW” | Q20: 亚马逊新闻：签署先进核能项目协议（Energy Northwest、Dominion） | R20: 2024-10-16 | S20: https://www.aboutamazon.com/news/sustainability/amazon-nuclear-small-modular-reactor-net-carbon-zero｜新闻 | T20: 2026-10-22 | U20: 公司目标 | W20: AMZN_NUC
A21: PPA-17 | B21: 亚马逊 | C21: 亚马逊 | D21: X-energy + AEP | E21: Sullivan 县（印第安纳） | F21: 小型模块堆 | G21: 先进堆/小堆 | H21: 联合开发协议 | I21: 960 | L21: 未披露 | M21: 2026-10-19 | N21: 否 | O21: =IF(N21="是",I21*'假设'!$C$11*'假设'!$C$12/1000000,0) -> 0 | P21: 12 台 Xe-100；亚马逊按里程碑提供开发资金 | Q21: X-energy 新闻：与亚马逊、AEP 在印第安纳推进小堆项目 | R21: 2026-10-19 | S21: https://x-energy.com/news/x-energy-amazon-american-electric-power-partner-to-bring-smr-project-to-indiana/｜新闻 | T21: 2026-10-22 | U21: 公司目标 | W21: XE_AEP
A22: PPA-18 | B22: 甲骨文 | C22: 甲骨文 | D22: We Energies（Point Beach 电量） | E22: Point Beach（威斯康星，MISO） | F22: 现役（认购） | G22: 现役/增容 | H22: 待州监管批准 | J22: 0 | L22: 未披露 | M22: 2026-10-02 | N22: 否 | O22: =IF(N22="是",I22*'假设'!$C$11*'假设'!$C$12/1000000,0) -> 0 | P22: 认购 We Energies 所购 Point Beach 电量的一部分（份额仅见二手报道：10–20%） | Q22: We Energies 新闻：与甲骨文的 Point Beach 认购协议 | R22: 2026-10-02 | S22: https://news.we-energies.com/we-energies-agreement-with-oracle-expected-to-save-customers-approximately-300-million/｜新闻 | T22: 2026-10-22 | U22: 披露事实 | V22: MW 未披露，不计入合计 | W22: WE_ORCL
A23: PPA-19 | B23: CyrusOne | C23: 其他 | D23: Constellation（Calpine） | E23: Freestone 与 Thad Hill 燃气电站旁数据中心（得州，ERCOT） | F23: 燃气（共址） | G23: 燃气 | H23: 确定 + 独家 | I23: 1160 | L23: 未披露 | M23: 2026-02-09 | N23: 否 | O23: =IF(N23="是",I23*'假设'!$C$11*'假设'!$C$12/1000000,0) -> 0 | P23: Freestone 380 MW + 二期 380 MW（独家）+ Thad Hill 400 MW | Q23: Constellation 新闻稿：与 CyrusOne 在得州 Freestone 能源中心建数据中心 | R23: 2026-02-09 | S23: https://www.constellationenergy.com/news/2026/02/constellation-and-cyrusone-announce-agreement-to-support-new-data-center-facility-at-freestone-energy-center-in-texas.html｜新闻稿；原始材料 10-Q“Freestone 新数据中心设施” | T23: 2026-10-22 | U23: 披露事实 | V23: 燃气，不是核电 | W23: CEG_CYRUS
A24: PPA-20 | B24: 沃尔玛 | C24: 其他 | D24: Constellation | E24: Dresden（伊利诺伊，PJM） | F24: 现役 + 增容 | G24: 现役/增容 | H24: 确定 | I24: 176 | J24: 30 | K24: 20 | L24: 2029–2032 | M24: 2026-08-06 | N24: 否 | O24: =IF(N24="是",I24*'假设'!$C$11*'假设'!$C$12/1000000,0) -> 0 | P24: 属二季度新签 920 MW 核电长约的一部分（非科技公司，作对照） | Q24: Constellation Energy Corp. 10-Q 季报（截至 2026-06-30 的季度） | R24: 2026-08-06（签署日） | S24: 材料/Constellation_2026Q2季报__ceg-20260630.htm｜原始材料 10-Q“长期核电购电协议” | T24: 原始材料 | U24: 披露事实 | W24: M3

Sheet D7_聚变
A1: D7 聚变：行业融资、公司融资、与科技公司的购电/承购协议、时间表
A2: 蓝底=输入（披露数据）；橙底=输入（假设）；绿底=公式（本表计算）。“出处定位”给出原始材料的文件与章节，或网页链接；“访问日期”为网页查阅日期。
A4: 编号 | B4: 类别 | C4: 指标 | D4: 主体/地区 | E4: 数值 | F4: 单位 | G4: 期间 | H4: 性质 | I4: 口径说明 | J4: 来源名称 | K4: 发布日期 | L4: 出处定位（文件章节/表名或网页链接） | M4: 访问日期 | N4: 来源编号
A5: FU-01 | B5: 产业 | C5: 聚变企业过去 12 个月融资额 | D5: 全球（FIA 调查） | E5: 4.48 | F5: 十亿美元 | G5: 截至 2026-07 | H5: 披露事实 | I5: 56 家企业；同比 +69%，2021 年有调查以来最高 | J5: 聚变产业协会（FIA）新闻稿：年度融资创纪录 44.8 亿美元，累计 142.4 亿美元 | K5: 2026-07-13 | L5: https://www.fusionindustryassociation.org/fusion-industry-attracts-record-annual-funding-of-4-48bn-raising-total-to-14-24bn/｜新闻稿 | M5: 2026-10-22 | N5: FIA26
A6: FU-02 | B6: 产业 | C6: 聚变企业累计融资额 | D6: 全球（FIA 调查） | E6: 14.24 | F6: 十亿美元 | G6: 截至 2026-07 | H6: 披露事实 | I6: 自 2021 年调查起累计 | J6: 聚变产业协会（FIA）新闻稿：年度融资创纪录 44.8 亿美元，累计 142.4 亿美元 | K6: 2026-07-13 | L6: https://www.fusionindustryassociation.org/fusion-industry-attracts-record-annual-funding-of-4-48bn-raising-total-to-14-24bn/｜新闻稿 | M6: 2026-10-22 | N6: FIA26
A7: FU-03 | B7: 产业 | C7: 受访聚变企业数量 | D7: 全球（FIA 调查） | E7: 56 | F7: 家 | G7: 2026-07 | H7: 披露事实 | I7: 2021 年为 23 家 | J7: 聚变产业协会（FIA）新闻稿：年度融资创纪录 44.8 亿美元，累计 142.4 亿美元 | K7: 2026-07-13 | L7: https://www.fusionindustryassociation.org/fusion-industry-attracts-record-annual-funding-of-4-48bn-raising-total-to-14-24bn/｜新闻稿 | M7: 2026-10-22 | N7: FIA26
A8: FU-04 | B8: 产业 | C8: 预计 2030 年代实现商业供电的企业比例 | D8: 全球（FIA 调查） | E8: 0.71 | F8: % | G8: 2026-07 | H8: 披露事实 | I8: 企业自我预期，非独立判断 | J8: 聚变产业协会（FIA）新闻稿：年度融资创纪录 44.8 亿美元，累计 142.4 亿美元 | K8: 2026-07-13 | L8: https://www.fusionindustryassociation.org/fusion-industry-attracts-record-annual-funding-of-4-48bn-raising-total-to-14-24bn/｜新闻稿 | M8: 2026-10-22 | N8: FIA26
A9: FU-05 | B9: 产业 | C9: 已签购电/承购或类似承诺的企业数 | D9: 全球（FIA 调查） | E9: 5 | F9: 家 | G9: 2026-07 | H9: 披露事实 | I9: 另有 2 家在谈 | J9: 聚变产业协会（FIA）新闻稿：年度融资创纪录 44.8 亿美元，累计 142.4 亿美元 | K9: 2026-07-13 | L9: https://www.fusionindustryassociation.org/fusion-industry-attracts-record-annual-funding-of-4-48bn-raising-total-to-14-24bn/｜新闻稿 | M9: 2026-10-22 | N9: FIA26
A10: FU-06 | B10: 产业 | C10: 聚变企业过去 12 个月融资额 | D10: 全球（FIA 调查） | E10: 2.64 | F10: 十亿美元 | G10: 截至 2025-07 | H10: 披露事实 | J10: 聚变产业协会（FIA）新闻稿：过去一年聚变产业投资超 25 亿美元 | K10: 2025-07-22 | L10: https://www.fusionindustryassociation.org/over-2-5-billion-invested-in-fusion-industry-in-past-year/｜新闻稿 | M10: 2026-10-22 | N10: FIA25
A11: FU-07 | B11: 产业 | C11: 聚变企业累计融资额 | D11: 全球（FIA 调查） | E11: 9.766 | F11: 十亿美元 | G11: 截至 2025-07 | H11: 披露事实 | I11: 53 家企业 | J11: 聚变产业协会（FIA）新闻稿：过去一年聚变产业投资超 25 亿美元 | K11: 2025-07-22 | L11: https://www.fusionindustryassociation.org/over-2-5-billion-invested-in-fusion-industry-in-past-year/｜新闻稿 | M11: 2026-10-22 | N11: FIA25
A12: FU-C01 | B12: 公司融资 | C12: Commonwealth Fusion Systems（CFS）累计融资 | D12: CFS（美国，高温超导托卡马克） | E12: 4 | F12: 十亿美元 | G12: 2026-07-30 | H12: 披露事实 | I12: 投资方含 Google、NVIDIA（NVentures）、Eni 等 | J12: CFS 新闻稿：再融资 10 亿美元，累计 40 亿美元 | K12: 2026-07-30 | L12: https://cfs.energy/news-and-media/commonwealth-fusion-systems-raises-another-1-billion-bringing-total-capital-raised-to-4-billion/｜新闻稿 | M12: 2026-10-22 | N12: CFS_1B
A13: FU-C02 | B13: 公司融资 | C13: Helion 累计融资 | D13: Helion（美国，脉冲场反位形） | E13: 1.5 | F13: 十亿美元 | G13: 2026-06-04 | H13: 披露事实 | I13: G 轮首关 4.65 亿美元后累计；9 月最终关账 5 亿美元；投后估值 155 亿美元 | J13: Helion 新闻：完成 4.65 亿美元 G 轮（2026 年 9 月更新：最终 5 亿美元） | K13: 2026-06-04 | L13: https://www.helionenergy.com/newsroom/helion-raises-465-million-series-g-funding-round-to-meet-surging-global-demand-for-power｜新闻稿 | M13: 2026-10-22 | N13: HEL_G
A14: FU-C03 | B14: 公司融资 | C14: TAE Technologies 累计股权融资 | D14: TAE（美国，束流驱动场反位形） | E14: 1.3 | F14: 十亿美元 | G14: 2025-06-02 | H14: 披露事实 | I14: 原文“超过 13 亿美元”；另与 TMTG 合并（估值超 60 亿美元）待完成 | J14: TAE 新闻：完成 1.5 亿美元融资（累计股权融资超 13 亿美元） | K14: 2025-06-02 | L14: https://tae.com/tae-technologies-raises-150-million-in-latest-funding-round/｜新闻稿 | M14: 2026-10-22 | N14: TAE_150
A15: FU-C04 | B15: 公司融资 | C15: Pacific Fusion A 轮承诺 | D15: Pacific Fusion（美国，脉冲功率惯性） | E15: 0.9 | F15: 十亿美元 | G15: 2024-10-25 | H15: 披露事实 | I15: 原文“超过 9 亿美元”，按里程碑释放 | J15: Pacific Fusion 创始人信（A 轮 9 亿美元以上） | K15: 2024-10-25 | L15: https://www.pacificfusion.com/updates/founders-letter｜创始人信 | M15: 2026-10-22 | N15: PAC_A
A16: FU-C05 | B16: 公司融资 | C16: Proxima Fusion 累计融资 | D16: Proxima（德国，仿星器） | E16: 0.74 | F16: 十亿美元 | G16: 2026-07-07 | H16: 披露事实 | I16: 超过 6.5 亿欧元（含 9500 万欧元公共资助），公司给出的美元数 | J16: Proxima Fusion 新闻：融资 4.11 亿欧元 | K16: 2026-07-07 | L16: https://www.proximafusion.com/press-news/proxima-fusion-raises-eu411-million-to-build-europes-commercial-fusion-champion｜新闻稿 | M16: 2026-10-22 | N16: PROXIMA
A17: FU-C06 | B17: 公司融资 | C17: Inertia Enterprises A 轮 | D17: Inertia（美国，激光惯性） | E17: 0.45 | F17: 十亿美元 | G17: 2026-02 | H17: 披露事实 | I17: GV（Alphabet）参投（二手） | J17: Nuclear Engineering International：Inertia 完成 A 轮 | K17: 2026-02-18 | L17: https://www.neimagazine.com/news/inertia-secures-series-a-fusion-funding/｜报道正文 | M17: 2026-10-22 | N17: NEI_INERTIA
A18: FU-C07 | B18: 公司融资 | C18: General Fusion 上市前累计融资 | D18: General Fusion（加拿大，磁化靶） | E18: 0.4 | F18: 十亿美元 | G18: 2026-01-22 | H18: 披露事实 | I18: 原文“超过 4 亿美元”；2026-07 经 SPAC 上市 | J18: General Fusion 新闻：与 Spring Valley III 合并上市 | K18: 2026-01-22 | L18: https://generalfusion.com/post/general-fusion-business-combination-announcement/｜新闻稿 | M18: 2026-10-22 | N18: GF_SPAC
A19: FU-C08 | B19: 公司融资 | C19: Tokamak Energy 累计融资 | D19: Tokamak Energy（英国，球形托卡马克） | E19: 0.335 | F19: 十亿美元 | G19: 2024-11-20 | H19: 披露事实 | I19: 私人 2.75 亿 + 政府 0.6 亿美元 | J19: Tokamak Energy 新闻：融资 1.25 亿美元 | K19: 2024-11-20 | L19: https://tokamakenergy.com/?p=7447｜新闻稿 | M19: 2026-10-22 | N19: TE_125
A20: FU-C09 | B20: 公司融资 | C20: Zap Energy 累计融资 | D20: Zap（美国，剪切流 Z 箍缩） | E20: 0.33 | F20: 十亿美元 | G20: 2024-10-09 | H20: 披露事实 | I20: 原文“超过 3.3 亿美元” | J20: Zap Energy 新闻：D 轮 1.3 亿美元 | K20: 2024-10-09 | L20: https://legacy.zapenergy.com/news/zap-attracts-130m-as-demo-system-begins-operations｜新闻稿 | M20: 2026-10-22 | N20: ZAP_D
A21: FU-C10 | B21: 公司融资 | C21: Type One Energy B 轮 | D21: Type One（美国，仿星器） | E21: 0.2 | F21: 十亿美元 | G21: 2026-10-06 | H21: 披露事实 | I21: 累计总额未披露；Infinity Two 规划 400 MWe | J21: Type One Energy 新闻：完成 2 亿美元 B 轮 | K21: 2026-10-06 | L21: https://typeoneenergy.com/insights-announcements/type-one-energy-completes-200m-series-b-financing/｜新闻稿 | M21: 2026-10-22 | N21: T1_B
A22: FU-C11 | B22: 公司融资 | C22: 中国聚变能源有限公司注册资本 | D22: 中国（中核集团控股） | E22: 15 | F22: 十亿元人民币 | G22: 2025-07 | H22: 披露事实 | I22: 国有企业注册资本，非风险投资；二手报道 | J22: 上海证券报：中国核电增资中国聚变能源有限公司（注册资本 150 亿元） | K22: 2025-07-23 | L22: https://paper.cnstock.com/html/2025-07/23/content_2097106.htm｜报道正文 | M22: 2026-10-22 | N22: CN_CFEC
... A37: FU-T10 | B37: 时间表 | C37: General Fusion 首座电站目标 | D37: General Fusion | E37: 2035 | F37: 年 | G37: 2026-08 | H37: 公司目标 | I37: 原文“约 2035 年” | J37: General Fusion 新闻：上市后首次业务更新 | K37: 2026-08-18 | L37: https://generalfusion.com/post/general-fusion-provides-first-public-company-business-update/｜新闻 | M37: 2026-10-22 | N37: GF_UPD

Sheet D8_成本与瓶颈
A1: D8 成本与瓶颈：燃机、度电成本、PJM 容量市场、电价、并网、设备、造价、政策
A2: 蓝底=输入（披露数据）；橙底=输入（假设）；绿底=公式（本表计算）。“出处定位”给出原始材料的文件与章节，或网页链接；“访问日期”为网页查阅日期。
A4: 编号 | B4: 类别 | C4: 指标 | D4: 主体/地区 | E4: 数值 | F4: 单位 | G4: 期间 | H4: 性质 | I4: 口径说明 | J4: 来源名称 | K4: 发布日期 | L4: 出处定位（文件章节/表名或网页链接） | M4: 访问日期 | N4: 来源编号
A5: COST-01 | B5: 燃气轮机 | C5: GE Vernova 燃机积压订单 + 产能预留协议 | D5: GE Vernova | E5: 62 | F5: GW | G5: 2025Q3 末 | H5: 披露事实 | I5: 预留协议不是确定订单 | J5: GE Vernova 2025 年四季度及全年业绩新闻稿 | K5: 2026-01-28 | L5: https://www.gevernova.com/news/articles/ge-vernova-releases-fourth-quarter-full-year-2025-financial｜新闻稿“从 62 GW 增至 83 GW” | M5: 2026-10-22 | N5: GEV4Q25
A6: COST-02 | B6: 燃气轮机 | C6: GE Vernova 燃机积压订单 + 产能预留协议 | D6: GE Vernova | E6: 83 | F6: GW | G6: 2025Q4 末 | H6: 披露事实 | I6: 同上 | J6: GE Vernova 2025 年四季度及全年业绩新闻稿 | K6: 2026-01-28 | L6: https://www.gevernova.com/news/articles/ge-vernova-releases-fourth-quarter-full-year-2025-financial｜同上 | M6: 2026-10-22 | N6: GEV4Q25
A7: COST-03 | B7: 燃气轮机 | C7: GE Vernova 燃机积压订单 + 产能预留协议 | D7: GE Vernova | E7: 100 | F7: GW | G7: 2026Q1 末 | H7: 披露事实 | I7: 同上 | J7: GE Vernova 2026 年一季度业绩新闻稿（8-K 附件） | K7: 2026-04-22 | L7: https://www.sec.gov/Archives/edgar/data/0001996810/000199681026000063/gevpressrelease1q26.htm｜新闻稿 | M7: 2026-10-22 | N7: GEV1Q26
A8: COST-04 | B8: 燃气轮机 | C8: GE Vernova 燃机积压订单 + 产能预留协议 | D8: GE Vernova | E8: 116 | F8: GW | G8: 2026Q2 末 | H8: 披露事实 | I8: 同上 | J8: GE Vernova 2026 年二季度业绩新闻稿（8-K 附件） | K8: 2026-07-22 | L8: https://www.sec.gov/Archives/edgar/data/0001996810/000199681026000147/gevpressrelease2q26.htm｜新闻稿“从 100 GW 增至 116 GW” | M8: 2026-10-22 | N8: GEV2Q26
A9: COST-05 | B9: 燃气轮机 | C9: GE Vernova 2026 年底在手目标 | D9: GE Vernova | E9: 125 | F9: GW | G9: 2026 年底 | H9: 公司指引 | I9: “至少 125 GW” | J9: GE Vernova 2026 年二季度业绩新闻稿（8-K 附件） | K9: 2026-07-22 | L9: https://www.sec.gov/Archives/edgar/data/0001996810/000199681026000147/gevpressrelease2q26.htm｜新闻稿 | M9: 2026-10-22 | N9: GEV2Q26
A10: COST-06 | B10: 燃气轮机 | C10: GE Vernova 燃机年产能 | D10: GE Vernova | E10: 20 | F10: GW/年 | G10: 2026 | H10: 公司指引 | I10: 2028 年 24 GW，2030 年 30 GW | J10: GE Vernova 2026 年二季度业绩新闻稿（8-K 附件） | K10: 2026-07-22 | L10: https://www.sec.gov/Archives/edgar/data/0001996810/000199681026000147/gevpressrelease2q26.htm｜新闻稿 | M10: 2026-10-22 | N10: GEV2Q26
A11: COST-07 | B11: 燃气轮机 | C11: GE Vernova 燃机年产能目标 | D11: GE Vernova | E11: 30 | F11: GW/年 | G11: 2030 | H11: 公司指引 | J11: GE Vernova 2026 年二季度业绩新闻稿（8-K 附件） | K11: 2026-07-22 | L11: https://www.sec.gov/Archives/edgar/data/0001996810/000199681026000147/gevpressrelease2q26.htm｜新闻稿 | M11: 2026-10-22 | N11: GEV2Q26
A12: COST-08 | B12: 燃气轮机 | C12: 西门子能源燃机积压订单 | D12: 西门子能源 | E12: 69 | F12: GW | G12: 2026Q2（FY26 Q3） | H12: 第三方估计 | I12: 交期 3 年以上（媒体转述） | J12: Utility Dive：西门子能源燃机积压订单接近 70 GW | K12: 2026-08-10 | L12: https://www.utilitydive.com/news/siemens-gas-turbine-backlog-nears-70-gw-as-company-expands-manufacturing/827390/｜报道正文 | M12: 2026-10-22 | N12: SIE_UD
A13: COST-09 | B13: 燃气轮机 | C13: 三菱重工大型燃机积压订单 | D13: 三菱重工 | E13: 35 | F13: GW | G13: 2026Q2 | H13: 第三方估计 | I13: 新订单交付期 2028–2030 年（媒体转述） | J13: Utility Dive：三菱重工燃机积压订单报道 | K13: 2026-08-13 | L13: https://www.utilitydive.com/news/mitsubishi-gas-turbine-backlog-earnings/827761/｜报道正文 | M13: 2026-10-22 | N13: MHI_UD
A14: COST-10 | B14: 燃气轮机 | C14: 燃气轮机设备价格（2027 年底预测） | D14: 美国市场 | E14: 600 | F14: 美元/kW | G14: 2027E | H14: 第三方估计 | I14: 较 2019 年 +195%；仅设备 | J14: Wood Mackenzie 新闻稿：燃气轮机价格较 2019 年上涨 195% | K14: 2026-04-01 | L14: https://www.woodmac.com/press-releases/gas-turbine-prices-soar-195-as-market-faces-supply-demand-crisis/｜新闻稿 | M14: 2026-10-22 | N14: WM_GT
A15: COST-11 | B15: 燃气电站造价 | C15: 联合循环电站造价（2022 年完工项目） | D15: NextEra | E15: 785 | F15: 美元/kW | G15: 2022 | H15: 第三方估计 | I15: CEO 公开发言 | J15: Power Engineering：NextEra CEO 谈燃气电站造价（CERAWeek 发言） | K15: 2025-03-10 | L15: https://www.power-eng.com/renewables/nextera-ceo-warns-against-scorning-renewable-generation-amidst-long-lead-times-for-gas-and-nuclear-development/｜报道正文 | M15: 2026-10-22 | N15: NEE_CEO
A16: COST-12 | B16: 燃气电站造价 | C16: 联合循环电站造价（2025 年新建） | D16: NextEra | E16: 2400 | F16: 美元/kW | G16: 2025 | H16: 第三方估计 | I16: CEO 公开发言，“三倍多” | J16: Power Engineering：NextEra CEO 谈燃气电站造价（CERAWeek 发言） | K16: 2025-03-10 | L16: https://www.power-eng.com/renewables/nextera-ceo-warns-against-scorning-renewable-generation-amidst-long-lead-times-for-gas-and-nuclear-development/｜报道正文 | M16: 2026-10-22 | N16: NEE_CEO
A17: COST-13 | B17: 燃气电站造价 | C17: 美国联合循环隔夜造价 | D17: BloombergNEF | E17: 2157 | F17: 美元/kW | G17: 2025 | H17: 第三方估计 | I17: 2023 年低于 1500，+66% | J17: Hoodline 转述 BloombergNEF：美国燃气联合循环造价上涨 66% | K17: 2026-04-23 | L17: https://hoodline.com/2026/04/sticker-shock-as-u-s-gas-plant-costs-soar-66-percent/｜报道正文 | M17: 2026-10-22 | N17: BNEF_CC
A18: COST-20 | B18: 度电成本 | C18: 燃气联合循环 LCOE 下限 | D18: 美国 | E18: 51 | F18: 美元/MWh | G18: 2026 版 | H18: 第三方估计 | I18: 不含补贴；2025 版 48 | J18: Lazard《平准化度电成本+》2026 年版（经 Utility Dive、pv magazine 报道） | K18: 2026-07-13 | L18: https://lazard.com/news-announcements/lazard-releases-2026-levelized-cost-of-energyplus-report-pr/｜Utility Dive 2026-07-16 报道 | M18: 2026-10-22 | N18: LAZ26
A19: COST-21 | B19: 度电成本 | C19: 燃气联合循环 LCOE 上限 | D19: 美国 | E19: 129 | F19: 美元/MWh | G19: 2026 版 | H19: 第三方估计 | I19: 15 年来最高；2025 版 109 | J19: Lazard《平准化度电成本+》2026 年版（经 Utility Dive、pv magazine 报道） | K19: 2026-07-13 | L19: https://lazard.com/news-announcements/lazard-releases-2026-levelized-cost-of-energyplus-report-pr/｜同上 | M19: 2026-10-22 | N19: LAZ26
A20: COST-22 | B20: 度电成本 | C20: 燃气调峰 LCOE 下限 | D20: 美国 | E20: 144 | F20: 美元/MWh | G20: 2026 版 | H20: 第三方估计 | I20: 2025 版 149 | J20: Lazard《平准化度电成本+》2026 年版（经 Utility Dive、pv magazine 报道） | K20: 2026-07-13 | L20: https://lazard.com/news-announcements/lazard-releases-2026-levelized-cost-of-energyplus-report-pr/｜同上 | M20: 2026-10-22 | N20: LAZ26
A21: COST-23 | B21: 度电成本 | C21: 燃气调峰 LCOE 上限 | D21: 美国 | E21: 276 | F21: 美元/MWh | G21: 2026 版 | H21: 第三方估计 | I21: 2025 版 251 | J21: Lazard《平准化度电成本+》2026 年版（经 Utility Dive、pv magazine 报道） | K21: 2026-07-13 | L21: https://lazard.com/news-announcements/lazard-releases-2026-levelized-cost-of-energyplus-report-pr/｜同上 | M21: 2026-10-22 | N21: LAZ26
A22: COST-24 | B22: 度电成本 | C22: 新建核电 LCOE 下限 | D22: 美国 | E22: 175 | F22: 美元/MWh | G22: 2026 版 | H22: 第三方估计 | I22: 2025 版 141 | J22: Lazard《平准化度电成本+》2026 年版（经 Utility Dive、pv magazine 报道） | K22: 2026-07-13 | L22: https://lazard.com/news-announcements/lazard-releases-2026-levelized-cost-of-energyplus-report-pr/｜同上 | M22: 2026-10-22 | N22: LAZ26
A23: COST-25 | B23: 度电成本 | C23: 新建核电 LCOE 上限 | D23: 美国 | E23: 255 | F23: 美元/MWh | G23: 2026 版 | H23: 第三方估计 | I23: 2025 版 220 | J23: Lazard《平准化度电成本+》2026 年版（经 Utility Dive、pv magazine 报道） | K23: 2026-07-13 | L23: https://lazard.com/news-announcements/lazard-releases-2026-levelized-cost-of-energyplus-report-pr/｜同上 | M23: 2026-10-22 | N23: LAZ26
... A29: COST-31 | B29: 度电成本 | C29: 光伏 + 储能 LCOE 上限 | D29: 美国 | E29: 156 | F29: 美元/MWh | G29: 2026 版 | H29: 第三方估计 | I29: 2025 版 131 | J29: Lazard《平准化度电成本+》2026 年版（经 Utility Dive、pv magazine 报道） | K29: 2026-07-13 | L29: https://lazard.com/news-announcements/lazard-releases-2026-levelized-cost-of-energyplus-report-pr/｜同上 | M29: 2026-10-22 | N29: LAZ26
A30: COST-32 | B30: 度电成本 | C30: 燃气联合循环 LCOE 下限 | D30: 美国 | E30: 48 | F30: 美元/MWh | G30: 2025 版 | H30: 第三方估计 | J30: Lazard《平准化度电成本+》2025 年版（经 pv magazine、Mercom 报道） | K30: 2025-06-16 | L30: https://www.lazard.com/news-announcements/lazard-releases-2025-levelized-cost-of-energyplus-report-pr/｜pv magazine 2025-06-17、Mercom 报道 | M30: 2026-10-22 | N30: LAZ25
A31: COST-33 | B31: 度电成本 | C31: 燃气联合循环 LCOE 上限 | D31: 美国 | E31: 109 | F31: 美元/MWh | G31: 2025 版 | H31: 第三方估计 | J31: Lazard《平准化度电成本+》2025 年版（经 pv magazine、Mercom 报道） | K31: 2025-06-16 | L31: https://www.lazard.com/news-announcements/lazard-releases-2025-levelized-cost-of-energyplus-report-pr/｜同上 | M31: 2026-10-22 | N31: LAZ25
A32: COST-34 | B32: 度电成本 | C32: 新建核电 LCOE 下限 | D32: 美国 | E32: 141 | F32: 美元/MWh | G32: 2025 版 | H32: 第三方估计 | J32: Lazard《平准化度电成本+》2025 年版（经 pv magazine、Mercom 报道） | K32: 2025-06-16 | L32: https://www.lazard.com/news-announcements/lazard-releases-2025-levelized-cost-of-energyplus-report-pr/｜同上 | M32: 2026-10-22 | N32: LAZ25
A33: COST-35 | B33: 度电成本 | C33: 新建核电 LCOE 上限 | D33: 美国 | E33: 220 | F33: 美元/MWh | G33: 2025 版 | H33: 第三方估计 | J33: Lazard《平准化度电成本+》2025 年版（经 pv magazine、Mercom 报道） | K33: 2025-06-16 | L33: https://www.lazard.com/news-announcements/lazard-releases-2025-levelized-cost-of-energyplus-report-pr/｜同上 | M33: 2026-10-22 | N33: LAZ25
A34: COST-40 | B34: 容量市场 | C34: PJM 容量拍卖全网出清价（2024/25 交付年） | D34: PJM | E34: 28.92 | F34: 美元/MW·天 | G34: 2024/25 | H34: 披露事实 | I34: 基准对照 | J34: PJM Inside Lines：2025/26 容量拍卖结果 | K34: 2024-07-30 | L34: https://insidelines.pjm.com/pjm-capacity-auction-procures-sufficient-resources-to-meet-rto-reliability-requirement/｜公告正文 | M34: 2026-10-22 | N34: PJM2526
A35: COST-41 | B35: 容量市场 | C35: PJM 容量拍卖全网出清价（2025/26 交付年） | D35: PJM | E35: 269.92 | F35: 美元/MW·天 | G35: 2025/26 | H35: 披露事实 | I35: 拍卖于 2024-07-30 | J35: PJM Inside Lines：2025/26 容量拍卖结果 | K35: 2024-07-30 | L35: https://insidelines.pjm.com/pjm-capacity-auction-procures-sufficient-resources-to-meet-rto-reliability-requirement/｜公告正文 | M35: 2026-10-22 | N35: PJM2526
A36: COST-42 | B36: 容量市场 | C36: PJM 容量拍卖全网出清价（2026/27 交付年） | D36: PJM | E36: 329.17 | F36: 美元/MW·天 | G36: 2026/27 | H36: 披露事实 | I36: 触及 FERC 批准的价格上限 | J36: PJM Inside Lines：2026/27 容量拍卖结果 | K36: 2025-07-22 | L36: https://insidelines.pjm.com/pjm-auction-procures-134311-mw-of-generation-resources-supply-responds-to-price-signal/｜公告正文 | M36: 2026-10-22 | N36: PJM2627
A37: COST-43 | B37: 容量市场 | C37: PJM 容量拍卖全网出清价（2027/28 交付年） | D37: PJM | E37: 333.44 | F37: 美元/MW·天 | G37: 2027/28 | H37: 披露事实 | I37: 触及上限；较可靠性要求短缺约 6623 MW | J37: PJM Inside Lines：2027/28 容量拍卖结果 | K37: 2025-12-17 | L37: https://insidelines.pjm.com/?p=209684｜公告正文 | M37: 2026-10-22 | N37: PJM2728
A38: COST-44 | B38: 容量市场 | C38: PJM 容量拍卖全网出清价（2028/29 交付年） | D38: PJM | E38: ='D5_Constellation'!$E$40 -> 325 | F38: 美元/MW·天 | G38: 2028/29 | H38: 披露事实 | I38: 触及上限；与原始材料 Constellation 二季报一致（引用该行） | J38: Constellation Energy Corp. 10-Q 季报（截至 2026-06-30 的季度） | K38: 2026-08-06（签署日） | L38: 材料/Constellation_2026Q2季报__ceg-20260630.htm｜见 D5 CEG-36；另见 APPA 2026-07-14 | M38: 原始材料 | N38: M3
A39: COST-58 | B39: 容量市场 | C39: PJM 2027/28 拍卖出清容量较可靠性要求的缺口 | D39: PJM | E39: 6623 | F39: MW | G39: 2027/28 | H39: 披露事实 | I39: 首次全网低于可靠性要求 | J39: PJM Inside Lines：2027/28 容量拍卖结果 | K39: 2025-12-17 | L39: https://insidelines.pjm.com/?p=209684｜公告正文 | M39: 2026-10-22 | N39: PJM2728
A40: COST-59 | B40: 容量市场 | C40: PJM 2028/29 拍卖出清容量较可靠性要求的缺口 | D40: PJM | E40: 6831 | F40: MW | G40: 2028/29 | H40: 披露事实 | I40: 连续第二期短缺（APPA 引述 PJM 公告） | J40: 美国公共电力协会（APPA）：PJM 2028/29 容量拍卖结果报道（引用 PJM 公告） | K40: 2026-07-14 | L40: https://www.publicpower.org/periodical/article/pjm-capacity-auction-procures-138318-mw-generation-resources-capacity-price-comes-cap-325｜报道正文 | M40: 2026-10-22 | N40: APPA2829
A41: COST-45 | B41: 容量市场 | C41: PJM 2027/28 预测峰荷增量 | D41: PJM | E41: 5250 | F41: MW | G41: 2027/28 | H41: 披露事实 | I41: 其中约 5100 MW 来自数据中心 | J41: PJM Inside Lines：2027/28 容量拍卖结果 | K41: 2025-12-17 | L41: https://insidelines.pjm.com/?p=209684｜公告正文 | M41: 2026-10-22 | N41: PJM2728
A42: COST-46 | B42: 容量市场 | C42: 其中数据中心贡献 | D42: PJM | E42: 5100 | F42: MW | G42: 2027/28 | H42: 披露事实 | J42: PJM Inside Lines：2027/28 容量拍卖结果 | K42: 2025-12-17 | L42: https://insidelines.pjm.com/?p=209684｜公告正文 | M42: 2026-10-22 | N42: PJM2728
A43: COST-47 | B43: 容量市场 | C43: 最近四次容量拍卖中数据中心负荷推高的容量费用 | D43: PJM | E43: 29.4 | F43: 十亿美元 | G43: 2025/26–2028/29 | H43: 第三方估计 | I43: PJM 独立市场监察员反事实测算；约占四次拍卖总成本 636 亿美元的 46% | J43: Utility Dive：PJM 市场监察员报告数据中心负荷占批发成本 9%（引用 IMM 2026 年二季度市场报告） | K43: 2026-08-27 | L43: https://www.utilitydive.com/news/data-center-load-pjm-wholesale-market/828917/｜报道正文 | M43: 2026-10-22 | N43: IMM26
A44: COST-48 | B44: 容量市场 | C44: 四次容量拍卖总成本（2025/26–2028/29） | D44: PJM | E44: 63.6 | F44: 十亿美元 | G44: 2025/26–2028/29 | H44: 第三方估计 | I44: 147+161+164+164 亿美元，单次总额来自媒体与 APPA 报道 | J44: 俄亥俄首府日报（经 Yahoo 转载）：容量拍卖总成本报道 | K44: 2025-07-24 | L44: https://www.yahoo.com/news/articles/energy-bills-likely-tick-again-084017412.html｜报道正文；APPA 2026-07-14 | M44: 2026-10-22 | N44: PJMCOST
A45: COST-50 | B45: 电价 | C45: 美国平均零售电价（全部门） | D45: 美国 | E45: 12.94 | F45: 美分/kWh | G45: 2024 | H45: 披露事实 | I45: 名义价格 | J45: EIA《电力月报》表 5.3 终端用户平均电价 | K45: 2026-09-24 | L45: https://www.eia.gov/electricity/monthly/epm_table_grapher.php?t=epmt_5_3｜表 5.3 | M45: 2026-10-22 | N45: EIA_EPM53
A46: COST-51 | B46: 电价 | C46: 美国平均零售电价（全部门） | D46: 美国 | E46: 13.63 | F46: 美分/kWh | G46: 2025 | H46: 披露事实 | J46: EIA《电力月报》表 5.3 终端用户平均电价 | K46: 2026-09-24 | L46: https://www.eia.gov/electricity/monthly/epm_table_grapher.php?t=epmt_5_3｜表 5.3 | M46: 2026-10-22 | N46: EIA_EPM53
A47: COST-52 | B47: 电价 | C47: 美国平均零售电价（全部门，1–7 月） | D47: 美国 | E47: 14.29 | F47: 美分/kWh | G47: 2026 年 1–7 月 | H47: 披露事实 | I47: 上年同期 13.46 | J47: EIA《电力月报》表 5.3 终端用户平均电价 | K47: 2026-09-24 | L47: https://www.eia.gov/electricity/monthly/epm_table_grapher.php?t=epmt_5_3｜表 5.3 | M47: 2026-10-22 | N47: EIA_EPM53
A48: COST-53 | B48: 电价 | C48: 美国居民电价 | D48: 美国 | E48: 16.48 | F48: 美分/kWh | G48: 2024 | H48: 披露事实 | J48: EIA《电力月报》表 5.3 终端用户平均电价 | K48: 2026-09-24 | L48: https://www.eia.gov/electricity/monthly/epm_table_grapher.php?t=epmt_5_3｜表 5.3 | M48: 2026-10-22 | N48: EIA_EPM53
A49: COST-54 | B49: 电价 | C49: 美国居民电价 | D49: 美国 | E49: 17.3 | F49: 美分/kWh | G49: 2025 | H49: 披露事实 | J49: EIA《电力月报》表 5.3 终端用户平均电价 | K49: 2026-09-24 | L49: https://www.eia.gov/electricity/monthly/epm_table_grapher.php?t=epmt_5_3｜表 5.3 | M49: 2026-10-22 | N49: EIA_EPM53
A50: COST-55 | B50: 电价 | C50: 美国居民电价（预测） | D50: 美国 | E50: 18.2 | F50: 美分/kWh | G50: 2026E | H50: 官方预测 | I50: 2027 年预测 18.7 | J50: EIA《短期能源展望》2026 年 10 月版（电力、煤炭与可再生能源） | K50: 2026-10-06 | L50: https://www.eia.gov/outlooks/steo/report/elec_coal_renew.php｜表“居民电价” | M50: 2026-10-22 | N50: EIA_STEO
A51: COST-60 | B51: 并网 | C51: 美国并网排队容量：发电 | D51: 美国 | E51: 1312 | F51: GW | G51: 2025 年底 | H51: 披露事实 | I51: 另有储能约 749 GW | J51: LBNL《排队：2026 年版》Queued Up: 2026 Edition（截至 2025 年底的并网排队） | K51: 2026-05 | L51: https://eta-publications.lbl.gov/publications/queued-2026-edition-characteristics｜摘要 | M51: 2026-10-22 | N51: LBNL_Q26
A52: COST-61 | B52: 并网 | C52: 美国并网排队容量：储能 | D52: 美国 | E52: 749 | F52: GW | G52: 2025 年底 | H52: 披露事实 | J52: LBNL《排队：2026 年版》Queued Up: 2026 Edition（截至 2025 年底的并网排队） | K52: 2026-05 | L52: https://eta-publications.lbl.gov/publications/queued-2026-edition-characteristics｜摘要 | M52: 2026-10-22 | N52: LBNL_Q26
A53: COST-62 | B53: 并网 | C53: 其中燃气 | D53: 美国 | E53: 253 | F53: GW | G53: 2025 年底 | H53: 披露事实 | I53: 同比 +86% | J53: LBNL《排队：2026 年版》Queued Up: 2026 Edition（截至 2025 年底的并网排队） | K53: 2026-05 | L53: https://eta-publications.lbl.gov/publications/queued-2026-edition-characteristics｜摘要 | M53: 2026-10-22 | N53: LBNL_Q26
A54: COST-63 | B54: 并网 | C54: 从申请到投运的中位时长 | D54: 美国 | E54: 5 | F54: 年 | G54: 2025 年投运项目 | H54: 披露事实 | I54: 原文“超过 5 年” | J54: LBNL《排队：2026 年版》Queued Up: 2026 Edition（截至 2025 年底的并网排队） | K54: 2026-05 | L54: https://eta-publications.lbl.gov/publications/queued-2026-edition-characteristics｜摘要 | M54: 2026-10-22 | N54: LBNL_Q26
A55: COST-64 | B55: 并网 | C55: 2000–2020 年申请容量中已投运比例 | D55: 美国 | E55: 0.13 | F55: % | G55: 截至 2025 年底 | H55: 披露事实 | I55: 75% 已撤回 | J55: LBNL《排队：2026 年版》Queued Up: 2026 Edition（截至 2025 年底的并网排队） | K55: 2026-05 | L55: https://eta-publications.lbl.gov/publications/queued-2026-edition-characteristics｜摘要 | M55: 2026-10-22 | N55: LBNL_Q26
A56: COST-65 | B56: 并网 | C56: 主要数据中心市场的平均并网等待时间 | D56: 主要市场 | E56: 4 | F56: 年 | G56: 2026 | H56: 第三方估计 | I56: 原文“超过四年” | J56: JLL《2026 全球数据中心展望》 | K56: 2026-01-05 | L56: https://www.jll.com/en-us/insights/market-outlook/data-center-outlook｜报告正文 | M56: 2026-10-22 | N56: JLL26
A57: COST-66 | B57: 设备 | C57: 电力变压器交货期 | D57: 美国 | E57: 128 | F57: 周 | G57: 2025Q2 | H57: 第三方估计 | I57: 发电机升压变压器 144 周 | J57: POWER 杂志：2026 年的变压器（引用 Wood Mackenzie 交期与价格数据） | K57: 2026-01 | L57: https://www.powermag.com/transformers-in-2026-shortage-scramble-or-self-inflicted-crisis/｜引用 Wood Mackenzie | M57: 2026-10-22 | N57: POWER_TX
A58: COST-67 | B58: 设备 | C58: 电力变压器价格较 2019 年涨幅 | D58: 美国 | E58: 0.77 | F58: % | G58: 2019–2025 | H58: 第三方估计 | J58: POWER 杂志：2026 年的变压器（引用 Wood Mackenzie 交期与价格数据） | K58: 2026-01 | L58: https://www.powermag.com/transformers-in-2026-shortage-scramble-or-self-inflicted-crisis/｜引用 Wood Mackenzie | M58: 2026-10-22 | N58: POWER_TX
A59: COST-68 | B59: 设备 | C59: 电力变压器供应缺口 | D59: 美国 | E59: 0.3 | F59: % | G59: 2025 | H59: 第三方估计 | I59: 2026 年缺口约 15% | J59: Wood Mackenzie 新闻稿：2025 年电力变压器供应缺口 30% | K59: 2025-08-14 | L59: https://www.woodmac.com/press-releases/power-transformers-and-distribution-transformers-will-face-supply-deficits-of-30-and-10-in-2025/｜新闻稿标题 | M59: 2026-10-22 | N59: WM_TX
A60: COST-69 | B60: 可靠性 | C60: 北美 10 年夏季峰荷增量预测 | D60: 北美 | E60: 224 | F60: GW | G60: 2026–2035 | H60: 官方预测 | I60: 上一版为 132 GW；23 个评估区中 13 个风险偏高 | J60: NERC 2025 长期可靠性评估（LTRA），经 POWER 杂志报道 | K60: 2026-01-29 | L60: https://www.powermag.com/nerc-warns-long-term-grid-reliability-risks-mounting-from-surging-demand-lagging-resources/｜报道正文 | M60: 2026-10-22 | N60: NERC25
A61: COST-70 | B61: 数据中心造价 | C61: 美国新建数据中心平均开发成本 | D61: 美国 | E61: 17.6 | F61: 百万美元/MW | G61: 2026 版 | H61: 第三方估计 | I61: 最新一代设施；较上版 +21%；不含 IT 设备 | J61: Cushman & Wakefield《2026 美国数据中心开发成本指南》 | K61: 2026（年度版） | L61: https://www.cushmanwakefield.com/en/united-states/insights/data-center-development-cost-guide｜报告正文 | M61: 2026-10-22 | N61: CW26
A62: COST-71 | B62: 数据中心造价 | C62: 全球数据中心土建与机电成本 | D62: 全球 | E62: 11.3 | F62: 百万美元/MW | G62: 2026E | H62: 第三方估计 | I62: 仅主体与机电；AI 装修最高可达 2500 万美元/MW | J62: JLL《2026 全球数据中心展望》 | K62: 2026-01-05 | L62: https://www.jll.com/en-us/insights/market-outlook/data-center-outlook｜报告正文 | M62: 2026-10-22 | N62: JLL26
A63: COST-72 | B63: 功率密度 | C63: NVIDIA 计划支持的单机柜 IT 功率 | D63: NVIDIA | E63: 1 | F63: MW/机柜 | G63: 2027 起 | H63: 公司指引 | I63: 800 V 直流供电架构 | J63: NVIDIA 技术博客：800 V 高压直流架构将为下一代 AI 工厂供电 | K63: 2025-05-20 | L63: https://developer.nvidia.com/blog/nvidia-800-v-hvdc-architecture-will-power-the-next-generation-of-ai-factories/｜博客正文 | M63: 2026-10-22 | N63: NV800
A64: COST-80 | B64: 核电成本 | C64: Vogtle 3、4 号机组总成本 | D64: 美国佐治亚州 | E64: 36.8 | F64: 十亿美元 | G64: 2024 完工 | H64: 第三方估计 | I64: 最初预算约 140 亿美元（二手汇编） | J64: 维基百科：Vogtle 核电站（引用 2024-05-29 媒体报道） | K64: 2024-05-29（被引报道） | L64: https://en.wikipedia.org/wiki/Vogtle_Electric_Generating_Plant｜词条正文 | M64: 2026-10-22 | N64: WIKI_VOG
A65: COST-81 | B65: 核电成本 | C65: Palisades 核电站重启贷款（美国能源部） | D65: Holtec | E65: 1.52 | F65: 十亿美元 | G65: 2024-09 | H65: 披露事实 | I65: 约 800 MW；2026-08-30 装料事故后暂停（二手） | J65: 美国能源部贷款办公室项目页：Holtec Palisades | K65: 项目页（未标日期） | L65: https://www.energy.gov/lpo/holtec-palisades｜项目页 | M65: 2026-10-22 | N65: DOE_PAL
A66: COST-82 | B66: 核电成本 | C66: Crane 重启投资（公司估算） | D66: Constellation | E66: 1.6 | F66: 十亿美元 | G66: 2024-09 | H66: 第三方估计 | I66: 二手汇编，引用 BBC | J66: 维基百科：三哩岛核电站（引用 BBC 2024-09-20 报道） | K66: 2024-09-20（被引报道） | L66: https://en.wikipedia.org/wiki/Three_Mile_Island_Nuclear_Generating_Station｜词条正文 | M66: 2026-10-22 | N66: WIKI_TMI
A67: COST-90 | B67: 政策 | C67: FERC 拟议“大负荷”门槛 | D67: 美国 | E67: 50 | F67: MW | G67: 2026-06-18 | H67: 披露事实 | I67: 单一场址峰荷 ≥50 MW、接入电压 ≥69 kV；向六大运营商发说明理由令 | J67: Orrick 律所：FERC 向六大区域电网运营商发出大负荷并网“说明理由令” | K67: 2026-07-06 | L67: https://www.orrick.com/en/Insights/2026/07/FERC-Show-Cause-Orders-Signal-Broad-Reform-to-Large-Load-Interconnection-Policies｜律所解读 | M67: 2026-10-22 | N67: FERC_SC
A68: COST-91 | B68: 政策 | C68: 得州 SB 6 大负荷门槛 | D68: 得州 | E68: 75 | F68: MW | G68: 2025-06-20 | H68: 披露事实 | I68: 紧急情况下可削减 2025 年后接入的大负荷 | J68: 得克萨斯州议会 SB 6 法案记录 | K68: 2025-06-20（签署） | L68: https://capitol.texas.gov/BillLookup/History.aspx?LegSess=89R&Bill=SB6｜法案记录 | M68: 2026-10-22 | N68: TXSB6
A69: COST-92 | B69: 政策 | C69: AEP Ohio 数据中心电价最低计费比例 | D69: 俄亥俄州 | E69: 0.85 | F69: % | G69: 2025-07-09 | H69: 披露事实 | I69: >25 MW 新数据中心；最长 12 年 | J69: POWER 杂志：俄亥俄监管机构批准 AEP Ohio 数据中心电价 | K69: 2025-07-09 | L69: https://www.powermag.com/regulator-approves-aep-ohios-landmark-data-center-tariff/｜报道正文 | M69: 2026-10-22 | N69: AEPOH

Sheet D9_托卡马克部件
A1: D9 托卡马克部件参数（ITER 官网；用于网页第一部分的部件卡片）
A2: 蓝底=输入（披露数据）；橙底=输入（假设）；绿底=公式（本表计算）。“出处定位”给出原始材料的文件与章节，或网页链接；“访问日期”为网页查阅日期。
A4: 编号 | B4: 类别 | C4: 指标 | D4: 主体/地区 | E4: 数值 | F4: 单位 | G4: 期间 | H4: 性质 | I4: 口径说明 | J4: 来源名称 | K4: 发布日期 | L4: 出处定位（文件章节/表名或网页链接） | M4: 访问日期 | N4: 来源编号
A5: TK-01 | B5: overview | C5: 等离子体温度 | D5: ITER | E5: 150 | F5: 百万摄氏度 | G5: 设计值 | H5: 官方预测 | I5: 设计目标 | J5: ITER 组织官网：事实与数据 | K5: 页面未标日期 | L5: https://www.iter.org/facts-figures｜“温度将达到 1.5 亿摄氏度” | M5: 2026-10-22 | N5: ITER_FF
A6: TK-02 | B6: overview | C6: 聚变功率（Q≥10 目标） | D6: ITER | E6: 500 | F6: MW | G6: 设计目标 | H6: 官方预测 | I6: 注入 50 MW 加热功率，持续 400–600 秒 | J6: ITER 组织官网：事实与数据 | K6: 页面未标日期 | L6: https://www.iter.org/facts-figures｜页面正文 | M6: 2026-10-22 | N6: ITER_FF
A7: TK-03 | B7: overview | C7: 加热功率 | D7: ITER | E7: 50 | F7: MW | G7: 设计目标 | H7: 官方预测 | J7: ITER 组织官网：事实与数据 | K7: 页面未标日期 | L7: https://www.iter.org/facts-figures｜页面正文 | M7: 2026-10-22 | N7: ITER_FF
A8: TK-04 | B8: overview | C8: 整机重量 | D8: ITER | E8: 23000 | F8: 吨 | G8: 设计值 | H8: 官方预测 | J8: ITER 组织官网：事实与数据 | K8: 页面未标日期 | L8: https://www.iter.org/facts-figures｜页面正文 | M8: 2026-10-22 | N8: ITER_FF
A9: TK-10 | B9: cryostat | C9: 宽度与高度 | D9: ITER | E9: 30 | F9: 米（约） | G9: 设计值 | H9: 披露事实 | I9: 原文“近 30 米宽、近 30 米高”，内径 28 米 | J9: ITER 组织官网：杜瓦（低温恒温器） | K9: 页面未标日期 | L9: https://www.iter.org/machine/cryostat｜页面正文 | M9: 2026-10-22 | N9: ITER_CRY
A10: TK-11 | B10: cryostat | C10: 重量 | D10: ITER | E10: 3850 | F10: 吨 | G10: 设计值 | H10: 披露事实 | I10: 底座 1250 吨 | J10: ITER 组织官网：杜瓦（低温恒温器） | K10: 页面未标日期 | L10: https://www.iter.org/machine/cryostat｜页面正文 | M10: 2026-10-22 | N10: ITER_CRY
A11: TK-12 | B11: cryostat | C11: 容积 | D11: ITER | E11: 16000 | F11: 立方米 | G11: 设计值 | H11: 披露事实 | J11: ITER 组织官网：杜瓦（低温恒温器） | K11: 页面未标日期 | L11: https://www.iter.org/machine/cryostat｜页面正文 | M11: 2026-10-22 | N11: ITER_CRY
A12: TK-20 | B12: tf | C12: 线圈数量 | D12: ITER | E12: 18 | F12: 个 | G12: 设计值 | H12: 披露事实 | I12: D 形 | J12: ITER 组织官网：磁体 | K12: 页面未标日期 | L12: https://www.iter.org/machine/magnets｜页面正文 | M12: 2026-10-22 | N12: ITER_MAG
A13: TK-21 | B13: tf | C13: 最大磁场 | D13: ITER | E13: 11.8 | F13: 特斯拉 | G13: 设计值 | H13: 披露事实 | I13: 线圈处峰值场 | J13: ITER 组织官网：磁体 | K13: 页面未标日期 | L13: https://www.iter.org/machine/magnets｜页面正文 | M13: 2026-10-22 | N13: ITER_MAG
A14: TK-22 | B14: tf | C14: 单个重量 | D14: ITER | E14: 330 | F14: 吨 | G14: 设计值 | H14: 披露事实 | I14: “事实与数据”页写约 310 吨 | J14: ITER 组织官网：磁体 | K14: 页面未标日期 | L14: https://www.iter.org/machine/magnets｜页面正文 | M14: 2026-10-22 | N14: ITER_MAG
A15: TK-30 | B15: pf | C15: 线圈数量 | D15: ITER | E15: 6 | F15: 个 | G15: 设计值 | H15: 披露事实 | I15: 环形 | J15: ITER 组织官网：磁体 | K15: 页面未标日期 | L15: https://www.iter.org/machine/magnets｜页面正文 | M15: 2026-10-22 | N15: ITER_MAG
A16: TK-31 | B16: pf | C16: 最大直径 | D16: ITER | E16: 24 | F16: 米 | G16: 设计值 | H16: 披露事实 | I16: 最重 400 吨 | J16: ITER 组织官网：磁体 | K16: 页面未标日期 | L16: https://www.iter.org/machine/magnets｜页面正文 | M16: 2026-10-22 | N16: ITER_MAG
A17: TK-32 | B17: pf | C17: 最大磁场 | D17: ITER | E17: 6 | F17: 特斯拉 | G17: 设计值 | H17: 披露事实 | J17: ITER 组织官网：磁体 | K17: 页面未标日期 | L17: https://www.iter.org/machine/magnets｜页面正文 | M17: 2026-10-22 | N17: ITER_MAG
A18: TK-40 | B18: cs | C18: 模块数量 | D18: ITER | E18: 6 | F18: 个 | G18: 设计值 | H18: 披露事实 | I18: 铌三锡超导 | J18: ITER 组织官网：磁体 | K18: 页面未标日期 | L18: https://www.iter.org/machine/magnets｜页面正文 | M18: 2026-10-22 | N18: ITER_MAG
A19: TK-41 | B19: cs | C19: 最大磁场 | D19: ITER | E19: 13 | F19: 特斯拉 | G19: 设计值 | H19: 披露事实 | J19: ITER 组织官网：磁体 | K19: 页面未标日期 | L19: https://www.iter.org/machine/magnets｜页面正文 | M19: 2026-10-22 | N19: ITER_MAG
A20: TK-42 | B20: cs | C20: 驱动的等离子体电流 | D20: ITER | E20: 15 | F20: 兆安 | G20: 设计值 | H20: 披露事实 | I20: 持续 300–500 秒 | J20: ITER 组织官网：磁体 | K20: 页面未标日期 | L20: https://www.iter.org/machine/magnets｜页面正文 | M20: 2026-10-22 | N20: ITER_MAG
A21: TK-50 | B21: vv | C21: 外径 | D21: ITER | E21: 19.4 | F21: 米 | G21: 设计值 | H21: 披露事实 | J21: ITER 组织官网：真空室 | K21: 页面未标日期 | L21: https://www.iter.org/machine/vacuum-vessel｜页面正文 | M21: 2026-10-22 | N21: ITER_VV
A22: TK-51 | B22: vv | C22: 高度 | D22: ITER | E22: 11.4 | F22: 米 | G22: 设计值 | H22: 披露事实 | J22: ITER 组织官网：真空室 | K22: 页面未标日期 | L22: https://www.iter.org/machine/vacuum-vessel｜页面正文 | M22: 2026-10-22 | N22: ITER_VV
A23: TK-52 | B23: vv | C23: 重量（空载） | D23: ITER | E23: 5200 | F23: 吨 | G23: 设计值 | H23: 披露事实 | I23: 装上包层与偏滤器后 8500 吨 | J23: ITER 组织官网：真空室 | K23: 页面未标日期 | L23: https://www.iter.org/machine/vacuum-vessel｜页面正文 | M23: 2026-10-22 | N23: ITER_VV
A24: TK-53 | B24: vv | C24: 扇区数 | D24: ITER | E24: 9 | F24: 个 | G24: 2026-10 | H24: 披露事实 | I24: 9 个扇区已全部运抵现场 | J24: ITER Newsline：最后一个真空室扇区运抵，所有主要磁体部件到场 | K24: 2026-10-05 | L24: https://www.iter.org/node/20687/remarkable-chapter-draws-close｜新闻 | M24: 2026-10-22 | N24: ITER_NL
A25: TK-60 | B25: blanket | C25: 模块数量 | D25: ITER | E25: 440 | F25: 块 | G25: 设计值 | H25: 披露事实 | I25: 每块约 1×1.5 米、最重 4.6 吨 | J25: ITER 组织官网：包层 | K25: 页面未标日期 | L25: https://www.iter.org/machine/blanket｜页面正文 | M25: 2026-10-22 | N25: ITER_BL
A26: TK-61 | B26: blanket | C26: 可带走热功率 | D26: ITER | E26: 736 | F26: MW | G26: 设计值 | H26: 披露事实 | J26: ITER 组织官网：包层 | K26: 页面未标日期 | L26: https://www.iter.org/machine/blanket｜页面正文 | M26: 2026-10-22 | N26: ITER_BL
A27: TK-62 | B27: blanket | C27: 覆盖面积 | D27: ITER | E27: 600 | F27: 平方米 | G27: 设计值 | H27: 披露事实 | J27: ITER 组织官网：包层 | K27: 页面未标日期 | L27: https://www.iter.org/machine/blanket｜页面正文 | M27: 2026-10-22 | N27: ITER_BL
A28: TK-70 | B28: divertor | C28: 盒式模块数量 | D28: ITER | E28: 54 | F28: 个 | G28: 设计值 | H28: 披露事实 | I28: 每个约 10 吨，钨铠甲 | J28: ITER 组织官网：偏滤器 | K28: 页面未标日期 | L28: https://www.iter.org/machine/divertor｜页面正文 | M28: 2026-10-22 | N28: ITER_DIV
A29: TK-71 | B29: divertor | C29: 稳态热流 | D29: ITER | E29: 10 | F29: MW/平方米 | G29: 设计值 | H29: 披露事实 | I29: 慢瞬态 20 MW/平方米 | J29: ITER 组织官网：偏滤器 | K29: 页面未标日期 | L29: https://www.iter.org/machine/divertor｜页面正文 | M29: 2026-10-22 | N29: ITER_DIV
A30: TK-80 | B30: plasma | C30: 等离子体体积 | D30: ITER | E30: 830 | F30: 立方米 | G30: 设计值 | H30: 披露事实 | I30: 真空室页面写 840 | J30: ITER 组织官网：事实与数据 | K30: 页面未标日期 | L30: https://www.iter.org/facts-figures｜页面正文 | M30: 2026-10-22 | N30: ITER_FF
A31: TK-81 | B31: plasma | C31: 中性束加热（两台合计） | D31: ITER | E31: 33 | F31: MW | G31: 设计值 | H31: 披露事实 | I31: 每台 16.5 MW | J31: ITER 组织官网：外部加热系统 | K31: 页面未标日期 | L31: https://www.iter.org/machine/supporting-systems/external-heating-systems｜页面正文 | M31: 2026-10-22 | N31: ITER_HEAT
A32: TK-90 | B32: final | C32: SPARC 轴上磁场（CFS，高温超导） | D32: CFS SPARC | E32: 12.2 | F32: 特斯拉 | G32: 设计值 | H32: 披露事实 | I32: 与 ITER 线圈峰值场口径不同 | J32: Journal of Plasma Physics：Overview of the SPARC tokamak（Creely 等） | K32: 2020-09-29 | L32: https://doi.org/10.1017/S0022377820001257｜论文摘要 | M32: 2026-10-22 | N32: SPARC20
A33: TK-91 | B33: final | C33: ARC 电站净发电功率（CFS） | D33: CFS ARC | E33: 400 | F33: MW | G33: 目标 | H33: 公司目标 | I33: 弗吉尼亚 Chesterfield 县，2030 年代初 | J33: CFS 博客：SPARC 进展与美国能源部里程碑批准 | K33: 2026-08-05 | L33: https://blog.cfs.energy/sparc-progress-doe-milestone-approvals-reflect-cfs-power-plant-maturity/｜博客正文 | M33: 2026-10-22 | N33: CFS_BLOG
A36: 部件说明（网页第一部分卡片文字；数值见上表）
A37: 部件键 | B37: 部件 | C37: 英文 | D37: 颜色（十六进制） | E37: 作用（网页卡片文字）
A38: overview | B38: 托卡马克 | C38: Tokamak | D38: 6B4DFF | E38: 托卡马克用强磁场把上亿度的氘氚等离子体“悬”在一个环形真空容器里，让原子核聚变放出能量。ITER 是目前在建规模最大的托卡马克，下面按从外到内的顺序逐层拆开。
A39: cryostat | B39: 杜瓦（低温恒温器） | C39: Cryostat | D39: 8EA3BD | E39: 最外层的不锈钢大罐，把整台装置包在真空里，给零下 269 摄氏度的超导磁体做“保温瓶”，挡住外界的热量。
A40: tf | B40: 环向场线圈 | C40: Toroidal field coils | D40: 2F62E0 | E40: 18 个 D 形超导线圈围成一圈，产生沿环方向的强磁场，是把等离子体约束住、不碰到器壁的主力。
A41: pf | B41: 极向场线圈 | C41: Poloidal field coils | D41: E07A3C | E41: 6 个水平大环套在外侧，像“缰绳”一样控制等离子体的形状和上下位置，让它保持 D 形截面。
A42: cs | B42: 中心螺线管 | C42: Central solenoid | D42: D9A52F | E42: 立在中心孔里的 6 段超导线圈，相当于一个大变压器的初级线圈，在等离子体里感应出强大电流并维持数分钟。
A43: vv | B43: 真空室 | C43: Vacuum vessel | D43: 8E9BAD | E43: 双层钢壁的密封环形容器，里面抽成高真空、装着等离子体，是阻挡放射性物质的第一道屏障；壁间填满屏蔽块和冷却水。
A44: blanket | B44: 包层 | C44: Blanket | D44: C19A5B | E44: 贴满真空室内壁的数百块模块，直面等离子体，吸收中子和热量、保护后面的钢壁和磁体；未来电站要靠它用锂“增殖”氚燃料。
A45: divertor | B45: 偏滤器 | C45: Divertor | D45: 4A515C | E45: 装在真空室底部的“排气口”，承受最集中的热流，把聚变产生的氦“灰”和杂质导出，防止污染等离子体。
A46: plasma | B46: 等离子体 | C46: Plasma | D46: E04FC0 | E46: 氘和氚被加热到约 1.5 亿摄氏度后形成的发光等离子体，被磁力线约束成环形；聚变产生的高能中子把能量带给包层，最终转换成电。
A47: final | B47: 重新组装 | C47: Assembled | D47: 6B4DFF | E47: 各层重新合拢。即便进度最快的私营聚变公司，向客户供电的目标最早也要到 2028 年，大规模商业发电要到 2030 年代；在此之前，数据中心的电主要来自现有电网。

Sheet 来源清单
A1: 来源清单（来源编号 → 名称、发布者、发布日期、链接/文件、访问日期）
A2: 原始材料（M1–M3）以 材料/ 目录中的文件为准；网页来源均于 2026-10-22 访问。“类型”标出一手披露、官方机构、第三方研究或二手转述。
A4: 来源编号 | B4: 来源名称 | C4: 发布者 | D4: 发布日期 | E4: 链接或文件 | F4: 访问日期 | G4: 类型
A5: M1 | B5: Meta Platforms, Inc. 10-Q 季报（截至 2026-09-30 的季度） | C5: Meta Platforms / 美国证交会 | D5: 2026-10-21（签署日） | E5: 材料/Meta_2026Q3季报__meta-20260930.htm | F5: 原始材料 | G5: 原始材料
A6: M2 | B6: Constellation Energy Corp. 10-K 年报（2025 财年） | C6: Constellation Energy / 美国证交会 | D6: 2026-02-24（签署日） | E6: 材料/Constellation_2025年报__ceg-20251231.htm | F6: 原始材料 | G6: 原始材料
A7: M3 | B7: Constellation Energy Corp. 10-Q 季报（截至 2026-06-30 的季度） | C7: Constellation Energy / 美国证交会 | D7: 2026-08-06（签署日） | E7: 材料/Constellation_2026Q2季报__ceg-20260630.htm | F7: 原始材料 | G7: 原始材料
A8: IEA25 | B8: IEA《能源与人工智能》Energy and AI（世界能源展望特别报告） | C8: 国际能源署 IEA | D8: 2025-04（PDF 元数据 2025-04-11） | E8: https://iea.blob.core.windows.net/assets/b3a8b37f-32d1-4873-9eca-31cec5895264/EnergyandAI.pdf | F8: 2026-10-22 | G8: 官方机构
A9: IEA26 | B9: IEA《能源与人工智能关键问题》Key Questions on Energy and AI（2026 年更新版） | C9: 国际能源署 IEA | D9: 2026-04-16 | E9: https://iea.blob.core.windows.net/assets/3179f7f8-01f6-4dd6-bffa-c9f7b73f1dc9/KeyQuestionsonEnergyandAI.pdf | F9: 2026-10-22 | G9: 官方机构
A10: IEAE26 | B10: IEA《电力 2026》Electricity 2026 – Analysis and forecast to 2030 | C10: 国际能源署 IEA | D10: 2026-02 | E10: https://iea.blob.core.windows.net/assets/b73798cb-e452-42b9-9d8a-07542de7a041/Electricity_2026.pdf | F10: 2026-10-22 | G10: 官方机构
A11: IEAGER26 | B11: IEA《全球能源回顾 2026》Global Energy Review 2026 | C11: 国际能源署 IEA | D11: 2026-04 | E11: https://iea.blob.core.windows.net/assets/df903e1c-49c6-4757-8cbf-6fbcfe7611a0/GlobalEnergyReview2026.pdf | F11: 2026-10-22 | G11: 官方机构
A12: DOE24 | B12: 美国能源部新闻稿：DOE Releases New Report Evaluating Increase in Electricity Demand from Data Centers（LBNL 2024 美国数据中心能耗报告） | C12: 美国能源部 / 劳伦斯伯克利国家实验室 | D12: 2024-12-20 | E12: https://www.energy.gov/articles/doe-releases-new-report-evaluating-increase-electricity-demand-data-centers | F12: 2026-10-22 | G12: 官方机构
A13: EIA_EPM51 | B13: EIA《电力月报》表 5.1 终端用户售电量 | C13: 美国能源信息署 EIA | D13: 2026-09-24 | E13: https://www.eia.gov/electricity/monthly/epm_table_grapher.php?t=epmt_5_01 | F13: 2026-10-22 | G13: 官方机构
A14: EIA_EPM53 | B14: EIA《电力月报》表 5.3 终端用户平均电价 | C14: 美国能源信息署 EIA | D14: 2026-09-24 | E14: https://www.eia.gov/electricity/monthly/epm_table_grapher.php?t=epmt_5_3 | F14: 2026-10-22 | G14: 官方机构
A15: EIA_STEO | B15: EIA《短期能源展望》2026 年 10 月版（电力、煤炭与可再生能源） | C15: 美国能源信息署 EIA | D15: 2026-10-06 | E15: https://www.eia.gov/outlooks/steo/report/elec_coal_renew.php | F15: 2026-10-22 | G15: 官方机构
... A159: DOE_FR | B159: 美国能源部：发布最终版聚变科技路线图 | C159: 美国能源部 | D159: 2026-06-09 | E159: https://www.energy.gov/articles/energy-department-releases-finalized-fusion-science-and-technology-roadmap-accelerate | F159: 2026-10-22 | G159: 官方机构
