Workbook
Name ACQ: '假设'!$D$5
Name DATE_P: '假设'!$D$7
Name DATE_U: '假设'!$D$6
Name EBITDA_BASIS: '假设'!$D$11
Name M_S_A: '换股比例'!$C$10
Name M_S_ALL: '换股比例'!$C$20
Name M_S_B: '换股比例'!$C$11
Name M_S_OPT: '换股比例'!$C$13
Name M_S_RS: '换股比例'!$C$12
Name M_T_ALL: '换股比例'!$C$21
Name M_T_BEN: '换股比例'!$C$14
Name M_T_RS18: '换股比例'!$C$15
Name M_T_RS25: '换股比例'!$C$16
Name N_S: '换股比例'!$C$18
Name N_S_A: '换股比例'!$C$7
Name N_S_B: '换股比例'!$C$8
Name N_S_EX: '换股比例'!$C$19
Name N_T: '换股比例'!$C$6
Name N_T_PRX: '换股比例'!$C$17
Name P_S_P: '市场数据'!$C$20
Name P_S_U: '市场数据'!$C$10
Name P_S_VWAP: '市场数据'!$C$14
Name P_T_P: '市场数据'!$C$19
Name P_T_U: '市场数据'!$C$9
Name P_T_VWAP: '市场数据'!$C$13
Name PPA_INT_SHARE: '假设'!$D$14
Name PPA_LIFE: '假设'!$D$15
Name PREM: '假设'!$D$10
Name PS_M1: '换股比例'!$D$55
Name PS_M2: '换股比例'!$D$56
Name PS_M3: '换股比例'!$D$57
Name PS_M4: '换股比例'!$D$58
Name PS_M5: '换股比例'!$D$59
Name PT_M1: '换股比例'!$C$55
Name PT_M2: '换股比例'!$C$56
Name PT_M3: '换股比例'!$C$57
Name PT_M4: '换股比例'!$C$58
Name PT_M5: '换股比例'!$C$59
Name Q4_RP_SHARE: '假设'!$D$12
Name R_M1: '换股比例'!$G$55
Name R_M2: '换股比例'!$G$56
Name R_M3: '换股比例'!$G$57
Name R_M4: '换股比例'!$G$58
Name R_M5: '换股比例'!$G$59
Name RP_RP_AR: '关联交易'!$E$12
Name RP_RP_COGS_9M26: '关联交易'!$E$9
Name RP_RP_COGS_FY25: '关联交易'!$E$7
Name RP_RP_COGS_Q326: '关联交易'!$E$11
Name RP_RP_DR: '关联交易'!$E$13
Name RP_RP_INV_COST: '关联交易'!$E$15
Name RP_RP_INV_FV: '关联交易'!$E$14
Name RP_RP_REV_9M26: '关联交易'!$E$8
Name RP_RP_REV_FY25: '关联交易'!$E$6
Name RP_RP_REV_Q326: '关联交易'!$E$10
Name RUNRATE_X: '假设'!$D$16
Name TAX_ELIM: '假设'!$D$13
Name VWAP_N: '假设'!$D$8
Name VWAP_TXT: '假设'!$D$9
Name X_TS_SPCX: '换股比例'!$C$9

Sheet 说明
B1: SpaceX × 特斯拉 合并财务分析模型
B2: 投行并购团队内部讨论用 · 研究与展示分析，不构成投资建议（不提供买入/卖出/持有建议或目标价，不评价股价高低）
B4: 用途 | C4: 为“两家若合并、账怎么算”的内部讨论准备的财务分析：两家各自最近四个季度与 FY2025 关键数字、合并备考、关联交易处理、换股比例（五种定价方法）与溢价敏感性。
B5: 取数日期 | C5: 2026-10-22。财务数据截至 2026-09-30（SpaceX 2026Q3 业绩公告 2026-10-20；特斯拉 2026Q3 Update 2026-10-21、10-Q）；市场数据截至 2026-10-21 收盘（10-22 为盘中，未用）。
B6: 单位 | C6: 金额：百万美元（标注“十亿美元”处除外）；股数：百万股；股价：美元/股；比例：%。
B7: 期间口径 | C7: 两家财年均为公历年。“最近四个季度” = 2025Q4、2026Q1、2026Q2、2026Q3；LTM = 四季合计；最近完整财年 = FY2025。SpaceX 2025Q4 = FY2025 − 2025 前三季度（推算）；SpaceX 2026Q2/Q3 现金流 = 年初至今累计数相减（推算）。资产负债项目取各期末值，LTM 列取 2026-09-30。
B8: 会计口径 | C8: 美国 GAAP。SpaceX 2025 年及以前数据已按同一控制下合并（xAI、X）追溯重述；其“SI（超级智能）”分部即招股书/二季报中的“AI”分部（2026Q3 更名）。SpaceX 于 2026-08-14 完成收购 Cursor，Q3 仅并表约 1.5 个月。
B9: 关键定义 | C9: 毛利 = 营收 − 营业成本（SpaceX 报表无毛利行，为计算值）；经营利润 = Income from operations；净利润：特斯拉取归属普通股股东净利润，SpaceX 取净利润；经营现金流 = 经营活动现金流量净额；资本开支 = 购置物业厂房设备（特斯拉口径含储能系统采购）；自由现金流 = 经营现金流 − 资本开支；现金和短期投资 = 现金及等价物 + 短期投资/有价证券；有息负债 = 债务及融资租赁账面值（流动+非流动）；股东权益 = 归属母公司股东权益（SpaceX 2025 年末另有 387.52 亿美元可赎回可转换优先股列于夹层，IPO 时已转股）。
B10: EBITDA 两种口径 | C10: ①公司口径调整后 EBITDA（非 GAAP，两家定义不同：SpaceX 扣除利息收入及其他收益、加回重组与收购相关股权激励；特斯拉未扣除利息收入，剔除数字资产与 SpaceX 股权公允价值损益）；②统一口径 EBITDA = 经营利润 + 折旧摊销（本模型计算，倍数法默认使用）。
B11: 分部口径 | C11: SpaceX 三个分部：航天、连接（Starlink）、SI；CODM 以分部经营利润衡量，另披露分部调整后 EBITDA。特斯拉两个分部：汽车（含服务及其他）、能源发电与储能；CODM 以分部毛利衡量，未披露分部经营利润。为可比，本模型对五个分部统一计算分部毛利。
B12: 颜色图例 | C12: 蓝底蓝字 = 披露数据（取自 材料/ 原始文件，单元格批注写明文件、报表与列）；绿底绿字 = 市场数据（网络取得，表头注明来源与访问日期）；黄底橙字 = 假设（可修改，相关结果自动更新）；白底黑字 = 公式；灰底斜体 = 校验。
B13: 工作表导航 | C13: 假设 → 关键数字（两家十项指标与分部汇总）→ SpaceX财务 / 特斯拉财务（A–E 原始数，F 标准化表）→ 市场数据（股价、VWAP）→ 合并备考（加总、抵销、结构、购买法示意）→ 关联交易（清单与处理）→ 换股比例（五种方法、合并后股权、马斯克持股）→ 敏感性（溢价率 × 方法）→ 校验。
B14: 数据来源（材料/） | C14: · SpaceX_招股书__spaceexplorationtechnologi.htm（424B4，2026-06-11） · SpaceX_2026Q2季报__spcx-20260630.htm（10-Q） · SpaceX_2026Q3业绩公告__spaceexplorationtechnologi.htm（8-K 附件99.1） · Tesla_2025年报__tsla-20251231.htm（10-K） · Tesla_2026Q3季报__tsla-20260930.htm（10-Q） · Tesla_2026Q3业绩公告__exhibit9914.htm（Q3 2026 Update，附件99.1） · Tesla_2026股东大会委托书__tm267596-1_def14a.htm（DEF 14A）
B15: 数据来源（网络） | C15: · 股价与成交量：Nasdaq.com 历史行情接口 https://api.nasdaq.com/api/quote/TSLA/historical 与 https://api.nasdaq.com/api/quote/SPCX/historical（assetclass=stocks，2026-08-03 至 2026-10-21），访问日期 2026-10-22。 · 交叉核对：https://stockanalysis.com/stocks/tsla/history/ 与 https://stockanalysis.com/stocks/spcx/history/，访问日期 2026-10-22（收盘价一致；成交量口径不同，模型使用 Nasdaq 合并成交量）。 · 股本未使用网络数据，均取自 材料/ 原始文件。
... B19: 图例示例 | C19: 披露数据（蓝）
C20: 市场数据（绿）
C21: 假设（黄/橙）
C22: 公式（白）
C23: 校验（灰）
B25: 校验状态 | C25: ="校验通过 "&'校验'!D127&" / "&'校验'!E127&" 项；公式错误值 "&'校验'!D139&" 个" -> 校验通过 121 / 121 项；公式错误值 0 个

Sheet 假设
B1: 假设与参数（黄底橙字 = 假设，可直接修改，相关结果自动联动）
B2: 本表所列均为分析假设，不是披露事实；披露数据见各财务表（蓝底）与市场数据表（绿底）。
B4: 编号 | C4: 假设项 | D4: 取值 | E4: 单位 | F4: 说明与依据 | G4: 主要影响
B5: A01 | C5: 收购方 / 发行新股的存续上市主体 | D5: SpaceX | E5: 文本 | F5: 可选“SpaceX”或“特斯拉”。基准情形假设由 SpaceX（市值较大、马斯克以 B 类股控制）发行 A 类股吸收合并特斯拉；溢价给予被收购方股东。 | G5: 换股比例方向、两家股东占比、马斯克持股
B6: A02 | C6: 定价基准日（不受影响日） | D6: 46315 | E6: 日期 | F6: 马斯克在 2026-10-20 美东 16:30 的 SpaceX 业绩电话会上提及两家特别委员会（任务背景/公开报道），当日收盘（16:00）为消息前最后收盘价，视为不受影响价格。若为非交易日，自动取此前最近交易日。 | G6: 方法①收盘市值、方法②VWAP 截止日、倍数法 EV 基准
B7: A03 | C7: 消息公布后参考日 | D7: 46316 | E7: 日期 | F7: 取消息公布后首个完整交易日收盘价作参考（方法③）。2026-10-22 为盘中数据，未采用；且招股书显示 Q3 业绩发布后第二个完整交易日（即 10-22）约 13 亿股 A 类股解禁。 | G7: 方法③
B8: A04 | C8: 成交量加权均价（VWAP）窗口 | D8: 30 | E8: 交易日 | F8: 以基准日为窗口末日向前取 N 个交易日；价格表覆盖 2026-08-03 至 2026-10-21 共 57 个交易日，N 最大约 50（基准日为 10-20 时）。 | G8: 方法②
B9: A05 | C9: VWAP 计算口径 | D9: 典型价×成交量 | E9: 文本 | F9: 缺少逐笔成交数据，以日度典型价（最高+最低+收盘）/3 按日成交量加权近似 VWAP（假设/近似）。 | G9: 方法②
B10: A06 | C10: 基准溢价率（给被收购方股东） | D10: 0 | E10: % | F10: 基准情形为按市价对等换股（0% 溢价）；溢价敏感性见“敏感性”表（0%–40%）。 | G10: 换股比例、两家股东占比、马斯克持股
B11: A07 | C11: 倍数法 EBITDA 口径 | D11: 统一口径 | E11: 文本 | F11: 可选“统一口径”（经营利润+折旧摊销，本模型计算）或“公司口径”（两家各自披露的调整后 EBITDA，非 GAAP，定义不同：特斯拉未扣除利息收入）。 | G11: 方法⑤
B12: A08 | C12: 特斯拉 2025 年对 xAI 关联收入中落在 2025Q4 的比例 | D12: 1 | E12: % | F12: 特斯拉 10-Q 披露 2025 年前三季度关联交易不重大，故假设 2025 年 4.30 亿美元 Megapack 关联收入全部发生在 Q4（用于 LTM 抵销）。 | G12: LTM 合并抵销
B13: A09 | C13: 关联毛利抵销对应税率 | D13: 0.21 | E13: % | F13: 按美国联邦法定税率 21% 估算抵销关联未实现利润对净利润的影响（假设）。SpaceX 股权投资公允价值变动的税后数取特斯拉披露的非 GAAP 调节表。 | G13: 合并净利润
B14: A10 | C14: 购买法示意：超额对价中分摊至有限寿命无形资产的比例 | D14: 0.2 | E14: % | F14: 仅为示意：合并若按 ASC 805 以 SpaceX 为会计收购方，特斯拉净资产按公允价值入账，超额对价形成商誉及可辨认无形资产。分摊比例需购买价格分摊（PPA）确定，此处为假设。 | G14: 合并 GAAP 经营利润（示意）
B15: A11 | C15: 购买法示意：无形资产摊销年限 | D15: 10 | E15: 年 | F15: 直线摊销，示意假设。 | G15: 合并 GAAP 经营利润（示意）
B16: A12 | C16: 最近一季年化倍数 | D16: 4 | E16: 倍 | F16: “最近一季年化” = 2026Q3 × 4，仅用于展示规模变化，不是预测。 | G16: 合并营收结构（年化示意）
B17: A13 | C17: 马斯克持股数据时点 | D17: 见说明 | E17: 文本 | F17: SpaceX 持股取招股书（截至 2026-05-01）；特斯拉持股取委托书（截至 2026-09-30）。假设此后未变动（招股书显示马斯克全部股份锁定 366 天）。分母取最新披露股本（SpaceX 2026-09-30、特斯拉 2026-10-15）。 | G17: 马斯克持股
B18: A14 | C18: 限制性股与业绩股处理 | D18: 见说明 | E18: 文本 | F18: 口径A：已发行限制性股（含尚未达成业绩条件的业绩股）全部计入马斯克及总股本（上限口径）。口径B：剔除尚未达成业绩条件的业绩股（SpaceX 13.02 亿股 B 类、特斯拉 2025 CEO 奖励 4.24 亿股），特斯拉口径与委托书一致。两口径均不含未行权期权。假设合并时各类限制性股按同一换股比例转换、原条件不变。 | G18: 马斯克持股
B19: A15 | C19: 合并后表决权结构 | D19: 见说明 | E19: 文本 | F19: 若 SpaceX 为存续主体：沿用双层股权（B 类 10 票/股），特斯拉股东（含马斯克）获发 A 类股；马斯克 2025 特斯拉业绩股继续按比例投票（计算表决权时剔除）。若特斯拉为存续主体：假设单一类别 1 股 1 票。 | G19: 马斯克表决权（示意）
B20: A16 | C20: 交易方式与其他 | D20: 见说明 | E20: 文本 | F20: 100% 换股；不考虑现金对价、交易费用、协同效应、税务影响与监管条件；合并后市值按两家不受影响市值相加减去交叉持股（示意）。 | G20: 全部

Sheet 关键数字
B1: 关键数字汇总：SpaceX 与特斯拉最近四个季度、LTM 与 FY2025
B2: 单位：百万美元。本表全部为公式，链接各财务表 F 部分（标准化）；原始数出处见 SpaceX财务 / 特斯拉财务 A–E 部分的单元格批注。
B4: SpaceX
B5: 指标 | C5: Q4 2025 | D5: Q1 2026 | E5: Q2 2026 | F5: Q3 2026 | G5: LTM（2025Q4–2026Q3） | H5: FY2025 | I5: 链接 / 计算方法
B6: 营收 | C6: ='SpaceX财务'!$C$89 -> 4960 | D6: ='SpaceX财务'!$D$89 -> 4694 | E6: ='SpaceX财务'!$E$89 -> 7814 | F6: ='SpaceX财务'!$F$89 -> 14575 | G6: ='SpaceX财务'!$G$89 -> 32043 | H6: ='SpaceX财务'!$H$89 -> 18674 | I6: SpaceX财务 F 部分：Q4=FY2025−9M2025；Q2/Q3 现金流=累计数相减；资产负债项目为期末值
B7: 毛利 | C7: ='SpaceX财务'!$C$91 -> 2458 | D7: ='SpaceX财务'!$D$91 -> 2306 | E7: ='SpaceX财务'!$E$91 -> 4319 | F7: ='SpaceX财务'!$F$91 -> 9097 | G7: ='SpaceX财务'!$G$91 -> 18180 | H7: ='SpaceX财务'!$H$91 -> 9223
B8: 经营利润（GAAP） | C8: ='SpaceX财务'!$C$93 -> -1373 | D8: ='SpaceX财务'!$D$93 -> -1943 | E8: ='SpaceX财务'!$E$93 -> -143 | F8: ='SpaceX财务'!$F$93 -> 2791 | G8: ='SpaceX财务'!$G$93 -> -668 | H8: ='SpaceX财务'!$H$93 -> -2589
B9: 净利润（GAAP；特斯拉为归属普通股股东） | C9: ='SpaceX财务'!$C$95 -> -2347 | D9: ='SpaceX财务'!$D$95 -> -4276 | E9: ='SpaceX财务'!$E$95 -> -541 | F9: ='SpaceX财务'!$F$95 -> 4404 | G9: ='SpaceX财务'!$G$95 -> -2760 | H9: ='SpaceX财务'!$H$95 -> -4937
B10: 经营现金流 | C10: ='SpaceX财务'!$C$99 -> 2665 | D10: ='SpaceX财务'!$D$99 -> 1047 | E10: ='SpaceX财务'!$E$99 -> 2419 | F10: ='SpaceX财务'!$F$99 -> 9631 | G10: ='SpaceX财务'!$G$99 -> 15762 | H10: ='SpaceX财务'!$H$99 -> 6785
B11: 资本开支 | C11: ='SpaceX财务'!$C$100 -> 6891 | D11: ='SpaceX财务'!$D$100 -> 10107 | E11: ='SpaceX财务'!$E$100 -> 18369 | F11: ='SpaceX财务'!$F$100 -> 19593 | G11: ='SpaceX财务'!$G$100 -> 54960 | H11: ='SpaceX财务'!$H$100 -> 20737
B12: 自由现金流 | C12: ='SpaceX财务'!$C$101 -> -4226 | D12: ='SpaceX财务'!$D$101 -> -9060 | E12: ='SpaceX财务'!$E$101 -> -15950 | F12: ='SpaceX财务'!$F$101 -> -9962 | G12: ='SpaceX财务'!$G$101 -> -39198 | H12: ='SpaceX财务'!$H$101 -> -13952
B13: 现金和短期投资（期末） | C13: ='SpaceX财务'!$C$102 -> 24747 | D13: ='SpaceX财务'!$D$102 -> 23675 | E13: ='SpaceX财务'!$E$102 -> 100009 | F13: ='SpaceX财务'!$F$102 -> 89855 | G13: ='SpaceX财务'!$G$102 -> 89855 | H13: ='SpaceX财务'!$H$102 -> 24747
B14: 有息负债（期末，含融资租赁） | C14: ='SpaceX财务'!$C$103 -> 22896 | D14: ='SpaceX财务'!$D$103 -> 30265 | E14: ='SpaceX财务'!$E$103 -> 39364 | F14: ='SpaceX财务'!$F$103 -> 38844 | G14: ='SpaceX财务'!$G$103 -> 38844 | H14: ='SpaceX财务'!$H$103 -> 22896
B15: 股东权益（期末） | C15: ='SpaceX财务'!$C$106 -> 2573 | D15: ='SpaceX财务'!$D$106 -> 34533 | E15: ='SpaceX财务'!$E$106 -> 127224 | F15: ='SpaceX财务'!$F$106 -> 176768 | G15: ='SpaceX财务'!$G$106 -> 176768 | H15: ='SpaceX财务'!$H$106 -> 2573
B16: 备查：调整后EBITDA（公司口径，非GAAP） | C16: ='SpaceX财务'!$C$98 -> 1471 | D16: ='SpaceX财务'!$D$98 -> 1127 | E16: ='SpaceX财务'!$E$98 -> 3538 | F16: ='SpaceX财务'!$F$98 -> 8809 | G16: ='SpaceX财务'!$G$98 -> 14945 | H16: ='SpaceX财务'!$H$98 -> 6584
B17: 备查：可赎回可转换优先股（夹层，IPO 时转股） | C17: ='SpaceX财务'!$C$107 -> 38752 | D17: ='SpaceX财务'!$D$107 -> 7049 | E17: ='SpaceX财务'!$E$107 -> 0 | F17: ='SpaceX财务'!$F$107 -> 0 | G17: ='SpaceX财务'!$G$107 -> 0 | H17: ='SpaceX财务'!$H$107 -> 38752
B19: 特斯拉
B20: 指标 | C20: Q4 2025 | D20: Q1 2026 | E20: Q2 2026 | F20: Q3 2026 | G20: LTM（2025Q4–2026Q3） | H20: FY2025 | I20: 链接 / 计算方法
B21: 营收 | C21: ='特斯拉财务'!$C$77 -> 24901 | D21: ='特斯拉财务'!$D$77 -> 22387 | E21: ='特斯拉财务'!$E$77 -> 28236 | F21: ='特斯拉财务'!$F$77 -> 28046 | G21: ='特斯拉财务'!$G$77 -> 103570 | H21: ='特斯拉财务'!$H$77 -> 94827 | I21: 特斯拉财务 F 部分：季度数取 2026Q3 Update；FY2025 取 2025 年报
B22: 毛利 | C22: ='特斯拉财务'!$C$79 -> 5009 | D22: ='特斯拉财务'!$D$79 -> 4720 | E22: ='特斯拉财务'!$E$79 -> 4751 | F22: ='特斯拉财务'!$F$79 -> 5494 | G22: ='特斯拉财务'!$G$79 -> 19974 | H22: ='特斯拉财务'!$H$79 -> 17094
B23: 经营利润（GAAP） | C23: ='特斯拉财务'!$C$81 -> 1409 | D23: ='特斯拉财务'!$D$81 -> 941 | E23: ='特斯拉财务'!$E$81 -> 398 | F23: ='特斯拉财务'!$F$81 -> 718 | G23: ='特斯拉财务'!$G$81 -> 3466 | H23: ='特斯拉财务'!$H$81 -> 4355
B24: 净利润（GAAP；特斯拉为归属普通股股东） | C24: ='特斯拉财务'!$C$83 -> 840 | D24: ='特斯拉财务'!$D$83 -> 477 | E24: ='特斯拉财务'!$E$83 -> 1114 | F24: ='特斯拉财务'!$F$83 -> 787 | G24: ='特斯拉财务'!$G$83 -> 3218 | H24: ='特斯拉财务'!$H$83 -> 3794
B25: 经营现金流 | C25: ='特斯拉财务'!$C$88 -> 3813 | D25: ='特斯拉财务'!$D$88 -> 3937 | E25: ='特斯拉财务'!$E$88 -> 4697 | F25: ='特斯拉财务'!$F$88 -> 6263 | G25: ='特斯拉财务'!$G$88 -> 18710 | H25: ='特斯拉财务'!$H$88 -> 14747
B26: 资本开支 | C26: ='特斯拉财务'!$C$89 -> 2393 | D26: ='特斯拉财务'!$D$89 -> 2493 | E26: ='特斯拉财务'!$E$89 -> 5789 | F26: ='特斯拉财务'!$F$89 -> 4732 | G26: ='特斯拉财务'!$G$89 -> 15407 | H26: ='特斯拉财务'!$H$89 -> 8527
B27: 自由现金流 | C27: ='特斯拉财务'!$C$90 -> 1420 | D27: ='特斯拉财务'!$D$90 -> 1444 | E27: ='特斯拉财务'!$E$90 -> -1092 | F27: ='特斯拉财务'!$F$90 -> 1531 | G27: ='特斯拉财务'!$G$90 -> 3303 | H27: ='特斯拉财务'!$H$90 -> 6220
B28: 现金和短期投资（期末） | C28: ='特斯拉财务'!$C$91 -> 44059 | D28: ='特斯拉财务'!$D$91 -> 44743 | E28: ='特斯拉财务'!$E$91 -> 43524 | F28: ='特斯拉财务'!$F$91 -> 45447 | G28: ='特斯拉财务'!$G$91 -> 45447 | H28: ='特斯拉财务'!$H$91 -> 44059
B29: 有息负债（期末，含融资租赁） | C29: ='特斯拉财务'!$C$92 -> 8376 | D29: ='特斯拉财务'!$D$92 -> 9229 | E29: ='特斯拉财务'!$E$92 -> 9342 | F29: ='特斯拉财务'!$F$92 -> 9523 | G29: ='特斯拉财务'!$G$92 -> 9523 | H29: ='特斯拉财务'!$H$92 -> 8376
B30: 股东权益（期末） | C30: ='特斯拉财务'!$C$94 -> 82137 | D30: ='特斯拉财务'!$D$94 -> 84116 | E30: ='特斯拉财务'!$E$94 -> 86858 | F30: ='特斯拉财务'!$F$94 -> 89289 | G30: ='特斯拉财务'!$G$94 -> 89289 | H30: ='特斯拉财务'!$H$94 -> 82137
B31: 备查：调整后EBITDA（公司口径，非GAAP） | C31: ='特斯拉财务'!$C$86 -> 4154 | D31: ='特斯拉财务'!$D$86 -> 3668 | E31: ='特斯拉财务'!$E$86 -> 3273 | F31: ='特斯拉财务'!$F$86 -> 3900 | G31: ='特斯拉财务'!$G$86 -> 14995 | H31: ='特斯拉财务'!$H$86 -> 14596
B33: 分部（按各自披露的分部）
B34: 分部 · 指标 | C34: Q4 2025 | D34: Q1 2026 | E34: Q2 2026 | F34: Q3 2026 | G34: LTM（2025Q4–2026Q3） | H34: FY2025 | I34: 说明
B35: SpaceX · 航天 · 营收 | C35: ='SpaceX财务'!$C$110 -> 809 | D35: ='SpaceX财务'!$D$110 -> 619 | E35: ='SpaceX财务'!$E$110 -> 962 | F35: ='SpaceX财务'!$F$110 -> 1767 | G35: ='SpaceX财务'!$G$110 -> 4157 | H35: ='SpaceX财务'!$H$110 -> 4086
B36: SpaceX · 连接 · 营收 | C36: ='SpaceX财务'!$C$111 -> 3228 | D36: ='SpaceX财务'!$D$111 -> 3257 | E36: ='SpaceX财务'!$E$111 -> 4291 | F36: ='SpaceX财务'!$F$111 -> 5248 | G36: ='SpaceX财务'!$G$111 -> 16024 | H36: ='SpaceX财务'!$H$111 -> 11387
B37: SpaceX · SI · 营收 | C37: ='SpaceX财务'!$C$112 -> 923 | D37: ='SpaceX财务'!$D$112 -> 818 | E37: ='SpaceX财务'!$E$112 -> 2561 | F37: ='SpaceX财务'!$F$112 -> 7560 | G37: ='SpaceX财务'!$G$112 -> 11862 | H37: ='SpaceX财务'!$H$112 -> 3201
B38: SpaceX · 航天 · 经营利润（CODM 口径） | C38: ='SpaceX财务'!$C$116 -> -476 | D38: ='SpaceX财务'!$D$116 -> -662 | E38: ='SpaceX财务'!$E$116 -> -542 | F38: ='SpaceX财务'!$F$116 -> -7 | G38: ='SpaceX财务'!$G$116 -> -1687 | H38: ='SpaceX财务'!$H$116 -> -657
B39: SpaceX · 连接 · 经营利润（CODM 口径） | C39: ='SpaceX财务'!$C$117 -> 1276 | D39: ='SpaceX财务'!$D$117 -> 1188 | E39: ='SpaceX财务'!$E$117 -> 1656 | F39: ='SpaceX财务'!$F$117 -> 2367 | G39: ='SpaceX财务'!$G$117 -> 6487 | H39: ='SpaceX财务'!$H$117 -> 4423
B40: SpaceX · SI · 经营利润（CODM 口径） | C40: ='SpaceX财务'!$C$118 -> -2173 | D40: ='SpaceX财务'!$D$118 -> -2469 | E40: ='SpaceX财务'!$E$118 -> -1257 | F40: ='SpaceX财务'!$F$118 -> 431 | G40: ='SpaceX财务'!$G$118 -> -5468 | H40: ='SpaceX财务'!$H$118 -> -6355
B41: SpaceX · 航天 · 分部调整后EBITDA（非GAAP） | C41: ='SpaceX财务'!$C$119 -> -150 | D41: ='SpaceX财务'!$D$119 -> -351 | E41: ='SpaceX财务'!$E$119 -> -205 | F41: ='SpaceX财务'!$F$119 -> 357 | G41: ='SpaceX财务'!$G$119 -> -349 | H41: ='SpaceX财务'!$H$119 -> 653
B42: SpaceX · 连接 · 分部调整后EBITDA（非GAAP） | C42: ='SpaceX财务'!$C$120 -> 2045 | D42: ='SpaceX财务'!$D$120 -> 2087 | E42: ='SpaceX财务'!$E$120 -> 2597 | F42: ='SpaceX财务'!$F$120 -> 3499 | G42: ='SpaceX财务'!$G$120 -> 10228 | H42: ='SpaceX财务'!$H$120 -> 7168
B43: SpaceX · SI · 分部调整后EBITDA（非GAAP） | C43: ='SpaceX财务'!$C$121 -> -424 | D43: ='SpaceX财务'!$D$121 -> -609 | E43: ='SpaceX财务'!$E$121 -> 1146 | F43: ='SpaceX财务'!$F$121 -> 4953 | G43: ='SpaceX财务'!$G$121 -> 5066 | H43: ='SpaceX财务'!$H$121 -> -1237
B44: 特斯拉 · 汽车（含服务及其他）· 营收 | C44: ='特斯拉财务'!$C$98 -> 21064 | D44: ='特斯拉财务'!$D$98 -> 19979 | E44: ='特斯拉财务'!$E$98 -> 25097 | F44: ='特斯拉财务'!$F$98 -> 25165 | G44: ='特斯拉财务'!$G$98 -> 91305 | H44: ='特斯拉财务'!$H$98 -> 82056
B45: 特斯拉 · 汽车（含服务及其他）· 分部毛利（CODM 口径） | C45: ='特斯拉财务'!$C$100 -> 3911 | D45: ='特斯拉财务'!$D$100 -> 3768 | E45: ='特斯拉财务'!$E$100 -> 4111 | F45: ='特斯拉财务'!$F$100 -> 4540 | G45: ='特斯拉财务'!$G$100 -> 16330 | H45: ='特斯拉财务'!$H$100 -> 13292
B46: 特斯拉 · 能源发电与储能 · 营收 | C46: ='特斯拉财务'!$C$99 -> 3837 | D46: ='特斯拉财务'!$D$99 -> 2408 | E46: ='特斯拉财务'!$E$99 -> 3139 | F46: ='特斯拉财务'!$F$99 -> 2881 | G46: ='特斯拉财务'!$G$99 -> 12265 | H46: ='特斯拉财务'!$H$99 -> 12771
B47: 特斯拉 · 能源发电与储能 · 分部毛利（CODM 口径） | C47: ='特斯拉财务'!$C$101 -> 1098 | D47: ='特斯拉财务'!$D$101 -> 952 | E47: ='特斯拉财务'!$E$101 -> 640 | F47: ='特斯拉财务'!$F$101 -> 954 | G47: ='特斯拉财务'!$G$101 -> 3644 | H47: ='特斯拉财务'!$H$101 -> 3802
B48: 注：SpaceX 以分部经营利润衡量业绩（另披露分部调整后EBITDA）；特斯拉以分部毛利衡量业绩，未披露分部经营利润。

Sheet SpaceX财务
B1: SpaceX（Space Exploration Technologies Corp.，SPCX）财务数据
B2: 单位：百万美元（另注明除外）。蓝底 = 披露数据（批注注明文件、报表与列）；白底 = 公式；灰底 = 校验。2025 年及以前数据已按同一控制下合并（xAI、X）追溯重述。
B4: A. 利润表与非 GAAP 调节（披露期间原始数）
B5: 项目 | C5: FY2025 | D5: 9M 2025 | E5: Q1 2026 | F5: Q2 2026 | G5: 6M 2026 | H5: Q3 2026 | I5: 9M 2026 | J5: 英文行项目 / 说明
B6: 出处（文件 · 报表 · 列） | C6: 招股书 F-5 | D6: Q3业绩公告 | E6: 招股书 F-64 | F6: Q2季报 | G6: Q2季报 | H6: Q3业绩公告 | I6: Q3业绩公告 | J6: 完整出处见各单元格批注
B7: 营收 | C7: 18674 | D7: 13714 | E7: 4694 | F7: 7814 | G7: 12508 | H7: 14575 | I7: 27083 | J7: Revenue
B8: 营业成本 | C8: 9451 | D8: 6949 | E8: 2388 | F8: 3495 | G8: 5883 | H8: 5478 | I8: 11361 | J8: Cost of revenue
B9: 研发费用 | C9: 8643 | D9: 5806 | E9: 3514 | F9: 3548 | G9: 7062 | H9: 4596 | I9: 11658 | J9: Research and development
B10: 销售、一般及管理费用 | C10: 2644 | D10: 1674 | E10: 746 | F10: 912 | G10: 1658 | H10: 1707 | I10: 3365 | J10: Selling, general, and administrative
B11: 重组费用（收益） | C11: 487 | D11: 472 | E11: -11 | F11: 2 | G11: -9 | H11: 3 | I11: -6 | J11: Restructuring charges (credits)
B12: 减值 | C12: 38 | D12: 29 | E12: 0 | F12: 0 | G12: 0 | H12: 0 | I12: 0 | J12: Impairment
B13: 经营利润（报告值） | C13: -2589 | D13: -1216 | E13: -1943 | F13: -143 | G13: -2086 | H13: 2791 | I13: 705 | J13: Income (loss) from operations
B14: 利息费用 | C14: -1945 | D14: -1372 | E14: -664 | F14: -629 | G14: -1293 | H14: -675 | I14: -1968 | J14: Interest expense
B15: 利息收入 | C15: 492 | D15: 370 | E15: 213 | F15: 340 | G15: 553 | H15: 873 | I15: 1426 | J15: Interest income
B16: 其他收益（费用）净额 | C16: -177 | D16: 342 | E16: -1876 | F16: -86 | G16: -1962 | H16: 1025 | I16: -937 | J16: Other income (expense), net
B17: 税前利润（报告值） | C17: -4219 | D17: -1876 | E17: -4270 | F17: -518 | G17: -4788 | H17: 4014 | I17: -774 | J17: Income (loss) before income taxes
B18: 所得税费用（负数为收益） | C18: 718 | D18: 714 | E18: 6 | F18: 23 | G18: 29 | H18: -390 | I18: -361 | J18: Provision for (benefit from) income taxes
... B24: 调整后EBITDA（公司口径，非GAAP） | C24: 6584 | D24: 5113 | E24: 1127 | F24: 3538 | G24: 4665 | H24: 8809 | I24: 13474 | J24: Adjusted EBITDA
B25: 校验：营收−各项成本费用−经营利润 | C25: =C7-C8-C9-C10-C11-C12-C13 -> 0 | D25: =D7-D8-D9-D10-D11-D12-D13 -> 0 | E25: =E7-E8-E9-E10-E11-E12-E13 -> 0 | F25: =F7-F8-F9-F10-F11-F12-F13 -> 0 | G25: =G7-G8-G9-G10-G11-G12-G13 -> 0 | H25: =H7-H8-H9-H10-H11-H12-H13 -> 0 | I25: =I7-I8-I9-I10-I11-I12-I13 -> 0
B26: 校验：经营利润+营业外−所得税−净利润 | C26: =C13+C14+C15+C16-C18-C19 -> 0 | D26: =D13+D14+D15+D16-D18-D19 -> 0 | E26: =E13+E14+E15+E16-E18-E19 -> 0 | F26: =F13+F14+F15+F16-F18-F19 -> 0 | G26: =G13+G14+G15+G16-G18-G19 -> 0 | H26: =H13+H14+H15+H16-H18-H19 -> 0 | I26: =I13+I14+I15+I16-I18-I19 -> 0
B27: 校验：调整后EBITDA 重算−报告值 | C27: =C19+C20+C21+C22+C23+C11+C12-C14-C15-C16+C18-C24 -> 0 | D27: =D19+D20+D21+D22+D23+D11+D12-D14-D15-D16+D18-D24 -> 0 | E27: =E19+E20+E21+E22+E23+E11+E12-E14-E15-E16+E18-E24 -> 0 | F27: =F19+F20+F21+F22+F23+F11+F12-F14-F15-F16+F18-F24 -> 0 | G27: =G19+G20+G21+G22+G23+G11+G12-G14-G15-G16+G18-G24 -> 0 | H27: =H19+H20+H21+H22+H23+H11+H12-H14-H15-H16+H18-H24 -> 0 | I27: =I19+I20+I21+I22+I23+I11+I12-I14-I15-I16+I18-I24 -> 0
B28: 校验：季度报告值 − 累计数相减（营收/经营利润/净利润/EBITDA 绝对差合计） | F28: =ABS(F7-(G7-E7))+ABS(F8-(G8-E8))+ABS(F13-(G13-E13))+ABS(F19-(G19-E19))+ABS(F20-(G20-E20))+ABS(F24-(G24-E24)) -> 0 | H28: =ABS(H7-(I7-G7))+ABS(H8-(I8-G8))+ABS(H13-(I13-G13))+ABS(H19-(I19-G19))+ABS(H20-(I20-G20))+ABS(H24-(I24-G24)) -> 0
B30: B. 现金流量（年初至今累计，原始数）
B31: 项目 | C31: FY2025 | D31: 9M 2025 | E31: Q1 2026 | F31: — | G31: 6M 2026 | H31: — | I31: 9M 2026 | J31: 英文行项目
B32: 经营活动现金流量净额 | C32: 6785 | D32: 4120 | E32: 1047 | F32: n/a | G32: 3466 | H32: n/a | I32: 13097 | J32: Net cash provided by operating activities
B33: 购置物业、厂房及设备（资本开支） | C33: 20737 | D33: 13846 | E33: 10107 | F33: n/a | G33: 28476 | H33: n/a | I33: 48069 | J33: Purchases of property, plant, and equipment
B35: C. 资产负债表（期末原始数）
B36: 项目 | C36: 2025-12-31 | D36: 2026-03-31 | E36: 2026-06-30 | F36: 2026-09-30 | J36: 英文行项目
B37: 现金及现金等价物 | C37: 24747 | D37: 15852 | E37: 93522 | F37: 51294 | J37: Cash and cash equivalents
B38: 有价证券（短期投资） | C38: 0 | D38: 7823 | E38: 6487 | F38: 38561 | J38: Marketable securities
B39: 一年内到期债务及融资租赁 | C39: 928 | D39: 1538 | E39: 2525 | F39: 2698 | J39: Debt and finance leases, current
B40: 长期债务及融资租赁 | C40: 21968 | D40: 28727 | E40: 36839 | F40: 36146 | J40: Debt and finance leases, net of current
B41: 其中：关联方（Valor）流动部分 | C41: 455 | D41: 1121 | E41: 2039 | F41: 2181 | J41: related party portion, current
B42: 其中：关联方（Valor）非流动部分 | C42: 4052 | D42: 7920 | E42: 11290 | F42: 10716 | J42: related party portion, non-current
B43: 股东权益合计 | C43: 2573 | D43: 34533 | E43: 127224 | F43: 176768 | J43: Total shareholders' equity
B44: 可赎回可转换优先股（夹层权益，备查） | C44: 38752 | D44: 7049 | E44: 0 | F44: 0 | J44: Redeemable convertible preferred stock
B45: 总资产（备查） | C45: 92079 | D45: 102094 | E45: 192770 | F45: 254045 | J45: Total assets
B47: D. 分部数据（原始数）
B48: 分部 · 指标 | C48: FY2025 | D48: 9M 2025 | E48: Q1 2026 | F48: Q2 2026 | G48: Q3 2026 | H48: 9M 2026 | J48: 说明
B49: 分部营收 · 航天 | C49: 4086 | D49: 3277 | E49: 619 | F49: 962 | G49: 1767 | H49: 3348
B50: 分部营收 · 连接 | C50: 11387 | D50: 8159 | E50: 3257 | F50: 4291 | G50: 5248 | H50: 12796
B51: 分部营收 · SI | C51: 3201 | D51: 2278 | E51: 818 | F51: 2561 | G51: 7560 | H51: 10939
B52: 校验：分部合计 − 合并数（分部营收） | C52: =C49+C50+C51-C7 -> 0 | D52: =D49+D50+D51-D7 -> 0 | E52: =E49+E50+E51-E7 -> 0 | F52: =F49+F50+F51-F7 -> 0 | G52: =G49+G50+G51-H7 -> 0 | H52: =H49+H50+H51-I7 -> 0
B53: 分部营业成本 · 航天 | C53: 1352 | D53: 1104 | E53: 281 | F53: 329 | G53: 435 | H53: 1045
B54: 分部营业成本 · 连接 | C54: 5921 | D54: 4271 | E54: 1651 | F54: 2060 | G54: 2368 | H54: 6079
B55: 分部营业成本 · SI | C55: 2178 | D55: 1574 | E55: 456 | F55: 1106 | G55: 2675 | H55: 4237
B56: 校验：分部合计 − 合并数（分部营业成本） | C56: =C53+C54+C55-C8 -> 0 | D56: =D53+D54+D55-D8 -> 0 | E56: =E53+E54+E55-E8 -> 0 | F56: =F53+F54+F55-F8 -> 0 | G56: =G53+G54+G55-H8 -> 0 | H56: =H53+H54+H55-I8 -> 0
B57: 分部经营利润 · 航天 | C57: -657 | D57: -181 | E57: -662 | F57: -542 | G57: -7 | H57: -1211 | J57: 分部经营利润为 CODM 业绩衡量口径；分部调整后EBITDA 为非 GAAP
B58: 分部经营利润 · 连接 | C58: 4423 | D58: 3147 | E58: 1188 | F58: 1656 | G58: 2367 | H58: 5211
B59: 分部经营利润 · SI | C59: -6355 | D59: -4182 | E59: -2469 | F59: -1257 | G59: 431 | H59: -3295
B60: 校验：分部合计 − 合并数（分部经营利润） | C60: =C57+C58+C59-C13 -> 0 | D60: =D57+D58+D59-D13 -> 0 | E60: =E57+E58+E59-E13 -> 0 | F60: =F57+F58+F59-F13 -> 0 | G60: =G57+G58+G59-H13 -> 0 | H60: =H57+H58+H59-I13 -> 0
B61: 分部调整后EBITDA · 航天 | C61: 653 | D61: 803 | E61: -351 | F61: -205 | G61: 357 | H61: -199 | J61: 分部经营利润为 CODM 业绩衡量口径；分部调整后EBITDA 为非 GAAP
B62: 分部调整后EBITDA · 连接 | C62: 7168 | D62: 5123 | E62: 2087 | F62: 2597 | G62: 3499 | H62: 8183
B63: 分部调整后EBITDA · SI | C63: -1237 | D63: -813 | E63: -609 | F63: 1146 | G63: 4953 | H63: 5490
B64: 校验：分部合计 − 合并数（分部调整后EBITDA（非GAAP）） | C64: =C61+C62+C63-C24 -> 0 | D64: =D61+D62+D63-D24 -> 0 | E64: =E61+E62+E63-E24 -> 0 | F64: =F61+F62+F63-F24 -> 0 | G64: =G61+G62+G63-H24 -> 0 | H64: =H61+H62+H63-I24 -> 0
B65: 分部资本开支 · 航天 | C65: 3832 | D65: 2818 | E65: 1052 | F65: 1174 | G65: 1606 | H65: 3832
B66: 分部资本开支 · 连接 | C66: 4178 | D66: 2951 | E66: 1332 | F66: 1367 | G66: 1543 | H66: 4242
B67: 分部资本开支 · SI | C67: 12727 | D67: 8077 | E67: 7723 | F67: 15828 | G67: 16444 | H67: 39995
B68: 校验：分部合计 − 合并数（分部资本开支） | C68: =C65+C66+C67-C33 -> 0 | D68: =D65+D66+D67-D33 -> 0 | E68: =E65+E66+E67-E33 -> 0 | F68: =F65+F66+F67-(G33-E33) -> 0 | G68: =G65+G66+G67-(I33-G33) -> 0 | H68: =H65+H66+H67-I33 -> 0
B70: E. 运营指标与收入明细（披露）
B71: 指标 | C71: 数值 | J71: 出处
B72: Starlink 消费者用户数（百万，期末） | C72: 13.6 | J72: SpaceX_2026Q3业绩公告__spaceexplorationtechnologi.htm（8-K 附件99.1） · Connectivity Segment Operating and Financial Data · Q3 2026
B73: Starlink 消费者月ARPU（美元） | C73: 69 | J73: SpaceX_2026Q3业绩公告__spaceexplorationtechnologi.htm（8-K 附件99.1） · Connectivity Segment Operating and Financial Data · Q3 2026
B74: 连接：消费者收入（Q3 2026） | C74: 3121 | J74: SpaceX_2026Q3业绩公告__spaceexplorationtechnologi.htm（8-K 附件99.1） · Connectivity Segment Operating and Financial Data
B75: 连接：企业与政府收入（Q3 2026） | C75: 2127 | J75: SpaceX_2026Q3业绩公告__spaceexplorationtechnologi.htm（8-K 附件99.1） · Connectivity Segment Operating and Financial Data
B76: 航天：发射服务收入（Q3 2026） | C76: 1130 | J76: SpaceX_2026Q3业绩公告__spaceexplorationtechnologi.htm（8-K 附件99.1） · Space Segment Operating and Financial Data
B77: 航天：发射与研发合同收入（Q3 2026） | C77: 637 | J77: SpaceX_2026Q3业绩公告__spaceexplorationtechnologi.htm（8-K 附件99.1） · Space Segment Operating and Financial Data
B78: 总发射次数（Q3 2026，次） | C78: 35 | J78: SpaceX_2026Q3业绩公告__spaceexplorationtechnologi.htm（8-K 附件99.1） · Space Segment Operating and Financial Data
B79: 其中：客户发射（Q3 2026，次） | C79: 12 | J79: SpaceX_2026Q3业绩公告__spaceexplorationtechnologi.htm（8-K 附件99.1） · Space Segment Operating and Financial Data
B80: 入轨质量（Q3 2026，公吨） | C80: 476 | J80: SpaceX_2026Q3业绩公告__spaceexplorationtechnologi.htm（8-K 附件99.1） · Space Segment Operating and Financial Data
B81: SI：广告收入（Q3 2026） | C81: 538 | J81: SpaceX_2026Q3业绩公告__spaceexplorationtechnologi.htm（8-K 附件99.1） · SI Segment Operating and Financial Data
B82: SI：解决方案与基础设施收入（Q3 2026） | C82: 7022 | J82: SpaceX_2026Q3业绩公告__spaceexplorationtechnologi.htm（8-K 附件99.1） · SI Segment Operating and Financial Data
B83: SI：铭牌算力（GW，期末） | C83: 1.7 | J83: SpaceX_2026Q3业绩公告__spaceexplorationtechnologi.htm（8-K 附件99.1） · SI Segment Operating and Financial Data
... B85: 在手订单 Backlog（2026-06-30） | C85: 47461 | J85: SpaceX_2026Q2季报__spcx-20260630.htm（10-Q） · 附注3 Revenue · Backlog
B87: F. 标准化：最近四个季度、LTM 与 FY2025（公式）
B88: 关键数字 | C88: Q4 2025 | D88: Q1 2026 | E88: Q2 2026 | F88: Q3 2026 | G88: LTM（2025Q4–2026Q3） | H88: FY2025 | J88: 计算方法
B89: 营收 | C89: =C7-D7 -> 4960 | D89: =E7 -> 4694 | E89: =F7 -> 7814 | F89: =H7 -> 14575 | G89: =SUM(C89:F89) -> 32043 | H89: =C7 -> 18674 | J89: Q4=FY2025−9M2025；Q1/Q2/Q3=当季报告值；LTM=四季合计
B90: 营业成本 | C90: =C8-D8 -> 2502 | D90: =E8 -> 2388 | E90: =F8 -> 3495 | F90: =H8 -> 5478 | G90: =SUM(C90:F90) -> 13863 | H90: =C8 -> 9451 | J90: 同上
B91: 毛利（营收−营业成本） | C91: =C89-C90 -> 2458 | D91: =D89-D90 -> 2306 | E91: =E89-E90 -> 4319 | F91: =F89-F90 -> 9097 | G91: =G89-G90 -> 18180 | H91: =H89-H90 -> 9223 | J91: 计算值：SpaceX 报表无毛利行
B92: 毛利率 | C92: =IF(C89=0,0,C91/C89) -> 0.49556452 | D92: =IF(D89=0,0,D91/D89) -> 0.49126545 | E92: =IF(E89=0,0,E91/E89) -> 0.55272588 | F92: =IF(F89=0,0,F91/F89) -> 0.62415094 | G92: =IF(G89=0,0,G91/G89) -> 0.56736261 | H92: =IF(H89=0,0,H91/H89) -> 0.49389526 | J92: 毛利/营收
B93: 经营利润（GAAP） | C93: =C13-D13 -> -1373 | D93: =E13 -> -1943 | E93: =F13 -> -143 | F93: =H13 -> 2791 | G93: =SUM(C93:F93) -> -668 | H93: =C13 -> -2589 | J93: Income (loss) from operations
B94: 经营利润率 | C94: =IF(C89=0,0,C93/C89) -> -0.27681452 | D94: =IF(D89=0,0,D93/D89) -> -0.41393268 | E94: =IF(E89=0,0,E93/E89) -> -0.018300486 | F94: =IF(F89=0,0,F93/F89) -> 0.19149228 | G94: =IF(G89=0,0,G93/G89) -> -0.020846987 | H94: =IF(H89=0,0,H93/H89) -> -0.13864196 | J94: 经营利润/营收
B95: 净利润（GAAP） | C95: =C19-D19 -> -2347 | D95: =E19 -> -4276 | E95: =F19 -> -541 | F95: =H19 -> 4404 | G95: =SUM(C95:F95) -> -2760 | H95: =C19 -> -4937 | J95: Net income (loss)；SpaceX 无少数股东
B96: 折旧与摊销 | C96: =C20-D20 -> 1917 | D96: =E20 -> 2442 | E96: =F20 -> 2848 | F96: =H20 -> 3644 | G96: =SUM(C96:F96) -> 10851 | H96: =C20 -> 6701 | J96: 调整后EBITDA 调节表
B97: EBITDA（统一口径：经营利润+折旧摊销） | C97: =C93+C96 -> 544 | D97: =D93+D96 -> 499 | E97: =E93+E96 -> 2705 | F97: =F93+F96 -> 6435 | G97: =G93+G96 -> 10183 | H97: =H93+H96 -> 4112 | J97: 本模型计算，用于倍数法
B98: 调整后EBITDA（公司口径，非GAAP） | C98: =C24-D24 -> 1471 | D98: =E24 -> 1127 | E98: =F24 -> 3538 | F98: =H24 -> 8809 | G98: =SUM(C98:F98) -> 14945 | H98: =C24 -> 6584 | J98: 公司披露；Q3 2026 起另扣除收购相关股权激励与收购费用
B99: 经营现金流 | C99: =C32-D32 -> 2665 | D99: =E32 -> 1047 | E99: =G32-E32 -> 2419 | F99: =I32-G32 -> 9631 | G99: =SUM(C99:F99) -> 15762 | H99: =C32 -> 6785 | J99: Q4=FY−9M；Q2=6M−Q1；Q3=9M−6M（年初至今累计相减）
B100: 资本开支（购置物业厂房设备） | C100: =C33-D33 -> 6891 | D100: =E33 -> 10107 | E100: =G33-E33 -> 18369 | F100: =I33-G33 -> 19593 | G100: =SUM(C100:F100) -> 54960 | H100: =C33 -> 20737 | J100: 同上
B101: 自由现金流（经营现金流−资本开支） | C101: =C99-C100 -> -4226 | D101: =D99-D100 -> -9060 | E101: =E99-E100 -> -15950 | F101: =F99-F100 -> -9962 | G101: =G99-G100 -> -39198 | H101: =H99-H100 -> -13952 | J101: 计算值
B102: 现金和短期投资（期末） | C102: =C37+C38 -> 24747 | D102: =D37+D38 -> 23675 | E102: =E37+E38 -> 100009 | F102: =F37+F38 -> 89855 | G102: =F37+F38 -> 89855 | H102: =C37+C38 -> 24747 | J102: 现金及等价物+有价证券；LTM 列=2026-09-30
B103: 有息负债（期末，含融资租赁） | C103: =C39+C40 -> 22896 | D103: =D39+D40 -> 30265 | E103: =E39+E40 -> 39364 | F103: =F39+F40 -> 38844 | G103: =F39+F40 -> 38844 | H103: =C39+C40 -> 22896 | J103: 流动+非流动债务及融资租赁账面值
B104: 其中：关联方（Valor）融资 | C104: =C41+C42 -> 4507 | D104: =D41+D42 -> 9041 | E104: =E41+E42 -> 13329 | F104: =F41+F42 -> 12897 | G104: =F41+F42 -> 12897 | H104: =C41+C42 -> 4507 | J104: 失败的售后回租形成的关联方融资
B105: 净现金（现金和短期投资−有息负债） | C105: =C102-C103 -> 1851 | D105: =D102-D103 -> -6590 | E105: =E102-E103 -> 60645 | F105: =F102-F103 -> 51011 | G105: =G102-G103 -> 51011 | H105: =H102-H103 -> 1851 | J105: 计算值
B106: 股东权益（期末） | C106: =C43 -> 2573 | D106: =D43 -> 34533 | E106: =E43 -> 127224 | F106: =F43 -> 176768 | G106: =F43 -> 176768 | H106: =C43 -> 2573 | J106: Total shareholders' equity；2025 末另有夹层优先股
B107: 备查：可赎回可转换优先股（夹层） | C107: =C44 -> 38752 | D107: =D44 -> 7049 | E107: =E44 -> 0 | F107: =F44 -> 0 | G107: =F44 -> 0 | H107: =C44 -> 38752 | J107: IPO 时全部转为普通股
B109: 分部（标准化） | C109: Q4 2025 | D109: Q1 2026 | E109: Q2 2026 | F109: Q3 2026 | G109: LTM（2025Q4–2026Q3） | H109: FY2025 | J109: 计算方法
B110: 营收 · 航天 | C110: =C49-D49 -> 809 | D110: =E49 -> 619 | E110: =F49 -> 962 | F110: =G49 -> 1767 | G110: =SUM(C110:F110) -> 4157 | H110: =C49 -> 4086 | J110: Q4=FY2025−9M2025；毛利=分部营收−分部营业成本
B111: 营收 · 连接 | C111: =C50-D50 -> 3228 | D111: =E50 -> 3257 | E111: =F50 -> 4291 | F111: =G50 -> 5248 | G111: =SUM(C111:F111) -> 16024 | H111: =C50 -> 11387
B112: 营收 · SI | C112: =C51-D51 -> 923 | D112: =E51 -> 818 | E112: =F51 -> 2561 | F112: =G51 -> 7560 | G112: =SUM(C112:F112) -> 11862 | H112: =C51 -> 3201
B113: 毛利 · 航天 | C113: =(C49-C53)-(D49-D53) -> 561 | D113: =(E49-E53) -> 338 | E113: =(F49-F53) -> 633 | F113: =(G49-G53) -> 1332 | G113: =SUM(C113:F113) -> 2864 | H113: =(C49-C53) -> 2734 | J113: Q4=FY2025−9M2025；毛利=分部营收−分部营业成本
...

Sheet 特斯拉财务
B1: 特斯拉（Tesla, Inc.，TSLA）财务数据
B2: 单位：百万美元（另注明除外）。蓝底 = 披露数据（批注注明文件、报表与列）；白底 = 公式；灰底 = 校验。季度数取自 2026Q3 Update（含近五个季度报表），全年取自 2025 年报。
B4: A. 利润表与非 GAAP 调节（原始数）
B5: 项目 | C5: FY2025 | D5: Q4 2025 | E5: Q1 2026 | F5: Q2 2026 | G5: Q3 2026 | H5: 9M 2026 | J5: 英文行项目 / 说明
B6: 出处（文件 · 报表 · 列） | C6: 2025年报 | D6: Q3 Update | E6: Q3 Update | F6: Q3 Update | G6: Q3 Update | H6: Q3季报 | J6: 完整出处见各单元格批注
B7: 汽车销售 | C7: 65821 | D7: 16750 | E7: 15473 | F7: 20006 | G7: 20094 | H7: 55573 | J7: Automotive sales
B8: 汽车监管积分 | C8: 1993 | D8: 542 | E8: 380 | F8: 146 | G8: 113 | H8: 639 | J8: Automotive regulatory credits
B9: 汽车租赁 | C9: 1712 | D9: 401 | E9: 381 | F9: 364 | G9: 353 | H9: 1098 | J9: Automotive leasing
B10: 能源发电与储能 | C10: 12771 | D10: 3837 | E10: 2408 | F10: 3139 | G10: 2881 | H10: 8428 | J10: Energy generation and storage
B11: 服务及其他 | C11: 12530 | D11: 3371 | E11: 3745 | F11: 4581 | G11: 4605 | H11: 12931 | J11: Services and other
B12: 营收合计（报告值） | C12: 94827 | D12: 24901 | E12: 22387 | F12: 28236 | G12: 28046 | H12: 78669 | J12: Total revenues
B13: 营业成本—汽车销售 | C13: 56267 | D13: 13874 | E13: 12616 | F13: 16866 | G13: 16570 | H13: 46052 | J13: Cost of revenues: Automotive sales
B14: 营业成本—汽车租赁 | C14: 898 | D14: 206 | E14: 196 | F14: 187 | G14: 184 | H14: 567 | J14: Cost of revenues: Automotive leasing
B15: 营业成本—能源发电与储能 | C15: 8969 | D15: 2739 | E15: 1456 | F15: 2499 | G15: 1927 | H15: 5882 | J15: Cost of revenues: Energy generation and storage
B16: 营业成本—服务及其他 | C16: 11599 | D16: 3073 | E16: 3399 | F16: 3933 | G16: 3871 | H16: 11203 | J16: Cost of revenues: Services and other
B17: 营业成本合计（报告值） | C17: 77733 | D17: 19892 | E17: 17667 | F17: 23485 | G17: 22552 | H17: 63704 | J17: Total cost of revenues
B18: 研发费用 | C18: 6411 | D18: 1783 | E18: 1946 | F18: 2371 | G18: 2761 | H18: 7078 | J18: Research and development
... B33: SpaceX股权投资未实现（收益）损失 | C33: 0 | D33: 0 | E33: 0 | F33: -1005 | G33: 142 | H33: -863 | J33: SpaceX equity investment unrealized (gain) loss
B34: 同上，税后（非GAAP调节表） | C34: 0 | D34: 0 | E34: 0 | F34: -763 | G34: 108 | H34: n/a | J34: SpaceX equity investment unrealized (gain) loss, net of tax
B35: 调整后EBITDA（公司口径，非GAAP） | C35: 14596 | D35: 4154 | E35: 3668 | F35: 3273 | G35: 3900 | H35: n/a | J35: Adjusted EBITDA
B36: 校验：收入分项合计−营收合计 | C36: =C7+C8+C9+C10+C11-C12 -> 0 | D36: =D7+D8+D9+D10+D11-D12 -> 0 | E36: =E7+E8+E9+E10+E11-E12 -> 0 | F36: =F7+F8+F9+F10+F11-F12 -> 0 | G36: =G7+G8+G9+G10+G11-G12 -> 0 | H36: =H7+H8+H9+H10+H11-H12 -> 0
B37: 校验：成本分项合计−营业成本合计 | C37: =C13+C14+C15+C16-C17 -> 0 | D37: =D13+D14+D15+D16-D17 -> 0 | E37: =E13+E14+E15+E16-E17 -> 0 | F37: =F13+F14+F15+F16-F17 -> 0 | G37: =G13+G14+G15+G16-G17 -> 0 | H37: =H13+H14+H15+H16-H17 -> 0
B38: 校验：营收−成本−费用−经营利润 | C38: =C12-C17-C18-C19-C20-C21 -> 0 | D38: =D12-D17-D18-D19-D20-D21 -> 0 | E38: =E12-E17-E18-E19-E20-E21 -> 0 | F38: =F12-F17-F18-F19-F20-F21 -> 0 | G38: =G12-G17-G18-G19-G20-G21 -> 0 | H38: =H12-H17-H18-H19-H20-H21 -> 0
B39: 校验：经营利润+营业外−所得税−净利润；净利润−少数股东−归母 | C39: =ABS(C21+C22+C23+C24-C26-C27)+ABS(C27-C28-C29) -> 0 | D39: =ABS(D21+D22+D23+D24-D26-D27)+ABS(D27-D28-D29) -> 0 | E39: =ABS(E21+E22+E23+E24-E26-E27)+ABS(E27-E28-E29) -> 0 | F39: =ABS(F21+F22+F23+F24-F26-F27)+ABS(F27-F28-F29) -> 0 | G39: =ABS(G21+G22+G23+G24-G26-G27)+ABS(G27-G28-G29) -> 0 | H39: =ABS(H21+H22+H23+H24-H26-H27)+ABS(H27-H28-H29) -> 0
B40: 校验：调整后EBITDA 重算−报告值 | C40: =C29-C23+C26+C30+C31+C32+C33-C35 -> 0 | D40: =D29-D23+D26+D30+D31+D32+D33-D35 -> 0 | E40: =E29-E23+E26+E30+E31+E32+E33-E35 -> 0 | F40: =F29-F23+F26+F30+F31+F32+F33-F35 -> 0 | G40: =G29-G23+G26+G30+G31+G32+G33-G35 -> 0 | H40: n/a
B41: 校验：Q1+Q2+Q3 − 9M（各主要行绝对差合计） | H41: =ABS(E12+F12+G12-H12)+ABS(E17+F17+G17-H17)+ABS(E18+F18+G18-H18)+ABS(E19+F19+G19-H19)+ABS(E21+F21+G21-H21)+ABS(E27+F27+G27-H27)+ABS(E29+F29+G29-H29)+ABS(E30+F30+G30-H30)+ABS(E31+F31+G31-H31) -> 0
B43: B. 现金流量（原始数；季度为当季数）
B44: 项目 | C44: FY2025 | D44: Q4 2025 | E44: Q1 2026 | F44: Q2 2026 | G44: Q3 2026 | H44: 9M 2026 | J44: 英文行项目
B45: 经营活动现金流量净额 | C45: 14747 | D45: 3813 | E45: 3937 | F45: 4697 | G45: 6263 | H45: 14897 | J45: Net cash provided by operating activities
B46: 资本开支（购置物业及设备，不含融资租赁，扣除出售） | C46: 8527 | D46: 2393 | E46: 2493 | F46: 5789 | G46: 4732 | H46: 13014 | J46: Capital expenditures / Purchases of property and equipment excluding finance leases, net of sales
B47: 校验：Q1+Q2+Q3 − 9M（经营现金流、资本开支绝对差合计） | H47: =ABS(E45+F45+G45-H45)+ABS(E46+F46+G46-H46) -> 0
B49: C. 资产负债表（期末原始数）
B50: 项目 | C50: 2025-12-31 | D50: 2026-03-31 | E50: 2026-06-30 | F50: 2026-09-30 | J50: 英文行项目
B51: 现金、现金等价物及短期投资 | C51: 44059 | D51: 44743 | E51: 43524 | F51: 45447 | J51: Cash, cash equivalents and short-term investments
B52: 一年内到期债务及融资租赁 | C52: 1640 | D52: 1447 | E52: 1418 | F52: 1387 | J52: Current portion of debt and finance leases
B53: 长期债务及融资租赁 | C53: 6736 | D53: 7782 | E53: 7924 | F53: 8136 | J53: Debt and finance leases, net of current portion
B54: 股东权益合计（归属普通股） | C54: 82137 | D54: 84116 | E54: 86858 | F54: 89289 | J54: Total stockholders' equity
B55: 少数股东权益 | C55: 670 | D55: 629 | E55: 607 | F55: 546 | J55: Noncontrolling interests in subsidiaries
B56: 可赎回少数股东权益 | C56: 58 | D56: 57 | E56: 54 | F56: 54 | J56: Redeemable noncontrolling interests in subsidiaries
B58: D. 分部数据（报告值，用于勾稽）
B59: 分部 · 指标 | C59: FY2025 | D59: Q3 2026 | E59: 9M 2026 | J59: 说明
B60: 汽车分部（含服务及其他）营收 | C60: 82056 | D60: 25165 | E60: 70241 | J60: 特斯拉 CODM 以分部毛利衡量业绩；未披露分部经营利润
B61: 汽车分部营业成本 | C61: 68764 | D61: 20625 | E61: 57822
B62: 汽车分部毛利 | C62: 13292 | D62: 4540 | E62: 12419
B63: 能源发电与储能分部营收 | C63: 12771 | D63: 2881 | E63: 8428
B64: 能源分部营业成本 | C64: 8969 | D64: 1927 | E64: 5882
B65: 能源分部毛利 | C65: 3802 | D65: 954 | E65: 2546
B67: E. 运营指标（披露）
B68: 指标 | C68: Q4 2025 | D68: Q1 2026 | E68: Q2 2026 | F68: Q3 2026 | G68: LTM / 期末 | J68: 出处
B69: 交付量（辆） | C69: 418227 | D69: 358023 | E69: 480126 | F69: 486532 | G69: =SUM(C69:F69) -> 1742908 | J69: Tesla_2026Q3业绩公告__exhibit9914.htm（Q3 2026 Update，附件99.1） · Operational Summary（各季度列）
B70: 产量（辆） | C70: 434358 | D70: 408386 | E70: 451758 | F70: 464391 | G70: =SUM(C70:F70) -> 1758893 | J70: Tesla_2026Q3业绩公告__exhibit9914.htm（Q3 2026 Update，附件99.1） · Operational Summary（各季度列）
B71: 储能部署（GWh） | C71: 14.2 | D71: 8.8 | E71: 13.5 | F71: 13.7 | G71: =SUM(C71:F71) -> 50.2 | J71: Tesla_2026Q3业绩公告__exhibit9914.htm（Q3 2026 Update，附件99.1） · Operational Summary（各季度列）
B72: FSD 活跃订阅（百万） | C72: 1.1 | D72: 1.28 | E72: 1.48 | F72: 1.74 | G72: =F72 -> 1.74 | J72: Tesla_2026Q3业绩公告__exhibit9914.htm（Q3 2026 Update，附件99.1） · Operational Summary（各季度列）
B73: 超充桩（个，期末） | C73: 77682 | D73: 79918 | E73: 82357 | F73: 84465 | G73: =F73 -> 84465 | J73: Tesla_2026Q3业绩公告__exhibit9914.htm（Q3 2026 Update，附件99.1） · Operational Summary（各季度列）
B75: F. 标准化：最近四个季度、LTM 与 FY2025（公式）
B76: 关键数字 | C76: Q4 2025 | D76: Q1 2026 | E76: Q2 2026 | F76: Q3 2026 | G76: LTM（2025Q4–2026Q3） | H76: FY2025 | J76: 计算方法
B77: 营收 | C77: =D12 -> 24901 | D77: =E12 -> 22387 | E77: =F12 -> 28236 | F77: =G12 -> 28046 | G77: =SUM(C77:F77) -> 103570 | H77: =C12 -> 94827 | J77: 季度取 Update 当季列；LTM=四季合计
B78: 营业成本 | C78: =D17 -> 19892 | D78: =E17 -> 17667 | E78: =F17 -> 23485 | F78: =G17 -> 22552 | G78: =SUM(C78:F78) -> 83596 | H78: =C17 -> 77733 | J78: 同上
B79: 毛利 | C79: =C77-C78 -> 5009 | D79: =D77-D78 -> 4720 | E79: =E77-E78 -> 4751 | F79: =F77-F78 -> 5494 | G79: =G77-G78 -> 19974 | H79: =H77-H78 -> 17094 | J79: Gross profit（报告值一致）
B80: 毛利率 | C80: =IF(C77=0,0,C79/C77) -> 0.20115658 | D80: =IF(D77=0,0,D79/D77) -> 0.21083665 | E80: =IF(E77=0,0,E79/E77) -> 0.16826038 | F80: =IF(F77=0,0,F79/F77) -> 0.19589246 | G80: =IF(G77=0,0,G79/G77) -> 0.19285507 | H80: =IF(H77=0,0,H79/H77) -> 0.18026511 | J80: 毛利/营收
B81: 经营利润（GAAP） | C81: =D21 -> 1409 | D81: =E21 -> 941 | E81: =F21 -> 398 | F81: =G21 -> 718 | G81: =SUM(C81:F81) -> 3466 | H81: =C21 -> 4355 | J81: Income from operations
B82: 经营利润率 | C82: =IF(C77=0,0,C81/C77) -> 0.056584073 | D82: =IF(D77=0,0,D81/D77) -> 0.042033323 | E82: =IF(E77=0,0,E81/E77) -> 0.014095481 | F82: =IF(F77=0,0,F81/F77) -> 0.025600799 | G82: =IF(G77=0,0,G81/G77) -> 0.033465289 | H82: =IF(H77=0,0,H81/H77) -> 0.045925738 | J82: 经营利润/营收
B83: 净利润（归属普通股股东，GAAP） | C83: =D29 -> 840 | D83: =E29 -> 477 | E83: =F29 -> 1114 | F83: =G29 -> 787 | G83: =SUM(C83:F83) -> 3218 | H83: =C29 -> 3794 | J83: Net income attributable to common stockholders
B84: 折旧、摊销及减值 | C84: =D30 -> 1643 | D84: =E30 -> 1590 | E84: =F30 -> 1619 | F84: =G30 -> 1852 | G84: =SUM(C84:F84) -> 6704 | H84: =C30 -> 6148 | J84: 现金流量表
B85: EBITDA（统一口径：经营利润+折旧摊销） | C85: =C81+C84 -> 3052 | D85: =D81+D84 -> 2531 | E85: =E81+E84 -> 2017 | F85: =F81+F84 -> 2570 | G85: =G81+G84 -> 10170 | H85: =H81+H84 -> 10503 | J85: 本模型计算，用于倍数法
B86: 调整后EBITDA（公司口径，非GAAP） | C86: =D35 -> 4154 | D86: =E35 -> 3668 | E86: =F35 -> 3273 | F86: =G35 -> 3900 | G86: =SUM(C86:F86) -> 14995 | H86: =C35 -> 14596 | J86: 公司披露；未扣除利息收入，与 SpaceX 定义不同
B87: 备查：SpaceX 股权投资公允价值（收益）损失，税后 | C87: =D34 -> 0 | D87: =E34 -> 0 | E87: =F34 -> -763 | F87: =G34 -> 108 | G87: =SUM(C87:F87) -> -655 | H87: =C34 -> 0 | J87: 非GAAP调节表；负数=收益
B88: 经营现金流 | C88: =D45 -> 3813 | D88: =E45 -> 3937 | E88: =F45 -> 4697 | F88: =G45 -> 6263 | G88: =SUM(C88:F88) -> 18710 | H88: =C45 -> 14747 | J88: 当季数
B89: 资本开支 | C89: =D46 -> 2393 | D89: =E46 -> 2493 | E89: =F46 -> 5789 | F89: =G46 -> 4732 | G89: =SUM(C89:F89) -> 15407 | H89: =C46 -> 8527 | J89: 当季数（含储能系统采购）
B90: 自由现金流（经营现金流−资本开支） | C90: =C88-C89 -> 1420 | D90: =D88-D89 -> 1444 | E90: =E88-E89 -> -1092 | F90: =F88-F89 -> 1531 | G90: =G88-G89 -> 3303 | H90: =H88-H89 -> 6220 | J90: 与公司口径一致
B91: 现金和短期投资（期末） | C91: =C51 -> 44059 | D91: =D51 -> 44743 | E91: =E51 -> 43524 | F91: =F51 -> 45447 | G91: =F51 -> 45447 | H91: =C51 -> 44059 | J91: LTM 列=2026-09-30
B92: 有息负债（期末，含融资租赁） | C92: =C52+C53 -> 8376 | D92: =D52+D53 -> 9229 | E92: =E52+E53 -> 9342 | F92: =F52+F53 -> 9523 | G92: =F52+F53 -> 9523 | H92: =C52+C53 -> 8376 | J92: 流动+非流动债务及融资租赁；主要为无追索权债务
B93: 净现金（现金和短期投资−有息负债） | C93: =C91-C92 -> 35683 | D93: =D91-D92 -> 35514 | E93: =E91-E92 -> 34182 | F93: =F91-F92 -> 35924 | G93: =G91-G92 -> 35924 | H93: =H91-H92 -> 35683 | J93: 计算值
B94: 股东权益（期末，归属普通股） | C94: =C54 -> 82137 | D94: =D54 -> 84116 | E94: =E54 -> 86858 | F94: =F54 -> 89289 | G94: =F54 -> 89289 | H94: =C54 -> 82137 | J94: Total stockholders' equity（不含少数股东）
B95: 备查：少数股东权益（含可赎回） | C95: =C55+C56 -> 728 | D95: =D55+D56 -> 686 | E95: =E55+E56 -> 661 | F95: =F55+F56 -> 600 | G95: =F55+F56 -> 600 | H95: =C55+C56 -> 728 | J95: 用于企业价值计算
B97: 分部（标准化） | C97: Q4 2025 | D97: Q1 2026 | E97: Q2 2026 | F97: Q3 2026 | G97: LTM（2025Q4–2026Q3） | H97: FY2025 | J97: 计算方法
B98: 营收 · 汽车（含服务及其他） | C98: =D7+D8+D9+D11 -> 21064 | D98: =E7+E8+E9+E11 -> 19979 | E98: =F7+F8+F9+F11 -> 25097 | F98: =G7+G8+G9+G11 -> 25165 | G98: =SUM(C98:F98) -> 91305 | H98: =C7+C8+C9+C11 -> 82056 | J98: 汽车销售+监管积分+租赁+服务及其他（即公司“汽车分部”）
B99: 营收 · 能源发电与储能 | C99: =D10 -> 3837 | D99: =E10 -> 2408 | E99: =F10 -> 3139 | F99: =G10 -> 2881 | G99: =SUM(C99:F99) -> 12265 | H99: =C10 -> 12771 | J99: 能源分部
B100: 毛利 · 汽车（含服务及其他） | C100: =C98-(D13+D14+D16) -> 3911 | D100: =D98-(E13+E14+E16) -> 3768 | E100: =E98-(F13+F14+F16) -> 4111 | F100: =F98-(G13+G14+G16) -> 4540 | G100: =SUM(C100:F100) -> 16330 | H100: =H98-(C13+C14+C16) -> 13292 | J100: 分部营收−对应营业成本
B101: 毛利 · 能源发电与储能 | C101: =C99-D15 -> 1098 | D101: =D99-E15 -> 952 | E101: =E99-F15 -> 640 | F101: =F99-G15 -> 954 | G101: =SUM(C101:F101) -> 3644 | H101: =H99-C15 -> 3802 | J101: 分部营收−能源营业成本
B102: 毛利率 · 汽车（含服务及其他） | C102: =IF(C98=0,0,C100/C98) -> 0.18567224 | D102: =IF(D98=0,0,D100/D98) -> 0.18859803 | E102: =IF(E98=0,0,E100/E98) -> 0.16380444 | F102: =IF(F98=0,0,F100/F98) -> 0.1804093 | G102: =IF(G98=0,0,G100/G98) -> 0.1788511 | H102: =IF(H98=0,0,H100/H98) -> 0.16198694 | J102: 计算值
B103: 毛利率 · 能源发电与储能 | C103: =IF(C99=0,0,C101/C99) -> 0.28616106 | D103: =IF(D99=0,0,D101/D99) -> 0.39534884 | E103: =IF(E99=0,0,E101/E99) -> 0.20388659 | F103: =IF(F99=0,0,F101/F99) -> 0.33113502 | G103: =IF(G99=0,0,G101/G99) -> 0.29710558 | H103: =IF(H99=0,0,H101/H99) -> 0.29770574 | J103: 计算值
B104: 校验：分部计算值−10-K/10-Q 分部报告值（FY2025、Q3 2026） | C104: =H98-C60 -> 0 | D104: =H100-C62 -> 0 | E104: =H101-C65 -> 0 | F104: =F98-D60 -> 0 | G104: =F100-D62 -> 0 | H104: =F101-D65 -> 0
B105: 校验：分部营收合计−营收 | C105: =C98+C99-C77 -> 0 | D105: =D98+D99-D77 -> 0 | E105: =E98+E99-E77 -> 0 | F105: =F98+F99-F77 -> 0 | G105: =G98+G99-G77 -> 0 | H105: =H98+H99-H77 -> 0
B106: 2025Q3 分部营收（同比基数，披露） | C106: 2025Q3 | D106: 2026Q3 | E106: 同比
B107: 营收 · 汽车（含服务及其他） | C107: 24680 | D107: =F98 -> 25165 | E107: =D107/C107-1 -> 0.01965154
B108: 营收 · 能源发电与储能 | C108: 3415 | D108: =F99 -> 2881 | E108: =D108/C108-1 -> -0.15636896
B109: 校验：前三季度分部毛利合计−10-Q 9M 报告值（汽车/能源） | C109: =D100+E100+F100-E62 -> 0 | D109: =D101+E101+F101-E65 -> 0

Sheet 市场数据
B1: 市场数据：股价、成交量与定价取数
B2: 来源：Nasdaq.com 历史行情（https://api.nasdaq.com/api/quote/TSLA/historical 及 /SPCX/historical，assetclass=stocks），访问日期 2026-10-22；收盘价为常规交易时段收盘价，成交量为全市场合并成交量。交叉核对：stockanalysis.com 历史行情页（同日访问），收盘价一致。
B3: 2026-10-22 为盘中（未收盘）数据，未纳入。绿底 = 市场数据输入；白底 = 公式。
B5: A. 定价取数（公式，随“假设”表联动）
B6: 定价基准日（不受影响日，取自假设 A02） | C6: =DATE_U -> 46315
B7: 基准日在价格表中的行序（≤该日的最近交易日） | C7: =COUNTIF($B$25:$B$81,">"&C6)+1 -> 2
B8: 实际取价交易日 | C8: =INDEX($B$25:$B$81,C7) -> 46315
B9: 特斯拉收盘价（美元） | C9: =INDEX($F$25:$F$81,C7) -> 373.71
B10: SpaceX 收盘价（美元） | C10: =INDEX($L$25:$L$81,C7) -> 147.79
B11: VWAP 窗口（交易日，取自假设 A04） | C11: =VWAP_N -> 30
B12: VWAP 窗口起始日 | C12: =INDEX($B$25:$B$81,C7+C11-1) -> 46274
B13: 特斯拉 VWAP（美元） | C13: =SUMPRODUCT(INDEX($H$25:$H$81,C7):INDEX($H$25:$H$81,C7+C11-1),INDEX($G$25:$G$81,C7):INDEX($G$25:$G$81,C7+C11-1))/SUM(INDEX($G$25:$G$81,C7):INDEX($G$25:$G$81,C7+C11-1)) -> 367.94223
B14: SpaceX VWAP（美元） | C14: =SUMPRODUCT(INDEX($N$25:$N$81,C7):INDEX($N$25:$N$81,C7+C11-1),INDEX($M$25:$M$81,C7):INDEX($M$25:$M$81,C7+C11-1))/SUM(INDEX($M$25:$M$81,C7):INDEX($M$25:$M$81,C7+C11-1)) -> 153.56437
B15: 校验：窗口内交易日数 − N | C15: =COUNT(INDEX($B$25:$B$81,C7):INDEX($B$25:$B$81,C7+C11-1))-C11 -> 0
B16: 消息公布后参考日（取自假设 A03） | C16: =DATE_P -> 46316
B17: 参考日行序 | C17: =COUNTIF($B$25:$B$81,">"&C16)+1 -> 1
B18: 实际取价交易日 | C18: =INDEX($B$25:$B$81,C17) -> 46316
B19: 特斯拉收盘价（参考日，美元） | C19: =INDEX($F$25:$F$81,C17) -> 386.47
B20: SpaceX 收盘价（参考日，美元） | C20: =INDEX($L$25:$L$81,C17) -> 159.31
B23: B. 日度行情（2026-08-03 至 2026-10-21，按日期降序；Nasdaq.com）
B24: 交易日 | C24: TSLA 开盘 | D24: TSLA 最高 | E24: TSLA 最低 | F24: TSLA 收盘 | G24: TSLA 成交量(股) | H24: TSLA 典型价 | I24: SPCX 开盘 | J24: SPCX 最高 | K24: SPCX 最低 | L24: SPCX 收盘 | M24: SPCX 成交量(股) | N24: SPCX 典型价
B25: 46316 | C25: 381.425 | D25: 388.843 | E25: 380.51 | F25: 386.47 | G25: 48875810 | H25: =(D25+E25+F25)/3 -> 385.27433 | I25: 160.555 | J25: 166.18 | K25: 156.9301 | L25: 159.31 | M25: 220785200 | N25: =(J25+K25+L25)/3 -> 160.8067
B26: 46315 | C26: 370.28 | D26: 377.59 | E26: 363.64 | F26: 373.71 | G26: 32123320 | H26: =(D26+E26+F26)/3 -> 371.64667 | I26: 146.165 | J26: 148.66 | K26: 143.27 | L26: 147.79 | M26: 117204900 | N26: =(J26+K26+L26)/3 -> 146.57333
B27: 46314 | C27: 357.5 | D27: 369.5808 | E27: 354.47 | F27: 368.06 | G27: 38817910 | H27: =(D27+E27+F27)/3 -> 364.03693 | I27: 149.23 | J27: 151.01 | K27: 146.83 | L27: 147.96 | M27: 74037780 | N27: =(J27+K27+L27)/3 -> 148.6
B28: 46311 | C28: 369.145 | D28: 370.5 | E28: 349.33 | F28: 354.72 | G28: 62067340 | H28: =(D28+E28+F28)/3 -> 358.18333 | I28: 147.8 | J28: 147.92 | K28: 142.95 | L28: 146.03 | M28: 88552890 | N28: =(J28+K28+L28)/3 -> 145.63333
B29: 46310 | C29: 360.57 | D29: 363.75 | E29: 355.23 | F29: 362.44 | G29: 26728310 | H29: =(D29+E29+F29)/3 -> 360.47333 | I29: 146.91 | J29: 149.04 | K29: 140.66 | L29: 148.62 | M29: 101177100 | N29: =(J29+K29+L29)/3 -> 146.10667
B30: 46309 | C30: 371.16 | D30: 371.39 | E30: 363.82 | F30: 367.16 | G30: 31001420 | H30: =(D30+E30+F30)/3 -> 367.45667 | I30: 154.98 | J30: 155.44 | K30: 151.1 | L30: 152.16 | M30: 68780980 | N30: =(J30+K30+L30)/3 -> 152.9
B31: 46308 | C31: 372.325 | D31: 377.05 | E31: 371.3 | F31: 375.23 | G31: 18393040 | H31: =(D31+E31+F31)/3 -> 374.52667 | I31: 161.982 | J31: 161.982 | K31: 156.05 | L31: 156.54 | M31: 69022480 | N31: =(J31+K31+L31)/3 -> 158.19067
B32: 46307 | C32: 382.605 | D32: 382.7 | E32: 377.58 | F32: 378.03 | G32: 20244290 | H32: =(D32+E32+F32)/3 -> 379.43667 | I32: 164.66 | J32: 167.065 | K32: 160.85 | L32: 163.42 | M32: 67434500 | N32: =(J32+K32+L32)/3 -> 163.77833
B33: 46304 | C33: 382.38 | D33: 388.56 | E33: 379.71 | F33: 382.7 | G33: 38952430 | H33: =(D33+E33+F33)/3 -> 383.65667 | I33: 165.34 | J33: 166.38 | K33: 160.61 | L33: 162.57 | M33: 93042640 | N33: =(J33+K33+L33)/3 -> 163.18667
B34: 46303 | C34: 374.12 | D34: 375.96 | E34: 368.0301 | F34: 375 | G34: 28394950 | H34: =(D34+E34+F34)/3 -> 372.9967 | I34: 167.465 | J34: 167.6 | K34: 160 | L34: 160.57 | M34: 71897850 | N34: =(J34+K34+L34)/3 -> 162.72333
B35: 46302 | C35: 378.445 | D35: 382.3499 | E35: 374.43 | F35: 377.81 | G35: 25594560 | H35: =(D35+E35+F35)/3 -> 378.19663 | I35: 168.125 | J35: 171.31 | K35: 165.65 | L35: 167.6 | M35: 77473020 | N35: =(J35+K35+L35)/3 -> 168.18667
B36: 46301 | C36: 381.975 | D36: 383.33 | E36: 378.52 | F36: 380.68 | G36: 27735440 | H36: =(D36+E36+F36)/3 -> 380.84333 | I36: 172.005 | J36: 176.4199 | K36: 171.3854 | L36: 171.92 | M36: 106952400 | N36: =(J36+K36+L36)/3 -> 173.24177
... B81: 46237 | C81: 310.96 | D81: 324.65 | E81: 310.425 | F81: 322.08 | G81: 38281360 | H81: =(D81+E81+F81)/3 -> 319.05167 | I81: 106.4 | J81: 114.92 | K81: 104.83 | L81: 114.53 | M81: 70524030 | N81: =(J81+K81+L81)/3 -> 111.42667

Sheet 合并备考
B1: 合并备考：把两家当成一家看（简单加总 + 关联交易抵销）
B2: 单位：百万美元。未作购买价格分摊（PPA）的简单加总口径；购买法影响仅在 E 部分示意。关联交易抵销取自“关联交易”表。
B4: A. LTM（2025Q4–2026Q3）损益与现金流
B5: 项目 | C5: 特斯拉 | D5: SpaceX | E5: 关联交易抵销/调整 | F5: 合并备考 | G5: 特斯拉占比 | H5: SpaceX占比 | K5: 说明
B6: 营收 | C6: ='特斯拉财务'!$G$77 -> 103570 | D6: ='SpaceX财务'!$G$89 -> 32043 | E6: =-'关联交易'!$E$19 -> -1056 | F6: =C6+D6+E6 -> 134557 | G6: =IF(F6=0,0,C6/(C6+D6)) -> 0.76371734 | H6: =IF(F6=0,0,D6/(C6+D6)) -> 0.23628266 | K6: 抵销特斯拉对 SpaceX 的 Megapack 销售
B7: 营业成本 | C7: ='特斯拉财务'!$G$78 -> 83596 | D7: ='SpaceX财务'!$G$90 -> 13863 | E7: =-'关联交易'!$F$19 -> -763 | F7: =C7+D7+E7 -> 96696
B8: 毛利 | C8: =C6-C7 -> 19974 | D8: =D6-D7 -> 18180 | E8: =E6-E7 -> -293 | F8: =C8+D8+E8 -> 37861 | G8: =IF(F8=0,0,C8/(C8+D8)) -> 0.52350999 | H8: =IF(F8=0,0,D8/(C8+D8)) -> 0.47649001 | K8: 抵销关联未实现利润
B9: 毛利率 | C9: =IF(C6=0,0,C8/C6) -> 0.19285507 | D9: =IF(D6=0,0,D8/D6) -> 0.56736261 | F9: =IF(F6=0,0,F8/F6) -> 0.28137518
B10: 经营利润（GAAP） | C10: ='特斯拉财务'!$G$81 -> 3466 | D10: ='SpaceX财务'!$G$93 -> -668 | E10: =-'关联交易'!$G$19 -> -293 | F10: =C10+D10+E10 -> 2505
B11: 经营利润率 | C11: =IF(C6=0,0,C10/C6) -> 0.033465289 | D11: =IF(D6=0,0,D10/D6) -> -0.020846987 | F11: =IF(F6=0,0,F10/F6) -> 0.018616646
B12: EBITDA（统一口径） | C12: ='特斯拉财务'!$G$85 -> 10170 | D12: ='SpaceX财务'!$G$97 -> 10183 | E12: =-'关联交易'!$G$19 -> -293 | F12: =C12+D12+E12 -> 20060 | G12: =IF(F12=0,0,C12/(C12+D12)) -> 0.49968064 | H12: =IF(F12=0,0,D12/(C12+D12)) -> 0.50031936 | K12: 经营利润+折旧摊销
B13: 调整后EBITDA（公司口径简单加总，非GAAP） | C13: ='特斯拉财务'!$G$86 -> 14995 | D13: ='SpaceX财务'!$G$98 -> 14945 | E13: =-'关联交易'!$G$19 -> -293 | F13: =C13+D13+E13 -> 29647 | K13: 两家定义不同，仅作参考
B14: 净利润（归母，GAAP） | C14: ='特斯拉财务'!$G$83 -> 3218 | D14: ='SpaceX财务'!$G$95 -> -2760 | E14: =-'关联交易'!$G$19*(1-TAX_ELIM)+'特斯拉财务'!$G$87 -> -886.47 | F14: =C14+D14+E14 -> -428.47 | K14: 抵销关联未实现利润（税后）并剔除特斯拉对 SpaceX 股权的公允价值损益（税后）
B15: 经营现金流 | C15: ='特斯拉财务'!$G$88 -> 18710 | D15: ='SpaceX财务'!$G$99 -> 15762 | E15: =-'关联交易'!$G$19 -> -293 | F15: =C15+D15+E15 -> 34179 | G15: =IF(F15=0,0,C15/(C15+D15)) -> 0.54275934 | H15: =IF(F15=0,0,D15/(C15+D15)) -> 0.45724066 | K15: 内部 Megapack 交易：特斯拉收款与 SpaceX 付款对冲，生产成本重分类为资本开支（以已确认收入/成本近似，忽略收付款时间差）
B16: 资本开支 | C16: ='特斯拉财务'!$G$89 -> 15407 | D16: ='SpaceX财务'!$G$100 -> 54960 | E16: =-'关联交易'!$G$19 -> -293 | F16: =C16+D16+E16 -> 70074 | G16: =IF(F16=0,0,C16/(C16+D16)) -> 0.21895207 | H16: =IF(F16=0,0,D16/(C16+D16)) -> 0.78104793 | K16: 同上；经营现金流与资本开支同减关联毛利，自由现金流不变
B17: 自由现金流 | C17: =C15-C16 -> 3303 | D17: =D15-D16 -> -39198 | E17: =E15-E16 -> 0 | F17: =C17+D17+E17 -> -35895 | K17: 经营现金流−资本开支
B19: B. 最近完整财年 FY2025 损益与现金流
B20: 项目 | C20: 特斯拉 | D20: SpaceX | E20: 关联交易抵销/调整 | F20: 合并备考 | G20: 特斯拉占比 | H20: SpaceX占比 | K20: 说明
B21: 营收 | C21: ='特斯拉财务'!$H$77 -> 94827 | D21: ='SpaceX财务'!$H$89 -> 18674 | E21: =-'关联交易'!$E$20 -> -430 | F21: =C21+D21+E21 -> 113071 | G21: =IF(F21=0,0,C21/(C21+D21)) -> 0.83547282 | H21: =IF(F21=0,0,D21/(C21+D21)) -> 0.16452718 | K21: 抵销特斯拉对 SpaceX 的 Megapack 销售
B22: 营业成本 | C22: ='特斯拉财务'!$H$78 -> 77733 | D22: ='SpaceX财务'!$H$90 -> 9451 | E22: =-'关联交易'!$F$20 -> -285 | F22: =C22+D22+E22 -> 86899
B23: 毛利 | C23: =C21-C22 -> 17094 | D23: =D21-D22 -> 9223 | E23: =E21-E22 -> -145 | F23: =C23+D23+E23 -> 26172 | G23: =IF(F23=0,0,C23/(C23+D23)) -> 0.64954212 | H23: =IF(F23=0,0,D23/(C23+D23)) -> 0.35045788 | K23: 抵销关联未实现利润
B24: 毛利率 | C24: =IF(C21=0,0,C23/C21) -> 0.18026511 | D24: =IF(D21=0,0,D23/D21) -> 0.49389526 | F24: =IF(F21=0,0,F23/F21) -> 0.23146519
B25: 经营利润（GAAP） | C25: ='特斯拉财务'!$H$81 -> 4355 | D25: ='SpaceX财务'!$H$93 -> -2589 | E25: =-'关联交易'!$G$20 -> -145 | F25: =C25+D25+E25 -> 1621
B26: 经营利润率 | C26: =IF(C21=0,0,C25/C21) -> 0.045925738 | D26: =IF(D21=0,0,D25/D21) -> -0.13864196 | F26: =IF(F21=0,0,F25/F21) -> 0.014336125
B27: EBITDA（统一口径） | C27: ='特斯拉财务'!$H$85 -> 10503 | D27: ='SpaceX财务'!$H$97 -> 4112 | E27: =-'关联交易'!$G$20 -> -145 | F27: =C27+D27+E27 -> 14470 | G27: =IF(F27=0,0,C27/(C27+D27)) -> 0.71864523 | H27: =IF(F27=0,0,D27/(C27+D27)) -> 0.28135477 | K27: 经营利润+折旧摊销
B28: 调整后EBITDA（公司口径简单加总，非GAAP） | C28: ='特斯拉财务'!$H$86 -> 14596 | D28: ='SpaceX财务'!$H$98 -> 6584 | E28: =-'关联交易'!$G$20 -> -145 | F28: =C28+D28+E28 -> 21035 | K28: 两家定义不同，仅作参考
B29: 净利润（归母，GAAP） | C29: ='特斯拉财务'!$H$83 -> 3794 | D29: ='SpaceX财务'!$H$95 -> -4937 | E29: =-'关联交易'!$G$20*(1-TAX_ELIM)+'特斯拉财务'!$H$87 -> -114.55 | F29: =C29+D29+E29 -> -1257.55 | K29: 抵销关联未实现利润（税后）并剔除特斯拉对 SpaceX 股权的公允价值损益（税后）
B30: 经营现金流 | C30: ='特斯拉财务'!$H$88 -> 14747 | D30: ='SpaceX财务'!$H$99 -> 6785 | E30: =-'关联交易'!$G$20 -> -145 | F30: =C30+D30+E30 -> 21387 | G30: =IF(F30=0,0,C30/(C30+D30)) -> 0.68488761 | H30: =IF(F30=0,0,D30/(C30+D30)) -> 0.31511239 | K30: 内部 Megapack 交易：特斯拉收款与 SpaceX 付款对冲，生产成本重分类为资本开支（以已确认收入/成本近似，忽略收付款时间差）
B31: 资本开支 | C31: ='特斯拉财务'!$H$89 -> 8527 | D31: ='SpaceX财务'!$H$100 -> 20737 | E31: =-'关联交易'!$G$20 -> -145 | F31: =C31+D31+E31 -> 29119 | G31: =IF(F31=0,0,C31/(C31+D31)) -> 0.2913819 | H31: =IF(F31=0,0,D31/(C31+D31)) -> 0.7086181 | K31: 同上；经营现金流与资本开支同减关联毛利，自由现金流不变
B32: 自由现金流 | C32: =C30-C31 -> 6220 | D32: =D30-D31 -> -13952 | E32: =E30-E31 -> 0 | F32: =C32+D32+E32 -> -7732 | K32: 经营现金流−资本开支
B34: C. 合并后营收结构（五个分部；关联抵销计入特斯拉能源分部）
B35: 分部 | C35: LTM 营收 | D35: LTM 占比 | E35: FY2025 营收 | F35: FY2025 占比 | G35: 2026Q3 年化（示意） | H35: 年化占比 | I35: 季度复合增速* | K35: 说明
B36: 特斯拉 · 汽车（含服务及其他） | C36: ='特斯拉财务'!$G$98 -> 91305 | D36: =C36/$C$41 -> 0.67856002 | E36: ='特斯拉财务'!$H$98 -> 82056 | F36: =E36/$E$41 -> 0.72570332 | G36: =('特斯拉财务'!$F$98)*RUNRATE_X -> 100660 | H36: =G36/$G$41 -> 0.59351415 | I36: =IF('特斯拉财务'!$C$98<=0,0,('特斯拉财务'!$F$98/'特斯拉财务'!$C$98)^(1/3)-1) -> 0.061089531
B37: 特斯拉 · 能源发电与储能（已抵销关联销售） | C37: ='特斯拉财务'!$G$99-'关联交易'!$E$19 -> 11209 | D37: =C37/$C$41 -> 0.083302987 | E37: ='特斯拉财务'!$H$99-'关联交易'!$E$20 -> 12341 | F37: =E37/$E$41 -> 0.10914381 | G37: =('特斯拉财务'!$F$99-'关联交易'!$E$21)*RUNRATE_X -> 10640 | H37: =G37/$G$41 -> 0.062735849 | I37: =IF('特斯拉财务'!$C$99<=0,0,('特斯拉财务'!$F$99/'特斯拉财务'!$C$99)^(1/3)-1) -> -0.091097803
B38: SpaceX · 连接（Starlink） | C38: ='SpaceX财务'!$G$111 -> 16024 | D38: =C38/$C$41 -> 0.11908708 | E38: ='SpaceX财务'!$H$111 -> 11387 | F38: =E38/$E$41 -> 0.10070664 | G38: =('SpaceX财务'!$F$111)*RUNRATE_X -> 20992 | H38: =G38/$G$41 -> 0.12377358 | I38: =IF('SpaceX财务'!$C$111<=0,0,('SpaceX财务'!$F$111/'SpaceX财务'!$C$111)^(1/3)-1) -> 0.17585409
B39: SpaceX · SI（超级智能/AI、X 平台） | C39: ='SpaceX财务'!$G$112 -> 11862 | D39: =C39/$C$41 -> 0.088155949 | E39: ='SpaceX财务'!$H$112 -> 3201 | F39: =E39/$E$41 -> 0.028309646 | G39: =('SpaceX财务'!$F$112)*RUNRATE_X -> 30240 | H39: =G39/$G$41 -> 0.17830189 | I39: =IF('SpaceX财务'!$C$112<=0,0,('SpaceX财务'!$F$112/'SpaceX财务'!$C$112)^(1/3)-1) -> 1.0157656
B40: SpaceX · 航天（发射与研发合同） | C40: ='SpaceX财务'!$G$110 -> 4157 | D40: =C40/$C$41 -> 0.030893971 | E40: ='SpaceX财务'!$H$110 -> 4086 | F40: =E40/$E$41 -> 0.036136587 | G40: =('SpaceX财务'!$F$110)*RUNRATE_X -> 7068 | H40: =G40/$G$41 -> 0.041674528 | I40: =IF('SpaceX财务'!$C$110<=0,0,('SpaceX财务'!$F$110/'SpaceX财务'!$C$110)^(1/3)-1) -> 0.29746607
B41: 合并营收（抵销后） | C41: =SUM(C36:C40) -> 134557 | D41: =SUM(D36:D40) -> 1 | E41: =SUM(E36:E40) -> 113071 | F41: =SUM(F36:F40) -> 1 | G41: =SUM(G36:G40) -> 169600 | H41: =SUM(H36:H40) -> 1 | K41: *2025Q4 至 2026Q3 的季度复合增速，仅描述历史
B42: 校验：分部合计 − A 部分合并营收（LTM / FY2025） | C42: =C41-F6 -> 0 | E42: =E41-F21 -> 0
B44: D. 合并后利润结构（LTM）
B45: 分部 | C45: 分部毛利 | D45: 毛利占比 | E45: 分部毛利率 | F45: 经营利润* | G45: 经营利润率 | H45: 分部调整后EBITDA* | K45: 说明
B46: 特斯拉 · 汽车（含服务及其他）〔经营利润为特斯拉整体〕 | C46: ='特斯拉财务'!$G$100 -> 16330 | D46: =C46/$C$51 -> 0.43131455 | E46: =IF('合并备考'!$C$36=0,0,C46/'合并备考'!$C$36) -> 0.1788511 | F46: ='特斯拉财务'!$G$81-'关联交易'!$G$19 -> 3173 | G46: =F46/('合并备考'!$C$36+'合并备考'!$C$37) -> 0.03095187 | H46: —
B47: 特斯拉 · 能源发电与储能（已抵销） | C47: ='特斯拉财务'!$G$101-'关联交易'!$G$19 -> 3351 | D47: =C47/$C$51 -> 0.088507963 | E47: =IF('合并备考'!$C$37=0,0,C47/'合并备考'!$C$37) -> 0.2989562 | F47: ↑ 特斯拉整体 | G47: ↑ | H47: —
B48: SpaceX · 连接（Starlink） | C48: ='SpaceX财务'!$G$114 -> 8295 | D48: =C48/$C$51 -> 0.21909089 | E48: =IF('合并备考'!$C$38=0,0,C48/'合并备考'!$C$38) -> 0.51766101 | F48: ='SpaceX财务'!$G$117 -> 6487 | G48: =IF('合并备考'!$C$38=0,0,F48/'合并备考'!$C$38) -> 0.40483025 | H48: ='SpaceX财务'!$G$120 -> 10228
B49: SpaceX · SI（超级智能/AI、X 平台） | C49: ='SpaceX财务'!$G$115 -> 7021 | D49: =C49/$C$51 -> 0.18544148 | E49: =IF('合并备考'!$C$39=0,0,C49/'合并备考'!$C$39) -> 0.59189007 | F49: ='SpaceX财务'!$G$118 -> -5468 | G49: =IF('合并备考'!$C$39=0,0,F49/'合并备考'!$C$39) -> -0.4609678 | H49: ='SpaceX财务'!$G$121 -> 5066
B50: SpaceX · 航天（发射与研发合同） | C50: ='SpaceX财务'!$G$113 -> 2864 | D50: =C50/$C$51 -> 0.075645123 | E50: =IF('合并备考'!$C$40=0,0,C50/'合并备考'!$C$40) -> 0.68895838 | F50: ='SpaceX财务'!$G$116 -> -1687 | G50: =IF('合并备考'!$C$40=0,0,F50/'合并备考'!$C$40) -> -0.40582151 | H50: ='SpaceX财务'!$G$119 -> -349
B51: 合计（抵销后） | C51: =SUM(C46:C50) -> 37861 | D51: =SUM(D46:D50) -> 1 | E51: =C51/C41 -> 0.28137518 | F51: =SUM(F46:F50) -> 2505 | G51: =F51/C41 -> 0.018616646 | K51: *特斯拉未披露分部经营利润，经营利润以公司整体（已扣关联未实现利润）列示于汽车行；分部调整后EBITDA 仅 SpaceX 披露（非GAAP）
B52: 校验：分部毛利合计 − A 部分合并毛利；经营利润合计 − A 部分合并经营利润 | C52: =C51-F8 -> 0 | F52: =F51-F10 -> 0
B54: E. 现金与负债（2026-09-30）
B55: 项目 | C55: 特斯拉 | D55: SpaceX | E55: 抵销/调整 | F55: 合并（简单加总） | K55: 说明
B56: 现金和短期投资 | C56: ='特斯拉财务'!$G$91 -> 45447 | D56: ='SpaceX财务'!$G$102 -> 89855 | E56: =0 -> 0 | F56: =C56+D56+E56 -> 135302 | K56: 内部往来不涉及现金
B57: 有息负债（含融资租赁） | C57: ='特斯拉财务'!$G$92 -> 9523 | D57: ='SpaceX财务'!$G$103 -> 38844 | E57: =0 -> 0 | F57: =C57+D57+E57 -> 48367 | K57: SpaceX 含关联方（Valor）融资 12,897
B58: 净现金 | C58: =C56-C57 -> 35924 | D58: =D56-D57 -> 51011 | E58: =E56-E57 -> 0 | F58: =C58+D58+E58 -> 86935 | K58: 现金和短期投资−有息负债
B59: 股东权益（归母） | C59: ='特斯拉财务'!$G$94 -> 89289 | D59: ='SpaceX财务'!$G$106 -> 176768 | E59: =-'关联交易'!$E$14-'关联交易'!$G$22 -> -3158 | F59: =C59+D59+E59 -> 262899 | K59: 剔除特斯拉持有的 SpaceX 股权（转库存股）及关联未实现利润；未作 PPA
B60: 备查：关联应收/应付对冲 | C60: ='关联交易'!$E$12 -> 729 | D60: =0 -> 0 | E60: =-'关联交易'!$E$12 -> -729 | F60: =C60+D60+E60 -> 0 | K60: 特斯拉应收 SpaceX 729 与 SpaceX 应付对冲（总资产、总负债同减）
B61: 备查：关联递延收入/预付对冲 | C61: ='关联交易'!$E$13 -> 648 | D61: =0 -> 0 | E61: =-'关联交易'!$E$13 -> -648 | F61: =C61+D61+E61 -> 0 | K61: 特斯拉递延收入 648 与 SpaceX 预付对冲
B63: F. 购买法会计影响（示意；全部基于假设 A06、A10、A11 与方法①）
B64: 收购对价（方法①，含基准溢价） | C64: ='换股比例'!$K$64*1000 -> 1477185.2 | K64: 换股比例×SpaceX 每股价值×特斯拉股本；若收购方为特斯拉则为对 SpaceX 的对价
B65: 被收购方账面归母权益（2026-09-30） | C65: =IF(ACQ="SpaceX",'特斯拉财务'!$G$94,'SpaceX财务'!$G$106) -> 89289 | K65: 未作公允价值调整
B66: 超额对价（商誉+可辨认无形资产等，待 PPA） | C66: =C64-C65 -> 1387896.2 | K66: 对价−账面权益
B67: 其中：有限寿命无形资产（假设 A10 比例） | C67: =C66*PPA_INT_SHARE -> 277579.23 | K67: 示意
B68: 年度摊销（假设 A11 年限，直线） | C68: =C67/PPA_LIFE -> 27757.923 | K68: 示意
B69: LTM 合并经营利润（扣除示意摊销后） | C69: =F10-C68 -> -25252.923 | K69: 仅说明 GAAP 利润可能被摊销显著压低

Sheet 关联交易
B1: 关联交易：两家之间及与马斯克旗下其他公司之间
B2: 金额单位：百万美元。A 部分为参与合并抵销计算的披露数（蓝底）；B 部分为全部识别出的关联交易清单及合并时处理建议。
B4: A. 抵销计算所用披露数
B5: # | C5: 项目 | E5: 金额 | G5: 出处
B6: 1 | C6: 特斯拉向 xAI（现属SpaceX）销售 Megapack 确认收入：2025年度 | E6: 430 | G6: Tesla_2025年报__tsla-20251231.htm（10-K） · 附注15 Related Party Transactions：$430 million of revenues
B7: 2 | C7: 同上，对应营业成本：2025年度 | E7: 285 | G7: Tesla_2025年报__tsla-20251231.htm（10-K） · 附注15：$285 million of cost of revenues
B8: 3 | C8: 特斯拉向 SpaceX 销售 Megapack 确认收入：2026年前三季度 | E8: 626 | G8: Tesla_2026Q3季报__tsla-20260930.htm（10-Q） · 附注13 Related Party Transactions：$626 million of revenues (nine months)
B9: 4 | C9: 同上，对应营业成本：2026年前三季度 | E9: 478 | G9: Tesla_2026Q3季报__tsla-20260930.htm（10-Q） · 附注13：$478 million of cost of revenues (nine months)
B10: 5 | C10: 特斯拉向 SpaceX 销售 Megapack 确认收入：2026年第三季度 | E10: 221 | G10: Tesla_2026Q3季报__tsla-20260930.htm（10-Q） · 附注13：$221 million (three months)
B11: 6 | C11: 同上，对应营业成本：2026年第三季度 | E11: 171 | G11: Tesla_2026Q3季报__tsla-20260930.htm（10-Q） · 附注13：$171 million (three months)
B12: 7 | C12: 特斯拉对 SpaceX 应收账款（2026-09-30） | E12: 729 | G12: Tesla_2026Q3季报__tsla-20260930.htm（10-Q） · 附注13：accounts receivable from SpaceX was $729 million
B13: 8 | C13: 特斯拉对 SpaceX 递延收入（2026-09-30，流动516+非流动132） | E13: 648 | G13: Tesla_2026Q3季报__tsla-20260930.htm（10-Q） · 附注13：deferred revenue ... $648 million
B14: 9 | C14: 特斯拉持有 SpaceX 股权公允价值（2026-09-30） | E14: 2865 | G14: Tesla_2026Q3季报__tsla-20260930.htm（10-Q） · 附注2 Fair Value：SpaceX equity investment $2,865（Level I）
B15: 10 | C15: 特斯拉 SpaceX 股权投资成本（2026年3月） | E15: 2002 | G15: Tesla_2026Q3季报__tsla-20260930.htm（10-Q） · 合并现金流量表：Purchase of SpaceX equity investment (2,002)
B17: 抵销额（公式）
C18: 项目 | E18: 营收 | F18: 营业成本 | G18: 毛利（未实现利润）
C19: LTM（2025Q4–2026Q3） | E19: =RP_RP_REV_FY25*Q4_RP_SHARE+RP_RP_REV_9M26 -> 1056 | F19: =RP_RP_COGS_FY25*Q4_RP_SHARE+RP_RP_COGS_9M26 -> 763 | G19: =E19-F19 -> 293
C20: FY2025 | E20: =RP_RP_REV_FY25 -> 430 | F20: =RP_RP_COGS_FY25 -> 285 | G20: =E20-F20 -> 145
C21: 2026Q3 | E21: =RP_RP_REV_Q326 -> 221 | F21: =RP_RP_COGS_Q326 -> 171 | G21: =E21-F21 -> 50
C22: 累计（2025 年 + 2026 前三季度，用于资产负债表） | E22: =RP_RP_REV_FY25+RP_RP_REV_9M26 -> 1056 | F22: =RP_RP_COGS_FY25+RP_RP_COGS_9M26 -> 763 | G22: =E22-F22 -> 293
C23: 说明：LTM 抵销 = 2025 年全年 × 假设 A08（落在 Q4 的比例）+ 2026 前三季度；仅抵销披露了收入与成本的 Megapack 交易，其余小额交易见 B 部分（未计入，金额不重大）。
B25: B. 关联交易清单与合并处理
B26: # | C26: 交易对手 / 类别 | D26: 交易内容 | E26: 期间 | F26: 金额（百万美元） | G26: 出处 | H26: 合并时怎么处理
B27: 1 | C27: 特斯拉 ↔ SpaceX（含 xAI） | D27: 特斯拉向 xAI/SpaceX 销售 Megapack 储能（特斯拉确认收入；SpaceX 计入固定资产） | E27: 2025年度 | F27: 收入 430 / 成本 285 | G27: Tesla 10-K 附注15；SpaceX 招股书附注18（SpaceX 侧：2024 年购买 191、2025 年 506） | H27: 内部交易：抵销特斯拉收入与成本；SpaceX 固定资产中所含未实现利润同步冲减（并调减后续折旧）。见 A 部分。
B28: 2 | C28: 特斯拉 ↔ SpaceX | D28: 同上（Megapack） | E28: 2026前三季度（其中Q3） | F28: 收入 626（221）/ 成本 478（171） | G28: Tesla 10-Q 附注13；SpaceX Q2 10-Q 附注17（SpaceX 侧：2026上半年购买 329） | H28: 同上；LTM 抵销收入 1,056、未实现毛利 293（含假设 A08）。
B29: 3 | C29: 特斯拉 ↔ SpaceX | D29: 特斯拉对 SpaceX 应收账款 729（含未交付 Megapack 里程碑开票 588）；递延收入 648 | E29: 2026-09-30 | F29: 应收 729；递延收入 648 | G29: Tesla 10-Q 附注13 | H29: 内部往来：与 SpaceX 应付款/预付款对冲抵销，不影响净资产。
B30: 4 | C30: 特斯拉 → SpaceX（股权） | D30: 特斯拉持有 SpaceX A 类股 18,990,195 股（2026-03 以 20.02 亿美元认购原 xAI 优先股转换而来），按公允价值计量 | E30: 2026-09-30 | F30: 公允价值 2,865；2026 前三季度公允价值收益 863 | G30: Tesla 10-Q 附注1、2、13；SpaceX 招股书“Transactions with Tesla”及附注21 | H30: 交叉持股：若 SpaceX 为存续主体，该部分转为库存股（冲减权益），不参与换股；合并报表剔除其公允价值变动损益。
B31: 5 | C31: 特斯拉 ↔ SpaceX | D31: 车辆销售（主要为 Cybertruck，SpaceX 按建议零售价购入，计入固定资产） | E31: 2025年度 | F31: 特斯拉确认收入约 143.3；SpaceX 购入 131 | G31: Tesla 委托书“Related Person Transactions”；SpaceX 招股书附注18 | H31: 内部交易：抵销；金额小，季度分布未披露，本模型未计入抵销（待核实）。
B32: 6 | C32: SpaceX ↔ 特斯拉 | D32: SpaceX 商务/许可/支持协议：SpaceX 自特斯拉取得商品服务；特斯拉相应费用 | E32: 2025年度 | F32: SpaceX 侧 147；特斯拉侧费用 11.4 | G32: SpaceX 招股书 Certain Relationships；Tesla 委托书 | H32: 内部交易：抵销（双方口径不一致，需核对）。
B33: 7 | C33: xAI ↔ 特斯拉 | D33: xAI 商务/咨询/支持协议；xAI 自特斯拉取得 1 百万美元收入（2026年1–4月） | E33: 2025年度 | F33: xAI 收入 2；特斯拉费用 4.0 | G33: SpaceX 招股书；Tesla 委托书 | H33: 内部交易：抵销（不重大）。
B34: 8 | C34: 特斯拉 → X（SpaceX） | D34: 特斯拉在 X 平台投放广告 | E34: 2025年度 | F34: SpaceX 侧 4；特斯拉侧 3.3 | G34: SpaceX 招股书；Tesla 委托书 | H34: 内部交易：抵销（不重大）。
B35: 9 | C35: SpaceX → 特斯拉 | D35: SpaceX 自有飞机供马斯克及特斯拉人员公务使用并向特斯拉收费 | E35: 2025年度 | F35: SpaceX 收费 2；特斯拉费用 0.4 | G35: SpaceX 招股书；Tesla 委托书 | H35: 内部交易：抵销（不重大）。
B36: 10 | C36: 特斯拉 ↔ SpaceX（战略合作） | D36: Terafab 芯片制造框架（2026-03 宣布，Intel 2026-04 加入）；Macrohard 智能体平台联合开发；2026-01 xAI–特斯拉合作框架协议 | E36: 2026年 | F36: 未披露财务条款 | G36: SpaceX 招股书 Business、Risk Factors；Tesla 委托书 | H36: 合并后转为内部项目；需核实成本分摊、知识产权归属与资本开支承诺。
B37: 11 | C37: 马斯克控制的安保公司 | D37: 为马斯克提供安保服务（与公司职务相关部分由公司承担） | E37: 2025年度 | F37: 特斯拉 4.8；SpaceX 4 | G37: Tesla 委托书；SpaceX 招股书 | H37: 合并后仍为关联交易（对手方为马斯克个人公司），需持续披露与审批。
B38: 12 | C38: The Boring Company（马斯克创办） | D38: 特斯拉商务协议；X 向其子公司租赁办公室；SpaceX 隧道工程 | E38: 2025年度 | F38: 特斯拉 0.9；X 租金 1；SpaceX 工程 1 | G38: Tesla 委托书；SpaceX 招股书 | H38: 合并后仍为关联交易。
... B45: 19 | C45: 董事交叉任职 | D45: Ira Ehrenpreis 同时任特斯拉董事（薪酬与治理委员会主席）与 SpaceX 董事（2026-02 起）；Kimbal Musk 任特斯拉董事、曾任 SpaceX 董事；马斯克任两家 CEO | E45: — | F45: — | G45: Tesla 委托书董事简介；SpaceX 招股书 Management | H45: 影响特别委员会独立性认定；交叉任职董事应回避。

Sheet 换股比例
B1: 换股比例：定价方法、合并后股权与马斯克持股
B2: 单位：股数为百万股，金额为百万美元（另注明为十亿美元），股价为美元/股。基准情形：SpaceX 发行 A 类股吸收合并特斯拉（见假设 A01），溢价给予被收购方股东。
B4: A. 股本与持股（披露数据，百万股）
B5: 项目 | C5: 数值 | N5: 出处
B6: 特斯拉已发行在外普通股 | C6: 3952.7579 | N6: Tesla_2026Q3季报__tsla-20260930.htm（10-Q） · 封面：As of October 15, 2026, 3,952,757,946 shares outstanding
B7: SpaceX A类普通股（已发行在外） | C7: 8240 | N7: SpaceX_2026Q3业绩公告__spaceexplorationtechnologi.htm（8-K 附件99.1） · Consolidated Balance Sheets · September 30, 2026：Class A 8,240 shares outstanding（百万股）
B8: SpaceX B类普通股（已发行在外，10票/股） | C8: 5339 | N8: SpaceX_2026Q3业绩公告__spaceexplorationtechnologi.htm（8-K 附件99.1） · Consolidated Balance Sheets · September 30, 2026：Class B 5,339 shares（百万股）
B9: 特斯拉持有的 SpaceX A类股 | C9: 18.990195 | N9: SpaceX_招股书__spaceexplorationtechnologi.htm（424B4，2026-06-11） · Certain Relationships and Related Person Transactions · Transactions with Tesla：18,990,195 shares（as of May 1, 2026）
B10: 马斯克持有 SpaceX A类股 | C10: 849.49444 | N10: SpaceX_招股书__spaceexplorationtechnologi.htm（424B4，2026-06-11） · Security Ownership of Certain Beneficial Owners and Management：849,494,440 Class A
B11: 马斯克持有 SpaceX B类股（已发行，含限制性股） | C11: 5219.0531 | N11: SpaceX_招股书__spaceexplorationtechnologi.htm（424B4，2026-06-11） · Prospectus Summary/Security Ownership：5,219,053,075 Class B（不含3.5亿股期权）
B12: 其中：尚未达成业绩条件的限制性B类股 | C12: 1302.0723 | N12: SpaceX_招股书__spaceexplorationtechnologi.htm（424B4，2026-06-11） · Security Ownership 脚注(1)：1,302,072,285 restricted Class B（SpaceX CEO Award 10亿股 + AI CEO Award 3.021亿股）
B13: 马斯克 SpaceX B类期权（60日内可行权，未计入已发行） | C13: 350 | N13: SpaceX_招股书__spaceexplorationtechnologi.htm（424B4，2026-06-11） · Security Ownership 脚注(1)：350,000,000 Class B issuable upon exercise of options
B14: 马斯克特斯拉实益持股（委托书口径） | C14: 699.58088 | N14: Tesla_2026股东大会委托书__tm267596-1_def14a.htm（DEF 14A） · Ownership of Securities（as of September 30, 2026）：699,580,882 shares，19.8%
B15: 其中：2018年奖励行权所得限制性股（服务期条件） | C15: 286.42877 | N15: Tesla_2026股东大会委托书__tm267596-1_def14a.htm（DEF 14A） · Ownership of Securities 脚注(2)：286,428,773 shares of restricted stock
B16: 马斯克 2025 CEO 业绩奖励限制性股（未赚取，按比例投票） | C16: 423.7439 | N16: Tesla_2026股东大会委托书__tm267596-1_def14a.htm（DEF 14A） · Ownership of Securities 脚注(2)；Tesla_2026Q3季报__tsla-20260930.htm（10-Q） 附注9：423,743,904 shares
B17: 特斯拉股数（委托书计算基数，2026-09-30，备查） | C17: 3952.6486 | N17: Tesla_2026股东大会委托书__tm267596-1_def14a.htm（DEF 14A） · Ownership of Securities：based on 3,952,648,559 shares outstanding at September 30, 2026
B18: SpaceX 已发行在外普通股合计（A+B） | C18: =N_S_A+N_S_B -> 13579 | N18: 计算值（2026-09-30）
B19: SpaceX 股本（剔除特斯拉持有部分，合并后成为库存股） | C19: =N_S-X_TS_SPCX -> 13560.01
B20: 马斯克持有 SpaceX 已发行股份合计（A+B，不含期权） | C20: =M_S_A+M_S_B -> 6068.5475
B21: 马斯克持有特斯拉已发行股份合计（含 2025 业绩股） | C21: =M_T_BEN+M_T_RS25 -> 1123.3248
B23: B. 马斯克持股：合并前
B24: 口径 | C24: SpaceX | D24: 特斯拉 | N24: 计算方法
B25: 经济持股 · 口径A（含全部已发行限制性股，上限） | C25: =M_S_ALL/N_S -> 0.44690681 | D25: =M_T_ALL/N_T -> 0.2841876 | N25: SpaceX：(A+B)/总股本；特斯拉：(实益持股+2025业绩股)/总股本
B26: 经济持股 · 口径B（剔除未达成业绩条件的业绩股） | C26: =(M_S_ALL-M_S_RS)/(N_S-M_S_RS) -> 0.38824658 | D26: =M_T_BEN/(N_T-M_T_RS25) -> 0.19823692 | N26: 特斯拉口径B 与委托书 19.8% 一致（分母差异来自股本日期）
B27: 表决权（示意） | C27: =(M_S_A+10*M_S_B)/(N_S_A+10*N_S_B) -> 0.86062024 | D27: =M_T_BEN/(N_T-M_T_RS25) -> 0.19823692 | N27: SpaceX B 类 10 票/股（含可由马斯克投票的限制性 B 类股，不含期权）；特斯拉 2025 业绩股按比例投票，故剔除
B28: 对照：招股书披露马斯克表决权 84.4%（IPO 后、含期权）；委托书披露特斯拉实益持股 19.8%
B30: C. 倍数法：企业价值与贡献度（基准日市场 EV；LTM 指标）
B31: 项目 | C31: 特斯拉 | D31: SpaceX | E31: 合计 | N31: 计算方法 / 出处
B32: 股权市值（基准日收盘） | C32: =P_T_U*N_T -> 1477185.2 | D32: =P_S_U*N_S -> 2006840.4 | E32: =C32+D32 -> 3484025.6 | N32: 收盘价×已发行股本
B33: 加：有息负债（2026-09-30） | C33: ='特斯拉财务'!$G$92 -> 9523 | D33: ='SpaceX财务'!$G$103 -> 38844 | E33: =C33+D33 -> 48367 | N33: 财务表标准化 LTM 列
B34: 减：现金和短期投资（2026-09-30） | C34: ='特斯拉财务'!$G$91 -> 45447 | D34: ='SpaceX财务'!$G$102 -> 89855 | E34: =C34+D34 -> 135302 | N34: 同上
B35: 加：少数股东权益（含可赎回） | C35: ='特斯拉财务'!$G$95 -> 600 | D35: =0 -> 0 | E35: =C35+D35 -> 600 | N35: SpaceX 无少数股东
B36: 减：特斯拉持有的 SpaceX 股权（按基准日股价） | C36: =X_TS_SPCX*P_S_U -> 2806.5609 | D36: =0 -> 0 | E36: =C36+D36 -> 2806.5609 | N36: 非经营性资产；合并后变为库存股
B37: 企业价值 EV | C37: =C32+C33-C34+C35-C36 -> 1439054.6 | D37: =D32+D33-D34+D35-D36 -> 1955829.4 | E37: =C37+D37 -> 3394884 | N37: 市值+负债−现金+少数股东−非经营性股权
B38: LTM 营收 | C38: ='特斯拉财务'!$G$77 -> 103570 | D38: ='SpaceX财务'!$G$89 -> 32043 | E38: =C38+D38 -> 135613 | N38: 2025Q4–2026Q3
B39: LTM EBITDA（按假设 A07 口径） | C39: =IF(EBITDA_BASIS="公司口径",'特斯拉财务'!$G$86,'特斯拉财务'!$G$85) -> 10170 | D39: =IF(EBITDA_BASIS="公司口径",'SpaceX财务'!$G$98,'SpaceX财务'!$G$97) -> 10183 | E39: =C39+D39 -> 20353 | N39: 统一口径=经营利润+折旧摊销；公司口径=各自调整后EBITDA
B40: 营收贡献占比 | C40: =C38/E38 -> 0.76371734 | D40: =D38/E38 -> 0.23628266 | E40: =C40+D40 -> 1 | N40: LTM 营收/合计
B41: EBITDA 贡献占比 | C41: =C39/E39 -> 0.49968064 | D41: =D39/E39 -> 0.50031936 | E41: =C41+D41 -> 1 | N41: LTM EBITDA/合计
B42: 备查：EV/LTM 营收（基准日市场隐含，倍） | C42: =C37/C38 -> 13.894512 | D42: =D37/D38 -> 61.03765 | E42: =E37/E38 -> 25.033618 | N42: 仅作计算中间量，不作评价
B43: 备查：EV/LTM EBITDA（基准日市场隐含，倍） | C43: =C37/C39 -> 141.49996 | D43: =D37/D39 -> 192.06809 | E43: =E37/E39 -> 166.80018 | N43: 同上
B45: 倍数法隐含价值 | C45: 特斯拉 | D45: SpaceX | E45: 合计 | N45: 计算方法
B46: 方法④ 营收贡献法：分配 EV（合计 EV×贡献占比） | C46: =$E$37*C40 -> 2592731.8 | D46: =$E$37*D40 -> 802152.22 | E46: =C46+D46 -> 3394884 | N46: 相当于两家按同一 EV/指标 倍数定价
B47: 方法④ 营收贡献法：隐含股权价值（EV−负债+现金−少数股东+非经营性股权） | C47: =C46-C33+C34-C35+C36 -> 2630862.4 | D47: =D46-D33+D34-D35+D36 -> 853163.22 | E47: =C47+D47 -> 3484025.6
B48: 方法④ 营收贡献法：隐含每股价值（美元） | C48: =C47/N_T -> 665.57639 | D48: =D47/N_S -> 62.829606
B49: 方法⑤ EBITDA 贡献法：分配 EV（合计 EV×贡献占比） | C49: =$E$37*C41 -> 1696357.8 | D49: =$E$37*D41 -> 1698526.2 | E49: =C49+D49 -> 3394884 | N49: 相当于两家按同一 EV/指标 倍数定价
B50: 方法⑤ EBITDA 贡献法：隐含股权价值（EV−负债+现金−少数股东+非经营性股权） | C50: =C49-C33+C34-C35+C36 -> 1734488.4 | D50: =D49-D33+D34-D35+D36 -> 1749537.2 | E50: =C50+D50 -> 3484025.6
B51: 方法⑤ EBITDA 贡献法：隐含每股价值（美元） | C51: =C50/N_T -> 438.8046 | D51: =D50/N_S -> 128.84139
B53: D. 各定价方法下的每股价值与相对价值
B54: 定价方法 | C54: 特斯拉每股价值（美元） | D54: SpaceX每股价值（美元） | E54: 特斯拉股权价值（十亿美元） | F54: SpaceX股权价值（十亿美元） | G54: 相对价值 R（特斯拉÷SpaceX 每股） | H54: 特斯拉股权价值占两家合计 | N54: 方法说明
B55: ① 不受影响日收盘市值 | C55: =P_T_U -> 373.71 | D55: =P_S_U -> 147.79 | E55: =C55*N_T/1000 -> 1477.1852 | F55: =D55*N_S/1000 -> 2006.8404 | G55: =C55/D55 -> 2.5286555 | H55: =E55/(E55+F55-X_TS_SPCX*D55/1000) -> 0.42432986 | N55: 按假设 A02 基准日收盘价×股本；两家消息前最后一个收盘
B56: ② N 日成交量加权均价（VWAP） | C56: =P_T_VWAP -> 367.94223 | D56: =P_S_VWAP -> 153.56437 | E56: =C56*N_T/1000 -> 1454.3866 | F56: =D56*N_S/1000 -> 2085.2506 | G56: =C56/D56 -> 2.396013 | H56: =E56/(E56+F56-X_TS_SPCX*D56/1000) -> 0.41122457 | N56: 截至基准日的 N 个交易日（假设 A04，默认 30 日）典型价 VWAP
B57: ③ 消息公布后收盘价（参考） | C57: =P_T_P -> 386.47 | D57: =P_S_P -> 159.31 | E57: =C57*N_T/1000 -> 1527.6224 | F57: =D57*N_S/1000 -> 2163.2705 | G57: =C57/D57 -> 2.4258992 | H57: =E57/(E57+F57-X_TS_SPCX*D57/1000) -> 0.41422919 | N57: 假设 A03 参考日收盘；已反映合并预期，仅作对照
B58: ④ LTM 营收贡献法（同一 EV/营收） | C58: =C48 -> 665.57639 | D58: =D48 -> 62.829606 | E58: =C58*N_T/1000 -> 2630.8624 | F58: =D58*N_S/1000 -> 853.16322 | G58: =C58/D58 -> 10.593356 | H58: =E58/(E58+F58-X_TS_SPCX*D58/1000) -> 0.75538011 | N58: 合计 EV 按 LTM 营收占比分配后加回净现金
B59: ⑤ LTM EBITDA 贡献法（同一 EV/EBITDA） | C59: =C51 -> 438.8046 | D59: =D51 -> 128.84139 | E59: =C59*N_T/1000 -> 1734.4884 | F59: =D59*N_S/1000 -> 1749.5372 | G59: =C59/D59 -> 3.4057736 | H59: =E59/(E59+F59-X_TS_SPCX*D59/1000) -> 0.49819017 | N59: 合计 EV 按 LTM EBITDA 占比分配（口径见假设 A07）
B61: E. 换股比例与合并后股权（基准溢价率，假设 A06）
B62: 交易结构 | C62: =ACQ -> SpaceX | D62: =IF(ACQ="SpaceX","收购特斯拉","收购SpaceX") -> 收购特斯拉 | E62: 基准溢价率 | F62: =PREM -> 0 | G62: =IF(ACQ="SpaceX","换股比例 = 每1股特斯拉换取的SpaceX A类股数","换股比例 = 每1股SpaceX换取的特斯拉股数") -> 换股比例 = 每1股特斯拉换取的SpaceX A类股数
B63: 定价方法 | C63: 换股比例 | D63: 新发行股数（百万） | E63: 合并后总股数（百万） | F63: 特斯拉原股东占比 | G63: SpaceX原股东占比 | H63: 马斯克持股·口径A | I63: 马斯克持股·口径B | J63: 马斯克表决权（示意） | K63: 隐含对价（十亿美元） | L63: 每股被收购方对价（美元）
B64: ① 不受影响日收盘市值 | C64: =IF(ACQ="SpaceX",R_M1*(1+PREM),(1/R_M1)*(1+PREM)) -> 2.5286555 | D64: =IF(ACQ="SpaceX",C64*N_T,C64*N_S_EX) -> 9995.1632 | E64: =IF(ACQ="SpaceX",N_S_EX+D64,N_T+D64) -> 23555.173 | F64: =IF(ACQ="SpaceX",D64,N_T)/E64 -> 0.42432986 | G64: =1-F64 -> 0.57567014 | H64: =IF(ACQ="SpaceX",(M_S_ALL+C64*M_T_ALL)/(N_S_EX+C64*N_T),(M_T_ALL+C64*M_S_ALL)/(N_T+C64*N_S_EX)) -> 0.37822048 | I64: =IF(ACQ="SpaceX",(M_S_ALL-M_S_RS+C64*M_T_BEN)/(N_S_EX-M_S_RS+C64*(N_T-M_T_RS25)),(M_T_BEN+C64*(M_S_ALL-M_S_RS))/(N_T-M_T_RS25+C64*(N_S_EX-M_S_RS))) -> 0.30854491 | J64: =IF(ACQ="SpaceX",(M_S_A+10*M_S_B+C64*M_T_BEN)/(N_S_A-X_TS_SPCX+10*N_S_B+C64*(N_T-M_T_RS25)),(M_T_BEN+C64*M_S_ALL)/(N_T-M_T_RS25+C64*N_S_EX)) -> 0.77705083 | K64: =IF(ACQ="SpaceX",D64*PS_M1,D64*PT_M1)/1000 -> 1477.1852 | L64: =IF(ACQ="SpaceX",C64*PS_M1,C64*PT_M1) -> 373.71
B65: ② N 日成交量加权均价（VWAP） | C65: =IF(ACQ="SpaceX",R_M2*(1+PREM),(1/R_M2)*(1+PREM)) -> 2.396013 | D65: =IF(ACQ="SpaceX",C65*N_T,C65*N_S_EX) -> 9470.8594 | E65: =IF(ACQ="SpaceX",N_S_EX+D65,N_T+D65) -> 23030.869 | F65: =IF(ACQ="SpaceX",D65,N_T)/E65 -> 0.41122457 | G65: =1-F65 -> 0.58877543 | H65: =IF(ACQ="SpaceX",(M_S_ALL+C65*M_T_ALL)/(N_S_EX+C65*N_T),(M_T_ALL+C65*M_S_ALL)/(N_T+C65*N_S_EX)) -> 0.38036117 | I65: =IF(ACQ="SpaceX",(M_S_ALL-M_S_RS+C65*M_T_BEN)/(N_S_EX-M_S_RS+C65*(N_T-M_T_RS25)),(M_T_BEN+C65*(M_S_ALL-M_S_RS))/(N_T-M_T_RS25+C65*(N_S_EX-M_S_RS))) -> 0.31103772 | J65: =IF(ACQ="SpaceX",(M_S_A+10*M_S_B+C65*M_T_BEN)/(N_S_A-X_TS_SPCX+10*N_S_B+C65*(N_T-M_T_RS25)),(M_T_BEN+C65*M_S_ALL)/(N_T-M_T_RS25+C65*N_S_EX)) -> 0.78091774 | K65: =IF(ACQ="SpaceX",D65*PS_M2,D65*PT_M2)/1000 -> 1454.3866 | L65: =IF(ACQ="SpaceX",C65*PS_M2,C65*PT_M2) -> 367.94223
B66: ③ 消息公布后收盘价（参考） | C66: =IF(ACQ="SpaceX",R_M3*(1+PREM),(1/R_M3)*(1+PREM)) -> 2.4258992 | D66: =IF(ACQ="SpaceX",C66*N_T,C66*N_S_EX) -> 9588.9923 | E66: =IF(ACQ="SpaceX",N_S_EX+D66,N_T+D66) -> 23149.002 | F66: =IF(ACQ="SpaceX",D66,N_T)/E66 -> 0.41422919 | G66: =1-F66 -> 0.58577081 | H66: =IF(ACQ="SpaceX",(M_S_ALL+C66*M_T_ALL)/(N_S_EX+C66*N_T),(M_T_ALL+C66*M_S_ALL)/(N_T+C66*N_S_EX)) -> 0.37987038 | I66: =IF(ACQ="SpaceX",(M_S_ALL-M_S_RS+C66*M_T_BEN)/(N_S_EX-M_S_RS+C66*(N_T-M_T_RS25)),(M_T_BEN+C66*(M_S_ALL-M_S_RS))/(N_T-M_T_RS25+C66*(N_S_EX-M_S_RS))) -> 0.31046627 | J66: =IF(ACQ="SpaceX",(M_S_A+10*M_S_B+C66*M_T_BEN)/(N_S_A-X_TS_SPCX+10*N_S_B+C66*(N_T-M_T_RS25)),(M_T_BEN+C66*M_S_ALL)/(N_T-M_T_RS25+C66*N_S_EX)) -> 0.78004197 | K66: =IF(ACQ="SpaceX",D66*PS_M3,D66*PT_M3)/1000 -> 1527.6224 | L66: =IF(ACQ="SpaceX",C66*PS_M3,C66*PT_M3) -> 386.47
B67: ④ LTM 营收贡献法（同一 EV/营收） | C67: =IF(ACQ="SpaceX",R_M4*(1+PREM),(1/R_M4)*(1+PREM)) -> 10.593356 | D67: =IF(ACQ="SpaceX",C67*N_T,C67*N_S_EX) -> 41872.973 | E67: =IF(ACQ="SpaceX",N_S_EX+D67,N_T+D67) -> 55432.982 | F67: =IF(ACQ="SpaceX",D67,N_T)/E67 -> 0.75538011 | G67: =1-F67 -> 0.24461989 | H67: =IF(ACQ="SpaceX",(M_S_ALL+C67*M_T_ALL)/(N_S_EX+C67*N_T),(M_T_ALL+C67*M_S_ALL)/(N_T+C67*N_S_EX)) -> 0.32414505 | I67: =IF(ACQ="SpaceX",(M_S_ALL-M_S_RS+C67*M_T_BEN)/(N_S_EX-M_S_RS+C67*(N_T-M_T_RS25)),(M_T_BEN+C67*(M_S_ALL-M_S_RS))/(N_T-M_T_RS25+C67*(N_S_EX-M_S_RS))) -> 0.24530387 | J67: =IF(ACQ="SpaceX",(M_S_A+10*M_S_B+C67*M_T_BEN)/(N_S_A-X_TS_SPCX+10*N_S_B+C67*(N_T-M_T_RS25)),(M_T_BEN+C67*M_S_ALL)/(N_T-M_T_RS25+C67*N_S_EX)) -> 0.61064565 | K67: =IF(ACQ="SpaceX",D67*PS_M4,D67*PT_M4)/1000 -> 2630.8624 | L67: =IF(ACQ="SpaceX",C67*PS_M4,C67*PT_M4) -> 665.57639
B68: ⑤ LTM EBITDA 贡献法（同一 EV/EBITDA） | C68: =IF(ACQ="SpaceX",R_M5*(1+PREM),(1/R_M5)*(1+PREM)) -> 3.4057736 | D68: =IF(ACQ="SpaceX",C68*N_T,C68*N_S_EX) -> 13462.199 | E68: =IF(ACQ="SpaceX",N_S_EX+D68,N_T+D68) -> 27022.209 | F68: =IF(ACQ="SpaceX",D68,N_T)/E68 -> 0.49819017 | G68: =1-F68 -> 0.50180983 | H68: =IF(ACQ="SpaceX",(M_S_ALL+C68*M_T_ALL)/(N_S_EX+C68*N_T),(M_T_ALL+C68*M_S_ALL)/(N_T+C68*N_S_EX)) -> 0.36615576 | I68: =IF(ACQ="SpaceX",(M_S_ALL-M_S_RS+C68*M_T_BEN)/(N_S_EX-M_S_RS+C68*(N_T-M_T_RS25)),(M_T_BEN+C68*(M_S_ALL-M_S_RS))/(N_T-M_T_RS25+C68*(N_S_EX-M_S_RS))) -> 0.29448041 | J68: =IF(ACQ="SpaceX",(M_S_A+10*M_S_B+C68*M_T_BEN)/(N_S_A-X_TS_SPCX+10*N_S_B+C68*(N_T-M_T_RS25)),(M_T_BEN+C68*M_S_ALL)/(N_T-M_T_RS25+C68*N_S_EX)) -> 0.75271784 | K68: =IF(ACQ="SpaceX",D68*PS_M5,D68*PT_M5)/1000 -> 1734.4884 | L68: =IF(ACQ="SpaceX",C68*PS_M5,C68*PT_M5) -> 438.8046
B69: 注：口径A/B 定义见“假设”A14；表决权示意见 A15。特斯拉持有的 1,899 万股 SpaceX 股份在合并后视为库存股，不参与分配。
B71: F. 合并后整体（示意，基准日价格，不含溢价与协同）
B72: 合并后股权市值（十亿美元）= 两家市值之和 − 交叉持股 | C72: =(P_T_U*N_T+P_S_U*N_S-X_TS_SPCX*P_S_U)/1000 -> 3481.219
B73: 合并后企业价值（十亿美元，示意） | C73: =E37/1000 -> 3394.884
B74: 合并后总股数（方法①，基准溢价，百万股） | C74: =E64 -> 23555.173
B76: G. 特斯拉公众股东（不含马斯克）合并后的经济权益与表决权（基准溢价）
B77: 定价方法 | C77: 经济占比 | D77: 表决权占比（示意） | E77: 合并前表决权占比（特斯拉） | N77: 计算方法
B78: ① 不受影响日收盘市值 | C78: =IF(ACQ="SpaceX",'换股比例'!$C$64*(N_T-M_T_ALL)/(N_S_EX+'换股比例'!$C$64*N_T),(N_T-M_T_ALL)/(N_T+'换股比例'!$C$64*N_S_EX)) -> 0.30374057 | D78: =IF(ACQ="SpaceX",'换股比例'!$C$64*(N_T-M_T_BEN-M_T_RS25)/(N_S_A-X_TS_SPCX+10*N_S_B+'换股比例'!$C$64*(N_T-M_T_RS25)),(N_T-M_T_BEN-M_T_RS25)/(N_T-M_T_RS25+'换股比例'!$C$64*N_S_EX)) -> 0.10143468 | E78: =(N_T-M_T_BEN-M_T_RS25)/(N_T-M_T_RS25) -> 0.80176308 | N78: 经济占比=公众持有特斯拉股份×换股比例/合并后总股数；表决权按假设 A15（SpaceX 存续时 B 类 10 票/股；2025 业绩股按比例投票，剔除）
B79: ② N 日成交量加权均价（VWAP） | C79: =IF(ACQ="SpaceX",'换股比例'!$C$65*(N_T-M_T_ALL)/(N_S_EX+'换股比例'!$C$65*N_T),(N_T-M_T_ALL)/(N_T+'换股比例'!$C$65*N_S_EX)) -> 0.29435965 | D79: =IF(ACQ="SpaceX",'换股比例'!$C$65*(N_T-M_T_BEN-M_T_RS25)/(N_S_A-X_TS_SPCX+10*N_S_B+'换股比例'!$C$65*(N_T-M_T_RS25)),(N_T-M_T_BEN-M_T_RS25)/(N_T-M_T_RS25+'换股比例'!$C$65*N_S_EX)) -> 0.09675596 | E79: =(N_T-M_T_BEN-M_T_RS25)/(N_T-M_T_RS25) -> 0.80176308 | N79: 经济占比=公众持有特斯拉股份×换股比例/合并后总股数；表决权按假设 A15（SpaceX 存续时 B 类 10 票/股；2025 业绩股按比例投票，剔除）
B80: ③ 消息公布后收盘价（参考） | C80: =IF(ACQ="SpaceX",'换股比例'!$C$66*(N_T-M_T_ALL)/(N_S_EX+'换股比例'!$C$66*N_T),(N_T-M_T_ALL)/(N_T+'换股比例'!$C$66*N_S_EX)) -> 0.29651039 | D80: =IF(ACQ="SpaceX",'换股比例'!$C$66*(N_T-M_T_BEN-M_T_RS25)/(N_S_A-X_TS_SPCX+10*N_S_B+'换股比例'!$C$66*(N_T-M_T_RS25)),(N_T-M_T_BEN-M_T_RS25)/(N_T-M_T_RS25+'换股比例'!$C$66*N_S_EX)) -> 0.097815589 | E80: =(N_T-M_T_BEN-M_T_RS25)/(N_T-M_T_RS25) -> 0.80176308 | N80: 经济占比=公众持有特斯拉股份×换股比例/合并后总股数；表决权按假设 A15（SpaceX 存续时 B 类 10 票/股；2025 业绩股按比例投票，剔除）
B81: ④ LTM 营收贡献法（同一 EV/营收） | C81: =IF(ACQ="SpaceX",'换股比例'!$C$67*(N_T-M_T_ALL)/(N_S_EX+'换股比例'!$C$67*N_T),(N_T-M_T_ALL)/(N_T+'换股比例'!$C$67*N_S_EX)) -> 0.54071045 | D81: =IF(ACQ="SpaceX",'换股比例'!$C$67*(N_T-M_T_BEN-M_T_RS25)/(N_S_A-X_TS_SPCX+10*N_S_B+'换股比例'!$C$67*(N_T-M_T_RS25)),(N_T-M_T_BEN-M_T_RS25)/(N_T-M_T_RS25+'换股比例'!$C$67*N_S_EX)) -> 0.30277447 | E81: =(N_T-M_T_BEN-M_T_RS25)/(N_T-M_T_RS25) -> 0.80176308 | N81: 经济占比=公众持有特斯拉股份×换股比例/合并后总股数；表决权按假设 A15（SpaceX 存续时 B 类 10 票/股；2025 业绩股按比例投票，剔除）
B82: ⑤ LTM EBITDA 贡献法（同一 EV/EBITDA） | C82: =IF(ACQ="SpaceX",'换股比例'!$C$68*(N_T-M_T_ALL)/(N_S_EX+'换股比例'!$C$68*N_T),(N_T-M_T_ALL)/(N_T+'换股比例'!$C$68*N_S_EX)) -> 0.3566107 | D82: =IF(ACQ="SpaceX",'换股比例'!$C$68*(N_T-M_T_BEN-M_T_RS25)/(N_S_A-X_TS_SPCX+10*N_S_B+'换股比例'!$C$68*(N_T-M_T_RS25)),(N_T-M_T_BEN-M_T_RS25)/(N_T-M_T_RS25+'换股比例'!$C$68*N_S_EX)) -> 0.13087606 | E82: =(N_T-M_T_BEN-M_T_RS25)/(N_T-M_T_RS25) -> 0.80176308 | N82: 经济占比=公众持有特斯拉股份×换股比例/合并后总股数；表决权按假设 A15（SpaceX 存续时 B 类 10 票/股；2025 业绩股按比例投票，剔除）

Sheet 敏感性
B1: 敏感性：溢价率 × 定价方法（二维表，全部为公式）
B2: 行 = 给被收购方股东的溢价率（黄底，可修改）；列 = 定价方法。交易结构随“假设”A01 联动。
B4: 表1 换股比例 | I4: =IF(ACQ="SpaceX","收购方：SpaceX；被收购方：特斯拉","收购方：特斯拉；被收购方：SpaceX") -> 收购方：SpaceX；被收购方：特斯拉
B5: 溢价率 \ 定价方法 | C5: ① 不受影响日收盘市值 | D5: ② N 日成交量加权均价（VWAP） | E5: ③ 消息公布后收盘价（参考） | F5: ④ LTM 营收贡献法（同一 EV/营收） | G5: ⑤ LTM EBITDA 贡献法（同一 EV/EBITDA）
B6: 0 | C6: =IF(ACQ="SpaceX",R_M1*(1+$B$6),(1/R_M1)*(1+$B$6)) -> 2.5286555 | D6: =IF(ACQ="SpaceX",R_M2*(1+$B$6),(1/R_M2)*(1+$B$6)) -> 2.396013 | E6: =IF(ACQ="SpaceX",R_M3*(1+$B$6),(1/R_M3)*(1+$B$6)) -> 2.4258992 | F6: =IF(ACQ="SpaceX",R_M4*(1+$B$6),(1/R_M4)*(1+$B$6)) -> 10.593356 | G6: =IF(ACQ="SpaceX",R_M5*(1+$B$6),(1/R_M5)*(1+$B$6)) -> 3.4057736
B7: 0.05 | C7: =IF(ACQ="SpaceX",R_M1*(1+$B$7),(1/R_M1)*(1+$B$7)) -> 2.6550883 | D7: =IF(ACQ="SpaceX",R_M2*(1+$B$7),(1/R_M2)*(1+$B$7)) -> 2.5158136 | E7: =IF(ACQ="SpaceX",R_M3*(1+$B$7),(1/R_M3)*(1+$B$7)) -> 2.5471941 | F7: =IF(ACQ="SpaceX",R_M4*(1+$B$7),(1/R_M4)*(1+$B$7)) -> 11.123024 | G7: =IF(ACQ="SpaceX",R_M5*(1+$B$7),(1/R_M5)*(1+$B$7)) -> 3.5760623
B8: 0.1 | C8: =IF(ACQ="SpaceX",R_M1*(1+$B$8),(1/R_M1)*(1+$B$8)) -> 2.7815211 | D8: =IF(ACQ="SpaceX",R_M2*(1+$B$8),(1/R_M2)*(1+$B$8)) -> 2.6356143 | E8: =IF(ACQ="SpaceX",R_M3*(1+$B$8),(1/R_M3)*(1+$B$8)) -> 2.6684891 | F8: =IF(ACQ="SpaceX",R_M4*(1+$B$8),(1/R_M4)*(1+$B$8)) -> 11.652692 | G8: =IF(ACQ="SpaceX",R_M5*(1+$B$8),(1/R_M5)*(1+$B$8)) -> 3.746351
B9: 0.15 | C9: =IF(ACQ="SpaceX",R_M1*(1+$B$9),(1/R_M1)*(1+$B$9)) -> 2.9079539 | D9: =IF(ACQ="SpaceX",R_M2*(1+$B$9),(1/R_M2)*(1+$B$9)) -> 2.7554149 | E9: =IF(ACQ="SpaceX",R_M3*(1+$B$9),(1/R_M3)*(1+$B$9)) -> 2.7897841 | F9: =IF(ACQ="SpaceX",R_M4*(1+$B$9),(1/R_M4)*(1+$B$9)) -> 12.18236 | G9: =IF(ACQ="SpaceX",R_M5*(1+$B$9),(1/R_M5)*(1+$B$9)) -> 3.9166397
B10: 0.2 | C10: =IF(ACQ="SpaceX",R_M1*(1+$B$10),(1/R_M1)*(1+$B$10)) -> 3.0343866 | D10: =IF(ACQ="SpaceX",R_M2*(1+$B$10),(1/R_M2)*(1+$B$10)) -> 2.8752156 | E10: =IF(ACQ="SpaceX",R_M3*(1+$B$10),(1/R_M3)*(1+$B$10)) -> 2.911079 | F10: =IF(ACQ="SpaceX",R_M4*(1+$B$10),(1/R_M4)*(1+$B$10)) -> 12.712027 | G10: =IF(ACQ="SpaceX",R_M5*(1+$B$10),(1/R_M5)*(1+$B$10)) -> 4.0869283
B11: 0.25 | C11: =IF(ACQ="SpaceX",R_M1*(1+$B$11),(1/R_M1)*(1+$B$11)) -> 3.1608194 | D11: =IF(ACQ="SpaceX",R_M2*(1+$B$11),(1/R_M2)*(1+$B$11)) -> 2.9950162 | E11: =IF(ACQ="SpaceX",R_M3*(1+$B$11),(1/R_M3)*(1+$B$11)) -> 3.032374 | F11: =IF(ACQ="SpaceX",R_M4*(1+$B$11),(1/R_M4)*(1+$B$11)) -> 13.241695 | G11: =IF(ACQ="SpaceX",R_M5*(1+$B$11),(1/R_M5)*(1+$B$11)) -> 4.257217
B12: 0.3 | C12: =IF(ACQ="SpaceX",R_M1*(1+$B$12),(1/R_M1)*(1+$B$12)) -> 3.2872522 | D12: =IF(ACQ="SpaceX",R_M2*(1+$B$12),(1/R_M2)*(1+$B$12)) -> 3.1148169 | E12: =IF(ACQ="SpaceX",R_M3*(1+$B$12),(1/R_M3)*(1+$B$12)) -> 3.1536689 | F12: =IF(ACQ="SpaceX",R_M4*(1+$B$12),(1/R_M4)*(1+$B$12)) -> 13.771363 | G12: =IF(ACQ="SpaceX",R_M5*(1+$B$12),(1/R_M5)*(1+$B$12)) -> 4.4275057
B13: 0.35 | C13: =IF(ACQ="SpaceX",R_M1*(1+$B$13),(1/R_M1)*(1+$B$13)) -> 3.413685 | D13: =IF(ACQ="SpaceX",R_M2*(1+$B$13),(1/R_M2)*(1+$B$13)) -> 3.2346175 | E13: =IF(ACQ="SpaceX",R_M3*(1+$B$13),(1/R_M3)*(1+$B$13)) -> 3.2749639 | F13: =IF(ACQ="SpaceX",R_M4*(1+$B$13),(1/R_M4)*(1+$B$13)) -> 14.301031 | G13: =IF(ACQ="SpaceX",R_M5*(1+$B$13),(1/R_M5)*(1+$B$13)) -> 4.5977944
B14: 0.4 | C14: =IF(ACQ="SpaceX",R_M1*(1+$B$14),(1/R_M1)*(1+$B$14)) -> 3.5401177 | D14: =IF(ACQ="SpaceX",R_M2*(1+$B$14),(1/R_M2)*(1+$B$14)) -> 3.3544182 | E14: =IF(ACQ="SpaceX",R_M3*(1+$B$14),(1/R_M3)*(1+$B$14)) -> 3.3962589 | F14: =IF(ACQ="SpaceX",R_M4*(1+$B$14),(1/R_M4)*(1+$B$14)) -> 14.830699 | G14: =IF(ACQ="SpaceX",R_M5*(1+$B$14),(1/R_M5)*(1+$B$14)) -> 4.7680831
B16: 表2 特斯拉原股东合并后持股比例 | I16: =IF(ACQ="SpaceX","收购方：SpaceX；被收购方：特斯拉","收购方：特斯拉；被收购方：SpaceX") -> 收购方：SpaceX；被收购方：特斯拉
B17: 溢价率 \ 定价方法 | C17: ① 不受影响日收盘市值 | D17: ② N 日成交量加权均价（VWAP） | E17: ③ 消息公布后收盘价（参考） | F17: ④ LTM 营收贡献法（同一 EV/营收） | G17: ⑤ LTM EBITDA 贡献法（同一 EV/EBITDA）
B18: =B6 -> 0 | C18: =IF(ACQ="SpaceX",(R_M1*(1+B$18))*N_T/(N_S_EX+(R_M1*(1+B$18))*N_T),N_T/(N_T+((1/R_M1)*(1+B$18))*N_S_EX)) -> 0.42432986 | D18: =IF(ACQ="SpaceX",(R_M2*(1+B$18))*N_T/(N_S_EX+(R_M2*(1+B$18))*N_T),N_T/(N_T+((1/R_M2)*(1+B$18))*N_S_EX)) -> 0.41122457 | E18: =IF(ACQ="SpaceX",(R_M3*(1+B$18))*N_T/(N_S_EX+(R_M3*(1+B$18))*N_T),N_T/(N_T+((1/R_M3)*(1+B$18))*N_S_EX)) -> 0.41422919 | F18: =IF(ACQ="SpaceX",(R_M4*(1+B$18))*N_T/(N_S_EX+(R_M4*(1+B$18))*N_T),N_T/(N_T+((1/R_M4)*(1+B$18))*N_S_EX)) -> 0.75538011 | G18: =IF(ACQ="SpaceX",(R_M5*(1+B$18))*N_T/(N_S_EX+(R_M5*(1+B$18))*N_T),N_T/(N_T+((1/R_M5)*(1+B$18))*N_S_EX)) -> 0.49819017
B19: =B7 -> 0.05 | C19: =IF(ACQ="SpaceX",(R_M1*(1+B$19))*N_T/(N_S_EX+(R_M1*(1+B$19))*N_T),N_T/(N_T+((1/R_M1)*(1+B$19))*N_S_EX)) -> 0.43628981 | D19: =IF(ACQ="SpaceX",(R_M2*(1+B$19))*N_T/(N_S_EX+(R_M2*(1+B$19))*N_T),N_T/(N_T+((1/R_M2)*(1+B$19))*N_S_EX)) -> 0.42308662 | E19: =IF(ACQ="SpaceX",(R_M3*(1+B$19))*N_T/(N_S_EX+(R_M3*(1+B$19))*N_T),N_T/(N_T+((1/R_M3)*(1+B$19))*N_S_EX)) -> 0.42611518 | F19: =IF(ACQ="SpaceX",(R_M4*(1+B$19))*N_T/(N_S_EX+(R_M4*(1+B$19))*N_T),N_T/(N_T+((1/R_M4)*(1+B$19))*N_S_EX)) -> 0.76428291 | G19: =IF(ACQ="SpaceX",(R_M5*(1+B$19))*N_T/(N_S_EX+(R_M5*(1+B$19))*N_T),N_T/(N_T+((1/R_M5)*(1+B$19))*N_S_EX)) -> 0.51038621
B20: =B8 -> 0.1 | C20: =IF(ACQ="SpaceX",(R_M1*(1+B$20))*N_T/(N_S_EX+(R_M1*(1+B$20))*N_T),N_T/(N_T+((1/R_M1)*(1+B$20))*N_S_EX)) -> 0.44776293 | D20: =IF(ACQ="SpaceX",(R_M2*(1+B$20))*N_T/(N_S_EX+(R_M2*(1+B$20))*N_T),N_T/(N_T+((1/R_M2)*(1+B$20))*N_S_EX)) -> 0.43448014 | E20: =IF(ACQ="SpaceX",(R_M3*(1+B$20))*N_T/(N_S_EX+(R_M3*(1+B$20))*N_T),N_T/(N_T+((1/R_M3)*(1+B$20))*N_S_EX)) -> 0.4375284 | F20: =IF(ACQ="SpaceX",(R_M4*(1+B$20))*N_T/(N_S_EX+(R_M4*(1+B$20))*N_T),N_T/(N_T+((1/R_M4)*(1+B$20))*N_S_EX)) -> 0.77256045 | G20: =IF(ACQ="SpaceX",(R_M5*(1+B$20))*N_T/(N_S_EX+(R_M5*(1+B$20))*N_T),N_T/(N_T+((1/R_M5)*(1+B$20))*N_S_EX)) -> 0.52200349
B21: =B9 -> 0.15 | C21: =IF(ACQ="SpaceX",(R_M1*(1+B$21))*N_T/(N_S_EX+(R_M1*(1+B$21))*N_T),N_T/(N_T+((1/R_M1)*(1+B$21))*N_S_EX)) -> 0.45877833 | D21: =IF(ACQ="SpaceX",(R_M2*(1+B$21))*N_T/(N_S_EX+(R_M2*(1+B$21))*N_T),N_T/(N_T+((1/R_M2)*(1+B$21))*N_S_EX)) -> 0.44543235 | E21: =IF(ACQ="SpaceX",(R_M3*(1+B$21))*N_T/(N_S_EX+(R_M3*(1+B$21))*N_T),N_T/(N_T+((1/R_M3)*(1+B$21))*N_S_EX)) -> 0.44849651 | F21: =IF(ACQ="SpaceX",(R_M4*(1+B$21))*N_T/(N_S_EX+(R_M4*(1+B$21))*N_T),N_T/(N_T+((1/R_M4)*(1+B$21))*N_S_EX)) -> 0.78027635 | G21: =IF(ACQ="SpaceX",(R_M5*(1+B$21))*N_T/(N_S_EX+(R_M5*(1+B$21))*N_T),N_T/(N_T+((1/R_M5)*(1+B$21))*N_S_EX)) -> 0.53308225
B22: =B10 -> 0.2 | C22: =IF(ACQ="SpaceX",(R_M1*(1+B$22))*N_T/(N_S_EX+(R_M1*(1+B$22))*N_T),N_T/(N_T+((1/R_M1)*(1+B$22))*N_S_EX)) -> 0.46936289 | D22: =IF(ACQ="SpaceX",(R_M2*(1+B$22))*N_T/(N_S_EX+(R_M2*(1+B$22))*N_T),N_T/(N_T+((1/R_M2)*(1+B$22))*N_S_EX)) -> 0.45596841 | E22: =IF(ACQ="SpaceX",(R_M3*(1+B$22))*N_T/(N_S_EX+(R_M3*(1+B$22))*N_T),N_T/(N_T+((1/R_M3)*(1+B$22))*N_S_EX)) -> 0.45904505 | F22: =IF(ACQ="SpaceX",(R_M4*(1+B$22))*N_T/(N_S_EX+(R_M4*(1+B$22))*N_T),N_T/(N_T+((1/R_M4)*(1+B$22))*N_S_EX)) -> 0.7874859 | G22: =IF(ACQ="SpaceX",(R_M5*(1+B$22))*N_T/(N_S_EX+(R_M5*(1+B$22))*N_T),N_T/(N_T+((1/R_M5)*(1+B$22))*N_S_EX)) -> 0.54365908
B23: =B11 -> 0.25 | C23: =IF(ACQ="SpaceX",(R_M1*(1+B$23))*N_T/(N_S_EX+(R_M1*(1+B$23))*N_T),N_T/(N_T+((1/R_M1)*(1+B$23))*N_S_EX)) -> 0.47954139 | D23: =IF(ACQ="SpaceX",(R_M2*(1+B$23))*N_T/(N_S_EX+(R_M2*(1+B$23))*N_T),N_T/(N_T+((1/R_M2)*(1+B$23))*N_S_EX)) -> 0.46611158 | E23: =IF(ACQ="SpaceX",(R_M3*(1+B$23))*N_T/(N_S_EX+(R_M3*(1+B$23))*N_T),N_T/(N_T+((1/R_M3)*(1+B$23))*N_S_EX)) -> 0.46919764 | F23: =IF(ACQ="SpaceX",(R_M4*(1+B$23))*N_T/(N_S_EX+(R_M4*(1+B$23))*N_T),N_T/(N_T+((1/R_M4)*(1+B$23))*N_S_EX)) -> 0.79423737 | G23: =IF(ACQ="SpaceX",(R_M5*(1+B$23))*N_T/(N_S_EX+(R_M5*(1+B$23))*N_T),N_T/(N_T+((1/R_M5)*(1+B$23))*N_S_EX)) -> 0.55376735
B24: =B12 -> 0.3 | C24: =IF(ACQ="SpaceX",(R_M1*(1+B$24))*N_T/(N_S_EX+(R_M1*(1+B$24))*N_T),N_T/(N_T+((1/R_M1)*(1+B$24))*N_S_EX)) -> 0.48933676 | D24: =IF(ACQ="SpaceX",(R_M2*(1+B$24))*N_T/(N_S_EX+(R_M2*(1+B$24))*N_T),N_T/(N_T+((1/R_M2)*(1+B$24))*N_S_EX)) -> 0.47588345 | E24: =IF(ACQ="SpaceX",(R_M3*(1+B$24))*N_T/(N_S_EX+(R_M3*(1+B$24))*N_T),N_T/(N_T+((1/R_M3)*(1+B$24))*N_S_EX)) -> 0.47897617 | F24: =IF(ACQ="SpaceX",(R_M4*(1+B$24))*N_T/(N_S_EX+(R_M4*(1+B$24))*N_T),N_T/(N_T+((1/R_M4)*(1+B$24))*N_S_EX)) -> 0.80057306 | G24: =IF(ACQ="SpaceX",(R_M5*(1+B$24))*N_T/(N_S_EX+(R_M5*(1+B$24))*N_T),N_T/(N_T+((1/R_M5)*(1+B$24))*N_S_EX)) -> 0.56343751
B25: =B13 -> 0.35 | C25: =IF(ACQ="SpaceX",(R_M1*(1+B$25))*N_T/(N_S_EX+(R_M1*(1+B$25))*N_T),N_T/(N_T+((1/R_M1)*(1+B$25))*N_S_EX)) -> 0.49877022 | D25: =IF(ACQ="SpaceX",(R_M2*(1+B$25))*N_T/(N_S_EX+(R_M2*(1+B$25))*N_T),N_T/(N_T+((1/R_M2)*(1+B$25))*N_S_EX)) -> 0.48530404 | E25: =IF(ACQ="SpaceX",(R_M3*(1+B$25))*N_T/(N_S_EX+(R_M3*(1+B$25))*N_T),N_T/(N_T+((1/R_M3)*(1+B$25))*N_S_EX)) -> 0.48840093 | F25: =IF(ACQ="SpaceX",(R_M4*(1+B$25))*N_T/(N_S_EX+(R_M4*(1+B$25))*N_T),N_T/(N_T+((1/R_M4)*(1+B$25))*N_S_EX)) -> 0.80653024 | G25: =IF(ACQ="SpaceX",(R_M5*(1+B$25))*N_T/(N_S_EX+(R_M5*(1+B$25))*N_T),N_T/(N_T+((1/R_M5)*(1+B$25))*N_S_EX)) -> 0.57269745
B26: =B14 -> 0.4 | C26: =IF(ACQ="SpaceX",(R_M1*(1+B$26))*N_T/(N_S_EX+(R_M1*(1+B$26))*N_T),N_T/(N_T+((1/R_M1)*(1+B$26))*N_S_EX)) -> 0.50786148 | D26: =IF(ACQ="SpaceX",(R_M2*(1+B$26))*N_T/(N_S_EX+(R_M2*(1+B$26))*N_T),N_T/(N_T+((1/R_M2)*(1+B$26))*N_S_EX)) -> 0.49439195 | E26: =IF(ACQ="SpaceX",(R_M3*(1+B$26))*N_T/(N_S_EX+(R_M3*(1+B$26))*N_T),N_T/(N_T+((1/R_M3)*(1+B$26))*N_S_EX)) -> 0.49749078 | F26: =IF(ACQ="SpaceX",(R_M4*(1+B$26))*N_T/(N_S_EX+(R_M4*(1+B$26))*N_T),N_T/(N_T+((1/R_M4)*(1+B$26))*N_S_EX)) -> 0.81214184 | G26: =IF(ACQ="SpaceX",(R_M5*(1+B$26))*N_T/(N_S_EX+(R_M5*(1+B$26))*N_T),N_T/(N_T+((1/R_M5)*(1+B$26))*N_S_EX)) -> 0.58157272
B28: 表3 马斯克合并后经济持股（口径A） | I28: =IF(ACQ="SpaceX","收购方：SpaceX；被收购方：特斯拉","收购方：特斯拉；被收购方：SpaceX") -> 收购方：SpaceX；被收购方：特斯拉
B29: 溢价率 \ 定价方法 | C29: ① 不受影响日收盘市值 | D29: ② N 日成交量加权均价（VWAP） | E29: ③ 消息公布后收盘价（参考） | F29: ④ LTM 营收贡献法（同一 EV/营收） | G29: ⑤ LTM EBITDA 贡献法（同一 EV/EBITDA）
B30: =B6 -> 0 | C30: =IF(ACQ="SpaceX",(M_S_ALL+R_M1*(1+B$30)*M_T_ALL)/(N_S_EX+R_M1*(1+B$30)*N_T),(M_T_ALL+(1/R_M1)*(1+B$30)*M_S_ALL)/(N_T+(1/R_M1)*(1+B$30)*N_S_EX)) -> 0.37822048 | D30: =IF(ACQ="SpaceX",(M_S_ALL+R_M2*(1+B$30)*M_T_ALL)/(N_S_EX+R_M2*(1+B$30)*N_T),(M_T_ALL+(1/R_M2)*(1+B$30)*M_S_ALL)/(N_T+(1/R_M2)*(1+B$30)*N_S_EX)) -> 0.38036117 | E30: =IF(ACQ="SpaceX",(M_S_ALL+R_M3*(1+B$30)*M_T_ALL)/(N_S_EX+R_M3*(1+B$30)*N_T),(M_T_ALL+(1/R_M3)*(1+B$30)*M_S_ALL)/(N_T+(1/R_M3)*(1+B$30)*N_S_EX)) -> 0.37987038 | F30: =IF(ACQ="SpaceX",(M_S_ALL+R_M4*(1+B$30)*M_T_ALL)/(N_S_EX+R_M4*(1+B$30)*N_T),(M_T_ALL+(1/R_M4)*(1+B$30)*M_S_ALL)/(N_T+(1/R_M4)*(1+B$30)*N_S_EX)) -> 0.32414505 | G30: =IF(ACQ="SpaceX",(M_S_ALL+R_M5*(1+B$30)*M_T_ALL)/(N_S_EX+R_M5*(1+B$30)*N_T),(M_T_ALL+(1/R_M5)*(1+B$30)*M_S_ALL)/(N_T+(1/R_M5)*(1+B$30)*N_S_EX)) -> 0.36615576
B31: =B7 -> 0.05 | C31: =IF(ACQ="SpaceX",(M_S_ALL+R_M1*(1+B$31)*M_T_ALL)/(N_S_EX+R_M1*(1+B$31)*N_T),(M_T_ALL+(1/R_M1)*(1+B$31)*M_S_ALL)/(N_T+(1/R_M1)*(1+B$31)*N_S_EX)) -> 0.37626688 | D31: =IF(ACQ="SpaceX",(M_S_ALL+R_M2*(1+B$31)*M_T_ALL)/(N_S_EX+R_M2*(1+B$31)*N_T),(M_T_ALL+(1/R_M2)*(1+B$31)*M_S_ALL)/(N_T+(1/R_M2)*(1+B$31)*N_S_EX)) -> 0.37842356 | E31: =IF(ACQ="SpaceX",(M_S_ALL+R_M3*(1+B$31)*M_T_ALL)/(N_S_EX+R_M3*(1+B$31)*N_T),(M_T_ALL+(1/R_M3)*(1+B$31)*M_S_ALL)/(N_T+(1/R_M3)*(1+B$31)*N_S_EX)) -> 0.37792886 | F31: =IF(ACQ="SpaceX",(M_S_ALL+R_M4*(1+B$31)*M_T_ALL)/(N_S_EX+R_M4*(1+B$31)*N_T),(M_T_ALL+(1/R_M4)*(1+B$31)*M_S_ALL)/(N_T+(1/R_M4)*(1+B$31)*N_S_EX)) -> 0.32269082 | G31: =IF(ACQ="SpaceX",(M_S_ALL+R_M5*(1+B$31)*M_T_ALL)/(N_S_EX+R_M5*(1+B$31)*N_T),(M_T_ALL+(1/R_M5)*(1+B$31)*M_S_ALL)/(N_T+(1/R_M5)*(1+B$31)*N_S_EX)) -> 0.3641636
B32: =B8 -> 0.1 | C32: =IF(ACQ="SpaceX",(M_S_ALL+R_M1*(1+B$32)*M_T_ALL)/(N_S_EX+R_M1*(1+B$32)*N_T),(M_T_ALL+(1/R_M1)*(1+B$32)*M_S_ALL)/(N_T+(1/R_M1)*(1+B$32)*N_S_EX)) -> 0.37439281 | D32: =IF(ACQ="SpaceX",(M_S_ALL+R_M2*(1+B$32)*M_T_ALL)/(N_S_EX+R_M2*(1+B$32)*N_T),(M_T_ALL+(1/R_M2)*(1+B$32)*M_S_ALL)/(N_T+(1/R_M2)*(1+B$32)*N_S_EX)) -> 0.37656249 | E32: =IF(ACQ="SpaceX",(M_S_ALL+R_M3*(1+B$32)*M_T_ALL)/(N_S_EX+R_M3*(1+B$32)*N_T),(M_T_ALL+(1/R_M3)*(1+B$32)*M_S_ALL)/(N_T+(1/R_M3)*(1+B$32)*N_S_EX)) -> 0.37606457 | F32: =IF(ACQ="SpaceX",(M_S_ALL+R_M4*(1+B$32)*M_T_ALL)/(N_S_EX+R_M4*(1+B$32)*N_T),(M_T_ALL+(1/R_M4)*(1+B$32)*M_S_ALL)/(N_T+(1/R_M4)*(1+B$32)*N_S_EX)) -> 0.32133873 | G32: =IF(ACQ="SpaceX",(M_S_ALL+R_M5*(1+B$32)*M_T_ALL)/(N_S_EX+R_M5*(1+B$32)*N_T),(M_T_ALL+(1/R_M5)*(1+B$32)*M_S_ALL)/(N_T+(1/R_M5)*(1+B$32)*N_S_EX)) -> 0.36226598
B33: =B9 -> 0.15 | C33: =IF(ACQ="SpaceX",(M_S_ALL+R_M1*(1+B$33)*M_T_ALL)/(N_S_EX+R_M1*(1+B$33)*N_T),(M_T_ALL+(1/R_M1)*(1+B$33)*M_S_ALL)/(N_T+(1/R_M1)*(1+B$33)*N_S_EX)) -> 0.37259349 | D33: =IF(ACQ="SpaceX",(M_S_ALL+R_M2*(1+B$33)*M_T_ALL)/(N_S_EX+R_M2*(1+B$33)*N_T),(M_T_ALL+(1/R_M2)*(1+B$33)*M_S_ALL)/(N_T+(1/R_M2)*(1+B$33)*N_S_EX)) -> 0.3747735 | E33: =IF(ACQ="SpaceX",(M_S_ALL+R_M3*(1+B$33)*M_T_ALL)/(N_S_EX+R_M3*(1+B$33)*N_T),(M_T_ALL+(1/R_M3)*(1+B$33)*M_S_ALL)/(N_T+(1/R_M3)*(1+B$33)*N_S_EX)) -> 0.37427298 | F33: =IF(ACQ="SpaceX",(M_S_ALL+R_M4*(1+B$33)*M_T_ALL)/(N_S_EX+R_M4*(1+B$33)*N_T),(M_T_ALL+(1/R_M4)*(1+B$33)*M_S_ALL)/(N_T+(1/R_M4)*(1+B$33)*N_S_EX)) -> 0.32007838 | G33: =IF(ACQ="SpaceX",(M_S_ALL+R_M5*(1+B$33)*M_T_ALL)/(N_S_EX+R_M5*(1+B$33)*N_T),(M_T_ALL+(1/R_M5)*(1+B$33)*M_S_ALL)/(N_T+(1/R_M5)*(1+B$33)*N_S_EX)) -> 0.36045632
B34: =B10 -> 0.2 | C34: =IF(ACQ="SpaceX",(M_S_ALL+R_M1*(1+B$34)*M_T_ALL)/(N_S_EX+R_M1*(1+B$34)*N_T),(M_T_ALL+(1/R_M1)*(1+B$34)*M_S_ALL)/(N_T+(1/R_M1)*(1+B$34)*N_S_EX)) -> 0.37086456 | D34: =IF(ACQ="SpaceX",(M_S_ALL+R_M2*(1+B$34)*M_T_ALL)/(N_S_EX+R_M2*(1+B$34)*N_T),(M_T_ALL+(1/R_M2)*(1+B$34)*M_S_ALL)/(N_T+(1/R_M2)*(1+B$34)*N_S_EX)) -> 0.37305248 | E34: =IF(ACQ="SpaceX",(M_S_ALL+R_M3*(1+B$34)*M_T_ALL)/(N_S_EX+R_M3*(1+B$34)*N_T),(M_T_ALL+(1/R_M3)*(1+B$34)*M_S_ALL)/(N_T+(1/R_M3)*(1+B$34)*N_S_EX)) -> 0.37254993 | F34: =IF(ACQ="SpaceX",(M_S_ALL+R_M4*(1+B$34)*M_T_ALL)/(N_S_EX+R_M4*(1+B$34)*N_T),(M_T_ALL+(1/R_M4)*(1+B$34)*M_S_ALL)/(N_T+(1/R_M4)*(1+B$34)*N_S_EX)) -> 0.31890073 | G34: =IF(ACQ="SpaceX",(M_S_ALL+R_M5*(1+B$34)*M_T_ALL)/(N_S_EX+R_M5*(1+B$34)*N_T),(M_T_ALL+(1/R_M5)*(1+B$34)*M_S_ALL)/(N_T+(1/R_M5)*(1+B$34)*N_S_EX)) -> 0.35872864
B35: =B11 -> 0.25 | C35: =IF(ACQ="SpaceX",(M_S_ALL+R_M1*(1+B$35)*M_T_ALL)/(N_S_EX+R_M1*(1+B$35)*N_T),(M_T_ALL+(1/R_M1)*(1+B$35)*M_S_ALL)/(N_T+(1/R_M1)*(1+B$35)*N_S_EX)) -> 0.36920195 | D35: =IF(ACQ="SpaceX",(M_S_ALL+R_M2*(1+B$35)*M_T_ALL)/(N_S_EX+R_M2*(1+B$35)*N_T),(M_T_ALL+(1/R_M2)*(1+B$35)*M_S_ALL)/(N_T+(1/R_M2)*(1+B$35)*N_S_EX)) -> 0.37139564 | E35: =IF(ACQ="SpaceX",(M_S_ALL+R_M3*(1+B$35)*M_T_ALL)/(N_S_EX+R_M3*(1+B$35)*N_T),(M_T_ALL+(1/R_M3)*(1+B$35)*M_S_ALL)/(N_T+(1/R_M3)*(1+B$35)*N_S_EX)) -> 0.37089155 | F35: =IF(ACQ="SpaceX",(M_S_ALL+R_M4*(1+B$35)*M_T_ALL)/(N_S_EX+R_M4*(1+B$35)*N_T),(M_T_ALL+(1/R_M4)*(1+B$35)*M_S_ALL)/(N_T+(1/R_M4)*(1+B$35)*N_S_EX)) -> 0.31779791 | G35: =IF(ACQ="SpaceX",(M_S_ALL+R_M5*(1+B$35)*M_T_ALL)/(N_S_EX+R_M5*(1+B$35)*N_T),(M_T_ALL+(1/R_M5)*(1+B$35)*M_S_ALL)/(N_T+(1/R_M5)*(1+B$35)*N_S_EX)) -> 0.35707751
B36: =B12 -> 0.3 | C36: =IF(ACQ="SpaceX",(M_S_ALL+R_M1*(1+B$36)*M_T_ALL)/(N_S_EX+R_M1*(1+B$36)*N_T),(M_T_ALL+(1/R_M1)*(1+B$36)*M_S_ALL)/(N_T+(1/R_M1)*(1+B$36)*N_S_EX)) -> 0.36760193 | D36: =IF(ACQ="SpaceX",(M_S_ALL+R_M2*(1+B$36)*M_T_ALL)/(N_S_EX+R_M2*(1+B$36)*N_T),(M_T_ALL+(1/R_M2)*(1+B$36)*M_S_ALL)/(N_T+(1/R_M2)*(1+B$36)*N_S_EX)) -> 0.36979946 | E36: =IF(ACQ="SpaceX",(M_S_ALL+R_M3*(1+B$36)*M_T_ALL)/(N_S_EX+R_M3*(1+B$36)*N_T),(M_T_ALL+(1/R_M3)*(1+B$36)*M_S_ALL)/(N_T+(1/R_M3)*(1+B$36)*N_S_EX)) -> 0.36929428 | F36: =IF(ACQ="SpaceX",(M_S_ALL+R_M4*(1+B$36)*M_T_ALL)/(N_S_EX+R_M4*(1+B$36)*N_T),(M_T_ALL+(1/R_M4)*(1+B$36)*M_S_ALL)/(N_T+(1/R_M4)*(1+B$36)*N_S_EX)) -> 0.31676301 | G36: =IF(ACQ="SpaceX",(M_S_ALL+R_M5*(1+B$36)*M_T_ALL)/(N_S_EX+R_M5*(1+B$36)*N_T),(M_T_ALL+(1/R_M5)*(1+B$36)*M_S_ALL)/(N_T+(1/R_M5)*(1+B$36)*N_S_EX)) -> 0.35549793
B37: =B13 -> 0.35 | C37: =IF(ACQ="SpaceX",(M_S_ALL+R_M1*(1+B$37)*M_T_ALL)/(N_S_EX+R_M1*(1+B$37)*N_T),(M_T_ALL+(1/R_M1)*(1+B$37)*M_S_ALL)/(N_T+(1/R_M1)*(1+B$37)*N_S_EX)) -> 0.36606102 | D37: =IF(ACQ="SpaceX",(M_S_ALL+R_M2*(1+B$37)*M_T_ALL)/(N_S_EX+R_M2*(1+B$37)*N_T),(M_T_ALL+(1/R_M2)*(1+B$37)*M_S_ALL)/(N_T+(1/R_M2)*(1+B$37)*N_S_EX)) -> 0.36826065 | E37: =IF(ACQ="SpaceX",(M_S_ALL+R_M3*(1+B$37)*M_T_ALL)/(N_S_EX+R_M3*(1+B$37)*N_T),(M_T_ALL+(1/R_M3)*(1+B$37)*M_S_ALL)/(N_T+(1/R_M3)*(1+B$37)*N_S_EX)) -> 0.36775479 | F37: =IF(ACQ="SpaceX",(M_S_ALL+R_M4*(1+B$37)*M_T_ALL)/(N_S_EX+R_M4*(1+B$37)*N_T),(M_T_ALL+(1/R_M4)*(1+B$37)*M_S_ALL)/(N_T+(1/R_M4)*(1+B$37)*N_S_EX)) -> 0.31578993 | G37: =IF(ACQ="SpaceX",(M_S_ALL+R_M5*(1+B$37)*M_T_ALL)/(N_S_EX+R_M5*(1+B$37)*N_T),(M_T_ALL+(1/R_M5)*(1+B$37)*M_S_ALL)/(N_T+(1/R_M5)*(1+B$37)*N_S_EX)) -> 0.35398537
B38: =B14 -> 0.4 | C38: =IF(ACQ="SpaceX",(M_S_ALL+R_M1*(1+B$38)*M_T_ALL)/(N_S_EX+R_M1*(1+B$38)*N_T),(M_T_ALL+(1/R_M1)*(1+B$38)*M_S_ALL)/(N_T+(1/R_M1)*(1+B$38)*N_S_EX)) -> 0.364576 | D38: =IF(ACQ="SpaceX",(M_S_ALL+R_M2*(1+B$38)*M_T_ALL)/(N_S_EX+R_M2*(1+B$38)*N_T),(M_T_ALL+(1/R_M2)*(1+B$38)*M_S_ALL)/(N_T+(1/R_M2)*(1+B$38)*N_S_EX)) -> 0.36677619 | E38: =IF(ACQ="SpaceX",(M_S_ALL+R_M3*(1+B$38)*M_T_ALL)/(N_S_EX+R_M3*(1+B$38)*N_T),(M_T_ALL+(1/R_M3)*(1+B$38)*M_S_ALL)/(N_T+(1/R_M3)*(1+B$38)*N_S_EX)) -> 0.36627001 | F38: =IF(ACQ="SpaceX",(M_S_ALL+R_M4*(1+B$38)*M_T_ALL)/(N_S_EX+R_M4*(1+B$38)*N_T),(M_T_ALL+(1/R_M4)*(1+B$38)*M_S_ALL)/(N_T+(1/R_M4)*(1+B$38)*N_S_EX)) -> 0.3148733 | G38: =IF(ACQ="SpaceX",(M_S_ALL+R_M5*(1+B$38)*M_T_ALL)/(N_S_EX+R_M5*(1+B$38)*N_T),(M_T_ALL+(1/R_M5)*(1+B$38)*M_S_ALL)/(N_T+(1/R_M5)*(1+B$38)*N_S_EX)) -> 0.35253564
B40: 表4 马斯克合并后经济持股（口径B） | I40: =IF(ACQ="SpaceX","收购方：SpaceX；被收购方：特斯拉","收购方：特斯拉；被收购方：SpaceX") -> 收购方：SpaceX；被收购方：特斯拉
B41: 溢价率 \ 定价方法 | C41: ① 不受影响日收盘市值 | D41: ② N 日成交量加权均价（VWAP） | E41: ③ 消息公布后收盘价（参考） | F41: ④ LTM 营收贡献法（同一 EV/营收） | G41: ⑤ LTM EBITDA 贡献法（同一 EV/EBITDA）
B42: =B6 -> 0 | C42: =IF(ACQ="SpaceX",(M_S_ALL-M_S_RS+R_M1*(1+B$42)*M_T_BEN)/(N_S_EX-M_S_RS+R_M1*(1+B$42)*(N_T-M_T_RS25)),(M_T_BEN+(1/R_M1)*(1+B$42)*(M_S_ALL-M_S_RS))/(N_T-M_T_RS25+(1/R_M1)*(1+B$42)*(N_S_EX-M_S_RS))) -> 0.30854491 | D42: =IF(ACQ="SpaceX",(M_S_ALL-M_S_RS+R_M2*(1+B$42)*M_T_BEN)/(N_S_EX-M_S_RS+R_M2*(1+B$42)*(N_T-M_T_RS25)),(M_T_BEN+(1/R_M2)*(1+B$42)*(M_S_ALL-M_S_RS))/(N_T-M_T_RS25+(1/R_M2)*(1+B$42)*(N_S_EX-M_S_RS))) -> 0.31103772 | E42: =IF(ACQ="SpaceX",(M_S_ALL-M_S_RS+R_M3*(1+B$42)*M_T_BEN)/(N_S_EX-M_S_RS+R_M3*(1+B$42)*(N_T-M_T_RS25)),(M_T_BEN+(1/R_M3)*(1+B$42)*(M_S_ALL-M_S_RS))/(N_T-M_T_RS25+(1/R_M3)*(1+B$42)*(N_S_EX-M_S_RS))) -> 0.31046627 | F42: =IF(ACQ="SpaceX",(M_S_ALL-M_S_RS+R_M4*(1+B$42)*M_T_BEN)/(N_S_EX-M_S_RS+R_M4*(1+B$42)*(N_T-M_T_RS25)),(M_T_BEN+(1/R_M4)*(1+B$42)*(M_S_ALL-M_S_RS))/(N_T-M_T_RS25+(1/R_M4)*(1+B$42)*(N_S_EX-M_S_RS))) -> 0.24530387 | G42: =IF(ACQ="SpaceX",(M_S_ALL-M_S_RS+R_M5*(1+B$42)*M_T_BEN)/(N_S_EX-M_S_RS+R_M5*(1+B$42)*(N_T-M_T_RS25)),(M_T_BEN+(1/R_M5)*(1+B$42)*(M_S_ALL-M_S_RS))/(N_T-M_T_RS25+(1/R_M5)*(1+B$42)*(N_S_EX-M_S_RS))) -> 0.29448041
B43: =B7 -> 0.05 | C43: =IF(ACQ="SpaceX",(M_S_ALL-M_S_RS+R_M1*(1+B$43)*M_T_BEN)/(N_S_EX-M_S_RS+R_M1*(1+B$43)*(N_T-M_T_RS25)),(M_T_BEN+(1/R_M1)*(1+B$43)*(M_S_ALL-M_S_RS))/(N_T-M_T_RS25+(1/R_M1)*(1+B$43)*(N_S_EX-M_S_RS))) -> 0.30626924 | D43: =IF(ACQ="SpaceX",(M_S_ALL-M_S_RS+R_M2*(1+B$43)*M_T_BEN)/(N_S_EX-M_S_RS+R_M2*(1+B$43)*(N_T-M_T_RS25)),(M_T_BEN+(1/R_M2)*(1+B$43)*(M_S_ALL-M_S_RS))/(N_T-M_T_RS25+(1/R_M2)*(1+B$43)*(N_S_EX-M_S_RS))) -> 0.30878142 | E43: =IF(ACQ="SpaceX",(M_S_ALL-M_S_RS+R_M3*(1+B$43)*M_T_BEN)/(N_S_EX-M_S_RS+R_M3*(1+B$43)*(N_T-M_T_RS25)),(M_T_BEN+(1/R_M3)*(1+B$43)*(M_S_ALL-M_S_RS))/(N_T-M_T_RS25+(1/R_M3)*(1+B$43)*(N_S_EX-M_S_RS))) -> 0.30820525 | F43: =IF(ACQ="SpaceX",(M_S_ALL-M_S_RS+R_M4*(1+B$43)*M_T_BEN)/(N_S_EX-M_S_RS+R_M4*(1+B$43)*(N_T-M_T_RS25)),(M_T_BEN+(1/R_M4)*(1+B$43)*(M_S_ALL-M_S_RS))/(N_T-M_T_RS25+(1/R_M4)*(1+B$43)*(N_S_EX-M_S_RS))) -> 0.24359594 | G43: =IF(ACQ="SpaceX",(M_S_ALL-M_S_RS+R_M5*(1+B$43)*M_T_BEN)/(N_S_EX-M_S_RS+R_M5*(1+B$43)*(N_T-M_T_RS25)),(M_T_BEN+(1/R_M5)*(1+B$43)*(M_S_ALL-M_S_RS))/(N_T-M_T_RS25+(1/R_M5)*(1+B$43)*(N_S_EX-M_S_RS))) -> 0.29215555
B44: =B8 -> 0.1 | C44: =IF(ACQ="SpaceX",(M_S_ALL-M_S_RS+R_M1*(1+B$44)*M_T_BEN)/(N_S_EX-M_S_RS+R_M1*(1+B$44)*(N_T-M_T_RS25)),(M_T_BEN+(1/R_M1)*(1+B$44)*(M_S_ALL-M_S_RS))/(N_T-M_T_RS25+(1/R_M1)*(1+B$44)*(N_S_EX-M_S_RS))) -> 0.30408558 | D44: =IF(ACQ="SpaceX",(M_S_ALL-M_S_RS+R_M2*(1+B$44)*M_T_BEN)/(N_S_EX-M_S_RS+R_M2*(1+B$44)*(N_T-M_T_RS25)),(M_T_BEN+(1/R_M2)*(1+B$44)*(M_S_ALL-M_S_RS))/(N_T-M_T_RS25+(1/R_M2)*(1+B$44)*(N_S_EX-M_S_RS))) -> 0.30661362 | E44: =IF(ACQ="SpaceX",(M_S_ALL-M_S_RS+R_M3*(1+B$44)*M_T_BEN)/(N_S_EX-M_S_RS+R_M3*(1+B$44)*(N_T-M_T_RS25)),(M_T_BEN+(1/R_M3)*(1+B$44)*(M_S_ALL-M_S_RS))/(N_T-M_T_RS25+(1/R_M3)*(1+B$44)*(N_S_EX-M_S_RS))) -> 0.30603353 | F44: =IF(ACQ="SpaceX",(M_S_ALL-M_S_RS+R_M4*(1+B$44)*M_T_BEN)/(N_S_EX-M_S_RS+R_M4*(1+B$44)*(N_T-M_T_RS25)),(M_T_BEN+(1/R_M4)*(1+B$44)*(M_S_ALL-M_S_RS))/(N_T-M_T_RS25+(1/R_M4)*(1+B$44)*(N_S_EX-M_S_RS))) -> 0.24200762 | G44: =IF(ACQ="SpaceX",(M_S_ALL-M_S_RS+R_M5*(1+B$44)*M_T_BEN)/(N_S_EX-M_S_RS+R_M5*(1+B$44)*(N_T-M_T_RS25)),(M_T_BEN+(1/R_M5)*(1+B$44)*(M_S_ALL-M_S_RS))/(N_T-M_T_RS25+(1/R_M5)*(1+B$44)*(N_S_EX-M_S_RS))) -> 0.28994036
B45: =B9 -> 0.15 | C45: =IF(ACQ="SpaceX",(M_S_ALL-M_S_RS+R_M1*(1+B$45)*M_T_BEN)/(N_S_EX-M_S_RS+R_M1*(1+B$45)*(N_T-M_T_RS25)),(M_T_BEN+(1/R_M1)*(1+B$45)*(M_S_ALL-M_S_RS))/(N_T-M_T_RS25+(1/R_M1)*(1+B$45)*(N_S_EX-M_S_RS))) -> 0.30198844 | D45: =IF(ACQ="SpaceX",(M_S_ALL-M_S_RS+R_M2*(1+B$45)*M_T_BEN)/(N_S_EX-M_S_RS+R_M2*(1+B$45)*(N_T-M_T_RS25)),(M_T_BEN+(1/R_M2)*(1+B$45)*(M_S_ALL-M_S_RS))/(N_T-M_T_RS25+(1/R_M2)*(1+B$45)*(N_S_EX-M_S_RS))) -> 0.3045292 | E45: =IF(ACQ="SpaceX",(M_S_ALL-M_S_RS+R_M3*(1+B$45)*M_T_BEN)/(N_S_EX-M_S_RS+R_M3*(1+B$45)*(N_T-M_T_RS25)),(M_T_BEN+(1/R_M3)*(1+B$45)*(M_S_ALL-M_S_RS))/(N_T-M_T_RS25+(1/R_M3)*(1+B$45)*(N_S_EX-M_S_RS))) -> 0.30394593 | F45: =IF(ACQ="SpaceX",(M_S_ALL-M_S_RS+R_M4*(1+B$45)*M_T_BEN)/(N_S_EX-M_S_RS+R_M4*(1+B$45)*(N_T-M_T_RS25)),(M_T_BEN+(1/R_M4)*(1+B$45)*(M_S_ALL-M_S_RS))/(N_T-M_T_RS25+(1/R_M4)*(1+B$45)*(N_S_EX-M_S_RS))) -> 0.24052677 | G45: =IF(ACQ="SpaceX",(M_S_ALL-M_S_RS+R_M5*(1+B$45)*M_T_BEN)/(N_S_EX-M_S_RS+R_M5*(1+B$45)*(N_T-M_T_RS25)),(M_T_BEN+(1/R_M5)*(1+B$45)*(M_S_ALL-M_S_RS))/(N_T-M_T_RS25+(1/R_M5)*(1+B$45)*(N_S_EX-M_S_RS))) -> 0.28782726
B46: =B10 -> 0.2 | C46: =IF(ACQ="SpaceX",(M_S_ALL-M_S_RS+R_M1*(1+B$46)*M_T_BEN)/(N_S_EX-M_S_RS+R_M1*(1+B$46)*(N_T-M_T_RS25)),(M_T_BEN+(1/R_M1)*(1+B$46)*(M_S_ALL-M_S_RS))/(N_T-M_T_RS25+(1/R_M1)*(1+B$46)*(N_S_EX-M_S_RS))) -> 0.29997278 | D46: =IF(ACQ="SpaceX",(M_S_ALL-M_S_RS+R_M2*(1+B$46)*M_T_BEN)/(N_S_EX-M_S_RS+R_M2*(1+B$46)*(N_T-M_T_RS25)),(M_T_BEN+(1/R_M2)*(1+B$46)*(M_S_ALL-M_S_RS))/(N_T-M_T_RS25+(1/R_M2)*(1+B$46)*(N_S_EX-M_S_RS))) -> 0.30252345 | E46: =IF(ACQ="SpaceX",(M_S_ALL-M_S_RS+R_M3*(1+B$46)*M_T_BEN)/(N_S_EX-M_S_RS+R_M3*(1+B$46)*(N_T-M_T_RS25)),(M_T_BEN+(1/R_M3)*(1+B$46)*(M_S_ALL-M_S_RS))/(N_T-M_T_RS25+(1/R_M3)*(1+B$46)*(N_S_EX-M_S_RS))) -> 0.30193765 | F46: =IF(ACQ="SpaceX",(M_S_ALL-M_S_RS+R_M4*(1+B$46)*M_T_BEN)/(N_S_EX-M_S_RS+R_M4*(1+B$46)*(N_T-M_T_RS25)),(M_T_BEN+(1/R_M4)*(1+B$46)*(M_S_ALL-M_S_RS))/(N_T-M_T_RS25+(1/R_M4)*(1+B$46)*(N_S_EX-M_S_RS))) -> 0.23914284 | G46: =IF(ACQ="SpaceX",(M_S_ALL-M_S_RS+R_M5*(1+B$46)*M_T_BEN)/(N_S_EX-M_S_RS+R_M5*(1+B$46)*(N_T-M_T_RS25)),(M_T_BEN+(1/R_M5)*(1+B$46)*(M_S_ALL-M_S_RS))/(N_T-M_T_RS25+(1/R_M5)*(1+B$46)*(N_S_EX-M_S_RS))) -> 0.28580935
B47: =B11 -> 0.25 | C47: =IF(ACQ="SpaceX",(M_S_ALL-M_S_RS+R_M1*(1+B$47)*M_T_BEN)/(N_S_EX-M_S_RS+R_M1*(1+B$47)*(N_T-M_T_RS25)),(M_T_BEN+(1/R_M1)*(1+B$47)*(M_S_ALL-M_S_RS))/(N_T-M_T_RS25+(1/R_M1)*(1+B$47)*(N_S_EX-M_S_RS))) -> 0.29803396 | D47: =IF(ACQ="SpaceX",(M_S_ALL-M_S_RS+R_M2*(1+B$47)*M_T_BEN)/(N_S_EX-M_S_RS+R_M2*(1+B$47)*(N_T-M_T_RS25)),(M_T_BEN+(1/R_M2)*(1+B$47)*(M_S_ALL-M_S_RS))/(N_T-M_T_RS25+(1/R_M2)*(1+B$47)*(N_S_EX-M_S_RS))) -> 0.300592 | E47: =IF(ACQ="SpaceX",(M_S_ALL-M_S_RS+R_M3*(1+B$47)*M_T_BEN)/(N_S_EX-M_S_RS+R_M3*(1+B$47)*(N_T-M_T_RS25)),(M_T_BEN+(1/R_M3)*(1+B$47)*(M_S_ALL-M_S_RS))/(N_T-M_T_RS25+(1/R_M3)*(1+B$47)*(N_S_EX-M_S_RS))) -> 0.30000426 | F47: =IF(ACQ="SpaceX",(M_S_ALL-M_S_RS+R_M4*(1+B$47)*M_T_BEN)/(N_S_EX-M_S_RS+R_M4*(1+B$47)*(N_T-M_T_RS25)),(M_T_BEN+(1/R_M4)*(1+B$47)*(M_S_ALL-M_S_RS))/(N_T-M_T_RS25+(1/R_M4)*(1+B$47)*(N_S_EX-M_S_RS))) -> 0.23784662 | G47: =IF(ACQ="SpaceX",(M_S_ALL-M_S_RS+R_M5*(1+B$47)*M_T_BEN)/(N_S_EX-M_S_RS+R_M5*(1+B$47)*(N_T-M_T_RS25)),(M_T_BEN+(1/R_M5)*(1+B$47)*(M_S_ALL-M_S_RS))/(N_T-M_T_RS25+(1/R_M5)*(1+B$47)*(N_S_EX-M_S_RS))) -> 0.28388034
B48: =B12 -> 0.3 | C48: =IF(ACQ="SpaceX",(M_S_ALL-M_S_RS+R_M1*(1+B$48)*M_T_BEN)/(N_S_EX-M_S_RS+R_M1*(1+B$48)*(N_T-M_T_RS25)),(M_T_BEN+(1/R_M1)*(1+B$48)*(M_S_ALL-M_S_RS))/(N_T-M_T_RS25+(1/R_M1)*(1+B$48)*(N_S_EX-M_S_RS))) -> 0.29616765 | D48: =IF(ACQ="SpaceX",(M_S_ALL-M_S_RS+R_M2*(1+B$48)*M_T_BEN)/(N_S_EX-M_S_RS+R_M2*(1+B$48)*(N_T-M_T_RS25)),(M_T_BEN+(1/R_M2)*(1+B$48)*(M_S_ALL-M_S_RS))/(N_T-M_T_RS25+(1/R_M2)*(1+B$48)*(N_S_EX-M_S_RS))) -> 0.29873079 | E48: =IF(ACQ="SpaceX",(M_S_ALL-M_S_RS+R_M3*(1+B$48)*M_T_BEN)/(N_S_EX-M_S_RS+R_M3*(1+B$48)*(N_T-M_T_RS25)),(M_T_BEN+(1/R_M3)*(1+B$48)*(M_S_ALL-M_S_RS))/(N_T-M_T_RS25+(1/R_M3)*(1+B$48)*(N_S_EX-M_S_RS))) -> 0.29814163 | F48: =IF(ACQ="SpaceX",(M_S_ALL-M_S_RS+R_M4*(1+B$48)*M_T_BEN)/(N_S_EX-M_S_RS+R_M4*(1+B$48)*(N_T-M_T_RS25)),(M_T_BEN+(1/R_M4)*(1+B$48)*(M_S_ALL-M_S_RS))/(N_T-M_T_RS25+(1/R_M4)*(1+B$48)*(N_S_EX-M_S_RS))) -> 0.23663002 | G48: =IF(ACQ="SpaceX",(M_S_ALL-M_S_RS+R_M5*(1+B$48)*M_T_BEN)/(N_S_EX-M_S_RS+R_M5*(1+B$48)*(N_T-M_T_RS25)),(M_T_BEN+(1/R_M5)*(1+B$48)*(M_S_ALL-M_S_RS))/(N_T-M_T_RS25+(1/R_M5)*(1+B$48)*(N_S_EX-M_S_RS))) -> 0.28203448
B49: =B13 -> 0.35 | C49: =IF(ACQ="SpaceX",(M_S_ALL-M_S_RS+R_M1*(1+B$49)*M_T_BEN)/(N_S_EX-M_S_RS+R_M1*(1+B$49)*(N_T-M_T_RS25)),(M_T_BEN+(1/R_M1)*(1+B$49)*(M_S_ALL-M_S_RS))/(N_T-M_T_RS25+(1/R_M1)*(1+B$49)*(N_S_EX-M_S_RS))) -> 0.29436986 | D49: =IF(ACQ="SpaceX",(M_S_ALL-M_S_RS+R_M2*(1+B$49)*M_T_BEN)/(N_S_EX-M_S_RS+R_M2*(1+B$49)*(N_T-M_T_RS25)),(M_T_BEN+(1/R_M2)*(1+B$49)*(M_S_ALL-M_S_RS))/(N_T-M_T_RS25+(1/R_M2)*(1+B$49)*(N_S_EX-M_S_RS))) -> 0.29693605 | E49: =IF(ACQ="SpaceX",(M_S_ALL-M_S_RS+R_M3*(1+B$49)*M_T_BEN)/(N_S_EX-M_S_RS+R_M3*(1+B$49)*(N_T-M_T_RS25)),(M_T_BEN+(1/R_M3)*(1+B$49)*(M_S_ALL-M_S_RS))/(N_T-M_T_RS25+(1/R_M3)*(1+B$49)*(N_S_EX-M_S_RS))) -> 0.29634597 | F49: =IF(ACQ="SpaceX",(M_S_ALL-M_S_RS+R_M4*(1+B$49)*M_T_BEN)/(N_S_EX-M_S_RS+R_M4*(1+B$49)*(N_T-M_T_RS25)),(M_T_BEN+(1/R_M4)*(1+B$49)*(M_S_ALL-M_S_RS))/(N_T-M_T_RS25+(1/R_M4)*(1+B$49)*(N_S_EX-M_S_RS))) -> 0.23548594 | G49: =IF(ACQ="SpaceX",(M_S_ALL-M_S_RS+R_M5*(1+B$49)*M_T_BEN)/(N_S_EX-M_S_RS+R_M5*(1+B$49)*(N_T-M_T_RS25)),(M_T_BEN+(1/R_M5)*(1+B$49)*(M_S_ALL-M_S_RS))/(N_T-M_T_RS25+(1/R_M5)*(1+B$49)*(N_S_EX-M_S_RS))) -> 0.28026651
B50: =B14 -> 0.4 | C50: =IF(ACQ="SpaceX",(M_S_ALL-M_S_RS+R_M1*(1+B$50)*M_T_BEN)/(N_S_EX-M_S_RS+R_M1*(1+B$50)*(N_T-M_T_RS25)),(M_T_BEN+(1/R_M1)*(1+B$50)*(M_S_ALL-M_S_RS))/(N_T-M_T_RS25+(1/R_M1)*(1+B$50)*(N_S_EX-M_S_RS))) -> 0.29263689 | D50: =IF(ACQ="SpaceX",(M_S_ALL-M_S_RS+R_M2*(1+B$50)*M_T_BEN)/(N_S_EX-M_S_RS+R_M2*(1+B$50)*(N_T-M_T_RS25)),(M_T_BEN+(1/R_M2)*(1+B$50)*(M_S_ALL-M_S_RS))/(N_T-M_T_RS25+(1/R_M2)*(1+B$50)*(N_S_EX-M_S_RS))) -> 0.2952043 | E50: =IF(ACQ="SpaceX",(M_S_ALL-M_S_RS+R_M3*(1+B$50)*M_T_BEN)/(N_S_EX-M_S_RS+R_M3*(1+B$50)*(N_T-M_T_RS25)),(M_T_BEN+(1/R_M3)*(1+B$50)*(M_S_ALL-M_S_RS))/(N_T-M_T_RS25+(1/R_M3)*(1+B$50)*(N_S_EX-M_S_RS))) -> 0.29461371 | F50: =IF(ACQ="SpaceX",(M_S_ALL-M_S_RS+R_M4*(1+B$50)*M_T_BEN)/(N_S_EX-M_S_RS+R_M4*(1+B$50)*(N_T-M_T_RS25)),(M_T_BEN+(1/R_M4)*(1+B$50)*(M_S_ALL-M_S_RS))/(N_T-M_T_RS25+(1/R_M4)*(1+B$50)*(N_S_EX-M_S_RS))) -> 0.23440806 | G50: =IF(ACQ="SpaceX",(M_S_ALL-M_S_RS+R_M5*(1+B$50)*M_T_BEN)/(N_S_EX-M_S_RS+R_M5*(1+B$50)*(N_T-M_T_RS25)),(M_T_BEN+(1/R_M5)*(1+B$50)*(M_S_ALL-M_S_RS))/(N_T-M_T_RS25+(1/R_M5)*(1+B$50)*(N_S_EX-M_S_RS))) -> 0.2785716
B52: 表5 隐含对价总额（十亿美元，按各方法收购方每股价值） | I52: =IF(ACQ="SpaceX","收购方：SpaceX；被收购方：特斯拉","收购方：特斯拉；被收购方：SpaceX") -> 收购方：SpaceX；被收购方：特斯拉
B53: 溢价率 \ 定价方法 | C53: ① 不受影响日收盘市值 | D53: ② N 日成交量加权均价（VWAP） | E53: ③ 消息公布后收盘价（参考） | F53: ④ LTM 营收贡献法（同一 EV/营收） | G53: ⑤ LTM EBITDA 贡献法（同一 EV/EBITDA）
B54: =B6 -> 0 | C54: =IF(ACQ="SpaceX",R_M1*(1+B$54)*N_T*PS_M1,(1/R_M1)*(1+B$54)*N_S_EX*PT_M1)/1000 -> 1477.1852 | D54: =IF(ACQ="SpaceX",R_M2*(1+B$54)*N_T*PS_M2,(1/R_M2)*(1+B$54)*N_S_EX*PT_M2)/1000 -> 1454.3866 | E54: =IF(ACQ="SpaceX",R_M3*(1+B$54)*N_T*PS_M3,(1/R_M3)*(1+B$54)*N_S_EX*PT_M3)/1000 -> 1527.6224 | F54: =IF(ACQ="SpaceX",R_M4*(1+B$54)*N_T*PS_M4,(1/R_M4)*(1+B$54)*N_S_EX*PT_M4)/1000 -> 2630.8624 | G54: =IF(ACQ="SpaceX",R_M5*(1+B$54)*N_T*PS_M5,(1/R_M5)*(1+B$54)*N_S_EX*PT_M5)/1000 -> 1734.4884
B55: =B7 -> 0.05 | C55: =IF(ACQ="SpaceX",R_M1*(1+B$55)*N_T*PS_M1,(1/R_M1)*(1+B$55)*N_S_EX*PT_M1)/1000 -> 1551.0444 | D55: =IF(ACQ="SpaceX",R_M2*(1+B$55)*N_T*PS_M2,(1/R_M2)*(1+B$55)*N_S_EX*PT_M2)/1000 -> 1527.1059 | E55: =IF(ACQ="SpaceX",R_M3*(1+B$55)*N_T*PS_M3,(1/R_M3)*(1+B$55)*N_S_EX*PT_M3)/1000 -> 1604.0035 | F55: =IF(ACQ="SpaceX",R_M4*(1+B$55)*N_T*PS_M4,(1/R_M4)*(1+B$55)*N_S_EX*PT_M4)/1000 -> 2762.4055 | G55: =IF(ACQ="SpaceX",R_M5*(1+B$55)*N_T*PS_M5,(1/R_M5)*(1+B$55)*N_S_EX*PT_M5)/1000 -> 1821.2128
B56: =B8 -> 0.1 | C56: =IF(ACQ="SpaceX",R_M1*(1+B$56)*N_T*PS_M1,(1/R_M1)*(1+B$56)*N_S_EX*PT_M1)/1000 -> 1624.9037 | D56: =IF(ACQ="SpaceX",R_M2*(1+B$56)*N_T*PS_M2,(1/R_M2)*(1+B$56)*N_S_EX*PT_M2)/1000 -> 1599.8252 | E56: =IF(ACQ="SpaceX",R_M3*(1+B$56)*N_T*PS_M3,(1/R_M3)*(1+B$56)*N_S_EX*PT_M3)/1000 -> 1680.3846 | F56: =IF(ACQ="SpaceX",R_M4*(1+B$56)*N_T*PS_M4,(1/R_M4)*(1+B$56)*N_S_EX*PT_M4)/1000 -> 2893.9486 | G56: =IF(ACQ="SpaceX",R_M5*(1+B$56)*N_T*PS_M5,(1/R_M5)*(1+B$56)*N_S_EX*PT_M5)/1000 -> 1907.9372
B57: =B9 -> 0.15 | C57: =IF(ACQ="SpaceX",R_M1*(1+B$57)*N_T*PS_M1,(1/R_M1)*(1+B$57)*N_S_EX*PT_M1)/1000 -> 1698.7629 | D57: =IF(ACQ="SpaceX",R_M2*(1+B$57)*N_T*PS_M2,(1/R_M2)*(1+B$57)*N_S_EX*PT_M2)/1000 -> 1672.5445 | E57: =IF(ACQ="SpaceX",R_M3*(1+B$57)*N_T*PS_M3,(1/R_M3)*(1+B$57)*N_S_EX*PT_M3)/1000 -> 1756.7657 | F57: =IF(ACQ="SpaceX",R_M4*(1+B$57)*N_T*PS_M4,(1/R_M4)*(1+B$57)*N_S_EX*PT_M4)/1000 -> 3025.4917 | G57: =IF(ACQ="SpaceX",R_M5*(1+B$57)*N_T*PS_M5,(1/R_M5)*(1+B$57)*N_S_EX*PT_M5)/1000 -> 1994.6616
B58: =B10 -> 0.2 | C58: =IF(ACQ="SpaceX",R_M1*(1+B$58)*N_T*PS_M1,(1/R_M1)*(1+B$58)*N_S_EX*PT_M1)/1000 -> 1772.6222 | D58: =IF(ACQ="SpaceX",R_M2*(1+B$58)*N_T*PS_M2,(1/R_M2)*(1+B$58)*N_S_EX*PT_M2)/1000 -> 1745.2639 | E58: =IF(ACQ="SpaceX",R_M3*(1+B$58)*N_T*PS_M3,(1/R_M3)*(1+B$58)*N_S_EX*PT_M3)/1000 -> 1833.1468 | F58: =IF(ACQ="SpaceX",R_M4*(1+B$58)*N_T*PS_M4,(1/R_M4)*(1+B$58)*N_S_EX*PT_M4)/1000 -> 3157.0348 | G58: =IF(ACQ="SpaceX",R_M5*(1+B$58)*N_T*PS_M5,(1/R_M5)*(1+B$58)*N_S_EX*PT_M5)/1000 -> 2081.386
B59: =B11 -> 0.25 | C59: =IF(ACQ="SpaceX",R_M1*(1+B$59)*N_T*PS_M1,(1/R_M1)*(1+B$59)*N_S_EX*PT_M1)/1000 -> 1846.4815 | D59: =IF(ACQ="SpaceX",R_M2*(1+B$59)*N_T*PS_M2,(1/R_M2)*(1+B$59)*N_S_EX*PT_M2)/1000 -> 1817.9832 | E59: =IF(ACQ="SpaceX",R_M3*(1+B$59)*N_T*PS_M3,(1/R_M3)*(1+B$59)*N_S_EX*PT_M3)/1000 -> 1909.528 | F59: =IF(ACQ="SpaceX",R_M4*(1+B$59)*N_T*PS_M4,(1/R_M4)*(1+B$59)*N_S_EX*PT_M4)/1000 -> 3288.578 | G59: =IF(ACQ="SpaceX",R_M5*(1+B$59)*N_T*PS_M5,(1/R_M5)*(1+B$59)*N_S_EX*PT_M5)/1000 -> 2168.1105
B60: =B12 -> 0.3 | C60: =IF(ACQ="SpaceX",R_M1*(1+B$60)*N_T*PS_M1,(1/R_M1)*(1+B$60)*N_S_EX*PT_M1)/1000 -> 1920.3407 | D60: =IF(ACQ="SpaceX",R_M2*(1+B$60)*N_T*PS_M2,(1/R_M2)*(1+B$60)*N_S_EX*PT_M2)/1000 -> 1890.7025 | E60: =IF(ACQ="SpaceX",R_M3*(1+B$60)*N_T*PS_M3,(1/R_M3)*(1+B$60)*N_S_EX*PT_M3)/1000 -> 1985.9091 | F60: =IF(ACQ="SpaceX",R_M4*(1+B$60)*N_T*PS_M4,(1/R_M4)*(1+B$60)*N_S_EX*PT_M4)/1000 -> 3420.1211 | G60: =IF(ACQ="SpaceX",R_M5*(1+B$60)*N_T*PS_M5,(1/R_M5)*(1+B$60)*N_S_EX*PT_M5)/1000 -> 2254.8349
B61: =B13 -> 0.35 | C61: =IF(ACQ="SpaceX",R_M1*(1+B$61)*N_T*PS_M1,(1/R_M1)*(1+B$61)*N_S_EX*PT_M1)/1000 -> 1994.2 | D61: =IF(ACQ="SpaceX",R_M2*(1+B$61)*N_T*PS_M2,(1/R_M2)*(1+B$61)*N_S_EX*PT_M2)/1000 -> 1963.4219 | E61: =IF(ACQ="SpaceX",R_M3*(1+B$61)*N_T*PS_M3,(1/R_M3)*(1+B$61)*N_S_EX*PT_M3)/1000 -> 2062.2902 | F61: =IF(ACQ="SpaceX",R_M4*(1+B$61)*N_T*PS_M4,(1/R_M4)*(1+B$61)*N_S_EX*PT_M4)/1000 -> 3551.6642 | G61: =IF(ACQ="SpaceX",R_M5*(1+B$61)*N_T*PS_M5,(1/R_M5)*(1+B$61)*N_S_EX*PT_M5)/1000 -> 2341.5593
B62: =B14 -> 0.4 | C62: =IF(ACQ="SpaceX",R_M1*(1+B$62)*N_T*PS_M1,(1/R_M1)*(1+B$62)*N_S_EX*PT_M1)/1000 -> 2068.0592 | D62: =IF(ACQ="SpaceX",R_M2*(1+B$62)*N_T*PS_M2,(1/R_M2)*(1+B$62)*N_S_EX*PT_M2)/1000 -> 2036.1412 | E62: =IF(ACQ="SpaceX",R_M3*(1+B$62)*N_T*PS_M3,(1/R_M3)*(1+B$62)*N_S_EX*PT_M3)/1000 -> 2138.6713 | F62: =IF(ACQ="SpaceX",R_M4*(1+B$62)*N_T*PS_M4,(1/R_M4)*(1+B$62)*N_S_EX*PT_M4)/1000 -> 3683.2073 | G62: =IF(ACQ="SpaceX",R_M5*(1+B$62)*N_T*PS_M5,(1/R_M5)*(1+B$62)*N_S_EX*PT_M5)/1000 -> 2428.2837
B64: 说明：方法③已包含消息公布后的市场反应，仅作对照；方法④⑤为“同一倍数”的贡献度测算，不代表对任何一方价值的判断。

Sheet 校验
B1: 校验汇总
B2: 差异绝对值 < 0.5（百万美元/股数）视为通过；最后一部分统计各工作表公式错误值数量。
B4: # | C4: 校验项 | D4: 差异 | E4: 结果
B5: 1 | C5: SpaceX FY2025 经营利润勾稽 | D5: ='SpaceX财务'!$C$25 -> 0 | E5: =IF(ABS(D5)<0.5,"通过","差异") -> 通过
B6: 2 | C6: SpaceX 9M 2025 经营利润勾稽 | D6: ='SpaceX财务'!$D$25 -> 0 | E6: =IF(ABS(D6)<0.5,"通过","差异") -> 通过
B7: 3 | C7: SpaceX Q1 2026 经营利润勾稽 | D7: ='SpaceX财务'!$E$25 -> 0 | E7: =IF(ABS(D7)<0.5,"通过","差异") -> 通过
B8: 4 | C8: SpaceX Q2 2026 经营利润勾稽 | D8: ='SpaceX财务'!$F$25 -> 0 | E8: =IF(ABS(D8)<0.5,"通过","差异") -> 通过
B9: 5 | C9: SpaceX 6M 2026 经营利润勾稽 | D9: ='SpaceX财务'!$G$25 -> 0 | E9: =IF(ABS(D9)<0.5,"通过","差异") -> 通过
B10: 6 | C10: SpaceX Q3 2026 经营利润勾稽 | D10: ='SpaceX财务'!$H$25 -> 0 | E10: =IF(ABS(D10)<0.5,"通过","差异") -> 通过
B11: 7 | C11: SpaceX 9M 2026 经营利润勾稽 | D11: ='SpaceX财务'!$I$25 -> 0 | E11: =IF(ABS(D11)<0.5,"通过","差异") -> 通过
B12: 8 | C12: SpaceX FY2025 净利润勾稽 | D12: ='SpaceX财务'!$C$26 -> 0 | E12: =IF(ABS(D12)<0.5,"通过","差异") -> 通过
B13: 9 | C13: SpaceX 9M 2025 净利润勾稽 | D13: ='SpaceX财务'!$D$26 -> 0 | E13: =IF(ABS(D13)<0.5,"通过","差异") -> 通过
B14: 10 | C14: SpaceX Q1 2026 净利润勾稽 | D14: ='SpaceX财务'!$E$26 -> 0 | E14: =IF(ABS(D14)<0.5,"通过","差异") -> 通过
B15: 11 | C15: SpaceX Q2 2026 净利润勾稽 | D15: ='SpaceX财务'!$F$26 -> 0 | E15: =IF(ABS(D15)<0.5,"通过","差异") -> 通过
B16: 12 | C16: SpaceX 6M 2026 净利润勾稽 | D16: ='SpaceX财务'!$G$26 -> 0 | E16: =IF(ABS(D16)<0.5,"通过","差异") -> 通过
B17: 13 | C17: SpaceX Q3 2026 净利润勾稽 | D17: ='SpaceX财务'!$H$26 -> 0 | E17: =IF(ABS(D17)<0.5,"通过","差异") -> 通过
B18: 14 | C18: SpaceX 9M 2026 净利润勾稽 | D18: ='SpaceX财务'!$I$26 -> 0 | E18: =IF(ABS(D18)<0.5,"通过","差异") -> 通过
B19: 15 | C19: SpaceX FY2025 调整后EBITDA勾稽 | D19: ='SpaceX财务'!$C$27 -> 0 | E19: =IF(ABS(D19)<0.5,"通过","差异") -> 通过
B20: 16 | C20: SpaceX 9M 2025 调整后EBITDA勾稽 | D20: ='SpaceX财务'!$D$27 -> 0 | E20: =IF(ABS(D20)<0.5,"通过","差异") -> 通过
B21: 17 | C21: SpaceX Q1 2026 调整后EBITDA勾稽 | D21: ='SpaceX财务'!$E$27 -> 0 | E21: =IF(ABS(D21)<0.5,"通过","差异") -> 通过
B22: 18 | C22: SpaceX Q2 2026 调整后EBITDA勾稽 | D22: ='SpaceX财务'!$F$27 -> 0 | E22: =IF(ABS(D22)<0.5,"通过","差异") -> 通过
B23: 19 | C23: SpaceX 6M 2026 调整后EBITDA勾稽 | D23: ='SpaceX财务'!$G$27 -> 0 | E23: =IF(ABS(D23)<0.5,"通过","差异") -> 通过
B24: 20 | C24: SpaceX Q3 2026 调整后EBITDA勾稽 | D24: ='SpaceX财务'!$H$27 -> 0 | E24: =IF(ABS(D24)<0.5,"通过","差异") -> 通过
B25: 21 | C25: SpaceX 9M 2026 调整后EBITDA勾稽 | D25: ='SpaceX财务'!$I$27 -> 0 | E25: =IF(ABS(D25)<0.5,"通过","差异") -> 通过
B26: 22 | C26: SpaceX Q2 2026 与累计数相减一致 | D26: ='SpaceX财务'!$F$28 -> 0 | E26: =IF(ABS(D26)<0.5,"通过","差异") -> 通过
B27: 23 | C27: SpaceX Q3 2026 与累计数相减一致 | D27: ='SpaceX财务'!$H$28 -> 0 | E27: =IF(ABS(D27)<0.5,"通过","差异") -> 通过
B28: 24 | C28: SpaceX FY2025 分部分部营收合计 | D28: ='SpaceX财务'!$C$52 -> 0 | E28: =IF(ABS(D28)<0.5,"通过","差异") -> 通过
B29: 25 | C29: SpaceX 9M 2025 分部分部营收合计 | D29: ='SpaceX财务'!$D$52 -> 0 | E29: =IF(ABS(D29)<0.5,"通过","差异") -> 通过
B30: 26 | C30: SpaceX Q1 2026 分部分部营收合计 | D30: ='SpaceX财务'!$E$52 -> 0 | E30: =IF(ABS(D30)<0.5,"通过","差异") -> 通过
B31: 27 | C31: SpaceX Q2 2026 分部分部营收合计 | D31: ='SpaceX财务'!$F$52 -> 0 | E31: =IF(ABS(D31)<0.5,"通过","差异") -> 通过
B32: 28 | C32: SpaceX Q3 2026 分部分部营收合计 | D32: ='SpaceX财务'!$G$52 -> 0 | E32: =IF(ABS(D32)<0.5,"通过","差异") -> 通过
B33: 29 | C33: SpaceX 9M 2026 分部分部营收合计 | D33: ='SpaceX财务'!$H$52 -> 0 | E33: =IF(ABS(D33)<0.5,"通过","差异") -> 通过
B34: 30 | C34: SpaceX FY2025 分部分部营业成本合计 | D34: ='SpaceX财务'!$C$56 -> 0 | E34: =IF(ABS(D34)<0.5,"通过","差异") -> 通过
B35: 31 | C35: SpaceX 9M 2025 分部分部营业成本合计 | D35: ='SpaceX财务'!$D$56 -> 0 | E35: =IF(ABS(D35)<0.5,"通过","差异") -> 通过
B36: 32 | C36: SpaceX Q1 2026 分部分部营业成本合计 | D36: ='SpaceX财务'!$E$56 -> 0 | E36: =IF(ABS(D36)<0.5,"通过","差异") -> 通过
B37: 33 | C37: SpaceX Q2 2026 分部分部营业成本合计 | D37: ='SpaceX财务'!$F$56 -> 0 | E37: =IF(ABS(D37)<0.5,"通过","差异") -> 通过
B38: 34 | C38: SpaceX Q3 2026 分部分部营业成本合计 | D38: ='SpaceX财务'!$G$56 -> 0 | E38: =IF(ABS(D38)<0.5,"通过","差异") -> 通过
B39: 35 | C39: SpaceX 9M 2026 分部分部营业成本合计 | D39: ='SpaceX财务'!$H$56 -> 0 | E39: =IF(ABS(D39)<0.5,"通过","差异") -> 通过
B40: 36 | C40: SpaceX FY2025 分部分部经营利润合计 | D40: ='SpaceX财务'!$C$60 -> 0 | E40: =IF(ABS(D40)<0.5,"通过","差异") -> 通过
B41: 37 | C41: SpaceX 9M 2025 分部分部经营利润合计 | D41: ='SpaceX财务'!$D$60 -> 0 | E41: =IF(ABS(D41)<0.5,"通过","差异") -> 通过
B42: 38 | C42: SpaceX Q1 2026 分部分部经营利润合计 | D42: ='SpaceX财务'!$E$60 -> 0 | E42: =IF(ABS(D42)<0.5,"通过","差异") -> 通过
B43: 39 | C43: SpaceX Q2 2026 分部分部经营利润合计 | D43: ='SpaceX财务'!$F$60 -> 0 | E43: =IF(ABS(D43)<0.5,"通过","差异") -> 通过
B44: 40 | C44: SpaceX Q3 2026 分部分部经营利润合计 | D44: ='SpaceX财务'!$G$60 -> 0 | E44: =IF(ABS(D44)<0.5,"通过","差异") -> 通过
B45: 41 | C45: SpaceX 9M 2026 分部分部经营利润合计 | D45: ='SpaceX财务'!$H$60 -> 0 | E45: =IF(ABS(D45)<0.5,"通过","差异") -> 通过
B46: 42 | C46: SpaceX FY2025 分部分部调整后EBITDA（非GAAP）合计 | D46: ='SpaceX财务'!$C$64 -> 0 | E46: =IF(ABS(D46)<0.5,"通过","差异") -> 通过
B47: 43 | C47: SpaceX 9M 2025 分部分部调整后EBITDA（非GAAP）合计 | D47: ='SpaceX财务'!$D$64 -> 0 | E47: =IF(ABS(D47)<0.5,"通过","差异") -> 通过
B48: 44 | C48: SpaceX Q1 2026 分部分部调整后EBITDA（非GAAP）合计 | D48: ='SpaceX财务'!$E$64 -> 0 | E48: =IF(ABS(D48)<0.5,"通过","差异") -> 通过
B49: 45 | C49: SpaceX Q2 2026 分部分部调整后EBITDA（非GAAP）合计 | D49: ='SpaceX财务'!$F$64 -> 0 | E49: =IF(ABS(D49)<0.5,"通过","差异") -> 通过
B50: 46 | C50: SpaceX Q3 2026 分部分部调整后EBITDA（非GAAP）合计 | D50: ='SpaceX财务'!$G$64 -> 0 | E50: =IF(ABS(D50)<0.5,"通过","差异") -> 通过
B51: 47 | C51: SpaceX 9M 2026 分部分部调整后EBITDA（非GAAP）合计 | D51: ='SpaceX财务'!$H$64 -> 0 | E51: =IF(ABS(D51)<0.5,"通过","差异") -> 通过
B52: 48 | C52: SpaceX FY2025 分部分部资本开支合计 | D52: ='SpaceX财务'!$C$68 -> 0 | E52: =IF(ABS(D52)<0.5,"通过","差异") -> 通过
B53: 49 | C53: SpaceX 9M 2025 分部分部资本开支合计 | D53: ='SpaceX财务'!$D$68 -> 0 | E53: =IF(ABS(D53)<0.5,"通过","差异") -> 通过
B54: 50 | C54: SpaceX Q1 2026 分部分部资本开支合计 | D54: ='SpaceX财务'!$E$68 -> 0 | E54: =IF(ABS(D54)<0.5,"通过","差异") -> 通过
B55: 51 | C55: SpaceX Q2 2026 分部分部资本开支合计 | D55: ='SpaceX财务'!$F$68 -> 0 | E55: =IF(ABS(D55)<0.5,"通过","差异") -> 通过
B56: 52 | C56: SpaceX Q3 2026 分部分部资本开支合计 | D56: ='SpaceX财务'!$G$68 -> 0 | E56: =IF(ABS(D56)<0.5,"通过","差异") -> 通过
B57: 53 | C57: SpaceX 9M 2026 分部分部资本开支合计 | D57: ='SpaceX财务'!$H$68 -> 0 | E57: =IF(ABS(D57)<0.5,"通过","差异") -> 通过
B58: 54 | C58: SpaceX 标准化 Q4 2025 分部营收合计 | D58: ='SpaceX财务'!$C$132 -> 0 | E58: =IF(ABS(D58)<0.5,"通过","差异") -> 通过
B59: 55 | C59: SpaceX 标准化 Q1 2026 分部营收合计 | D59: ='SpaceX财务'!$D$132 -> 0 | E59: =IF(ABS(D59)<0.5,"通过","差异") -> 通过
B60: 56 | C60: SpaceX 标准化 Q2 2026 分部营收合计 | D60: ='SpaceX财务'!$E$132 -> 0 | E60: =IF(ABS(D60)<0.5,"通过","差异") -> 通过
B61: 57 | C61: SpaceX 标准化 Q3 2026 分部营收合计 | D61: ='SpaceX财务'!$F$132 -> 0 | E61: =IF(ABS(D61)<0.5,"通过","差异") -> 通过
B62: 58 | C62: SpaceX 标准化 LTM（2025Q4–2026Q3） 分部营收合计 | D62: ='SpaceX财务'!$G$132 -> 0 | E62: =IF(ABS(D62)<0.5,"通过","差异") -> 通过
B63: 59 | C63: SpaceX 标准化 FY2025 分部营收合计 | D63: ='SpaceX财务'!$H$132 -> 0 | E63: =IF(ABS(D63)<0.5,"通过","差异") -> 通过
B64: 60 | C64: SpaceX 标准化 Q4 2025 分部经营利润合计 | D64: ='SpaceX财务'!$C$133 -> 0 | E64: =IF(ABS(D64)<0.5,"通过","差异") -> 通过
B65: 61 | C65: SpaceX 标准化 Q1 2026 分部经营利润合计 | D65: ='SpaceX财务'!$D$133 -> 0 | E65: =IF(ABS(D65)<0.5,"通过","差异") -> 通过
B66: 62 | C66: SpaceX 标准化 Q2 2026 分部经营利润合计 | D66: ='SpaceX财务'!$E$133 -> 0 | E66: =IF(ABS(D66)<0.5,"通过","差异") -> 通过
B67: 63 | C67: SpaceX 标准化 Q3 2026 分部经营利润合计 | D67: ='SpaceX财务'!$F$133 -> 0 | E67: =IF(ABS(D67)<0.5,"通过","差异") -> 通过
B68: 64 | C68: SpaceX 标准化 LTM（2025Q4–2026Q3） 分部经营利润合计 | D68: ='SpaceX财务'!$G$133 -> 0 | E68: =IF(ABS(D68)<0.5,"通过","差异") -> 通过
B69: 65 | C69: SpaceX 标准化 FY2025 分部经营利润合计 | D69: ='SpaceX财务'!$H$133 -> 0 | E69: =IF(ABS(D69)<0.5,"通过","差异") -> 通过
B70: 66 | C70: SpaceX 标准化 Q4 2025 分部资本开支合计 | D70: ='SpaceX财务'!$C$134 -> 0 | E70: =IF(ABS(D70)<0.5,"通过","差异") -> 通过
B71: 67 | C71: SpaceX 标准化 Q1 2026 分部资本开支合计 | D71: ='SpaceX财务'!$D$134 -> 0 | E71: =IF(ABS(D71)<0.5,"通过","差异") -> 通过
B72: 68 | C72: SpaceX 标准化 Q2 2026 分部资本开支合计 | D72: ='SpaceX财务'!$E$134 -> 0 | E72: =IF(ABS(D72)<0.5,"通过","差异") -> 通过
B73: 69 | C73: SpaceX 标准化 Q3 2026 分部资本开支合计 | D73: ='SpaceX财务'!$F$134 -> 0 | E73: =IF(ABS(D73)<0.5,"通过","差异") -> 通过
B74: 70 | C74: SpaceX 标准化 LTM（2025Q4–2026Q3） 分部资本开支合计 | D74: ='SpaceX财务'!$G$134 -> 0 | E74: =IF(ABS(D74)<0.5,"通过","差异") -> 通过
B75: 71 | C75: SpaceX 标准化 FY2025 分部资本开支合计 | D75: ='SpaceX财务'!$H$134 -> 0 | E75: =IF(ABS(D75)<0.5,"通过","差异") -> 通过
B76: 72 | C76: 特斯拉 FY2025 营收分项合计 | D76: ='特斯拉财务'!$C$36 -> 0 | E76: =IF(ABS(D76)<0.5,"通过","差异") -> 通过
B77: 73 | C77: 特斯拉 Q4 2025 营收分项合计 | D77: ='特斯拉财务'!$D$36 -> 0 | E77: =IF(ABS(D77)<0.5,"通过","差异") -> 通过
B78: 74 | C78: 特斯拉 Q1 2026 营收分项合计 | D78: ='特斯拉财务'!$E$36 -> 0 | E78: =IF(ABS(D78)<0.5,"通过","差异") -> 通过
B79: 75 | C79: 特斯拉 Q2 2026 营收分项合计 | D79: ='特斯拉财务'!$F$36 -> 0 | E79: =IF(ABS(D79)<0.5,"通过","差异") -> 通过
B80: 76 | C80: 特斯拉 Q3 2026 营收分项合计 | D80: ='特斯拉财务'!$G$36 -> 0 | E80: =IF(ABS(D80)<0.5,"通过","差异") -> 通过
B81: 77 | C81: 特斯拉 9M 2026 营收分项合计 | D81: ='特斯拉财务'!$H$36 -> 0 | E81: =IF(ABS(D81)<0.5,"通过","差异") -> 通过
B82: 78 | C82: 特斯拉 FY2025 营业成本分项合计 | D82: ='特斯拉财务'!$C$37 -> 0 | E82: =IF(ABS(D82)<0.5,"通过","差异") -> 通过
B83: 79 | C83: 特斯拉 Q4 2025 营业成本分项合计 | D83: ='特斯拉财务'!$D$37 -> 0 | E83: =IF(ABS(D83)<0.5,"通过","差异") -> 通过
B84: 80 | C84: 特斯拉 Q1 2026 营业成本分项合计 | D84: ='特斯拉财务'!$E$37 -> 0 | E84: =IF(ABS(D84)<0.5,"通过","差异") -> 通过
B85: 81 | C85: 特斯拉 Q2 2026 营业成本分项合计 | D85: ='特斯拉财务'!$F$37 -> 0 | E85: =IF(ABS(D85)<0.5,"通过","差异") -> 通过
B86: 82 | C86: 特斯拉 Q3 2026 营业成本分项合计 | D86: ='特斯拉财务'!$G$37 -> 0 | E86: =IF(ABS(D86)<0.5,"通过","差异") -> 通过
B87: 83 | C87: 特斯拉 9M 2026 营业成本分项合计 | D87: ='特斯拉财务'!$H$37 -> 0 | E87: =IF(ABS(D87)<0.5,"通过","差异") -> 通过
B88: 84 | C88: 特斯拉 FY2025 经营利润勾稽 | D88: ='特斯拉财务'!$C$38 -> 0 | E88: =IF(ABS(D88)<0.5,"通过","差异") -> 通过
B89: 85 | C89: 特斯拉 Q4 2025 经营利润勾稽 | D89: ='特斯拉财务'!$D$38 -> 0 | E89: =IF(ABS(D89)<0.5,"通过","差异") -> 通过
B90: 86 | C90: 特斯拉 Q1 2026 经营利润勾稽 | D90: ='特斯拉财务'!$E$38 -> 0 | E90: =IF(ABS(D90)<0.5,"通过","差异") -> 通过
B91: 87 | C91: 特斯拉 Q2 2026 经营利润勾稽 | D91: ='特斯拉财务'!$F$38 -> 0 | E91: =IF(ABS(D91)<0.5,"通过","差异") -> 通过
B92: 88 | C92: 特斯拉 Q3 2026 经营利润勾稽 | D92: ='特斯拉财务'!$G$38 -> 0 | E92: =IF(ABS(D92)<0.5,"通过","差异") -> 通过
B93: 89 | C93: 特斯拉 9M 2026 经营利润勾稽 | D93: ='特斯拉财务'!$H$38 -> 0 | E93: =IF(ABS(D93)<0.5,"通过","差异") -> 通过
B94: 90 | C94: 特斯拉 FY2025 净利润勾稽 | D94: ='特斯拉财务'!$C$39 -> 0 | E94: =IF(ABS(D94)<0.5,"通过","差异") -> 通过
B95: 91 | C95: 特斯拉 Q4 2025 净利润勾稽 | D95: ='特斯拉财务'!$D$39 -> 0 | E95: =IF(ABS(D95)<0.5,"通过","差异") -> 通过
B96: 92 | C96: 特斯拉 Q1 2026 净利润勾稽 | D96: ='特斯拉财务'!$E$39 -> 0 | E96: =IF(ABS(D96)<0.5,"通过","差异") -> 通过
B97: 93 | C97: 特斯拉 Q2 2026 净利润勾稽 | D97: ='特斯拉财务'!$F$39 -> 0 | E97: =IF(ABS(D97)<0.5,"通过","差异") -> 通过
B98: 94 | C98: 特斯拉 Q3 2026 净利润勾稽 | D98: ='特斯拉财务'!$G$39 -> 0 | E98: =IF(ABS(D98)<0.5,"通过","差异") -> 通过
B99: 95 | C99: 特斯拉 9M 2026 净利润勾稽 | D99: ='特斯拉财务'!$H$39 -> 0 | E99: =IF(ABS(D99)<0.5,"通过","差异") -> 通过
B100: 96 | C100: 特斯拉 FY2025 调整后EBITDA勾稽 | D100: ='特斯拉财务'!$C$40 -> 0 | E100: =IF(ABS(D100)<0.5,"通过","差异") -> 通过
B101: 97 | C101: 特斯拉 Q4 2025 调整后EBITDA勾稽 | D101: ='特斯拉财务'!$D$40 -> 0 | E101: =IF(ABS(D101)<0.5,"通过","差异") -> 通过
...
