Workbook

Sheet 说明
B1: 交班之后，伯克希尔的账本
B3: 2021—2025年｜2026年上半年｜公式联动研究底稿
B5: 这份账本把经营分部、浮存金、流动性、股票组合、回购与每股账面价值放在同一套可追溯口径里。
B7: =资产负债!$G9/1000 -> 365.514 | C7: =资产负债!$G10/1000 -> 323.779 | D7: =资产负债!$G5/1000 -> 177.5 | E7: =资产负债!$G13 -> 522395.51
B8: 现金及短期国债 2026年6月末｜十亿美元 | C8: 股票投资组合 2026年6月末｜十亿美元 | D8: 保险浮存金 2026年6月末｜十亿美元 | E8: A类每股账面价值 2026年6月末｜美元
B10: 使用顺序
B11: 1 | C11: 先看『变化』 | D11: 同比、占比、图表和情景结果集中在一页。
B12: 2 | C12: 再看各主题表 | D12: 分部利润、资产负债、股票组合、经营细节均为公式取数。
B13: 3 | C13: 到『数据』追来源 | D13: 黄色为原始输入；每个数值都有来源编号、文件名、章节和批注。
B14: 4 | C14: 修改『假设』B3/B4 | D14: 橙色假设输入会驱动全年情景及『变化』页；不是预测。
B15: 5 | C15: 最后看『校验』 | D15: 所有对账目标为0，总状态应为PASS。
B17: 颜色与口径
B18: 黄色 | C18: 原始披露输入
B19: 蓝色 | C19: 公式计算，不要覆盖
B20: 橙色 | C20: 假设输入，可修改
B22: 必须保留的解释
B23: • 利润：税后、归属伯克希尔股东；核心五项不含投资损益和权益法投资减值。
B24: • 现金及短期国债＝保险及其他现金＋铁路公用事业能源现金＋短期美国国债；不等于可自由分配现金。
B25: • 每股账面价值为本工作簿公式：归母权益÷期末A类等价股数；2021—2022采用后续年报追溯调整口径。
B26: • 浮存金为披露的约数；2026H1与年末差额会受四舍五入影响。
B27: • 研究展示用途，不构成买入、卖出、持有或目标价建议。
B29: 游戏脚本与网页共用同一份题目、选项、分数和引文。网页仅讲历史决策，不放外部链接，不使用公司标志或国旗。

Sheet 数据
A1: 原始数据与逐项出处
A2: 记录 | B2: 类别 | C2: 指标 | D2: 期间 | E2: 数值 | F2: 单位 | G2: 来源编号 | H2: 文件名＋章节/表名 | I2: 口径与备注
A3: 2 | B3: 利润 | C3: 保险承保利润 | D3: 2022A | E3: -30 | F3: 百万美元 | G3: AR23_MD | H3: 交付/来源/Berkshire_2023年报_官方.pdf｜Item 7, MD&A—Results of Operations（K-34） | I3: 税后、归属伯克希尔股东；2021—2022采用2023年报追溯调整口径
A4: 3 | B4: 利润 | C4: 保险承保利润 | D4: 2023A | E4: 5428 | F4: 百万美元 | G4: AR25_MD | H4: 材料/Berkshire_2025年报__brka-20251231.htm｜Item 7, MD&A—Results of Operations（K-34起） | I4: 税后、归属伯克希尔股东；2021—2022采用2023年报追溯调整口径
A5: 4 | B5: 利润 | C5: 保险承保利润 | D5: 2024A | E5: 9020 | F5: 百万美元 | G5: AR25_MD | H5: 材料/Berkshire_2025年报__brka-20251231.htm｜Item 7, MD&A—Results of Operations（K-34起） | I5: 税后、归属伯克希尔股东；2021—2022采用2023年报追溯调整口径
A6: 5 | B6: 利润 | C6: 保险承保利润 | D6: 2025A | E6: 7258 | F6: 百万美元 | G6: AR25_MD | H6: 材料/Berkshire_2025年报__brka-20251231.htm｜Item 7, MD&A—Results of Operations（K-34起） | I6: 税后、归属伯克希尔股东；2021—2022采用2023年报追溯调整口径
A7: 6 | B7: 利润 | C7: 保险承保利润 | D7: 2025H1 | E7: 3328 | F7: 百万美元 | G7: Q226_MD | H7: 材料/Berkshire_2026Q2季报__brka-20260630.htm｜Item 2, MD&A—Results of Operations（第33页） | I7: 税后、归属伯克希尔股东；2021—2022采用2023年报追溯调整口径
A8: 7 | B8: 利润 | C8: 保险承保利润 | D8: 2026H1 | E8: 3448 | F8: 百万美元 | G8: Q226_MD | H8: 材料/Berkshire_2026Q2季报__brka-20260630.htm｜Item 2, MD&A—Results of Operations（第33页） | I8: 税后、归属伯克希尔股东；2021—2022采用2023年报追溯调整口径
A9: 8 | B9: 利润 | C9: 保险投资收益 | D9: 2021A | E9: 4807 | F9: 百万美元 | G9: AR23_MD | H9: 交付/来源/Berkshire_2023年报_官方.pdf｜Item 7, MD&A—Results of Operations（K-34） | I9: 税后、归属伯克希尔股东；2021—2022采用2023年报追溯调整口径
A10: 9 | B10: 利润 | C10: 保险投资收益 | D10: 2022A | E10: 6484 | F10: 百万美元 | G10: AR23_MD | H10: 交付/来源/Berkshire_2023年报_官方.pdf｜Item 7, MD&A—Results of Operations（K-34） | I10: 税后、归属伯克希尔股东；2021—2022采用2023年报追溯调整口径
A11: 10 | B11: 利润 | C11: 保险投资收益 | D11: 2023A | E11: 9567 | F11: 百万美元 | G11: AR25_MD | H11: 材料/Berkshire_2025年报__brka-20251231.htm｜Item 7, MD&A—Results of Operations（K-34起） | I11: 税后、归属伯克希尔股东；2021—2022采用2023年报追溯调整口径
A12: 11 | B12: 利润 | C12: 保险投资收益 | D12: 2024A | E12: 13670 | F12: 百万美元 | G12: AR25_MD | H12: 材料/Berkshire_2025年报__brka-20251231.htm｜Item 7, MD&A—Results of Operations（K-34起） | I12: 税后、归属伯克希尔股东；2021—2022采用2023年报追溯调整口径
A13: 12 | B13: 利润 | C13: 保险投资收益 | D13: 2025A | E13: 12513 | F13: 百万美元 | G13: AR25_MD | H13: 材料/Berkshire_2025年报__brka-20251231.htm｜Item 7, MD&A—Results of Operations（K-34起） | I13: 税后、归属伯克希尔股东；2021—2022采用2023年报追溯调整口径
A14: 13 | B14: 利润 | C14: 保险投资收益 | D14: 2025H1 | E14: 6260 | F14: 百万美元 | G14: Q226_MD | H14: 材料/Berkshire_2026Q2季报__brka-20260630.htm｜Item 2, MD&A—Results of Operations（第33页） | I14: 税后、归属伯克希尔股东；2021—2022采用2023年报追溯调整口径
... A67: 66 | B67: 资产负债 | C67: 保险浮存金 | D67: 2026H1 | E67: 177500 | F67: 百万美元 | G67: Q226_FLOAT | H67: 材料/Berkshire_2026Q2季报__brka-20260630.htm｜Item 2—Insurance—Investment Income（第38页） | I67: 原披露为约数；2026年6月末为约1775亿美元
A68: 67 | B68: 资产负债 | C68: 保险及其他现金及现金等价物 | D68: 2021A | E68: 85319 | F68: 百万美元 | G68: AR22_BS | H68: 交付/来源/Berkshire_2022年报_官方.pdf｜Consolidated Balance Sheets
A69: 68 | B69: 资产负债 | C69: 铁路、公用事业及能源现金 | D69: 2021A | E69: 2865 | F69: 百万美元 | G69: AR22_BS | H69: 交付/来源/Berkshire_2022年报_官方.pdf｜Consolidated Balance Sheets
A70: 69 | B70: 资产负债 | C70: 短期美国国债 | D70: 2021A | E70: 58535 | F70: 百万美元 | G70: AR22_BS | H70: 交付/来源/Berkshire_2022年报_官方.pdf｜Consolidated Balance Sheets | I70: 合并资产负债表口径；现金及短期国债合计由公式计算
A71: 70 | B71: 资产负债 | C71: 保险及其他现金及现金等价物 | D71: 2022A | E71: 32260 | F71: 百万美元 | G71: AR23_BS | H71: 交付/来源/Berkshire_2023年报_官方.pdf｜Consolidated Balance Sheets（K-66）
A72: 71 | B72: 资产负债 | C72: 铁路、公用事业及能源现金 | D72: 2022A | E72: 3551 | F72: 百万美元 | G72: AR23_BS | H72: 交付/来源/Berkshire_2023年报_官方.pdf｜Consolidated Balance Sheets（K-66）
A73: 72 | B73: 资产负债 | C73: 短期美国国债 | D73: 2022A | E73: 92774 | F73: 百万美元 | G73: AR23_BS | H73: 交付/来源/Berkshire_2023年报_官方.pdf｜Consolidated Balance Sheets（K-66） | I73: 合并资产负债表口径；现金及短期国债合计由公式计算
A74: 73 | B74: 资产负债 | C74: 保险及其他现金及现金等价物 | D74: 2023A | E74: 33672 | F74: 百万美元 | G74: AR23_BS | H74: 交付/来源/Berkshire_2023年报_官方.pdf｜Consolidated Balance Sheets（K-66）
A75: 74 | B75: 资产负债 | C75: 铁路、公用事业及能源现金 | D75: 2023A | E75: 4350 | F75: 百万美元 | G75: AR23_BS | H75: 交付/来源/Berkshire_2023年报_官方.pdf｜Consolidated Balance Sheets（K-66）
A76: 75 | B76: 资产负债 | C76: 短期美国国债 | D76: 2023A | E76: 129619 | F76: 百万美元 | G76: AR23_BS | H76: 交付/来源/Berkshire_2023年报_官方.pdf｜Consolidated Balance Sheets（K-66） | I76: 合并资产负债表口径；现金及短期国债合计由公式计算
A77: 76 | B77: 资产负债 | C77: 保险及其他现金及现金等价物 | D77: 2024A | E77: 44333 | F77: 百万美元 | G77: AR25_BS | H77: 材料/Berkshire_2025年报__brka-20251231.htm｜Consolidated Balance Sheets（K-66）
A78: 77 | B78: 资产负债 | C78: 铁路、公用事业及能源现金 | D78: 2024A | E78: 3396 | F78: 百万美元 | G78: AR25_BS | H78: 材料/Berkshire_2025年报__brka-20251231.htm｜Consolidated Balance Sheets（K-66）
A79: 78 | B79: 资产负债 | C79: 短期美国国债 | D79: 2024A | E79: 286472 | F79: 百万美元 | G79: AR25_BS | H79: 材料/Berkshire_2025年报__brka-20251231.htm｜Consolidated Balance Sheets（K-66） | I79: 合并资产负债表口径；现金及短期国债合计由公式计算
A80: 79 | B80: 资产负债 | C80: 保险及其他现金及现金等价物 | D80: 2025A | E80: 47719 | F80: 百万美元 | G80: AR25_BS | H80: 材料/Berkshire_2025年报__brka-20251231.htm｜Consolidated Balance Sheets（K-66）
A81: 80 | B81: 资产负债 | C81: 铁路、公用事业及能源现金 | D81: 2025A | E81: 4158 | F81: 百万美元 | G81: AR25_BS | H81: 材料/Berkshire_2025年报__brka-20251231.htm｜Consolidated Balance Sheets（K-66）
A82: 81 | B82: 资产负债 | C82: 短期美国国债 | D82: 2025A | E82: 321434 | F82: 百万美元 | G82: AR25_BS | H82: 材料/Berkshire_2025年报__brka-20251231.htm｜Consolidated Balance Sheets（K-66） | I82: 合并资产负债表口径；现金及短期国债合计由公式计算
A83: 82 | B83: 资产负债 | C83: 保险及其他现金及现金等价物 | D83: 2026H1 | E83: 35096 | F83: 百万美元 | G83: Q226_BS | H83: 材料/Berkshire_2026Q2季报__brka-20260630.htm｜Consolidated Balance Sheets（第2至3页）
A84: 83 | B84: 资产负债 | C84: 铁路、公用事业及能源现金 | D84: 2026H1 | E84: 5513 | F84: 百万美元 | G84: Q226_BS | H84: 材料/Berkshire_2026Q2季报__brka-20260630.htm｜Consolidated Balance Sheets（第2至3页）
A85: 84 | B85: 资产负债 | C85: 短期美国国债 | D85: 2026H1 | E85: 324905 | F85: 百万美元 | G85: Q226_BS | H85: 材料/Berkshire_2026Q2季报__brka-20260630.htm｜Consolidated Balance Sheets（第2至3页） | I85: 合并资产负债表口径；现金及短期国债合计由公式计算
A86: 85 | B86: 权益组成 | C86: 权益组成—股本及资本公积 | D86: 2021A | E86: 35600 | F86: 百万美元 | G86: AR23_CF | H86: 交付/来源/Berkshire_2023年报_官方.pdf｜Consolidated Statements of Cash Flows及Statements of Changes in Shareholders’ Equity | I86: 2023年报追溯调整后2021年末股东权益变动表
A87: 86 | B87: 权益组成 | C87: 权益组成—其他综合收益 | D87: 2021A | E87: -8123 | F87: 百万美元 | G87: AR23_CF | H87: 交付/来源/Berkshire_2023年报_官方.pdf｜Consolidated Statements of Cash Flows及Statements of Changes in Shareholders’ Equity | I87: 2023年报追溯调整后2021年末股东权益变动表
A88: 87 | B88: 权益组成 | C88: 权益组成—留存收益 | D88: 2021A | E88: 533886 | F88: 百万美元 | G88: AR23_CF | H88: 交付/来源/Berkshire_2023年报_官方.pdf｜Consolidated Statements of Cash Flows及Statements of Changes in Shareholders’ Equity | I88: 2023年报追溯调整后2021年末股东权益变动表
A89: 88 | B89: 权益组成 | C89: 权益组成—库存股 | D89: 2021A | E89: -59795 | F89: 百万美元 | G89: AR23_CF | H89: 交付/来源/Berkshire_2023年报_官方.pdf｜Consolidated Statements of Cash Flows及Statements of Changes in Shareholders’ Equity | I89: 2023年报追溯调整后2021年末股东权益变动表
A90: 89 | B90: 资产负债 | C90: 归母股东权益 | D90: 2021A | E90: =SUMIFS($E$2:$E$197,$B$2:$B$197,"权益组成",$D$2:$D$197,D90) -> 501568 | F90: 百万美元 | G90: AR23_CF | H90: 交付/来源/Berkshire_2023年报_官方.pdf｜Consolidated Statements of Cash Flows及Statements of Changes in Shareholders’ Equity | I90: 公式：2023年报追溯调整后四项归母权益组成之和；非2022年报旧口径
A91: 90 | B91: 资产负债 | C91: 归母股东权益 | D91: 2022A | E91: 473424 | F91: 百万美元 | G91: AR23_BS | H91: 交付/来源/Berkshire_2023年报_官方.pdf｜Consolidated Balance Sheets（K-66） | I91: 归属伯克希尔股东
A92: 91 | B92: 资产负债 | C92: 归母股东权益 | D92: 2023A | E92: 561273 | F92: 百万美元 | G92: AR23_BS | H92: 交付/来源/Berkshire_2023年报_官方.pdf｜Consolidated Balance Sheets（K-66） | I92: 归属伯克希尔股东
A93: 92 | B93: 资产负债 | C93: 归母股东权益 | D93: 2024A | E93: 649368 | F93: 百万美元 | G93: AR25_BS | H93: 材料/Berkshire_2025年报__brka-20251231.htm｜Consolidated Balance Sheets（K-66） | I93: 归属伯克希尔股东
A94: 93 | B94: 资产负债 | C94: 归母股东权益 | D94: 2025A | E94: 717419 | F94: 百万美元 | G94: AR25_BS | H94: 材料/Berkshire_2025年报__brka-20251231.htm｜Consolidated Balance Sheets（K-66） | I94: 归属伯克希尔股东
A95: 94 | B95: 资产负债 | C95: 归母股东权益 | D95: 2026H1 | E95: 747910 | F95: 百万美元 | G95: Q226_BS | H95: 材料/Berkshire_2026Q2季报__brka-20260630.htm｜Consolidated Balance Sheets（第2至3页） | I95: 归属伯克希尔股东
A96: 95 | B96: 资产负债 | C96: 期末A类等价股数 | D96: 2021A | E96: 1477429 | F96: 股 | G96: AR22_EQ | H96: 交付/来源/Berkshire_2022年报_官方.pdf｜Notes—Common stock | I96: 期末股数，不是加权平均股数；B股按1/1500折算
A97: 96 | B97: 资产负债 | C97: 期末A类等价股数 | D97: 2022A | E97: 1459733 | F97: 股 | G97: AR23_EQ | H97: 交付/来源/Berkshire_2023年报_官方.pdf｜Notes—Common stock | I97: 期末股数，不是加权平均股数；B股按1/1500折算
A98: 97 | B98: 资产负债 | C98: 期末A类等价股数 | D98: 2023A | E98: 1441483 | F98: 股 | G98: AR23_EQ | H98: 交付/来源/Berkshire_2023年报_官方.pdf｜Notes—Common stock | I98: 期末股数，不是加权平均股数；B股按1/1500折算
A99: 98 | B99: 资产负债 | C99: 期末A类等价股数 | D99: 2024A | E99: 1438223 | F99: 股 | G99: AR25_EQ | H99: 材料/Berkshire_2025年报__brka-20251231.htm｜Notes—Common stock（K-101至K-102） | I99: 期末股数，不是加权平均股数；B股按1/1500折算
A100: 99 | B100: 资产负债 | C100: 期末A类等价股数 | D100: 2025A | E100: 1438223 | F100: 股 | G100: AR25_EQ | H100: 材料/Berkshire_2025年报__brka-20251231.htm｜Notes—Common stock（K-101至K-102） | I100: 期末股数，不是加权平均股数；B股按1/1500折算
A101: 100 | B101: 资产负债 | C101: 期末A类等价股数 | D101: 2026H1 | E101: 1431693 | F101: 股 | G101: Q226_EQ | H101: 材料/Berkshire_2026Q2季报__brka-20260630.htm｜Note 18—Common stock（第21页） | I101: 期末股数，不是加权平均股数；B股按1/1500折算
A102: 101 | B102: 资本配置 | C102: 回购金额（现金流量表） | D102: 2021A | E102: 27061 | F102: 百万美元 | G102: AR23_CF | H102: 交付/来源/Berkshire_2023年报_官方.pdf｜Consolidated Statements of Cash Flows及Statements of Changes in Shareholders’ Equity | I102: 正数表示现金流出绝对值
... A147: 146 | B147: 资本配置 | C147: 出售股票（现金流） | D147: 2021A | E147: 15849 | F147: 百万美元 | G147: AR23_CF | H147: 交付/来源/Berkshire_2023年报_官方.pdf｜Consolidated Statements of Cash Flows及Statements of Changes in Shareholders’ Equity | I147: 正数表示现金流入
A148: 147 | B148: 现金流 | C148: 经营活动现金流净额 | D148: 2021A | E148: 39427 | F148: 百万美元 | G148: AR23_CF | H148: 交付/来源/Berkshire_2023年报_官方.pdf｜Consolidated Statements of Cash Flows及Statements of Changes in Shareholders’ Equity
A149: 148 | B149: 资本配置 | C149: 购买股票（现金流） | D149: 2022A | E149: 67930 | F149: 百万美元 | G149: AR23_CF | H149: 交付/来源/Berkshire_2023年报_官方.pdf｜Consolidated Statements of Cash Flows及Statements of Changes in Shareholders’ Equity | I149: 正数表示现金流出绝对值
A150: 149 | B150: 资本配置 | C150: 出售股票（现金流） | D150: 2022A | E150: 33664 | F150: 百万美元 | G150: AR23_CF | H150: 交付/来源/Berkshire_2023年报_官方.pdf｜Consolidated Statements of Cash Flows及Statements of Changes in Shareholders’ Equity | I150: 正数表示现金流入
A151: 150 | B151: 现金流 | C151: 经营活动现金流净额 | D151: 2022A | E151: 37350 | F151: 百万美元 | G151: AR23_CF | H151: 交付/来源/Berkshire_2023年报_官方.pdf｜Consolidated Statements of Cash Flows及Statements of Changes in Shareholders’ Equity
A152: 151 | B152: 资本配置 | C152: 购买股票（现金流） | D152: 2023A | E152: 16462 | F152: 百万美元 | G152: AR25_CF | H152: 材料/Berkshire_2025年报__brka-20251231.htm｜Consolidated Statements of Cash Flows（K-70） | I152: 正数表示现金流出绝对值
A153: 152 | B153: 资本配置 | C153: 出售股票（现金流） | D153: 2023A | E153: 40631 | F153: 百万美元 | G153: AR25_CF | H153: 材料/Berkshire_2025年报__brka-20251231.htm｜Consolidated Statements of Cash Flows（K-70） | I153: 正数表示现金流入
A154: 153 | B154: 现金流 | C154: 经营活动现金流净额 | D154: 2023A | E154: 49196 | F154: 百万美元 | G154: AR25_CF | H154: 材料/Berkshire_2025年报__brka-20251231.htm｜Consolidated Statements of Cash Flows（K-70）
A155: 154 | B155: 资本配置 | C155: 购买股票（现金流） | D155: 2024A | E155: 9237 | F155: 百万美元 | G155: AR25_CF | H155: 材料/Berkshire_2025年报__brka-20251231.htm｜Consolidated Statements of Cash Flows（K-70） | I155: 正数表示现金流出绝对值
A156: 155 | B156: 资本配置 | C156: 出售股票（现金流） | D156: 2024A | E156: 143359 | F156: 百万美元 | G156: AR25_CF | H156: 材料/Berkshire_2025年报__brka-20251231.htm｜Consolidated Statements of Cash Flows（K-70） | I156: 正数表示现金流入
A157: 156 | B157: 现金流 | C157: 经营活动现金流净额 | D157: 2024A | E157: 30592 | F157: 百万美元 | G157: AR25_CF | H157: 材料/Berkshire_2025年报__brka-20251231.htm｜Consolidated Statements of Cash Flows（K-70）
A158: 157 | B158: 资本配置 | C158: 购买股票（现金流） | D158: 2025A | E158: 16923 | F158: 百万美元 | G158: AR25_CF | H158: 材料/Berkshire_2025年报__brka-20251231.htm｜Consolidated Statements of Cash Flows（K-70） | I158: 正数表示现金流出绝对值
A159: 158 | B159: 资本配置 | C159: 出售股票（现金流） | D159: 2025A | E159: 30686 | F159: 百万美元 | G159: AR25_CF | H159: 材料/Berkshire_2025年报__brka-20251231.htm｜Consolidated Statements of Cash Flows（K-70） | I159: 正数表示现金流入
A160: 159 | B160: 现金流 | C160: 经营活动现金流净额 | D160: 2025A | E160: 45969 | F160: 百万美元 | G160: AR25_CF | H160: 材料/Berkshire_2025年报__brka-20251231.htm｜Consolidated Statements of Cash Flows（K-70）
A161: 160 | B161: 资本配置 | C161: 购买股票（现金流） | D161: 2025H1 | E161: 7092 | F161: 百万美元 | G161: Q226_CF | H161: 材料/Berkshire_2026Q2季报__brka-20260630.htm｜Consolidated Statements of Cash Flows（第7页） | I161: 正数表示现金流出绝对值
A162: 161 | B162: 资本配置 | C162: 出售股票（现金流） | D162: 2025H1 | E162: 11592 | F162: 百万美元 | G162: Q226_CF | H162: 材料/Berkshire_2026Q2季报__brka-20260630.htm｜Consolidated Statements of Cash Flows（第7页） | I162: 正数表示现金流入
A163: 162 | B163: 现金流 | C163: 经营活动现金流净额 | D163: 2025H1 | E163: 20988 | F163: 百万美元 | G163: Q226_CF | H163: 材料/Berkshire_2026Q2季报__brka-20260630.htm｜Consolidated Statements of Cash Flows（第7页）
A164: 163 | B164: 资本配置 | C164: 购买股票（现金流） | D164: 2026H1 | E164: 39405 | F164: 百万美元 | G164: Q226_CF | H164: 材料/Berkshire_2026Q2季报__brka-20260630.htm｜Consolidated Statements of Cash Flows（第7页） | I164: 正数表示现金流出绝对值
A165: 164 | B165: 资本配置 | C165: 出售股票（现金流） | D165: 2026H1 | E165: 27780 | F165: 百万美元 | G165: Q226_CF | H165: 材料/Berkshire_2026Q2季报__brka-20260630.htm｜Consolidated Statements of Cash Flows（第7页） | I165: 正数表示现金流入
A166: 165 | B166: 现金流 | C166: 经营活动现金流净额 | D166: 2026H1 | E166: 21653 | F166: 百万美元 | G166: Q226_CF | H166: 材料/Berkshire_2026Q2季报__brka-20260630.htm｜Consolidated Statements of Cash Flows（第7页）
A167: 166 | B167: 经营细节 | C167: GEICO已赚保费 | D167: 2025H1 | E167: 21816 | F167: 百万美元 | G167: Q226_DETAIL | H167: 材料/Berkshire_2026Q2季报__brka-20260630.htm｜Item 2—GEICO、BNSF、BHE、Manufacturing分段（第34至47页）
A168: 167 | B168: 经营细节 | C168: GEICO已赚保费 | D168: 2026H1 | E168: 22477 | F168: 百万美元 | G168: Q226_DETAIL | H168: 材料/Berkshire_2026Q2季报__brka-20260630.htm｜Item 2—GEICO、BNSF、BHE、Manufacturing分段（第34至47页）
A169: 168 | B169: 经营细节 | C169: GEICO税前承保利润 | D169: 2025H1 | E169: 3994 | F169: 百万美元 | G169: Q226_DETAIL | H169: 材料/Berkshire_2026Q2季报__brka-20260630.htm｜Item 2—GEICO、BNSF、BHE、Manufacturing分段（第34至47页）
A170: 169 | B170: 经营细节 | C170: GEICO税前承保利润 | D170: 2026H1 | E170: 2410 | F170: 百万美元 | G170: Q226_DETAIL | H170: 材料/Berkshire_2026Q2季报__brka-20260630.htm｜Item 2—GEICO、BNSF、BHE、Manufacturing分段（第34至47页）
A171: 170 | B171: 经营细节 | C171: GEICO赔付率 | D171: 2025H1 | E171: 0.704 | F171: 百分比 | G171: Q226_DETAIL | H171: 材料/Berkshire_2026Q2季报__brka-20260630.htm｜Item 2—GEICO、BNSF、BHE、Manufacturing分段（第34至47页）
A172: 171 | B172: 经营细节 | C172: GEICO赔付率 | D172: 2026H1 | E172: 0.753 | F172: 百分比 | G172: Q226_DETAIL | H172: 材料/Berkshire_2026Q2季报__brka-20260630.htm｜Item 2—GEICO、BNSF、BHE、Manufacturing分段（第34至47页）
A173: 172 | B173: 经营细节 | C173: GEICO费用率 | D173: 2025H1 | E173: 0.113 | F173: 百分比 | G173: Q226_DETAIL | H173: 材料/Berkshire_2026Q2季报__brka-20260630.htm｜Item 2—GEICO、BNSF、BHE、Manufacturing分段（第34至47页）
A174: 173 | B174: 经营细节 | C174: GEICO费用率 | D174: 2026H1 | E174: 0.14 | F174: 百分比 | G174: Q226_DETAIL | H174: 材料/Berkshire_2026Q2季报__brka-20260630.htm｜Item 2—GEICO、BNSF、BHE、Manufacturing分段（第34至47页）
A175: 174 | B175: 经营细节 | C175: BH Primary税前承保利润 | D175: 2025H1 | E175: -81 | F175: 百万美元 | G175: Q226_DETAIL | H175: 材料/Berkshire_2026Q2季报__brka-20260630.htm｜Item 2—GEICO、BNSF、BHE、Manufacturing分段（第34至47页）
A176: 175 | B176: 经营细节 | C176: BH Primary税前承保利润 | D176: 2026H1 | E176: 749 | F176: 百万美元 | G176: Q226_DETAIL | H176: 材料/Berkshire_2026Q2季报__brka-20260630.htm｜Item 2—GEICO、BNSF、BHE、Manufacturing分段（第34至47页）
A177: 176 | B177: 经营细节 | C177: BHRG税前承保利润 | D177: 2025H1 | E177: 343 | F177: 百万美元 | G177: Q226_DETAIL | H177: 材料/Berkshire_2026Q2季报__brka-20260630.htm｜Item 2—GEICO、BNSF、BHE、Manufacturing分段（第34至47页）
... A194: 193 | B194: 经营细节 | C194: 工业产品税前利润 | D194: 2026H1 | E194: 4508 | F194: 百万美元 | G194: Q226_DETAIL | H194: 材料/Berkshire_2026Q2季报__brka-20260630.htm｜Item 2—GEICO、BNSF、BHE、Manufacturing分段（第34至47页）
A195: 194 | B195: 经营细节 | C195: OxyChem营业收入 | D195: 2026H1 | E195: 2600 | F195: 百万美元 | G195: Q226_DETAIL | H195: 材料/Berkshire_2026Q2季报__brka-20260630.htm｜Item 2—GEICO、BNSF、BHE、Manufacturing分段（第34至47页） | I195: 2026年1月2日起并表
A196: 195 | B196: 经营细节 | C196: OxyChem税前利润 | D196: 2026H1 | E196: 121 | F196: 百万美元 | G196: Q226_DETAIL | H196: 材料/Berkshire_2026Q2季报__brka-20260630.htm｜Item 2—GEICO、BNSF、BHE、Manufacturing分段（第34至47页） | I196: 含收购会计折旧摊销及过渡成本影响
A197: 196 | B197: 资本配置 | C197: OxyChem收购对价（约数） | D197: 2026H1 | E197: 9500 | F197: 百万美元 | G197: AR25_ACQ | H197: 材料/Berkshire_2025年报__brka-20251231.htm｜Note 2—Business acquisitions（K-77至K-78） | I197: 2026年1月2日支付，可按协议调整；Occidental保留历史环境负债

Sheet 分部利润
A1: 各业务板块利润｜税后、归属伯克希尔股东
A2: 单位：百万美元。核心五项与公司经营利润（含Other）分列；投资损益及减值不混入核心经营表现。
A4: 指标 | B4: 2021年 | C4: 2022年 | D4: 2023年 | E4: 2024年 | F4: 2025年 | G4: 2025年上半年 | H4: 2026年上半年
A5: 保险承保利润 | B5: =IF(COUNTIFS(数据!$C$2:$C$197,"保险承保利润",数据!$D$2:$D$197,"2021A")=0,0,SUMIFS(数据!$E$2:$E$197,数据!$C$2:$C$197,"保险承保利润",数据!$D$2:$D$197,"2021A")) -> 870 | C5: =IF(COUNTIFS(数据!$C$2:$C$197,"保险承保利润",数据!$D$2:$D$197,"2022A")=0,0,SUMIFS(数据!$E$2:$E$197,数据!$C$2:$C$197,"保险承保利润",数据!$D$2:$D$197,"2022A")) -> -30 | D5: =IF(COUNTIFS(数据!$C$2:$C$197,"保险承保利润",数据!$D$2:$D$197,"2023A")=0,0,SUMIFS(数据!$E$2:$E$197,数据!$C$2:$C$197,"保险承保利润",数据!$D$2:$D$197,"2023A")) -> 5428 | E5: =IF(COUNTIFS(数据!$C$2:$C$197,"保险承保利润",数据!$D$2:$D$197,"2024A")=0,0,SUMIFS(数据!$E$2:$E$197,数据!$C$2:$C$197,"保险承保利润",数据!$D$2:$D$197,"2024A")) -> 9020 | F5: =IF(COUNTIFS(数据!$C$2:$C$197,"保险承保利润",数据!$D$2:$D$197,"2025A")=0,0,SUMIFS(数据!$E$2:$E$197,数据!$C$2:$C$197,"保险承保利润",数据!$D$2:$D$197,"2025A")) -> 7258 | G5: =IF(COUNTIFS(数据!$C$2:$C$197,"保险承保利润",数据!$D$2:$D$197,"2025H1")=0,0,SUMIFS(数据!$E$2:$E$197,数据!$C$2:$C$197,"保险承保利润",数据!$D$2:$D$197,"2025H1")) -> 3328 | H5: =IF(COUNTIFS(数据!$C$2:$C$197,"保险承保利润",数据!$D$2:$D$197,"2026H1")=0,0,SUMIFS(数据!$E$2:$E$197,数据!$C$2:$C$197,"保险承保利润",数据!$D$2:$D$197,"2026H1")) -> 3448
A6: 保险投资收益 | B6: =IF(COUNTIFS(数据!$C$2:$C$197,"保险投资收益",数据!$D$2:$D$197,"2021A")=0,0,SUMIFS(数据!$E$2:$E$197,数据!$C$2:$C$197,"保险投资收益",数据!$D$2:$D$197,"2021A")) -> 4807 | C6: =IF(COUNTIFS(数据!$C$2:$C$197,"保险投资收益",数据!$D$2:$D$197,"2022A")=0,0,SUMIFS(数据!$E$2:$E$197,数据!$C$2:$C$197,"保险投资收益",数据!$D$2:$D$197,"2022A")) -> 6484 | D6: =IF(COUNTIFS(数据!$C$2:$C$197,"保险投资收益",数据!$D$2:$D$197,"2023A")=0,0,SUMIFS(数据!$E$2:$E$197,数据!$C$2:$C$197,"保险投资收益",数据!$D$2:$D$197,"2023A")) -> 9567 | E6: =IF(COUNTIFS(数据!$C$2:$C$197,"保险投资收益",数据!$D$2:$D$197,"2024A")=0,0,SUMIFS(数据!$E$2:$E$197,数据!$C$2:$C$197,"保险投资收益",数据!$D$2:$D$197,"2024A")) -> 13670 | F6: =IF(COUNTIFS(数据!$C$2:$C$197,"保险投资收益",数据!$D$2:$D$197,"2025A")=0,0,SUMIFS(数据!$E$2:$E$197,数据!$C$2:$C$197,"保险投资收益",数据!$D$2:$D$197,"2025A")) -> 12513 | G6: =IF(COUNTIFS(数据!$C$2:$C$197,"保险投资收益",数据!$D$2:$D$197,"2025H1")=0,0,SUMIFS(数据!$E$2:$E$197,数据!$C$2:$C$197,"保险投资收益",数据!$D$2:$D$197,"2025H1")) -> 6260 | H6: =IF(COUNTIFS(数据!$C$2:$C$197,"保险投资收益",数据!$D$2:$D$197,"2026H1")=0,0,SUMIFS(数据!$E$2:$E$197,数据!$C$2:$C$197,"保险投资收益",数据!$D$2:$D$197,"2026H1")) -> 5738
A7: 铁路（BNSF）利润 | B7: =IF(COUNTIFS(数据!$C$2:$C$197,"铁路（BNSF）利润",数据!$D$2:$D$197,"2021A")=0,0,SUMIFS(数据!$E$2:$E$197,数据!$C$2:$C$197,"铁路（BNSF）利润",数据!$D$2:$D$197,"2021A")) -> 5990 | C7: =IF(COUNTIFS(数据!$C$2:$C$197,"铁路（BNSF）利润",数据!$D$2:$D$197,"2022A")=0,0,SUMIFS(数据!$E$2:$E$197,数据!$C$2:$C$197,"铁路（BNSF）利润",数据!$D$2:$D$197,"2022A")) -> 5946 | D7: =IF(COUNTIFS(数据!$C$2:$C$197,"铁路（BNSF）利润",数据!$D$2:$D$197,"2023A")=0,0,SUMIFS(数据!$E$2:$E$197,数据!$C$2:$C$197,"铁路（BNSF）利润",数据!$D$2:$D$197,"2023A")) -> 5087 | E7: =IF(COUNTIFS(数据!$C$2:$C$197,"铁路（BNSF）利润",数据!$D$2:$D$197,"2024A")=0,0,SUMIFS(数据!$E$2:$E$197,数据!$C$2:$C$197,"铁路（BNSF）利润",数据!$D$2:$D$197,"2024A")) -> 5031 | F7: =IF(COUNTIFS(数据!$C$2:$C$197,"铁路（BNSF）利润",数据!$D$2:$D$197,"2025A")=0,0,SUMIFS(数据!$E$2:$E$197,数据!$C$2:$C$197,"铁路（BNSF）利润",数据!$D$2:$D$197,"2025A")) -> 5476 | G7: =IF(COUNTIFS(数据!$C$2:$C$197,"铁路（BNSF）利润",数据!$D$2:$D$197,"2025H1")=0,0,SUMIFS(数据!$E$2:$E$197,数据!$C$2:$C$197,"铁路（BNSF）利润",数据!$D$2:$D$197,"2025H1")) -> 2680 | H7: =IF(COUNTIFS(数据!$C$2:$C$197,"铁路（BNSF）利润",数据!$D$2:$D$197,"2026H1")=0,0,SUMIFS(数据!$E$2:$E$197,数据!$C$2:$C$197,"铁路（BNSF）利润",数据!$D$2:$D$197,"2026H1")) -> 2935
A8: 能源（BHE）利润 | B8: =IF(COUNTIFS(数据!$C$2:$C$197,"能源（BHE）利润",数据!$D$2:$D$197,"2021A")=0,0,SUMIFS(数据!$E$2:$E$197,数据!$C$2:$C$197,"能源（BHE）利润",数据!$D$2:$D$197,"2021A")) -> 3572 | C8: =IF(COUNTIFS(数据!$C$2:$C$197,"能源（BHE）利润",数据!$D$2:$D$197,"2022A")=0,0,SUMIFS(数据!$E$2:$E$197,数据!$C$2:$C$197,"能源（BHE）利润",数据!$D$2:$D$197,"2022A")) -> 3904 | D8: =IF(COUNTIFS(数据!$C$2:$C$197,"能源（BHE）利润",数据!$D$2:$D$197,"2023A")=0,0,SUMIFS(数据!$E$2:$E$197,数据!$C$2:$C$197,"能源（BHE）利润",数据!$D$2:$D$197,"2023A")) -> 2331 | E8: =IF(COUNTIFS(数据!$C$2:$C$197,"能源（BHE）利润",数据!$D$2:$D$197,"2024A")=0,0,SUMIFS(数据!$E$2:$E$197,数据!$C$2:$C$197,"能源（BHE）利润",数据!$D$2:$D$197,"2024A")) -> 3730 | F8: =IF(COUNTIFS(数据!$C$2:$C$197,"能源（BHE）利润",数据!$D$2:$D$197,"2025A")=0,0,SUMIFS(数据!$E$2:$E$197,数据!$C$2:$C$197,"能源（BHE）利润",数据!$D$2:$D$197,"2025A")) -> 3979 | G8: =IF(COUNTIFS(数据!$C$2:$C$197,"能源（BHE）利润",数据!$D$2:$D$197,"2025H1")=0,0,SUMIFS(数据!$E$2:$E$197,数据!$C$2:$C$197,"能源（BHE）利润",数据!$D$2:$D$197,"2025H1")) -> 1799 | H8: =IF(COUNTIFS(数据!$C$2:$C$197,"能源（BHE）利润",数据!$D$2:$D$197,"2026H1")=0,0,SUMIFS(数据!$E$2:$E$197,数据!$C$2:$C$197,"能源（BHE）利润",数据!$D$2:$D$197,"2026H1")) -> 2005
A9: 制造、服务及零售利润 | B9: =IF(COUNTIFS(数据!$C$2:$C$197,"制造、服务及零售利润",数据!$D$2:$D$197,"2021A")=0,0,SUMIFS(数据!$E$2:$E$197,数据!$C$2:$C$197,"制造、服务及零售利润",数据!$D$2:$D$197,"2021A")) -> 11120 | C9: =IF(COUNTIFS(数据!$C$2:$C$197,"制造、服务及零售利润",数据!$D$2:$D$197,"2022A")=0,0,SUMIFS(数据!$E$2:$E$197,数据!$C$2:$C$197,"制造、服务及零售利润",数据!$D$2:$D$197,"2022A")) -> 12512 | D9: =IF(COUNTIFS(数据!$C$2:$C$197,"制造、服务及零售利润",数据!$D$2:$D$197,"2023A")=0,0,SUMIFS(数据!$E$2:$E$197,数据!$C$2:$C$197,"制造、服务及零售利润",数据!$D$2:$D$197,"2023A")) -> 13362 | E9: =IF(COUNTIFS(数据!$C$2:$C$197,"制造、服务及零售利润",数据!$D$2:$D$197,"2024A")=0,0,SUMIFS(数据!$E$2:$E$197,数据!$C$2:$C$197,"制造、服务及零售利润",数据!$D$2:$D$197,"2024A")) -> 13072 | F9: =IF(COUNTIFS(数据!$C$2:$C$197,"制造、服务及零售利润",数据!$D$2:$D$197,"2025A")=0,0,SUMIFS(数据!$E$2:$E$197,数据!$C$2:$C$197,"制造、服务及零售利润",数据!$D$2:$D$197,"2025A")) -> 13647 | G9: =IF(COUNTIFS(数据!$C$2:$C$197,"制造、服务及零售利润",数据!$D$2:$D$197,"2025H1")=0,0,SUMIFS(数据!$E$2:$E$197,数据!$C$2:$C$197,"制造、服务及零售利润",数据!$D$2:$D$197,"2025H1")) -> 6661 | H9: =IF(COUNTIFS(数据!$C$2:$C$197,"制造、服务及零售利润",数据!$D$2:$D$197,"2026H1")=0,0,SUMIFS(数据!$E$2:$E$197,数据!$C$2:$C$197,"制造、服务及零售利润",数据!$D$2:$D$197,"2026H1")) -> 7669
A10: 核心五项经营利润小计 | B10: =SUM(B5:B9) -> 26359 | C10: =SUM(C5:C9) -> 28816 | D10: =SUM(D5:D9) -> 35775 | E10: =SUM(E5:E9) -> 44523 | F10: =SUM(F5:F9) -> 42873 | G10: =SUM(G5:G9) -> 20728 | H10: =SUM(H5:H9) -> 21795
A11: 其他（含旧口径非控制企业） | B11: =SUMIFS(数据!$E$2:$E$197,数据!$C$2:$C$197,"其他利润",数据!$D$2:$D$197,"2021A")+SUMIFS(数据!$E$2:$E$197,数据!$C$2:$C$197,"非控制企业利润（旧口径）",数据!$D$2:$D$197,"2021A") -> 1238 | C11: =SUMIFS(数据!$E$2:$E$197,数据!$C$2:$C$197,"其他利润",数据!$D$2:$D$197,"2022A")+SUMIFS(数据!$E$2:$E$197,数据!$C$2:$C$197,"非控制企业利润（旧口径）",数据!$D$2:$D$197,"2022A") -> 2037 | D11: =SUMIFS(数据!$E$2:$E$197,数据!$C$2:$C$197,"其他利润",数据!$D$2:$D$197,"2023A")+SUMIFS(数据!$E$2:$E$197,数据!$C$2:$C$197,"非控制企业利润（旧口径）",数据!$D$2:$D$197,"2023A") -> 1575 | E11: =SUMIFS(数据!$E$2:$E$197,数据!$C$2:$C$197,"其他利润",数据!$D$2:$D$197,"2024A")+SUMIFS(数据!$E$2:$E$197,数据!$C$2:$C$197,"非控制企业利润（旧口径）",数据!$D$2:$D$197,"2024A") -> 2914 | F11: =SUMIFS(数据!$E$2:$E$197,数据!$C$2:$C$197,"其他利润",数据!$D$2:$D$197,"2025A")+SUMIFS(数据!$E$2:$E$197,数据!$C$2:$C$197,"非控制企业利润（旧口径）",数据!$D$2:$D$197,"2025A") -> 1613 | G11: =SUMIFS(数据!$E$2:$E$197,数据!$C$2:$C$197,"其他利润",数据!$D$2:$D$197,"2025H1")+SUMIFS(数据!$E$2:$E$197,数据!$C$2:$C$197,"非控制企业利润（旧口径）",数据!$D$2:$D$197,"2025H1") -> 73 | H11: =SUMIFS(数据!$E$2:$E$197,数据!$C$2:$C$197,"其他利润",数据!$D$2:$D$197,"2026H1")+SUMIFS(数据!$E$2:$E$197,数据!$C$2:$C$197,"非控制企业利润（旧口径）",数据!$D$2:$D$197,"2026H1") -> 2534
A12: 公司经营利润（核心五项＋其他） | B12: =B10+B11 -> 27597 | C12: =C10+C11 -> 30853 | D12: =D10+D11 -> 37350 | E12: =E10+E11 -> 47437 | F12: =F10+F11 -> 44486 | G12: =G10+G11 -> 20801 | H12: =H10+H11 -> 24329
A13: 投资损益 | B13: =IF(COUNTIFS(数据!$C$2:$C$197,"投资损益",数据!$D$2:$D$197,"2021A")=0,0,SUMIFS(数据!$E$2:$E$197,数据!$C$2:$C$197,"投资损益",数据!$D$2:$D$197,"2021A")) -> 62340 | C13: =IF(COUNTIFS(数据!$C$2:$C$197,"投资损益",数据!$D$2:$D$197,"2022A")=0,0,SUMIFS(数据!$E$2:$E$197,数据!$C$2:$C$197,"投资损益",数据!$D$2:$D$197,"2022A")) -> -53612 | D13: =IF(COUNTIFS(数据!$C$2:$C$197,"投资损益",数据!$D$2:$D$197,"2023A")=0,0,SUMIFS(数据!$E$2:$E$197,数据!$C$2:$C$197,"投资损益",数据!$D$2:$D$197,"2023A")) -> 58873 | E13: =IF(COUNTIFS(数据!$C$2:$C$197,"投资损益",数据!$D$2:$D$197,"2024A")=0,0,SUMIFS(数据!$E$2:$E$197,数据!$C$2:$C$197,"投资损益",数据!$D$2:$D$197,"2024A")) -> 41558 | F13: =IF(COUNTIFS(数据!$C$2:$C$197,"投资损益",数据!$D$2:$D$197,"2025A")=0,0,SUMIFS(数据!$E$2:$E$197,数据!$C$2:$C$197,"投资损益",数据!$D$2:$D$197,"2025A")) -> 30737 | G13: =IF(COUNTIFS(数据!$C$2:$C$197,"投资损益",数据!$D$2:$D$197,"2025H1")=0,0,SUMIFS(数据!$E$2:$E$197,数据!$C$2:$C$197,"投资损益",数据!$D$2:$D$197,"2025H1")) -> -68 | H13: =IF(COUNTIFS(数据!$C$2:$C$197,"投资损益",数据!$D$2:$D$197,"2026H1")=0,0,SUMIFS(数据!$E$2:$E$197,数据!$C$2:$C$197,"投资损益",数据!$D$2:$D$197,"2026H1")) -> 11444
A14: 权益法投资非暂时性减值 | B14: =IF(COUNTIFS(数据!$C$2:$C$197,"权益法投资减值",数据!$D$2:$D$197,"2021A")=0,0,SUMIFS(数据!$E$2:$E$197,数据!$C$2:$C$197,"权益法投资减值",数据!$D$2:$D$197,"2021A")) -> 0 | C14: =IF(COUNTIFS(数据!$C$2:$C$197,"权益法投资减值",数据!$D$2:$D$197,"2022A")=0,0,SUMIFS(数据!$E$2:$E$197,数据!$C$2:$C$197,"权益法投资减值",数据!$D$2:$D$197,"2022A")) -> 0 | D14: =IF(COUNTIFS(数据!$C$2:$C$197,"权益法投资减值",数据!$D$2:$D$197,"2023A")=0,0,SUMIFS(数据!$E$2:$E$197,数据!$C$2:$C$197,"权益法投资减值",数据!$D$2:$D$197,"2023A")) -> 0 | E14: =IF(COUNTIFS(数据!$C$2:$C$197,"权益法投资减值",数据!$D$2:$D$197,"2024A")=0,0,SUMIFS(数据!$E$2:$E$197,数据!$C$2:$C$197,"权益法投资减值",数据!$D$2:$D$197,"2024A")) -> 0 | F14: =IF(COUNTIFS(数据!$C$2:$C$197,"权益法投资减值",数据!$D$2:$D$197,"2025A")=0,0,SUMIFS(数据!$E$2:$E$197,数据!$C$2:$C$197,"权益法投资减值",数据!$D$2:$D$197,"2025A")) -> -8255 | G14: =IF(COUNTIFS(数据!$C$2:$C$197,"权益法投资减值",数据!$D$2:$D$197,"2025H1")=0,0,SUMIFS(数据!$E$2:$E$197,数据!$C$2:$C$197,"权益法投资减值",数据!$D$2:$D$197,"2025H1")) -> -3760 | H14: =IF(COUNTIFS(数据!$C$2:$C$197,"权益法投资减值",数据!$D$2:$D$197,"2026H1")=0,0,SUMIFS(数据!$E$2:$E$197,数据!$C$2:$C$197,"权益法投资减值",数据!$D$2:$D$197,"2026H1")) -> 0
A15: 归母净利润 | B15: =IF(COUNTIFS(数据!$C$2:$C$197,"归母净利润",数据!$D$2:$D$197,"2021A")=0,0,SUMIFS(数据!$E$2:$E$197,数据!$C$2:$C$197,"归母净利润",数据!$D$2:$D$197,"2021A")) -> 89937 | C15: =IF(COUNTIFS(数据!$C$2:$C$197,"归母净利润",数据!$D$2:$D$197,"2022A")=0,0,SUMIFS(数据!$E$2:$E$197,数据!$C$2:$C$197,"归母净利润",数据!$D$2:$D$197,"2022A")) -> -22759 | D15: =IF(COUNTIFS(数据!$C$2:$C$197,"归母净利润",数据!$D$2:$D$197,"2023A")=0,0,SUMIFS(数据!$E$2:$E$197,数据!$C$2:$C$197,"归母净利润",数据!$D$2:$D$197,"2023A")) -> 96223 | E15: =IF(COUNTIFS(数据!$C$2:$C$197,"归母净利润",数据!$D$2:$D$197,"2024A")=0,0,SUMIFS(数据!$E$2:$E$197,数据!$C$2:$C$197,"归母净利润",数据!$D$2:$D$197,"2024A")) -> 88995 | F15: =IF(COUNTIFS(数据!$C$2:$C$197,"归母净利润",数据!$D$2:$D$197,"2025A")=0,0,SUMIFS(数据!$E$2:$E$197,数据!$C$2:$C$197,"归母净利润",数据!$D$2:$D$197,"2025A")) -> 66968 | G15: =IF(COUNTIFS(数据!$C$2:$C$197,"归母净利润",数据!$D$2:$D$197,"2025H1")=0,0,SUMIFS(数据!$E$2:$E$197,数据!$C$2:$C$197,"归母净利润",数据!$D$2:$D$197,"2025H1")) -> 16973 | H15: =IF(COUNTIFS(数据!$C$2:$C$197,"归母净利润",数据!$D$2:$D$197,"2026H1")=0,0,SUMIFS(数据!$E$2:$E$197,数据!$C$2:$C$197,"归母净利润",数据!$D$2:$D$197,"2026H1")) -> 35773
A16: 对账差异（应为0） | B16: =B15-(B12+B13+B14) -> 0 | C16: =C15-(C12+C13+C14) -> 0 | D16: =D15-(D12+D13+D14) -> 0 | E16: =E15-(E12+E13+E14) -> 0 | F16: =F15-(F12+F13+F14) -> 0 | G16: =G15-(G12+G13+G14) -> 0 | H16: =H15-(H12+H13+H14) -> 0
A18: 经营活动现金流净额 | B18: =IF(COUNTIFS(数据!$C$2:$C$197,"经营活动现金流净额",数据!$D$2:$D$197,"2021A")=0,0,SUMIFS(数据!$E$2:$E$197,数据!$C$2:$C$197,"经营活动现金流净额",数据!$D$2:$D$197,"2021A")) -> 39427 | C18: =IF(COUNTIFS(数据!$C$2:$C$197,"经营活动现金流净额",数据!$D$2:$D$197,"2022A")=0,0,SUMIFS(数据!$E$2:$E$197,数据!$C$2:$C$197,"经营活动现金流净额",数据!$D$2:$D$197,"2022A")) -> 37350 | D18: =IF(COUNTIFS(数据!$C$2:$C$197,"经营活动现金流净额",数据!$D$2:$D$197,"2023A")=0,0,SUMIFS(数据!$E$2:$E$197,数据!$C$2:$C$197,"经营活动现金流净额",数据!$D$2:$D$197,"2023A")) -> 49196 | E18: =IF(COUNTIFS(数据!$C$2:$C$197,"经营活动现金流净额",数据!$D$2:$D$197,"2024A")=0,0,SUMIFS(数据!$E$2:$E$197,数据!$C$2:$C$197,"经营活动现金流净额",数据!$D$2:$D$197,"2024A")) -> 30592 | F18: =IF(COUNTIFS(数据!$C$2:$C$197,"经营活动现金流净额",数据!$D$2:$D$197,"2025A")=0,0,SUMIFS(数据!$E$2:$E$197,数据!$C$2:$C$197,"经营活动现金流净额",数据!$D$2:$D$197,"2025A")) -> 45969 | G18: =IF(COUNTIFS(数据!$C$2:$C$197,"经营活动现金流净额",数据!$D$2:$D$197,"2025H1")=0,0,SUMIFS(数据!$E$2:$E$197,数据!$C$2:$C$197,"经营活动现金流净额",数据!$D$2:$D$197,"2025H1")) -> 20988 | H18: =IF(COUNTIFS(数据!$C$2:$C$197,"经营活动现金流净额",数据!$D$2:$D$197,"2026H1")=0,0,SUMIFS(数据!$E$2:$E$197,数据!$C$2:$C$197,"经营活动现金流净额",数据!$D$2:$D$197,"2026H1")) -> 21653
A20: 口径说明：2021—2022年采用2023年报追溯调整数据；为衔接2025年报，旧表Non-controlled businesses并入Other。2023年制造、服务及零售采用2025年报列示，已包含PTC。半年数据不能与全年直接比较。

Sheet 资产负债
A1: 浮存金、流动性、每股账面价值与资本配置
A2: 单位：百万美元；股数为股；每股账面价值为美元。存量项目取期末，流量项目取全年或半年。
A4: 指标 | B4: 2021年 | C4: 2022年 | D4: 2023年 | E4: 2024年 | F4: 2025年 | G4: 2026年上半年
A5: 保险浮存金（约数） | B5: =IF(COUNTIFS(数据!$C$2:$C$197,"保险浮存金",数据!$D$2:$D$197,"2021A")=0,0,SUMIFS(数据!$E$2:$E$197,数据!$C$2:$C$197,"保险浮存金",数据!$D$2:$D$197,"2021A")) -> 147000 | C5: =IF(COUNTIFS(数据!$C$2:$C$197,"保险浮存金",数据!$D$2:$D$197,"2022A")=0,0,SUMIFS(数据!$E$2:$E$197,数据!$C$2:$C$197,"保险浮存金",数据!$D$2:$D$197,"2022A")) -> 164000 | D5: =IF(COUNTIFS(数据!$C$2:$C$197,"保险浮存金",数据!$D$2:$D$197,"2023A")=0,0,SUMIFS(数据!$E$2:$E$197,数据!$C$2:$C$197,"保险浮存金",数据!$D$2:$D$197,"2023A")) -> 169000 | E5: =IF(COUNTIFS(数据!$C$2:$C$197,"保险浮存金",数据!$D$2:$D$197,"2024A")=0,0,SUMIFS(数据!$E$2:$E$197,数据!$C$2:$C$197,"保险浮存金",数据!$D$2:$D$197,"2024A")) -> 171000 | F5: =IF(COUNTIFS(数据!$C$2:$C$197,"保险浮存金",数据!$D$2:$D$197,"2025A")=0,0,SUMIFS(数据!$E$2:$E$197,数据!$C$2:$C$197,"保险浮存金",数据!$D$2:$D$197,"2025A")) -> 176000 | G5: =IF(COUNTIFS(数据!$C$2:$C$197,"保险浮存金",数据!$D$2:$D$197,"2026H1")=0,0,SUMIFS(数据!$E$2:$E$197,数据!$C$2:$C$197,"保险浮存金",数据!$D$2:$D$197,"2026H1")) -> 177500
A6: 保险及其他：现金及现金等价物 | B6: =IF(COUNTIFS(数据!$C$2:$C$197,"保险及其他现金及现金等价物",数据!$D$2:$D$197,"2021A")=0,0,SUMIFS(数据!$E$2:$E$197,数据!$C$2:$C$197,"保险及其他现金及现金等价物",数据!$D$2:$D$197,"2021A")) -> 85319 | C6: =IF(COUNTIFS(数据!$C$2:$C$197,"保险及其他现金及现金等价物",数据!$D$2:$D$197,"2022A")=0,0,SUMIFS(数据!$E$2:$E$197,数据!$C$2:$C$197,"保险及其他现金及现金等价物",数据!$D$2:$D$197,"2022A")) -> 32260 | D6: =IF(COUNTIFS(数据!$C$2:$C$197,"保险及其他现金及现金等价物",数据!$D$2:$D$197,"2023A")=0,0,SUMIFS(数据!$E$2:$E$197,数据!$C$2:$C$197,"保险及其他现金及现金等价物",数据!$D$2:$D$197,"2023A")) -> 33672 | E6: =IF(COUNTIFS(数据!$C$2:$C$197,"保险及其他现金及现金等价物",数据!$D$2:$D$197,"2024A")=0,0,SUMIFS(数据!$E$2:$E$197,数据!$C$2:$C$197,"保险及其他现金及现金等价物",数据!$D$2:$D$197,"2024A")) -> 44333 | F6: =IF(COUNTIFS(数据!$C$2:$C$197,"保险及其他现金及现金等价物",数据!$D$2:$D$197,"2025A")=0,0,SUMIFS(数据!$E$2:$E$197,数据!$C$2:$C$197,"保险及其他现金及现金等价物",数据!$D$2:$D$197,"2025A")) -> 47719 | G6: =IF(COUNTIFS(数据!$C$2:$C$197,"保险及其他现金及现金等价物",数据!$D$2:$D$197,"2026H1")=0,0,SUMIFS(数据!$E$2:$E$197,数据!$C$2:$C$197,"保险及其他现金及现金等价物",数据!$D$2:$D$197,"2026H1")) -> 35096
A7: 铁路、公用事业及能源：现金 | B7: =IF(COUNTIFS(数据!$C$2:$C$197,"铁路、公用事业及能源现金",数据!$D$2:$D$197,"2021A")=0,0,SUMIFS(数据!$E$2:$E$197,数据!$C$2:$C$197,"铁路、公用事业及能源现金",数据!$D$2:$D$197,"2021A")) -> 2865 | C7: =IF(COUNTIFS(数据!$C$2:$C$197,"铁路、公用事业及能源现金",数据!$D$2:$D$197,"2022A")=0,0,SUMIFS(数据!$E$2:$E$197,数据!$C$2:$C$197,"铁路、公用事业及能源现金",数据!$D$2:$D$197,"2022A")) -> 3551 | D7: =IF(COUNTIFS(数据!$C$2:$C$197,"铁路、公用事业及能源现金",数据!$D$2:$D$197,"2023A")=0,0,SUMIFS(数据!$E$2:$E$197,数据!$C$2:$C$197,"铁路、公用事业及能源现金",数据!$D$2:$D$197,"2023A")) -> 4350 | E7: =IF(COUNTIFS(数据!$C$2:$C$197,"铁路、公用事业及能源现金",数据!$D$2:$D$197,"2024A")=0,0,SUMIFS(数据!$E$2:$E$197,数据!$C$2:$C$197,"铁路、公用事业及能源现金",数据!$D$2:$D$197,"2024A")) -> 3396 | F7: =IF(COUNTIFS(数据!$C$2:$C$197,"铁路、公用事业及能源现金",数据!$D$2:$D$197,"2025A")=0,0,SUMIFS(数据!$E$2:$E$197,数据!$C$2:$C$197,"铁路、公用事业及能源现金",数据!$D$2:$D$197,"2025A")) -> 4158 | G7: =IF(COUNTIFS(数据!$C$2:$C$197,"铁路、公用事业及能源现金",数据!$D$2:$D$197,"2026H1")=0,0,SUMIFS(数据!$E$2:$E$197,数据!$C$2:$C$197,"铁路、公用事业及能源现金",数据!$D$2:$D$197,"2026H1")) -> 5513
A8: 短期美国国债 | B8: =IF(COUNTIFS(数据!$C$2:$C$197,"短期美国国债",数据!$D$2:$D$197,"2021A")=0,0,SUMIFS(数据!$E$2:$E$197,数据!$C$2:$C$197,"短期美国国债",数据!$D$2:$D$197,"2021A")) -> 58535 | C8: =IF(COUNTIFS(数据!$C$2:$C$197,"短期美国国债",数据!$D$2:$D$197,"2022A")=0,0,SUMIFS(数据!$E$2:$E$197,数据!$C$2:$C$197,"短期美国国债",数据!$D$2:$D$197,"2022A")) -> 92774 | D8: =IF(COUNTIFS(数据!$C$2:$C$197,"短期美国国债",数据!$D$2:$D$197,"2023A")=0,0,SUMIFS(数据!$E$2:$E$197,数据!$C$2:$C$197,"短期美国国债",数据!$D$2:$D$197,"2023A")) -> 129619 | E8: =IF(COUNTIFS(数据!$C$2:$C$197,"短期美国国债",数据!$D$2:$D$197,"2024A")=0,0,SUMIFS(数据!$E$2:$E$197,数据!$C$2:$C$197,"短期美国国债",数据!$D$2:$D$197,"2024A")) -> 286472 | F8: =IF(COUNTIFS(数据!$C$2:$C$197,"短期美国国债",数据!$D$2:$D$197,"2025A")=0,0,SUMIFS(数据!$E$2:$E$197,数据!$C$2:$C$197,"短期美国国债",数据!$D$2:$D$197,"2025A")) -> 321434 | G8: =IF(COUNTIFS(数据!$C$2:$C$197,"短期美国国债",数据!$D$2:$D$197,"2026H1")=0,0,SUMIFS(数据!$E$2:$E$197,数据!$C$2:$C$197,"短期美国国债",数据!$D$2:$D$197,"2026H1")) -> 324905
A9: 现金及短期国债合计（公式） | B9: =SUM(B6:B8) -> 146719 | C9: =SUM(C6:C8) -> 128585 | D9: =SUM(D6:D8) -> 167641 | E9: =SUM(E6:E8) -> 334201 | F9: =SUM(F6:F8) -> 373311 | G9: =SUM(G6:G8) -> 365514
A10: 股票投资组合（公允价值） | B10: =IF(COUNTIFS(数据!$C$2:$C$197,"股票组合合计（披露）",数据!$D$2:$D$197,"2021A")=0,0,SUMIFS(数据!$E$2:$E$197,数据!$C$2:$C$197,"股票组合合计（披露）",数据!$D$2:$D$197,"2021A")) -> 350719 | C10: =IF(COUNTIFS(数据!$C$2:$C$197,"股票组合合计（披露）",数据!$D$2:$D$197,"2022A")=0,0,SUMIFS(数据!$E$2:$E$197,数据!$C$2:$C$197,"股票组合合计（披露）",数据!$D$2:$D$197,"2022A")) -> 308793 | D10: =IF(COUNTIFS(数据!$C$2:$C$197,"股票组合合计（披露）",数据!$D$2:$D$197,"2023A")=0,0,SUMIFS(数据!$E$2:$E$197,数据!$C$2:$C$197,"股票组合合计（披露）",数据!$D$2:$D$197,"2023A")) -> 353842 | E10: =IF(COUNTIFS(数据!$C$2:$C$197,"股票组合合计（披露）",数据!$D$2:$D$197,"2024A")=0,0,SUMIFS(数据!$E$2:$E$197,数据!$C$2:$C$197,"股票组合合计（披露）",数据!$D$2:$D$197,"2024A")) -> 271588 | F10: =IF(COUNTIFS(数据!$C$2:$C$197,"股票组合合计（披露）",数据!$D$2:$D$197,"2025A")=0,0,SUMIFS(数据!$E$2:$E$197,数据!$C$2:$C$197,"股票组合合计（披露）",数据!$D$2:$D$197,"2025A")) -> 297778 | G10: =IF(COUNTIFS(数据!$C$2:$C$197,"股票组合合计（披露）",数据!$D$2:$D$197,"2026H1")=0,0,SUMIFS(数据!$E$2:$E$197,数据!$C$2:$C$197,"股票组合合计（披露）",数据!$D$2:$D$197,"2026H1")) -> 323779
A11: 归母股东权益 | B11: =IF(COUNTIFS(数据!$C$2:$C$197,"归母股东权益",数据!$D$2:$D$197,"2021A")=0,0,SUMIFS(数据!$E$2:$E$197,数据!$C$2:$C$197,"归母股东权益",数据!$D$2:$D$197,"2021A")) -> 501568 | C11: =IF(COUNTIFS(数据!$C$2:$C$197,"归母股东权益",数据!$D$2:$D$197,"2022A")=0,0,SUMIFS(数据!$E$2:$E$197,数据!$C$2:$C$197,"归母股东权益",数据!$D$2:$D$197,"2022A")) -> 473424 | D11: =IF(COUNTIFS(数据!$C$2:$C$197,"归母股东权益",数据!$D$2:$D$197,"2023A")=0,0,SUMIFS(数据!$E$2:$E$197,数据!$C$2:$C$197,"归母股东权益",数据!$D$2:$D$197,"2023A")) -> 561273 | E11: =IF(COUNTIFS(数据!$C$2:$C$197,"归母股东权益",数据!$D$2:$D$197,"2024A")=0,0,SUMIFS(数据!$E$2:$E$197,数据!$C$2:$C$197,"归母股东权益",数据!$D$2:$D$197,"2024A")) -> 649368 | F11: =IF(COUNTIFS(数据!$C$2:$C$197,"归母股东权益",数据!$D$2:$D$197,"2025A")=0,0,SUMIFS(数据!$E$2:$E$197,数据!$C$2:$C$197,"归母股东权益",数据!$D$2:$D$197,"2025A")) -> 717419 | G11: =IF(COUNTIFS(数据!$C$2:$C$197,"归母股东权益",数据!$D$2:$D$197,"2026H1")=0,0,SUMIFS(数据!$E$2:$E$197,数据!$C$2:$C$197,"归母股东权益",数据!$D$2:$D$197,"2026H1")) -> 747910
A12: 期末A类等价股数 | B12: =IF(COUNTIFS(数据!$C$2:$C$197,"期末A类等价股数",数据!$D$2:$D$197,"2021A")=0,0,SUMIFS(数据!$E$2:$E$197,数据!$C$2:$C$197,"期末A类等价股数",数据!$D$2:$D$197,"2021A")) -> 1477429 | C12: =IF(COUNTIFS(数据!$C$2:$C$197,"期末A类等价股数",数据!$D$2:$D$197,"2022A")=0,0,SUMIFS(数据!$E$2:$E$197,数据!$C$2:$C$197,"期末A类等价股数",数据!$D$2:$D$197,"2022A")) -> 1459733 | D12: =IF(COUNTIFS(数据!$C$2:$C$197,"期末A类等价股数",数据!$D$2:$D$197,"2023A")=0,0,SUMIFS(数据!$E$2:$E$197,数据!$C$2:$C$197,"期末A类等价股数",数据!$D$2:$D$197,"2023A")) -> 1441483 | E12: =IF(COUNTIFS(数据!$C$2:$C$197,"期末A类等价股数",数据!$D$2:$D$197,"2024A")=0,0,SUMIFS(数据!$E$2:$E$197,数据!$C$2:$C$197,"期末A类等价股数",数据!$D$2:$D$197,"2024A")) -> 1438223 | F12: =IF(COUNTIFS(数据!$C$2:$C$197,"期末A类等价股数",数据!$D$2:$D$197,"2025A")=0,0,SUMIFS(数据!$E$2:$E$197,数据!$C$2:$C$197,"期末A类等价股数",数据!$D$2:$D$197,"2025A")) -> 1438223 | G12: =IF(COUNTIFS(数据!$C$2:$C$197,"期末A类等价股数",数据!$D$2:$D$197,"2026H1")=0,0,SUMIFS(数据!$E$2:$E$197,数据!$C$2:$C$197,"期末A类等价股数",数据!$D$2:$D$197,"2026H1")) -> 1431693
A13: 每股账面价值—A类（公式） | B13: =B11*1000000/B12 -> 339487.04 | C13: =C11*1000000/C12 -> 324322.32 | D13: =D11*1000000/D12 -> 389371.92 | E13: =E11*1000000/E12 -> 451507.17 | F13: =F11*1000000/F12 -> 498823.2 | G13: =G11*1000000/G12 -> 522395.51
A14: 每股账面价值—B类（A类÷1500） | B14: =B13/1500 -> 226.32469 | C14: =C13/1500 -> 216.21488 | D14: =D13/1500 -> 259.58128 | E14: =E13/1500 -> 301.00478 | F14: =F13/1500 -> 332.5488 | G14: =G13/1500 -> 348.26368
A16: 资本配置与股票现金流
A17: 回购金额（现金流量表） | B17: =IF(COUNTIFS(数据!$C$2:$C$197,"回购金额（现金流量表）",数据!$D$2:$D$197,"2021A")=0,0,SUMIFS(数据!$E$2:$E$197,数据!$C$2:$C$197,"回购金额（现金流量表）",数据!$D$2:$D$197,"2021A")) -> 27061 | C17: =IF(COUNTIFS(数据!$C$2:$C$197,"回购金额（现金流量表）",数据!$D$2:$D$197,"2022A")=0,0,SUMIFS(数据!$E$2:$E$197,数据!$C$2:$C$197,"回购金额（现金流量表）",数据!$D$2:$D$197,"2022A")) -> 7854 | D17: =IF(COUNTIFS(数据!$C$2:$C$197,"回购金额（现金流量表）",数据!$D$2:$D$197,"2023A")=0,0,SUMIFS(数据!$E$2:$E$197,数据!$C$2:$C$197,"回购金额（现金流量表）",数据!$D$2:$D$197,"2023A")) -> 9171 | E17: =IF(COUNTIFS(数据!$C$2:$C$197,"回购金额（现金流量表）",数据!$D$2:$D$197,"2024A")=0,0,SUMIFS(数据!$E$2:$E$197,数据!$C$2:$C$197,"回购金额（现金流量表）",数据!$D$2:$D$197,"2024A")) -> 2918 | F17: =IF(COUNTIFS(数据!$C$2:$C$197,"回购金额（现金流量表）",数据!$D$2:$D$197,"2025A")=0,0,SUMIFS(数据!$E$2:$E$197,数据!$C$2:$C$197,"回购金额（现金流量表）",数据!$D$2:$D$197,"2025A")) -> 0 | G17: =IF(COUNTIFS(数据!$C$2:$C$197,"回购金额（现金流量表）",数据!$D$2:$D$197,"2026H1")=0,0,SUMIFS(数据!$E$2:$E$197,数据!$C$2:$C$197,"回购金额（现金流量表）",数据!$D$2:$D$197,"2026H1")) -> 4444
A18: 回购成本（权益变动表） | B18: =IF(COUNTIFS(数据!$C$2:$C$197,"回购成本（权益变动表）",数据!$D$2:$D$197,"2021A")=0,0,SUMIFS(数据!$E$2:$E$197,数据!$C$2:$C$197,"回购成本（权益变动表）",数据!$D$2:$D$197,"2021A")) -> 26942 | C18: =IF(COUNTIFS(数据!$C$2:$C$197,"回购成本（权益变动表）",数据!$D$2:$D$197,"2022A")=0,0,SUMIFS(数据!$E$2:$E$197,数据!$C$2:$C$197,"回购成本（权益变动表）",数据!$D$2:$D$197,"2022A")) -> 8031 | D18: =IF(COUNTIFS(数据!$C$2:$C$197,"回购成本（权益变动表）",数据!$D$2:$D$197,"2023A")=0,0,SUMIFS(数据!$E$2:$E$197,数据!$C$2:$C$197,"回购成本（权益变动表）",数据!$D$2:$D$197,"2023A")) -> 8976 | E18: =IF(COUNTIFS(数据!$C$2:$C$197,"回购成本（权益变动表）",数据!$D$2:$D$197,"2024A")=0,0,SUMIFS(数据!$E$2:$E$197,数据!$C$2:$C$197,"回购成本（权益变动表）",数据!$D$2:$D$197,"2024A")) -> 2918 | F18: =IF(COUNTIFS(数据!$C$2:$C$197,"回购成本（权益变动表）",数据!$D$2:$D$197,"2025A")=0,0,SUMIFS(数据!$E$2:$E$197,数据!$C$2:$C$197,"回购成本（权益变动表）",数据!$D$2:$D$197,"2025A")) -> 0 | G18: =IF(COUNTIFS(数据!$C$2:$C$197,"回购成本（权益变动表）",数据!$D$2:$D$197,"2026H1")=0,0,SUMIFS(数据!$E$2:$E$197,数据!$C$2:$C$197,"回购成本（权益变动表）",数据!$D$2:$D$197,"2026H1")) -> 4762
A19: 购买股票（现金流） | B19: =IF(COUNTIFS(数据!$C$2:$C$197,"购买股票（现金流）",数据!$D$2:$D$197,"2021A")=0,0,SUMIFS(数据!$E$2:$E$197,数据!$C$2:$C$197,"购买股票（现金流）",数据!$D$2:$D$197,"2021A")) -> 8448 | C19: =IF(COUNTIFS(数据!$C$2:$C$197,"购买股票（现金流）",数据!$D$2:$D$197,"2022A")=0,0,SUMIFS(数据!$E$2:$E$197,数据!$C$2:$C$197,"购买股票（现金流）",数据!$D$2:$D$197,"2022A")) -> 67930 | D19: =IF(COUNTIFS(数据!$C$2:$C$197,"购买股票（现金流）",数据!$D$2:$D$197,"2023A")=0,0,SUMIFS(数据!$E$2:$E$197,数据!$C$2:$C$197,"购买股票（现金流）",数据!$D$2:$D$197,"2023A")) -> 16462 | E19: =IF(COUNTIFS(数据!$C$2:$C$197,"购买股票（现金流）",数据!$D$2:$D$197,"2024A")=0,0,SUMIFS(数据!$E$2:$E$197,数据!$C$2:$C$197,"购买股票（现金流）",数据!$D$2:$D$197,"2024A")) -> 9237 | F19: =IF(COUNTIFS(数据!$C$2:$C$197,"购买股票（现金流）",数据!$D$2:$D$197,"2025A")=0,0,SUMIFS(数据!$E$2:$E$197,数据!$C$2:$C$197,"购买股票（现金流）",数据!$D$2:$D$197,"2025A")) -> 16923 | G19: =IF(COUNTIFS(数据!$C$2:$C$197,"购买股票（现金流）",数据!$D$2:$D$197,"2026H1")=0,0,SUMIFS(数据!$E$2:$E$197,数据!$C$2:$C$197,"购买股票（现金流）",数据!$D$2:$D$197,"2026H1")) -> 39405
A20: 出售股票（现金流） | B20: =IF(COUNTIFS(数据!$C$2:$C$197,"出售股票（现金流）",数据!$D$2:$D$197,"2021A")=0,0,SUMIFS(数据!$E$2:$E$197,数据!$C$2:$C$197,"出售股票（现金流）",数据!$D$2:$D$197,"2021A")) -> 15849 | C20: =IF(COUNTIFS(数据!$C$2:$C$197,"出售股票（现金流）",数据!$D$2:$D$197,"2022A")=0,0,SUMIFS(数据!$E$2:$E$197,数据!$C$2:$C$197,"出售股票（现金流）",数据!$D$2:$D$197,"2022A")) -> 33664 | D20: =IF(COUNTIFS(数据!$C$2:$C$197,"出售股票（现金流）",数据!$D$2:$D$197,"2023A")=0,0,SUMIFS(数据!$E$2:$E$197,数据!$C$2:$C$197,"出售股票（现金流）",数据!$D$2:$D$197,"2023A")) -> 40631 | E20: =IF(COUNTIFS(数据!$C$2:$C$197,"出售股票（现金流）",数据!$D$2:$D$197,"2024A")=0,0,SUMIFS(数据!$E$2:$E$197,数据!$C$2:$C$197,"出售股票（现金流）",数据!$D$2:$D$197,"2024A")) -> 143359 | F20: =IF(COUNTIFS(数据!$C$2:$C$197,"出售股票（现金流）",数据!$D$2:$D$197,"2025A")=0,0,SUMIFS(数据!$E$2:$E$197,数据!$C$2:$C$197,"出售股票（现金流）",数据!$D$2:$D$197,"2025A")) -> 30686 | G20: =IF(COUNTIFS(数据!$C$2:$C$197,"出售股票（现金流）",数据!$D$2:$D$197,"2026H1")=0,0,SUMIFS(数据!$E$2:$E$197,数据!$C$2:$C$197,"出售股票（现金流）",数据!$D$2:$D$197,"2026H1")) -> 27780
A21: 股票净购买（购买－出售） | B21: =B19-B20 -> -7401 | C21: =C19-C20 -> 34266 | D21: =D19-D20 -> -24169 | E21: =E19-E20 -> -134122 | F21: =F19-F20 -> -13763 | G21: =G19-G20 -> 11625
A23: 每股账面价值＝归母股东权益×1,000,000÷期末A类等价股数；不是公司披露的GAAP每股指标。2021年权益采用2023年报追溯调整后的四项归母权益组成之和。回购现金流与库存股取得成本因口径及结算时点不同而并列。2026年业绩公告约48亿美元对应权益变动表口径。

Sheet 股票组合
A1: 股票投资组合｜披露行业与主要持仓
A2: 单位：百万美元；按公允价值。行业合计不含按权益法核算的Kraft Heinz与Occidental普通股。
A4: 指标 | B4: 2021年 | C4: 2022年 | D4: 2023年 | E4: 2024年 | F4: 2025年 | G4: 2026年上半年
A5: 银行、保险及金融 | B5: =IF(COUNTIFS(数据!$C$2:$C$197,"股票—银行、保险及金融",数据!$D$2:$D$197,"2021A")=0,0,SUMIFS(数据!$E$2:$E$197,数据!$C$2:$C$197,"股票—银行、保险及金融",数据!$D$2:$D$197,"2021A")) -> 89058 | C5: =IF(COUNTIFS(数据!$C$2:$C$197,"股票—银行、保险及金融",数据!$D$2:$D$197,"2022A")=0,0,SUMIFS(数据!$E$2:$E$197,数据!$C$2:$C$197,"股票—银行、保险及金融",数据!$D$2:$D$197,"2022A")) -> 69556 | D5: =IF(COUNTIFS(数据!$C$2:$C$197,"股票—银行、保险及金融",数据!$D$2:$D$197,"2023A")=0,0,SUMIFS(数据!$E$2:$E$197,数据!$C$2:$C$197,"股票—银行、保险及金融",数据!$D$2:$D$197,"2023A")) -> 78312 | E5: =IF(COUNTIFS(数据!$C$2:$C$197,"股票—银行、保险及金融",数据!$D$2:$D$197,"2024A")=0,0,SUMIFS(数据!$E$2:$E$197,数据!$C$2:$C$197,"股票—银行、保险及金融",数据!$D$2:$D$197,"2024A")) -> 91643 | F5: =IF(COUNTIFS(数据!$C$2:$C$197,"股票—银行、保险及金融",数据!$D$2:$D$197,"2025A")=0,0,SUMIFS(数据!$E$2:$E$197,数据!$C$2:$C$197,"股票—银行、保险及金融",数据!$D$2:$D$197,"2025A")) -> 104129 | G5: =IF(COUNTIFS(数据!$C$2:$C$197,"股票—银行、保险及金融",数据!$D$2:$D$197,"2026H1")=0,0,SUMIFS(数据!$E$2:$E$197,数据!$C$2:$C$197,"股票—银行、保险及金融",数据!$D$2:$D$197,"2026H1")) -> 94477
A6: 消费品 | B6: =IF(COUNTIFS(数据!$C$2:$C$197,"股票—消费品",数据!$D$2:$D$197,"2021A")=0,0,SUMIFS(数据!$E$2:$E$197,数据!$C$2:$C$197,"股票—消费品",数据!$D$2:$D$197,"2021A")) -> 191021 | C6: =IF(COUNTIFS(数据!$C$2:$C$197,"股票—消费品",数据!$D$2:$D$197,"2022A")=0,0,SUMIFS(数据!$E$2:$E$197,数据!$C$2:$C$197,"股票—消费品",数据!$D$2:$D$197,"2022A")) -> 152892 | D6: =IF(COUNTIFS(数据!$C$2:$C$197,"股票—消费品",数据!$D$2:$D$197,"2023A")=0,0,SUMIFS(数据!$E$2:$E$197,数据!$C$2:$C$197,"股票—消费品",数据!$D$2:$D$197,"2023A")) -> 201143 | E6: =IF(COUNTIFS(数据!$C$2:$C$197,"股票—消费品",数据!$D$2:$D$197,"2024A")=0,0,SUMIFS(数据!$E$2:$E$197,数据!$C$2:$C$197,"股票—消费品",数据!$D$2:$D$197,"2024A")) -> 104749 | F6: =IF(COUNTIFS(数据!$C$2:$C$197,"股票—消费品",数据!$D$2:$D$197,"2025A")=0,0,SUMIFS(数据!$E$2:$E$197,数据!$C$2:$C$197,"股票—消费品",数据!$D$2:$D$197,"2025A")) -> 94954 | G6: =IF(COUNTIFS(数据!$C$2:$C$197,"股票—消费品",数据!$D$2:$D$197,"2026H1")=0,0,SUMIFS(数据!$E$2:$E$197,数据!$C$2:$C$197,"股票—消费品",数据!$D$2:$D$197,"2026H1")) -> 100486
A7: 商业、工业及其他 | B7: =IF(COUNTIFS(数据!$C$2:$C$197,"股票—商业、工业及其他",数据!$D$2:$D$197,"2021A")=0,0,SUMIFS(数据!$E$2:$E$197,数据!$C$2:$C$197,"股票—商业、工业及其他",数据!$D$2:$D$197,"2021A")) -> 70640 | C7: =IF(COUNTIFS(数据!$C$2:$C$197,"股票—商业、工业及其他",数据!$D$2:$D$197,"2022A")=0,0,SUMIFS(数据!$E$2:$E$197,数据!$C$2:$C$197,"股票—商业、工业及其他",数据!$D$2:$D$197,"2022A")) -> 86345 | D7: =IF(COUNTIFS(数据!$C$2:$C$197,"股票—商业、工业及其他",数据!$D$2:$D$197,"2023A")=0,0,SUMIFS(数据!$E$2:$E$197,数据!$C$2:$C$197,"股票—商业、工业及其他",数据!$D$2:$D$197,"2023A")) -> 74387 | E7: =IF(COUNTIFS(数据!$C$2:$C$197,"股票—商业、工业及其他",数据!$D$2:$D$197,"2024A")=0,0,SUMIFS(数据!$E$2:$E$197,数据!$C$2:$C$197,"股票—商业、工业及其他",数据!$D$2:$D$197,"2024A")) -> 75196 | F7: =IF(COUNTIFS(数据!$C$2:$C$197,"股票—商业、工业及其他",数据!$D$2:$D$197,"2025A")=0,0,SUMIFS(数据!$E$2:$E$197,数据!$C$2:$C$197,"股票—商业、工业及其他",数据!$D$2:$D$197,"2025A")) -> 98695 | G7: =IF(COUNTIFS(数据!$C$2:$C$197,"股票—商业、工业及其他",数据!$D$2:$D$197,"2026H1")=0,0,SUMIFS(数据!$E$2:$E$197,数据!$C$2:$C$197,"股票—商业、工业及其他",数据!$D$2:$D$197,"2026H1")) -> 128816
A8: 行业合计（公式） | B8: =SUM(B5:B7) -> 350719 | C8: =SUM(C5:C7) -> 308793 | D8: =SUM(D5:D7) -> 353842 | E8: =SUM(E5:E7) -> 271588 | F8: =SUM(F5:F7) -> 297778 | G8: =SUM(G5:G7) -> 323779
A9: 披露合计 | B9: =IF(COUNTIFS(数据!$C$2:$C$197,"股票组合合计（披露）",数据!$D$2:$D$197,"2021A")=0,0,SUMIFS(数据!$E$2:$E$197,数据!$C$2:$C$197,"股票组合合计（披露）",数据!$D$2:$D$197,"2021A")) -> 350719 | C9: =IF(COUNTIFS(数据!$C$2:$C$197,"股票组合合计（披露）",数据!$D$2:$D$197,"2022A")=0,0,SUMIFS(数据!$E$2:$E$197,数据!$C$2:$C$197,"股票组合合计（披露）",数据!$D$2:$D$197,"2022A")) -> 308793 | D9: =IF(COUNTIFS(数据!$C$2:$C$197,"股票组合合计（披露）",数据!$D$2:$D$197,"2023A")=0,0,SUMIFS(数据!$E$2:$E$197,数据!$C$2:$C$197,"股票组合合计（披露）",数据!$D$2:$D$197,"2023A")) -> 353842 | E9: =IF(COUNTIFS(数据!$C$2:$C$197,"股票组合合计（披露）",数据!$D$2:$D$197,"2024A")=0,0,SUMIFS(数据!$E$2:$E$197,数据!$C$2:$C$197,"股票组合合计（披露）",数据!$D$2:$D$197,"2024A")) -> 271588 | F9: =IF(COUNTIFS(数据!$C$2:$C$197,"股票组合合计（披露）",数据!$D$2:$D$197,"2025A")=0,0,SUMIFS(数据!$E$2:$E$197,数据!$C$2:$C$197,"股票组合合计（披露）",数据!$D$2:$D$197,"2025A")) -> 297778 | G9: =IF(COUNTIFS(数据!$C$2:$C$197,"股票组合合计（披露）",数据!$D$2:$D$197,"2026H1")=0,0,SUMIFS(数据!$E$2:$E$197,数据!$C$2:$C$197,"股票组合合计（披露）",数据!$D$2:$D$197,"2026H1")) -> 323779
A10: 对账差异（应为0） | B10: =B8-B9 -> 0 | C10: =C8-C9 -> 0 | D10: =D8-D9 -> 0 | E10: =E8-E9 -> 0 | F10: =F8-F9 -> 0 | G10: =G8-G9 -> 0
A11: 行业占比（公式）
A12: 银行、保险及金融占比 | B12: =B5/B8 -> 0.25392978 | C12: =C5/C8 -> 0.22525122 | D12: =D5/D8 -> 0.22131912 | E12: =E5/E8 -> 0.33743391 | F12: =F5/F8 -> 0.34968668 | G12: =G5/G8 -> 0.29179471
A13: 消费品占比 | B13: =B6/B8 -> 0.54465541 | C13: =C6/C8 -> 0.4951278 | D13: =D6/D8 -> 0.56845428 | E13: =E6/E8 -> 0.38569083 | F13: =F6/F8 -> 0.31887514 | G13: =G6/G8 -> 0.31035367
A14: 商业、工业及其他占比 | B14: =B7/B8 -> 0.20141481 | C14: =C7/C8 -> 0.27962098 | D14: =D7/D8 -> 0.2102266 | E14: =E7/E8 -> 0.27687527 | F14: =F7/F8 -> 0.33143819 | G14: =G7/G8 -> 0.39785162
A16: 主要持仓集中度 | B16: =IF(COUNTIFS(数据!$C$2:$C$197,"主要持仓集中度",数据!$D$2:$D$197,"2021A")=0,0,SUMIFS(数据!$E$2:$E$197,数据!$C$2:$C$197,"主要持仓集中度",数据!$D$2:$D$197,"2021A")) -> 0.73 | C16: =IF(COUNTIFS(数据!$C$2:$C$197,"主要持仓集中度",数据!$D$2:$D$197,"2022A")=0,0,SUMIFS(数据!$E$2:$E$197,数据!$C$2:$C$197,"主要持仓集中度",数据!$D$2:$D$197,"2022A")) -> 0.75 | D16: =IF(COUNTIFS(数据!$C$2:$C$197,"主要持仓集中度",数据!$D$2:$D$197,"2023A")=0,0,SUMIFS(数据!$E$2:$E$197,数据!$C$2:$C$197,"主要持仓集中度",数据!$D$2:$D$197,"2023A")) -> 0.79 | E16: =IF(COUNTIFS(数据!$C$2:$C$197,"主要持仓集中度",数据!$D$2:$D$197,"2024A")=0,0,SUMIFS(数据!$E$2:$E$197,数据!$C$2:$C$197,"主要持仓集中度",数据!$D$2:$D$197,"2024A")) -> 0.71 | F16: =IF(COUNTIFS(数据!$C$2:$C$197,"主要持仓集中度",数据!$D$2:$D$197,"2025A")=0,0,SUMIFS(数据!$E$2:$E$197,数据!$C$2:$C$197,"主要持仓集中度",数据!$D$2:$D$197,"2025A")) -> 0.65 | G16: =IF(COUNTIFS(数据!$C$2:$C$197,"主要持仓集中度",数据!$D$2:$D$197,"2026H1")=0,0,SUMIFS(数据!$E$2:$E$197,数据!$C$2:$C$197,"主要持仓集中度",数据!$D$2:$D$197,"2026H1")) -> 0.66
A17: 主要持仓名单 | B17: American Express、Apple、Bank of America、Coca-Cola（前四大） | C17: American Express、Apple、Bank of America、Coca-Cola、Chevron（前五大） | D17: American Express、Apple、Bank of America、Coca-Cola、Chevron（前五大） | E17: American Express、Apple、Bank of America、Coca-Cola、Chevron（前五大） | F17: American Express、Apple、Bank of America、Coca-Cola、Chevron（前五大） | G17: Alphabet、American Express、Apple、Bank of America、Coca-Cola（前五大）
A19: 2026年6月末前五大为Alphabet、American Express、Apple、Bank of America、Coca-Cola；2025年末为American Express、Apple、Bank of America、Coca-Cola、Chevron。原始披露只给出前五大合计集中度，不给出本期每家公司的单独公允价值，本表不作拆分估算。

Sheet 经营细节
A1: 2026年上半年经营细节｜与2025年上半年比较
A2: 单位依指标而定；变化额与变化率均为公式。基数小于等于0时变化率标为N/M。
A4: 指标 | B4: 2025年上半年 | C4: 2026年上半年 | D4: 变化额 | E4: 变化率 | F4: 说明
A5: GEICO已赚保费 | B5: =IF(COUNTIFS(数据!$C$2:$C$197,"GEICO已赚保费",数据!$D$2:$D$197,"2025H1")=0,"—",SUMIFS(数据!$E$2:$E$197,数据!$C$2:$C$197,"GEICO已赚保费",数据!$D$2:$D$197,"2025H1")) -> 21816 | C5: =IF(COUNTIFS(数据!$C$2:$C$197,"GEICO已赚保费",数据!$D$2:$D$197,"2026H1")=0,"—",SUMIFS(数据!$E$2:$E$197,数据!$C$2:$C$197,"GEICO已赚保费",数据!$D$2:$D$197,"2026H1")) -> 22477 | D5: =IF(OR(NOT(ISNUMBER(B5)),NOT(ISNUMBER(C5))),"—",C5-B5) -> 661 | E5: =IF(OR(NOT(ISNUMBER(B5)),NOT(ISNUMBER(C5)),B5<=0),"N/M",C5/B5-1) -> 0.030298863
A6: GEICO税前承保利润 | B6: =IF(COUNTIFS(数据!$C$2:$C$197,"GEICO税前承保利润",数据!$D$2:$D$197,"2025H1")=0,"—",SUMIFS(数据!$E$2:$E$197,数据!$C$2:$C$197,"GEICO税前承保利润",数据!$D$2:$D$197,"2025H1")) -> 3994 | C6: =IF(COUNTIFS(数据!$C$2:$C$197,"GEICO税前承保利润",数据!$D$2:$D$197,"2026H1")=0,"—",SUMIFS(数据!$E$2:$E$197,数据!$C$2:$C$197,"GEICO税前承保利润",数据!$D$2:$D$197,"2026H1")) -> 2410 | D6: =IF(OR(NOT(ISNUMBER(B6)),NOT(ISNUMBER(C6))),"—",C6-B6) -> -1584 | E6: =IF(OR(NOT(ISNUMBER(B6)),NOT(ISNUMBER(C6)),B6<=0),"N/M",C6/B6-1) -> -0.39659489
A7: GEICO赔付率 | B7: =IF(COUNTIFS(数据!$C$2:$C$197,"GEICO赔付率",数据!$D$2:$D$197,"2025H1")=0,"—",SUMIFS(数据!$E$2:$E$197,数据!$C$2:$C$197,"GEICO赔付率",数据!$D$2:$D$197,"2025H1")) -> 0.704 | C7: =IF(COUNTIFS(数据!$C$2:$C$197,"GEICO赔付率",数据!$D$2:$D$197,"2026H1")=0,"—",SUMIFS(数据!$E$2:$E$197,数据!$C$2:$C$197,"GEICO赔付率",数据!$D$2:$D$197,"2026H1")) -> 0.753 | D7: =IF(OR(NOT(ISNUMBER(B7)),NOT(ISNUMBER(C7))),"—",C7-B7) -> 0.049 | E7: =IF(OR(NOT(ISNUMBER(B7)),NOT(ISNUMBER(C7)),B7<=0),"N/M",C7/B7-1) -> 0.069602273
A8: GEICO费用率 | B8: =IF(COUNTIFS(数据!$C$2:$C$197,"GEICO费用率",数据!$D$2:$D$197,"2025H1")=0,"—",SUMIFS(数据!$E$2:$E$197,数据!$C$2:$C$197,"GEICO费用率",数据!$D$2:$D$197,"2025H1")) -> 0.113 | C8: =IF(COUNTIFS(数据!$C$2:$C$197,"GEICO费用率",数据!$D$2:$D$197,"2026H1")=0,"—",SUMIFS(数据!$E$2:$E$197,数据!$C$2:$C$197,"GEICO费用率",数据!$D$2:$D$197,"2026H1")) -> 0.14 | D8: =IF(OR(NOT(ISNUMBER(B8)),NOT(ISNUMBER(C8))),"—",C8-B8) -> 0.027 | E8: =IF(OR(NOT(ISNUMBER(B8)),NOT(ISNUMBER(C8)),B8<=0),"N/M",C8/B8-1) -> 0.23893805
A9: BH Primary税前承保利润 | B9: =IF(COUNTIFS(数据!$C$2:$C$197,"BH Primary税前承保利润",数据!$D$2:$D$197,"2025H1")=0,"—",SUMIFS(数据!$E$2:$E$197,数据!$C$2:$C$197,"BH Primary税前承保利润",数据!$D$2:$D$197,"2025H1")) -> -81 | C9: =IF(COUNTIFS(数据!$C$2:$C$197,"BH Primary税前承保利润",数据!$D$2:$D$197,"2026H1")=0,"—",SUMIFS(数据!$E$2:$E$197,数据!$C$2:$C$197,"BH Primary税前承保利润",数据!$D$2:$D$197,"2026H1")) -> 749 | D9: =IF(OR(NOT(ISNUMBER(B9)),NOT(ISNUMBER(C9))),"—",C9-B9) -> 830 | E9: =IF(OR(NOT(ISNUMBER(B9)),NOT(ISNUMBER(C9)),B9<=0),"N/M",C9/B9-1) -> N/M
A10: BHRG税前承保利润 | B10: =IF(COUNTIFS(数据!$C$2:$C$197,"BHRG税前承保利润",数据!$D$2:$D$197,"2025H1")=0,"—",SUMIFS(数据!$E$2:$E$197,数据!$C$2:$C$197,"BHRG税前承保利润",数据!$D$2:$D$197,"2025H1")) -> 343 | C10: =IF(COUNTIFS(数据!$C$2:$C$197,"BHRG税前承保利润",数据!$D$2:$D$197,"2026H1")=0,"—",SUMIFS(数据!$E$2:$E$197,数据!$C$2:$C$197,"BHRG税前承保利润",数据!$D$2:$D$197,"2026H1")) -> 1286 | D10: =IF(OR(NOT(ISNUMBER(B10)),NOT(ISNUMBER(C10))),"—",C10-B10) -> 943 | E10: =IF(OR(NOT(ISNUMBER(B10)),NOT(ISNUMBER(C10)),B10<=0),"N/M",C10/B10-1) -> 2.7492711
A11: BNSF铁路营业收入 | B11: =IF(COUNTIFS(数据!$C$2:$C$197,"BNSF铁路营业收入",数据!$D$2:$D$197,"2025H1")=0,"—",SUMIFS(数据!$E$2:$E$197,数据!$C$2:$C$197,"BNSF铁路营业收入",数据!$D$2:$D$197,"2025H1")) -> 11402 | C11: =IF(COUNTIFS(数据!$C$2:$C$197,"BNSF铁路营业收入",数据!$D$2:$D$197,"2026H1")=0,"—",SUMIFS(数据!$E$2:$E$197,数据!$C$2:$C$197,"BNSF铁路营业收入",数据!$D$2:$D$197,"2026H1")) -> 12521 | D11: =IF(OR(NOT(ISNUMBER(B11)),NOT(ISNUMBER(C11))),"—",C11-B11) -> 1119 | E11: =IF(OR(NOT(ISNUMBER(B11)),NOT(ISNUMBER(C11)),B11<=0),"N/M",C11/B11-1) -> 0.098140677
A12: BNSF货运量 | B12: =IF(COUNTIFS(数据!$C$2:$C$197,"BNSF货运量",数据!$D$2:$D$197,"2025H1")=0,"—",SUMIFS(数据!$E$2:$E$197,数据!$C$2:$C$197,"BNSF货运量",数据!$D$2:$D$197,"2025H1")) -> 4684 | C12: =IF(COUNTIFS(数据!$C$2:$C$197,"BNSF货运量",数据!$D$2:$D$197,"2026H1")=0,"—",SUMIFS(数据!$E$2:$E$197,数据!$C$2:$C$197,"BNSF货运量",数据!$D$2:$D$197,"2026H1")) -> 4887 | D12: =IF(OR(NOT(ISNUMBER(B12)),NOT(ISNUMBER(C12))),"—",C12-B12) -> 203 | E12: =IF(OR(NOT(ISNUMBER(B12)),NOT(ISNUMBER(C12)),B12<=0),"N/M",C12/B12-1) -> 0.043339026
A13: BHE美国公用事业利润 | B13: =IF(COUNTIFS(数据!$C$2:$C$197,"BHE美国公用事业利润",数据!$D$2:$D$197,"2025H1")=0,"—",SUMIFS(数据!$E$2:$E$197,数据!$C$2:$C$197,"BHE美国公用事业利润",数据!$D$2:$D$197,"2025H1")) -> 862 | C13: =IF(COUNTIFS(数据!$C$2:$C$197,"BHE美国公用事业利润",数据!$D$2:$D$197,"2026H1")=0,"—",SUMIFS(数据!$E$2:$E$197,数据!$C$2:$C$197,"BHE美国公用事业利润",数据!$D$2:$D$197,"2026H1")) -> 956 | D13: =IF(OR(NOT(ISNUMBER(B13)),NOT(ISNUMBER(C13))),"—",C13-B13) -> 94 | E13: =IF(OR(NOT(ISNUMBER(B13)),NOT(ISNUMBER(C13)),B13<=0),"N/M",C13/B13-1) -> 0.10904872
A14: BHE天然气管道利润 | B14: =IF(COUNTIFS(数据!$C$2:$C$197,"BHE天然气管道利润",数据!$D$2:$D$197,"2025H1")=0,"—",SUMIFS(数据!$E$2:$E$197,数据!$C$2:$C$197,"BHE天然气管道利润",数据!$D$2:$D$197,"2025H1")) -> 671 | C14: =IF(COUNTIFS(数据!$C$2:$C$197,"BHE天然气管道利润",数据!$D$2:$D$197,"2026H1")=0,"—",SUMIFS(数据!$E$2:$E$197,数据!$C$2:$C$197,"BHE天然气管道利润",数据!$D$2:$D$197,"2026H1")) -> 848 | D14: =IF(OR(NOT(ISNUMBER(B14)),NOT(ISNUMBER(C14))),"—",C14-B14) -> 177 | E14: =IF(OR(NOT(ISNUMBER(B14)),NOT(ISNUMBER(C14)),B14<=0),"N/M",C14/B14-1) -> 0.26378539
A15: BHE其他能源利润 | B15: =IF(COUNTIFS(数据!$C$2:$C$197,"BHE其他能源利润",数据!$D$2:$D$197,"2025H1")=0,"—",SUMIFS(数据!$E$2:$E$197,数据!$C$2:$C$197,"BHE其他能源利润",数据!$D$2:$D$197,"2025H1")) -> 650 | C15: =IF(COUNTIFS(数据!$C$2:$C$197,"BHE其他能源利润",数据!$D$2:$D$197,"2026H1")=0,"—",SUMIFS(数据!$E$2:$E$197,数据!$C$2:$C$197,"BHE其他能源利润",数据!$D$2:$D$197,"2026H1")) -> 546 | D15: =IF(OR(NOT(ISNUMBER(B15)),NOT(ISNUMBER(C15))),"—",C15-B15) -> -104 | E15: =IF(OR(NOT(ISNUMBER(B15)),NOT(ISNUMBER(C15)),B15<=0),"N/M",C15/B15-1) -> -0.16
A16: BHE房地产经纪利润 | B16: =IF(COUNTIFS(数据!$C$2:$C$197,"BHE房地产经纪利润",数据!$D$2:$D$197,"2025H1")=0,"—",SUMIFS(数据!$E$2:$E$197,数据!$C$2:$C$197,"BHE房地产经纪利润",数据!$D$2:$D$197,"2025H1")) -> 30 | C16: =IF(COUNTIFS(数据!$C$2:$C$197,"BHE房地产经纪利润",数据!$D$2:$D$197,"2026H1")=0,"—",SUMIFS(数据!$E$2:$E$197,数据!$C$2:$C$197,"BHE房地产经纪利润",数据!$D$2:$D$197,"2026H1")) -> 8 | D16: =IF(OR(NOT(ISNUMBER(B16)),NOT(ISNUMBER(C16))),"—",C16-B16) -> -22 | E16: =IF(OR(NOT(ISNUMBER(B16)),NOT(ISNUMBER(C16)),B16<=0),"N/M",C16/B16-1) -> -0.73333333
A17: BHE公司利息及其他 | B17: =IF(COUNTIFS(数据!$C$2:$C$197,"BHE公司利息及其他",数据!$D$2:$D$197,"2025H1")=0,"—",SUMIFS(数据!$E$2:$E$197,数据!$C$2:$C$197,"BHE公司利息及其他",数据!$D$2:$D$197,"2025H1")) -> -411 | C17: =IF(COUNTIFS(数据!$C$2:$C$197,"BHE公司利息及其他",数据!$D$2:$D$197,"2026H1")=0,"—",SUMIFS(数据!$E$2:$E$197,数据!$C$2:$C$197,"BHE公司利息及其他",数据!$D$2:$D$197,"2026H1")) -> -353 | D17: =IF(OR(NOT(ISNUMBER(B17)),NOT(ISNUMBER(C17))),"—",C17-B17) -> 58 | E17: =IF(OR(NOT(ISNUMBER(B17)),NOT(ISNUMBER(C17)),B17<=0),"N/M",C17/B17-1) -> N/M | F17: 负数表示净损失；变化率因负基数标为N/M
A18: 工业产品税前利润 | B18: =IF(COUNTIFS(数据!$C$2:$C$197,"工业产品税前利润",数据!$D$2:$D$197,"2025H1")=0,"—",SUMIFS(数据!$E$2:$E$197,数据!$C$2:$C$197,"工业产品税前利润",数据!$D$2:$D$197,"2025H1")) -> 3409 | C18: =IF(COUNTIFS(数据!$C$2:$C$197,"工业产品税前利润",数据!$D$2:$D$197,"2026H1")=0,"—",SUMIFS(数据!$E$2:$E$197,数据!$C$2:$C$197,"工业产品税前利润",数据!$D$2:$D$197,"2026H1")) -> 4508 | D18: =IF(OR(NOT(ISNUMBER(B18)),NOT(ISNUMBER(C18))),"—",C18-B18) -> 1099 | E18: =IF(OR(NOT(ISNUMBER(B18)),NOT(ISNUMBER(C18)),B18<=0),"N/M",C18/B18-1) -> 0.32238193
A19: OxyChem营业收入 | B19: =IF(COUNTIFS(数据!$C$2:$C$197,"OxyChem营业收入",数据!$D$2:$D$197,"2025H1")=0,"—",SUMIFS(数据!$E$2:$E$197,数据!$C$2:$C$197,"OxyChem营业收入",数据!$D$2:$D$197,"2025H1")) -> — | C19: =IF(COUNTIFS(数据!$C$2:$C$197,"OxyChem营业收入",数据!$D$2:$D$197,"2026H1")=0,"—",SUMIFS(数据!$E$2:$E$197,数据!$C$2:$C$197,"OxyChem营业收入",数据!$D$2:$D$197,"2026H1")) -> 2600 | D19: =IF(OR(NOT(ISNUMBER(B19)),NOT(ISNUMBER(C19))),"—",C19-B19) -> — | E19: =IF(OR(NOT(ISNUMBER(B19)),NOT(ISNUMBER(C19)),B19<=0),"N/M",C19/B19-1) -> N/M | F19: 2026年1月2日起并表；上年同期无同口径数据
A20: OxyChem税前利润 | B20: =IF(COUNTIFS(数据!$C$2:$C$197,"OxyChem税前利润",数据!$D$2:$D$197,"2025H1")=0,"—",SUMIFS(数据!$E$2:$E$197,数据!$C$2:$C$197,"OxyChem税前利润",数据!$D$2:$D$197,"2025H1")) -> — | C20: =IF(COUNTIFS(数据!$C$2:$C$197,"OxyChem税前利润",数据!$D$2:$D$197,"2026H1")=0,"—",SUMIFS(数据!$E$2:$E$197,数据!$C$2:$C$197,"OxyChem税前利润",数据!$D$2:$D$197,"2026H1")) -> 121 | D20: =IF(OR(NOT(ISNUMBER(B20)),NOT(ISNUMBER(C20))),"—",C20-B20) -> — | E20: =IF(OR(NOT(ISNUMBER(B20)),NOT(ISNUMBER(C20)),B20<=0),"N/M",C20/B20-1) -> N/M | F20: 2026年1月2日起并表；上年同期无同口径数据
A22: OxyChem收购对价（约数） | C22: =IF(COUNTIFS(数据!$C$2:$C$197,"OxyChem收购对价（约数）",数据!$D$2:$D$197,"2026H1")=0,0,SUMIFS(数据!$E$2:$E$197,数据!$C$2:$C$197,"OxyChem收购对价（约数）",数据!$D$2:$D$197,"2026H1")) -> 9500
A23: GEICO需要同时看已赚保费、赔付率和费用率；BHE分部明细为归属BHE口径，房地产及优先股调节后才到归属伯克希尔股东利润。OxyChem收购对价约95亿美元，可按协议调整。

Sheet 变化
A1: 变化｜同比、占比与图表
A2: 利润按可比期间同比；存量指标2026H1与2025年末比较；比例仅在有经济意义时计算。
A4: ① 2026年上半年核心经营利润：同比与占比
A5: 指标 | B5: 2025H1 | C5: 2026H1 | D5: 变化额 | E5: 同比 | F5: 2025H1占比 | G5: 2026H1占比 | H5: 读法
A6: 保险承保利润 | B6: =分部利润!$G5 -> 3328 | C6: =分部利润!$H5 -> 3448 | D6: =C6-B6 -> 120 | E6: =IF(B6=0,"N/M",C6/B6-1) -> 0.036057692 | F6: =B6/B$11 -> 0.16055577 | G6: =C6/C$11 -> 0.15820142 | H6: GEICO承压，再保险与Primary改善
A7: 保险投资收益 | B7: =分部利润!$G6 -> 6260 | C7: =分部利润!$H6 -> 5738 | D7: =C7-B7 -> -522 | E7: =IF(B7=0,"N/M",C7/B7-1) -> -0.083386581 | F7: =B7/B$11 -> 0.30200695 | G7: =C7/C$11 -> 0.26327139 | H7: 短端利率下降
A8: 铁路（BNSF）利润 | B8: =分部利润!$G7 -> 2680 | C8: =分部利润!$H7 -> 2935 | D8: =C8-B8 -> 255 | E8: =IF(B8=0,"N/M",C8/B8-1) -> 0.095149254 | F8: =B8/B$11 -> 0.12929371 | G8: =C8/C$11 -> 0.13466391 | H8: 运量与效率改善
A9: 能源（BHE）利润 | B9: =分部利润!$G8 -> 1799 | C9: =分部利润!$H8 -> 2005 | D9: =C9-B9 -> 206 | E9: =IF(B9=0,"N/M",C9/B9-1) -> 0.11450806 | F9: =B9/B$11 -> 0.086790814 | G9: =C9/C$11 -> 0.091993577 | H9: 公用事业与管道推动
A10: 制造、服务及零售利润 | B10: =分部利润!$G9 -> 6661 | C10: =分部利润!$H9 -> 7669 | D10: =C10-B10 -> 1008 | E10: =IF(B10=0,"N/M",C10/B10-1) -> 0.15132863 | F10: =B10/B$11 -> 0.32135276 | G10: =C10/C$11 -> 0.35186969 | H10: 工业与服务推动，含并购影响
A11: 核心五项合计 | B11: =SUM(B6:B10) -> 20728 | C11: =SUM(C6:C10) -> 21795 | D11: =C11-B11 -> 1067 | E11: =C11/B11-1 -> 0.051476264 | F11: =SUM(F6:F10) -> 1 | G11: =SUM(G6:G10) -> 1 | H11: 合计增长5.1%；不要把Other的汇率收益当作核心经营改善
A14: ② 2025年核心经营利润：同比与占比
A15: 指标 | B15: 2024年 | C15: 2025年 | D15: 变化额 | E15: 同比 | F15: 2024占比 | G15: 2025占比 | H15: 读法
A16: 保险承保利润 | B16: =分部利润!$E5 -> 9020 | C16: =分部利润!$F5 -> 7258 | D16: =C16-B16 -> -1762 | E16: =C16/B16-1 -> -0.19534368 | F16: =B16/B$21 -> 0.20259192 | G16: =C16/C$21 -> 0.1692907 | H16: 承保利润回落
A17: 保险投资收益 | B17: =分部利润!$E6 -> 13670 | C17: =分部利润!$F6 -> 12513 | D17: =C17-B17 -> -1157 | E17: =C17/B17-1 -> -0.084637893 | F17: =B17/B$21 -> 0.30703232 | G17: =C17/C$21 -> 0.29186201 | H17: 利息及股息下降
A18: 铁路（BNSF）利润 | B18: =分部利润!$E7 -> 5031 | C18: =分部利润!$F7 -> 5476 | D18: =C18-B18 -> 445 | E18: =C18/B18-1 -> 0.0884516 | F18: =B18/B$21 -> 0.11299778 | G18: =C18/C$21 -> 0.12772607 | H18: 成本效率改善
A19: 能源（BHE）利润 | B19: =分部利润!$E8 -> 3730 | C19: =分部利润!$F8 -> 3979 | D19: =C19-B19 -> 249 | E19: =C19/B19-1 -> 0.066756032 | F19: =B19/B$21 -> 0.083776924 | G19: =C19/C$21 -> 0.092808994 | H19: 野火计提压力缓和
A20: 制造、服务及零售利润 | B20: =分部利润!$E9 -> 13072 | C20: =分部利润!$F9 -> 13647 | D20: =C20-B20 -> 575 | E20: =C20/B20-1 -> 0.043987148 | F20: =B20/B$21 -> 0.29360106 | G20: =C20/C$21 -> 0.31831222 | H20: 制造与服务增长、零售偏弱
A21: 核心五项合计 | B21: =SUM(B16:B20) -> 44523 | C21: =SUM(C16:C20) -> 42873 | D21: =C21-B21 -> -1650 | E21: =C21/B21-1 -> -0.037059497 | F21: =SUM(F16:F20) -> 1 | G21: =SUM(G16:G20) -> 1
A23: ③ 股票组合：行业同比、占比与2026H1变化
A24: 行业 | B24: 2024年末 | C24: 2025年末 | D24: 2025同比 | E24: 2025占比 | F24: 2026H1 | G24: 较2025年末 | H24: 2026H1占比
A25: 银行、保险及金融 | B25: =股票组合!$E5 -> 91643 | C25: =股票组合!$F5 -> 104129 | D25: =C25/B25-1 -> 0.13624609 | E25: =C25/C$28 -> 0.34968668 | F25: =股票组合!$G5 -> 94477 | G25: =F25/C25-1 -> -0.092692718 | H25: =F25/F$28 -> 0.29179471
A26: 消费品 | B26: =股票组合!$E6 -> 104749 | C26: =股票组合!$F6 -> 94954 | D26: =C26/B26-1 -> -0.093509246 | E26: =C26/C$28 -> 0.31887514 | F26: =股票组合!$G6 -> 100486 | G26: =F26/C26-1 -> 0.058259789 | H26: =F26/F$28 -> 0.31035367
A27: 商业、工业及其他 | B27: =股票组合!$E7 -> 75196 | C27: =股票组合!$F7 -> 98695 | D27: =C27/B27-1 -> 0.31250332 | E27: =C27/C$28 -> 0.33143819 | F27: =股票组合!$G7 -> 128816 | G27: =F27/C27-1 -> 0.30519277 | H27: =F27/F$28 -> 0.39785162
A28: 合计 | B28: =SUM(B25:B27) -> 271588 | C28: =SUM(C25:C27) -> 297778 | D28: =C28/B28-1 -> 0.096432832 | E28: =SUM(E25:E27) -> 1 | F28: =SUM(F25:F27) -> 323779 | G28: =F28/C28-1 -> 0.087316726 | H28: =SUM(H25:H27) -> 1
A31: ④ 关键账面与资本配置指标
A32: 指标 | B32: 2024 | C32: 2025 | D32: 2025变化额 | E32: 2025同比 | F32: 2026H1 | G32: H1比较变化额* | H32: 比较口径
A33: 保险浮存金 | B33: =资产负债!$E5 -> 171000 | C33: =资产负债!$F5 -> 176000 | D33: =C33-B33 -> 5000 | E33: =IF(B33=0,"N/M",C33/B33-1) -> 0.029239766 | F33: =资产负债!$G5 -> 177500 | G33: =F33-C33 -> 1500 | H33: 2026H1末 vs 2025年末
A34: 现金及短期国债 | B34: =资产负债!$E9 -> 334201 | C34: =资产负债!$F9 -> 373311 | D34: =C34-B34 -> 39110 | E34: =IF(B34=0,"N/M",C34/B34-1) -> 0.11702538 | F34: =资产负债!$G9 -> 365514 | G34: =F34-C34 -> -7797 | H34: 2026H1末 vs 2025年末
A35: 股票组合合计（披露） | B35: =资产负债!$E10 -> 271588 | C35: =资产负债!$F10 -> 297778 | D35: =C35-B35 -> 26190 | E35: =IF(B35=0,"N/M",C35/B35-1) -> 0.096432832 | F35: =资产负债!$G10 -> 323779 | G35: =F35-C35 -> 26001 | H35: 2026H1末 vs 2025年末
A36: A类每股账面价值 | B36: =资产负债!$E13 -> 451507.17 | C36: =资产负债!$F13 -> 498823.2 | D36: =C36-B36 -> 47316.028 | E36: =IF(B36=0,"N/M",C36/B36-1) -> 0.10479574 | F36: =资产负债!$G13 -> 522395.51 | G36: =F36-C36 -> 23572.313 | H36: 2026H1末 vs 2025年末
A37: 回购金额（现金流量表） | B37: =资产负债!$E17 -> 2918 | C37: =资产负债!$F17 -> 0 | D37: =C37-B37 -> -2918 | E37: =IF(B37=0,"N/M",C37/B37-1) -> -1 | F37: =资产负债!$G17 -> 4444 | G37: =F37-SUMIFS(数据!$E$2:$E$197,数据!$C$2:$C$197,"回购金额（现金流量表）",数据!$D$2:$D$197,"2025H1") -> 4444 | H37: 2026H1 vs 2025H1（流量）
A38: 股票净购买 | B38: =资产负债!$E21 -> -134122 | C38: =资产负债!$F21 -> -13763 | D38: =C38-B38 -> 120359 | E38: =IF(B38=0,"N/M",C38/B38-1) -> -0.89738447 | F38: =资产负债!$G21 -> 11625 | G38: =F38-(SUMIFS(数据!$E$2:$E$197,数据!$C$2:$C$197,"购买股票（现金流）",数据!$D$2:$D$197,"2025H1")-SUMIFS(数据!$E$2:$E$197,数据!$C$2:$C$197,"出售股票（现金流）",数据!$D$2:$D$197,"2025H1")) -> 16125 | H38: 2026H1 vs 2025H1（流量）
A40: * 浮存金为约数，2026H1与2025年末差额受四舍五入影响；季报自身披露增加约11亿美元。回购和股票净购买是流量，使用上半年同比；其余为期末存量或每股指标。现金及短期国债不是“可自由分配现金”，其中包含支持保险与极端情景所需资金。
A43: ⑤ 假设联动的简化情景（不是预测）
A44: 2026全年核心五项利润情景 | B44: =假设!$G12 -> 43940 | C44: 修改『假设』B3自动更新
A45: 2026年末现金及短期国债情景 | B45: =假设!$B17 -> 365514 | C45: 修改『假设』B4自动更新

Sheet 假设
A1: 可修改假设｜2026全年简化情景
A2: 橙色为假设输入；蓝色为公式。仅作敏感性演示，不是预测，也不是投资建议。
A3: 假设：2026H2核心五项利润较2025H2变动 | B3: 0
A4: 假设：2026H2现金及短期国债净变动（百万美元） | B4: 0
A6: 指标 | B6: 2025全年 | C6: 2025H1 | D6: 2025H2 | E6: 2026H1 | F6: 2026H2情景 | G6: 2026全年情景
A7: 保险承保利润 | B7: =分部利润!$F5 -> 7258 | C7: =分部利润!$G5 -> 3328 | D7: =B7-C7 -> 3930 | E7: =分部利润!$H5 -> 3448 | F7: =D7*(1+$B$3) -> 3930 | G7: =E7+F7 -> 7378
A8: 保险投资收益 | B8: =分部利润!$F6 -> 12513 | C8: =分部利润!$G6 -> 6260 | D8: =B8-C8 -> 6253 | E8: =分部利润!$H6 -> 5738 | F8: =D8*(1+$B$3) -> 6253 | G8: =E8+F8 -> 11991
A9: 铁路（BNSF）利润 | B9: =分部利润!$F7 -> 5476 | C9: =分部利润!$G7 -> 2680 | D9: =B9-C9 -> 2796 | E9: =分部利润!$H7 -> 2935 | F9: =D9*(1+$B$3) -> 2796 | G9: =E9+F9 -> 5731
A10: 能源（BHE）利润 | B10: =分部利润!$F8 -> 3979 | C10: =分部利润!$G8 -> 1799 | D10: =B10-C10 -> 2180 | E10: =分部利润!$H8 -> 2005 | F10: =D10*(1+$B$3) -> 2180 | G10: =E10+F10 -> 4185
A11: 制造、服务及零售利润 | B11: =分部利润!$F9 -> 13647 | C11: =分部利润!$G9 -> 6661 | D11: =B11-C11 -> 6986 | E11: =分部利润!$H9 -> 7669 | F11: =D11*(1+$B$3) -> 6986 | G11: =E11+F11 -> 14655
A12: 核心五项经营利润合计 | B12: =SUM(B7:B11) -> 42873 | C12: =SUM(C7:C11) -> 20728 | D12: =SUM(D7:D11) -> 22145 | E12: =SUM(E7:E11) -> 21795 | F12: =SUM(F7:F11) -> 22145 | G12: =SUM(G7:G11) -> 43940
A14: 流动性情景
A15: 2026H1现金及短期国债 | B15: =资产负债!$G9 -> 365514
A16: 2026H2净变动（链接假设） | B16: =$B$4 -> 0
A17: 2026年末现金及短期国债情景 | B17: =B15+B16 -> 365514
A19: 方法：2025H2＝2025全年－2025H1；2026H2情景＝2025H2×（1＋假设变动率）；2026全年情景＝2026H1实际＋2026H2情景。未建模并购、投资损益、税项、汇率或股数变化，不能把结果理解为业绩预测。

Sheet 游戏脚本
A1: 和巴菲特一起做决定｜网页脚本与数字镜像
A2: 10个真实历史决策；每段英文引文不超过两句。契合度衡量思路，不代表事后结果正确；不涉及当前买卖建议。
A4: 题号 | B4: 决策年份 | C4: 标题 | D4: 当时处境 | E4: 选项与契合分 | F4: 实际做法 | G4: 为什么 | H4: 股东信原文 | I4: 引文年份 | J4: 出处 | K4: 本题要点
A5: 1 | B5: 1972 | C5: 一颗糖果，值多少经济商誉？ | D5: 1972年，喜诗糖果年销售约3000万美元、税前利润不足500万美元，经营所需资本约800万美元。卖方要价3000万美元，而你坚持不超过2500万美元。行业增长并不快，你会怎么做？ | E5: 1. 只按有形资产砍价（契合45；商业质量55、价格纪律90、风险边界65、长期耐心40）：无形资产难以丈量，价格必须贴近可辨认资产。 2. 不超过2500万美元买下（契合100；商业质量95、价格纪律90、风险边界85、长期耐心100）：为持久品牌与定价权付费，同时守住价格上限。 3. 行业不增长，直接放弃（契合30；商业质量40、价格纪律70、风险边界55、长期耐心25）：只有高销量增长才值得投入资本。 | F5: 通过Blue Chip Stamps以2500万美元买入喜诗。卖方最终接受了这一上限；巴菲特后来承认，自己险些因价格坚持而错失它。 | G5: 关键不是糖果销量能否高速增长，而是品牌带来的定价权，以及利润增长时是否需要同比例追加资本。这是从“便宜资产”走向“优质企业”的重要一课。 | H5: We bought See’s for $25 million when its sales were $30 million and pre-tax earnings were less than $5 million. The capital then required to conduct the business was $8 million. | I5: 2007 | J5: 材料/股东信/2007ltr.pdf，Dream Businesses / See’s Candy段 | K5: 经济商誉：持久的定价权 + 较低的增量资本需求。
A6: 2 | B6: 1983 | C6: 买店，还是买下这支管理团队？ | D6: 1983年，Rose Blumkin家族经营的一家约20万平方英尺门店，年销售已超过1亿美元。创始人已90岁，成本低、顾客价值突出，家族希望解决所有权传承。你会如何安排交易？ | E6: 1. 买90%，家族继续经营（契合100；商业质量100、价格纪律80、风险边界90、长期耐心100）：保留家族10%，并向关键年轻家族经理授予另外10%的选择权。 2. 买100%，总部接管（契合35；商业质量45、价格纪律65、风险边界40、长期耐心35）：获得完整控制权，再派新团队替换原有管理层。 3. 创始人高龄，放弃（契合25；商业质量35、价格纪律55、风险边界60、长期耐心20）：把年龄当作否决项，不评估团队与企业文化。 | F6: 收购90%，给经营家族保留10%，并向关键年轻家族经理授予另外10%的选择权；Blumkin家族继续管理。 | G6: 巴菲特买下的不仅是门店，更是难以复制的低价运营能力、顾客信任和经营者文化。交易结构让原来的主人仍然有动力继续创造价值。 | H6: One question I always ask myself in appraising a business is how I would like, assuming I had ample capital and skilled personnel, to compete with it. I’d rather wrestle grizzlies than compete with Mrs. B and her progeny. | I6: 1983 | J6: 材料/股东信/1983ltr.html，Nebraska Furniture Mart段 | K6: 优秀企业的价值，常常写在“谁在读懂顾客、谁在长期经营”里。
A7: 3 | B7: 1988 | C7: 看了五十年，终于看见什么？ | D7: 1988年，这种饮料你早已熟悉数十年。1981年后新管理层重新聚焦经营，海外销售加速；但企业的优点也并非无人知晓。你会如何决策？ | E7: 1. 只因市场都知道，继续等待（契合45；商业质量65、价格纪律80、风险边界65、长期耐心55）：人尽皆知的优点不可能形成可投框架。 2. 做短线，先赚预期差（契合25；商业质量40、价格纪律45、风险边界35、长期耐心10）：以季度消息决定进出，不准备长期持有。 3. 理解焕新后的企业，开始买入（契合100；商业质量100、价格纪律75、风险边界80、长期耐心100）：看见产品优势与管理层执行形成合力，以长期企业所有者方式行动。 | F7: 1988年夏开始买入，年末持有14,172,500股；1989年继续增至23,350,000股，1989年末披露成本约10.239亿美元。 | G7: 重要的不是“从未听过这家公司”，而是何时真正理解产品与管理层组合的经济意义。巴菲特在信中还自嘲，自己本可以更早想明白。 | H7: What I then perceived was both clear and fascinating. After drifting somewhat in the 1970's, Coca-Cola had in 1981 become a new company with the move of Roberto Goizueta to CEO. | I7: 1989 | J7: 材料/股东信/1989ltr.html，Common Stocks / Coca-Cola段 | K7: 认知到位比动作新奇更重要；熟悉不等于理解。
A8: 4 | B8: 1993 | C8: 好公司，可以用股票随便换吗？ | D8: 1993年，Dexter管理优秀，年产超过750万双鞋；但美国鞋业正面对低工资地区进口竞争。卖方不想要现金，更希望换得伯克希尔股票。你会怎么做？ | E8: 1. 完全拒绝研究这个行业（契合40；商业质量45、价格纪律70、风险边界80、长期耐心45）：进口压力已经说明一切，不需要评估具体企业。 2. 坚持用现金，否则不做（契合65；商业质量70、价格纪律85、风险边界90、长期耐心65）：避免交出伯克希尔的股权，把支付货币当作风险边界。 3. 发行25,203股A股收购（契合100；商业质量70、价格纪律35、风险边界35、长期耐心85）：按当时披露约4.33亿美元，以伯克希尔股票完成交易。 | F8: 发行25,203股伯克希尔A股收购，披露成本约4.33亿美元。后来Dexter竞争优势消失，巴菲特把这笔交易称为当时最糟糕的交易。 | G8: 这一题故意保留“契合不等于正确”：管理层优秀不等于竞争优势持久；用本身很优质的股票支付，又放大了误判的代价。 | H8: Finally, I made an even worse mistake when I said “yes” to Dexter, a shoe business I bought in 1993 for $433 million in Berkshire stock (25,203 shares of A). What I had assessed as durable competitive advantage vanished within a few years. | I8: 2007 | J8: 材料/股东信/2007ltr.pdf，Acquisition Mistakes / Dexter段 | K8: 既要问“得到的值多少”，也要问“交出去的到底值多少”。
A9: 5 | B9: 1995 | C9: 已经持有一半，还要买下其余吗？ | D9: 1995年，伯克希尔已持有GEICO约51%。这家汽车保险公司以低成本运营形成低价格、留住客户、再降低获客费用的循环；剩余49%需要约23亿美元。你会怎么做？ | E9: 1. 收购剩余49%（契合100；商业质量100、价格纪律80、风险边界85、长期耐心100）：把已理解多年的低成本优势完整纳入保险主业。 2. 维持51%，不再投入（契合45；商业质量65、价格纪律75、风险边界65、长期耐心55）：已经控制，额外持股不会增加经济价值。 3. 卖掉原有持股（契合25；商业质量30、价格纪律40、风险边界50、长期耐心15）：保险利润有波动，因此不再承担承保风险。 | F9: 同意以约23亿美元收购剩余49%，交易于1996年1月2日完成，GEICO成为全资子公司。 | G9: 低成本不是静态标签，而是能自我强化的经营系统。长期跟踪降低了理解企业的难度，全资持有也让伯克希尔完整获得浮存金与经营成果。 | H9: GEICO's sustainable cost advantage is what attracted me to the company way back in 1951, when the entire business was valued at $7 million. It is also why I felt Berkshire should pay $2.3 billion last year for the 49% of the company that we didn't then own. | I9: 1996 | J9: 材料/股东信/1996ltr.html，Insurance—GEICO and Other Primary Operations | K9: 低成本飞轮：成本、价格、客户留存与获客费用彼此强化。
A10: 6 | B10: 2006 | C10: 一封短笺，能不能通向跨国收购？ | D10: 2005年，你收到一封约1.25页的介绍信：一家在61个国家经营的切削工具家族企业正在考虑传承。你从未收购过美国以外的企业，管理层看起来非常出色。下一步怎么做？ | E10: 1. 不熟的地域一律回避（契合35；商业质量45、价格纪律60、风险边界75、长期耐心40）：不把学习税务、法律与商业环境列入流程。 2. 研究后买80%，家族留20%（契合100；商业质量100、价格纪律80、风险边界90、长期耐心100）：先补齐跨国知识，再以约40亿美元收购并保留经营团队。 3. 买100%并迅速整合（契合40；商业质量50、价格纪律65、风险边界45、长期耐心40）：消除家族影响，用统一总部流程改造企业。 | F10: 先学习税务和司法管辖事项，再于2006年7月5日以约40亿美元收购Iscar 80%；Wertheimer家族保留20%并继续经营。 | G10: 能力圈可以通过学习拓展，而不是靠跳过尽调拓展。小型耗材帮助昂贵机床提高生产率，客户越成功，企业自身也越有价值。 | H10: The result: ISCAR makes money because it enables its customers to make more money. There is no better recipe for continued success. | I10: 2006 | J10: 材料/股东信/2006ltr.pdf，Acquisitions / ISCAR段 | K10: 好产品让客户更赚钱；好交易让原团队愿意继续留下。
A11: 7 | B11: 2008 | C11: 风暴中，现金要不要上场？ | D11: 2008年金融市场承压， Wrigley、Goldman Sachs与General Electric能提供高当前收益率的固定收益工具，并附带额外股权参与。你拥有充足现金，但未来仍充满不确定性。 | E11: 1. 全部现金，不做任何承诺（契合55；商业质量55、价格纪律80、风险边界95、长期耐心70）：只要环境不确定，就把等待本身当作唯一答案。 2. 借款放大这类机会（契合10；商业质量45、价格纪律30、风险边界0、长期耐心20）：收益率已经很高，再加杠杆追求更大结果。 3. 投入145亿美元，仍保留充裕现金（契合100；商业质量85、价格纪律95、风险边界100、长期耐心90）：要求高当前收益率与股权参与，同时不以牺牲流动性为代价。 | F11: 2008年合计投入145亿美元购买Wrigley、Goldman Sachs和General Electric的固定收益工具，并获得额外股权参与；同时坚持保留充裕现金。 | G11: 危机本身不是行动理由，条款才是。高当前收益率提供基础回报，股权参与提供额外可能，而流动性底线避免把明天寄托于外部融资。 | H11: On the plus side last year, we made purchases totaling $14.5 billion in fixed-income securities issued by Wrigley, Goldman Sachs and General Electric. We very much like these commitments, which carry high current yields that, in themselves, make the investments more than satisfactory. | I11: 2008 | J11: 材料/股东信/2008ltr.pdf，Investments段 | K11: 既利用机会，也不拿一夜安眠去换额外利润。
A12: 8 | B12: 2009 | C12: 一列火车，值得交出股票吗？ | D12: 2009年，你考虑以每股100美元收购BNSF。铁路服务长期必需，但需要持续巨额资本投入；交易若全用股票会稀释伯克希尔，若全用现金又会压缩机动空间。 | E12: 1. 混合支付，限制股票比例（契合100；商业质量95、价格纪律85、风险边界90、长期耐心100）：部署约220亿美元现金，整体约30%成本用股票支付，并保留长期经营团队。 2. 全部用股票，现金一分不动（契合30；商业质量65、价格纪律20、风险边界55、长期耐心70）：把股票价格当作唯一成本，不考虑交出企业的内在价值。 3. 资本密集，坚决不碰（契合40；商业质量45、价格纪律60、风险边界75、长期耐心45）：任何需要持续再投资的企业都不值得研究。 | F12: 按每股100美元推进收购，整体约30%成本以伯克希尔股票支付，并部署约220亿美元现金；交易于2010年完成，Matt Rose团队继续经营。 | G12: 巴菲特并不喜欢发股，因此必须衡量换来的长期盈利与额外再投资机会是否足以抵消稀释。他明确说，如果需要使用更多股票，交易就不成立。 | H12: In the end, Charlie and I decided that the disadvantage of paying 30% of the price through stock was offset by the opportunity the acquisition gave us to deploy $22 billion of cash in a business we understood and liked for the long term. It has the additional virtue of being run by Matt Rose, whom we trust and admire. | I12: 2009 | J12: 材料/股东信/2009ltr.pdf，An Inconvenient Truth (Boardroom Overheating) | K12: 支付工具也是交易价格的一部分；资本密集不等于没有合理回报。
A13: 9 | B13: 2015 | C13: 精密零件，怎样变成长期现金机器？ | D13: 2015年，Precision Castparts是航空零部件供应商，许多产品来自多年合同。CEO Mark Donegan把普通原材料变成高附加值组件；收购需要逾320亿美元现金。 | E13: 1. 收购后由总部接管（契合35；商业质量55、价格纪律65、风险边界40、长期耐心35）：支付价格后，用集中管控取代原有管理层。 2. 航空业有周期，直接放弃（契合40；商业质量45、价格纪律60、风险边界70、长期耐心40）：不评估产品关键性、合同与管理者，只看行业标签。 3. 逾320亿美元现金收购并留任团队（契合100；商业质量100、价格纪律75、风险边界85、长期耐心100）：认可关键组件与经理人的组合，让Donegan继续配置经营资本。 | F13: 2015年宣布、2016年1月完成，以逾320亿美元现金收购PCC；Mark Donegan继续领导，并可利用伯克希尔资本进行后续收购。 | G13: 产品虽小，却是大型飞机的关键组件；多年合同、制造能力与经理人共同构成经营质量。伯克希尔的角色不是接管日常经营，而是提供长期资本与自主空间。 | H13: Under CEO Mark Donegan, PCC has become the world’s premier supplier of aerospace components (most of them destined to be original equipment, though spares are important to the company as well). Mark’s accomplishments remind me of the magic regularly performed by Jacob Harpaz at IMC, our remarkable Israeli manufacturer of cutting tools. | I13: 2015 | J13: 材料/股东信/2015ltr.pdf，Precision Castparts段 | K13: 关键组件 + 优秀经理人 + 不轻易干预，是伯克希尔式收购组合。
A14: 10 | B14: 2020 | C14: 没有大收购，资本还能去哪？ | D14: 2020年，伯克希尔没有完成大型收购，经营利润下降9%。管理层认为公司股票低于保守估计的内在价值，同时希望保留足以应对机会与问题的资金。你会怎么做？ | E14: 1. 只要现金多就持续回购（契合35；商业质量45、价格纪律10、风险边界55、长期耐心55）：无需考虑价格，回购本身总能创造价值。 2. 满足两个条件才回购（契合100；商业质量85、价格纪律100、风险边界100、长期耐心95）：提升持续股东的每股内在价值，并在回购后仍保留充裕资金。 3. 为维持股价而借款回购（契合5；商业质量20、价格纪律15、风险边界0、长期耐心10）：把短期市场反应置于财务韧性之上。 | F14: 2020年回购80,998股A类等价股，耗资247亿美元；持续股东对伯克希尔各项业务的持股比例因此提高5.2%。 | G14: 回购不是天然正确：价格必须低于保守内在价值，且不能耗尽应对风险与机会的资金。对持续股东而言，重点是每股所代表的企业权益是否增加。 | H14: Last year we demonstrated our enthusiasm for Berkshire’s spread of properties by repurchasing the equivalent of 80,998 “A” shares, spending $24.7 billion in the process. That action increased your ownership in all of Berkshire’s businesses by 5.2% without requiring you to so much as touch your wallet. | I14: 2020 | J14: 材料/股东信/2020ltr.pdf，Share Repurchases段 | K14: 回购的两道门：每股价值提升 + 回购后仍有充裕资金。

Sheet 出处
A1: 来源登记｜文件、章节、网页与访问日期
A2: 2022、2023官方年报用于补齐历史序列；下载件保留于交付/来源。网页出处只在Excel/README列示，游戏网页不放外部链接。
A4: 来源编号 | B4: 文件名 | C4: 章节或表名 | D4: 网页链接（如有） | E4: 访问日期
A5: AR25_MD | B5: 材料/Berkshire_2025年报__brka-20251231.htm | C5: Item 7, MD&A—Results of Operations（K-34起） | D5: — | E5: 原始材料
A6: AR25_BS | B6: 材料/Berkshire_2025年报__brka-20251231.htm | C6: Consolidated Balance Sheets（K-66） | D6: — | E6: 原始材料
A7: AR25_CF | B7: 材料/Berkshire_2025年报__brka-20251231.htm | C7: Consolidated Statements of Cash Flows（K-70） | D7: — | E7: 原始材料
A8: AR25_SE | B8: 材料/Berkshire_2025年报__brka-20251231.htm | C8: Consolidated Statements of Changes in Shareholders’ Equity（K-69） | D8: — | E8: 原始材料
A9: AR25_EQ | B9: 材料/Berkshire_2025年报__brka-20251231.htm | C9: Notes—Common stock（K-101至K-102） | D9: — | E9: 原始材料
A10: AR25_PORT | B10: 材料/Berkshire_2025年报__brka-20251231.htm | C10: Note 4—Investments in equity securities（K-79） | D10: — | E10: 原始材料
A11: AR25_FLOAT | B11: 材料/Berkshire_2025年报__brka-20251231.htm | C11: Item 7—Insurance—Investment Income（K-40） | D11: — | E11: 原始材料
A12: AR25_ACQ | B12: 材料/Berkshire_2025年报__brka-20251231.htm | C12: Note 2—Business acquisitions（K-77至K-78） | D12: — | E12: 原始材料
A13: Q226_MD | B13: 材料/Berkshire_2026Q2季报__brka-20260630.htm | C13: Item 2, MD&A—Results of Operations（第33页） | D13: — | E13: 原始材料
A14: Q226_BS | B14: 材料/Berkshire_2026Q2季报__brka-20260630.htm | C14: Consolidated Balance Sheets（第2至3页） | D14: — | E14: 原始材料
A15: Q226_CF | B15: 材料/Berkshire_2026Q2季报__brka-20260630.htm | C15: Consolidated Statements of Cash Flows（第7页） | D15: — | E15: 原始材料
... A31: LETTER25 | B31: 材料/股东信/2025ltr.pdf | C31: Greg Abel首封年度股东信—文化、资本配置与业务讨论 | D31: — | E31: 原始材料

Sheet 校验
A1: 自动校验｜公式、对账与来源完整性
A2: 所有检查项应为0；总状态为PASS才通过。另在外部用LibreOffice重算并扫描错误值。
A4: 检查项 | B4: 结果 | C4: 目标 | D4: 说明
A5: 归母净利润对账｜2021年 | B5: =分部利润!$B16 -> 0 | C5: 0 | D5: 公司经营利润＋投资损益＋权益法投资减值＝归母净利润
A6: 归母净利润对账｜2022年 | B6: =分部利润!$C16 -> 0 | C6: 0 | D6: 公司经营利润＋投资损益＋权益法投资减值＝归母净利润
A7: 归母净利润对账｜2023年 | B7: =分部利润!$D16 -> 0 | C7: 0 | D7: 公司经营利润＋投资损益＋权益法投资减值＝归母净利润
A8: 归母净利润对账｜2024年 | B8: =分部利润!$E16 -> 0 | C8: 0 | D8: 公司经营利润＋投资损益＋权益法投资减值＝归母净利润
A9: 归母净利润对账｜2025年 | B9: =分部利润!$F16 -> 0 | C9: 0 | D9: 公司经营利润＋投资损益＋权益法投资减值＝归母净利润
A10: 归母净利润对账｜2025年上半年 | B10: =分部利润!$G16 -> 0 | C10: 0 | D10: 公司经营利润＋投资损益＋权益法投资减值＝归母净利润
A11: 归母净利润对账｜2026年上半年 | B11: =分部利润!$H16 -> 0 | C11: 0 | D11: 公司经营利润＋投资损益＋权益法投资减值＝归母净利润
A12: 股票行业合计对账｜2021年 | B12: =股票组合!$B10 -> 0 | C12: 0 | D12: 三行业之和＝披露合计
A13: 股票行业合计对账｜2022年 | B13: =股票组合!$C10 -> 0 | C13: 0 | D13: 三行业之和＝披露合计
A14: 股票行业合计对账｜2023年 | B14: =股票组合!$D10 -> 0 | C14: 0 | D14: 三行业之和＝披露合计
A15: 股票行业合计对账｜2024年 | B15: =股票组合!$E10 -> 0 | C15: 0 | D15: 三行业之和＝披露合计
A16: 股票行业合计对账｜2025年 | B16: =股票组合!$F10 -> 0 | C16: 0 | D16: 三行业之和＝披露合计
A17: 股票行业合计对账｜2026年上半年 | B17: =股票组合!$G10 -> 0 | C17: 0 | D17: 三行业之和＝披露合计
A18: 数据键重复数 | B18: =SUMPRODUCT((COUNTIFS(数据!$C$2:$C$197,数据!$C$2:$C$197,数据!$D$2:$D$197,数据!$D$2:$D$197)>1)*1) -> 0 | C18: 0 | D18: 指标＋期间应唯一
A19: 来源编号空白数 | B19: =COUNTBLANK(数据!$G$2:$G$197) -> 0 | C19: 0 | D19: 每个原始数值必须有来源编号
A20: 分部利润公式错误数 | B20: =SUMPRODUCT(--ISERROR(分部利润!B5:H18)) -> 0 | C20: 0 | D20: 不得出现#REF!、#DIV/0!、#VALUE!等
A21: 资产负债公式错误数 | B21: =SUMPRODUCT(--ISERROR(资产负债!B5:G21)) -> 0 | C21: 0 | D21: 不得出现公式错误值
A22: 变化页公式错误数 | B22: =SUMPRODUCT(--ISERROR(变化!B6:H45)) -> 0 | C22: 0 | D22: 不得出现公式错误值
A23: 总状态 | B23: =IF(SUM(B5:B22)=0,"PASS","CHECK") -> PASS | C23: PASS表示当前工作簿内对账及结构检查通过
