Workbook

Sheet 使用说明
A1: 内存芯片公司｜16季度经营三张表
A2: 数据期间：第1—16季｜金额单位：十亿美元｜数量单位：千片（产能为千片/季）
B4: 交付结论
B5: 期末股东权益 | E5: 累计净利润 | H5: 累计经营现金流
B6: ='资产负债表'!Q12 -> 211.7094 | E6: =SUM('利润表'!B18:Q18) -> 176.7495 | H6: =SUM('现金流量表'!B8:Q8) -> 220.5995
B9: 工作簿结构
B10: 输入数据 | C10: 引擎导出值与期初状态，黄色单元格为事实输入；Q0仅用于期初余额和均值计算。
B11: 利润表 | C11: 逐季普通内存/HBM收入、成本、费用与净利润；成本合计已正确包含存货跌价。
B12: 资产负债表 | C12: 逐季资产、债务与股东权益，并计算净负债和平衡校验。
B13: 现金流量表 | C13: 净利润、折旧、营运资金及其他调整、投资、融资与现金滚动。
B14: 分析 | C14: 毛利率、存货周转天数、经营现金流、净负债、年化ROE、HBM收入占比及图表。
B15: 校验 | C15: 公式结果与引擎披露值逐项对照，包含资产平衡和现金滚动校验。
B18: 颜色、公式与假设
B19: 黄色：引擎事实输入。蓝色：情景假设输入。绿色：公式计算。修改‘分析’页蓝色假设，相关收入、成本、利润与权益会自动更新。
B20: 情景分析仅调整所选季度的价格、销货成本（含跌价）和税率；其他项目不变，权益按净利润差额估算。它是简化假设，不是重新运行经营引擎。
B21: 存货周转天数 = 平均存货 ÷ 不含存货跌价的销货成本 × 90天。年化ROE = 当季净利润 × 4 ÷ 期初、期末平均股东权益。
B22: 净负债 = 普通债务 + 紧急债务 − 现金；负数表示净现金。净利息支出为负时表示净利息收益。
B25: 出处与边界
B26: 主要数字：交付/data/export.json 的 history、final、cumulative_net_income；期初余额：交付/data/q00_state.json。无外部行业数字、无网页资料。市场、时间和公司均为虚构；本工作簿仅用于研究与展示，不构成投资建议。

Sheet 输入数据
A1: 输入数据｜引擎事实与期初余额
A2: 黄色单元格为输入事实；灰色空格表示该季度无此项目。所有派生报表与分析均引用本页。
A5: 季度 | B5: 普通价格指数 | C5: HBM价格指数 | D5: 普通需求 (千片) | E5: HBM需求 (千片) | F5: 开工率 | G5: 销售比例 | H5: 资本开支 (十亿美元) | I5: 额外HBM研发 (十亿美元) | J5: HBM产能分配 | K5: 新增/(偿还)借款 (十亿美元) | L5: 总产量 (千片) | M5: HBM产量 (千片) | N5: 普通销量 (千片) | O5: HBM销量 (千片) | P5: 单位成本 (百万美元/千片) | Q5: 产能 (千片/季) | R5: 普通收入 (十亿美元) | S5: HBM收入 (十亿美元) | T5: 销货成本含跌价 (十亿美元) | U5: 存货跌价 (十亿美元) | V5: 研发费用 (十亿美元) | W5: 销管费用 (十亿美元) | X5: 净利息支出/(收益) (十亿美元) | Y5: 所得税 (十亿美元) | Z5: 折旧 (十亿美元) | AA5: 经营现金流 (十亿美元) | AB5: 投资现金流 (十亿美元) | AC5: 融资现金流 (十亿美元) | AD5: 紧急授信发生额 (十亿美元) | AE5: 现金 (十亿美元) | AF5: 存货 (十亿美元) | AG5: 固定资产净额 (十亿美元) | AH5: 普通债务 (十亿美元) | AI5: 紧急债务 (十亿美元) | AJ5: 库存量 (千片) | AK5: 股东权益 (十亿美元) | AL5: HBM量产资格 1=是 | AM5: 引擎披露收入 (十亿美元) | AN5: 引擎披露毛利 (十亿美元) | AO5: 引擎披露营业利润 (十亿美元) | AP5: 引擎披露净利润 (十亿美元) | AQ5: 引擎披露资产总计 (十亿美元)
A6: 0 | Q6: 300 | AE6: 10 | AF6: 0.96 | AG6: 30 | AH6: 6 | AI6: 0 | AJ6: 60 | AK6: 34.96 | AL6: 0 | AQ6: 40.96
A7: 1 | B7: 0.8 | C7: 1.6 | D7: 240 | E7: 5 | F7: 0.75 | G7: 1 | H7: 1.5 | I7: 1 | J7: 0 | K7: 0 | L7: 225 | M7: 0 | N7: 240 | O7: 0 | P7: 18.333 | Q7: 300 | R7: 4.608 | S7: 0 | T7: 4.2821 | U7: 0 | V7: 1.8 | W7: 0.25 | X7: 0.01 | Y7: 0 | Z7: 2 | AA7: 0.423 | AB7: -1.5 | AC7: 0 | AD7: 0 | AE7: 8.923 | AF7: 0.8029 | AG7: 29.5 | AH7: 6 | AI7: 0 | AJ7: 45 | AK7: 33.2259 | AL7: 0 | AM7: 4.608 | AN7: 0.3259 | AO7: -1.7241 | AP7: -1.7341 | AQ7: 39.2259
A8: 2 | B8: 0.56 | C8: 1.4 | D8: 210 | E8: 5 | F8: 0.6 | G8: 1 | H8: 1.5 | I8: 1 | J8: 0 | K8: 0 | L8: 180 | M8: 0 | N8: 210 | O8: 0 | P8: 21.667 | Q8: 300 | R8: 2.8224 | S8: 0 | T8: 4.5114 | U8: 0.122 | V8: 1.8 | W8: 0.25 | X8: 0.0186 | Y8: 0 | Z8: 2 | AA8: -1.1462 | AB8: -1.5 | AC8: 0 | AD8: 0 | AE8: 6.2768 | AF8: 0.1915 | AG8: 29 | AH8: 6 | AI8: 0 | AJ8: 15 | AK8: 29.4683 | AL8: 0 | AM8: 2.8224 | AN8: -1.689 | AO8: -3.739 | AP8: -3.7576 | AQ8: 35.4683
A9: 3 | B9: 0.5 | C9: 1.3 | D9: 205 | E9: 6 | F9: 0.55 | G9: 1 | H9: 1.5 | I9: 1 | J9: 0 | K9: 2 | L9: 165 | M9: 0 | N9: 180 | O9: 0 | P9: 23.182 | Q9: 300 | R9: 2.16 | S9: 0 | T9: 4.0165 | U9: 0 | V9: 1.8 | W9: 0.25 | X9: 0.0398 | Y9: 0 | Z9: 2 | AA9: -1.7548 | AB9: -1.5 | AC9: 2 | AD9: 0 | AE9: 5.022 | AF9: 0 | AG9: 28.5 | AH9: 8 | AI9: 0 | AJ9: 0 | AK9: 25.522 | AL9: 0 | AM9: 2.16 | AN9: -1.8565 | AO9: -3.9065 | AP9: -3.9463 | AQ9: 33.522
A10: 4 | B10: 0.53 | C10: 1.4 | D10: 215 | E10: 8 | F10: 0.7 | G10: 1 | H10: 1.5 | I10: 0 | J10: 0 | K10: 2 | L10: 210 | M10: 0 | N10: 210 | O10: 0 | P10: 19.286 | Q10: 300 | R10: 2.6712 | S10: 0 | T10: 4.05 | U10: 0 | V10: 0.8 | W10: 0.25 | X10: 0.0798 | Y10: 0 | Z10: 2 | AA10: -0.5086 | AB10: -1.5 | AC10: 2 | AD10: 0 | AE10: 5.0134 | AF10: 0 | AG10: 28 | AH10: 10 | AI10: 0 | AJ10: 0 | AK10: 23.0134 | AL10: 0 | AM10: 2.6712 | AN10: -1.3788 | AO10: -2.4288 | AP10: -2.5086 | AQ10: 33.0134
A11: 5 | B11: 0.6 | C11: 1.6 | D11: 235 | E11: 12 | F11: 0.8 | G11: 1 | H11: 1.5 | I11: 0 | J11: 0 | K11: 0 | L11: 240 | M11: 0 | N11: 235 | O11: 0 | P11: 17.813 | Q11: 300 | R11: 3.384 | S11: 0 | T11: 4.2066 | U11: 0.0207 | V11: 0.8 | W11: 0.25 | X11: 0.1099 | Y11: 0 | Z11: 2.075 | AA11: 0.0241 | AB11: -1.5 | AC11: 0 | AD11: 0 | AE11: 3.5375 | AF11: 0.0684 | AG11: 27.425 | AH11: 10 | AI11: 0 | AJ11: 5 | AK11: 21.0309 | AL11: 0 | AM11: 3.384 | AN11: -0.8226 | AO11: -1.8726 | AP11: -1.9825 | AQ11: 31.0309
A12: 6 | B12: 0.72 | C12: 1.9 | D12: 260 | E12: 18 | F12: 0.9 | G12: 1 | H12: 1.5 | I12: 0 | J12: 0.07 | K12: 0 | L12: 270 | M12: 18.9 | N12: 256.1 | O12: 18 | P12: 16.667 | Q12: 300 | R12: 4.4254 | S12: 0.8208 | T12: 4.5684 | U12: 0 | V12: 0.8 | W12: 0.25 | X12: 0.1217 | Y12: 0 | Z12: 2.15 | AA12: 1.7245 | AB12: -1.5 | AC12: 0 | AD12: 0 | AE12: 3.762 | AF12: 0 | AG12: 26.775 | AH12: 10 | AI12: 0 | AJ12: 0 | AK12: 20.537 | AL12: 1 | AM12: 5.2462 | AN12: 0.6778 | AO12: -0.3722 | AP12: -0.4939 | AQ12: 30.537
A13: 7 | B13: 0.83 | C13: 2.3 | D13: 285 | E13: 26 | F13: 1 | G13: 1 | H13: 5.1 | I13: 0 | J13: 0.09 | K13: 1 | L13: 300 | M13: 27 | N13: 273 | O13: 26 | P13: 15.75 | Q13: 300 | R13: 5.4382 | S13: 1.4352 | T13: 4.725 | U13: 0 | V13: 0.8 | W13: 0.25 | X13: 0.1199 | Y13: 0.1468 | Z13: 2.225 | AA13: 3.0567 | AB13: -5.1 | AC13: 1 | AD13: 0 | AE13: 2.7187 | AF13: 0 | AG13: 29.65 | AH13: 11 | AI13: 0 | AJ13: 0 | AK13: 21.3687 | AL13: 1 | AM13: 6.8734 | AN13: 2.1484 | AO13: 1.0984 | AP13: 0.8317 | AQ13: 32.3687
A14: 8 | B14: 0.92 | C14: 2.8 | D14: 305 | E14: 36 | F14: 1 | G14: 1 | H14: 6.3 | I14: 0 | J14: 0.13 | K14: 1 | L14: 300 | M14: 39 | N14: 261 | O14: 36 | P14: 16 | Q14: 300 | R14: 5.7629 | S14: 2.4192 | T14: 4.8 | U14: 0 | V14: 0.8 | W14: 0.25 | X14: 0.1433 | Y14: 0.3283 | Z14: 2.3 | AA14: 4.1605 | AB14: -6.3 | AC14: 1 | AD14: 0 | AE14: 1.5792 | AF14: 0 | AG14: 33.65 | AH14: 12 | AI14: 0 | AJ14: 0 | AK14: 23.2292 | AL14: 1 | AM14: 8.1821 | AN14: 3.3821 | AO14: 2.3321 | AP14: 1.8605 | AQ14: 35.2292
A15: 9 | B15: 1 | C15: 3.4 | D15: 320 | E15: 48 | F15: 1 | G15: 1 | H15: 6.3 | I15: 0 | J15: 0.17 | K15: 1.5 | L15: 300 | M15: 51 | N15: 249 | O15: 48 | P15: 16.25 | Q15: 300 | R15: 5.976 | S15: 3.9168 | T15: 4.875 | U15: 0 | V15: 0.8 | W15: 0.25 | X15: 0.1674 | Y15: 0.5701 | Z15: 2.375 | AA15: 5.6054 | AB15: -6.3 | AC15: 1.5 | AD15: 0 | AE15: 2.3846 | AF15: 0 | AG15: 37.575 | AH15: 13.5 | AI15: 0 | AJ15: 0 | AK15: 26.4596 | AL15: 1 | AM15: 9.8928 | AN15: 5.0178 | AO15: 3.9678 | AP15: 3.2304 | AQ15: 39.9596
A16: 10 | B16: 0.97 | C16: 4 | D16: 320 | E16: 60 | F16: 1 | G16: 1 | H16: 6.3 | I16: 0 | J16: 0.21 | K16: 0 | L16: 300 | M16: 63 | N16: 237 | O16: 60 | P16: 16.5 | Q16: 300 | R16: 5.5174 | S16: 5.76 | T16: 4.95 | U16: 0 | V16: 0.8 | W16: 0.25 | X16: 0.1834 | Y16: 0.7641 | Z16: 2.45 | AA16: 6.7798 | AB16: -6.3 | AC16: 0 | AD16: 0 | AE16: 2.8644 | AF16: 0 | AG16: 41.425 | AH16: 13.5 | AI16: 0 | AJ16: 0 | AK16: 30.7894 | AL16: 1 | AM16: 11.2774 | AN16: 6.3274 | AO16: 5.2774 | AP16: 4.3298 | AQ16: 44.2894
A17: 11 | B17: 1.06 | C17: 4.6 | D17: 340 | E17: 74 | F17: 1 | G17: 1 | H17: 8.7 | I17: 0 | J17: 0.24 | K17: 0 | L17: 330 | M17: 79.2 | N17: 250.8 | O17: 74 | P17: 16.227 | Q17: 330 | R17: 6.3804 | S17: 8.1696 | T17: 5.355 | U17: 0 | V17: 0.8 | W17: 0.25 | X17: 0.1796 | Y17: 1.1948 | Z17: 2.705 | AA17: 9.4756 | AB17: -8.7 | AC17: 0 | AD17: 0 | AE17: 3.64 | AF17: 0 | AG17: 47.42 | AH17: 13.5 | AI17: 0 | AJ17: 0 | AK17: 37.56 | AL17: 1 | AM17: 14.55 | AN17: 9.195 | AO17: 8.145 | AP17: 6.7706 | AQ17: 51.06
A18: 12 | B18: 1.28 | C18: 5.4 | D18: 365 | E18: 90 | F18: 1 | G18: 1 | H18: 8.7 | I18: 0 | J18: 0.26 | K18: -5 | L18: 370 | M18: 96.2 | N18: 273.8 | O18: 90 | P18: 15.865 | Q18: 370 | R18: 8.4111 | S18: 11.664 | T18: 5.87 | U18: 0 | V18: 0.8 | W18: 0.25 | X18: 0.1734 | Y18: 1.9473 | Z18: 3.02 | AA18: 14.0545 | AB18: -8.7 | AC18: -5 | AD18: 0 | AE18: 3.9945 | AF18: 0 | AG18: 53.1 | AH18: 8.5 | AI18: 0 | AJ18: 0 | AK18: 48.5945 | AL18: 1 | AM18: 20.0751 | AN18: 14.2051 | AO18: 13.1551 | AP18: 11.0345 | AQ18: 57.0945
... A22: 16 | B22: 4.55 | C22: 9.6 | D22: 510 | E22: 185 | F22: 1 | G22: 1 | H22: 1.5 | I22: 0 | J22: 0.3246 | K22: 0 | L22: 570 | M22: 185.02 | N22: 384.98 | O22: 185 | P22: 14.684 | Q22: 570 | R22: 42.0396 | S22: 42.624 | T22: 8.37 | U22: 0 | V22: 0.8 | W22: 0.25 | X22: -0.8043 | Y22: 11.4072 | Z22: 4.52 | AA22: 69.1607 | AB22: -1.5 | AC22: 0 | AD22: 0 | AE22: 168.1994 | AF22: 0 | AG22: 43.51 | AH22: 0 | AI22: 0 | AJ22: 0 | AK22: 211.7094 | AL22: 1 | AM22: 84.6636 | AN22: 76.2936 | AO22: 75.2436 | AP22: 64.6407 | AQ22: 211.7094

Sheet 利润表
A1: 逐季利润表
A2: 金额单位：十亿美元。cogs已含存货跌价，本表拆分后加总；净利润引用引擎披露输入，保留其四位小数舍入口径。
A4: 项目 | B4: Q1 | C4: Q2 | D4: Q3 | E4: Q4 | F4: Q5 | G4: Q6 | H4: Q7 | I4: Q8 | J4: Q9 | K4: Q10 | L4: Q11 | M4: Q12 | N4: Q13 | O4: Q14 | P4: Q15 | Q4: Q16
A5: 普通内存收入 | B5: ='输入数据'!$R$7 -> 4.608 | C5: ='输入数据'!$R$8 -> 2.8224 | D5: ='输入数据'!$R$9 -> 2.16 | E5: ='输入数据'!$R$10 -> 2.6712 | F5: ='输入数据'!$R$11 -> 3.384 | G5: ='输入数据'!$R$12 -> 4.4254 | H5: ='输入数据'!$R$13 -> 5.4382 | I5: ='输入数据'!$R$14 -> 5.7629 | J5: ='输入数据'!$R$15 -> 5.976 | K5: ='输入数据'!$R$16 -> 5.5174 | L5: ='输入数据'!$R$17 -> 6.3804 | M5: ='输入数据'!$R$18 -> 8.4111 | N5: ='输入数据'!$R$19 -> 12.3285 | O5: ='输入数据'!$R$20 -> 20.3202 | P5: ='输入数据'!$R$21 -> 32.6992 | Q5: ='输入数据'!$R$22 -> 42.0396
A6: HBM收入 | B6: ='输入数据'!$S$7 -> 0 | C6: ='输入数据'!$S$8 -> 0 | D6: ='输入数据'!$S$9 -> 0 | E6: ='输入数据'!$S$10 -> 0 | F6: ='输入数据'!$S$11 -> 0 | G6: ='输入数据'!$S$12 -> 0.8208 | H6: ='输入数据'!$S$13 -> 1.4352 | I6: ='输入数据'!$S$14 -> 2.4192 | J6: ='输入数据'!$S$15 -> 3.9168 | K6: ='输入数据'!$S$16 -> 5.76 | L6: ='输入数据'!$S$17 -> 8.1696 | M6: ='输入数据'!$S$18 -> 11.664 | N6: ='输入数据'!$S$19 -> 16.5627 | O6: ='输入数据'!$S$20 -> 23.8032 | P6: ='输入数据'!$S$21 -> 33.792 | Q6: ='输入数据'!$S$22 -> 42.624
A7: 营业收入 | B7: =SUM(B5:B6) -> 4.608 | C7: =SUM(C5:C6) -> 2.8224 | D7: =SUM(D5:D6) -> 2.16 | E7: =SUM(E5:E6) -> 2.6712 | F7: =SUM(F5:F6) -> 3.384 | G7: =SUM(G5:G6) -> 5.2462 | H7: =SUM(H5:H6) -> 6.8734 | I7: =SUM(I5:I6) -> 8.1821 | ... Q7: =SUM(Q5:Q6) -> 84.6636
A8: 销货成本（不含存货跌价） | B8: ='输入数据'!$T$7-'输入数据'!$U$7 -> 4.2821 | C8: ='输入数据'!$T$8-'输入数据'!$U$8 -> 4.3894 | D8: ='输入数据'!$T$9-'输入数据'!$U$9 -> 4.0165 | E8: ='输入数据'!$T$10-'输入数据'!$U$10 -> 4.05 | F8: ='输入数据'!$T$11-'输入数据'!$U$11 -> 4.1859 | G8: ='输入数据'!$T$12-'输入数据'!$U$12 -> 4.5684 | H8: ='输入数据'!$T$13-'输入数据'!$U$13 -> 4.725 | I8: ='输入数据'!$T$14-'输入数据'!$U$14 -> 4.8 | J8: ='输入数据'!$T$15-'输入数据'!$U$15 -> 4.875 | K8: ='输入数据'!$T$16-'输入数据'!$U$16 -> 4.95 | L8: ='输入数据'!$T$17-'输入数据'!$U$17 -> 5.355 | M8: ='输入数据'!$T$18-'输入数据'!$U$18 -> 5.87 | N8: ='输入数据'!$T$19-'输入数据'!$U$19 -> 6.385 | O8: ='输入数据'!$T$20-'输入数据'!$U$20 -> 6.9 | P8: ='输入数据'!$T$21-'输入数据'!$U$21 -> 7.635 | Q8: ='输入数据'!$T$22-'输入数据'!$U$22 -> 8.37
A9: 存货跌价损失 | B9: ='输入数据'!$U$7 -> 0 | C9: ='输入数据'!$U$8 -> 0.122 | D9: ='输入数据'!$U$9 -> 0 | E9: ='输入数据'!$U$10 -> 0 | F9: ='输入数据'!$U$11 -> 0.0207 | G9: ='输入数据'!$U$12 -> 0 | H9: ='输入数据'!$U$13 -> 0 | I9: ='输入数据'!$U$14 -> 0 | J9: ='输入数据'!$U$15 -> 0 | K9: ='输入数据'!$U$16 -> 0 | L9: ='输入数据'!$U$17 -> 0 | M9: ='输入数据'!$U$18 -> 0 | N9: ='输入数据'!$U$19 -> 0 | O9: ='输入数据'!$U$20 -> 0 | P9: ='输入数据'!$U$21 -> 0 | Q9: ='输入数据'!$U$22 -> 0
A10: 营业成本合计 | B10: =SUM(B8:B9) -> 4.2821 | C10: =SUM(C8:C9) -> 4.5114 | D10: =SUM(D8:D9) -> 4.0165 | E10: =SUM(E8:E9) -> 4.05 | F10: =SUM(F8:F9) -> 4.2066 | G10: =SUM(G8:G9) -> 4.5684 | H10: =SUM(H8:H9) -> 4.725 | I10: =SUM(I8:I9) -> 4.8 | ... Q10: =SUM(Q8:Q9) -> 8.37
A11: 毛利 | B11: =B7-B10 -> 0.3259 | C11: =C7-C10 -> -1.689 | D11: =D7-D10 -> -1.8565 | E11: =E7-E10 -> -1.3788 | F11: =F7-F10 -> -0.8226 | G11: =G7-G10 -> 0.6778 | H11: =H7-H10 -> 2.1484 | I11: =I7-I10 -> 3.3821 | ... Q11: =Q7-Q10 -> 76.2936
A12: 研发费用 | B12: ='输入数据'!$V$7 -> 1.8 | C12: ='输入数据'!$V$8 -> 1.8 | D12: ='输入数据'!$V$9 -> 1.8 | E12: ='输入数据'!$V$10 -> 0.8 | F12: ='输入数据'!$V$11 -> 0.8 | G12: ='输入数据'!$V$12 -> 0.8 | H12: ='输入数据'!$V$13 -> 0.8 | I12: ='输入数据'!$V$14 -> 0.8 | J12: ='输入数据'!$V$15 -> 0.8 | K12: ='输入数据'!$V$16 -> 0.8 | L12: ='输入数据'!$V$17 -> 0.8 | M12: ='输入数据'!$V$18 -> 0.8 | N12: ='输入数据'!$V$19 -> 0.8 | O12: ='输入数据'!$V$20 -> 0.8 | P12: ='输入数据'!$V$21 -> 0.8 | Q12: ='输入数据'!$V$22 -> 0.8
A13: 销售管理费用 | B13: ='输入数据'!$W$7 -> 0.25 | C13: ='输入数据'!$W$8 -> 0.25 | D13: ='输入数据'!$W$9 -> 0.25 | E13: ='输入数据'!$W$10 -> 0.25 | F13: ='输入数据'!$W$11 -> 0.25 | G13: ='输入数据'!$W$12 -> 0.25 | H13: ='输入数据'!$W$13 -> 0.25 | I13: ='输入数据'!$W$14 -> 0.25 | J13: ='输入数据'!$W$15 -> 0.25 | K13: ='输入数据'!$W$16 -> 0.25 | L13: ='输入数据'!$W$17 -> 0.25 | M13: ='输入数据'!$W$18 -> 0.25 | N13: ='输入数据'!$W$19 -> 0.25 | O13: ='输入数据'!$W$20 -> 0.25 | P13: ='输入数据'!$W$21 -> 0.25 | Q13: ='输入数据'!$W$22 -> 0.25
A14: 营业利润 | B14: =B11-B12-B13 -> -1.7241 | C14: =C11-C12-C13 -> -3.739 | D14: =D11-D12-D13 -> -3.9065 | E14: =E11-E12-E13 -> -2.4288 | F14: =F11-F12-F13 -> -1.8726 | G14: =G11-G12-G13 -> -0.3722 | H14: =H11-H12-H13 -> 1.0984 | I14: =I11-I12-I13 -> 2.3321 | ... Q14: =Q11-Q12-Q13 -> 75.2436
A15: 净利息支出/(收益) | B15: ='输入数据'!$X$7 -> 0.01 | C15: ='输入数据'!$X$8 -> 0.0186 | D15: ='输入数据'!$X$9 -> 0.0398 | E15: ='输入数据'!$X$10 -> 0.0798 | F15: ='输入数据'!$X$11 -> 0.1099 | G15: ='输入数据'!$X$12 -> 0.1217 | H15: ='输入数据'!$X$13 -> 0.1199 | I15: ='输入数据'!$X$14 -> 0.1433 | J15: ='输入数据'!$X$15 -> 0.1674 | K15: ='输入数据'!$X$16 -> 0.1834 | L15: ='输入数据'!$X$17 -> 0.1796 | M15: ='输入数据'!$X$18 -> 0.1734 | N15: ='输入数据'!$X$19 -> 0.0955 | O15: ='输入数据'!$X$20 -> -0.1239 | P15: ='输入数据'!$X$21 -> -0.3879 | Q15: ='输入数据'!$X$22 -> -0.8043
A16: 税前利润 | B16: =B14-B15 -> -1.7341 | C16: =C14-C15 -> -3.7576 | D16: =D14-D15 -> -3.9463 | E16: =E14-E15 -> -2.5086 | F16: =F14-F15 -> -1.9825 | G16: =G14-G15 -> -0.4939 | H16: =H14-H15 -> 0.9785 | I16: =I14-I15 -> 2.1888 | ... Q16: =Q14-Q15 -> 76.0479
A17: 所得税 | B17: ='输入数据'!$Y$7 -> 0 | C17: ='输入数据'!$Y$8 -> 0 | D17: ='输入数据'!$Y$9 -> 0 | E17: ='输入数据'!$Y$10 -> 0 | F17: ='输入数据'!$Y$11 -> 0 | G17: ='输入数据'!$Y$12 -> 0 | H17: ='输入数据'!$Y$13 -> 0.1468 | I17: ='输入数据'!$Y$14 -> 0.3283 | J17: ='输入数据'!$Y$15 -> 0.5701 | K17: ='输入数据'!$Y$16 -> 0.7641 | L17: ='输入数据'!$Y$17 -> 1.1948 | M17: ='输入数据'!$Y$18 -> 1.9473 | N17: ='输入数据'!$Y$19 -> 3.2041 | O17: ='输入数据'!$Y$20 -> 5.4446 | P17: ='输入数据'!$Y$21 -> 8.7291 | Q17: ='输入数据'!$Y$22 -> 11.4072
A18: 净利润 | B18: ='输入数据'!$AP$7 -> -1.7341 | C18: ='输入数据'!$AP$8 -> -3.7576 | D18: ='输入数据'!$AP$9 -> -3.9463 | E18: ='输入数据'!$AP$10 -> -2.5086 | F18: ='输入数据'!$AP$11 -> -1.9825 | G18: ='输入数据'!$AP$12 -> -0.4939 | H18: ='输入数据'!$AP$13 -> 0.8317 | I18: ='输入数据'!$AP$14 -> 1.8605 | J18: ='输入数据'!$AP$15 -> 3.2304 | K18: ='输入数据'!$AP$16 -> 4.3298 | L18: ='输入数据'!$AP$17 -> 6.7706 | M18: ='输入数据'!$AP$18 -> 11.0345 | N18: ='输入数据'!$AP$19 -> 18.1566 | O18: ='输入数据'!$AP$20 -> 30.8527 | P18: ='输入数据'!$AP$21 -> 49.465 | Q18: ='输入数据'!$AP$22 -> 64.6407
A19: 毛利率 | B19: =IFERROR(B11/B7,0) -> 0.070724826 | C19: =IFERROR(C11/C7,0) -> -0.59842687 | D19: =IFERROR(D11/D7,0) -> -0.85949074 | E19: =IFERROR(E11/E7,0) -> -0.51617251 | F19: =IFERROR(F11/F7,0) -> -0.24308511 | G19: =IFERROR(G11/G7,0) -> 0.12919828 | H19: =IFERROR(H11/H7,0) -> 0.31256729 | I19: =IFERROR(I11/I7,0) -> 0.41335354 | ... Q19: =IFERROR(Q11/Q7,0) -> 0.90113815
A20: 净利率 | B20: =IFERROR(B18/B7,0) -> -0.37632378 | C20: =IFERROR(C18/C7,0) -> -1.3313492 | D20: =IFERROR(D18/D7,0) -> -1.8269907 | E20: =IFERROR(E18/E7,0) -> -0.93912848 | F20: =IFERROR(F18/F7,0) -> -0.58584515 | G20: =IFERROR(G18/G7,0) -> -0.094144333 | H20: =IFERROR(H18/H7,0) -> 0.12100271 | I20: =IFERROR(I18/I7,0) -> 0.22738661 | ... Q20: =IFERROR(Q18/Q7,0) -> 0.76350049

Sheet 资产负债表
A1: 逐季资产负债表
A2: 金额单位：十亿美元；净负债为负表示净现金。平衡校验应为0。
A4: 项目 | B4: Q1 | C4: Q2 | D4: Q3 | E4: Q4 | F4: Q5 | G4: Q6 | H4: Q7 | I4: Q8 | J4: Q9 | K4: Q10 | L4: Q11 | M4: Q12 | N4: Q13 | O4: Q14 | P4: Q15 | Q4: Q16
A5: 现金 | B5: ='输入数据'!$AE$7 -> 8.923 | C5: ='输入数据'!$AE$8 -> 6.2768 | D5: ='输入数据'!$AE$9 -> 5.022 | E5: ='输入数据'!$AE$10 -> 5.0134 | F5: ='输入数据'!$AE$11 -> 3.5375 | G5: ='输入数据'!$AE$12 -> 3.762 | H5: ='输入数据'!$AE$13 -> 2.7187 | I5: ='输入数据'!$AE$14 -> 1.5792 | J5: ='输入数据'!$AE$15 -> 2.3846 | K5: ='输入数据'!$AE$16 -> 2.8644 | L5: ='输入数据'!$AE$17 -> 3.64 | M5: ='输入数据'!$AE$18 -> 3.9945 | N5: ='输入数据'!$AE$19 -> 15.486 | O5: ='输入数据'!$AE$20 -> 48.4887 | P5: ='输入数据'!$AE$21 -> 100.5387 | Q5: ='输入数据'!$AE$22 -> 168.1994
A6: 存货 | B6: ='输入数据'!$AF$7 -> 0.8029 | C6: ='输入数据'!$AF$8 -> 0.1915 | D6: ='输入数据'!$AF$9 -> 0 | E6: ='输入数据'!$AF$10 -> 0 | F6: ='输入数据'!$AF$11 -> 0.0684 | G6: ='输入数据'!$AF$12 -> 0 | H6: ='输入数据'!$AF$13 -> 0 | I6: ='输入数据'!$AF$14 -> 0 | J6: ='输入数据'!$AF$15 -> 0 | K6: ='输入数据'!$AF$16 -> 0 | L6: ='输入数据'!$AF$17 -> 0 | M6: ='输入数据'!$AF$18 -> 0 | N6: ='输入数据'!$AF$19 -> 0 | O6: ='输入数据'!$AF$20 -> 0 | P6: ='输入数据'!$AF$21 -> 0 | Q6: ='输入数据'!$AF$22 -> 0
A7: 固定资产净额 | B7: ='输入数据'!$AG$7 -> 29.5 | C7: ='输入数据'!$AG$8 -> 29 | D7: ='输入数据'!$AG$9 -> 28.5 | E7: ='输入数据'!$AG$10 -> 28 | F7: ='输入数据'!$AG$11 -> 27.425 | G7: ='输入数据'!$AG$12 -> 26.775 | H7: ='输入数据'!$AG$13 -> 29.65 | I7: ='输入数据'!$AG$14 -> 33.65 | J7: ='输入数据'!$AG$15 -> 37.575 | K7: ='输入数据'!$AG$16 -> 41.425 | L7: ='输入数据'!$AG$17 -> 47.42 | M7: ='输入数据'!$AG$18 -> 53.1 | N7: ='输入数据'!$AG$19 -> 51.265 | O7: ='输入数据'!$AG$20 -> 49.115 | P7: ='输入数据'!$AG$21 -> 46.53 | Q7: ='输入数据'!$AG$22 -> 43.51
A8: 资产总计 | B8: =SUM(B5:B7) -> 39.2259 | C8: =SUM(C5:C7) -> 35.4683 | D8: =SUM(D5:D7) -> 33.522 | E8: =SUM(E5:E7) -> 33.0134 | F8: =SUM(F5:F7) -> 31.0309 | G8: =SUM(G5:G7) -> 30.537 | H8: =SUM(H5:H7) -> 32.3687 | I8: =SUM(I5:I7) -> 35.2292 | ... Q8: =SUM(Q5:Q7) -> 211.7094
A9: 普通债务 | B9: ='输入数据'!$AH$7 -> 6 | C9: ='输入数据'!$AH$8 -> 6 | D9: ='输入数据'!$AH$9 -> 8 | E9: ='输入数据'!$AH$10 -> 10 | F9: ='输入数据'!$AH$11 -> 10 | G9: ='输入数据'!$AH$12 -> 10 | H9: ='输入数据'!$AH$13 -> 11 | I9: ='输入数据'!$AH$14 -> 12 | J9: ='输入数据'!$AH$15 -> 13.5 | K9: ='输入数据'!$AH$16 -> 13.5 | L9: ='输入数据'!$AH$17 -> 13.5 | M9: ='输入数据'!$AH$18 -> 8.5 | N9: ='输入数据'!$AH$19 -> 0 | O9: ='输入数据'!$AH$20 -> 0 | P9: ='输入数据'!$AH$21 -> 0 | Q9: ='输入数据'!$AH$22 -> 0
A10: 紧急债务 | B10: ='输入数据'!$AI$7 -> 0 | C10: ='输入数据'!$AI$8 -> 0 | D10: ='输入数据'!$AI$9 -> 0 | E10: ='输入数据'!$AI$10 -> 0 | F10: ='输入数据'!$AI$11 -> 0 | G10: ='输入数据'!$AI$12 -> 0 | H10: ='输入数据'!$AI$13 -> 0 | I10: ='输入数据'!$AI$14 -> 0 | J10: ='输入数据'!$AI$15 -> 0 | K10: ='输入数据'!$AI$16 -> 0 | L10: ='输入数据'!$AI$17 -> 0 | M10: ='输入数据'!$AI$18 -> 0 | N10: ='输入数据'!$AI$19 -> 0 | O10: ='输入数据'!$AI$20 -> 0 | P10: ='输入数据'!$AI$21 -> 0 | Q10: ='输入数据'!$AI$22 -> 0
A11: 负债合计 | B11: =SUM(B9:B10) -> 6 | C11: =SUM(C9:C10) -> 6 | D11: =SUM(D9:D10) -> 8 | E11: =SUM(E9:E10) -> 10 | F11: =SUM(F9:F10) -> 10 | G11: =SUM(G9:G10) -> 10 | H11: =SUM(H9:H10) -> 11 | I11: =SUM(I9:I10) -> 12 | ... Q11: =SUM(Q9:Q10) -> 0
A12: 股东权益 | B12: ='输入数据'!$AK$7 -> 33.2259 | C12: ='输入数据'!$AK$8 -> 29.4683 | D12: ='输入数据'!$AK$9 -> 25.522 | E12: ='输入数据'!$AK$10 -> 23.0134 | F12: ='输入数据'!$AK$11 -> 21.0309 | G12: ='输入数据'!$AK$12 -> 20.537 | H12: ='输入数据'!$AK$13 -> 21.3687 | I12: ='输入数据'!$AK$14 -> 23.2292 | J12: ='输入数据'!$AK$15 -> 26.4596 | K12: ='输入数据'!$AK$16 -> 30.7894 | L12: ='输入数据'!$AK$17 -> 37.56 | M12: ='输入数据'!$AK$18 -> 48.5945 | N12: ='输入数据'!$AK$19 -> 66.751 | O12: ='输入数据'!$AK$20 -> 97.6037 | P12: ='输入数据'!$AK$21 -> 147.0687 | Q12: ='输入数据'!$AK$22 -> 211.7094
A13: 负债和股东权益 | B13: =B11+B12 -> 39.2259 | C13: =C11+C12 -> 35.4683 | D13: =D11+D12 -> 33.522 | E13: =E11+E12 -> 33.0134 | F13: =F11+F12 -> 31.0309 | G13: =G11+G12 -> 30.537 | H13: =H11+H12 -> 32.3687 | I13: =I11+I12 -> 35.2292 | ... Q13: =Q11+Q12 -> 211.7094
A14: 平衡校验 | B14: =B8-B13 -> -7.1054274e-15 | C14: =C8-C13 -> 0 | D14: =D8-D13 -> 0 | E14: =E8-E13 -> -7.1054274e-15 | F14: =F8-F13 -> 3.5527137e-15 | G14: =G8-G13 -> 0 | H14: =H8-H13 -> -7.1054274e-15 | I14: =I8-I13 -> 0 | ... Q14: =Q8-Q13 -> 0
A16: 补充：库存量（千片） | B16: ='输入数据'!$AJ$7 -> 45 | C16: ='输入数据'!$AJ$8 -> 15 | D16: ='输入数据'!$AJ$9 -> 0 | E16: ='输入数据'!$AJ$10 -> 0 | F16: ='输入数据'!$AJ$11 -> 5 | G16: ='输入数据'!$AJ$12 -> 0 | H16: ='输入数据'!$AJ$13 -> 0 | I16: ='输入数据'!$AJ$14 -> 0 | J16: ='输入数据'!$AJ$15 -> 0 | K16: ='输入数据'!$AJ$16 -> 0 | L16: ='输入数据'!$AJ$17 -> 0 | M16: ='输入数据'!$AJ$18 -> 0 | N16: ='输入数据'!$AJ$19 -> 0 | O16: ='输入数据'!$AJ$20 -> 0 | P16: ='输入数据'!$AJ$21 -> 0 | Q16: ='输入数据'!$AJ$22 -> 0
A17: 补充：产能（千片/季） | B17: ='输入数据'!$Q$7 -> 300 | C17: ='输入数据'!$Q$8 -> 300 | D17: ='输入数据'!$Q$9 -> 300 | E17: ='输入数据'!$Q$10 -> 300 | F17: ='输入数据'!$Q$11 -> 300 | G17: ='输入数据'!$Q$12 -> 300 | H17: ='输入数据'!$Q$13 -> 300 | I17: ='输入数据'!$Q$14 -> 300 | J17: ='输入数据'!$Q$15 -> 300 | K17: ='输入数据'!$Q$16 -> 300 | L17: ='输入数据'!$Q$17 -> 330 | M17: ='输入数据'!$Q$18 -> 370 | N17: ='输入数据'!$Q$19 -> 410 | O17: ='输入数据'!$Q$20 -> 450 | P17: ='输入数据'!$Q$21 -> 510 | Q17: ='输入数据'!$Q$22 -> 570
A18: 净负债/(净现金) | B18: =B11-B5 -> -2.923 | C18: =C11-C5 -> -0.2768 | D18: =D11-D5 -> 2.978 | E18: =E11-E5 -> 4.9866 | F18: =F11-F5 -> 6.4625 | G18: =G11-G5 -> 6.238 | H18: =H11-H5 -> 8.2813 | I18: =I11-I5 -> 10.4208 | ... Q18: =Q11-Q5 -> -168.1994

Sheet 现金流量表
A1: 逐季现金流量表
A2: 金额单位：十亿美元。营运资金及其他调整为经营现金流与净利润、折旧之间的差额；现金校验应为0。
A4: 项目 | B4: Q1 | C4: Q2 | D4: Q3 | E4: Q4 | F4: Q5 | G4: Q6 | H4: Q7 | I4: Q8 | J4: Q9 | K4: Q10 | L4: Q11 | M4: Q12 | N4: Q13 | O4: Q14 | P4: Q15 | Q4: Q16
A5: 净利润 | B5: ='利润表'!B18 -> -1.7341 | C5: ='利润表'!C18 -> -3.7576 | D5: ='利润表'!D18 -> -3.9463 | E5: ='利润表'!E18 -> -2.5086 | F5: ='利润表'!F18 -> -1.9825 | G5: ='利润表'!G18 -> -0.4939 | H5: ='利润表'!H18 -> 0.8317 | I5: ='利润表'!I18 -> 1.8605 | ... Q5: ='利润表'!Q18 -> 64.6407
A6: 加：折旧 | B6: ='输入数据'!$Z$7 -> 2 | C6: ='输入数据'!$Z$8 -> 2 | D6: ='输入数据'!$Z$9 -> 2 | E6: ='输入数据'!$Z$10 -> 2 | F6: ='输入数据'!$Z$11 -> 2.075 | G6: ='输入数据'!$Z$12 -> 2.15 | H6: ='输入数据'!$Z$13 -> 2.225 | I6: ='输入数据'!$Z$14 -> 2.3 | J6: ='输入数据'!$Z$15 -> 2.375 | K6: ='输入数据'!$Z$16 -> 2.45 | L6: ='输入数据'!$Z$17 -> 2.705 | M6: ='输入数据'!$Z$18 -> 3.02 | N6: ='输入数据'!$Z$19 -> 3.335 | O6: ='输入数据'!$Z$20 -> 3.65 | P6: ='输入数据'!$Z$21 -> 4.085 | Q6: ='输入数据'!$Z$22 -> 4.52
A7: 营运资金及其他调整 | B7: ='输入数据'!$AA$7-B5-B6 -> 0.1571 | C7: ='输入数据'!$AA$8-C5-C6 -> 0.6114 | D7: ='输入数据'!$AA$9-D5-D6 -> 0.1915 | E7: ='输入数据'!$AA$10-E5-E6 -> 0 | F7: ='输入数据'!$AA$11-F5-F6 -> -0.0684 | G7: ='输入数据'!$AA$12-G5-G6 -> 0.0684 | H7: ='输入数据'!$AA$13-H5-H6 -> 0 | I7: ='输入数据'!$AA$14-I5-I6 -> 0 | J7: ='输入数据'!$AA$15-J5-J6 -> 4.4408921e-16 | K7: ='输入数据'!$AA$16-K5-K6 -> 0 | L7: ='输入数据'!$AA$17-L5-L6 -> 0 | M7: ='输入数据'!$AA$18-M5-M6 -> 1.3322676e-15 | N7: ='输入数据'!$AA$19-N5-N6 -> -2.6645353e-15 | O7: ='输入数据'!$AA$20-O5-O6 -> -1.3322676e-15 | P7: ='输入数据'!$AA$21-P5-P6 -> -6.2172489e-15 | Q7: ='输入数据'!$AA$22-Q5-Q6 -> 1.0658141e-14
A8: 经营活动现金流 | B8: =SUM(B5:B7) -> 0.423 | C8: =SUM(C5:C7) -> -1.1462 | D8: =SUM(D5:D7) -> -1.7548 | E8: =SUM(E5:E7) -> -0.5086 | F8: =SUM(F5:F7) -> 0.0241 | G8: =SUM(G5:G7) -> 1.7245 | H8: =SUM(H5:H7) -> 3.0567 | I8: =SUM(I5:I7) -> 4.1605 | ... Q8: =SUM(Q5:Q7) -> 69.1607
A9: 资本开支 | B9: =-'输入数据'!$H$7 -> -1.5 | C9: =-'输入数据'!$H$8 -> -1.5 | D9: =-'输入数据'!$H$9 -> -1.5 | E9: =-'输入数据'!$H$10 -> -1.5 | F9: =-'输入数据'!$H$11 -> -1.5 | G9: =-'输入数据'!$H$12 -> -1.5 | H9: =-'输入数据'!$H$13 -> -5.1 | I9: =-'输入数据'!$H$14 -> -6.3 | J9: =-'输入数据'!$H$15 -> -6.3 | K9: =-'输入数据'!$H$16 -> -6.3 | L9: =-'输入数据'!$H$17 -> -8.7 | M9: =-'输入数据'!$H$18 -> -8.7 | N9: =-'输入数据'!$H$19 -> -1.5 | O9: =-'输入数据'!$H$20 -> -1.5 | P9: =-'输入数据'!$H$21 -> -1.5 | Q9: =-'输入数据'!$H$22 -> -1.5
A10: 其他投资活动 | B10: ='输入数据'!$AB$7+'输入数据'!$H$7 -> 0 | C10: ='输入数据'!$AB$8+'输入数据'!$H$8 -> 0 | D10: ='输入数据'!$AB$9+'输入数据'!$H$9 -> 0 | E10: ='输入数据'!$AB$10+'输入数据'!$H$10 -> 0 | F10: ='输入数据'!$AB$11+'输入数据'!$H$11 -> 0 | G10: ='输入数据'!$AB$12+'输入数据'!$H$12 -> 0 | H10: ='输入数据'!$AB$13+'输入数据'!$H$13 -> 0 | I10: ='输入数据'!$AB$14+'输入数据'!$H$14 -> 0 | J10: ='输入数据'!$AB$15+'输入数据'!$H$15 -> 0 | K10: ='输入数据'!$AB$16+'输入数据'!$H$16 -> 0 | L10: ='输入数据'!$AB$17+'输入数据'!$H$17 -> 0 | M10: ='输入数据'!$AB$18+'输入数据'!$H$18 -> 0 | N10: ='输入数据'!$AB$19+'输入数据'!$H$19 -> 0 | O10: ='输入数据'!$AB$20+'输入数据'!$H$20 -> 0 | P10: ='输入数据'!$AB$21+'输入数据'!$H$21 -> 0 | Q10: ='输入数据'!$AB$22+'输入数据'!$H$22 -> 0
A11: 投资活动现金流 | B11: =SUM(B9:B10) -> -1.5 | C11: =SUM(C9:C10) -> -1.5 | D11: =SUM(D9:D10) -> -1.5 | E11: =SUM(E9:E10) -> -1.5 | F11: =SUM(F9:F10) -> -1.5 | G11: =SUM(G9:G10) -> -1.5 | H11: =SUM(H9:H10) -> -5.1 | I11: =SUM(I9:I10) -> -6.3 | ... Q11: =SUM(Q9:Q10) -> -1.5
A12: 新增/(偿还)普通借款 | B12: ='输入数据'!$K$7 -> 0 | C12: ='输入数据'!$K$8 -> 0 | D12: ='输入数据'!$K$9 -> 2 | E12: ='输入数据'!$K$10 -> 2 | F12: ='输入数据'!$K$11 -> 0 | G12: ='输入数据'!$K$12 -> 0 | H12: ='输入数据'!$K$13 -> 1 | I12: ='输入数据'!$K$14 -> 1 | J12: ='输入数据'!$K$15 -> 1.5 | K12: ='输入数据'!$K$16 -> 0 | L12: ='输入数据'!$K$17 -> 0 | M12: ='输入数据'!$K$18 -> -5 | N12: ='输入数据'!$K$19 -> -8.5 | O12: ='输入数据'!$K$20 -> 0 | P12: ='输入数据'!$K$21 -> 0 | Q12: ='输入数据'!$K$22 -> 0
A13: 紧急授信变动 | B13: ='输入数据'!$AD$7 -> 0 | C13: ='输入数据'!$AD$8 -> 0 | D13: ='输入数据'!$AD$9 -> 0 | E13: ='输入数据'!$AD$10 -> 0 | F13: ='输入数据'!$AD$11 -> 0 | G13: ='输入数据'!$AD$12 -> 0 | H13: ='输入数据'!$AD$13 -> 0 | I13: ='输入数据'!$AD$14 -> 0 | J13: ='输入数据'!$AD$15 -> 0 | K13: ='输入数据'!$AD$16 -> 0 | L13: ='输入数据'!$AD$17 -> 0 | M13: ='输入数据'!$AD$18 -> 0 | N13: ='输入数据'!$AD$19 -> 0 | O13: ='输入数据'!$AD$20 -> 0 | P13: ='输入数据'!$AD$21 -> 0 | Q13: ='输入数据'!$AD$22 -> 0
A14: 融资活动现金流 | B14: =SUM(B12:B13) -> 0 | C14: =SUM(C12:C13) -> 0 | D14: =SUM(D12:D13) -> 2 | E14: =SUM(E12:E13) -> 2 | F14: =SUM(F12:F13) -> 0 | G14: =SUM(G12:G13) -> 0 | H14: =SUM(H12:H13) -> 1 | I14: =SUM(I12:I13) -> 1 | ... Q14: =SUM(Q12:Q13) -> 0
A15: 现金净增加额 | B15: =B8+B11+B14 -> -1.077 | C15: =C8+C11+C14 -> -2.6462 | D15: =D8+D11+D14 -> -1.2548 | E15: =E8+E11+E14 -> -0.0086 | F15: =F8+F11+F14 -> -1.4759 | G15: =G8+G11+G14 -> 0.2245 | H15: =H8+H11+H14 -> -1.0433 | I15: =I8+I11+I14 -> -1.1395 | ... Q15: =Q8+Q11+Q14 -> 67.6607
A16: 期初现金 | B16: ='输入数据'!$AE$6 -> 10 | C16: ='输入数据'!$AE$7 -> 8.923 | D16: ='输入数据'!$AE$8 -> 6.2768 | E16: ='输入数据'!$AE$9 -> 5.022 | F16: ='输入数据'!$AE$10 -> 5.0134 | G16: ='输入数据'!$AE$11 -> 3.5375 | H16: ='输入数据'!$AE$12 -> 3.762 | I16: ='输入数据'!$AE$13 -> 2.7187 | J16: ='输入数据'!$AE$14 -> 1.5792 | K16: ='输入数据'!$AE$15 -> 2.3846 | L16: ='输入数据'!$AE$16 -> 2.8644 | M16: ='输入数据'!$AE$17 -> 3.64 | N16: ='输入数据'!$AE$18 -> 3.9945 | O16: ='输入数据'!$AE$19 -> 15.486 | P16: ='输入数据'!$AE$20 -> 48.4887 | Q16: ='输入数据'!$AE$21 -> 100.5387
A17: 期末现金 | B17: =B16+B15 -> 8.923 | C17: =C16+C15 -> 6.2768 | D17: =D16+D15 -> 5.022 | E17: =E16+E15 -> 5.0134 | F17: =F16+F15 -> 3.5375 | G17: =G16+G15 -> 3.762 | H17: =H16+H15 -> 2.7187 | I17: =I16+I15 -> 1.5792 | ... Q17: =Q16+Q15 -> 168.1994
A18: 现金校验 | B18: =B17-'输入数据'!$AE$7 -> 0 | C18: =C17-'输入数据'!$AE$8 -> 0 | D18: =D17-'输入数据'!$AE$9 -> 0 | E18: =E17-'输入数据'!$AE$10 -> 8.8817842e-16 | F18: =F17-'输入数据'!$AE$11 -> -4.4408921e-16 | G18: =G17-'输入数据'!$AE$12 -> 0 | H18: =H17-'输入数据'!$AE$13 -> 4.4408921e-16 | I18: =I17-'输入数据'!$AE$14 -> 2.220446e-16 | J18: =J17-'输入数据'!$AE$15 -> 8.8817842e-16 | K18: =K17-'输入数据'!$AE$16 -> 0 | L18: =L17-'输入数据'!$AE$17 -> 4.4408921e-16 | M18: =M17-'输入数据'!$AE$18 -> 1.7763568e-15 | N18: =N17-'输入数据'!$AE$19 -> 0.0001 | O18: =O17-'输入数据'!$AE$20 -> -7.1054274e-15 | P18: =P17-'输入数据'!$AE$21 -> 0 | Q18: =Q17-'输入数据'!$AE$22 -> 2.8421709e-14

Sheet 分析
A1: 经营分析｜公式指标、情景假设与图表
A2: 绿色为公式，蓝色为可修改假设。存货周转天数按90天/季；年化ROE仅为季度年化的分析口径。
A4: 期末股东权益 | D4: 累计净利润 | G4: 累计经营现金流 | J4: 期末净负债 | M4: HBM累计收入 | P4: 期末产能 | S4: 资金链
A5: ='资产负债表'!Q12 -> 211.7094 | D5: =SUM('利润表'!B18:Q18) -> 176.7495 | G5: =SUM('现金流量表'!B8:Q8) -> 220.5995 | J5: ='资产负债表'!Q18 -> -168.1994 | M5: =SUM('利润表'!B6:Q6) -> 150.9675 | P5: ='资产负债表'!Q17 -> 570 | S5: =IF(COUNTIF('输入数据'!AI7:AI22,">0")=0,"未断裂","检查") -> 未断裂
A8: 情景假设（蓝色可改）与联动结果
A9: 情景季度 | B9: 16 | D9: 普通价格变动 | E9: 0 | G9: HBM价格变动 | H9: 0 | J9: 销货成本变动 | K9: 0 | M9: 所得税率 | N9: 0.15 | P9: 改蓝色假设，C列情景结果自动更新
A11: 项目 | B11: 实际 | C11: 情景 | E11: 情景说明：普通收入与HBM收入分别按各自价格假设变化；营业成本（含跌价）按成本假设变化；其他费用与净利息不变；所得税按所设税率且不为负；情景权益=实际权益+净利润差额。以上为简化假设，不代表引擎重跑结果。
A12: 普通内存收入 | B12: =INDEX('利润表'!$B$5:$Q$5,1,$B$9) -> 42.0396 | C12: =B12*(1+$E$9) -> 42.0396
A13: HBM收入 | B13: =INDEX('利润表'!$B$6:$Q$6,1,$B$9) -> 42.624 | C13: =B13*(1+$H$9) -> 42.624
A14: 营业收入 | B14: =SUM(B12:B13) -> 84.6636 | C14: =SUM(C12:C13) -> 84.6636
A15: 营业成本（含跌价） | B15: =INDEX('利润表'!$B$10:$Q$10,1,$B$9) -> 8.37 | C15: =B15*(1+$K$9) -> 8.37 | E15: 指标口径：存货周转天数=平均存货÷不含跌价销货成本×90；年化ROE=当季净利润×4÷平均权益；净负债=普通债务+紧急债务−现金。期初余额来自q00_state.json。
A16: 毛利 | B16: =B14-B15 -> 76.2936 | C16: =C14-C15 -> 76.2936
A17: 毛利率 | B17: =IFERROR(B16/B14,0) -> 0.90113815 | C17: =IFERROR(C16/C14,0) -> 0.90113815
A18: 税前利润 | B18: =INDEX('利润表'!$B$16:$Q$16,1,$B$9) -> 76.0479 | C18: =B18+(C14-B14)-(C15-B15) -> 76.0479
A19: 所得税 | B19: =INDEX('利润表'!$B$17:$Q$17,1,$B$9) -> 11.4072 | C19: =MAX(0,C18*$N$9) -> 11.4072
A20: 净利润 | B20: =INDEX('利润表'!$B$18:$Q$18,1,$B$9) -> 64.6407 | C20: =B20+(C18-B18)-(C19-B19) -> 64.6407
A21: 期末股东权益 | B21: =INDEX('资产负债表'!$B$12:$Q$12,1,$B$9) -> 211.7094 | C21: =B21+(C20-B20) -> 211.7094
A24: 季度 | B24: 营业收入 | C24: 净利润 | D24: 毛利率 | E24: 存货周转天数 | F24: 经营现金流 | G24: 净负债 | H24: 年化ROE | I24: 股东权益 | J24: 现金 | K24: 产能 | L24: 库存量 | M24: 开工率 | N24: HBM产量 | O24: HBM收入占比 | P24: 资本开支 | Q24: 普通价格 | R24: HBM价格 | S24: 普通债务 | T24: 紧急债务
A25: 1 | B25: ='利润表'!B7 -> 4.608 | C25: ='利润表'!B18 -> -1.7341 | D25: =IFERROR('利润表'!B11/'利润表'!B7,0) -> 0.070724826 | E25: =IFERROR(AVERAGE('输入数据'!$AF$6,'输入数据'!$AF$7)/'利润表'!B8*90,0) -> 18.526074 | F25: ='现金流量表'!B8 -> 0.423 | G25: ='资产负债表'!B18 -> -2.923 | H25: =IFERROR('利润表'!B18*4/AVERAGE('输入数据'!$AK$6,'输入数据'!$AK$7),0) -> -0.20345555 | I25: ='资产负债表'!B12 -> 33.2259 | J25: ='资产负债表'!B5 -> 8.923 | K25: ='资产负债表'!B17 -> 300 | L25: ='资产负债表'!B16 -> 45 | M25: ='输入数据'!$F$7 -> 0.75 | N25: ='输入数据'!$M$7 -> 0 | O25: =IFERROR('利润表'!B6/'利润表'!B7,0) -> 0 | P25: ='输入数据'!$H$7 -> 1.5 | Q25: ='输入数据'!$B$7 -> 0.8 | R25: ='输入数据'!$C$7 -> 1.6 | S25: ='输入数据'!$AH$7 -> 6 | T25: ='输入数据'!$AI$7 -> 0
A26: 2 | B26: ='利润表'!C7 -> 2.8224 | C26: ='利润表'!C18 -> -3.7576 | D26: =IFERROR('利润表'!C11/'利润表'!C7,0) -> -0.59842687 | E26: =IFERROR(AVERAGE('输入数据'!$AF$7,'输入数据'!$AF$8)/'利润表'!C8*90,0) -> 10.19456 | F26: ='现金流量表'!C8 -> -1.1462 | G26: ='资产负债表'!C18 -> -0.2768 | H26: =IFERROR('利润表'!C18*4/AVERAGE('输入数据'!$AK$7,'输入数据'!$AK$8),0) -> -0.47948295 | I26: ='资产负债表'!C12 -> 29.4683 | J26: ='资产负债表'!C5 -> 6.2768 | K26: ='资产负债表'!C17 -> 300 | L26: ='资产负债表'!C16 -> 15 | M26: ='输入数据'!$F$8 -> 0.6 | N26: ='输入数据'!$M$8 -> 0 | O26: =IFERROR('利润表'!C6/'利润表'!C7,0) -> 0 | P26: ='输入数据'!$H$8 -> 1.5 | Q26: ='输入数据'!$B$8 -> 0.56 | R26: ='输入数据'!$C$8 -> 1.4 | S26: ='输入数据'!$AH$8 -> 6 | T26: ='输入数据'!$AI$8 -> 0
A27: 3 | B27: ='利润表'!D7 -> 2.16 | C27: ='利润表'!D18 -> -3.9463 | D27: =IFERROR('利润表'!D11/'利润表'!D7,0) -> -0.85949074 | E27: =IFERROR(AVERAGE('输入数据'!$AF$8,'输入数据'!$AF$9)/'利润表'!D8*90,0) -> 2.1455247 | F27: ='现金流量表'!D8 -> -1.7548 | G27: ='资产负债表'!D18 -> 2.978 | H27: =IFERROR('利润表'!D18*4/AVERAGE('输入数据'!$AK$8,'输入数据'!$AK$9),0) -> -0.57410852 | I27: ='资产负债表'!D12 -> 25.522 | J27: ='资产负债表'!D5 -> 5.022 | K27: ='资产负债表'!D17 -> 300 | L27: ='资产负债表'!D16 -> 0 | M27: ='输入数据'!$F$9 -> 0.55 | N27: ='输入数据'!$M$9 -> 0 | O27: =IFERROR('利润表'!D6/'利润表'!D7,0) -> 0 | P27: ='输入数据'!$H$9 -> 1.5 | Q27: ='输入数据'!$B$9 -> 0.5 | R27: ='输入数据'!$C$9 -> 1.3 | S27: ='输入数据'!$AH$9 -> 8 | T27: ='输入数据'!$AI$9 -> 0
A28: 4 | B28: ='利润表'!E7 -> 2.6712 | C28: ='利润表'!E18 -> -2.5086 | D28: =IFERROR('利润表'!E11/'利润表'!E7,0) -> -0.51617251 | E28: =IFERROR(AVERAGE('输入数据'!$AF$9,'输入数据'!$AF$10)/'利润表'!E8*90,0) -> 0 | F28: ='现金流量表'!E8 -> -0.5086 | G28: ='资产负债表'!E18 -> 4.9866 | H28: =IFERROR('利润表'!E18*4/AVERAGE('输入数据'!$AK$9,'输入数据'!$AK$10),0) -> -0.41348789 | I28: ='资产负债表'!E12 -> 23.0134 | J28: ='资产负债表'!E5 -> 5.0134 | K28: ='资产负债表'!E17 -> 300 | L28: ='资产负债表'!E16 -> 0 | M28: ='输入数据'!$F$10 -> 0.7 | N28: ='输入数据'!$M$10 -> 0 | O28: =IFERROR('利润表'!E6/'利润表'!E7,0) -> 0 | P28: ='输入数据'!$H$10 -> 1.5 | Q28: ='输入数据'!$B$10 -> 0.53 | R28: ='输入数据'!$C$10 -> 1.4 | S28: ='输入数据'!$AH$10 -> 10 | T28: ='输入数据'!$AI$10 -> 0
A29: 5 | B29: ='利润表'!F7 -> 3.384 | C29: ='利润表'!F18 -> -1.9825 | D29: =IFERROR('利润表'!F11/'利润表'!F7,0) -> -0.24308511 | E29: =IFERROR(AVERAGE('输入数据'!$AF$10,'输入数据'!$AF$11)/'利润表'!F8*90,0) -> 0.73532574 | F29: ='现金流量表'!F8 -> 0.0241 | G29: ='资产负债表'!F18 -> 6.4625 | H29: =IFERROR('利润表'!F18*4/AVERAGE('输入数据'!$AK$10,'输入数据'!$AK$11),0) -> -0.360092 | I29: ='资产负债表'!F12 -> 21.0309 | J29: ='资产负债表'!F5 -> 3.5375 | K29: ='资产负债表'!F17 -> 300 | L29: ='资产负债表'!F16 -> 5 | M29: ='输入数据'!$F$11 -> 0.8 | N29: ='输入数据'!$M$11 -> 0 | O29: =IFERROR('利润表'!F6/'利润表'!F7,0) -> 0 | P29: ='输入数据'!$H$11 -> 1.5 | Q29: ='输入数据'!$B$11 -> 0.6 | R29: ='输入数据'!$C$11 -> 1.6 | S29: ='输入数据'!$AH$11 -> 10 | T29: ='输入数据'!$AI$11 -> 0
A30: 6 | B30: ='利润表'!G7 -> 5.2462 | C30: ='利润表'!G18 -> -0.4939 | D30: =IFERROR('利润表'!G11/'利润表'!G7,0) -> 0.12919828 | E30: =IFERROR(AVERAGE('输入数据'!$AF$11,'输入数据'!$AF$12)/'利润表'!G8*90,0) -> 0.67375887 | F30: ='现金流量表'!G8 -> 1.7245 | G30: ='资产负债表'!G18 -> 6.238 | H30: =IFERROR('利润表'!G18*4/AVERAGE('输入数据'!$AK$11,'输入数据'!$AK$12),0) -> -0.095054116 | I30: ='资产负债表'!G12 -> 20.537 | J30: ='资产负债表'!G5 -> 3.762 | K30: ='资产负债表'!G17 -> 300 | L30: ='资产负债表'!G16 -> 0 | M30: ='输入数据'!$F$12 -> 0.9 | N30: ='输入数据'!$M$12 -> 18.9 | O30: =IFERROR('利润表'!G6/'利润表'!G7,0) -> 0.1564561 | P30: ='输入数据'!$H$12 -> 1.5 | Q30: ='输入数据'!$B$12 -> 0.72 | R30: ='输入数据'!$C$12 -> 1.9 | S30: ='输入数据'!$AH$12 -> 10 | T30: ='输入数据'!$AI$12 -> 0
A31: 7 | B31: ='利润表'!H7 -> 6.8734 | C31: ='利润表'!H18 -> 0.8317 | D31: =IFERROR('利润表'!H11/'利润表'!H7,0) -> 0.31256729 | E31: =IFERROR(AVERAGE('输入数据'!$AF$12,'输入数据'!$AF$13)/'利润表'!H8*90,0) -> 0 | F31: ='现金流量表'!H8 -> 3.0567 | G31: ='资产负债表'!H18 -> 8.2813 | H31: =IFERROR('利润表'!H18*4/AVERAGE('输入数据'!$AK$12,'输入数据'!$AK$13),0) -> 0.15877554 | I31: ='资产负债表'!H12 -> 21.3687 | J31: ='资产负债表'!H5 -> 2.7187 | K31: ='资产负债表'!H17 -> 300 | L31: ='资产负债表'!H16 -> 0 | M31: ='输入数据'!$F$13 -> 1 | N31: ='输入数据'!$M$13 -> 27 | O31: =IFERROR('利润表'!H6/'利润表'!H7,0) -> 0.20880496 | P31: ='输入数据'!$H$13 -> 5.1 | Q31: ='输入数据'!$B$13 -> 0.83 | R31: ='输入数据'!$C$13 -> 2.3 | S31: ='输入数据'!$AH$13 -> 11 | T31: ='输入数据'!$AI$13 -> 0
A32: 8 | B32: ='利润表'!I7 -> 8.1821 | C32: ='利润表'!I18 -> 1.8605 | D32: =IFERROR('利润表'!I11/'利润表'!I7,0) -> 0.41335354 | E32: =IFERROR(AVERAGE('输入数据'!$AF$13,'输入数据'!$AF$14)/'利润表'!I8*90,0) -> 0 | F32: ='现金流量表'!I8 -> 4.1605 | G32: ='资产负债表'!I18 -> 10.4208 | H32: =IFERROR('利润表'!I18*4/AVERAGE('输入数据'!$AK$13,'输入数据'!$AK$14),0) -> 0.33373769 | I32: ='资产负债表'!I12 -> 23.2292 | J32: ='资产负债表'!I5 -> 1.5792 | K32: ='资产负债表'!I17 -> 300 | L32: ='资产负债表'!I16 -> 0 | M32: ='输入数据'!$F$14 -> 1 | N32: ='输入数据'!$M$14 -> 39 | O32: =IFERROR('利润表'!I6/'利润表'!I7,0) -> 0.29566982 | P32: ='输入数据'!$H$14 -> 6.3 | Q32: ='输入数据'!$B$14 -> 0.92 | R32: ='输入数据'!$C$14 -> 2.8 | S32: ='输入数据'!$AH$14 -> 12 | T32: ='输入数据'!$AI$14 -> 0
A33: 9 | B33: ='利润表'!J7 -> 9.8928 | C33: ='利润表'!J18 -> 3.2304 | D33: =IFERROR('利润表'!J11/'利润表'!J7,0) -> 0.50721737 | E33: =IFERROR(AVERAGE('输入数据'!$AF$14,'输入数据'!$AF$15)/'利润表'!J8*90,0) -> 0 | F33: ='现金流量表'!J8 -> 5.6054 | G33: ='资产负债表'!J18 -> 11.1154 | H33: =IFERROR('利润表'!J18*4/AVERAGE('输入数据'!$AK$14,'输入数据'!$AK$15),0) -> 0.52010111 | I33: ='资产负债表'!J12 -> 26.4596 | J33: ='资产负债表'!J5 -> 2.3846 | K33: ='资产负债表'!J17 -> 300 | L33: ='资产负债表'!J16 -> 0 | M33: ='输入数据'!$F$15 -> 1 | N33: ='输入数据'!$M$15 -> 51 | O33: =IFERROR('利润表'!J6/'利润表'!J7,0) -> 0.39592431 | P33: ='输入数据'!$H$15 -> 6.3 | Q33: ='输入数据'!$B$15 -> 1 | R33: ='输入数据'!$C$15 -> 3.4 | S33: ='输入数据'!$AH$15 -> 13.5 | T33: ='输入数据'!$AI$15 -> 0
A34: 10 | B34: ='利润表'!K7 -> 11.2774 | C34: ='利润表'!K18 -> 4.3298 | D34: =IFERROR('利润表'!K11/'利润表'!K7,0) -> 0.56106904 | E34: =IFERROR(AVERAGE('输入数据'!$AF$15,'输入数据'!$AF$16)/'利润表'!K8*90,0) -> 0 | F34: ='现金流量表'!K8 -> 6.7798 | G34: ='资产负债表'!K18 -> 10.6356 | H34: =IFERROR('利润表'!K18*4/AVERAGE('输入数据'!$AK$15,'输入数据'!$AK$16),0) -> 0.60504812 | I34: ='资产负债表'!K12 -> 30.7894 | J34: ='资产负债表'!K5 -> 2.8644 | K34: ='资产负债表'!K17 -> 300 | L34: ='资产负债表'!K16 -> 0 | M34: ='输入数据'!$F$16 -> 1 | N34: ='输入数据'!$M$16 -> 63 | O34: =IFERROR('利润表'!K6/'利润表'!K7,0) -> 0.51075603 | P34: ='输入数据'!$H$16 -> 6.3 | Q34: ='输入数据'!$B$16 -> 0.97 | R34: ='输入数据'!$C$16 -> 4 | S34: ='输入数据'!$AH$16 -> 13.5 | T34: ='输入数据'!$AI$16 -> 0
A35: 11 | B35: ='利润表'!L7 -> 14.55 | C35: ='利润表'!L18 -> 6.7706 | D35: =IFERROR('利润表'!L11/'利润表'!L7,0) -> 0.63195876 | E35: =IFERROR(AVERAGE('输入数据'!$AF$16,'输入数据'!$AF$17)/'利润表'!L8*90,0) -> 0 | F35: ='现金流量表'!L8 -> 9.4756 | G35: ='资产负债表'!L18 -> 9.86 | H35: =IFERROR('利润表'!L18*4/AVERAGE('输入数据'!$AK$16,'输入数据'!$AK$17),0) -> 0.79246928 | I35: ='资产负债表'!L12 -> 37.56 | J35: ='资产负债表'!L5 -> 3.64 | K35: ='资产负债表'!L17 -> 330 | L35: ='资产负债表'!L16 -> 0 | M35: ='输入数据'!$F$17 -> 1 | N35: ='输入数据'!$M$17 -> 79.2 | O35: =IFERROR('利润表'!L6/'利润表'!L7,0) -> 0.56148454 | P35: ='输入数据'!$H$17 -> 8.7 | Q35: ='输入数据'!$B$17 -> 1.06 | R35: ='输入数据'!$C$17 -> 4.6 | S35: ='输入数据'!$AH$17 -> 13.5 | T35: ='输入数据'!$AI$17 -> 0
A36: 12 | B36: ='利润表'!M7 -> 20.0751 | C36: ='利润表'!M18 -> 11.0345 | D36: =IFERROR('利润表'!M11/'利润表'!M7,0) -> 0.70759797 | E36: =IFERROR(AVERAGE('输入数据'!$AF$17,'输入数据'!$AF$18)/'利润表'!M8*90,0) -> 0 | F36: ='现金流量表'!M8 -> 14.0545 | G36: ='资产负债表'!M18 -> 4.5055 | H36: =IFERROR('利润表'!M18*4/AVERAGE('输入数据'!$AK$17,'输入数据'!$AK$18),0) -> 1.0246244 | I36: ='资产负债表'!M12 -> 48.5945 | J36: ='资产负债表'!M5 -> 3.9945 | K36: ='资产负债表'!M17 -> 370 | L36: ='资产负债表'!M16 -> 0 | M36: ='输入数据'!$F$18 -> 1 | N36: ='输入数据'!$M$18 -> 96.2 | O36: =IFERROR('利润表'!M6/'利润表'!M7,0) -> 0.58101828 | P36: ='输入数据'!$H$18 -> 8.7 | Q36: ='输入数据'!$B$18 -> 1.28 | R36: ='输入数据'!$C$18 -> 5.4 | S36: ='输入数据'!$AH$18 -> 8.5 | T36: ='输入数据'!$AI$18 -> 0
A37: 13 | B37: ='利润表'!N7 -> 28.8912 | C37: ='利润表'!N18 -> 18.1566 | D37: =IFERROR('利润表'!N11/'利润表'!N7,0) -> 0.77899845 | E37: =IFERROR(AVERAGE('输入数据'!$AF$18,'输入数据'!$AF$19)/'利润表'!N8*90,0) -> 0 | F37: ='现金流量表'!N8 -> 21.4916 | G37: ='资产负债表'!N18 -> -15.486 | H37: =IFERROR('利润表'!N18*4/AVERAGE('输入数据'!$AK$18,'输入数据'!$AK$19),0) -> 1.2592845 | I37: ='资产负债表'!N12 -> 66.751 | J37: ='资产负债表'!N5 -> 15.486 | K37: ='资产负债表'!N17 -> 410 | L37: ='资产负债表'!N16 -> 0 | M37: ='输入数据'!$F$19 -> 1 | N37: ='输入数据'!$M$19 -> 107.83 | O37: =IFERROR('利润表'!N6/'利润表'!N7,0) -> 0.57327837 | P37: ='输入数据'!$H$19 -> 1.5 | Q37: ='输入数据'!$B$19 -> 1.7 | R37: ='输入数据'!$C$19 -> 6.4 | S37: ='输入数据'!$AH$19 -> 0 | T37: ='输入数据'!$AI$19 -> 0
A38: 14 | B38: ='利润表'!O7 -> 44.1234 | C38: ='利润表'!O18 -> 30.8527 | D38: =IFERROR('利润表'!O11/'利润表'!O7,0) -> 0.84362039 | E38: =IFERROR(AVERAGE('输入数据'!$AF$19,'输入数据'!$AF$20)/'利润表'!O8*90,0) -> 0 | F38: ='现金流量表'!O8 -> 34.5027 | G38: ='资产负债表'!O18 -> -48.4887 | H38: =IFERROR('利润表'!O18*4/AVERAGE('输入数据'!$AK$19,'输入数据'!$AK$20),0) -> 1.5017617 | I38: ='资产负债表'!O12 -> 97.6037 | J38: ='资产负债表'!O5 -> 48.4887 | K38: ='资产负债表'!O17 -> 450 | L38: ='资产负债表'!O16 -> 0 | M38: ='输入数据'!$F$20 -> 1 | N38: ='输入数据'!$M$20 -> 130.5 | O38: =IFERROR('利润表'!O6/'利润表'!O7,0) -> 0.53946885 | P38: ='输入数据'!$H$20 -> 1.5 | Q38: ='输入数据'!$B$20 -> 2.65 | R38: ='输入数据'!$C$20 -> 7.6 | S38: ='输入数据'!$AH$20 -> 0 | T38: ='输入数据'!$AI$20 -> 0
A39: 15 | B39: ='利润表'!P7 -> 66.4912 | C39: ='利润表'!P18 -> 49.465 | D39: =IFERROR('利润表'!P11/'利润表'!P7,0) -> 0.88517277 | E39: =IFERROR(AVERAGE('输入数据'!$AF$20,'输入数据'!$AF$21)/'利润表'!P8*90,0) -> 0 | F39: ='现金流量表'!P8 -> 53.55 | G39: ='资产负债表'!P18 -> -100.5387 | H39: =IFERROR('利润表'!P18*4/AVERAGE('输入数据'!$AK$20,'输入数据'!$AK$21),0) -> 1.6173463 | I39: ='资产负债表'!P12 -> 147.0687 | J39: ='资产负债表'!P5 -> 100.5387 | K39: ='资产负债表'!P17 -> 510 | L39: ='资产负债表'!P16 -> 0 | M39: ='输入数据'!$F$21 -> 1 | N39: ='输入数据'!$M$21 -> 160.65 | O39: =IFERROR('利润表'!P6/'利润表'!P7,0) -> 0.50821763 | P39: ='输入数据'!$H$21 -> 1.5 | Q39: ='输入数据'!$B$21 -> 3.9 | R39: ='输入数据'!$C$21 -> 8.8 | S39: ='输入数据'!$AH$21 -> 0 | T39: ='输入数据'!$AI$21 -> 0
A40: 16 | B40: ='利润表'!Q7 -> 84.6636 | C40: ='利润表'!Q18 -> 64.6407 | D40: =IFERROR('利润表'!Q11/'利润表'!Q7,0) -> 0.90113815 | E40: =IFERROR(AVERAGE('输入数据'!$AF$21,'输入数据'!$AF$22)/'利润表'!Q8*90,0) -> 0 | F40: ='现金流量表'!Q8 -> 69.1607 | G40: ='资产负债表'!Q18 -> -168.1994 | H40: =IFERROR('利润表'!Q18*4/AVERAGE('输入数据'!$AK$21,'输入数据'!$AK$22),0) -> 1.4413522 | I40: ='资产负债表'!Q12 -> 211.7094 | J40: ='资产负债表'!Q5 -> 168.1994 | K40: ='资产负债表'!Q17 -> 570 | L40: ='资产负债表'!Q16 -> 0 | M40: ='输入数据'!$F$22 -> 1 | N40: ='输入数据'!$M$22 -> 185.02 | O40: =IFERROR('利润表'!Q6/'利润表'!Q7,0) -> 0.50345131 | P40: ='输入数据'!$H$22 -> 1.5 | Q40: ='输入数据'!$B$22 -> 4.55 | R40: ='输入数据'!$C$22 -> 9.6 | S40: ='输入数据'!$AH$22 -> 0 | T40: ='输入数据'!$AI$22 -> 0

Sheet 校验
A1: 校验｜公式结果对照引擎披露值
A2: 所有数值为绝对差异，单位为十亿美元；容差0.0002（即20万美元），用于容纳引擎四位小数舍入。
A4: 总体状态 | C4: =IF(MAX(B10:J25)<0.0002,"全部通过","检查差异") -> 全部通过 | F4: 修改输入或假设后，本页可检查三表勾稽是否仍然成立。情景分析不改变实际报表，因此不影响这些校验。
A9: 季度 | B9: 收入差异 | C9: 毛利差异 | D9: 营业利润差异 | E9: 净利润差异 | F9: 资产差异 | G9: 现金滚动差异 | H9: 资产平衡差异 | I9: 投资现金流差异 | J9: 融资现金流差异
A10: 1 | B10: =ABS('利润表'!B7-'输入数据'!$AM$7) -> 0 | C10: =ABS('利润表'!B11-'输入数据'!$AN$7) -> 0 | D10: =ABS('利润表'!B14-'输入数据'!$AO$7) -> 0 | E10: =ABS('利润表'!B18-'输入数据'!$AP$7) -> 0 | F10: =ABS('资产负债表'!B8-'输入数据'!$AQ$7) -> 0 | G10: =ABS('现金流量表'!B18) -> 0 | H10: =ABS('资产负债表'!B14) -> 0 | I10: =ABS('现金流量表'!B11-'输入数据'!$AB$7) -> 0 | J10: =ABS('现金流量表'!B14-'输入数据'!$AC$7) -> 0
A11: 2 | B11: =ABS('利润表'!C7-'输入数据'!$AM$8) -> 0 | C11: =ABS('利润表'!C11-'输入数据'!$AN$8) -> 0 | D11: =ABS('利润表'!C14-'输入数据'!$AO$8) -> 0 | E11: =ABS('利润表'!C18-'输入数据'!$AP$8) -> 0 | F11: =ABS('资产负债表'!C8-'输入数据'!$AQ$8) -> 0 | G11: =ABS('现金流量表'!C18) -> 0 | H11: =ABS('资产负债表'!C14) -> 0 | I11: =ABS('现金流量表'!C11-'输入数据'!$AB$8) -> 0 | J11: =ABS('现金流量表'!C14-'输入数据'!$AC$8) -> 0
A12: 3 | B12: =ABS('利润表'!D7-'输入数据'!$AM$9) -> 0 | C12: =ABS('利润表'!D11-'输入数据'!$AN$9) -> 0 | D12: =ABS('利润表'!D14-'输入数据'!$AO$9) -> 0 | E12: =ABS('利润表'!D18-'输入数据'!$AP$9) -> 0 | F12: =ABS('资产负债表'!D8-'输入数据'!$AQ$9) -> 0 | G12: =ABS('现金流量表'!D18) -> 0 | H12: =ABS('资产负债表'!D14) -> 0 | I12: =ABS('现金流量表'!D11-'输入数据'!$AB$9) -> 0 | J12: =ABS('现金流量表'!D14-'输入数据'!$AC$9) -> 0
A13: 4 | B13: =ABS('利润表'!E7-'输入数据'!$AM$10) -> 0 | C13: =ABS('利润表'!E11-'输入数据'!$AN$10) -> 0 | D13: =ABS('利润表'!E14-'输入数据'!$AO$10) -> 0 | E13: =ABS('利润表'!E18-'输入数据'!$AP$10) -> 0 | F13: =ABS('资产负债表'!E8-'输入数据'!$AQ$10) -> 0 | G13: =ABS('现金流量表'!E18) -> 0 | H13: =ABS('资产负债表'!E14) -> 0 | I13: =ABS('现金流量表'!E11-'输入数据'!$AB$10) -> 0 | J13: =ABS('现金流量表'!E14-'输入数据'!$AC$10) -> 0
A14: 5 | B14: =ABS('利润表'!F7-'输入数据'!$AM$11) -> 0 | C14: =ABS('利润表'!F11-'输入数据'!$AN$11) -> 0 | D14: =ABS('利润表'!F14-'输入数据'!$AO$11) -> 0 | E14: =ABS('利润表'!F18-'输入数据'!$AP$11) -> 0 | F14: =ABS('资产负债表'!F8-'输入数据'!$AQ$11) -> 0 | G14: =ABS('现金流量表'!F18) -> 0 | H14: =ABS('资产负债表'!F14) -> 0 | I14: =ABS('现金流量表'!F11-'输入数据'!$AB$11) -> 0 | J14: =ABS('现金流量表'!F14-'输入数据'!$AC$11) -> 0
A15: 6 | B15: =ABS('利润表'!G7-'输入数据'!$AM$12) -> 0 | C15: =ABS('利润表'!G11-'输入数据'!$AN$12) -> 0 | D15: =ABS('利润表'!G14-'输入数据'!$AO$12) -> 0 | E15: =ABS('利润表'!G18-'输入数据'!$AP$12) -> 0 | F15: =ABS('资产负债表'!G8-'输入数据'!$AQ$12) -> 0 | G15: =ABS('现金流量表'!G18) -> 0 | H15: =ABS('资产负债表'!G14) -> 0 | I15: =ABS('现金流量表'!G11-'输入数据'!$AB$12) -> 0 | J15: =ABS('现金流量表'!G14-'输入数据'!$AC$12) -> 0
A16: 7 | B16: =ABS('利润表'!H7-'输入数据'!$AM$13) -> 0 | C16: =ABS('利润表'!H11-'输入数据'!$AN$13) -> 0 | D16: =ABS('利润表'!H14-'输入数据'!$AO$13) -> 0 | E16: =ABS('利润表'!H18-'输入数据'!$AP$13) -> 0 | F16: =ABS('资产负债表'!H8-'输入数据'!$AQ$13) -> 0 | G16: =ABS('现金流量表'!H18) -> 0 | H16: =ABS('资产负债表'!H14) -> 0 | I16: =ABS('现金流量表'!H11-'输入数据'!$AB$13) -> 0 | J16: =ABS('现金流量表'!H14-'输入数据'!$AC$13) -> 0
A17: 8 | B17: =ABS('利润表'!I7-'输入数据'!$AM$14) -> 0 | C17: =ABS('利润表'!I11-'输入数据'!$AN$14) -> 0 | D17: =ABS('利润表'!I14-'输入数据'!$AO$14) -> 0 | E17: =ABS('利润表'!I18-'输入数据'!$AP$14) -> 0 | F17: =ABS('资产负债表'!I8-'输入数据'!$AQ$14) -> 0 | G17: =ABS('现金流量表'!I18) -> 0 | H17: =ABS('资产负债表'!I14) -> 0 | I17: =ABS('现金流量表'!I11-'输入数据'!$AB$14) -> 0 | J17: =ABS('现金流量表'!I14-'输入数据'!$AC$14) -> 0
A18: 9 | B18: =ABS('利润表'!J7-'输入数据'!$AM$15) -> 0 | C18: =ABS('利润表'!J11-'输入数据'!$AN$15) -> 0 | D18: =ABS('利润表'!J14-'输入数据'!$AO$15) -> 0 | E18: =ABS('利润表'!J18-'输入数据'!$AP$15) -> 0 | F18: =ABS('资产负债表'!J8-'输入数据'!$AQ$15) -> 0 | G18: =ABS('现金流量表'!J18) -> 0 | H18: =ABS('资产负债表'!J14) -> 0 | I18: =ABS('现金流量表'!J11-'输入数据'!$AB$15) -> 0 | J18: =ABS('现金流量表'!J14-'输入数据'!$AC$15) -> 0
A19: 10 | B19: =ABS('利润表'!K7-'输入数据'!$AM$16) -> 0 | C19: =ABS('利润表'!K11-'输入数据'!$AN$16) -> 0 | D19: =ABS('利润表'!K14-'输入数据'!$AO$16) -> 0 | E19: =ABS('利润表'!K18-'输入数据'!$AP$16) -> 0 | F19: =ABS('资产负债表'!K8-'输入数据'!$AQ$16) -> 0 | G19: =ABS('现金流量表'!K18) -> 0 | H19: =ABS('资产负债表'!K14) -> 0 | I19: =ABS('现金流量表'!K11-'输入数据'!$AB$16) -> 0 | J19: =ABS('现金流量表'!K14-'输入数据'!$AC$16) -> 0
A20: 11 | B20: =ABS('利润表'!L7-'输入数据'!$AM$17) -> 0 | C20: =ABS('利润表'!L11-'输入数据'!$AN$17) -> 0 | D20: =ABS('利润表'!L14-'输入数据'!$AO$17) -> 0 | E20: =ABS('利润表'!L18-'输入数据'!$AP$17) -> 0 | F20: =ABS('资产负债表'!L8-'输入数据'!$AQ$17) -> 0 | G20: =ABS('现金流量表'!L18) -> 0 | H20: =ABS('资产负债表'!L14) -> 0 | I20: =ABS('现金流量表'!L11-'输入数据'!$AB$17) -> 0 | J20: =ABS('现金流量表'!L14-'输入数据'!$AC$17) -> 0
A21: 12 | B21: =ABS('利润表'!M7-'输入数据'!$AM$18) -> 0 | C21: =ABS('利润表'!M11-'输入数据'!$AN$18) -> 0 | D21: =ABS('利润表'!M14-'输入数据'!$AO$18) -> 0 | E21: =ABS('利润表'!M18-'输入数据'!$AP$18) -> 0 | F21: =ABS('资产负债表'!M8-'输入数据'!$AQ$18) -> 0 | G21: =ABS('现金流量表'!M18) -> 0 | H21: =ABS('资产负债表'!M14) -> 0 | I21: =ABS('现金流量表'!M11-'输入数据'!$AB$18) -> 0 | J21: =ABS('现金流量表'!M14-'输入数据'!$AC$18) -> 0
A22: 13 | B22: =ABS('利润表'!N7-'输入数据'!$AM$19) -> 0 | C22: =ABS('利润表'!N11-'输入数据'!$AN$19) -> 0 | D22: =ABS('利润表'!N14-'输入数据'!$AO$19) -> 0 | E22: =ABS('利润表'!N18-'输入数据'!$AP$19) -> 0 | F22: =ABS('资产负债表'!N8-'输入数据'!$AQ$19) -> 0 | G22: =ABS('现金流量表'!N18) -> 0 | H22: =ABS('资产负债表'!N14) -> 0 | I22: =ABS('现金流量表'!N11-'输入数据'!$AB$19) -> 0 | J22: =ABS('现金流量表'!N14-'输入数据'!$AC$19) -> 0
A23: 14 | B23: =ABS('利润表'!O7-'输入数据'!$AM$20) -> 0 | C23: =ABS('利润表'!O11-'输入数据'!$AN$20) -> 0 | D23: =ABS('利润表'!O14-'输入数据'!$AO$20) -> 0 | E23: =ABS('利润表'!O18-'输入数据'!$AP$20) -> 0 | F23: =ABS('资产负债表'!O8-'输入数据'!$AQ$20) -> 0 | G23: =ABS('现金流量表'!O18) -> 0 | H23: =ABS('资产负债表'!O14) -> 0 | I23: =ABS('现金流量表'!O11-'输入数据'!$AB$20) -> 0 | J23: =ABS('现金流量表'!O14-'输入数据'!$AC$20) -> 0
A24: 15 | B24: =ABS('利润表'!P7-'输入数据'!$AM$21) -> 0 | C24: =ABS('利润表'!P11-'输入数据'!$AN$21) -> 0 | D24: =ABS('利润表'!P14-'输入数据'!$AO$21) -> 0 | E24: =ABS('利润表'!P18-'输入数据'!$AP$21) -> 0 | F24: =ABS('资产负债表'!P8-'输入数据'!$AQ$21) -> 0 | G24: =ABS('现金流量表'!P18) -> 0 | H24: =ABS('资产负债表'!P14) -> 0 | I24: =ABS('现金流量表'!P11-'输入数据'!$AB$21) -> 0 | J24: =ABS('现金流量表'!P14-'输入数据'!$AC$21) -> 0
A25: 16 | B25: =ABS('利润表'!Q7-'输入数据'!$AM$22) -> 0 | C25: =ABS('利润表'!Q11-'输入数据'!$AN$22) -> 0 | D25: =ABS('利润表'!Q14-'输入数据'!$AO$22) -> 0 | E25: =ABS('利润表'!Q18-'输入数据'!$AP$22) -> 0 | F25: =ABS('资产负债表'!Q8-'输入数据'!$AQ$22) -> 0 | G25: =ABS('现金流量表'!Q18) -> 0 | H25: =ABS('资产负债表'!Q14) -> 0 | I25: =ABS('现金流量表'!Q11-'输入数据'!$AB$22) -> 0 | J25: =ABS('现金流量表'!Q14-'输入数据'!$AC$22) -> 0
