Workbook

Sheet 导览与假设
A1: 晶序内存 / 导览与假设
A3: 模拟经营 · 金额：十亿美元 USD bn；数量：千片 · 蓝色=源数据；浅绿=公式；浅黄=假设
A4: 项目 / 季度 | B4: Q01 | C4: Q02 | D4: Q03 | E4: Q04 | F4: Q05 | G4: Q06 | H4: Q07 | I4: Q08 | J4: Q09 | K4: Q10 | L4: Q11 | M4: Q12 | N4: Q13 | O4: Q14 | P4: Q15 | Q4: Q16 | R4: 来源 / 口径
A5: 仅黄色单元格为分析假设；不改写已发生经营结果。
A6: 季度天数（假设） | B6: 90 | C6: 用于存货周转天数，统一90天。
A7: 全年季度数（假设） | B7: 4 | C7: 仅用于年化ROE；不是全年实际收益。
A8: 收入压力比例（假设） | B8: 0.2 | C8: 收入下降20%，成本/费用/产销/利息不变；无库存、营运资金响应。
A9: 税率（规则） | B9: 0.15 | C9: 规则.txt：仅盈利征税。
A10: 最低现金缓冲（假设） | B10: 3 | C10: 分析目标，不是引擎0.5的紧急授信触发线。
A11: 期初现金（事实） | B11: 10 | C11: Q01_决策前.json → balance_sheet_now.cash
A12: 期初库存账面价值（事实） | B12: 0.96 | C12: Q01_决策前.json → balance_sheet_now.inventory
A13: 期初股东权益（事实） | B13: 34.96 | C13: Q01_决策前.json → balance_sheet_now.equity
A14: 期初普通借款（事实） | B14: 6 | C14: Q01_决策前.json → balance_sheet_now.debt
A15: 期初固定资产净额（事实） | B15: 30 | C15: Q01_决策前.json → balance_sheet_now.ppe_net
A18: 读取路径：原始数据 → 三张表 → 经营分析。所有逐季事实仅来自完整导出，Q0来自首季状态。
A19: 毛利率=毛利/营业收入；存货周转天数=平均普通库存账面额/总销售成本×假设天数。引擎未分拆普通成本，故DIO为混合成本近似口径。
A20: ROE=本季净利润/期初期末平均权益；年化ROE=单季ROE×假设全年季度数，不代表已实现年回报。
A21: 存货减值已包含在cogs中，利润表单列作备忘，不二次扣减；经营现金流采用净库存变化重构，不重复加回减值。
A22: 净负债=普通借款+紧急借款−现金；自由现金流=经营现金流−资本开支。负净负债代表净现金。
A23: 压力情景只测静态收入下降，盈利时按15%税率计税，亏损无所得税；不模拟价格/销量/产能的共同变化。
A24: 会计对账有0.0001量级舍入差异；审计容差0.0003十亿美元。累计净利润以export.cumulative_net_income为准。
A25: 本项目为虚构经营研究与展示，不构成投资建议。季度没有对应真实日历日期；2026-10-22为本次接口读取日。
A26: 没有单列应收、应付、股本、留存收益的接口字段；资产负债表忠实保留引擎简化口径，不虚构科目。

Sheet 经营分析
A1: 晶序内存 / 经营分析
A3: 模拟经营 · 金额：十亿美元 USD bn；数量：千片 · 蓝色=源数据；浅绿=公式；浅黄=假设
A4: 项目 / 季度 | B4: Q01 | C4: Q02 | D4: Q03 | E4: Q04 | F4: Q05 | G4: Q06 | H4: Q07 | I4: Q08 | J4: Q09 | K4: Q10 | L4: Q11 | M4: Q12 | N4: Q13 | O4: Q14 | P4: Q15 | Q4: Q16 | R4: 来源 / 口径
A5: 营业收入 | B5: ='利润表'!B5 -> 4.608 | C5: ='利润表'!C5 -> 2.6208 | D5: ='利润表'!D5 -> 2.34 | E5: ='利润表'!E5 -> 2.8789 | F5: ='利润表'!F5 -> 3.744 | G5: ='利润表'!G5 -> 5.1598 | H5: ='利润表'!H5 -> 6.8734 | I5: ='利润表'!I5 -> 8.2483 | ... Q5: ='利润表'!Q5 -> 57.306
A6: 净利润 | B6: ='利润表'!B15 -> -3.9148 | C6: ='利润表'!C15 -> -2.8354 | D6: ='利润表'!D15 -> -2.7333 | E6: ='利润表'!E15 -> -2.3172 | F6: ='利润表'!F15 -> -1.6757 | G6: ='利润表'!G15 -> -0.5007 | H6: ='利润表'!H15 -> 0.8407 | I6: ='利润表'!I15 -> 1.9461 | ... Q6: ='利润表'!Q15 -> 43.7258
A7: 毛利率 | B7: =IFERROR('利润表'!B9/'利润表'!B5,0) -> 0.031510417 | C7: =IFERROR('利润表'!C9/'利润表'!C5,0) -> -0.66826923 | D7: =IFERROR('利润表'!D9/'利润表'!D5,0) -> -0.69871795 | E7: =IFERROR('利润表'!E9/'利润表'!E5,0) -> -0.41720796 | F7: =IFERROR('利润表'!F9/'利润表'!F5,0) -> -0.14182692 | G7: =IFERROR('利润表'!G9/'利润表'!G5,0) -> 0.12787317 | H7: =IFERROR('利润表'!H9/'利润表'!H5,0) -> 0.31256729 | I7: =IFERROR('利润表'!I9/'利润表'!I5,0) -> 0.4180619 | ... Q7: =IFERROR('利润表'!Q9/'利润表'!Q5,0) -> 0.90097023
A8: HBM收入占比 | B8: =IFERROR('利润表'!B7/'利润表'!B5,0) -> 0 | C8: =IFERROR('利润表'!C7/'利润表'!C5,0) -> 0 | D8: =IFERROR('利润表'!D7/'利润表'!D5,0) -> 0 | E8: =IFERROR('利润表'!E7/'利润表'!E5,0) -> 0.093368995 | F8: =IFERROR('利润表'!F7/'利润表'!F5,0) -> 0.12307692 | G8: =IFERROR('利润表'!G7/'利润表'!G5,0) -> 0.15907593 | H8: =IFERROR('利润表'!H7/'利润表'!H5,0) -> 0.20880496 | I8: =IFERROR('利润表'!I7/'利润表'!I5,0) -> 0.2932968 | ... Q8: =IFERROR('利润表'!Q7/'利润表'!Q5,0) -> 0.72369385
A9: 存货周转天数（近似） | B9: =IFERROR(('导览与假设'!$B$12+'资产负债表'!B6)/2/'利润表'!B8*'导览与假设'!$B$6,0) -> 15.197634 | C9: =IFERROR(('资产负债表'!B6+'资产负债表'!C6)/2/'利润表'!C8*'导览与假设'!$B$6,0) -> 5.6319473 | D9: =IFERROR(('资产负债表'!C6+'资产负债表'!D6)/2/'利润表'!D8*'导览与假设'!$B$6,0) -> 0 | E9: =IFERROR(('资产负债表'!D6+'资产负债表'!E6)/2/'利润表'!E8*'导览与假设'!$B$6,0) -> 0 | F9: =IFERROR(('资产负债表'!E6+'资产负债表'!F6)/2/'利润表'!F8*'导览与假设'!$B$6,0) -> 0 | G9: =IFERROR(('资产负债表'!F6+'资产负债表'!G6)/2/'利润表'!G8*'导览与假设'!$B$6,0) -> 0 | H9: =IFERROR(('资产负债表'!G6+'资产负债表'!H6)/2/'利润表'!H8*'导览与假设'!$B$6,0) -> 0 | I9: =IFERROR(('资产负债表'!H6+'资产负债表'!I6)/2/'利润表'!I8*'导览与假设'!$B$6,0) -> 0 | J9: =IFERROR(('资产负债表'!I6+'资产负债表'!J6)/2/'利润表'!J8*'导览与假设'!$B$6,0) -> 0 | ... Q9: =IFERROR(('资产负债表'!P6+'资产负债表'!Q6)/2/'利润表'!Q8*'导览与假设'!$B$6,0) -> 0
A10: 经营现金流 | B10: ='现金流量表'!B10 -> -1.502 | C10: ='现金流量表'!C10 -> -0.2882 | D10: ='现金流量表'!D10 -> -0.7333 | E10: ='现金流量表'!E10 -> -0.3172 | F10: ='现金流量表'!F10 -> 0.3993 | G10: ='现金流量表'!G10 -> 1.6493 | H10: ='现金流量表'!H10 -> 3.0657 | I10: ='现金流量表'!I10 -> 4.2461 | ... Q10: ='现金流量表'!Q10 -> 46.7758
A11: 自由现金流 | B11: =B10+'现金流量表'!B12 -> -3.002 | C11: =C10+'现金流量表'!C12 -> -1.7882 | D11: =D10+'现金流量表'!D12 -> -2.2333 | E11: =E10+'现金流量表'!E12 -> -1.8172 | F11: =F10+'现金流量表'!F12 -> -1.1007 | G11: =G10+'现金流量表'!G12 -> 0.1493 | H11: =H10+'现金流量表'!H12 -> 0.0657 | I11: =I10+'现金流量表'!I12 -> 1.2461 | ... Q11: =Q10+'现金流量表'!Q12 -> 45.2758
A12: 期末现金 | B12: ='资产负债表'!B5 -> 6.998 | C12: ='资产负债表'!C5 -> 5.2098 | D12: ='资产负债表'!D5 -> 2.9765 | E12: ='资产负债表'!E5 -> 3.1592 | F12: ='资产负债表'!F5 -> 3.0585 | G12: ='资产负债表'!G5 -> 3.2078 | H12: ='资产负债表'!H5 -> 3.2734 | I12: ='资产负债表'!I5 -> 4.5195 | ... Q12: ='资产负债表'!Q5 -> 152.9207
A13: 净负债 | B13: ='资产负债表'!B12-'资产负债表'!B5 -> -0.998 | C13: ='资产负债表'!C12-'资产负债表'!C5 -> 0.7902 | D13: ='资产负债表'!D12-'资产负债表'!D5 -> 3.0235 | E13: ='资产负债表'!E12-'资产负债表'!E5 -> 4.8408 | F13: ='资产负债表'!F12-'资产负债表'!F5 -> 5.9415 | G13: ='资产负债表'!G12-'资产负债表'!G5 -> 5.7922 | H13: ='资产负债表'!H12-'资产负债表'!H5 -> 5.7266 | I13: ='资产负债表'!I12-'资产负债表'!I5 -> 4.4805 | ... Q13: ='资产负债表'!Q12-'资产负债表'!Q5 -> -152.9207
A14: 股东权益 | B14: ='资产负债表'!B13 -> 31.0452 | C14: ='资产负债表'!C13 -> 28.2098 | D14: ='资产负债表'!D13 -> 25.4765 | E14: ='资产负债表'!E13 -> 23.1592 | F14: ='资产负债表'!F13 -> 21.4835 | G14: ='资产负债表'!G13 -> 20.9828 | H14: ='资产负债表'!H13 -> 21.8234 | I14: ='资产负债表'!I13 -> 23.7695 | ... Q14: ='资产负债表'!Q13 -> 171.2457
A15: 单季ROE | B15: =IFERROR(B6/(('导览与假设'!$B$13+B14)/2),0) -> -0.11862096 | C15: =IFERROR(C6/(('资产负债表'!B13+C14)/2),0) -> -0.095701629 | D15: =IFERROR(D6/(('资产负债表'!C13+D14)/2),0) -> -0.10182486 | E15: =IFERROR(E6/(('资产负债表'!D13+E14)/2),0) -> -0.095288029 | F15: =IFERROR(F6/(('资产负债表'!E13+F14)/2),0) -> -0.075071624 | G15: =IFERROR(G6/(('资产负债表'!F13+G14)/2),0) -> -0.023581051 | H15: =IFERROR(H6/(('资产负债表'!G13+H14)/2),0) -> 0.039279357 | I15: =IFERROR(I6/(('资产负债表'!H13+I14)/2),0) -> 0.085368555 | J15: =IFERROR(J6/(('资产负债表'!I13+J14)/2),0) -> 0.13015261 | ... Q15: =IFERROR(Q6/(('资产负债表'!P13+Q14)/2),0) -> 0.29270974
A16: 简单年化ROE（假设） | B16: =B15*'导览与假设'!$B$7 -> -0.47448383 | C16: =C15*'导览与假设'!$B$7 -> -0.38280651 | D16: =D15*'导览与假设'!$B$7 -> -0.40729944 | E16: =E15*'导览与假设'!$B$7 -> -0.38115212 | F16: =F15*'导览与假设'!$B$7 -> -0.3002865 | G16: =G15*'导览与假设'!$B$7 -> -0.094324205 | H16: =H15*'导览与假设'!$B$7 -> 0.15711743 | I16: =I15*'导览与假设'!$B$7 -> 0.34147422 | ... Q16: =Q15*'导览与假设'!$B$7 -> 1.1708389
A17: 开工率 | B17: ='原始数据'!B5 -> 0.7 | C17: ='原始数据'!C5 -> 0.55 | D17: ='原始数据'!D5 -> 0.65 | E17: ='原始数据'!E5 -> 0.72 | F17: ='原始数据'!F5 -> 0.8 | G17: ='原始数据'!G5 -> 0.9 | H17: ='原始数据'!H5 -> 1 | I17: ='原始数据'!I5 -> 1 | ... Q17: ='原始数据'!Q5 -> 1
A18: 普通库存数量（千片） | B18: ='原始数据'!B47 -> 30 | C18: ='原始数据'!C47 -> 0 | D18: ='原始数据'!D47 -> 0 | E18: ='原始数据'!E47 -> 0 | F18: ='原始数据'!F47 -> 0 | G18: ='原始数据'!G47 -> 0 | H18: ='原始数据'!H47 -> 0 | I18: ='原始数据'!I47 -> 0 | ... Q18: ='原始数据'!Q47 -> 0
A19: HBM生产（千片） | B19: ='原始数据'!B16 -> 0 | C19: ='原始数据'!C16 -> 0 | D19: ='原始数据'!D16 -> 0 | E19: ='原始数据'!E16 -> 10.8 | F19: ='原始数据'!F16 -> 12 | G19: ='原始数据'!G16 -> 18.9 | H19: ='原始数据'!H16 -> 27 | I19: ='原始数据'!I16 -> 36 | ... Q19: ='原始数据'!Q16 -> 180
A20: HBM销售（千片） | B20: ='原始数据'!B18 -> 0 | C20: ='原始数据'!C18 -> 0 | D20: ='原始数据'!D18 -> 0 | E20: ='原始数据'!E18 -> 8 | F20: ='原始数据'!F18 -> 12 | G20: ='原始数据'!G18 -> 18 | H20: ='原始数据'!H18 -> 26 | I20: ='原始数据'!I18 -> 36 | ... Q20: ='原始数据'!Q18 -> 180
A21: HBM报废（千片） | B21: =B19-B20 -> 0 | C21: =C19-C20 -> 0 | D21: =D19-D20 -> 0 | E21: =E19-E20 -> 2.8 | F21: =F19-F20 -> 0 | G21: =G19-G20 -> 0.9 | H21: =H19-H20 -> 1 | I21: =I19-I20 -> 0 | ... Q21: =Q19-Q20 -> 0
A22: 累计净利润 | B22: =SUM($B6:B6) -> -3.9148 | C22: =SUM($B6:C6) -> -6.7502 | D22: =SUM($B6:D6) -> -9.4835 | E22: =SUM($B6:E6) -> -11.8007 | F22: =SUM($B6:F6) -> -13.4764 | G22: =SUM($B6:G6) -> -13.9771 | H22: =SUM($B6:H6) -> -13.1364 | I22: =SUM($B6:I6) -> -11.1903 | ... Q22: =SUM($B6:Q6) -> 136.2858
A24: 压力情景：收入（假设） | B24: =B5*(1-'导览与假设'!$B$8) -> 3.6864 | C24: =C5*(1-'导览与假设'!$B$8) -> 2.09664 | D24: =D5*(1-'导览与假设'!$B$8) -> 1.872 | E24: =E5*(1-'导览与假设'!$B$8) -> 2.30312 | F24: =F5*(1-'导览与假设'!$B$8) -> 2.9952 | G24: =G5*(1-'导览与假设'!$B$8) -> 4.12784 | H24: =H5*(1-'导览与假设'!$B$8) -> 5.49872 | I24: =I5*(1-'导览与假设'!$B$8) -> 6.59864 | ... Q24: =Q5*(1-'导览与假设'!$B$8) -> 45.8448
A25: 压力情景：税前利润 | B25: =B24-'利润表'!B8-'利润表'!B10-'利润表'!B11-'利润表'!B13 -> -4.8364 | C25: =C24-'利润表'!C8-'利润表'!C10-'利润表'!C11-'利润表'!C13 -> -3.35956 | D25: =D24-'利润表'!D8-'利润表'!D10-'利润表'!D11-'利润表'!D13 -> -3.2013 | E25: =E24-'利润表'!E8-'利润表'!E10-'利润表'!E11-'利润表'!E13 -> -2.89308 | F25: =F24-'利润表'!F8-'利润表'!F10-'利润表'!F11-'利润表'!F13 -> -2.4245 | G25: =G24-'利润表'!G8-'利润表'!G10-'利润表'!G11-'利润表'!G13 -> -1.53266 | H25: =H24-'利润表'!H8-'利润表'!H10-'利润表'!H11-'利润表'!H13 -> -0.38558 | I25: =I24-'利润表'!I8-'利润表'!I10-'利润表'!I11-'利润表'!I13 -> 0.63984 | ... Q25: =Q24-'利润表'!Q8-'利润表'!Q10-'利润表'!Q11-'利润表'!Q13 -> 39.981
A26: 压力情景：净利润 | B26: =B25-MAX(B25,0)*'导览与假设'!$B$9 -> -4.8364 | C26: =C25-MAX(C25,0)*'导览与假设'!$B$9 -> -3.35956 | D26: =D25-MAX(D25,0)*'导览与假设'!$B$9 -> -3.2013 | E26: =E25-MAX(E25,0)*'导览与假设'!$B$9 -> -2.89308 | F26: =F25-MAX(F25,0)*'导览与假设'!$B$9 -> -2.4245 | G26: =G25-MAX(G25,0)*'导览与假设'!$B$9 -> -1.53266 | H26: =H25-MAX(H25,0)*'导览与假设'!$B$9 -> -0.38558 | I26: =I25-MAX(I25,0)*'导览与假设'!$B$9 -> 0.543864 | ... Q26: =Q25-MAX(Q25,0)*'导览与假设'!$B$9 -> 33.98385
A27: 压力情景：经营现金流 | B27: =B10+B26-B6 -> -2.4236 | C27: =C10+C26-C6 -> -0.81236 | D27: =D10+D26-D6 -> -1.2013 | E27: =E10+E26-E6 -> -0.89308 | F27: =F10+F26-F6 -> -0.3495 | G27: =G10+G26-G6 -> 0.61734 | H27: =H10+H26-H6 -> 1.83942 | I27: =I10+I26-I6 -> 2.843864 | ... Q27: =Q10+Q26-Q6 -> 37.03385
A28: 实际现金高于缓冲 | B28: =B12-'导览与假设'!$B$10 -> 3.998 | C28: =C12-'导览与假设'!$B$10 -> 2.2098 | D28: =D12-'导览与假设'!$B$10 -> -0.0235 | E28: =E12-'导览与假设'!$B$10 -> 0.1592 | F28: =F12-'导览与假设'!$B$10 -> 0.0585 | G28: =G12-'导览与假设'!$B$10 -> 0.2078 | H28: =H12-'导览与假设'!$B$10 -> 0.2734 | I28: =I12-'导览与假设'!$B$10 -> 1.5195 | ... Q28: =Q12-'导览与假设'!$B$10 -> 149.9207
I50: 读图提醒：收入和利润后期的大幅增长来自模拟市场价格急升，不能外推为现实预测。压力情景用于检视收入冲击，非对历史数据的替代。

Sheet 利润表
A1: 晶序内存 / 利润表
A3: 模拟经营 · 金额：十亿美元 USD bn；数量：千片 · 蓝色=源数据；浅绿=公式；浅黄=假设
A4: 项目 / 季度 | B4: Q01 | C4: Q02 | D4: Q03 | E4: Q04 | F4: Q05 | G4: Q06 | H4: Q07 | I4: Q08 | J4: Q09 | K4: Q10 | L4: Q11 | M4: Q12 | N4: Q13 | O4: Q14 | P4: Q15 | Q4: Q16 | R4: 来源 / 口径
A5: 营业收入 | B5: ='原始数据'!B22 -> 4.608 | C5: ='原始数据'!C22 -> 2.6208 | D5: ='原始数据'!D22 -> 2.34 | E5: ='原始数据'!E22 -> 2.8789 | F5: ='原始数据'!F22 -> 3.744 | G5: ='原始数据'!G22 -> 5.1598 | H5: ='原始数据'!H22 -> 6.8734 | I5: ='原始数据'!I22 -> 8.2483 | ... Q5: ='原始数据'!Q22 -> 57.306 | R5: 完整导出 history[].income_statement.revenue
A6: 其中：普通内存收入 | B6: ='原始数据'!B23 -> 4.608 | C6: ='原始数据'!C23 -> 2.6208 | D6: ='原始数据'!D23 -> 2.34 | E6: ='原始数据'!E23 -> 2.6101 | F6: ='原始数据'!F23 -> 3.2832 | G6: ='原始数据'!G23 -> 4.339 | H6: ='原始数据'!H23 -> 5.4382 | I6: ='原始数据'!I23 -> 5.8291 | ... Q6: ='原始数据'!Q23 -> 15.834 | R6: 完整导出 history[].income_statement.revenue_std
A7: 其中：HBM收入 | B7: ='原始数据'!B24 -> 0 | C7: ='原始数据'!C24 -> 0 | D7: ='原始数据'!D24 -> 0 | E7: ='原始数据'!E24 -> 0.2688 | F7: ='原始数据'!F24 -> 0.4608 | G7: ='原始数据'!G24 -> 0.8208 | H7: ='原始数据'!H24 -> 1.4352 | I7: ='原始数据'!I24 -> 2.4192 | ... Q7: ='原始数据'!Q24 -> 41.472 | R7: 完整导出 history[].income_statement.revenue_hbm
A8: 销售成本（含减值） | B8: ='原始数据'!B25 -> 4.4628 | C8: ='原始数据'!C25 -> 4.3722 | D8: ='原始数据'!D25 -> 3.975 | E8: ='原始数据'!E25 -> 4.08 | F8: ='原始数据'!F25 -> 4.275 | G8: ='原始数据'!G25 -> 4.5 | H8: ='原始数据'!H25 -> 4.725 | I8: ='原始数据'!I25 -> 4.8 | ... Q8: ='原始数据'!Q25 -> 5.675 | R8: 完整导出 history[].income_statement.cogs
A9: 毛利 | B9: ='原始数据'!B27 -> 0.1452 | C9: ='原始数据'!C27 -> -1.7514 | D9: ='原始数据'!D27 -> -1.635 | E9: ='原始数据'!E27 -> -1.2011 | F9: ='原始数据'!F27 -> -0.531 | G9: ='原始数据'!G27 -> 0.6598 | H9: ='原始数据'!H27 -> 2.1484 | I9: ='原始数据'!I27 -> 3.4483 | ... Q9: ='原始数据'!Q27 -> 51.631 | R9: 完整导出 history[].income_statement.gross_profit
A10: 研发费用（含额外HBM） | B10: ='原始数据'!B29 -> 3.8 | C10: ='原始数据'!C29 -> 0.8 | D10: ='原始数据'!D29 -> 0.8 | E10: ='原始数据'!E29 -> 0.8 | F10: ='原始数据'!F29 -> 0.8 | G10: ='原始数据'!G29 -> 0.8 | H10: ='原始数据'!H29 -> 0.8 | I10: ='原始数据'!I29 -> 0.8 | ... Q10: ='原始数据'!Q29 -> 0.8 | R10: 完整导出 history[].income_statement.rnd
A11: 销售与管理费用 | B11: ='原始数据'!B30 -> 0.25 | C11: ='原始数据'!C30 -> 0.25 | D11: ='原始数据'!D30 -> 0.25 | E11: ='原始数据'!E30 -> 0.25 | F11: ='原始数据'!F30 -> 0.25 | G11: ='原始数据'!G30 -> 0.25 | H11: ='原始数据'!H30 -> 0.25 | I11: ='原始数据'!I30 -> 0.25 | ... Q11: ='原始数据'!Q30 -> 0.25 | R11: 完整导出 history[].income_statement.sga
A12: 营业利润 | B12: ='原始数据'!B31 -> -3.9048 | C12: ='原始数据'!C31 -> -2.8014 | D12: ='原始数据'!D31 -> -2.685 | E12: ='原始数据'!E31 -> -2.2511 | F12: ='原始数据'!F31 -> -1.581 | G12: ='原始数据'!G31 -> -0.3902 | H12: ='原始数据'!H31 -> 1.0984 | I12: ='原始数据'!I31 -> 2.3983 | ... Q12: ='原始数据'!Q31 -> 50.581 | R12: 完整导出 history[].income_statement.operating_income
A13: 净利息费用（负为收益） | B13: ='原始数据'!B32 -> 0.01 | C13: ='原始数据'!C32 -> 0.034 | D13: ='原始数据'!D32 -> 0.0483 | E13: ='原始数据'!E32 -> 0.0662 | F13: ='原始数据'!F32 -> 0.0947 | G13: ='原始数据'!G32 -> 0.1105 | H13: ='原始数据'!H32 -> 0.1093 | I13: ='原始数据'!I32 -> 0.1088 | ... Q13: ='原始数据'!Q32 -> -0.8612 | R13: 完整导出 history[].income_statement.net_interest
A14: 所得税 | B14: ='原始数据'!B33 -> 0 | C14: ='原始数据'!C33 -> 0 | D14: ='原始数据'!D33 -> 0 | E14: ='原始数据'!E33 -> 0 | F14: ='原始数据'!F33 -> 0 | G14: ='原始数据'!G33 -> 0 | H14: ='原始数据'!H33 -> 0.1484 | I14: ='原始数据'!I33 -> 0.3434 | ... Q14: ='原始数据'!Q33 -> 7.7163 | R14: 完整导出 history[].income_statement.tax
A15: 净利润 | B15: ='原始数据'!B34 -> -3.9148 | C15: ='原始数据'!C34 -> -2.8354 | D15: ='原始数据'!D34 -> -2.7333 | E15: ='原始数据'!E34 -> -2.3172 | F15: ='原始数据'!F34 -> -1.6757 | G15: ='原始数据'!G34 -> -0.5007 | H15: ='原始数据'!H34 -> 0.8407 | I15: ='原始数据'!I34 -> 1.9461 | ... Q15: ='原始数据'!Q34 -> 43.7258 | R15: 完整导出 history[].income_statement.net_income
A16: 毛利率 | B16: =IFERROR(B9/B5,0) -> 0.031510417 | C16: =IFERROR(C9/C5,0) -> -0.66826923 | D16: =IFERROR(D9/D5,0) -> -0.69871795 | E16: =IFERROR(E9/E5,0) -> -0.41720796 | F16: =IFERROR(F9/F5,0) -> -0.14182692 | G16: =IFERROR(G9/G5,0) -> 0.12787317 | H16: =IFERROR(H9/H5,0) -> 0.31256729 | I16: =IFERROR(I9/I5,0) -> 0.4180619 | ... Q16: =IFERROR(Q9/Q5,0) -> 0.90097023
A17: 备忘：存货跌价 | B17: ='原始数据'!B26 -> 0.0095 | C17: ='原始数据'!C26 -> 0 | D17: ='原始数据'!D26 -> 0 | E17: ='原始数据'!E26 -> 0 | F17: ='原始数据'!F26 -> 0 | G17: ='原始数据'!G26 -> 0 | H17: ='原始数据'!H26 -> 0 | I17: ='原始数据'!I26 -> 0 | ... Q17: ='原始数据'!Q26 -> 0 | R17: 完整导出 history[].income_statement.inventory_writedown
A19: 收入分项差额 | B19: =B5-B6-B7 -> 0 | C19: =C5-C6-C7 -> 0 | D19: =D5-D6-D7 -> 0 | E19: =E5-E6-E7 -> -2.7755576e-16 | F19: =F5-F6-F7 -> 3.3306691e-16 | G19: =G5-G6-G7 -> -6.6613381e-16 | H19: =H5-H6-H7 -> 0 | I19: =I5-I6-I7 -> 0 | ... Q19: =Q5-Q6-Q7 -> -7.1054274e-15
A20: 利润重算差额 | B20: =B5-B8-B10-B11-B13-B14-B15 -> 4.4408921e-16 | C20: =C5-C8-C10-C11-C13-C14-C15 -> 0 | D20: =D5-D8-D10-D11-D13-D14-D15 -> -4.4408921e-16 | E20: =E5-E8-E10-E11-E13-E14-E15 -> -0.0001 | F20: =F5-F8-F10-F11-F13-F14-F15 -> -2.220446e-16 | G20: =G5-G8-G10-G11-G13-G14-G15 -> -3.3306691e-16 | H20: =H5-H8-H10-H11-H13-H14-H15 -> 5.5511151e-16 | I20: =I5-I8-I10-I11-I13-I14-I15 -> 8.8817842e-16 | ... Q20: =Q5-Q8-Q10-Q11-Q13-Q14-Q15 -> 0.0001

Sheet 资产负债表
A1: 晶序内存 / 资产负债表
A3: 模拟经营 · 金额：十亿美元 USD bn；数量：千片 · 蓝色=源数据；浅绿=公式；浅黄=假设
A4: 项目 / 季度 | B4: Q01 | C4: Q02 | D4: Q03 | E4: Q04 | F4: Q05 | G4: Q06 | H4: Q07 | I4: Q08 | J4: Q09 | K4: Q10 | L4: Q11 | M4: Q12 | N4: Q13 | O4: Q14 | P4: Q15 | Q4: Q16 | R4: 来源 / 口径
A5: 现金 | B5: ='原始数据'!B40 -> 6.998 | C5: ='原始数据'!C40 -> 5.2098 | D5: ='原始数据'!D40 -> 2.9765 | E5: ='原始数据'!E40 -> 3.1592 | F5: ='原始数据'!F40 -> 3.0585 | G5: ='原始数据'!G40 -> 3.2078 | H5: ='原始数据'!H40 -> 3.2734 | I5: ='原始数据'!I40 -> 4.5195 | ... Q5: ='原始数据'!Q40 -> 152.9207 | R5: 完整导出 history[].balance_sheet.cash
A6: 普通内存存货（净额） | B6: ='原始数据'!B41 -> 0.5472 | C6: ='原始数据'!C41 -> 0 | D6: ='原始数据'!D41 -> 0 | E6: ='原始数据'!E41 -> 0 | F6: ='原始数据'!F41 -> 0 | G6: ='原始数据'!G41 -> 0 | H6: ='原始数据'!H41 -> 0 | I6: ='原始数据'!I41 -> 0 | ... Q6: ='原始数据'!Q41 -> 0 | R6: 完整导出 history[].balance_sheet.inventory
A7: 固定资产净额 | B7: ='原始数据'!B42 -> 29.5 | C7: ='原始数据'!C42 -> 29 | D7: ='原始数据'!D42 -> 28.5 | E7: ='原始数据'!E42 -> 28 | F7: ='原始数据'!F42 -> 27.425 | G7: ='原始数据'!G42 -> 26.775 | H7: ='原始数据'!H42 -> 27.55 | I7: ='原始数据'!I42 -> 28.25 | ... Q7: ='原始数据'!Q42 -> 18.325 | R7: 完整导出 history[].balance_sheet.ppe_net
A8: 资产总额 | B8: ='原始数据'!B43 -> 37.0452 | C8: ='原始数据'!C43 -> 34.2098 | D8: ='原始数据'!D43 -> 31.4765 | E8: ='原始数据'!E43 -> 31.1592 | F8: ='原始数据'!F43 -> 30.4835 | G8: ='原始数据'!G43 -> 29.9828 | H8: ='原始数据'!H43 -> 30.8234 | I8: ='原始数据'!I43 -> 32.7695 | ... Q8: ='原始数据'!Q43 -> 171.2457 | R8: 完整导出 history[].balance_sheet.total_assets
A10: 普通借款 | B10: ='原始数据'!B44 -> 6 | C10: ='原始数据'!C44 -> 6 | D10: ='原始数据'!D44 -> 6 | E10: ='原始数据'!E44 -> 8 | F10: ='原始数据'!F44 -> 9 | G10: ='原始数据'!G44 -> 9 | H10: ='原始数据'!H44 -> 9 | I10: ='原始数据'!I44 -> 9 | ... Q10: ='原始数据'!Q44 -> 0 | R10: 完整导出 history[].balance_sheet.debt
A11: 紧急授信借款 | B11: ='原始数据'!B45 -> 0 | C11: ='原始数据'!C45 -> 0 | D11: ='原始数据'!D45 -> 0 | E11: ='原始数据'!E45 -> 0 | F11: ='原始数据'!F45 -> 0 | G11: ='原始数据'!G45 -> 0 | H11: ='原始数据'!H45 -> 0 | I11: ='原始数据'!I45 -> 0 | ... Q11: ='原始数据'!Q45 -> 0 | R11: 完整导出 history[].balance_sheet.emergency_debt
A12: 负债合计 | B12: =B10+B11 -> 6 | C12: =C10+C11 -> 6 | D12: =D10+D11 -> 6 | E12: =E10+E11 -> 8 | F12: =F10+F11 -> 9 | G12: =G10+G11 -> 9 | H12: =H10+H11 -> 9 | I12: =I10+I11 -> 9 | ... Q12: =Q10+Q11 -> 0
A13: 股东权益 | B13: ='原始数据'!B46 -> 31.0452 | C13: ='原始数据'!C46 -> 28.2098 | D13: ='原始数据'!D46 -> 25.4765 | E13: ='原始数据'!E46 -> 23.1592 | F13: ='原始数据'!F46 -> 21.4835 | G13: ='原始数据'!G46 -> 20.9828 | H13: ='原始数据'!H46 -> 21.8234 | I13: ='原始数据'!I46 -> 23.7695 | ... Q13: ='原始数据'!Q46 -> 171.2457 | R13: 完整导出 history[].balance_sheet.equity
A14: 负债与权益合计 | B14: =B12+B13 -> 37.0452 | C14: =C12+C13 -> 34.2098 | D14: =D12+D13 -> 31.4765 | E14: =E12+E13 -> 31.1592 | F14: =F12+F13 -> 30.4835 | G14: =G12+G13 -> 29.9828 | H14: =H12+H13 -> 30.8234 | I14: =I12+I13 -> 32.7695 | ... Q14: =Q12+Q13 -> 171.2457
A15: 资产负债平衡差额 | B15: =B8-B14 -> 0 | C15: =C8-C14 -> 0 | D15: =D8-D14 -> 0 | E15: =E8-E14 -> 0 | F15: =F8-F14 -> 0 | G15: =G8-G14 -> 0 | H15: =H8-H14 -> 0 | I15: =I8-I14 -> 0 | ... Q15: =Q8-Q14 -> 0
A17: 备忘：库存数量（千片） | B17: ='原始数据'!B47 -> 30 | C17: ='原始数据'!C47 -> 0 | D17: ='原始数据'!D47 -> 0 | E17: ='原始数据'!E47 -> 0 | F17: ='原始数据'!F47 -> 0 | G17: ='原始数据'!G47 -> 0 | H17: ='原始数据'!H47 -> 0 | I17: ='原始数据'!I47 -> 0 | ... Q17: ='原始数据'!Q47 -> 0 | R17: 完整导出 history[].balance_sheet.inventory_kwafers
A18: 备忘：产能（千片/季） | B18: ='原始数据'!B48 -> 300 | C18: ='原始数据'!C48 -> 300 | D18: ='原始数据'!D48 -> 300 | E18: ='原始数据'!E48 -> 300 | F18: ='原始数据'!F48 -> 300 | G18: ='原始数据'!G48 -> 300 | H18: ='原始数据'!H48 -> 300 | I18: ='原始数据'!I48 -> 300 | ... Q18: ='原始数据'!Q48 -> 325 | R18: 完整导出 history[].balance_sheet.capacity_kwafers

Sheet 现金流量表
A1: 晶序内存 / 现金流量表
A3: 模拟经营 · 金额：十亿美元 USD bn；数量：千片 · 蓝色=源数据；浅绿=公式；浅黄=假设
A4: 项目 / 季度 | B4: Q01 | C4: Q02 | D4: Q03 | E4: Q04 | F4: Q05 | G4: Q06 | H4: Q07 | I4: Q08 | J4: Q09 | K4: Q10 | L4: Q11 | M4: Q12 | N4: Q13 | O4: Q14 | P4: Q15 | Q4: Q16 | R4: 来源 / 口径
A5: 期初现金 | B5: ='导览与假设'!$B$11 -> 10 | C5: ='资产负债表'!B5 -> 6.998 | D5: ='资产负债表'!C5 -> 5.2098 | E5: ='资产负债表'!D5 -> 2.9765 | F5: ='资产负债表'!E5 -> 3.1592 | G5: ='资产负债表'!F5 -> 3.0585 | H5: ='资产负债表'!G5 -> 3.2078 | I5: ='资产负债表'!H5 -> 3.2734 | J5: ='资产负债表'!I5 -> 4.5195 | ... Q5: ='资产负债表'!P5 -> 107.6449
A6: 净利润 | B6: ='原始数据'!B34 -> -3.9148 | C6: ='原始数据'!C34 -> -2.8354 | D6: ='原始数据'!D34 -> -2.7333 | E6: ='原始数据'!E34 -> -2.3172 | F6: ='原始数据'!F34 -> -1.6757 | G6: ='原始数据'!G34 -> -0.5007 | H6: ='原始数据'!H34 -> 0.8407 | I6: ='原始数据'!I34 -> 1.9461 | ... Q6: ='原始数据'!Q34 -> 43.7258 | R6: 完整导出 history[].income_statement.net_income
A7: 折旧（非现金） | B7: ='原始数据'!B38 -> 2 | C7: ='原始数据'!C38 -> 2 | D7: ='原始数据'!D38 -> 2 | E7: ='原始数据'!E38 -> 2 | F7: ='原始数据'!F38 -> 2.075 | G7: ='原始数据'!G38 -> 2.15 | H7: ='原始数据'!H38 -> 2.225 | I7: ='原始数据'!I38 -> 2.3 | ... Q7: ='原始数据'!Q38 -> 3.05 | R7: 完整导出 history[].cash_flow.depreciation
A8: 存货减少 /（增加） | B8: ='导览与假设'!$B$12-'资产负债表'!B6 -> 0.4128 | C8: ='资产负债表'!B6-'资产负债表'!C6 -> 0.5472 | D8: ='资产负债表'!C6-'资产负债表'!D6 -> 0 | E8: ='资产负债表'!D6-'资产负债表'!E6 -> 0 | F8: ='资产负债表'!E6-'资产负债表'!F6 -> 0 | G8: ='资产负债表'!F6-'资产负债表'!G6 -> 0 | H8: ='资产负债表'!G6-'资产负债表'!H6 -> 0 | I8: ='资产负债表'!H6-'资产负债表'!I6 -> 0 | J8: ='资产负债表'!I6-'资产负债表'!J6 -> 0 | ... Q8: ='资产负债表'!P6-'资产负债表'!Q6 -> 0
A9: 经营活动现金流（重构） | B9: =SUM(B6:B8) -> -1.502 | C9: =SUM(C6:C8) -> -0.2882 | D9: =SUM(D6:D8) -> -0.7333 | E9: =SUM(E6:E8) -> -0.3172 | F9: =SUM(F6:F8) -> 0.3993 | G9: =SUM(G6:G8) -> 1.6493 | H9: =SUM(H6:H8) -> 3.0657 | I9: =SUM(I6:I8) -> 4.2461 | ... Q9: =SUM(Q6:Q8) -> 46.7758
A10: 经营活动现金流（接口） | B10: ='原始数据'!B35 -> -1.502 | C10: ='原始数据'!C35 -> -0.2882 | D10: ='原始数据'!D35 -> -0.7333 | E10: ='原始数据'!E35 -> -0.3172 | F10: ='原始数据'!F35 -> 0.3993 | G10: ='原始数据'!G35 -> 1.6493 | H10: ='原始数据'!H35 -> 3.0657 | I10: ='原始数据'!I35 -> 4.2461 | ... Q10: ='原始数据'!Q35 -> 46.7758 | R10: 完整导出 history[].cash_flow.operating
A11: 经营现金流对账差额 | B11: =B9-B10 -> -2.220446e-16 | C11: =C9-C10 -> 1.110223e-16 | D11: =D9-D10 -> 1.110223e-16 | E11: =E9-E10 -> -1.6653345e-16 | F11: =F9-F10 -> 2.220446e-16 | G11: =G9-G10 -> -2.220446e-16 | H11: =H9-H10 -> 0 | I11: =I9-I10 -> 0 | ... Q11: =Q9-Q10 -> 0
A12: 投资活动现金流 | B12: ='原始数据'!B36 -> -1.5 | C12: ='原始数据'!C36 -> -1.5 | D12: ='原始数据'!D36 -> -1.5 | E12: ='原始数据'!E36 -> -1.5 | F12: ='原始数据'!F36 -> -1.5 | G12: ='原始数据'!G36 -> -1.5 | H12: ='原始数据'!H36 -> -3 | I12: ='原始数据'!I36 -> -3 | ... Q12: ='原始数据'!Q36 -> -1.5 | R12: 完整导出 history[].cash_flow.investing
A13: 融资活动现金流 | B13: ='原始数据'!B37 -> 0 | C13: ='原始数据'!C37 -> 0 | D13: ='原始数据'!D37 -> 0 | E13: ='原始数据'!E37 -> 2 | F13: ='原始数据'!F37 -> 1 | G13: ='原始数据'!G37 -> 0 | H13: ='原始数据'!H37 -> 0 | I13: ='原始数据'!I37 -> 0 | ... Q13: ='原始数据'!Q37 -> 0 | R13: 完整导出 history[].cash_flow.financing
A14: 现金净增加额 | B14: =B10+B12+B13 -> -3.002 | C14: =C10+C12+C13 -> -1.7882 | D14: =D10+D12+D13 -> -2.2333 | E14: =E10+E12+E13 -> 0.1828 | F14: =F10+F12+F13 -> -0.1007 | G14: =G10+G12+G13 -> 0.1493 | H14: =H10+H12+H13 -> 0.0657 | I14: =I10+I12+I13 -> 1.2461 | ... Q14: =Q10+Q12+Q13 -> 45.2758
A15: 期末现金（重构） | B15: =B5+B14 -> 6.998 | C15: =C5+C14 -> 5.2098 | D15: =D5+D14 -> 2.9765 | E15: =E5+E14 -> 3.1593 | F15: =F5+F14 -> 3.0585 | G15: =G5+G14 -> 3.2078 | H15: =H5+H14 -> 3.2735 | I15: =I5+I14 -> 4.5195 | ... Q15: =Q5+Q14 -> 152.9207
A16: 期末现金（接口） | B16: ='原始数据'!B40 -> 6.998 | C16: ='原始数据'!C40 -> 5.2098 | D16: ='原始数据'!D40 -> 2.9765 | E16: ='原始数据'!E40 -> 3.1592 | F16: ='原始数据'!F40 -> 3.0585 | G16: ='原始数据'!G40 -> 3.2078 | H16: ='原始数据'!H40 -> 3.2734 | I16: ='原始数据'!I40 -> 4.5195 | ... Q16: ='原始数据'!Q40 -> 152.9207 | R16: 完整导出 history[].balance_sheet.cash
A17: 现金对账差额 | B17: =B15-B16 -> 0 | C17: =C15-C16 -> 0 | D17: =D15-D16 -> 4.4408921e-16 | E17: =E15-E16 -> 0.0001 | F17: =F15-F16 -> -4.4408921e-16 | G17: =G15-G16 -> -4.4408921e-16 | H17: =H15-H16 -> 0.0001 | I17: =I15-I16 -> 8.8817842e-16 | ... Q17: =Q15-Q16 -> 0
A19: 备忘：紧急借款流入 | B19: ='原始数据'!B39 -> 0 | C19: ='原始数据'!C39 -> 0 | D19: ='原始数据'!D39 -> 0 | E19: ='原始数据'!E39 -> 0 | F19: ='原始数据'!F39 -> 0 | G19: ='原始数据'!G39 -> 0 | H19: ='原始数据'!H39 -> 0 | I19: ='原始数据'!I39 -> 0 | ... Q19: ='原始数据'!Q39 -> 0 | R19: 完整导出 history[].cash_flow.emergency_borrowing

Sheet 原始数据
A1: 晶序内存 / 原始数据
A3: 模拟经营 · 金额：十亿美元 USD bn；数量：千片 · 蓝色=源数据；浅绿=公式；浅黄=假设
A4: 项目 / 季度 | B4: Q01 | C4: Q02 | D4: Q03 | E4: Q04 | F4: Q05 | G4: Q06 | H4: Q07 | I4: Q08 | J4: Q09 | K4: Q10 | L4: Q11 | M4: Q12 | N4: Q13 | O4: Q14 | P4: Q15 | Q4: Q16 | R4: 来源 / 口径
A5: decision.utilization | B5: 0.7 | C5: 0.55 | D5: 0.65 | E5: 0.72 | F5: 0.8 | G5: 0.9 | H5: 1 | I5: 1 | J5: 1 | K5: 1 | L5: 1 | M5: 1 | N5: 1 | O5: 1 | P5: 1 | Q5: 1 | R5: 数据/完整导出.json → history[季度-1].decision.utilization
A6: decision.sell_fraction | B6: 1 | C6: 1 | D6: 1 | E6: 1 | F6: 1 | G6: 1 | H6: 1 | I6: 1 | J6: 1 | K6: 1 | L6: 1 | M6: 1 | N6: 1 | O6: 1 | P6: 1 | Q6: 1 | R6: 数据/完整导出.json → history[季度-1].decision.sell_fraction
A7: decision.capex | B7: 1.5 | C7: 1.5 | D7: 1.5 | E7: 1.5 | F7: 1.5 | G7: 1.5 | H7: 3 | I7: 3 | J7: 1.5 | K7: 1.5 | L7: 1.5 | M7: 1.5 | N7: 1.5 | O7: 1.5 | P7: 1.5 | Q7: 1.5 | R7: 数据/完整导出.json → history[季度-1].decision.capex
A8: decision.hbm_rnd | B8: 3 | C8: 0 | D8: 0 | E8: 0 | F8: 0 | G8: 0 | H8: 0 | I8: 0 | J8: 0 | K8: 0 | L8: 0 | M8: 0 | N8: 0 | O8: 0 | P8: 0 | Q8: 0 | R8: 数据/完整导出.json → history[季度-1].decision.hbm_rnd
A9: decision.hbm_share | B9: 0 | C9: 0 | D9: 0 | E9: 0.05 | F9: 0.05 | G9: 0.07 | H9: 0.09 | I9: 0.12 | J9: 0.166667 | K9: 0.21 | L9: 0.24 | M9: 0.28 | N9: 0.338462 | O9: 0.4 | P9: 0.492308 | Q9: 0.553846 | R9: 数据/完整导出.json → history[季度-1].decision.hbm_share
A10: decision.borrow | B10: 0 | C10: 0 | D10: 0 | E10: 2 | F10: 1 | G10: 0 | H10: 0 | I10: 0 | J10: -2 | K10: -4 | L10: -3 | M10: 0 | N10: 0 | O10: 0 | P10: 0 | Q10: 0 | R10: 数据/完整导出.json → history[季度-1].decision.borrow
A11: market.price_index | B11: 0.8 | C11: 0.56 | D11: 0.5 | E11: 0.53 | F11: 0.6 | G11: 0.72 | H11: 0.83 | I11: 0.92 | J11: 1 | K11: 0.97 | L11: 1.06 | M11: 1.28 | N11: 1.7 | O11: 2.65 | P11: 3.9 | Q11: 4.55 | R11: 数据/完整导出.json → history[季度-1].market.price_index
A12: market.hbm_price_index | B12: 1.6 | C12: 1.4 | D12: 1.3 | E12: 1.4 | F12: 1.6 | G12: 1.9 | H12: 2.3 | I12: 2.8 | J12: 3.4 | K12: 4 | L12: 4.6 | M12: 5.4 | N12: 6.4 | O12: 7.6 | P12: 8.8 | Q12: 9.6 | R12: 数据/完整导出.json → history[季度-1].market.hbm_price_index
A13: market.demand_kwafers | B13: 240 | C13: 210 | D13: 205 | E13: 215 | F13: 235 | G13: 260 | H13: 285 | I13: 305 | J13: 320 | K13: 320 | L13: 340 | M13: 365 | N13: 400 | O13: 440 | P13: 480 | Q13: 510 | R13: 数据/完整导出.json → history[季度-1].market.demand_kwafers
A14: market.hbm_demand_kwafers | B14: 5 | C14: 5 | D14: 6 | E14: 8 | F14: 12 | G14: 18 | H14: 26 | I14: 36 | J14: 48 | K14: 60 | L14: 74 | M14: 90 | N14: 110 | O14: 135 | P14: 160 | Q14: 185 | R14: 数据/完整导出.json → history[季度-1].market.hbm_demand_kwafers
A15: operations.produced_kwafers | B15: 210 | C15: 165 | D15: 195 | E15: 216 | F15: 240 | G15: 270 | H15: 300 | I15: 300 | J15: 300 | K15: 300 | L15: 312.5 | M15: 325 | N15: 325 | O15: 325 | P15: 325 | Q15: 325 | R15: 数据/完整导出.json → history[季度-1].operations.produced_kwafers
A16: operations.hbm_kwafers | B16: 0 | C16: 0 | D16: 0 | E16: 10.8 | F16: 12 | G16: 18.9 | H16: 27 | I16: 36 | J16: 50 | K16: 63 | L16: 75 | M16: 91 | N16: 110 | O16: 130 | P16: 160 | Q16: 180 | R16: 数据/完整导出.json → history[季度-1].operations.hbm_kwafers
... A48: balance_sheet.capacity_kwafers | B48: 300 | C48: 300 | D48: 300 | E48: 300 | F48: 300 | G48: 300 | H48: 300 | I48: 300 | J48: 300 | K48: 300 | L48: 312.5 | M48: 325 | N48: 325 | O48: 325 | P48: 325 | Q48: 325 | R48: 数据/完整导出.json → history[季度-1].balance_sheet.capacity_kwafers
