Workbook

Sheet 明细
A1: 披露与统计 · 数据明细
A2: 蓝色数值 = 来源输入；绿色 = 公式；橙色 = 假设。所有金额统一为百万美元；美元支出用正值表示。发布日期、口径和定位均随行保存。
A4: ID | B4: 分类 | C4: 指标 | D4: 期间 | E4: 数值 | F4: 单位 | G4: 性质 | H4: 来源ID | I4: 来源名称 | J4: 发布日期 | K4: 访问/读取日 | L4: 文件/网址及定位 | M4: 口径说明
A5: D01 | B5: 用电 | C5: 全球数据中心终端用电 | D5: 2024 | E5: 415 | F5: TWh | G5: IEA估计 | H5: S1 | I5: IEA · Energy and AI / Demand & Executive summary | J5: 2025-04-10 | K5: 2026-10-22 | L5: https://www.iea.org/reports/energy-and-ai | Global outlook | M5: 不是AI独占；不含加密货币挖矿；包含设施用电。
A6: D02 | B6: 用电 | C6: 全球数据中心终端用电 | D6: 2030 | E6: 945 | F6: TWh | G6: IEA预测·旧版 | H6: S1 | I6: IEA · Energy and AI / Demand & Executive summary | J6: 2025-04-10 | K6: 2026-10-22 | L6: https://www.iea.org/reports/energy-and-ai | Base Case | M6: 2025版预测，保留用于版本比较。
A7: D03 | B7: 用电 | C7: 全球数据中心终端用电 | D7: 2025 | E7: 485 | F7: TWh | G7: IEA估计 | H7: S3 | I7: IEA · Key Questions on Energy and AI | J7: 2026-04-16 | K7: 2026-10-22 | L7: https://www.iea.org/reports/key-questions-on-energy-and-ai/executive-summary | Updated demand outlook | M7: 使用摘要约数；最新完整年度估计。
A8: D04 | B8: 用电 | C8: 全球数据中心终端用电 | D8: 2030 | E8: 950 | F8: TWh | G8: IEA预测·新版 | H8: S3 | I8: IEA · Key Questions on Energy and AI | J8: 2026-04-16 | K8: 2026-10-22 | L8: https://www.iea.org/reports/key-questions-on-energy-and-ai/executive-summary | Updated demand outlook | M8: 使用摘要约数；基准预测不是确定结果。
A9: D05 | B9: 用电 | C9: 全球电力消费占比 | D9: 2024 | E9: 0.015 | F9: % | G9: IEA估计 | H9: S1 | I9: IEA · Energy and AI / Demand & Executive summary | J9: 2025-04-10 | K9: 2026-10-22 | L9: https://www.iea.org/reports/energy-and-ai | Global outlook
A10: D06 | B10: 用电 | C10: 全球电力消费占比 | D10: 2030 | E10: 0.03 | F10: % | G10: IEA预测·新版 | H10: S3 | I10: IEA · Key Questions on Energy and AI | J10: 2026-04-16 | K10: 2026-10-22 | L10: https://www.iea.org/reports/key-questions-on-energy-and-ai/executive-summary | Updated demand outlook | M10: 约3%。
A11: D07 | B11: 用电 | C11: 数据中心用电同比增长 | D11: 2025 | E11: 0.17 | F11: % | G11: IEA估计 | H11: S3 | I11: IEA · Key Questions on Energy and AI | J11: 2026-04-16 | K11: 2026-10-22 | L11: https://www.iea.org/reports/key-questions-on-energy-and-ai/executive-summary | Energy consumption
A12: D08 | B12: 用电 | C12: AI-focused数据中心用电同比增长 | D12: 2025 | E12: 0.5 | F12: % | G12: IEA估计 | H12: S3 | I12: IEA · Key Questions on Energy and AI | J12: 2026-04-16 | K12: 2026-10-22 | L12: https://www.iea.org/reports/key-questions-on-energy-and-ai/executive-summary | Energy consumption | M12: AI-focused分类不等于逐任务计量。
A13: D09 | B13: 用电 | C13: AI-focused用电增长倍数 | D13: 2025—2030 | E13: 3 | F13: 倍 | G13: IEA预测 | H13: S3 | I13: IEA · Key Questions on Energy and AI | J13: 2026-04-16 | K13: 2026-10-22 | L13: https://www.iea.org/reports/key-questions-on-energy-and-ai/executive-summary | Updated demand outlook
A14: D10 | B14: 供电 | C14: 服务数据中心的发电量 | D14: 2024 | E14: 460 | F14: TWh | G14: IEA估计 | H14: S2 | I14: IEA · Energy and AI / Supply | J14: 2025-04-10 | K14: 2026-10-22 | L14: https://www.iea.org/reports/energy-and-ai/energy-supply-for-ai | Global supply | M14: 发电端；与415终端用电存在系统损耗等口径差异，不能相加。
A15: D11 | B15: 供电结构 | C15: 煤电 | D15: 2024 | E15: 0.3 | F15: % | G15: IEA约数 | H15: S2 | I15: IEA · Energy and AI / Supply | J15: 2025-04-10 | K15: 2026-10-22 | L15: https://www.iea.org/reports/energy-and-ai/energy-supply-for-ai | Global electricity supply | M15: 物理供电来源而非合同或绿证结构；本文将比例用于终端用电分摊示意。
A16: D12 | B16: 供电结构 | C16: 燃气 | D16: 2024 | E16: 0.26 | F16: % | G16: IEA约数 | H16: S2 | I16: IEA · Energy and AI / Supply | J16: 2025-04-10 | K16: 2026-10-22 | L16: https://www.iea.org/reports/energy-and-ai/energy-supply-for-ai | Global electricity supply | M16: 物理供电来源而非合同或绿证结构；本文将比例用于终端用电分摊示意。
A17: D13 | B17: 供电结构 | C17: 核裂变 | D17: 2024 | E17: 0.15 | F17: % | G17: IEA约数 | H17: S2 | I17: IEA · Energy and AI / Supply | J17: 2025-04-10 | K17: 2026-10-22 | L17: https://www.iea.org/reports/energy-and-ai/energy-supply-for-ai | Global electricity supply | M17: 物理供电来源而非合同或绿证结构；本文将比例用于终端用电分摊示意。
A18: D14 | B18: 供电结构 | C18: 可再生能源 | D18: 2024 | E18: 0.27 | F18: % | G18: IEA约数 | H18: S2 | I18: IEA · Energy and AI / Supply | J18: 2025-04-10 | K18: 2026-10-22 | L18: https://www.iea.org/reports/energy-and-ai/energy-supply-for-ai | Global electricity supply | M18: 物理供电来源而非合同或绿证结构；本文将比例用于终端用电分摊示意。
A19: D15 | B19: 区域 | C19: 美国在全球数据中心用电中的份额 | D19: 2024 | E19: 0.45 | F19: % | G19: IEA约数 | H19: S1 | I19: IEA · Energy and AI / Demand & Executive summary | J19: 2025-04-10 | K19: 2026-10-22 | L19: https://www.iea.org/reports/energy-and-ai | Executive summary / Data centres electricity consumption
A20: D16 | B20: 瓶颈 | C20: 现场燃气发电相对负荷超配下限 | D20: 2030前 | E20: 0.3 | F20: % | G20: IEA分析 | H20: S3 | I20: IEA · Key Questions on Energy and AI | J20: 2026-04-16 | K20: 2026-10-22 | L20: https://www.iea.org/reports/key-questions-on-energy-and-ai/executive-summary | Onsite natural gas
A21: D17 | B21: 瓶颈 | C21: 现场燃气发电相对负荷超配上限 | D21: 2030前 | E21: 0.7 | F21: % | G21: IEA分析 | H21: S3 | I21: IEA · Key Questions on Energy and AI | J21: 2026-04-16 | K21: 2026-10-22 | L21: https://www.iea.org/reports/key-questions-on-energy-and-ai/executive-summary | Onsite natural gas
A22: M01 | B22: Meta | C22: 购建固定资产现金支出 | D22: 2026前九个月 | E22: 83055 | F22: 百万美元 | G22: 文件披露 | H22: F1 | I22: Meta 2026Q3 Form 10-Q | J22: 2026-10-21 | K22: 2026-10-22 | L22: 材料/Meta_2026Q3季报__meta-20260930.htm | 现金流量表 p.10 | M22: 正值列示支出；非完整Capex。
A23: M02 | B23: Meta | C23: 融资租赁本金支付 | D23: 2026前九个月 | E23: 2769 | F23: 百万美元 | G23: 文件披露 | H23: F1 | I23: Meta 2026Q3 Form 10-Q | J23: 2026-10-21 | K23: 2026-10-22 | L23: 材料/Meta_2026Q3季报__meta-20260930.htm | 现金流量表 p.10 | M23: 与购建固定资产相加可得含租赁本金Capex。
A24: M03 | B24: Meta | C24: 购建固定资产现金支出 | D24: 2025前九个月 | E24: 48308 | F24: 百万美元 | G24: 文件披露 | H24: F1 | I24: Meta 2026Q3 Form 10-Q | J24: 2026-10-21 | K24: 2026-10-22 | L24: 材料/Meta_2026Q3季报__meta-20260930.htm | 现金流量表 p.10 | M24: 同期比较。
A25: M04 | B25: Meta | C25: 融资租赁本金支付 | D25: 2025前九个月 | E25: 1770 | F25: 百万美元 | G25: 文件披露 | H25: F1 | I25: Meta 2026Q3 Form 10-Q | J25: 2026-10-21 | K25: 2026-10-22 | L25: 材料/Meta_2026Q3季报__meta-20260930.htm | 现金流量表 p.10 | M25: 同期比较。
A26: M05 | B26: Meta | C26: 资本开支（含租赁本金） | D26: 2026Q3 | E26: 34910 | F26: 百万美元 | G26: 文件披露 | H26: F1 | I26: Meta 2026Q3 Form 10-Q | J26: 2026-10-21 | K26: 2026-10-22 | L26: 材料/Meta_2026Q3季报__meta-20260930.htm | MD&A / Executive Overview | M26: 公司四舍五入至0.01十亿美元。
A27: M06 | B27: Meta | C27: 全年资本开支指引下限 | D27: 2026 | E27: 135000 | F27: 百万美元 | G27: 公司指引 | H27: F1 | I27: Meta 2026Q3 Form 10-Q | J27: 2026-10-21 | K27: 2026-10-22 | L27: 材料/Meta_2026Q3季报__meta-20260930.htm | MD&A / Liquidity and Capital Resources | M27: 管理层指引，不是实际。
A28: M07 | B28: Meta | C28: 全年资本开支指引上限 | D28: 2026 | E28: 145000 | F28: 百万美元 | G28: 公司指引 | H28: F1 | I28: Meta 2026Q3 Form 10-Q | J28: 2026-10-21 | K28: 2026-10-22 | L28: 材料/Meta_2026Q3季报__meta-20260930.htm | MD&A / Liquidity and Capital Resources | M28: 管理层指引，不是实际。
A29: M08 | B29: Meta | C29: 经营活动现金流 | D29: 2026前九个月 | E29: 96873 | F29: 百万美元 | G29: 文件披露 | H29: F1 | I29: Meta 2026Q3 Form 10-Q | J29: 2026-10-21 | K29: 2026-10-22 | L29: 材料/Meta_2026Q3季报__meta-20260930.htm | 现金流量表 p.10 | M29: 合并口径。
A30: M09 | B30: Meta | C30: 在建工程 | D30: 2026-09-30 | E30: 89499 | F30: 百万美元 | G30: 文件披露 | H30: F1 | I30: Meta 2026Q3 Form 10-Q | J30: 2026-10-21 | K30: 2026-10-22 | L30: 材料/Meta_2026Q3季报__meta-20260930.htm | Note 6 / Property and Equipment | M30: 主要为数据中心、服务器和网络基础设施；并非已通电容量。
A31: M10 | B31: Meta | C31: 在建工程 | D31: 2025-12-31 | E31: 50521 | F31: 百万美元 | G31: 文件披露 | H31: F1 | I31: Meta 2026Q3 Form 10-Q | J31: 2026-10-21 | K31: 2026-10-22 | L31: 材料/Meta_2026Q3季报__meta-20260930.htm | Note 6 / Property and Equipment | M31: 期末存量。
A32: M11 | B32: Meta | C32: 服务器与网络资产原值 | D32: 2026-09-30 | E32: 133626 | F32: 百万美元 | G32: 文件披露 | H32: F1 | I32: Meta 2026Q3 Form 10-Q | J32: 2026-10-21 | K32: 2026-10-22 | L32: 材料/Meta_2026Q3季报__meta-20260930.htm | Note 6 / Property and Equipment | M32: 未扣累计折旧。
A33: M12 | B33: Meta | C33: 服务器与网络资产原值 | D33: 2025-12-31 | E33: 98040 | F33: 百万美元 | G33: 文件披露 | H33: F1 | I33: Meta 2026Q3 Form 10-Q | J33: 2026-10-21 | K33: 2026-10-22 | L33: 材料/Meta_2026Q3季报__meta-20260930.htm | Note 6 / Property and Equipment | M33: 未扣累计折旧。
... A81: C19 | B81: Constellation | C81: 合并净利润 | D81: 2025 | E81: 2323 | F81: 百万美元 | G81: 文件披露 | H81: F2 | I81: Constellation 2025 Form 10-K | J81: 2026-02-24 | K81: 2026-10-22 | L81: 材料/Constellation_2025年报__ceg-20251231.htm | CEG Parent Consolidated Statements of Cash Flows / Net income | M81: 含非控股权益前的合并净利润，非AI项目单独利润。
A82: C16 | B82: 项目事件 | C82: PJM研究所含部分输电升级可能最晚完工日 | D82: Crane重启 | E82: 2030-12 | F82: 年月 | G82: 文件披露 | H82: F3 | I82: Constellation 2026Q2 Form 10-Q | J82: 2026-08-06 | K82: 2026-10-22 | L82: 材料/Constellation_2026Q2季报__ceg-20260630.htm | Note 3 / Capacity Interconnection Rights for Crane | M82: 研究中的或有升级日期，不是Crane确定投运日。
A83: C17 | B83: 项目事件 | C83: FERC批准容量接入权转移豁免 | D83: Crane重启 | E83: 2026-06 | F83: 年月 | G83: 文件披露 | H83: F3 | I83: Constellation 2026Q2 Form 10-Q | J83: 2026-08-06 | K83: 2026-10-22 | L83: 材料/Constellation_2026Q2季报__ceg-20260630.htm | Note 3 / Capacity Interconnection Rights for Crane | M83: 不代表所有重启审批完成。
A84: C18 | B84: 项目事件 | C84: Calpine收购完成并表日 | D84: Constellation | E84: 2026-01-07 | F84: 日期 | G84: 文件披露 | H84: F3 | I84: Constellation 2026Q2 Form 10-Q | J84: 2026-08-06 | K84: 2026-10-22 | L84: 材料/Constellation_2026Q2季报__ceg-20260630.htm | Note 2 / Acquisition of Calpine | M84: 收入、资产与现金流比较须考虑组合变化。
A85: U15 | B85: 聚变时间表 | C85: TAE Copernicus净能量目标 | D85: 2025年公司声明 | E85: 2020年代结束前 | F85: 目标时段 | G85: 公司目标 | H85: S13 | I85: TAE · latest equity funding | J85: 2025-06-02 | K85: 2026-10-22 | L85: https://tae.com/tae-technologies-raises-150-million-in-latest-funding-round/ | 公告正文 | M85: 净能量不等于净电输出；不保证兑现。
A86: U16 | B86: 聚变时间表 | C86: TAE Da Vinci原型电厂目标 | D86: 2025年公司声明 | E86: 2030年代初 | F86: 目标时段 | G86: 公司目标 | H86: S13 | I86: TAE · latest equity funding | J86: 2025-06-02 | K86: 2026-10-22 | L86: https://tae.com/tae-technologies-raises-150-million-in-latest-funding-round/ | 公告正文 | M86: 后续拟议并购与融资可能影响进度；非保证。

Sheet 假设
A1: 可调整假设 · 输入面板
A2: 橙色数值可以调整；模型、汇总和图表自动重算。2030供电结构为研究假设；“其他”取残差，超过100%将显示检查失败。历史估计不可当成精确测量。
A4: ID | B4: 假设名称 | C4: 数值 | D4: 单位 | E4: 性质 | F4: 来源 | G4: 设定日期 | H4: 口径/用途
A5: A01 | B5: 2030用电基准倍数 | C5: 1 | D5: 倍 | E5: 假设 | F5: 研究模型自设 | G5: 2026-10-22 | H5: 作用于IEA 950TWh基准；改变后流向与汇总同步。
A6: A02 | B6: 低需求情景倍数 | C6: 0.8 | D6: 倍 | E6: 假设 | F6: 研究模型自设 | G6: 2026-10-22 | H6: 非IEA官方情景，围绕基准的敏感性测试。
A7: A03 | B7: 高需求情景倍数 | C7: 1.2 | D7: 倍 | E7: 假设 | F7: 研究模型自设 | G7: 2026-10-22 | H7: 非IEA官方情景。
A8: A04 | B8: 2030煤电份额 | C8: 0.18 | D8: % | E8: 假设 | F8: 研究模型自设 | G8: 2026-10-22 | H8: 研究展示分摊假设，不是IEA逐燃料预测；其他为残差，合计必须为100%。
A9: A05 | B9: 2030燃气份额 | C9: 0.26 | D9: % | E9: 假设 | F9: 研究模型自设 | G9: 2026-10-22 | H9: 研究展示分摊假设，不是IEA逐燃料预测；其他为残差，合计必须为100%。
A10: A06 | B10: 2030核裂变份额 | C10: 0.14 | D10: % | E10: 假设 | F10: 研究模型自设 | G10: 2026-10-22 | H10: 研究展示分摊假设，不是IEA逐燃料预测；其他为残差，合计必须为100%。
A11: A07 | B11: 2030可再生能源份额 | C11: 0.4 | D11: % | E11: 假设 | F11: 研究模型自设 | G11: 2026-10-22 | H11: 研究展示分摊假设，不是IEA逐燃料预测；其他为残差，合计必须为100%。
A12: A08 | B12: 2030聚变份额 | C12: 0 | D12: % | E12: 假设 | F12: 研究模型自设 | G12: 2026-10-22 | H12: 研究展示分摊假设，不是IEA逐燃料预测；其他为残差，合计必须为100%。
A13: A09 | B13: 示例数据中心IT名义功率 | C13: 1 | D13: GW | E13: 假设 | F13: 研究模型自设 | G13: 2026-10-22 | H13: 独立示例，不对应任何公司或已公告园区。
A14: A10 | B14: IT平均负载率 | C14: 0.85 | D14: % | E14: 假设 | F14: 研究模型自设 | G14: 2026-10-22 | H14: 已含利用率；PUE再计设施额外用电，不能重复算利用率。
A15: A11 | B15: PUE | C15: 1.2 | D15: 倍 | E15: 假设 | F15: 研究模型自设 | G15: 2026-10-22 | H15: 设施总用电/IT用电；峰值估算也采用同一PUE作为简化。
A16: A12 | B16: 全年小时数 | C16: 8760 | D16: 小时 | E16: 假设 | F16: 研究模型自设 | G16: 2026-10-22 | H16: 按非闰年标准化，不是2024年实际小时。
... A22: A18 | B22: 现场燃气超配比例 | C22: 0.35 | D22: % | E22: 假设 | F22: 研究模型自设 | G22: 2026-10-22 | H22: 取IEA30%–70%范围内示意值；非工程设计。

Sheet 模型
A1: 计算与校验 · 从输入到结论
A2: 绿色单元格均为公式。网页读取“电力流向”导出快照；调整Excel后，保存重算结果，再运行工作底稿/同步网页.py。
A4: 模型ID | B4: 计算指标 | C4: 结果 | D4: 单位 | E4: 计算口径/来源 | F4: 发布日期/性质
A5: K01 | B5: Meta 前九个月资本开支 | C5: ='明细'!E22+'明细'!E23 -> 85824 | D5: 百万美元 | E5: 购建固定资产＋融资租赁本金；现金流表精确求和。 | F5: F1 / 2026-10-21
A6: K02 | B6: Meta 上年同期资本开支 | C6: ='明细'!E24+'明细'!E25 -> 50078 | D6: 百万美元 | E6: 同口径。 | F6: F1 / 2026-10-21
A7: K03 | B7: Meta 资本开支同比 | C7: ='模型'!C5/'模型'!C6-1 -> 0.71380646 | D7: % | E7: 含融资租赁本金。 | F7: F1 / 2026-10-21；计算
A8: K04 | B8: Meta 指引隐含Q4资本开支下限 | C8: ='明细'!E27-'模型'!C5 -> 49176 | D8: 百万美元 | E8: 全年指引减去前三季度实际；不是单独Q4指引。 | F8: F1 / 2026-10-21；计算
A9: K05 | B9: Meta 指引隐含Q4资本开支上限 | C9: ='明细'!E28-'模型'!C5 -> 59176 | D9: 百万美元 | E9: 同上。 | F9: F1 / 2026-10-21；计算
A10: K06 | B10: Meta 资本开支/经营现金流 | C10: ='模型'!C5/'明细'!E29 -> 0.88594345 | D10: % | E10: 前三季度合并现金口径；不是资本回报率。 | F10: F1 / 2026-10-21；计算
A11: K07 | B11: Meta 经营现金流减资本开支 | C11: ='明细'!E29-'模型'!C5 -> 11049 | D11: 百万美元 | E11: 研究简化剩余现金，不是净利润；未扣其他投资和分红。 | F11: F1 / 2026-10-21；计算
A12: K08 | B12: Meta 在建工程较年末增幅 | C12: ='明细'!E30/'明细'!E31-1 -> 0.77152075 | D12: % | E12: 存量增长不能推导当期用电增长。 | F12: F1 / 2026-10-21；计算
A13: K09 | B13: Meta Capex精确和与披露约数差 | C13: ='模型'!C5-'明细'!E34 -> 4 | D13: 百万美元 | E13: 差额4百万美元是858.24与858.20亿美元的舍入差。 | F13: F1 / 2026-10-21；计算
A14: K10 | B14: Amazon TTM净购建固定资产推导 | C14: ='明细'!E43-'明细'!E44 -> 169000 | D14: 百万美元 | E14: 经营现金流－自由现金流；净额包括出售与激励抵减；摘要约数。 | F14: S6 / 2026-07-30；推导
A15: K11 | B15: Constellation H1收入增幅 | C15: ='明细'!E50/'明细'!E51-1 -> 0.44510823 | D15: % | E15: 并表Calpine，不能作为AI有机增长。 | F15: F3 / 2026-08-06；计算
A16: K12 | B16: Constellation H1资本开支增幅 | C16: ='明细'!E52/'明细'!E53-1 -> 0.60267006 | D16: % | E16: 组合边界发生变化。 | F16: F3 / 2026-08-06；计算
A17: K13 | B17: Constellation H1核电量同比 | C17: ='明细'!E54/'明细'!E55-1 -> -0.021222439 | D17: % | E17: 按持有比例的发电量。 | F17: F3 / 2026-08-06；计算
A18: K14 | B18: 全球2030基准用电 | C18: ='明细'!E8*'假设'!C5 -> 950 | D18: TWh | E18: IEA新版基准×研究倍数假设。 | F18: S3 / 2026-04-16 + A01假设
A19: K15 | B19: 全球2030低需求敏感性 | C19: ='模型'!C18*'假设'!C6 -> 760 | D19: TWh | E19: 非IEA官方情景。 | F19: 2026-10-22；假设计算
A20: K16 | B20: 全球2030高需求敏感性 | C20: ='模型'!C18*'假设'!C7 -> 1140 | D20: TWh | E20: 非IEA官方情景。 | F20: 2026-10-22；假设计算
A21: K17 | B21: 2025至2030用电年均增速 | C21: =('模型'!C18/'明细'!E7)^(1/5)-1 -> 0.1439219 | D21: % | E21: 5年复合增速；基于约数。 | F21: S3 + A01；计算
A22: K18 | B22: 2030等效平均功率 | C22: ='模型'!C18*1000/'假设'!C16 -> 108.44749 | D22: GW | E22: 不是峰值接入容量。 | F22: S3 + A01/A12；计算
A23: K19 | B23: 美国2024用电近似推导 | C23: ='明细'!E5*'明细'!E19 -> 186.75 | D23: TWh | E23: 全球用电×美国约45%；双重约数，仅数量级。 | F23: S1 / 2025-04-10；计算
A24: K20 | B24: 1GW IT示例年用电 | C24: ='假设'!C13*'假设'!C14*'假设'!C15*'假设'!C16/1000 -> 8.9352 | D24: TWh | E24: IT功率×负载率×PUE×小时/1000；独立假设算例。 | F24: 2026-10-22；假设
A25: K21 | B25: 示例年电费·低 | C25: ='模型'!C24*'假设'!C17 -> 536.112 | D25: 百万美元 | E25: TWh×美元/MWh = 百万美元；仅电费。 | F25: 2026-10-22；假设
A26: K22 | B26: 示例年电费·基准 | C26: ='模型'!C24*'假设'!C18 -> 804.168 | D26: 百万美元 | E26: TWh×美元/MWh = 百万美元；仅电费。 | F26: 2026-10-22；假设
A27: K23 | B27: 示例年电费·高 | C27: ='模型'!C24*'假设'!C19 -> 1072.224 | D27: 百万美元 | E27: TWh×美元/MWh = 百万美元；仅电费。 | F27: 2026-10-22；假设
A28: K24 | B28: 示例设施峰值功率 | C28: ='假设'!C13*'假设'!C15 -> 1.2 | D28: GW | E28: 简化采用相同PUE；不含电力冗余。 | F28: 2026-10-22；假设
A29: K25 | B29: 示例核电年电量等效容量 | C29: ='模型'!C24*1000/'假设'!C16/'假设'!C20 -> 1.1333333 | D29: GW | E29: 只匹配年电量；检修和瞬时功率仍需其他保供。 | F29: 2026-10-22；假设
A30: K26 | B30: 示例光伏年电量等效容量 | C30: ='模型'!C24*1000/'假设'!C16/'假设'!C21 -> 4.08 | D30: GW | E30: 只匹配年电量；不含储能与夜间保供。 | F30: 2026-10-22；假设
A31: K27 | B31: 示例现场燃气名义容量 | C31: ='模型'!C28*(1+'假设'!C22) -> 1.62 | D31: GW | E31: 峰值负荷×(1+超配比例)，非工程建议。 | F31: S3背景 + A18；假设
A32: K28 | B32: Crane满运行年电量示意 | C32: ='明细'!E58*'假设'!C20*'假设'!C16/1000000 -> 6.58314 | D32: TWh | E32: 容量×90%容量因子×8760小时；非实际交付、非合同承诺；不同起始年份。 | F32: 原始容量披露 + A16/A12假设
A33: K29 | B33: Clinton满运行年电量示意 | C33: ='明细'!E60*'假设'!C20*'假设'!C16/1000000 -> 8.837964 | D33: TWh | E33: 容量×90%容量因子×8760小时；非实际交付、非合同承诺；不同起始年份。 | F33: 原始容量披露 + A16/A12假设
A34: K30 | B34: Talen合约满量年电量示意 | C34: ='明细'!E63*'假设'!C20*'假设'!C16/1000000 -> 15.13728 | D34: TWh | E34: 容量×90%容量因子×8760小时；非实际交付、非合同承诺；不同起始年份。 | F34: 原始容量披露 + A16/A12假设
A35: K31 | B35: 2030其余来源份额 | C35: =1-SUM('假设'!C8,'假设'!C9,'假设'!C10,'假设'!C11,'假设'!C12) -> 0.02 | D35: % | E35: 残差，不额外计入电网或储能。 | F35: 2026-10-22；假设计算
A36: K32 | B36: 2030份额校验 | C36: =IF(AND('模型'!C35>-0.0000001,'模型'!C35<=1),"通过","失败：份额超过100%") -> 通过 | D36: 状态 | E36: 若失败，请调低假设份额；不得把负残差视为电量。 | F36: 研究模型
A37: K33 | B37: 2024其余来源份额 | C37: =1-SUM('明细'!E15,'明细'!E16,'明细'!E17,'明细'!E18) -> 0.02 | D37: % | E37: IEA已列份额约数之和为98%；残差包括其他来源及舍入。 | F37: S2；分摊计算

Sheet 电力流向
A1: 电力流向 · 网页同源模型
A2: 全表为终端用电的来源分摊；电网是输送层，储能是时间转移，均不重复加总。2030结构为研究假设。聚变默认零贡献。
A4: 来源 | B4: 2024份额 | C4: 2024 TWh | D4: 2030份额(假设) | E4: 2030基准 TWh | F4: 2030低 TWh | G4: 2030高 TWh | H4: 依据及日期
A5: 煤电 | B5: ='明细'!E15 -> 0.3 | C5: =B5*'明细'!E5 -> 124.5 | D5: ='假设'!C8 -> 0.18 | E5: =D5*'模型'!C18 -> 171 | F5: =D5*'模型'!C19 -> 136.8 | G5: =D5*'模型'!C20 -> 205.2 | H5: 2024：IEA 2025-04-10约数分摊；2030：研究假设 2026-10-22。
A6: 燃气 | B6: ='明细'!E16 -> 0.26 | C6: =B6*'明细'!E5 -> 107.9 | D6: ='假设'!C9 -> 0.26 | E6: =D6*'模型'!C18 -> 247 | F6: =D6*'模型'!C19 -> 197.6 | G6: =D6*'模型'!C20 -> 296.4 | H6: 2024：IEA 2025-04-10约数分摊；2030：研究假设 2026-10-22。
A7: 核裂变 | B7: ='明细'!E17 -> 0.15 | C7: =B7*'明细'!E5 -> 62.25 | D7: ='假设'!C10 -> 0.14 | E7: =D7*'模型'!C18 -> 133 | F7: =D7*'模型'!C19 -> 106.4 | G7: =D7*'模型'!C20 -> 159.6 | H7: 2024：IEA 2025-04-10约数分摊；2030：研究假设 2026-10-22。
A8: 可再生能源 | B8: ='明细'!E18 -> 0.27 | C8: =B8*'明细'!E5 -> 112.05 | D8: ='假设'!C11 -> 0.4 | E8: =D8*'模型'!C18 -> 380 | F8: =D8*'模型'!C19 -> 304 | G8: =D8*'模型'!C20 -> 456 | H8: 2024：IEA 2025-04-10约数分摊；2030：研究假设 2026-10-22。
A9: 其他 | B9: ='模型'!C37 -> 0.02 | C9: =B9*'明细'!E5 -> 8.3 | D9: ='模型'!C35 -> 0.02 | E9: =D9*'模型'!C18 -> 19 | F9: =D9*'模型'!C19 -> 15.2 | G9: =D9*'模型'!C20 -> 22.8 | H9: 2024：IEA 2025-04-10约数分摊；2030：研究假设 2026-10-22。
A10: 聚变 | B10: =0 -> 0 | C10: =B10*'明细'!E5 -> 0 | D10: ='假设'!C12 -> 0 | E10: =D10*'模型'!C18 -> 0 | F10: =D10*'模型'!C19 -> 0 | G10: =D10*'模型'!C20 -> 0 | H10: 零贡献为谨慎建模假设，不是断言2030无任何聚变示范。
A11: 合计 | B11: =SUM(B5:B10) -> 1 | C11: =SUM(C5:C10) -> 415 | D11: =SUM(D5:D10) -> 1 | E11: =SUM(E5:E10) -> 950 | F11: =SUM(F5:F10) -> 760 | G11: =SUM(G5:G10) -> 1140
A12: 守恒校验 | C12: =C11-'明细'!E5 -> 0 | E12: =E11-'模型'!C18 -> 0 | H12: 应为0；允许浮点计算尾差。

Sheet 汇总
A1: AI 的电从哪来
A2: 研究日期 2026-10-22 ｜ 绿色数值直接引用明细或模型；图表引用本页或电力流向。各公司支出期间与租赁口径不同，不做总量排名或相加。
A4: 指标 | B4: 结果 | C4: 单位 | D4: 解释 | E4: 来源/发布日期
A5: 全球数据中心用电 2024 | B5: ='明细'!E5 -> 415 | C5: TWh | D5: IEA估计；包含非AI负荷 | E5: S1 / 2025-04-10
A6: 全球数据中心用电 2025 | B6: ='明细'!E7 -> 485 | C6: TWh | D6: 最新完整年度估计 | E6: S3 / 2026-04-16
A7: 2030基准预测/情景 | B7: ='模型'!C18 -> 950 | C7: TWh | D7: IEA 2026版×可调倍数 | E7: 见模型 K14 的来源列
A8: 2030低需求敏感性 | B8: ='模型'!C19 -> 760 | C8: TWh | D8: 研究假设：基准×80% | E8: 见模型 K15 的来源列
A9: 2030高需求敏感性 | B9: ='模型'!C20 -> 1140 | C9: TWh | D9: 研究假设：基准×120% | E9: 见模型 K16 的来源列
A10: 2025—2030年均增速 | B10: ='模型'!C21 -> 0.1439219 | C10: % | D10: 约数计算 | E10: 见模型 K17 的来源列
A11: Meta 2026前九个月Capex | B11: ='模型'!C5 -> 85824 | C11: 百万美元 | D11: 含融资租赁本金 | E11: 见模型 K01 的来源列
A12: Meta Capex同比 | B12: ='模型'!C7 -> 0.71380646 | C12: % | D12: 同为前九个月 | E12: 见模型 K03 的来源列
A13: Meta Q4隐含支出下限 | B13: ='模型'!C8 -> 49176 | C13: 百万美元 | D13: 全年指引减前三季度 | E13: 见模型 K04 的来源列
A14: Meta Q4隐含支出上限 | B14: ='模型'!C9 -> 59176 | C14: 百万美元 | D14: 计算值不是Q4管理层单独指引 | E14: 见模型 K05 的来源列
A15: 1GW IT示例年用电 | B15: ='模型'!C24 -> 8.9352 | C15: TWh | D15: 85%负载率，PUE1.2，假设 | E15: 见模型 K20 的来源列
A16: 示例年电费·基准 | B16: ='模型'!C26 -> 804.168 | C16: 百万美元 | D16: 90美元/MWh，假设 | E16: 见模型 K22 的来源列
A17: Constellation 2025核电量 | B17: ='明细'!E48 -> 182690 | C17: GWh | D17: 持有比例口径 | E17: F2 / 2026-02-24
A18: Constellation 2026H1核电量同比 | B18: ='模型'!C17 -> -0.021222439 | C18: % | D18: 包含相同比例口径 | E18: 见模型 K13 的来源列
A19: 2030结构校验 | B19: ='模型'!C36 -> 通过 | C19: 状态 | D19: 份额调整后必须通过 | E19: 见模型 K32 的来源列
A42: 来源 | B42: 2024 | C42: 2030基准（假设结构）
A43: 煤电 | B43: ='电力流向'!C5 -> 124.5 | C43: ='电力流向'!E5 -> 171
A44: 燃气 | B44: ='电力流向'!C6 -> 107.9 | C44: ='电力流向'!E6 -> 247
A45: 核裂变 | B45: ='电力流向'!C7 -> 62.25 | C45: ='电力流向'!E7 -> 133
A46: 可再生能源 | B46: ='电力流向'!C8 -> 112.05 | C46: ='电力流向'!E8 -> 380
A47: 其他 | B47: ='电力流向'!C9 -> 8.3 | C47: ='电力流向'!E9 -> 19
A48: 聚变 | B48: ='电力流向'!C10 -> 0 | C48: ='电力流向'!E10 -> 0

Sheet 来源索引
A1: 来源索引与证据边界
A2: 访问日期统一为2026-10-22；本地文件发布日期取签署日。网页链接保留于报告和Excel，3D网页只显示来源名称与日期。
A4: ID | B4: 来源名称 | C4: 发布日期 | D4: 访问/读取日 | E4: 文件路径或URL | F4: 说明
A5: F1 | B5: Meta 2026Q3 Form 10-Q | C5: 2026-10-21 | D5: 2026-10-22 | E5: 材料/Meta_2026Q3季报__meta-20260930.htm | F5: 日期采用文件签署日；财务数字完全按用户提供原件，未另行验证其与在线申报的同一性。
A6: F2 | B6: Constellation 2025 Form 10-K | C6: 2026-02-24 | D6: 2026-10-22 | E6: 材料/Constellation_2025年报__ceg-20251231.htm | F6: 日期采用文件签署日；CEG Parent 合并口径。
A7: F3 | B7: Constellation 2026Q2 Form 10-Q | C7: 2026-08-06 | D7: 2026-10-22 | E7: 材料/Constellation_2026Q2季报__ceg-20260630.htm | F7: 日期采用文件签署日；2026年已并表Calpine，不能将全部增长归于AI。
A8: S1 | B8: IEA · Energy and AI / Demand & Executive summary | C8: 2025-04-10 | D8: 2026-10-22 | E8: https://www.iea.org/reports/energy-and-ai
A9: S2 | B9: IEA · Energy and AI / Supply | C9: 2025-04-10 | D9: 2026-10-22 | E9: https://www.iea.org/reports/energy-and-ai/energy-supply-for-ai
A10: S3 | B10: IEA · Key Questions on Energy and AI | C10: 2026-04-16 | D10: 2026-10-22 | E10: https://www.iea.org/reports/key-questions-on-energy-and-ai/executive-summary | F10: 最新总量采用此版本；不得与2025版发电量不加调整混用。
A11: S4 | B11: Alphabet · 2026Q2 earnings release | C11: 2026-07-22 | D11: 2026-10-22 | E11: https://www.sec.gov/Archives/edgar/data/1652044/000165204426000066/googexhibit991q22026.htm
A12: S5 | B12: Microsoft · FY2026Q4 earnings release | C12: 2026-07-29 | D12: 2026-10-22 | E12: https://www.microsoft.com/en-us/investor/earnings/fy-2026-q4/press-release-webcast
A13: S6 | B13: Amazon · 2026Q2 earnings release | C13: 2026-07-30 | D13: 2026-10-22 | E13: https://www.aboutamazon.com/news/company-news/amazon-earnings-q2-2026-report
A14: S7 | B14: Constellation · Meta / Clinton PPA | C14: 2025-06-03 | D14: 2026-10-22 | E14: https://investors.constellationenergy.com/news-releases/news-release-details/constellation-meta-sign-20-year-deal-clean-reliable-nuclear
A15: S8 | B15: Talen · Amazon PPA expansion | C15: 2025-06-11 | D15: 2026-10-22 | E15: https://ir.talenenergy.com/news-releases/news-release-details/talen-energy-expands-nuclear-energy-relationship-amazon
A16: S9 | B16: CFS · Series B2 funding | C16: 2025-08-28 | D16: 2026-10-22 | E16: https://www.cfs.energy/news-and-media/commonwealth-fusion-systems-raises-863-million-series-b2-round-to-accelerate-the-commercialization-of-fusion-energy/
A17: S10 | B17: CFS · Google power agreement | C17: 2025-06-30 | D17: 2026-10-22 | E17: https://www.cfs.energy/news-and-media/google-and-commonwealth-fusion-systems-sign-strategic-partnership/
A18: S11 | B18: Helion · Series G funding | C18: 2026-06-04；更新2026-09（日未披露） | D18: 2026-10-22 | E18: https://www.helionenergy.com/newsroom/helion-raises-465-million-series-g-funding-round-to-meet-surging-global-demand-for-power | F18: 原公告465百万美元；网页新增注释说明2026年9月最终关闭为500百万美元。
A19: S12 | B19: Helion · Microsoft fusion PPA | C19: 2023-05-10 | D19: 2026-10-22 | E19: https://www.helionenergy.com/newsroom/helion-announces-worlds-first-fusion-ppa-with-microsoft
A20: S13 | B20: TAE · latest equity funding | C20: 2025-06-02 | D20: 2026-10-22 | E20: https://tae.com/tae-technologies-raises-150-million-in-latest-funding-round/
A21: S14 | B21: TMTG / TAE · proposed merger update | C21: 2026-09-30 | D21: 2026-10-22 | E21: https://www.sec.gov/Archives/edgar/data/1849635/000143774926031535/ex_1020869.htm | F21: 用于说明交易进度；不是完成融资或商业发电证明。
A22: S15 | B22: Type One Energy · Series B | C22: 2026-10-06 | D22: 2026-10-22 | E22: https://typeoneenergy.com/insights-announcements/type-one-energy-completes-200m-series-b-financing/
A23: S16 | B23: Type One Energy · UK Infinity consortium | C23: 2026-05-06 | D23: 2026-10-22 | E23: https://typeoneenergy.com/insights-announcements/uk-infinity-fusion-consortium/ | F23: 商业运行2034年为公司目标。
A24: S17 | B24: IRENA · Renewable Power Generation Costs in 2024 | C24: 2025-07-22 | D24: 2026-10-22 | E24: https://www.irena.org/News/pressreleases/2025/Jul/91-Percent-of-New-Renewable-Projects-Now-Cheaper-Than-Fossil-Fuels-Alternatives
A25: S18 | B25: ITER · The tokamak / components | C25: 未标注发布日期 | D25: 2026-10-22 | E25: https://www.iter.org/components | F25: 仅用于部件原理；网页为概念化D-T托卡马克，不是ITER或ARC工程复刻。
A26: S19 | B26: ITER · Blanket | C26: 未标注发布日期 | D26: 2026-10-22 | E26: https://www.iter.org/machine/blanket | F26: ITER屏蔽包层与未来商业增殖包层应区分；本图显示商业D-T概念。
