Workbook

Sheet 说明
A1: SpaceX × Tesla 合并财务分析模型
A2: 投行并购组内部讨论稿 ｜ 数据截止 2026 年 9 月 30 日 ｜ 市场数据 2026 年 10 月 21 日收盘 ｜ 编制日期 2026 年 10 月 22 日
A4: 一、模型目的与使用说明
B5: 目的：把 SpaceX 与 Tesla 视为一家公司，测算合并后的收入、利润、现金与负债结构，并用至少三种方法测算换股比例、双方原股东持股与马斯克个人持股变化。本模型为潜在交易的情景分析，不假设交易必然发生；仅用于内部研究与演示，不构成投资建议，不含买入/卖出/持有评级或目标价。
B6: 口径：除特别注明外，金额单位为百万美元（$M），股数为百万股，股价为美元/股。财年均为自然年。SpaceX 的“SI”即 Super Intelligence 分部（原 AI 分部）；Tesla 的“汽车”分部含服务及其他。
B7: 期间：最近四个季度（LTM）= 2025Q4 + 2026Q1 + 2026Q2 + 2026Q3；最近一个完整财年 = 2025 财年。SpaceX 2025Q4 由 2025 全年减去 2025 年前三季度推导；Tesla 2025Q4 及 2026 各季度取自 2026Q3 业绩公告的季度财务摘要。
B8: 来源：所有历史财务数字以“材料/”文件夹内的原始披露文件为准（招股书、季报、年报、业绩公告、委托书）；市场数据来自公开行情网站，具体日期与链接见“市场数据”页。每个数字在 H 列标注了文件名与章节/表名。
B9: 假设与事实分离：黄色底色为输入/披露数据，蓝色底色为公式计算；所有估算、假设均以“假设”字样标注，并在“合并备考”第六节与 README 中集中列示。不要将假设当作披露事实。
B10: 公式联动：修改“换股比例”页的溢价率、倍数，或“市场数据”页的股价、股本，换股比例、持股结构、敏感性表与备考商誉会自动更新。请勿覆盖蓝色公式格。
B11: 限制：本模型未做完整购买会计（PPA）、未做税务结构设计、未计入协同效应、未做协同成本、未考虑异议股东评估权与监管审批条件；换股比例仅为财务测算，不构成交易报价。
A13: 二、颜色与标记图例
B14: 输入/披露 | C14: 来自原始文件的数字，或需要用户调整的假设
B15: 公式 | C15: 由其他单元格计算，不应手动覆盖
B16: 表头 | C16: 列标题/小计标签
B17: 假设 | C17: 带“假设”字样的输入格，属于估算而非披露
A19: 三、原始文件清单
C20: 文件 | D20: 内容/用途 | E20: 日期
C21: SpaceX_招股书__spaceexplorationtechnologi.htm | D21: 424B4 招股书：2025 全年及 2026Q1 财务、分部、关联交易、股权结构 | E21: 2026-06
C22: SpaceX_2026Q2季报__spcx-20260630.htm | D22: 2026Q2 Form 10-Q：Q2/H1 财务、分部、关联交易 | E22: 2026-08
C23: SpaceX_2026Q3业绩公告__spaceexplorationtechnologi.htm | D23: 2026Q3 业绩公告：Q3/9M 财务、分部、资产负债表、现金流 | E23: 2026-10-20
C24: Tesla_2025年报__tsla-20251231.htm | D24: 2025 Form 10-K：全年财务、分部、关联交易 | E24: 2026-02
C25: Tesla_2026Q3季报__tsla-20260930.htm | D25: 2026Q3 Form 10-Q：Q3/9M 财务、资产负债表、关联交易 | E25: 2026-10-22
C26: Tesla_2026Q3业绩公告__exhibit9914.htm | D26: 2026Q3 业绩公告：季度财务摘要、TTM、非GAAP调节 | E26: 2026-10-21
C27: Tesla_2026股东大会委托书__tm267596-1_def14a.htm | D27: 2026 委托书：马斯克持股、关联交易、高管薪酬 | E27: 2026-09
A29: 四、核心假设清单（均标为“假设”，与披露事实分开）
B30: 编号 | C30: 假设 | D30: 数值/处理 | E30: 影响
B31: A1 | C31: 换股溢价率（相对 Tesla 2026-10-21 收盘市值） | D31: 20% | E31: 基准情形换股比例与持股结构
B32: A2 | C32: 收入倍数法：SpaceX / Tesla LTM 收入倍数 | D32: 50.0x / 12.0x | E32: 方法 D 的隐含股权价值
B33: A3 | C33: EBITDA 倍数法：SpaceX / Tesla LTM Adj. EBITDA 倍数 | D33: 110.0x / 70.0x | E33: 方法 E 的隐含股权价值
B34: A4 | C34: 2025Q4 Tesla→SpaceX/xAI 关联收入 | D34: 250.4（=573.4−323.0） | E34: LTM 内部收入抵消
B35: A5 | C35: 2025 前三季度 Tesla 关联方收入 | D35: 323.0 | E35: 仅用于推导 2025Q4，属估算
B36: A6 | C36: Tesla 总部运营费用按毛利占比分摊至汽车/服务/能源 | D36: 按毛利占比 | E36: 利润结构中的业务贡献
B37: A7 | C37: 备考所得税率（用于调整项） | D37: 21% | E37: 关联交易与公允价值变动调整的税盾
B38: A8 | C38: 购买会计：可辨认无形资产增值 / 摊销年限 | D38: 30,000 / 10 年 | E38: 商誉与增量摊销（仅示意）
B39: A9 | C39: 交易费用率 | D39: 对价的 0.5% | E39: 一次性费用（未计入备考利润）
B40: A10 | C40: Tesla 持有的 SpaceX 股权按库存股/交叉持股抵消 | D40: 2,865（9/30/26 公允价值） | E40: 减少备考权益与资产
B41: A11 | C41: SpaceX 股本口径：8,240 A + 5,339 B（含未归属限制性股票） | D41: 13,579 | E41: 换股分母；不含未行权期权
... B44: A14 | C44: 协同效应 | D44: 0（未计入） | E44: 备考利润不含协同，属保守处理
A46: 五、重要提示
B47: 本模型中的“备考”数字是把两家公司历史报表简单相加并做关联交易/交叉持股抵消，不是购买会计后的合并报表。实际交易完成后，收购价格分摊、商誉、无形资产摊销、库存增值、递延税、交易费用与协同效应都会改变报告利润。换股比例是财务测算，不是报价，也不构成任何投资建议。

Sheet 市场数据
A1: 市场数据、股本与持股
A2: 价格日期 2026-10-21 收盘（宣布前参考 2026-10-19）；行情来源 stockanalysis.com，访问日期 2026-10-22；股数来自公司披露
A4: 项目 | B4: 数值 | C4: 单位 | D4: 日期 | E4: 来源/备注
A5: SpaceX（SPCX）收盘价 | B5: 159.31 | C5: $/股 | D5: 2026-10-21 | E5: stockanalysis.com/stocks/spcx/history/；收盘价
A6: Tesla（TSLA）收盘价 | B6: 386.47 | C6: $/股 | D6: 2026-10-21 | E6: stockanalysis.com/stocks/tsla/history/；收盘价
A7: SPCX 收盘价（宣布前） | B7: 147.96 | C7: $/股 | D7: 2026-10-19 | E7: 合并消息前最后一个交易日收盘
A8: TSLA 收盘价（宣布前） | B8: 368.06 | C8: $/股 | D8: 2026-10-19 | E8: 合并消息前最后一个交易日收盘
A9: SPCX 30日成交量加权均价 | B9: 154.35 | C9: $/股 | D9: 2026-09-10至10-21 | E9: 按收盘价×成交量计算，30个交易日；近似VWAP
A10: TSLA 30日成交量加权均价 | B10: 368.4 | C10: $/股 | D10: 2026-09-10至10-21 | E10: 按收盘价×成交量计算，30个交易日；近似VWAP
A11: SPCX 在外股本 | B11: 13579 | C11: 百万股 | D11: 2026-09-30 | E11: Q3业绩公告资产负债表：8,240 A + 5,339 B
A12: TSLA 在外股本 | B12: 3952.758 | C12: 百万股 | D12: 2026-10-15 | E12: 2026Q3 Form 10-Q 封面：3,952,757,946 股
A13: SPCX 市值 | B13: =B5*B11 | C13: $M | D13: 2026-10-21 | E13: 公式：收盘价×股本
A14: TSLA 市值 | B14: =B6*B12 | C14: $M | D14: 2026-10-21 | E14: 公式：收盘价×股本
A15: SPCX 市值（宣布前） | B15: =B7*B11 | C15: $M | D15: 2026-10-19 | E15: 公式
A16: TSLA 市值（宣布前） | B16: =B8*B12 | C16: $M | D16: 2026-10-19 | E16: 公式
A17: SPCX 市值（30日VWAP） | B17: =B9*B11 | C17: $M | D17: 2026-09-10至10-21 | E17: 公式
A18: TSLA 市值（30日VWAP） | B18: =B10*B12 | C18: $M | D18: 2026-09-10至10-21 | E18: 公式
A19: SPCX 净债务/(净现金) | B19: ='SpaceX数据'!G28 | C19: $M | D19: 2026-09-30 | E19: 有息负债−现金及短期投资；负数为净现金
A20: TSLA 净债务/(净现金) | B20: ='Tesla数据'!G28 | C20: $M | D20: 2026-09-30 | E20: 有息负债−现金及短期投资；负数为净现金
A21: SPCX 企业价值 | B21: =B13+B19 | C21: $M | D21: 2026-10-21 | E21: 市值+净债务
A22: TSLA 企业价值 | B22: =B14+B20 | C22: $M | D22: 2026-10-21 | E22: 市值+净债务
A23: SPCX LTM 营业收入 | B23: ='SpaceX数据'!G5 | C23: $M | D23: 2025Q4-2026Q3 | E23: 最近四个季度合计
A24: TSLA LTM 营业收入 | B24: ='Tesla数据'!G5 | C24: $M | D24: 2025Q4-2026Q3 | E24: 最近四个季度合计
A25: SPCX LTM 调整后EBITDA | B25: ='SpaceX数据'!G31 | C25: $M | D25: 2025Q4-2026Q3 | E25: 公司披露口径
A26: TSLA LTM 调整后EBITDA | B26: ='Tesla数据'!G31 | C26: $M | D26: 2025Q4-2026Q3 | E26: 公司披露口径
A27: SPCX EV / LTM 营收 | B27: =B21/B23 | C27: x | D27: 2026-10-21 | E27: 公式
A28: TSLA EV / LTM 营收 | B28: =B22/B24 | C28: x | D28: 2026-10-21 | E28: 公式
A29: SPCX EV / LTM Adj. EBITDA | B29: =B21/B25 | C29: x | D29: 2026-10-21 | E29: 公式
A30: TSLA EV / LTM Adj. EBITDA | B30: =B22/B26 | C30: x | D30: 2026-10-21 | E30: 公式
A33: 持股与交叉持股（用于换股与马斯克持股测算）
A34: 项目 | B34: 数值 | C34: 单位 | D34: 日期 | E34: 来源/备注
A35: 马斯克持有 SPCX 股数 | B35: 6418.5475 | C35: 百万股 | D35: 2026-05-01 | E35: 招股书 Security Ownership：849.5 A + 5,569.1 B（含 350.0 期权/限制性股票）
A36: 马斯克持有 TSLA 股数 | B36: 699.58088 | C36: 百万股 | D36: 2026-09-30 | E36: 2026 委托书 Ownership of Securities：699,580,882 股
A37: 马斯克持有 SPCX 比例 | B37: =B35/B11 | C37: % | D37: 2026-09-30 | E37: 按 9/30 在外股本计算；招股书按 5/1 口径披露 49.0% 经济权益
A38: 马斯克持有 TSLA 比例 | B38: =B36/B12 | C38: % | D38: 2026-09-30 | E38: 按 10-Q 股本计算；委托书按自身口径披露 19.8%
A39: Tesla 持有 SPCX 股数（假设） | B39: 14.8 | C39: 百万股 | D39: 2026-09-30 | E39: 假设：$2.0bn 投资 / $135 IPO价；公司披露持股 <1%
A40: Tesla 持有 SPCX 公允价值 | B40: 2865 | C40: $M | D40: 2026-09-30 | E40: Tesla Q3 10-Q Note 2：Level 1 公允价值 2,865
A41: Tesla 持有 SPCX 比例 | B41: =B39/B11 | C41: % | D41: 2026-09-30 | E41: 公式；与“<1%”披露一致
A42: 马斯克合并前 look-through 经济权益 | B42: =(B35*B5+B36*B6)/(B13+B14) | C42: % | D42: 2026-10-21 | E42: 按两家市值加权：马斯克持股市值 / 两家合计市值
A43: SPCX Class A 总股数 | B43: 8240 | C43: 百万股 | D43: 2026-09-30 | E43: Q3业绩公告资产负债表
A44: SPCX Class B 总股数 | B44: 5339 | C44: 百万股 | D44: 2026-09-30 | E44: Q3业绩公告资产负债表
A45: 马斯克 Class A 股数 | B45: 849.49444 | C45: 百万股 | D45: 2026-05-01 | E45: 招股书
A46: 马斯克 Class B 股数（推算） | B46: 5219.0531 | C46: 百万股 | D46: 2026-05-01 | E46: 5,569.053 − 350.0 期权 = 5,219.053（假设期权未行权）
A47: 马斯克 SPCX 投票权（计算） | B47: =(B45+B46*10)/(B43+B44*10) | C47: % | D47: 2026-05-01 | E47: 假设 Class B 每股 10 票
A48: 马斯克 SPCX 投票权（披露） | B48: 0.844 | C48: % | D48: 2026-05-01 | E48: 招股书：合并投票权约 84.4%
A49: 差异说明（计算 vs 披露） | B49: =B47-B48 | C49: pp | D49: — | E49: 主要因期权/限制性股票是否计入、Class B 归属口径不同
A51: 注：行情网站为公开数据，仅用于定价参考；公司披露的股本与持股以原始文件为准。Tesla 对 SpaceX 的 2,865 美元公允价值含 2026 年 9M 累计 863 美元公允价值变动收益。

Sheet SpaceX数据
A1: SpaceX：最近四个季度与 2025 财年关键财务
A2: $M；Q4-25 由 FY2025 − 9M2025 推导；Q1-26 来自招股书，Q2-26 来自 10-Q，Q3-26 来自业绩公告；LTM = Q4-25+Q1-26+Q2-26+Q3-26
A4: 项目 | B4: FY2025 | C4: Q4-25 | D4: Q1-26 | E4: Q2-26 | F4: Q3-26 | G4: LTM | H4: 来源/口径 | I4: 2025前三季度（推导用）
A5: 营业收入 | B5: 18674 | C5: =B5-I5 | D5: 4694 | E5: 7814 | F5: 14575 | G5: =SUM(C5:F5) | H5: 招股书 Summary/利润表；Q1 招股书；Q2 10-Q；Q3 公告 | I5: 13714
A6: 营业成本 | B6: 9451 | C6: =B6-I6 | D6: 2388 | E6: 3495 | F6: 5478 | G6: =SUM(C6:F6) | H6: 招股书 MD&A/利润表；Q2 10-Q；Q3 公告 | I6: 6949
A7: 毛利 | B7: =B5-B6 | C7: =B7-I7 | D7: =D5-D6 | E7: =E5-E6 | F7: =F5-F6 | G7: =SUM(C7:F7) | H7: = 营业收入 − 营业成本 | I7: =I5-I6
A8: 研发费用 | B8: 8643 | C8: =B8-I8 | D8: 3514 | E8: 3548 | F8: 4596 | G8: =SUM(C8:F8) | H8: 招股书利润表；Q2 10-Q；Q3 公告 | I8: 5806
A9: 销售及管理费用 | B9: 2644 | C9: =B9-I9 | D9: 746 | E9: 912 | F9: 1707 | G9: =SUM(C9:F9) | H9: 同上 | I9: 1674
A10: 重组费用（收益） | B10: 487 | C10: =B10-I10 | D10: -11 | E10: 2 | F10: 3 | G10: =SUM(C10:F10) | H10: 同上 | I10: 472
A11: 减值 | B11: 38 | C11: =B11-I11 | D11: 0 | E11: 0 | F11: 0 | G11: =SUM(C11:F11) | H11: 同上 | I11: 29
A12: 总成本与费用 | B12: =B6+B8+B9+B10+B11 | C12: =B12-I12 | D12: =D6+D8+D9+D10+D11 | E12: =E6+E8+E9+E10+E11 | F12: =F6+F8+F9+F10+F11 | G12: =SUM(C12:F12) | H12: = 营业成本+研发+销售管理+重组+减值 | I12: =I6+I8+I9+I10+I11
A13: 经营利润/(亏损) | B13: =B5-B12 | C13: =B13-I13 | D13: =D5-D12 | E13: =E5-E12 | F13: =F5-F12 | G13: =SUM(C13:F13) | H13: = 毛利 − 总成本与费用 | I13: =I5-I12
A14: 利息费用 | B14: 1945 | C14: =B14-I14 | D14: 664 | E14: 629 | F14: 675 | G14: =SUM(C14:F14) | H14: 利润表；Q3 公告（其中关联方 351） | I14: 1372
A15: 利息收入 | B15: 492 | C15: =B15-I15 | D15: 213 | E15: 340 | F15: 873 | G15: =SUM(C15:F15) | H15: 利润表 | I15: 370
A16: 其他收益/(费用)净额 | B16: -177 | C16: =B16-I16 | D16: -1876 | E16: -86 | F16: 1025 | G16: =SUM(C16:F16) | H16: 利润表；Q3 含关联方 561 | I16: 342
A17: 税前利润 | B17: =B13-B14+B15+B16 | C17: =B17-I17 | D17: =D13-D14+D15+D16 | E17: =E13-E14+E15+E16 | F17: =F13-F14+F15+F16 | G17: =SUM(C17:F17) | H17: = 经营利润 − 利息费用 + 利息收入 + 其他 | I17: =I13-I14+I15+I16
A18: 所得税费用/(收益) | B18: 718 | C18: =B18-I18 | D18: 6 | E18: 23 | F18: -390 | G18: =SUM(C18:F18) | H18: 利润表 | I18: 714
A19: 净利润/(亏损) | B19: =B17-B18 | C19: =B19-I19 | D19: =D17-D18 | E19: =E17-E18 | F19: =F17-F18 | G19: =SUM(C19:F19) | H19: = 税前利润 − 所得税 | I19: =I17-I18
A20: 归母净利润 | B20: =B19 | C20: =B20-I20 | D20: =D19 | E20: =E19 | F20: =F19 | G20: =SUM(C20:F20) | H20: SpaceX 无少数股东，等于净利润 | I20: =I19
A21: 经营活动现金流 | B21: 6785 | C21: =B21-I21 | D21: 1047 | E21: 2419 | F21: 9631 | G21: =SUM(C21:F21) | H21: Q3 公告现金流量表；Q2 10-Q；Q1 招股书 | I21: 4120
A22: 资本开支 | B22: 20737 | C22: =B22-I22 | D22: 10107 | E22: 18369 | F22: 19593 | G22: =SUM(C22:F22) | H22: Q3 公告现金流量表：购置 PP&E | I22: 13846
A23: 自由现金流 | B23: =B21-B22 | C23: =B23-I23 | D23: =D21-D22 | E23: =E21-E22 | F23: =F21-F22 | G23: =SUM(C23:F23) | H23: = 经营现金流 − 资本开支 | I23: =I21-I22
A24: 现金及现金等价物 | B24: 24747 | F24: 51294 | G24: =F24 | H24: Q3公告资产负债表；FY2025 招股书
A25: 有价证券（短期投资） | B25: 0 | F25: 38561 | G25: =F25 | H25: 同上
A26: 现金及短期投资 | B26: =B24+B25 | F26: =F24+F25 | G26: =F26 | H26: = 现金 + 有价证券
A27: 有息负债（含融资租赁） | B27: 22896 | F27: 38844 | G27: =F27 | H27: Q3公告：流动 2,698 + 长期 36,146；FY：928+21,968
A28: 净债务/(净现金) | B28: =B27-B26 | F28: =F27-F26 | G28: =F28 | H28: = 有息负债 − 现金及短期投资
A29: 股东权益合计 | B29: 2573 | F29: 176768 | G29: =F29 | H29: Q3公告资产负债表
A30: 可转换优先股（夹层权益） | B30: 38752 | F30: 0 | G30: =F30 | H30: FY2025 38,752；IPO 时已转普通股，Q3 为 0
A31: 调整后 EBITDA | B31: 6584 | C31: =B31-I31 | D31: 1127 | E31: 3538 | F31: 8809 | G31: =SUM(C31:F31) | H31: 公司披露的非GAAP口径；FY 6,584 / 9M25 5,113 | I31: 5113
A34: 分业务数据（按公司披露的分部；Space / Connectivity / SI）
A35: 项目 | B35: FY2025 | C35: Q4-25 | D35: Q1-26 | E35: Q2-26 | F35: Q3-26 | G35: LTM | H35: 来源/口径 | I35: 2025前三季度（推导用）
A36: Space 收入 | B36: 4086 | C36: =B36-I36 | D36: 619 | E36: 962 | F36: 1767 | G36: =SUM(C36:F36) | H36: Q3公告分部表；Q2 10-Q Note 18；Q1 招股书 | I36: 3277
A37: Connectivity 收入 | B37: 11387 | C37: =B37-I37 | D37: 3257 | E37: 4291 | F37: 5248 | G37: =SUM(C37:F37) | H37: 同上 | I37: 8159
A38: SI（原AI）收入 | B38: 3201 | C38: =B38-I38 | D38: 818 | E38: 2561 | F38: 7560 | G38: =SUM(C38:F38) | H38: 同上 | I38: 2278
A39: 分部收入合计 | B39: =SUM(B36:B38) | C39: =B39-I39 | D39: =SUM(D36:D38) | E39: =SUM(E36:E38) | F39: =SUM(F36:F38) | G39: =SUM(C39:F39) | H39: 分部加总 | I39: =SUM(I36:I38)
A40: Space 毛利 | B40: 2734 | D40: 338 | E40: 633 | F40: 1332 | H40: FY2025 Note 19；Q1 招股书；Q2 10-Q；Q3 公告；Q4 分部毛利未披露
A41: Connectivity 毛利 | B41: 5466 | D41: 1606 | E41: 2231 | F41: 2880 | H41: 同上
A42: SI 毛利 | B42: 1023 | D42: 362 | E42: 1455 | F42: 4885 | H42: 同上
A43: 分部毛利合计 | B43: =SUM(B40:B42) | H43: 分部加总
A44: Space 经营利润 | B44: -657 | C44: =B44-I44 | D44: -662 | E44: -542 | F44: -7 | G44: =SUM(C44:F44) | H44: Q3公告分部表 | I44: -181
A45: Connectivity 经营利润 | B45: 4423 | C45: =B45-I45 | D45: 1188 | E45: 1656 | F45: 2367 | G45: =SUM(C45:F45) | H45: 同上 | I45: 3147
A46: SI 经营利润 | B46: -6355 | C46: =B46-I46 | D46: -2469 | E46: -1257 | F46: 431 | G46: =SUM(C46:F46) | H46: 同上 | I46: -4182
A47: 分部经营利润合计 | B47: =SUM(B44:B46) | C47: =B47-I47 | D47: =SUM(D44:D46) | E47: =SUM(E44:E46) | F47: =SUM(F44:F46) | G47: =SUM(C47:F47) | H47: 分部加总 | I47: =SUM(I44:I46)
A48: Space 资本开支 | B48: 3832 | C48: =B48-I48 | D48: 1052 | E48: 1174 | F48: 1606 | G48: =SUM(C48:F48) | H48: Q3公告分部表 | I48: 2818
A49: Connectivity 资本开支 | B49: 4178 | C49: =B49-I49 | D49: 1332 | E49: 1367 | F49: 1543 | G49: =SUM(C49:F49) | H49: 同上 | I49: 2951
A50: SI 资本开支 | B50: 12727 | C50: =B50-I50 | D50: 7723 | E50: 15828 | F50: 16444 | G50: =SUM(C50:F50) | H50: 同上 | I50: 8077
A51: 分部资本开支合计 | B51: =SUM(B48:B50) | C51: =B51-I51 | D51: =SUM(D48:D50) | E51: =SUM(E48:E50) | F51: =SUM(F48:F50) | G51: =SUM(C51:F51) | H51: 分部加总 | I51: =SUM(I48:I50)
A52: Space 调整后EBITDA | B52: 653 | C52: =B52-I52 | D52: -351 | E52: -205 | F52: 357 | G52: =SUM(C52:F52) | H52: Q3公告分部表 | I52: 803
A53: Connectivity 调整后EBITDA | B53: 7168 | C53: =B53-I53 | D53: 2087 | E53: 2597 | F53: 3499 | G53: =SUM(C53:F53) | H53: 同上 | I53: 5123
A54: SI 调整后EBITDA | B54: -1237 | C54: =B54-I54 | D54: -609 | E54: 1146 | F54: 4953 | G54: =SUM(C54:F54) | H54: 同上 | I54: -813
A55: 分部调整后EBITDA合计 | B55: =SUM(B52:B54) | C55: =B55-I55 | D55: =SUM(D52:D54) | E55: =SUM(E52:E54) | F55: =SUM(F52:F54) | G55: =SUM(C55:F55) | H55: 分部加总 | I55: =SUM(I52:I54)

Sheet Tesla数据
A1: Tesla：最近四个季度与 2025 财年关键财务
A2: $M；Q4-25 与 2026 各季度取自 2026Q3 业绩公告季度财务摘要；FY2025 取自 2025 10-K；LTM = Q4-25+Q1-26+Q2-26+Q3-26
A4: 项目 | B4: FY2025 | C4: Q4-25 | D4: Q1-26 | E4: Q2-26 | F4: Q3-26 | G4: LTM | H4: 来源/口径 | I4: 2025前三季度（推导用）
A5: 营业收入 | B5: 94827 | C5: =B5-I5 | D5: 22387 | E5: 28236 | F5: 28046 | G5: =SUM(C5:F5) | H5: 2025 10-K 利润表；2026Q3 公告 Financial Summary | I5: 69926
A6: 营业成本 | B6: 77733 | C6: =B6-I6 | D6: 17667 | E6: 23485 | F6: 22552 | G6: =SUM(C6:F6) | H6: 同上 | I6: 57841
A7: 毛利 | B7: =B5-B6 | C7: =B7-I7 | D7: =D5-D6 | E7: =E5-E6 | F7: =F5-F6 | G7: =SUM(C7:F7) | H7: = 营业收入 − 营业成本 | I7: =I5-I6
A8: 研发费用 | B8: 6411 | C8: =B8-I8 | D8: 1946 | E8: 2371 | F8: 2761 | G8: =SUM(C8:F8) | H8: 同上 | I8: 4628
A9: 销售及管理费用 | B9: 5834 | C9: =B9-I9 | D9: 1833 | E9: 1982 | F9: 2015 | G9: =SUM(C9:F9) | H9: 同上 | I9: 4179
A10: 重组及其他费用 | B10: 494 | C10: =B10-I10 | D10: 0 | E10: 0 | F10: 0 | G10: =SUM(C10:F10) | H10: 同上 | I10: 332
A11: 总运营费用 | B11: =B8+B9+B10 | C11: =B11-I11 | D11: =D8+D9+D10 | E11: =E8+E9+E10 | F11: =F8+F9+F10 | G11: =SUM(C11:F11) | H11: = 研发+销售管理+重组 | I11: =I8+I9+I10
A12: 经营利润 | B12: =B7-B11 | C12: =B12-I12 | D12: =D7-D11 | E12: =E7-E11 | F12: =F7-F11 | G12: =SUM(C12:F12) | H12: = 毛利 − 总运营费用 | I12: =I7-I11
A13: 利息收入 | B13: 1680 | C13: =B13-I13 | D13: 434 | E13: 422 | F13: 445 | G13: =SUM(C13:F13) | H13: 公告利润表 | I13: 1231
A14: 利息费用 | B14: 338 | C14: =B14-I14 | D14: 92 | E14: 81 | F14: 90 | G14: =SUM(C14:F14) | H14: 公告利润表 | I14: 253
A15: 其他收益/(费用)净额 | B15: -419 | C15: =B15-I15 | D15: -535 | E15: 590 | F15: -117 | G15: =SUM(C15:F15) | H15: 公告利润表；含 SpaceX 股权投资公允价值变动 | I15: 173
A16: 税前利润 | B16: =B12+B13-B14+B15 | C16: =B16-I16 | D16: =D12+D13-D14+D15 | E16: =E12+E13-E14+E15 | F16: =F12+F13-F14+F15 | G16: =SUM(C16:F16) | H16: = 经营利润 + 利息收入 − 利息费用 + 其他 | I16: =I12+I13-I14+I15
A17: 所得税费用 | B17: 1423 | C17: =B17-I17 | D17: 257 | E17: 201 | F17: 152 | G17: =SUM(C17:F17) | H17: 公告利润表 | I17: 1098
A18: 净利润 | B18: =B16-B17 | C18: =B18-I18 | D18: =D16-D17 | E18: =E16-E17 | F18: =F16-F17 | G18: =SUM(C18:F18) | H18: = 税前利润 − 所得税 | I18: =I16-I17
A19: 减：少数股东损益 | B19: 61 | C19: =B19-I19 | D19: 14 | E19: 14 | F19: 17 | G19: =SUM(C19:F19) | H19: 公告利润表 | I19: 45
A20: 归母净利润 | B20: =B18-B19 | C20: =B20-I20 | D20: =D18-D19 | E20: =E18-E19 | F20: =F18-F19 | G20: =SUM(C20:F20) | H20: = 净利润 − 少数股东损益 | I20: =I18-I19
A21: 经营活动现金流 | B21: 14747 | C21: =B21-I21 | D21: 3937 | E21: 4697 | F21: 6263 | G21: =SUM(C21:F21) | H21: 2025 10-K 现金流量表；2026Q3 公告/10-Q | I21: 10934
A22: 资本开支 | B22: 8527 | C22: =B22-I22 | D22: 2493 | E22: 5789 | F22: 4732 | G22: =SUM(C22:F22) | H22: 2025 10-K；2026Q3 公告（不含融资租赁） | I22: 6134
A23: 自由现金流 | B23: =B21-B22 | C23: =B23-I23 | D23: =D21-D22 | E23: =E21-E22 | F23: =F21-F22 | G23: =SUM(C23:F23) | H23: = 经营现金流 − 资本开支 | I23: =I21-I22
A24: 现金及现金等价物 | B24: 16513 | F24: 17853 | G24: =F24 | H24: 2026Q3 10-Q 资产负债表；FY2025 10-K
A25: 短期投资 | B25: 27546 | F25: 27594 | G25: =F25 | H25: 同上
A26: 现金及短期投资 | B26: =B24+B25 | F26: =F24+F25 | G26: =F26 | H26: = 现金 + 短期投资
A27: 有息负债（含融资租赁） | B27: 8376 | F27: 9523 | G27: =F27 | H27: Q3：流动 1,387 + 长期 8,136；FY：1,640+6,736
A28: 净债务/(净现金) | B28: =B27-B26 | F28: =F27-F26 | G28: =F28 | H28: = 有息负债 − 现金及短期投资
A29: 股东权益合计 | B29: 82137 | F29: 89289 | G29: =F29 | H29: 2026Q3 10-Q；FY2025 10-K
A30: 少数股东权益 | B30: 670 | F30: 546 | G30: =F30 | H30: 资产负债表
A31: 调整后 EBITDA | B31: 14596 | C31: 4154 | D31: 3668 | E31: 3273 | F31: 3900 | G31: =SUM(C31:F31) | H31: 公司披露的非GAAP口径；FY 14,596；TTM 表交叉核对 14,995
A34: 分业务数据（两个报告分部：汽车 / 能源；并拆出汽车与服务收入）
A35: 项目 | B35: FY2025 | C35: Q4-25 | D35: Q1-26 | E35: Q2-26 | F35: Q3-26 | G35: LTM | H35: 来源/口径 | I35: 2025前三季度（推导用）
A36: 汽车分部收入（含服务） | B36: 82056 | C36: =B36-I36 | D36: 19979 | E36: 25097 | F36: 25165 | G36: =SUM(C36:F36) | H36: 2025 10-K Note 16；2026Q3 10-Q Note 14；Q4 由差额推导 | I36: 60992
A37: 能源分部收入 | B37: 12771 | C37: =B37-I37 | D37: 2408 | E37: 3139 | F37: 2881 | G37: =SUM(C37:F37) | H37: 同上 | I37: 8934
A38: 分部收入合计 | B38: =B36+B37 | C38: =B38-I38 | D38: =D36+D37 | E38: =E36+E37 | F38: =F36+F37 | G38: =SUM(C38:F38) | H38: = 汽车分部 + 能源分部 | I38: =I36+I37
A39: 汽车分部毛利 | B39: 13292 | C39: =B39-I39 | D39: 3768 | E39: 4111 | F39: 4540 | G39: =SUM(C39:F39) | H39: 同上 | I39: 9381
A40: 能源分部毛利 | B40: 3802 | C40: =B40-I40 | D40: 952 | E40: 640 | F40: 954 | G40: =SUM(C40:F40) | H40: 同上 | I40: 2704
A41: 分部毛利合计 | B41: =B39+B40 | C41: =B41-I41 | D41: =D39+D40 | E41: =E39+E40 | F41: =F39+F40 | G41: =SUM(C41:F41) | H41: = 汽车分部毛利 + 能源分部毛利 | I41: =I39+I40
A42: 汽车（整车/积分/租赁）收入 | B42: 69526 | C42: =B42-I42 | D42: 16234 | E42: 20516 | F42: 20560 | G42: =SUM(C42:F42) | H42: 2026Q3 公告 Financial Summary；Q4 由差额 | I42: 51833
A43: 服务及其他收入 | B43: 12530 | C43: =B43-I43 | D43: 3745 | E43: 4581 | F43: 4605 | G43: =SUM(C43:F43) | H43: 同上 | I43: 9159
A44: 汽车（整车/积分/租赁）毛利 | B44: 12361 | C44: =B44-I44 | D44: 3422 | E44: 3463 | F44: 3806 | G44: =SUM(C44:F44) | H44: 收入减成本；Q4 由差额 | I44: 8748
A45: 服务及其他毛利 | B45: 931 | C45: =B45-I45 | D45: 346 | E45: 648 | F45: 734 | G45: =SUM(C45:F45) | H45: 同上 | I45: 633
A46: 能源分部毛利（备查） | B46: =B40 | C46: =C40 | D46: =D40 | E46: =E40 | F46: =F40 | G46: =G40 | H46: = 能源分部毛利

Sheet 合并备考
A1: 合并备考：把两家公司当成一家看
A2: LTM = 2025Q4 + 2026Q1 + 2026Q2 + 2026Q3；历史报表相加并抵消关联交易与交叉持股，不含购买会计与协同效应
A4: 一、交易与备考基准（基准情形 = 市值法 + 20% 溢价）
A5: 基准定价方法 | B5: A 市值法（2026-10-21 收盘） | D5: 来自“换股比例”方法 A
A6: 换股溢价率 | B6: ='换股比例'!B19 | D6: 输入格在“换股比例”页；改变后本页与敏感性自动更新
A7: 换股比例（SPCX 股 / TSLA 股） | B7: ='换股比例'!H35 | D7: 每 1 股 Tesla 换得的 SpaceX 股数
A8: 交易对价（$M） | B8: ='市场数据'!B14*(1+B6) | D8: Tesla 市值 × (1+溢价)
A9: 合并后总股本（百万股） | B9: ='换股比例'!J35 | D9: SpaceX 现有 + 新发 − Tesla 持有的 SpaceX 股份
A10: Tesla 原股东持股 | B10: ='换股比例'!K35 | D10: 新发股份 / 合并后总股本
A11: SpaceX 原股东持股 | B11: ='换股比例'!L35 | D11: (SpaceX 现有 − Tesla 持有) / 合并后总股本
A12: 马斯克合并后经济权益 | B12: ='换股比例'!M35 | D12: (马斯克 SpaceX + 马斯克 Tesla×换股比例) / 合并后总股本
A13: 马斯克合并后投票权（估算） | B13: ='换股比例'!O35 | D13: 假设新发股份为 Class A（1票/股），Class B 10票/股
A15: 二、LTM 备考利润表（$M）
A16: 项目 | B16: SpaceX LTM | C16: Tesla LTM | D16: 备考调整 | E16: 备考合计 | F16: 备注
A18: 营业收入 | B18: ='SpaceX数据'!G5 | C18: ='Tesla数据'!G5 | D18: =-B88 | E18: =SUM(B18:D18) | F18: 抵消 Tesla 对 SpaceX/xAI 的关联销售收入（LTM）
A19: 营业成本 | B19: ='SpaceX数据'!G6 | C19: ='Tesla数据'!G6 | D19: =-B91 | E19: =SUM(B19:D19) | F19: 抵消对应成本；未实现利润留在 PP&E，按交付额抵消资本开支
A20: 毛利 | B20: =B18-B19 | C20: =C18-C19 | D20: =D18-D19 | E20: =SUM(B20:D20) | F20: = 收入 − 成本
A21: 研发费用 | B21: ='SpaceX数据'!G8 | C21: ='Tesla数据'!G8 | D21: 0 | E21: =SUM(B21:D21) | F21: 无抵消
A22: 销售及管理费用 | B22: ='SpaceX数据'!G9 | C22: ='Tesla数据'!G9 | D22: 0 | E22: =SUM(B22:D22) | F22: 无抵消
A23: 重组及减值 | B23: ='SpaceX数据'!G10+'SpaceX数据'!G11 | C23: ='Tesla数据'!G10 | D23: 0 | E23: =SUM(B23:D23) | F23: SpaceX：重组+减值；Tesla：重组及其他
A24: 总运营费用 | B24: =SUM(B21:B23) | C24: =SUM(C21:C23) | D24: =SUM(D21:D23) | E24: =SUM(B24:D24) | F24: = 研发 + 销售管理 + 重组减值
A25: 经营利润 | B25: =B20-B24 | C25: =C20-C24 | D25: =D20-D24 | E25: =SUM(B25:D25) | F25: = 毛利 − 总运营费用
A26: 利息费用 | B26: ='SpaceX数据'!G14 | C26: ='Tesla数据'!G14 | D26: 0 | E26: =SUM(B26:D26) | F26: SpaceX 含 Valor 关联方租赁利息
A27: 利息收入 | B27: ='SpaceX数据'!G15 | C27: ='Tesla数据'!G13 | D27: 0 | E27: =SUM(B27:D27) | F27: —
A28: 其他收益/(费用)净额 | B28: ='SpaceX数据'!G16 | C28: ='Tesla数据'!G15 | D28: =-863 | E28: =SUM(B28:D28) | F28: 剔除 Tesla 对 SpaceX 股权投资的 863 公允价值收益
A29: 税前利润 | B29: =B25-B26+B27+B28 | C29: =C25-C26+C27+C28 | D29: =D25-D26+D27+D28 | E29: =SUM(B29:D29) | F29: = 经营利润 − 利息费用 + 利息收入 + 其他
A30: 所得税费用 | B30: ='SpaceX数据'!G18 | C30: ='Tesla数据'!G17 | D30: =D29*$B$93 | E30: =SUM(B30:D30) | F30: 按 21% 对调整项计税；两家实际税费加总
A31: 净利润（含少数股东） | B31: =B29-B30 | C31: =C29-C30 | D31: =D29-D30 | E31: =SUM(B31:D31) | F31: = 税前利润 − 所得税
A32: 归母净利润 | B32: ='SpaceX数据'!G20 | C32: ='Tesla数据'!G20 | D32: =D31 | E32: =E31-'Tesla数据'!G19 | F32: SpaceX 无少数股东；Tesla 已扣少数股东损益
A33: 调整后 EBITDA | B33: ='SpaceX数据'!G31 | C33: ='Tesla数据'!G31 | D33: =D20 | E33: =SUM(B33:D33) | F33: 抵消未实现利润；不含 863 非现金收益（两家口径均已剔除）
A34: 经营活动现金流 | B34: ='SpaceX数据'!G21 | C34: ='Tesla数据'!G21 | D34: =-B94 | E34: =SUM(B34:D34) | F34: 抵消内部采购的现金流入/流出
A35: 资本开支 | B35: ='SpaceX数据'!G22 | C35: ='Tesla数据'!G22 | D35: =-B94 | E35: =SUM(B35:D35) | F35: 抵消 SpaceX 向 Tesla 采购的资本开支
A36: 自由现金流 | B36: =B34-B35 | C36: =C34-C35 | D36: =D34-D35 | E36: =SUM(B36:D36) | F36: = 经营现金流 − 资本开支
A39: 三、备考收入结构（按业务；LTM 与 FY2025）
A40: 业务 | B40: LTM 收入 | C40: 占比 | D40: FY2025 收入 | E40: 占比 | F40: 说明
A41: Tesla 汽车（整车、积分、租赁） | B41: ='Tesla数据'!G42 | C41: =B41/$B$48 | D41: ='Tesla数据'!B42 | E41: =D41/$D$48 | F41: 含 Model 3/Y、其他车型、监管积分、租赁
A42: Tesla 服务及其他 | B42: ='Tesla数据'!G43 | C42: =B42/$B$48 | D42: ='Tesla数据'!B43 | E42: =D42/$D$48 | F42: 超充、维修、保险、二手车等
A43: Tesla 能源 | B43: ='Tesla数据'!G37 | C43: =B43/$B$48 | D43: ='Tesla数据'!B37 | E43: =D43/$D$48 | F43: Megapack、Powerwall、太阳能
A44: SpaceX Space | B44: ='SpaceX数据'!G36 | C44: =B44/$B$48 | D44: ='SpaceX数据'!B36 | E44: =D44/$D$48 | F44: 发射服务、载人/货运、Starship 研发
A45: SpaceX Connectivity | B45: ='SpaceX数据'!G37 | C45: =B45/$B$48 | D45: ='SpaceX数据'!B37 | E45: =D45/$D$48 | F45: Starlink 消费、企业/政府
A46: SpaceX SI | B46: ='SpaceX数据'!G38 | C46: =B46/$B$48 | D46: ='SpaceX数据'!B38 | E46: =D46/$D$48 | F46: Grok、云/算力、广告、Cursor
A47: 内部抵消 | B47: =-B88 | C47: =B47/$B$48 | D47: =-B85 | E47: =D47/$D$48 | F47: Tesla 向 SpaceX/xAI 的关联销售
A48: 合计 | B48: =SUM(B41:B47) | C48: =SUM(C41:C47) | D48: =SUM(D41:D47) | E48: =SUM(E41:E47) | F48: 备考合并收入
A51: 四、备考利润结构（LTM 贡献利润；Tesla 总部费用按毛利占比分摊 — 假设）
A52: 业务 | B52: 贡献利润 | C52: 占合计 | D52: LTM 收入 | E52: 利润率 | F52: 说明
A53: Tesla 汽车（整车、积分、租赁） | B53: =B62-B61*B62/B60 | C53: =B53/$B$59 | D53: =B41 | E53: =IF(D53=0,"",B53/D53) | F53: 汽车毛利 − 分摊总部费用
A54: Tesla 服务及其他 | B54: =B63-B61*B63/B60 | C54: =B54/$B$59 | D54: =B42 | E54: =IF(D54=0,"",B54/D54) | F54: 服务毛利 − 分摊总部费用
A55: Tesla 能源 | B55: =B64-B61*B64/B60-B65 | C55: =B55/$B$59 | D55: =B43 | E55: =IF(D55=0,"",B55/D55) | F55: 能源毛利 − 分摊总部费用 − 内部未实现利润
A56: SpaceX Space | B56: ='SpaceX数据'!G44 | C56: =B56/$B$59 | D56: =B44 | E56: =IF(D56=0,"",B56/D56) | F56: 披露的分部经营利润
A57: SpaceX Connectivity | B57: ='SpaceX数据'!G45 | C57: =B57/$B$59 | D57: =B45 | E57: =IF(D57=0,"",B57/D57) | F57: 披露的分部经营利润
A58: SpaceX SI | B58: ='SpaceX数据'!G46 | C58: =B58/$B$59 | D58: =B46 | E58: =IF(D58=0,"",B58/D58) | F58: 披露的分部经营利润
A59: 合计 | B59: =SUM(B53:B58) | C59: =SUM(C53:C58) | D59: =SUM(D53:D58) | E59: =B59/D59 | F59: 应等于备考经营利润 E25
A60: Tesla 毛利合计（LTM） | B60: ='Tesla数据'!G7 | F60: 用于分摊总部费用的分母
A61: Tesla 运营费用合计（LTM） | B61: ='Tesla数据'!G11 | F61: 研发+销售管理+重组
A62: Tesla 汽车毛利（LTM） | B62: ='Tesla数据'!G44
A63: Tesla 服务毛利（LTM） | B63: ='Tesla数据'!G45
A64: Tesla 能源毛利（LTM） | B64: ='Tesla数据'!G46
A65: 内部未实现利润（LTM） | B65: =B92 | F65: 从能源贡献利润中扣除
A68: 五、关联交易与交叉持股：披露、金额与合并处理
A69: 交易/余额 | B69: 关联方 | C69: 期间 | D69: 金额($M) | E69: 备考处理（含来源）
A70: Tesla 向 SpaceX 销售 Megapack（收入） | B70: SpaceX | C70: 9M2026 | D70: 626 | E70: 全额抵消收入；对应成本按 76.4% 抵消（来源：Tesla 2026Q3 10-Q Note 13）
A71: Tesla 向 SpaceX 销售 Megapack（成本） | B71: SpaceX | C71: 9M2026 | D71: 478 | E71: 抵消成本；未实现利润留在 SpaceX 的 PP&E（来源：同上）
A72: Tesla 对 SpaceX 应收账款 | B72: SpaceX | C72: 2026-09-30 | D72: 729 | E72: 与 SpaceX 应付对冲；差额待核（含未交付 Megapack）（来源：同上）
A73: Tesla 对 SpaceX 递延收入 | B73: SpaceX | C73: 2026-09-30 | D73: 648 | E73: 合并层面抵消未实现收入（来源：同上）
A74: SpaceX 向 Tesla 采购 Megapack | B74: Tesla | C74: FY2025 | D74: 506 | E74: 资本开支，合并抵消（来源：SpaceX 招股书 Note 18）
A75: SpaceX 向 Tesla 采购 Cybertruck | B75: Tesla | C75: FY2025 | D75: 131 | E75: 资本开支，合并抵消（来源：同上）
A76: SpaceX 向 Tesla 采购（9M2026） | B76: Tesla | C76: 9M2026 | D76: 480 | E76: 资本开支/现金流抵消（来源：SpaceX 2026Q3 公告现金流量表）
A77: Tesla 向 xAI 销售 Megapack | B77: xAI（现属 SpaceX） | C77: FY2025 | D77: 430 | E77: 合并范围内抵消（xAI 于 2026-02-02 并入 SpaceX）（来源：Tesla 2025 10-K Note 15）
A78: Tesla 持有 SpaceX 股权 | B78: SpaceX | C78: 2026-09-30 | D78: 2865 | E78: 按交叉持股/库存股抵消；公允价值变动不再入损益（来源：Tesla 2026Q3 10-Q Note 2/13）
A79: SpaceX 对 Valor 设备租赁负债 | B79: Valor（董事关联） | C79: 2026-09-30 | D79: 12897 | E79: 不抵消；作为有息负债，披露关联方性质（来源：SpaceX 2026Q3 公告；Q2 10-Q Note 17）
A80: 马斯克关联方交易（安保、广告等） | B80: Musk 关联 | C80: FY2025 | D80: 8.1 | E80: 不抵消；治理审查事项（来源：Tesla 2026 委托书）
A83: 六、备考关键假设与购买会计示意
A84: 项目 | B84: 数值 | C84: 单位 | D84: 说明
A85: FY2025 Tesla 关联方收入（披露加总） | B85: 573.4 | C85: $M | D85: xAI 430.1 + SpaceX 143.3；来自 2026 委托书
A86: 2025 前三季度关联方收入（假设） | B86: 323 | C86: $M | D86: 假设 = FY2025 × 56.3%，仅用于推导 Q4
A87: 2025Q4 关联方收入（推导） | B87: =B85-B86 | C87: $M | D87: = FY2025 − 前三季度
A88: LTM 关联方收入 | B88: =B87+B89 | C88: $M | D88: = Q4-25 + 9M2026；用于收入与利润抵消
A89: 9M2026 关联方收入（披露） | B89: 626 | C89: $M | D89: Tesla 2026Q3 10-Q Note 13
A90: 关联成本率 | B90: =478/626 | C90: % | D90: = 9M2026 关联成本 / 关联收入
A91: LTM 关联成本 | B91: =B88*B90 | C91: $M | D91: = 关联收入 × 成本率
A92: LTM 未实现利润 | B92: =B88-B91 | C92: $M | D92: = 关联收入 − 关联成本；在合并层面抵消
A93: 所得税率（调整项） | B93: 0.21 | C93: % | D93: 假设：美国联邦法定税率 21%
A94: 内部现金流/资本开支抵消 | B94: 480 | C94: $M | D94: SpaceX 9M2026 向 Tesla 采购额；用于现金流抵消
A95: 可辨认无形资产增值（假设） | B95: 30000 | C95: $M | D95: 购买会计示意；非披露事实
A96: 摊销年限（假设） | B96: 10 | C96: 年 | D96: 直线法；年增量摊销 3,000
A97: 递延所得税负债 | B97: =B95*B93 | C97: $M | D97: = 增值 × 税率
A98: 交易费用率（假设） | B98: 0.005 | C98: % | D98: 对价的 0.5%
A99: 交易费用 | B99: =B8*B98 | C99: $M | D99: 一次性费用，未计入备考利润
A100: 备考商誉（示意） | B100: =B8-('Tesla数据'!F29+B95-B97) | C100: $M | D100: = 对价 − (Tesla 账面权益 + 增值 − 递延税负债)
A101: 年增量摊销 | B101: =B95/B96 | C101: $M | D101: 税前；税后 2,370
A102: 协同效应（未计入） | B102: 0 | C102: $M | D102: 保守处理；未计入收入或成本协同
A105: 七、备考资产负债表关键项（2026-09-30 账面，$M）
A106: 项目 | B106: SpaceX | C106: Tesla | D106: 调整 | E106: 备考 | F106: 说明
A107: 现金及短期投资 | B107: ='SpaceX数据'!F26 | C107: ='Tesla数据'!F26 | D107: 0 | E107: =SUM(B107:D107) | F107: = 两家账面加总
A108: 有息负债（含融资租赁） | B108: ='SpaceX数据'!F27 | C108: ='Tesla数据'!F27 | D108: 0 | E108: =SUM(B108:D108) | F108: = 两家账面加总；未做再融资调整
A109: 净债务/(净现金) | B109: =B108-B107 | C109: =C108-C107 | D109: =D108-D107 | E109: =SUM(B109:D109) | F109: = 有息负债 − 现金；负数为净现金
A110: 股东权益 | B110: ='SpaceX数据'!F29 | C110: ='Tesla数据'!F29 | D110: =-'市场数据'!B40 | E110: =SUM(B110:D110) | F110: 抵消 Tesla 持有的 SpaceX 股权（公允价值 2,865）
A111: 少数股东权益 | B111: 0 | C111: ='Tesla数据'!F30 | D111: 0 | E111: =SUM(B111:D111) | F111: Tesla 子公司少数股东
A112: 可转换优先股 | B112: ='SpaceX数据'!F30 | C112: 0 | D112: 0 | E112: =SUM(B112:D112) | F112: SpaceX IPO 时优先股已转普通股
A113: 备考商誉（示意） | B113: 0 | C113: 0 | D113: =B100 | E113: =SUM(B113:D113) | F113: 仅示意；不含其他无形资产与递延税影响
...

Sheet 换股比例
A1: 换股比例：三种以上定价方法与双方持股
A2: 基准：SpaceX 发行 Class A 新股收购 Tesla；换股比例 = Tesla 每股隐含价值 × (1+溢价) ÷ SpaceX 每股价值
A4: 一、市场输入（黄色为可改假设）
A5: SPCX 收盘价（2026-10-21） | B5: ='市场数据'!B5 | C5: 市场数据
A6: TSLA 收盘价（2026-10-21） | B6: ='市场数据'!B6 | C6: 市场数据
A7: SPCX 收盘价（2026-10-19，宣布前） | B7: ='市场数据'!B7 | C7: 市场数据
A8: TSLA 收盘价（2026-10-19，宣布前） | B8: ='市场数据'!B8 | C8: 市场数据
A9: SPCX 30日 VWAP | B9: ='市场数据'!B9 | C9: 2026-09-10 至 10-21
A10: TSLA 30日 VWAP | B10: ='市场数据'!B10 | C10: 2026-09-10 至 10-21
A11: SPCX 在外股本（百万股） | B11: ='市场数据'!B11 | C11: 8,240 A + 5,339 B
A12: TSLA 在外股本（百万股） | B12: ='市场数据'!B12 | C12: 3,952.758
A13: SPCX 净债务/(净现金)（$M） | B13: ='市场数据'!B19 | C13: 负数为净现金
A14: TSLA 净债务/(净现金)（$M） | B14: ='市场数据'!B20 | C14: 负数为净现金
A15: SPCX LTM 营业收入（$M） | B15: ='市场数据'!B23 | C15: 2025Q4-2026Q3
A16: TSLA LTM 营业收入（$M） | B16: ='市场数据'!B24 | C16: 2025Q4-2026Q3
A17: SPCX LTM 调整后 EBITDA（$M） | B17: ='市场数据'!B25 | C17: 公司口径
A18: TSLA LTM 调整后 EBITDA（$M） | B18: ='市场数据'!B26 | C18: 公司口径
A19: 换股溢价率（假设） | B19: 0.2 | C19: 基准情形 20%；可改
A20: SPCX LTM 收入倍数（假设） | B20: 50 | C20: 方法 D
A21: Tesla LTM 收入倍数（假设） | B21: 12 | C21: 方法 D
A22: SPCX LTM Adj. EBITDA 倍数（假设） | B22: 110 | C22: 方法 E
A23: Tesla LTM Adj. EBITDA 倍数（假设） | B23: 70 | C23: 方法 E
A24: Tesla 持有 SPCX 股数（假设） | B24: 14.8 | C24: $2.0bn / $135 IPO价；披露 <1%
A25: 马斯克持有 SPCX 股数 | B25: ='市场数据'!B35 | C25: 招股书 2026-05-01
A26: 马斯克持有 TSLA 股数 | B26: ='市场数据'!B36 | C26: 委托书 2026-09-30
A27: 马斯克 SPCX Class A 股数 | B27: ='市场数据'!B45 | C27: 招股书
A28: 马斯克 SPCX Class B 股数（推算） | B28: ='市场数据'!B46 | C28: 5,569.053 − 350.0 期权
A29: SPCX Class A 总股数 | B29: ='市场数据'!B43 | C29: Q3 资产负债表
A30: SPCX Class B 总股数 | B30: ='市场数据'!B44 | C30: Q3 资产负债表
A31: 马斯克 SPCX 披露投票权 | B31: ='市场数据'!B48 | C31: 招股书 84.4%
A33: 二、五种定价方法与换股比例（基准溢价率 = B19）
A34: 方法 | B34: 定价基础/日期 | C34: SPCX 隐含股权价值($M) | D34: Tesla 隐含股权价值($M) | E34: SPCX 隐含每股($) | F34: Tesla 隐含每股($) | G34: 换股比例(SPCX/TSLA) | H34: 溢价后换股比例 | I34: 新发SPCX股数(百万) | J34: 合并后总股本(百万) | K34: Tesla原股东占比 | L34: SpaceX原股东占比 | M34: Musk合并后占比 | N34: 隐含合并股权价值($M) | O34: Musk投票权(估算) | P34: 备注
A35: A 市值法（10/21收盘） | B35: 2026-10-21 收盘价 × 在外股本 | C35: =B5*B11 | D35: =B6*B12 | E35: =C35/$B$11 | F35: =D35/$B$12 | G35: =F35/E35 | H35: =G35*(1+$B$19) | I35: =H35*$B$12 | J35: =$B$11-$B$24+I35 | K35: =I35/J35 | L35: =($B$11-$B$24)/J35 | M35: =($B$25+$B$26*H35)/J35 | N35: =C35+D35*(1+$B$19) | O35: =($B$27+$B$28*10+$B$26*H35)/($B$29-$B$24+$B$30*10+I35) | P35: 已反映合并消息：SPCX +7.8%，TSLA +3.4%
A36: B 市值法（10/19收盘，宣布前） | B36: 2026-10-19 收盘价 × 在外股本 | C36: =B7*B11 | D36: =B8*B12 | E36: =C36/$B$11 | F36: =D36/$B$12 | G36: =F36/E36 | H36: =G36*(1+$B$19) | I36: =H36*$B$12 | J36: =$B$11-$B$24+I36 | K36: =I36/J36 | L36: =($B$11-$B$24)/J36 | M36: =($B$25+$B$26*H36)/J36 | N36: =C36+D36*(1+$B$19) | O36: =($B$27+$B$28*10+$B$26*H36)/($B$29-$B$24+$B$30*10+I36) | P36: 最后一个未被合并消息影响的交易日
A37: C 30日成交量加权均价 | B37: 2026-09-10 至 10-21，收盘价×成交量 | C37: =B9*B11 | D37: =B10*B12 | E37: =C37/$B$11 | F37: =D37/$B$12 | G37: =F37/E37 | H37: =G37*(1+$B$19) | I37: =H37*$B$12 | J37: =$B$11-$B$24+I37 | K37: =I37/J37 | L37: =($B$11-$B$24)/J37 | M37: =($B$25+$B$26*H37)/J37 | N37: =C37+D37*(1+$B$19) | O37: =($B$27+$B$28*10+$B$26*H37)/($B$29-$B$24+$B$30*10+I37) | P37: 近似 VWAP，不含 10/22 盘中
A38: D LTM 收入倍数法 | B38: SPCX 50x / Tesla 12x LTM 收入（假设） | C38: =B20*B15-B13 | D38: =B21*B16-B14 | E38: =C38/$B$11 | F38: =D38/$B$12 | G38: =F38/E38 | H38: =G38*(1+$B$19) | I38: =H38*$B$12 | J38: =$B$11-$B$24+I38 | K38: =I38/J38 | L38: =($B$11-$B$24)/J38 | M38: =($B$25+$B$26*H38)/J38 | N38: =C38+D38*(1+$B$19) | O38: =($B$27+$B$28*10+$B$26*H38)/($B$29-$B$24+$B$30*10+I38) | P38: 倍数低于当前市场隐含倍数，反映执行风险
A39: E LTM 调整后EBITDA倍数法 | B39: SPCX 110x / Tesla 70x LTM Adj. EBITDA（假设） | C39: =B22*B17-B13 | D39: =B23*B18-B14 | E39: =C39/$B$11 | F39: =D39/$B$12 | G39: =F39/E39 | H39: =G39*(1+$B$19) | I39: =H39*$B$12 | J39: =$B$11-$B$24+I39 | K39: =I39/J39 | L39: =($B$11-$B$24)/J39 | M39: =($B$25+$B$26*H39)/J39 | N39: =C39+D39*(1+$B$19) | O39: =($B$27+$B$28*10+$B$26*H39)/($B$29-$B$24+$B$30*10+I39) | P39: 高倍数下绝对值对假设敏感
A42: 三、基准情形与持股桥（基准 = 方法 A + 20% 溢价）
A43: 基准定价方法 | B43: A 市值法（2026-10-21 收盘） | C43: —
A44: 基准溢价率 | B44: =B19 | C44: 可改 B19
A45: 基准换股比例（SPCX 股 / TSLA 股） | B45: =H35 | C45: 每 1 股 Tesla 换得
A46: 新发 SPCX 股数（百万股） | B46: =I35 | C46: 换股比例 × Tesla 股本
A47: 合并后总股本（百万股） | B47: =J35 | C47: SpaceX 现有 − Tesla 持有 + 新发
A48: Tesla 原股东持股 | B48: =K35 | C48: 新发 / 合并后总股本
A49: SpaceX 原股东持股 | B49: =L35 | C49: (现有 − Tesla 持有) / 合并后
A50: 马斯克合并后经济权益 | B50: =M35 | C50: (SpaceX 持股 + Tesla 持股×换股比例) / 合并后
A51: 马斯克合并前 SpaceX 持股 | B51: =B25/B11 | C51: 按 9/30 股本
A52: 马斯克合并前 Tesla 持股 | B52: =B26/B12 | C52: 按 10-Q 股本
A53: 马斯克合并前 look-through 经济权益 | B53: ='市场数据'!B42 | C53: 按两家市值加权
A54: 马斯克合并后投票权（估算） | B54: =O35 | C54: Class A 1票、Class B 10票
A55: 马斯克合并前投票权（计算） | B55: ='市场数据'!B47 | C55: 计算值；披露 84.4%
A56: 马斯克 SpaceX 披露投票权 | B56: =B31 | C56: 招股书
A57: 每 1 股 Tesla 可换得 SPCX 股数 | B57: =H35 | C57: = 基准换股比例
A58: 每 1 股 SPCX 可换得 Tesla 股数 | B58: =1/H35 | C58: 反向换股（参考）
A59: 100 股 Tesla 可换得 SPCX 股数 | B59: =100*H35 | C59: 示例
A62: 四、方法说明与限制
A63: 1. 方法 A/B/C 直接以市场交易价格或成交量加权均价作为每股价值，属于“市场怎么定价就怎么换”的思路；方法 D/E 以倍数反推股权价值，属于“基本面值多少”的思路。三种以上方法并列，是为了让董事会看到换股比例对定价基准的敏感性，而不是选一个“正确”的答案。
A64: 2. 换股比例定义为 SpaceX 新发 Class A 股数 / Tesla 现有股数。若改为 Tesla 收购 SpaceX，则比例取倒数、双方持股互换；由于 Tesla 持有 <1% SpaceX 股权，反向交易还需先处理该交叉持股，经济结果近似。
A65: 3. 股本口径为已发行在外普通股（含未归属限制性股票），不含未行权期权与可转债。若按完全摊薄口径，SpaceX 约 14.1bn 股、Tesla 约 4.25bn 股（假设），换股比例与持股结构会有 1–3 个百分点的差异。
A66: 4. Tesla 持有的 SpaceX 股份在合并时按交叉持股/库存股抵消，因此 SpaceX 原股东持股分母减去了 14.8 百万股；这使 SpaceX 原股东持股略高于不做抵消的情形。
A67: 5. 马斯克投票权按“Class B 每股 10 票、新发股份为 Class A”估算。计算得到的合并前投票权约 86.1%，高于招股书披露的 84.4%，差异主要来自期权/限制性股票是否计入；合并后投票权约 75%，仍足以控制股东大会普通决议。
A68: 6. 上述比例为财务测算，不构成报价或投资建议；实际换股比例还需考虑锁定期、异议股东评估权、税务、监管审批与特别委员会谈判。

Sheet 敏感性
A1: 敏感性：溢价率 × 定价方法（二维表）
A2: 行 = 换股溢价率；列 = 五种定价方法。所有结果由“换股比例”页的基准比例与市场输入驱动；改 B19 或价格/股本，本页自动更新
A4: 表1：换股比例（每 1 股 Tesla 换得的 SpaceX 股数）
A5: 溢价率 | B5: A 市值法(10/21) | C5: B 市值法(10/19) | D5: C 30日VWAP | E5: D 收入倍数 | F5: E EBITDA倍数 | G5: 说明
A6: 0 | B6: ='换股比例'!$G$35*(1+$A6) | C6: ='换股比例'!$G$36*(1+$A6) | D6: ='换股比例'!$G$37*(1+$A6) | E6: ='换股比例'!$G$38*(1+$A6) | F6: ='换股比例'!$G$39*(1+$A6)
A7: 0.05 | B7: ='换股比例'!$G$35*(1+$A7) | C7: ='换股比例'!$G$36*(1+$A7) | D7: ='换股比例'!$G$37*(1+$A7) | E7: ='换股比例'!$G$38*(1+$A7) | F7: ='换股比例'!$G$39*(1+$A7)
A8: 0.1 | B8: ='换股比例'!$G$35*(1+$A8) | C8: ='换股比例'!$G$36*(1+$A8) | D8: ='换股比例'!$G$37*(1+$A8) | E8: ='换股比例'!$G$38*(1+$A8) | F8: ='换股比例'!$G$39*(1+$A8)
A9: 0.15 | B9: ='换股比例'!$G$35*(1+$A9) | C9: ='换股比例'!$G$36*(1+$A9) | D9: ='换股比例'!$G$37*(1+$A9) | E9: ='换股比例'!$G$38*(1+$A9) | F9: ='换股比例'!$G$39*(1+$A9)
A10: 0.2 | B10: ='换股比例'!$G$35*(1+$A10) | C10: ='换股比例'!$G$36*(1+$A10) | D10: ='换股比例'!$G$37*(1+$A10) | E10: ='换股比例'!$G$38*(1+$A10) | F10: ='换股比例'!$G$39*(1+$A10) | G10: 基准情形：20% 溢价
A11: 0.25 | B11: ='换股比例'!$G$35*(1+$A11) | C11: ='换股比例'!$G$36*(1+$A11) | D11: ='换股比例'!$G$37*(1+$A11) | E11: ='换股比例'!$G$38*(1+$A11) | F11: ='换股比例'!$G$39*(1+$A11)
A12: 0.3 | B12: ='换股比例'!$G$35*(1+$A12) | C12: ='换股比例'!$G$36*(1+$A12) | D12: ='换股比例'!$G$37*(1+$A12) | E12: ='换股比例'!$G$38*(1+$A12) | F12: ='换股比例'!$G$39*(1+$A12)
A13: 0.35 | B13: ='换股比例'!$G$35*(1+$A13) | C13: ='换股比例'!$G$36*(1+$A13) | D13: ='换股比例'!$G$37*(1+$A13) | E13: ='换股比例'!$G$38*(1+$A13) | F13: ='换股比例'!$G$39*(1+$A13)
A14: 0.4 | B14: ='换股比例'!$G$35*(1+$A14) | C14: ='换股比例'!$G$36*(1+$A14) | D14: ='换股比例'!$G$37*(1+$A14) | E14: ='换股比例'!$G$38*(1+$A14) | F14: ='换股比例'!$G$39*(1+$A14)
A16: 表2：Tesla 原股东在合并后公司的持股比例
A17: 溢价率 | B17: A 市值法(10/21) | C17: B 市值法(10/19) | D17: C 30日VWAP | E17: D 收入倍数 | F17: E EBITDA倍数 | G17: 说明
A19: =A6 | B19: =('换股比例'!$B$12*B6)/(('换股比例'!$B$11-'换股比例'!$B$24)+'换股比例'!$B$12*B6) | C19: =('换股比例'!$B$12*C6)/(('换股比例'!$B$11-'换股比例'!$B$24)+'换股比例'!$B$12*C6) | D19: =('换股比例'!$B$12*D6)/(('换股比例'!$B$11-'换股比例'!$B$24)+'换股比例'!$B$12*D6) | E19: =('换股比例'!$B$12*E6)/(('换股比例'!$B$11-'换股比例'!$B$24)+'换股比例'!$B$12*E6) | F19: =('换股比例'!$B$12*F6)/(('换股比例'!$B$11-'换股比例'!$B$24)+'换股比例'!$B$12*F6) | G19: = 新发股数 / 合并后总股本
A20: =A7 | B20: =('换股比例'!$B$12*B7)/(('换股比例'!$B$11-'换股比例'!$B$24)+'换股比例'!$B$12*B7) | C20: =('换股比例'!$B$12*C7)/(('换股比例'!$B$11-'换股比例'!$B$24)+'换股比例'!$B$12*C7) | D20: =('换股比例'!$B$12*D7)/(('换股比例'!$B$11-'换股比例'!$B$24)+'换股比例'!$B$12*D7) | E20: =('换股比例'!$B$12*E7)/(('换股比例'!$B$11-'换股比例'!$B$24)+'换股比例'!$B$12*E7) | F20: =('换股比例'!$B$12*F7)/(('换股比例'!$B$11-'换股比例'!$B$24)+'换股比例'!$B$12*F7)
A21: =A8 | B21: =('换股比例'!$B$12*B8)/(('换股比例'!$B$11-'换股比例'!$B$24)+'换股比例'!$B$12*B8) | C21: =('换股比例'!$B$12*C8)/(('换股比例'!$B$11-'换股比例'!$B$24)+'换股比例'!$B$12*C8) | D21: =('换股比例'!$B$12*D8)/(('换股比例'!$B$11-'换股比例'!$B$24)+'换股比例'!$B$12*D8) | E21: =('换股比例'!$B$12*E8)/(('换股比例'!$B$11-'换股比例'!$B$24)+'换股比例'!$B$12*E8) | F21: =('换股比例'!$B$12*F8)/(('换股比例'!$B$11-'换股比例'!$B$24)+'换股比例'!$B$12*F8)
A22: =A9 | B22: =('换股比例'!$B$12*B9)/(('换股比例'!$B$11-'换股比例'!$B$24)+'换股比例'!$B$12*B9) | C22: =('换股比例'!$B$12*C9)/(('换股比例'!$B$11-'换股比例'!$B$24)+'换股比例'!$B$12*C9) | D22: =('换股比例'!$B$12*D9)/(('换股比例'!$B$11-'换股比例'!$B$24)+'换股比例'!$B$12*D9) | E22: =('换股比例'!$B$12*E9)/(('换股比例'!$B$11-'换股比例'!$B$24)+'换股比例'!$B$12*E9) | F22: =('换股比例'!$B$12*F9)/(('换股比例'!$B$11-'换股比例'!$B$24)+'换股比例'!$B$12*F9)
A23: =A10 | B23: =('换股比例'!$B$12*B10)/(('换股比例'!$B$11-'换股比例'!$B$24)+'换股比例'!$B$12*B10) | C23: =('换股比例'!$B$12*C10)/(('换股比例'!$B$11-'换股比例'!$B$24)+'换股比例'!$B$12*C10) | D23: =('换股比例'!$B$12*D10)/(('换股比例'!$B$11-'换股比例'!$B$24)+'换股比例'!$B$12*D10) | E23: =('换股比例'!$B$12*E10)/(('换股比例'!$B$11-'换股比例'!$B$24)+'换股比例'!$B$12*E10) | F23: =('换股比例'!$B$12*F10)/(('换股比例'!$B$11-'换股比例'!$B$24)+'换股比例'!$B$12*F10)
A24: =A11 | B24: =('换股比例'!$B$12*B11)/(('换股比例'!$B$11-'换股比例'!$B$24)+'换股比例'!$B$12*B11) | C24: =('换股比例'!$B$12*C11)/(('换股比例'!$B$11-'换股比例'!$B$24)+'换股比例'!$B$12*C11) | D24: =('换股比例'!$B$12*D11)/(('换股比例'!$B$11-'换股比例'!$B$24)+'换股比例'!$B$12*D11) | E24: =('换股比例'!$B$12*E11)/(('换股比例'!$B$11-'换股比例'!$B$24)+'换股比例'!$B$12*E11) | F24: =('换股比例'!$B$12*F11)/(('换股比例'!$B$11-'换股比例'!$B$24)+'换股比例'!$B$12*F11)
A25: =A12 | B25: =('换股比例'!$B$12*B12)/(('换股比例'!$B$11-'换股比例'!$B$24)+'换股比例'!$B$12*B12) | C25: =('换股比例'!$B$12*C12)/(('换股比例'!$B$11-'换股比例'!$B$24)+'换股比例'!$B$12*C12) | D25: =('换股比例'!$B$12*D12)/(('换股比例'!$B$11-'换股比例'!$B$24)+'换股比例'!$B$12*D12) | E25: =('换股比例'!$B$12*E12)/(('换股比例'!$B$11-'换股比例'!$B$24)+'换股比例'!$B$12*E12) | F25: =('换股比例'!$B$12*F12)/(('换股比例'!$B$11-'换股比例'!$B$24)+'换股比例'!$B$12*F12)
A26: =A13 | B26: =('换股比例'!$B$12*B13)/(('换股比例'!$B$11-'换股比例'!$B$24)+'换股比例'!$B$12*B13) | C26: =('换股比例'!$B$12*C13)/(('换股比例'!$B$11-'换股比例'!$B$24)+'换股比例'!$B$12*C13) | D26: =('换股比例'!$B$12*D13)/(('换股比例'!$B$11-'换股比例'!$B$24)+'换股比例'!$B$12*D13) | E26: =('换股比例'!$B$12*E13)/(('换股比例'!$B$11-'换股比例'!$B$24)+'换股比例'!$B$12*E13) | F26: =('换股比例'!$B$12*F13)/(('换股比例'!$B$11-'换股比例'!$B$24)+'换股比例'!$B$12*F13)
A27: =A14 | B27: =('换股比例'!$B$12*B14)/(('换股比例'!$B$11-'换股比例'!$B$24)+'换股比例'!$B$12*B14) | C27: =('换股比例'!$B$12*C14)/(('换股比例'!$B$11-'换股比例'!$B$24)+'换股比例'!$B$12*C14) | D27: =('换股比例'!$B$12*D14)/(('换股比例'!$B$11-'换股比例'!$B$24)+'换股比例'!$B$12*D14) | E27: =('换股比例'!$B$12*E14)/(('换股比例'!$B$11-'换股比例'!$B$24)+'换股比例'!$B$12*E14) | F27: =('换股比例'!$B$12*F14)/(('换股比例'!$B$11-'换股比例'!$B$24)+'换股比例'!$B$12*F14)
A29: 表3：马斯克合并后经济权益（含其 Tesla 股份换股）
A30: 溢价率 | B30: A 市值法(10/21) | C30: B 市值法(10/19) | D30: C 30日VWAP | E30: D 收入倍数 | F30: E EBITDA倍数 | G30: 说明
A32: =A6 | B32: =('换股比例'!$B$25+'换股比例'!$B$26*B6)/(('换股比例'!$B$11-'换股比例'!$B$24)+'换股比例'!$B$12*B6) | C32: =('换股比例'!$B$25+'换股比例'!$B$26*C6)/(('换股比例'!$B$11-'换股比例'!$B$24)+'换股比例'!$B$12*C6) | D32: =('换股比例'!$B$25+'换股比例'!$B$26*D6)/(('换股比例'!$B$11-'换股比例'!$B$24)+'换股比例'!$B$12*D6) | E32: =('换股比例'!$B$25+'换股比例'!$B$26*E6)/(('换股比例'!$B$11-'换股比例'!$B$24)+'换股比例'!$B$12*E6) | F32: =('换股比例'!$B$25+'换股比例'!$B$26*F6)/(('换股比例'!$B$11-'换股比例'!$B$24)+'换股比例'!$B$12*F6) | G32: = (马斯克SpaceX + 马斯克Tesla×比例) / 合并后总股本
A33: =A7 | B33: =('换股比例'!$B$25+'换股比例'!$B$26*B7)/(('换股比例'!$B$11-'换股比例'!$B$24)+'换股比例'!$B$12*B7) | C33: =('换股比例'!$B$25+'换股比例'!$B$26*C7)/(('换股比例'!$B$11-'换股比例'!$B$24)+'换股比例'!$B$12*C7) | D33: =('换股比例'!$B$25+'换股比例'!$B$26*D7)/(('换股比例'!$B$11-'换股比例'!$B$24)+'换股比例'!$B$12*D7) | E33: =('换股比例'!$B$25+'换股比例'!$B$26*E7)/(('换股比例'!$B$11-'换股比例'!$B$24)+'换股比例'!$B$12*E7) | F33: =('换股比例'!$B$25+'换股比例'!$B$26*F7)/(('换股比例'!$B$11-'换股比例'!$B$24)+'换股比例'!$B$12*F7)
A34: =A8 | B34: =('换股比例'!$B$25+'换股比例'!$B$26*B8)/(('换股比例'!$B$11-'换股比例'!$B$24)+'换股比例'!$B$12*B8) | C34: =('换股比例'!$B$25+'换股比例'!$B$26*C8)/(('换股比例'!$B$11-'换股比例'!$B$24)+'换股比例'!$B$12*C8) | D34: =('换股比例'!$B$25+'换股比例'!$B$26*D8)/(('换股比例'!$B$11-'换股比例'!$B$24)+'换股比例'!$B$12*D8) | E34: =('换股比例'!$B$25+'换股比例'!$B$26*E8)/(('换股比例'!$B$11-'换股比例'!$B$24)+'换股比例'!$B$12*E8) | F34: =('换股比例'!$B$25+'换股比例'!$B$26*F8)/(('换股比例'!$B$11-'换股比例'!$B$24)+'换股比例'!$B$12*F8)
A35: =A9 | B35: =('换股比例'!$B$25+'换股比例'!$B$26*B9)/(('换股比例'!$B$11-'换股比例'!$B$24)+'换股比例'!$B$12*B9) | C35: =('换股比例'!$B$25+'换股比例'!$B$26*C9)/(('换股比例'!$B$11-'换股比例'!$B$24)+'换股比例'!$B$12*C9) | D35: =('换股比例'!$B$25+'换股比例'!$B$26*D9)/(('换股比例'!$B$11-'换股比例'!$B$24)+'换股比例'!$B$12*D9) | E35: =('换股比例'!$B$25+'换股比例'!$B$26*E9)/(('换股比例'!$B$11-'换股比例'!$B$24)+'换股比例'!$B$12*E9) | F35: =('换股比例'!$B$25+'换股比例'!$B$26*F9)/(('换股比例'!$B$11-'换股比例'!$B$24)+'换股比例'!$B$12*F9)
A36: =A10 | B36: =('换股比例'!$B$25+'换股比例'!$B$26*B10)/(('换股比例'!$B$11-'换股比例'!$B$24)+'换股比例'!$B$12*B10) | C36: =('换股比例'!$B$25+'换股比例'!$B$26*C10)/(('换股比例'!$B$11-'换股比例'!$B$24)+'换股比例'!$B$12*C10) | D36: =('换股比例'!$B$25+'换股比例'!$B$26*D10)/(('换股比例'!$B$11-'换股比例'!$B$24)+'换股比例'!$B$12*D10) | E36: =('换股比例'!$B$25+'换股比例'!$B$26*E10)/(('换股比例'!$B$11-'换股比例'!$B$24)+'换股比例'!$B$12*E10) | F36: =('换股比例'!$B$25+'换股比例'!$B$26*F10)/(('换股比例'!$B$11-'换股比例'!$B$24)+'换股比例'!$B$12*F10)
A37: =A11 | B37: =('换股比例'!$B$25+'换股比例'!$B$26*B11)/(('换股比例'!$B$11-'换股比例'!$B$24)+'换股比例'!$B$12*B11) | C37: =('换股比例'!$B$25+'换股比例'!$B$26*C11)/(('换股比例'!$B$11-'换股比例'!$B$24)+'换股比例'!$B$12*C11) | D37: =('换股比例'!$B$25+'换股比例'!$B$26*D11)/(('换股比例'!$B$11-'换股比例'!$B$24)+'换股比例'!$B$12*D11) | E37: =('换股比例'!$B$25+'换股比例'!$B$26*E11)/(('换股比例'!$B$11-'换股比例'!$B$24)+'换股比例'!$B$12*E11) | F37: =('换股比例'!$B$25+'换股比例'!$B$26*F11)/(('换股比例'!$B$11-'换股比例'!$B$24)+'换股比例'!$B$12*F11)
A38: =A12 | B38: =('换股比例'!$B$25+'换股比例'!$B$26*B12)/(('换股比例'!$B$11-'换股比例'!$B$24)+'换股比例'!$B$12*B12) | C38: =('换股比例'!$B$25+'换股比例'!$B$26*C12)/(('换股比例'!$B$11-'换股比例'!$B$24)+'换股比例'!$B$12*C12) | D38: =('换股比例'!$B$25+'换股比例'!$B$26*D12)/(('换股比例'!$B$11-'换股比例'!$B$24)+'换股比例'!$B$12*D12) | E38: =('换股比例'!$B$25+'换股比例'!$B$26*E12)/(('换股比例'!$B$11-'换股比例'!$B$24)+'换股比例'!$B$12*E12) | F38: =('换股比例'!$B$25+'换股比例'!$B$26*F12)/(('换股比例'!$B$11-'换股比例'!$B$24)+'换股比例'!$B$12*F12)
A39: =A13 | B39: =('换股比例'!$B$25+'换股比例'!$B$26*B13)/(('换股比例'!$B$11-'换股比例'!$B$24)+'换股比例'!$B$12*B13) | C39: =('换股比例'!$B$25+'换股比例'!$B$26*C13)/(('换股比例'!$B$11-'换股比例'!$B$24)+'换股比例'!$B$12*C13) | D39: =('换股比例'!$B$25+'换股比例'!$B$26*D13)/(('换股比例'!$B$11-'换股比例'!$B$24)+'换股比例'!$B$12*D13) | E39: =('换股比例'!$B$25+'换股比例'!$B$26*E13)/(('换股比例'!$B$11-'换股比例'!$B$24)+'换股比例'!$B$12*E13) | F39: =('换股比例'!$B$25+'换股比例'!$B$26*F13)/(('换股比例'!$B$11-'换股比例'!$B$24)+'换股比例'!$B$12*F13)
A40: =A14 | B40: =('换股比例'!$B$25+'换股比例'!$B$26*B14)/(('换股比例'!$B$11-'换股比例'!$B$24)+'换股比例'!$B$12*B14) | C40: =('换股比例'!$B$25+'换股比例'!$B$26*C14)/(('换股比例'!$B$11-'换股比例'!$B$24)+'换股比例'!$B$12*C14) | D40: =('换股比例'!$B$25+'换股比例'!$B$26*D14)/(('换股比例'!$B$11-'换股比例'!$B$24)+'换股比例'!$B$12*D14) | E40: =('换股比例'!$B$25+'换股比例'!$B$26*E14)/(('换股比例'!$B$11-'换股比例'!$B$24)+'换股比例'!$B$12*E14) | F40: =('换股比例'!$B$25+'换股比例'!$B$26*F14)/(('换股比例'!$B$11-'换股比例'!$B$24)+'换股比例'!$B$12*F14)
A42: 表4：隐含合并股权价值（$M；SpaceX 价值 + Tesla 价值×(1+溢价)）
A43: 溢价率 | B43: A 市值法(10/21) | C43: B 市值法(10/19) | D43: C 30日VWAP | E43: D 收入倍数 | F43: E EBITDA倍数 | G43: 说明
A45: =A6 | B45: ='换股比例'!$C$35+'换股比例'!$D$35*(1+$A45) | C45: ='换股比例'!$C$36+'换股比例'!$D$36*(1+$A45) | D45: ='换股比例'!$C$37+'换股比例'!$D$37*(1+$A45) | E45: ='换股比例'!$C$38+'换股比例'!$D$38*(1+$A45) | F45: ='换股比例'!$C$39+'换股比例'!$D$39*(1+$A45) | G45: 不同方法的绝对值差异较大，但换股比例/持股结构才是交易条款的核心
A46: =A7 | B46: ='换股比例'!$C$35+'换股比例'!$D$35*(1+$A46) | C46: ='换股比例'!$C$36+'换股比例'!$D$36*(1+$A46) | D46: ='换股比例'!$C$37+'换股比例'!$D$37*(1+$A46) | E46: ='换股比例'!$C$38+'换股比例'!$D$38*(1+$A46) | F46: ='换股比例'!$C$39+'换股比例'!$D$39*(1+$A46)
A47: =A8 | B47: ='换股比例'!$C$35+'换股比例'!$D$35*(1+$A47) | C47: ='换股比例'!$C$36+'换股比例'!$D$36*(1+$A47) | D47: ='换股比例'!$C$37+'换股比例'!$D$37*(1+$A47) | E47: ='换股比例'!$C$38+'换股比例'!$D$38*(1+$A47) | F47: ='换股比例'!$C$39+'换股比例'!$D$39*(1+$A47)
A48: =A9 | B48: ='换股比例'!$C$35+'换股比例'!$D$35*(1+$A48) | C48: ='换股比例'!$C$36+'换股比例'!$D$36*(1+$A48) | D48: ='换股比例'!$C$37+'换股比例'!$D$37*(1+$A48) | E48: ='换股比例'!$C$38+'换股比例'!$D$38*(1+$A48) | F48: ='换股比例'!$C$39+'换股比例'!$D$39*(1+$A48)
A49: =A10 | B49: ='换股比例'!$C$35+'换股比例'!$D$35*(1+$A49) | C49: ='换股比例'!$C$36+'换股比例'!$D$36*(1+$A49) | D49: ='换股比例'!$C$37+'换股比例'!$D$37*(1+$A49) | E49: ='换股比例'!$C$38+'换股比例'!$D$38*(1+$A49) | F49: ='换股比例'!$C$39+'换股比例'!$D$39*(1+$A49)
A50: =A11 | B50: ='换股比例'!$C$35+'换股比例'!$D$35*(1+$A50) | C50: ='换股比例'!$C$36+'换股比例'!$D$36*(1+$A50) | D50: ='换股比例'!$C$37+'换股比例'!$D$37*(1+$A50) | E50: ='换股比例'!$C$38+'换股比例'!$D$38*(1+$A50) | F50: ='换股比例'!$C$39+'换股比例'!$D$39*(1+$A50)
A51: =A12 | B51: ='换股比例'!$C$35+'换股比例'!$D$35*(1+$A51) | C51: ='换股比例'!$C$36+'换股比例'!$D$36*(1+$A51) | D51: ='换股比例'!$C$37+'换股比例'!$D$37*(1+$A51) | E51: ='换股比例'!$C$38+'换股比例'!$D$38*(1+$A51) | F51: ='换股比例'!$C$39+'换股比例'!$D$39*(1+$A51)
A52: =A13 | B52: ='换股比例'!$C$35+'换股比例'!$D$35*(1+$A52) | C52: ='换股比例'!$C$36+'换股比例'!$D$36*(1+$A52) | D52: ='换股比例'!$C$37+'换股比例'!$D$37*(1+$A52) | E52: ='换股比例'!$C$38+'换股比例'!$D$38*(1+$A52) | F52: ='换股比例'!$C$39+'换股比例'!$D$39*(1+$A52)
A53: =A14 | B53: ='换股比例'!$C$35+'换股比例'!$D$35*(1+$A53) | C53: ='换股比例'!$C$36+'换股比例'!$D$36*(1+$A53) | D53: ='换股比例'!$C$37+'换股比例'!$D$37*(1+$A53) | E53: ='换股比例'!$C$38+'换股比例'!$D$38*(1+$A53) | F53: ='换股比例'!$C$39+'换股比例'!$D$39*(1+$A53)
A57: 读表说明
A58: 1. 表1 的换股比例 = 该方法下 Tesla 每股价值 × (1+溢价) ÷ SpaceX 每股价值；表2/3 的持股比例由表1 的比例与双方股本、Tesla 持有的 SpaceX 股份计算。
A59: 2. 行方向看溢价：溢价越高，Tesla 原股东分到的合并后公司比例越高、马斯克经济权益越低；列方向看方法：收入倍数法给出的 Tesla 相对价值最高（Tesla 原股东约 48%），EBITDA 倍数法最低（约 43%）。
A60: 3. 基准情形（20% 溢价 + 市值法）下：换股比例约 2.91 股 SpaceX / 1 股 Tesla，Tesla 原股东约 45.9%，SpaceX 原股东约 54.1%，马斯克约 33.7%。
A61: 4. 敏感性表只改变溢价与定价方法，不改变股本、净债务、关联交易与协同假设；若同时改变这些输入，应回到“换股比例”页调整。
A62: 5. 本表不构成报价或投资建议；实际条款还会受锁定期、监管、税务、评估权与谈判力量影响。

Sheet 检查
A1: 模型检查：加总、勾稽与公式错误
A2: 所有检查应为“OK”；若出现“差异”，回到对应页检查输入或公式。打开文件时已设置为自动重算
A4: 检查项 | B4: 结果 | C4: 公式/说明
A5: SpaceX 分部收入合计 = 合并收入（FY2025） | B5: =IF(ABS('SpaceX数据'!B39-'SpaceX数据'!B5)<0.5,"OK","差异") | C5: Space / Connectivity / SI 收入加总
A6: SpaceX 分部收入合计 = 合并收入（Q3-26） | B6: =IF(ABS('SpaceX数据'!F39-'SpaceX数据'!F5)<0.5,"OK","差异") | C6: Q3 分部收入加总
A7: SpaceX LTM 收入 = 四个季度之和 | B7: =IF(ABS('SpaceX数据'!G5-SUM('SpaceX数据'!C5:F5))<0.5,"OK","差异") | C7: LTM 勾稽
A8: SpaceX 分部经营利润合计 = 合并经营利润（LTM） | B8: =IF(ABS('SpaceX数据'!G47-'SpaceX数据'!G13)<0.5,"OK","差异") | C8: 分部经营利润加总
A9: Tesla 分部收入合计 = 合并收入（FY2025） | B9: =IF(ABS('Tesla数据'!B38-'Tesla数据'!B5)<0.5,"OK","差异") | C9: 汽车 + 能源
A10: Tesla 分部收入合计 = 合并收入（Q3-26） | B10: =IF(ABS('Tesla数据'!F38-'Tesla数据'!F5)<0.5,"OK","差异") | C10: Q3 勾稽
A11: Tesla LTM 收入 = 四个季度之和 | B11: =IF(ABS('Tesla数据'!G5-SUM('Tesla数据'!C5:F5))<0.5,"OK","差异") | C11: LTM 勾稽
A12: Tesla 分部毛利合计 = 合并毛利（FY2025） | B12: =IF(ABS('Tesla数据'!B41-'Tesla数据'!B7)<0.5,"OK","差异") | C12: 汽车 + 能源毛利
A13: 备考收入 = 六条业务线加总（LTM） | B13: =IF(ABS('合并备考'!E18-'合并备考'!B48)<0.5,"OK","差异") | C13: 收入结构勾稽
A14: 备考经营利润 = 业务贡献利润合计（LTM） | B14: =IF(ABS('合并备考'!E25-'合并备考'!B59)<0.5,"OK","差异") | C14: 利润结构勾稽
A15: 备考毛利 = 备考收入 − 备考成本 | B15: =IF(ABS('合并备考'!E20-('合并备考'!E18-'合并备考'!E19))<0.5,"OK","差异") | C15: 利润表勾稽
A16: Tesla 原股东 + SpaceX 原股东 = 100%（基准） | B16: =IF(ABS('换股比例'!K35+'换股比例'!L35-1)<0.0001,"OK","差异") | C16: 持股结构勾稽
A17: 备考净债务 = 有息负债 − 现金及短期投资 | B17: =IF(ABS('合并备考'!E109-('合并备考'!E108-'合并备考'!E107))<0.5,"OK","差异") | C17: 资产负债表勾稽
A18: 备考商誉 = 对价 − 可辨认净资产公允价值 | B18: =IF(ABS('合并备考'!B100-('合并备考'!B8-('Tesla数据'!F29+'合并备考'!B95-'合并备考'!B97)))<0.5,"OK","差异") | C18: 购买会计勾稽
A19: 敏感性表 Tesla 持股均 < 100% | B19: =IF(MAX('敏感性'!B19:F27)<1,"OK","差异") | C19: 上限检查
A20: 关键区域错误值计数 | B20: =SUMPRODUCT(--ISERROR('SpaceX数据'!B5:G55))+SUMPRODUCT(--ISERROR('Tesla数据'!B5:G46))+SUMPRODUCT(--ISERROR('合并备考'!B5:E118))+SUMPRODUCT(--ISERROR('换股比例'!B5:O59)) | C20: 应为 0
A22: 总体状态 | B22: =IF(COUNTIF(B5:B19,"差异")=0,"全部通过","存在差异，请检查") | C22: 若第20项 >0，说明存在 #REF/#VALUE/#DIV0 等错误值
